{
  "type": "Feature",
  "properties": {
    "iso:country":"US",
    "sg:address":"202 Tunnelton St",
    "sg:city":"Kingwood",
    "sg:classifiers":[
        {
            "category":"Professional",
            "subcategory":"Lawyer & Legal Services",
            "type":"Services"
        },
        {
            "category":"Government",
            "subcategory":"Court House",
            "type":"Public Place"
        }
    ],
    "sg:phone":"+1 304 329 1173",
    "sg:postcode":"26537",
    "sg:province":"WV",
    "sg:tags":[
        "attorney"
    ],
    "wof:name":"Williams Law Office",
    "wof:placetype":"venue"
},
  "geometry": {"coordinates":[-79.689899,39.470824],"type":"Point"}
}