{
  "type": "Feature",
  "properties": {
    "addr:full":"325 7th St Parkersburg WV 26101",
    "addr:housenumber":"325",
    "addr:postcode":"26101",
    "addr:street":"7Th St",
    "iso:country":"US",
    "sg:address":"325 7th St",
    "sg:city":"Parkersburg",
    "sg:classifiers":[
        {
            "category":"Professional",
            "subcategory":"Lawyer & Legal Services",
            "type":"Services"
        }
    ],
    "sg:phone":"+1 304 422 3574",
    "sg:postcode":"26101",
    "sg:province":"WV",
    "sg:tags":[
        "attorney"
    ],
    "wof:name":"Richardson Richardson Campbell",
    "wof:placetype":"venue"
},
  "geometry": {"coordinates":[-81.557412,39.266293],"type":"Point"}
}