{
  "type": "Feature",
  "properties": {
    "iso:country":"US",
    "sg:address":"404 Little Sandy Rd",
    "sg:city":"Elkview",
    "sg:classifiers":[
        {
            "category":"Home & Garden",
            "subcategory":"Building Materials",
            "type":"Retail Goods"
        }
    ],
    "sg:phone":"+1 304 965 7084",
    "sg:postcode":"25071",
    "sg:province":"WV",
    "sg:tags":[
        "lumber"
    ],
    "wof:name":"84 Lumber",
    "wof:placetype":"venue"
},
  "geometry": {"coordinates":[-81.498261,38.455948],"type":"Point"}
}