{
  "type": "Feature",
  "properties": {
    "addr:full":"4642 Lynn Creek Rd Lavalette WV 25535",
    "addr:housenumber":"4642",
    "addr:postcode":"25535",
    "addr:street":"Lynn Creek Rd",
    "iso:country":"US",
    "sg:address":"4642 Lynn Creek Rd",
    "sg:city":"Lavalette",
    "sg:classifiers":[
        {
            "category":"Government",
            "subcategory":"Post Office",
            "type":"Public Place"
        }
    ],
    "sg:phone":"+1 304 529 4223",
    "sg:postcode":"25535",
    "sg:province":"WV",
    "wof:name":"US Post Office",
    "wof:placetype":"venue"
},
  "geometry": {"coordinates":[-82.449271,38.322899],"type":"Point"}
}