{
  "type": "Feature",
  "properties": {
    "addr:full":"2628 5th Ave Huntington WV 25702",
    "addr:housenumber":"2628",
    "addr:postcode":"25702",
    "addr:street":"5Th Ave",
    "iso:country":"US",
    "sg:address":"2628 5th Ave",
    "sg:city":"Huntington",
    "sg:classifiers":[
        {
            "category":"Health Services",
            "subcategory":"Doctor",
            "type":"Services"
        }
    ],
    "sg:phone":"+1 304 529 0000",
    "sg:postcode":"25702",
    "sg:province":"WV",
    "sg:tags":[
        "clinic"
    ],
    "wof:name":"Tri-State Medical Ctr",
    "wof:placetype":"venue"
},
  "geometry": {"coordinates":[-82.406336,38.425916],"type":"Point"}
}