{
  "type": "Feature",
  "properties": {
    "iso:country":"US",
    "sg:address":"301 S Wickham Ave",
    "sg:city":"Princeton",
    "sg:classifiers":[
        {
            "category":"Retail",
            "subcategory":"Auto Repair",
            "type":"Services"
        }
    ],
    "sg:phone":"+1 304 425 8830",
    "sg:postcode":"24740",
    "sg:province":"WV",
    "sg:tags":[
        "wrecker"
    ],
    "wof:name":"Glen's Towing",
    "wof:placetype":"venue"
},
  "geometry": {"coordinates":[-81.08226500000001,37.367335],"type":"Point"}
}