{
  "type": "Feature",
  "properties": {
    "addr:full":"5965 US Hwy 60 Barboursville WV 25504",
    "addr:housenumber":"5965",
    "addr:postcode":"25504",
    "addr:street":"Us Hwy 60",
    "iso:country":"US",
    "sg:address":"5965 US Hwy 60",
    "sg:city":"Barboursville",
    "sg:classifiers":[
        {
            "category":"Restaurant",
            "type":"Food & Drink"
        }
    ],
    "sg:phone":"+1 304 736 5819",
    "sg:postcode":"25504",
    "sg:province":"WV",
    "sg:tags":[
        "eating"
    ],
    "wof:name":"Farley's Famous Hot Dog's Inc",
    "wof:placetype":"venue"
},
  "geometry": {"coordinates":[-82.30201599999999,38.414421],"type":"Point"}
}