{
  "type": "Feature",
  "properties": {
    "iso:country":"US",
    "sg:address":"938 Pine Hill Dr",
    "sg:city":"Fairmont",
    "sg:classifiers":[
        {
            "category":"Organizations",
            "subcategory":"Religious Organization",
            "type":"Services"
        }
    ],
    "sg:phone":"+1 304 366 3139",
    "sg:postcode":"26554",
    "sg:province":"WV",
    "sg:tags":[
        "clergy"
    ],
    "wof:name":"David E Jasper",
    "wof:placetype":"venue"
},
  "geometry": {"coordinates":[-80.158509,39.473096],"type":"Point"}
}