{
  "type": "Feature",
  "properties": {
    "iso:country":"US",
    "sg:address":"170 Lakeview Dr",
    "sg:city":"Morgantown",
    "sg:classifiers":[
        {
            "category":"Health Services",
            "subcategory":"Health Practitioner",
            "type":"Services"
        }
    ],
    "sg:phone":"+1 304 594 2500",
    "sg:postcode":"26508",
    "sg:province":"WV",
    "sg:tags":[
        "therapist",
        "physical"
    ],
    "wof:name":"Lakeside Physical Therapy",
    "wof:placetype":"venue"
},
  "geometry": {"coordinates":[-79.908416,39.502689],"type":"Point"}
}