{
  "type": "Feature",
  "properties": {
    "addr:full":"212 100th St Marmet WV 25315",
    "addr:housenumber":"212",
    "addr:postcode":"25315",
    "addr:street":"100Th St",
    "iso:country":"US",
    "sg:address":"212 100th St",
    "sg:city":"Marmet",
    "sg:classifiers":[
        {
            "category":"Freight",
            "type":"Transportation"
        }
    ],
    "sg:phone":"+1 304 949 1631",
    "sg:postcode":"25315",
    "sg:province":"WV",
    "sg:tags":[
        "commercial",
        "storage"
    ],
    "wof:name":"H & J Storage",
    "wof:placetype":"venue"
},
  "geometry": {"coordinates":[-81.56259799999999,38.243832],"type":"Point"}
}