{
  "type": "Feature",
  "properties": {
    "iso:country":"US",
    "sg:address":"100 Fernwood Dr",
    "sg:city":"Wellsburg",
    "sg:classifiers":[
        {
            "category":"Building & Trades",
            "subcategory":"Construction",
            "type":"Services"
        }
    ],
    "sg:phone":"+1 304 737 1889",
    "sg:postcode":"26070",
    "sg:province":"WV",
    "sg:tags":[
        "water",
        "well",
        "drilling"
    ],
    "wof:name":"Hervey Well Drlg & Exavating",
    "wof:placetype":"venue"
},
  "geometry": {"coordinates":[-80.55781899999999,40.275017],"type":"Point"}
}