{
  "type": "Feature",
  "properties": {
    "iso:country":"US",
    "sg:address":"202 Tunnelton St",
    "sg:city":"Kingwood",
    "sg:classifiers":[
        {
            "category":"Health Services",
            "subcategory":"Doctor",
            "type":"Services"
        }
    ],
    "sg:phone":"+1 304 329 1125",
    "sg:postcode":"26537",
    "sg:province":"WV",
    "sg:tags":[
        "clinic",
        "care",
        "medical",
        "primary"
    ],
    "wof:name":"Preston Taylor Cmnty Hlth Ctrs",
    "wof:placetype":"venue"
},
  "geometry": {"coordinates":[-79.689899,39.470824],"type":"Point"}
}