{
  "type": "Feature",
  "properties": {
    "iso:country":"US",
    "sg:address":"1201 Main Ave",
    "sg:city":"Nitro",
    "sg:classifiers":[
        {
            "category":"Wholesale",
            "subcategory":"Construction Materials",
            "type":"Manufacturing & Wholesale Goods"
        }
    ],
    "sg:phone":"+1 304 722 4601",
    "sg:postcode":"25143",
    "sg:province":"WV",
    "sg:tags":[
        "brick",
        "common",
        "face"
    ],
    "sg:website":"www.kanawhabrick.com",
    "wof:name":"Kanawha Brick & Block Co",
    "wof:placetype":"venue"
},
  "geometry": {"coordinates":[-81.836905,38.398241],"type":"Point"}
}