{
  "type": "Feature",
  "properties": {
    "iso:country":"US",
    "sg:address":"1756 Mileground Rd",
    "sg:city":"Morgantown",
    "sg:classifiers":[
        {
            "category":"Personal",
            "subcategory":"Beauty Salon",
            "type":"Services"
        }
    ],
    "sg:phone":"+1 304 296 5356",
    "sg:postcode":"26505",
    "sg:province":"WV",
    "wof:name":"Mackadoo's Beauty Salon",
    "wof:placetype":"venue"
},
  "geometry": {"coordinates":[-79.928012,39.644194],"type":"Point"}
}