{
  "type": "Feature",
  "properties": {
    "addr:full":"6090 Sissonville Dr Charleston WV 25312",
    "addr:housenumber":"6090",
    "addr:postcode":"25312",
    "addr:street":"Sissonville Dr",
    "iso:country":"US",
    "sg:address":"6090 Sissonville Dr",
    "sg:city":"Charleston",
    "sg:classifiers":[
        {
            "category":"Restaurant",
            "type":"Food & Drink"
        }
    ],
    "sg:phone":"+1 304 984 9519",
    "sg:postcode":"25312",
    "sg:province":"WV",
    "sg:tags":[
        "eating"
    ],
    "wof:name":"Subway",
    "wof:placetype":"venue"
},
  "geometry": {"coordinates":[-81.669358,38.467589],"type":"Point"}
}