{
  "type": "Feature",
  "properties": {
    "iso:country":"US",
    "sg:address":"111 Pike St",
    "sg:city":"Shinnston",
    "sg:classifiers":[
        {
            "category":"Restaurant",
            "type":"Food & Drink"
        }
    ],
    "sg:phone":"+1 304 592 3994",
    "sg:postcode":"26431",
    "sg:province":"WV",
    "sg:tags":[
        "eating"
    ],
    "wof:name":"A's Pizza & Restaurant",
    "wof:placetype":"venue"
},
  "geometry": {"coordinates":[-80.30224200000001,39.394835],"type":"Point"}
}