{
  "type": "Feature",
  "properties": {
    "iso:country":"US",
    "sg:address":"66 Westwood Ave",
    "sg:city":"Jane Lew",
    "sg:classifiers":[
        {
            "category":"Building & Trades",
            "subcategory":"Construction",
            "type":"Services"
        }
    ],
    "sg:phone":"+1 304 884 7197",
    "sg:postcode":"26330",
    "sg:province":"WV",
    "sg:tags":[
        "excavation",
        "contractor"
    ],
    "wof:name":"Hoover M R Construction Co LLC",
    "wof:placetype":"venue"
},
  "geometry": {"coordinates":[-80.270826,39.301119],"type":"Point"}
}