{
  "type": "Feature",
  "properties": {
    "iso:country":"US",
    "sg:address":"510 Logan St",
    "sg:city":"Williamson",
    "sg:classifiers":[
        {
            "category":"Professional",
            "subcategory":"Accounting & Tax Preparation",
            "type":"Services"
        }
    ],
    "sg:phone":"+1 304 235 3384",
    "sg:postcode":"25661",
    "sg:province":"WV",
    "sg:tags":[
        "accountant"
    ],
    "wof:name":"Paul W Lawson CPA",
    "wof:placetype":"venue"
},
  "geometry": {"coordinates":[-82.275233,37.673835],"type":"Point"}
}