{
  "type": "Feature",
  "properties": {
    "iso:country":"US",
    "sg:address":"600 Slack St",
    "sg:city":"Charleston",
    "sg:classifiers":[
        {
            "category":"Wholesale",
            "subcategory":"Scrap",
            "type":"Manufacturing & Wholesale Goods"
        }
    ],
    "sg:phone":"+1 304 342 4477",
    "sg:postcode":"25301",
    "sg:province":"WV",
    "sg:tags":[
        "recycling",
        "center"
    ],
    "wof:name":"Kanawha County Solid Waste",
    "wof:placetype":"venue"
},
  "geometry": {"coordinates":[-81.624092,38.357941],"type":"Point"}
}