{
  "type": "Feature",
  "properties": {
    "iso:country":"US",
    "sg:address":"1538 Kanawha Blvd E",
    "sg:city":"Charleston",
    "sg:classifiers":[
        {
            "category":"Banks & Credit Unions",
            "subcategory":"Bank",
            "type":"Services"
        }
    ],
    "sg:phone":"+1 304 346 2246",
    "sg:postcode":"25311",
    "sg:province":"WV",
    "sg:tags":[
        "broker",
        "mortgage"
    ],
    "wof:name":"West Virginia 5 Star Mtg Corp",
    "wof:placetype":"venue"
},
  "geometry": {"coordinates":[-81.62480600000001,38.339905],"type":"Point"}
}