{
  "type": "Feature",
  "properties": {
    "iso:country":"US",
    "sg:address":"608 Harrison St",
    "sg:city":"Princeton",
    "sg:classifiers":[
        {
            "category":"Retail",
            "subcategory":"Repair Shop",
            "type":"Services"
        }
    ],
    "sg:phone":"+1 304 425 2200",
    "sg:postcode":"24740",
    "sg:province":"WV",
    "sg:tags":[
        "television",
        "radio"
    ],
    "wof:name":"Topps Electronic Svc",
    "wof:placetype":"venue"
},
  "geometry": {"coordinates":[-81.091223,37.369119],"type":"Point"}
}