{
  "type": "Feature",
  "properties": {
    "iso:country":"US",
    "sg:address":"1200 Quarrier St",
    "sg:city":"Charleston",
    "sg:classifiers":[
        {
            "category":"Health Services",
            "subcategory":"Doctor",
            "type":"Services"
        }
    ],
    "sg:phone":"+1 304 343 9855",
    "sg:postcode":"25301",
    "sg:province":"WV",
    "sg:tags":[
        "dentist"
    ],
    "wof:name":"Alex W Skaff Dental Assoc Inc",
    "wof:placetype":"venue"
},
  "geometry": {"coordinates":[-81.629576,38.34571],"type":"Point"}
}