{
  "type": "Feature",
  "properties": {
    "iso:country":"US",
    "sg:address":"6313 Maccorkle Ave SE",
    "sg:city":"Charleston",
    "sg:classifiers":[
        {
            "category":"Autos & Motor Vehicles",
            "subcategory":"Fuel & Gas Station",
            "type":"Retail Goods"
        }
    ],
    "sg:phone":"+1 304 926 0078",
    "sg:postcode":"25304",
    "sg:province":"WV",
    "sg:tags":[
        "oil"
    ],
    "wof:name":"Clark's Pump & Shop Bp",
    "wof:placetype":"venue"
},
  "geometry": {"coordinates":[-81.56342100000001,38.307828],"type":"Point"}
}