{
  "type": "Feature",
  "properties": {
    "iso:country":"US",
    "sg:address":"2197 National Rd",
    "sg:city":"Wheeling",
    "sg:classifiers":[
        {
            "category":"Home & Garden",
            "subcategory":"Carpets & Floor Coverings",
            "type":"Retail Goods"
        }
    ],
    "sg:phone":"+1 304 242 8750",
    "sg:postcode":"26003",
    "sg:province":"WV",
    "wof:name":"P & W Flooring Inc",
    "wof:placetype":"venue"
},
  "geometry": {"coordinates":[-80.660633,40.045834],"type":"Point"}
}