{
  "type": "Feature",
  "properties": {
    "iso:country":"US",
    "sg:address":"143 Spur Rd",
    "sg:city":"Martinsburg",
    "sg:classifiers":[
        {
            "category":"Real Estate",
            "subcategory":"Real Estate Operator",
            "type":"Services"
        }
    ],
    "sg:phone":"+1 304 263 6440",
    "sg:postcode":"25404",
    "sg:province":"WV",
    "sg:tags":[
        "mobile",
        "home",
        "site"
    ],
    "wof:name":"Margarets Way Mobile Estates",
    "wof:placetype":"venue"
},
  "geometry": {"coordinates":[-77.92121299999999,39.50163],"type":"Point"}
}