{
  "type": "Feature",
  "properties": {
    "iso:country":"US",
    "sg:address":"489 Clear Fork Rd",
    "sg:city":"Beckley",
    "sg:classifiers":[
        {
            "category":"Mining & Drilling",
            "type":"Manufacturing & Wholesale Goods"
        }
    ],
    "sg:phone":"+1 304 877 3393",
    "sg:postcode":"25801",
    "sg:province":"WV",
    "sg:tags":[
        "construction"
    ],
    "wof:name":"Jerry Bowyer",
    "wof:placetype":"venue"
},
  "geometry": {"coordinates":[-81.279062,37.873681],"type":"Point"}
}