{
  "type": "Feature",
  "properties": {
    "addr:full":"121 Virginia St E Charleston WV 25301",
    "addr:housenumber":"121",
    "addr:postcode":"25301",
    "addr:street":"Virginia St E",
    "iso:country":"US",
    "sg:address":"121 Virginia St E",
    "sg:city":"Charleston",
    "sg:classifiers":[
        {
            "category":"Restaurant",
            "type":"Food & Drink"
        }
    ],
    "sg:menulink":"http://www.allmenus.com/wv/belle/195878-wendys/menu/",
    "sg:phone":"+1 304 342 0662",
    "sg:postcode":"25301",
    "sg:province":"WV",
    "sg:tags":[
        "burger",
        "american",
        "soup"
    ],
    "wof:name":"Wendy's",
    "wof:placetype":"venue"
},
  "geometry": {"coordinates":[-81.64208000000001,38.354287],"type":"Point"}
}