{
  "type": "Feature",
  "properties": {
    "iso:country":"US",
    "sg:address":"47 Honeysuckle",
    "sg:city":"Bluefield",
    "sg:classifiers":[
        {
            "category":"Home & Garden",
            "subcategory":"Hardware",
            "type":"Retail Goods"
        }
    ],
    "sg:phone":"+1 304 327 7738",
    "sg:postcode":"24701",
    "sg:province":"WV",
    "wof:name":"Christian Brokerage & Supply",
    "wof:placetype":"venue"
},
  "geometry": {"coordinates":[-81.17856,37.270138],"type":"Point"}
}