{
  "type": "Feature",
  "properties": {
    "iso:country":"US",
    "sg:address":"3600 Wetzel St",
    "sg:city":"Wheeling",
    "sg:classifiers":[
        {
            "category":"Manufacturing",
            "subcategory":"Paper Products",
            "type":"Manufacturing & Wholesale Goods"
        }
    ],
    "sg:phone":"+1 304 232 3470",
    "sg:postcode":"26003",
    "sg:province":"WV",
    "sg:tags":[
        "bag",
        "coated",
        "plastic"
    ],
    "wof:name":"Proven Papers Inc",
    "wof:placetype":"venue"
},
  "geometry": {"coordinates":[-80.72211299999999,40.04495],"type":"Point"}
}