{
  "type": "Feature",
  "properties": {
    "iso:country":"US",
    "sg:address":"6150 Rosalind Ct",
    "sg:city":"Huntington",
    "sg:classifiers":[
        {
            "category":"Health Services",
            "subcategory":"Medical Lab",
            "type":"Services"
        }
    ],
    "sg:phone":"+1 304 736 7097",
    "sg:postcode":"25705",
    "sg:province":"WV",
    "sg:tags":[
        "laboratory",
        "dental"
    ],
    "wof:name":"Ceramic Arts Dental Lab",
    "wof:placetype":"venue"
},
  "geometry": {"coordinates":[-82.309911,38.42322],"type":"Point"}
}