{
  "type": "Feature",
  "properties": {
    "iso:country":"US",
    "sg:address":"6961 Emerson Ave",
    "sg:city":"Parkersburg",
    "sg:classifiers":[
        {
            "category":"Building & Trades",
            "subcategory":"Construction",
            "type":"Services"
        }
    ],
    "sg:phone":"+1 304 464 4500",
    "sg:postcode":"26104",
    "sg:province":"WV",
    "sg:tags":[
        "downspouts",
        "gutter"
    ],
    "wof:name":"Leaf Guard Of West Virginia",
    "wof:placetype":"venue"
},
  "geometry": {"coordinates":[-81.464567,39.315591],"type":"Point"}
}