{
  "type": "Feature",
  "properties": {
    "addr:full":"319 Kingwood St Morgantown WV 26501",
    "addr:housenumber":"319",
    "addr:postcode":"26501",
    "addr:street":"Kingwood St",
    "iso:country":"US",
    "sg:address":"319 Kingwood St",
    "sg:city":"Morgantown",
    "sg:classifiers":[
        {
            "category":"Professional",
            "subcategory":"Employment Agencies",
            "type":"Services"
        }
    ],
    "sg:phone":"+1 304 296 4925",
    "sg:postcode":"26501",
    "sg:province":"WV",
    "sg:tags":[
        "help",
        "supply"
    ],
    "wof:name":"Mountain State Balloon Co LLC",
    "wof:placetype":"venue"
},
  "geometry": {"coordinates":[-79.95178900000001,39.624623],"type":"Point"}
}