{
  "type": "Feature",
  "properties": {
    "addr:full":"1515 Blizzard Dr Parkersburg WV 26101",
    "addr:housenumber":"1515",
    "addr:postcode":"26101",
    "addr:street":"Blizzard Dr",
    "iso:country":"US",
    "sg:address":"1515 Blizzard Dr",
    "sg:city":"Parkersburg",
    "sg:classifiers":[
        {
            "category":"Education",
            "subcategory":"School",
            "type":"Public Place"
        }
    ],
    "sg:phone":"+1 304 420 9501",
    "sg:postcode":"26101",
    "sg:province":"WV",
    "wof:name":"Wood County Technical Ctr",
    "wof:placetype":"venue"
},
  "geometry": {"coordinates":[-81.548697,39.241832],"type":"Point"}
}