{
  "type": "Feature",
  "properties": {
    "iso:country":"US",
    "sg:address":"1204 Norfolk Ave",
    "sg:city":"Wayne",
    "sg:classifiers":[
        {
            "category":"Home & Garden",
            "subcategory":"Furniture",
            "type":"Retail Goods"
        }
    ],
    "sg:phone":"+1 304 272 6140",
    "sg:postcode":"25570",
    "sg:province":"WV",
    "wof:name":"Town & Country Furniture Appl",
    "wof:placetype":"venue"
},
  "geometry": {"coordinates":[-82.439215,38.221074],"type":"Point"}
}