{
  "type": "Feature",
  "properties": {
    "iso:country":"US",
    "sg:address":"18 W Main St",
    "sg:city":"White Slphr Spgs",
    "sg:classifiers":[
        {
            "category":"Real Estate",
            "subcategory":"Real Estate Agent",
            "type":"Services"
        },
        {
            "category":"Professional",
            "subcategory":"Accounting & Tax Preparation",
            "type":"Services"
        }
    ],
    "sg:phone":"+1 304 536 3474",
    "sg:postcode":"24986",
    "sg:province":"WV",
    "sg:tags":[
        "return"
    ],
    "wof:name":"Checkerboard Realty Inc",
    "wof:placetype":"venue"
},
  "geometry": {"coordinates":[-80.30116599999999,37.793623],"type":"Point"}
}