{
  "type": "Feature",
  "properties": {
    "addr:full":"112 Lafayette Ave Moundsville WV 26041",
    "addr:housenumber":"112",
    "addr:postcode":"26041",
    "addr:street":"Lafayette Ave",
    "iso:country":"US",
    "sg:address":"112 Lafayette Ave",
    "sg:city":"Moundsville",
    "sg:classifiers":[
        {
            "category":"Travel",
            "subcategory":"Hotels & Motels",
            "type":"Entertainment"
        }
    ],
    "sg:phone":"+1 304 455 5309",
    "sg:postcode":"26041",
    "sg:province":"WV",
    "sg:tags":[
        "operation"
    ],
    "wof:name":"K Mistri",
    "wof:placetype":"venue"
},
  "geometry": {"coordinates":[-80.752028,39.931656],"type":"Point"}
}