{
  "type": "Feature",
  "properties": {
    "iso:country":"US",
    "sg:address":"2020 Wiltshire Blvd",
    "sg:city":"Huntington",
    "sg:classifiers":[
        {
            "category":"Insurance",
            "subcategory":"Insurance Agent",
            "type":"Services"
        }
    ],
    "sg:phone":"+1 304 529 7047",
    "sg:postcode":"25701",
    "sg:province":"WV",
    "wof:name":"Benefits & Insurance Advisors",
    "wof:placetype":"venue"
},
  "geometry": {"coordinates":[-82.41604599999999,38.404703],"type":"Point"}
}