{
  "type": "Feature",
  "properties": {
    "addr:full":"2302 Ritz Ave Wheeling WV 26003",
    "addr:housenumber":"2302",
    "addr:postcode":"26003",
    "addr:street":"Ritz Ave",
    "iso:country":"US",
    "sg:address":"2302 Ritz Ave",
    "sg:city":"Wheeling",
    "sg:classifiers":[
        {
            "category":"Health Services",
            "subcategory":"Nursing And Care Facility",
            "type":"Services"
        }
    ],
    "sg:phone":"+1 304 234 3561",
    "sg:postcode":"26003",
    "sg:province":"WV",
    "wof:name":"Ritz Avenue Group Home",
    "wof:placetype":"venue"
},
  "geometry": {"coordinates":[-80.702859,40.125578],"type":"Point"}
}