{
  "type": "Feature",
  "properties": {
    "iso:country":"US",
    "sg:address":"609 49th St SE",
    "sg:city":"Charleston",
    "sg:classifiers":[
        {
            "category":"Retail",
            "subcategory":"Auto Repair",
            "type":"Services"
        }
    ],
    "sg:phone":"+1 304 720 2276",
    "sg:postcode":"25304",
    "sg:province":"WV",
    "sg:tags":[
        "truck"
    ],
    "wof:name":"T J's Truck & Trailer Repair",
    "wof:placetype":"venue"
},
  "geometry": {"coordinates":[-81.58083999999999,38.31826],"type":"Point"}
}