{
  "type": "Feature",
  "properties": {
    "iso:country":"US",
    "sg:address":"2 Saylor Rd",
    "sg:city":"Morgantown",
    "sg:classifiers":[
        {
            "category":"Building & Trades",
            "subcategory":"Construction",
            "type":"Services"
        }
    ],
    "sg:phone":"+1 304 296 6990",
    "sg:postcode":"26501",
    "sg:province":"WV",
    "sg:tags":[
        "house"
    ],
    "wof:name":"Burch Roofing & Construction",
    "wof:placetype":"venue"
},
  "geometry": {"coordinates":[-80.00266499999999,39.609304],"type":"Point"}
}