{
  "type": "Feature",
  "properties": {
    "iso:country":"US",
    "sg:address":"3300 McColloch St",
    "sg:city":"Wheeling",
    "sg:classifiers":[
        {
            "category":"Home & Garden",
            "subcategory":"Hardware",
            "type":"Retail Goods"
        }
    ],
    "sg:phone":"+1 304 233 3600",
    "sg:postcode":"26003",
    "sg:province":"WV",
    "wof:name":"Kennedy Hardware Co",
    "wof:placetype":"venue"
},
  "geometry": {"coordinates":[-80.721898,40.048779],"type":"Point"}
}