{
  "type": "Feature",
  "properties": {
    "iso:country":"US",
    "sg:address":"122 Harris Dr",
    "sg:city":"Poca",
    "sg:classifiers":[
        {
            "category":"Professional",
            "subcategory":"Engineering",
            "type":"Services"
        }
    ],
    "sg:phone":"+1 304 755 4374",
    "sg:postcode":"25159",
    "sg:province":"WV",
    "sg:tags":[
        "engineer"
    ],
    "sg:website":"www.preparationcontrol.com",
    "wof:name":"Preparation Control Inc",
    "wof:placetype":"venue"
},
  "geometry": {"coordinates":[-81.82039399999999,38.449633],"type":"Point"}
}