{
  "type": "Feature",
  "properties": {
    "iso:country":"US",
    "sg:address":"207 Short St",
    "sg:city":"Huntington",
    "sg:classifiers":[
        {
            "category":"Retail",
            "subcategory":"Auto Repair",
            "type":"Services"
        }
    ],
    "sg:phone":"+1 304 529 2404",
    "sg:postcode":"25702",
    "sg:province":"WV",
    "sg:tags":[
        "transmission"
    ],
    "wof:name":"Laneys Transmission",
    "wof:placetype":"venue"
},
  "geometry": {"coordinates":[-82.38464,38.428878],"type":"Point"}
}