{
  "type": "Feature",
  "properties": {
    "iso:country":"US",
    "sg:address":"3304 Pennsylvania Ave",
    "sg:city":"Weirton",
    "sg:classifiers":[
        {
            "category":"Government",
            "subcategory":"Police Station",
            "type":"Public Place"
        }
    ],
    "sg:phone":"+1 304 723 0360",
    "sg:postcode":"26062",
    "sg:province":"WV",
    "sg:tags":[
        "department"
    ],
    "wof:name":"Weirton Police Drug Task Force",
    "wof:placetype":"venue"
},
  "geometry": {"coordinates":[-80.53820899999999,40.408539],"type":"Point"}
}