{
  "type": "Feature",
  "properties": {
    "iso:country":"US",
    "sg:address":"5 Blackberry Orchard",
    "sg:city":"Danville",
    "sg:classifiers":[
        {
            "category":"Retail",
            "subcategory":"Auto Repair",
            "type":"Services"
        }
    ],
    "sg:phone":"+1 304 369 5725",
    "sg:postcode":"25053",
    "sg:province":"WV",
    "sg:tags":[
        "glass",
        "replacement"
    ],
    "wof:name":"Buster Glass Ltd",
    "wof:placetype":"venue"
},
  "geometry": {"coordinates":[-81.845201,38.061893],"type":"Point"}
}