{
  "type": "Feature",
  "properties": {
    "iso:country":"US",
    "sg:address":"1806 N 23rd St",
    "sg:city":"Clarksburg",
    "sg:classifiers":[
        {
            "category":"Professional",
            "subcategory":"Secretarial Services",
            "type":"Services"
        }
    ],
    "sg:phone":"+1 304 622 3794",
    "sg:postcode":"26301",
    "sg:province":"WV",
    "sg:tags":[
        "reporting"
    ],
    "wof:name":"Frances A Camigliano",
    "wof:placetype":"venue"
},
  "geometry": {"coordinates":[-80.35115999999999,39.301252],"type":"Point"}
}