{
  "type": "Feature",
  "properties": {
    "addr:full":"207 Chestnut St Henderson WV 25106",
    "addr:housenumber":"207",
    "addr:postcode":"25106",
    "addr:street":"Chestnut St",
    "iso:country":"US",
    "sg:address":"207 Chestnut St",
    "sg:city":"Henderson",
    "sg:classifiers":[
        {
            "category":"Autos & Motor Vehicles",
            "subcategory":"Motorcycle Sales",
            "type":"Retail Goods"
        }
    ],
    "sg:phone":"+1 304 675 3027",
    "sg:postcode":"25106",
    "sg:province":"WV",
    "sg:tags":[
        "scooter"
    ],
    "wof:name":"Heydoug Cycles LLC",
    "wof:placetype":"venue"
},
  "geometry": {"coordinates":[-82.139375,38.834206],"type":"Point"}
}