{
  "type": "Feature",
  "properties": {
    "addr:full":"366 Norway Ave Huntington WV 25705",
    "addr:housenumber":"366",
    "addr:postcode":"25705",
    "addr:street":"Norway Ave",
    "iso:country":"US",
    "sg:address":"366 Norway Ave",
    "sg:city":"Huntington",
    "sg:classifiers":[
        {
            "category":"Health Services",
            "subcategory":"Doctor",
            "type":"Services"
        }
    ],
    "sg:phone":"+1 304 697 2500",
    "sg:postcode":"25705",
    "sg:province":"WV",
    "sg:tags":[
        "dentist"
    ],
    "wof:name":"George D Beldon DDS Inc",
    "wof:placetype":"venue"
},
  "geometry": {"coordinates":[-82.40599,38.406823],"type":"Point"}
}