{
  "type": "Feature",
  "properties": {
    "addr:full":"1033 Main St Milton WV 25541",
    "addr:housenumber":"1033",
    "addr:postcode":"25541",
    "addr:street":"Main St",
    "iso:country":"US",
    "sg:address":"1033 Main St",
    "sg:city":"Milton",
    "sg:classifiers":[
        {
            "category":"Recreation",
            "type":"Entertainment"
        }
    ],
    "sg:phone":"+1 304 743 1543",
    "sg:postcode":"25541",
    "sg:province":"WV",
    "sg:tags":[
        "club",
        "membership"
    ],
    "wof:name":"Milton Moose Lodge",
    "wof:placetype":"venue"
},
  "geometry": {"coordinates":[-82.14619999999999,38.434311],"type":"Point"}
}