{
  "type": "Feature",
  "properties": {
    "addr:full":"301 39th St Huntington WV 25702",
    "addr:housenumber":"301",
    "addr:postcode":"25702",
    "addr:street":"39Th St",
    "iso:country":"US",
    "sg:address":"301 39th St",
    "sg:city":"Huntington",
    "sg:classifiers":[
        {
            "category":"Health Services",
            "subcategory":"Clinic",
            "type":"Services"
        }
    ],
    "sg:phone":"+1 304 522 8846",
    "sg:postcode":"25702",
    "sg:province":"WV",
    "sg:tags":[
        "home",
        "care"
    ],
    "wof:name":"Peggy Cazad",
    "wof:placetype":"venue"
},
  "geometry": {"coordinates":[-82.37461399999999,38.430109],"type":"Point"}
}