{
  "type": "Feature",
  "properties": {
    "addr:full":"246 Kruger St Wheeling WV 26003",
    "addr:housenumber":"246",
    "addr:postcode":"26003",
    "addr:street":"Kruger St",
    "iso:country":"US",
    "sg:address":"246 Kruger St",
    "sg:city":"Wheeling",
    "sg:classifiers":[
        {
            "category":"Professional",
            "subcategory":"Advertising",
            "type":"Services"
        }
    ],
    "sg:phone":"+1 304 242 6160",
    "sg:postcode":"26003",
    "sg:province":"WV",
    "sg:tags":[
        "agency"
    ],
    "wof:name":"River City Advertising",
    "wof:placetype":"venue"
},
  "geometry": {"coordinates":[-80.658119,40.037101],"type":"Point"}
}