{
  "type": "Feature",
  "properties": {
    "iso:country":"US",
    "sg:address":"1933 7th St",
    "sg:city":"Parkersburg",
    "sg:classifiers":[
        {
            "category":"Retail",
            "subcategory":"Laundry & Dry Cleaning",
            "type":"Services"
        }
    ],
    "sg:phone":"+1 304 428 9470",
    "sg:postcode":"26101",
    "sg:province":"WV",
    "sg:tags":[
        "cleaners"
    ],
    "wof:name":"Vogue Swift Cleaners",
    "wof:placetype":"venue"
},
  "geometry": {"coordinates":[-81.525081,39.267754],"type":"Point"}
}