{
  "type": "Feature",
  "properties": {
    "addr:full":"1 Kennedy Dr Elkins WV 26241",
    "addr:housenumber":"1",
    "addr:postcode":"26241",
    "addr:street":"Kennedy Dr",
    "iso:country":"US",
    "sg:address":"1 Kennedy Dr",
    "sg:city":"Elkins",
    "sg:classifiers":[
        {
            "category":"Autos & Motor Vehicles",
            "subcategory":"Automobile Sales",
            "type":"Retail Goods"
        }
    ],
    "sg:phone":"+1 304 636 9461",
    "sg:postcode":"26241",
    "sg:province":"WV",
    "sg:tags":[
        "car",
        "dealer"
    ],
    "wof:name":"Team One Auto Mall",
    "wof:placetype":"venue"
},
  "geometry": {"coordinates":[-79.84899299999999,38.892057],"type":"Point"}
}