{
  "type": "Feature",
  "properties": {
    "iso:country":"US",
    "sg:address":"3100 Maccorkle Ave SW",
    "sg:city":"Charleston",
    "sg:classifiers":[
        {
            "category":"Autos & Motor Vehicles",
            "subcategory":"Automobile Sales",
            "type":"Retail Goods"
        }
    ],
    "sg:phone":"+1 304 744 1321",
    "sg:postcode":"25303",
    "sg:province":"WV",
    "sg:tags":[
        "truck"
    ],
    "sg:website":"www.gtswv.com",
    "wof:name":"General Truck Sales Corp",
    "wof:placetype":"venue"
},
  "geometry": {"coordinates":[-81.706092,38.365185],"type":"Point"}
}