{
  "type": "Feature",
  "properties": {
    "addr:full":"249 Jefferson Ave Moundsville WV 26041",
    "addr:housenumber":"249",
    "addr:postcode":"26041",
    "addr:street":"Jefferson Ave",
    "iso:country":"US",
    "sg:address":"249 Jefferson Ave",
    "sg:city":"Moundsville",
    "sg:classifiers":[
        {
            "category":"Retail",
            "subcategory":"Portrait Studio",
            "type":"Services"
        }
    ],
    "sg:phone":"+1 304 845 8970",
    "sg:postcode":"26041",
    "sg:province":"WV",
    "sg:tags":[
        "photo"
    ],
    "wof:name":"Ken Blake Photography",
    "wof:placetype":"venue"
},
  "geometry": {"coordinates":[-80.742977,39.922268],"type":"Point"}
}