{
  "type": "Feature",
  "properties": {
    "iso:country":"US",
    "sg:address":"607 Monticello Ave",
    "sg:city":"Clarksburg",
    "sg:classifiers":[
        {
            "category":"Food & Beverages",
            "subcategory":"Groceries & Convenience Stores",
            "type":"Retail Goods"
        }
    ],
    "sg:phone":"+1 304 622 8311",
    "sg:postcode":"26301",
    "sg:province":"WV",
    "sg:tags":[
        "ice",
        "mfg"
    ],
    "wof:name":"North Pole Ice Co",
    "wof:placetype":"venue"
},
  "geometry": {"coordinates":[-80.336095,39.27269],"type":"Point"}
}