{
  "type": "Feature",
  "properties": {
    "iso:country":"US",
    "sg:address":"925 Lexington Dr",
    "sg:city":"St Albans",
    "sg:classifiers":[
        {
            "category":"Banks & Credit Unions",
            "subcategory":"Bank",
            "type":"Services"
        }
    ],
    "sg:phone":"+1 304 727 4802",
    "sg:postcode":"25177",
    "sg:province":"WV",
    "sg:tags":[
        "loan"
    ],
    "wof:name":"Alternative Lending Mortgage",
    "wof:placetype":"venue"
},
  "geometry": {"coordinates":[-81.806033,38.370757],"type":"Point"}
}