{
  "type": "Feature",
  "properties": {
    "iso:country":"US",
    "sg:address":"3318 Emerson Ave",
    "sg:city":"Parkersburg",
    "sg:classifiers":[
        {
            "category":"Food & Beverages",
            "subcategory":"Bakery",
            "type":"Retail Goods"
        }
    ],
    "sg:phone":"+1 304 428 9097",
    "sg:postcode":"26104",
    "sg:province":"WV",
    "sg:tags":[
        "baker"
    ],
    "wof:name":"J R's Bakery Products",
    "wof:placetype":"venue"
},
  "geometry": {"coordinates":[-81.536269,39.286614],"type":"Point"}
}