{
  "type": "Feature",
  "properties": {
    "iso:country":"US",
    "sg:address":"222 E Main St",
    "sg:city":"Bridgeport",
    "sg:classifiers":[
        {
            "category":"Real Estate",
            "subcategory":"Real Estate Agent",
            "type":"Services"
        }
    ],
    "sg:phone":"+1 304 842 2468",
    "sg:postcode":"26330",
    "sg:province":"WV",
    "wof:name":"Kaufman Real Estate Inc",
    "wof:placetype":"venue"
},
  "geometry": {"coordinates":[-80.248423,39.286167],"type":"Point"}
}