{
  "type": "Feature",
  "properties": {
    "addr:full":"2209 Camden Ave Parkersburg WV 26101",
    "addr:housenumber":"2209",
    "addr:postcode":"26101",
    "addr:street":"Camden Ave",
    "iso:country":"US",
    "sg:address":"2209 Camden Ave",
    "sg:city":"Parkersburg",
    "sg:classifiers":[
        {
            "category":"Social Services",
            "subcategory":"Child Care",
            "type":"Services"
        }
    ],
    "sg:phone":"+1 304 422 2600",
    "sg:postcode":"26101",
    "sg:province":"WV",
    "wof:name":"Mary Anns Learning Ctr",
    "wof:placetype":"venue"
},
  "geometry": {"coordinates":[-81.550211,39.254964],"type":"Point"}
}