{
  "type": "Feature",
  "properties": {
    "addr:full":"216 Court St Clarksburg WV 26301",
    "addr:housenumber":"216",
    "addr:postcode":"26301",
    "addr:street":"Court St",
    "iso:country":"US",
    "sg:address":"216 Court St",
    "sg:city":"Clarksburg",
    "sg:classifiers":[
        {
            "category":"Professional",
            "subcategory":"Lawyer & Legal Services",
            "type":"Services"
        }
    ],
    "sg:phone":"+1 304 622 8402",
    "sg:postcode":"26301",
    "sg:province":"WV",
    "sg:tags":[
        "attorney"
    ],
    "wof:name":"Gale E Carroll",
    "wof:placetype":"venue"
},
  "geometry": {"coordinates":[-80.33965600000001,39.279146],"type":"Point"}
}