{
  "type": "Feature",
  "properties": {
    "addr:full":"257 Virgina Ave Welch WV 24801",
    "addr:housenumber":"257",
    "addr:postcode":"24801",
    "addr:street":"Virgina Ave",
    "iso:country":"US",
    "sg:address":"257 Virgina Ave",
    "sg:city":"Welch",
    "sg:classifiers":[
        {
            "category":"Local Transit",
            "type":"Transportation"
        }
    ],
    "sg:phone":"+1 304 436 4106",
    "sg:postcode":"24801",
    "sg:province":"WV",
    "sg:tags":[
        "passenger",
        "ambulance"
    ],
    "wof:name":"McDowell County Emergency 911",
    "wof:placetype":"venue"
},
  "geometry": {"coordinates":[-81.58181,37.433077],"type":"Point"}
}