{
  "type": "Feature",
  "properties": {
    "iso:country":"US",
    "sg:address":"845 4th Ave",
    "sg:city":"Huntington",
    "sg:classifiers":[
        {
            "category":"Banks & Credit Unions",
            "subcategory":"Investment Brokerage",
            "type":"Services"
        }
    ],
    "sg:phone":"+1 304 529 2474",
    "sg:postcode":"25701",
    "sg:province":"WV",
    "sg:tags":[
        "advisory",
        "financial"
    ],
    "wof:name":"Money Financial Svc",
    "wof:placetype":"venue"
},
  "geometry": {"coordinates":[-82.444472,38.420568],"type":"Point"}
}