{
  "type": "Feature",
  "properties": {
    "iso:country":"US",
    "sg:address":"2600 Pennsylvania Ave",
    "sg:city":"Weirton",
    "sg:classifiers":[
        {
            "category":"Restaurant",
            "type":"Food & Drink"
        }
    ],
    "sg:phone":"+1 304 723 4208",
    "sg:postcode":"26062",
    "sg:province":"WV",
    "wof:name":"Very Important Palats",
    "wof:placetype":"venue"
},
  "geometry": {"coordinates":[-80.556023,40.417597],"type":"Point"}
}