{
  "type": "Feature",
  "properties": {
    "iso:country":"US",
    "sg:address":"147 Ruthlawn Dr",
    "sg:city":"Charleston",
    "sg:classifiers":[
        {
            "category":"Real Estate",
            "subcategory":"Real Estate Agent",
            "type":"Services"
        }
    ],
    "sg:phone":"+1 304 744 9832",
    "sg:postcode":"25309",
    "sg:province":"WV",
    "wof:name":"Donna Grass Realtors",
    "wof:placetype":"venue"
},
  "geometry": {"coordinates":[-81.727148,38.322632],"type":"Point"}
}