{
  "type": "Feature",
  "properties": {
    "iso:country":"US",
    "sg:address":"1343 Wilkie Dr",
    "sg:city":"Charleston",
    "sg:classifiers":[
        {
            "category":"Professional",
            "subcategory":"Lawyer & Legal Services",
            "type":"Services"
        }
    ],
    "sg:phone":"+1 304 342 2469",
    "sg:postcode":"25314",
    "sg:province":"WV",
    "wof:name":"Anthony G Halkias Esq",
    "wof:placetype":"venue"
},
  "geometry": {"coordinates":[-81.665177,38.347425],"type":"Point"}
}