{
  "type": "Feature",
  "properties": {
    "iso:country":"US",
    "sg:address":"841 Jackson Ave",
    "sg:city":"Huntington",
    "sg:classifiers":[
        {
            "category":"Government",
            "subcategory":"Office",
            "type":"Public Place"
        }
    ],
    "sg:phone":"+1 304 523 7471",
    "sg:postcode":"25704",
    "sg:province":"WV",
    "sg:tags":[
        "center",
        "reserve"
    ],
    "wof:name":"Naval Reserve Center",
    "wof:placetype":"venue"
},
  "geometry": {"coordinates":[-82.468418,38.409725],"type":"Point"}
}