{
  "type": "Feature",
  "properties": {
    "iso:country":"US",
    "sg:address":"114 W 2nd Ave",
    "sg:city":"Williamson",
    "sg:classifiers":[
        {
            "category":"Health Services",
            "subcategory":"Doctor",
            "type":"Services"
        }
    ],
    "sg:phone":"+1 304 235 4194",
    "sg:postcode":"25661",
    "sg:province":"WV",
    "sg:tags":[
        "physician",
        "pediatrics-orthopedic",
        "surgeons",
        "orthopedics",
        "surgeon",
        "surgery"
    ],
    "sg:website":"http://www.drdianeshafer.com",
    "wof:name":"Diane E Shafer",
    "wof:placetype":"venue"
},
  "geometry": {"coordinates":[-82.277918,37.672387],"type":"Point"}
}