{
  "type": "Feature",
  "properties": {
    "iso:country":"US",
    "sg:address":"819 Main St E",
    "sg:city":"Oak Hill",
    "sg:classifiers":[
        {
            "category":"Retail",
            "subcategory":"Self-service Laundry",
            "type":"Services"
        }
    ],
    "sg:phone":"+1 304 465 5800",
    "sg:postcode":"25901",
    "sg:province":"WV",
    "wof:name":"Ward's Laundry Svc Inc",
    "wof:placetype":"venue"
},
  "geometry": {"coordinates":[-81.13868600000001,37.980067],"type":"Point"}
}