{
  "type": "Feature",
  "properties": {
    "addr:full":"961 Virginia St W Charleston WV 25302",
    "addr:housenumber":"961",
    "addr:postcode":"25302",
    "addr:street":"Virginia St W",
    "iso:country":"US",
    "sg:address":"961 Virginia St W",
    "sg:city":"Charleston",
    "sg:phone":"+1 304 346 0521",
    "sg:postcode":"25302",
    "sg:province":"WV",
    "sg:tags":[
        "equipment",
        "supply"
    ],
    "sg:website":"www.hootenequipment.com",
    "wof:name":"Hooten Equipment Co",
    "wof:placetype":"venue"
},
  "geometry": {"coordinates":[-81.65339899999999,38.367295],"type":"Point"}
}