{
  "type": "Feature",
  "properties": {
    "iso:country":"US",
    "sg:address":"8131 Maccorkle Ave",
    "sg:city":"Charleston",
    "sg:classifiers":[
        {
            "category":"Retail",
            "subcategory":"Auto Repair",
            "type":"Services"
        }
    ],
    "sg:phone":"+1 304 949 5990",
    "sg:postcode":"25315",
    "sg:province":"WV",
    "sg:tags":[
        "body",
        "automobile",
        "painting"
    ],
    "wof:name":"Greg Chandler's Frame & Body",
    "wof:placetype":"venue"
},
  "geometry": {"coordinates":[-81.572717,38.254081],"type":"Point"}
}