{
  "type": "Feature",
  "properties": {
    "iso:country":"US",
    "sg:address":"2706 Rte 75",
    "sg:city":"Kenova",
    "sg:classifiers":[
        {
            "category":"Professional",
            "subcategory":"Computer Services",
            "type":"Services"
        }
    ],
    "sg:phone":"+1 304 453 4255",
    "sg:postcode":"25530",
    "sg:province":"WV",
    "wof:name":"A & C Computer Svc",
    "wof:placetype":"venue"
},
  "geometry": {"coordinates":[-82.526792,38.356953],"type":"Point"}
}