{
  "type": "Feature",
  "properties": {
    "iso:country":"US",
    "sg:address":"2418 Jackson Ave",
    "sg:city":"Point Pleasant",
    "sg:classifiers":[
        {
            "category":"Shopping",
            "subcategory":"Pharmacy",
            "type":"Retail Goods"
        }
    ],
    "sg:phone":"+1 304 675 1624",
    "sg:postcode":"25550",
    "sg:province":"WV",
    "wof:name":"Rite Aid Pharmacy",
    "wof:placetype":"venue"
},
  "geometry": {"coordinates":[-82.126057,38.867112],"type":"Point"}
}