{
  "type": "Feature",
  "properties": {
    "iso:country":"US",
    "sg:address":"2301 Virginia Ave",
    "sg:city":"Culloden",
    "sg:classifiers":[
        {
            "category":"Manufacturing",
            "subcategory":"Metals",
            "type":"Manufacturing & Wholesale Goods"
        }
    ],
    "sg:phone":"+1 304 743 9046",
    "sg:postcode":"25510",
    "sg:province":"WV",
    "sg:tags":[
        "barrels",
        "drum"
    ],
    "wof:name":"Greif Inc",
    "wof:placetype":"venue"
},
  "geometry": {"coordinates":[-82.049685,38.423507],"type":"Point"}
}