{
  "type": "Feature",
  "properties": {
    "iso:country":"US",
    "sg:address":"216 Skidmore Rd",
    "sg:city":"Sutton",
    "sg:classifiers":[
        {
            "category":"Shopping",
            "subcategory":"Shoes",
            "type":"Retail Goods"
        }
    ],
    "sg:phone":"+1 304 765 7017",
    "sg:postcode":"26601",
    "sg:province":"WV",
    "wof:name":"Factory Brand Shoes",
    "wof:placetype":"venue"
},
  "geometry": {"coordinates":[-80.707379,38.665365],"type":"Point"}
}