{
  "type": "Feature",
  "properties": {
    "iso:country":"US",
    "sg:address":"119 Main St Poca",
    "sg:city":"Poca",
    "sg:classifiers":[
        {
            "category":"Restaurant",
            "type":"Food & Drink"
        }
    ],
    "sg:phone":"+1 304 755 7479",
    "sg:postcode":"25159",
    "sg:province":"WV",
    "sg:tags":[
        "italian",
        "pizza"
    ],
    "sg:website":"http://www.ginospizza.com",
    "wof:name":"Gino's Pizza & Spaghetti House",
    "wof:placetype":"venue"
},
  "geometry": {"coordinates":[-81.842201,38.512756],"type":"Point"}
}