{
  "type": "Feature",
  "properties": {
    "addr:full":"9 Falling Rock Rd Clendenin WV 25045",
    "addr:housenumber":"9",
    "addr:postcode":"25045",
    "addr:street":"Falling Rock Rd",
    "iso:country":"US",
    "sg:address":"9 Falling Rock Rd",
    "sg:city":"Clendenin",
    "sg:classifiers":[
        {
            "category":"Organizations",
            "subcategory":"Religious Organization",
            "type":"Services"
        }
    ],
    "sg:phone":"+1 304 548 5011",
    "sg:postcode":"25045",
    "sg:province":"WV",
    "sg:tags":[
        "church"
    ],
    "wof:name":"Cold Springs Gospel Tabernacle",
    "wof:placetype":"venue"
},
  "geometry": {"coordinates":[-81.268722,38.412988],"type":"Point"}
}