{
  "type": "Feature",
  "properties": {
    "iso:country":"US",
    "sg:address":"1001 Crescent Rd",
    "sg:city":"Charleston",
    "sg:classifiers":[
        {
            "category":"Organizations",
            "subcategory":"Religious Organization",
            "type":"Services"
        }
    ],
    "sg:phone":"+1 304 342 0295",
    "sg:postcode":"25302",
    "sg:province":"WV",
    "sg:tags":[
        "church"
    ],
    "wof:name":"Elmore Memorial Advent Church",
    "wof:placetype":"venue"
},
  "geometry": {"coordinates":[-81.63127900000001,38.36152],"type":"Point"}
}