{
  "type": "Feature",
  "properties": {
    "iso:country":"US",
    "sg:address":"409 E 8th St",
    "sg:city":"Parkersburg",
    "sg:classifiers":[
        {
            "category":"Retail",
            "subcategory":"Auto Repair",
            "type":"Services"
        }
    ],
    "sg:phone":"+1 304 485 9050",
    "sg:postcode":"26101",
    "sg:province":"WV",
    "sg:tags":[
        "repairing",
        "automobile"
    ],
    "wof:name":"Griffs Automotive",
    "wof:placetype":"venue"
},
  "geometry": {"coordinates":[-81.555836,39.265965],"type":"Point"}
}