{
  "type": "Feature",
  "properties": {
    "iso:country":"US",
    "sg:address":"1403 Honaker Ave",
    "sg:city":"Princeton",
    "sg:classifiers":[
        {
            "category":"Government",
            "subcategory":"Office",
            "type":"Public Place"
        }
    ],
    "sg:phone":"+1 304 425 4583",
    "sg:postcode":"24740",
    "sg:province":"WV",
    "wof:name":"Mercer County Bus Garage",
    "wof:placetype":"venue"
},
  "geometry": {"coordinates":[-81.10115999999999,37.366615],"type":"Point"}
}