{
  "type": "Feature",
  "properties": {
    "iso:country":"US",
    "sg:address":"116 N Main St",
    "sg:city":"Philippi",
    "sg:classifiers":[
        {
            "category":"Restaurant",
            "type":"Food & Drink"
        }
    ],
    "sg:phone":"+1 304 457 9881",
    "sg:postcode":"26416",
    "sg:province":"WV",
    "sg:tags":[
        "eating"
    ],
    "wof:name":"Chinese Restaurant",
    "wof:placetype":"venue"
},
  "geometry": {"coordinates":[-80.04001,39.152564],"type":"Point"}
}