{
  "type": "Feature",
  "properties": {
    "iso:country":"US",
    "sg:address":"121 Pennsylvania Ave",
    "sg:city":"Parsons",
    "sg:classifiers":[
        {
            "category":"Personal",
            "subcategory":"Beauty Salon",
            "type":"Services"
        }
    ],
    "sg:phone":"+1 304 478 4880",
    "sg:postcode":"26287",
    "sg:province":"WV",
    "wof:name":"Steel Magnolia's Hair Salon",
    "wof:placetype":"venue"
},
  "geometry": {"coordinates":[-79.672759,39.098098],"type":"Point"}
}