{
  "type": "Feature",
  "properties": {
    "iso:country":"US",
    "sg:address":"622 Commerce St",
    "sg:city":"Bluefield",
    "sg:classifiers":[
        {
            "category":"Organizations",
            "subcategory":"Membership Organization",
            "type":"Services"
        }
    ],
    "sg:phone":"+1 304 327 8187",
    "sg:postcode":"24701",
    "sg:province":"WV",
    "sg:tags":[
        "club",
        "automobile"
    ],
    "wof:name":"AAA Automobile Club",
    "wof:placetype":"venue"
},
  "geometry": {"coordinates":[-81.220483,37.268918],"type":"Point"}
}