{
  "type": "Feature",
  "properties": {
    "iso:country":"US",
    "sg:address":"2503 Washington Blvd",
    "sg:city":"Huntington",
    "sg:classifiers":[
        {
            "category":"Retail",
            "subcategory":"Laundry & Dry Cleaning",
            "type":"Services"
        }
    ],
    "sg:phone":"+1 304 525 3985",
    "sg:postcode":"25705",
    "sg:province":"WV",
    "sg:tags":[
        "plant",
        "coin"
    ],
    "wof:name":"Norge Cleaning Village",
    "wof:placetype":"venue"
},
  "geometry": {"coordinates":[-82.404399,38.406546],"type":"Point"}
}