{
  "type": "Feature",
  "properties": {
    "addr:full":"201 Main St Logan WV 25601",
    "addr:housenumber":"201",
    "addr:postcode":"25601",
    "addr:street":"Main St",
    "iso:country":"US",
    "sg:address":"201 Main St",
    "sg:city":"Logan",
    "sg:classifiers":[
        {
            "category":"Travel",
            "subcategory":"Hotels & Motels",
            "type":"Entertainment"
        }
    ],
    "sg:phone":"+1 304 752 1000",
    "sg:postcode":"25601",
    "sg:province":"WV",
    "sg:tags":[
        "operation"
    ],
    "wof:name":"Aracoma Hotel Inc",
    "wof:placetype":"venue"
},
  "geometry": {"coordinates":[-81.99276999999999,37.847218],"type":"Point"}
}