{
  "type": "Feature",
  "properties": {
    "iso:country":"US",
    "sg:address":"11835 Maccorkle Ave",
    "sg:city":"Charleston",
    "sg:classifiers":[
        {
            "category":"Organizations",
            "subcategory":"Religious Organization",
            "type":"Services"
        }
    ],
    "sg:phone":"+1 304 595 5319",
    "sg:postcode":"25315",
    "sg:province":"WV",
    "sg:tags":[
        "church"
    ],
    "wof:name":"Apostolic Church",
    "wof:placetype":"venue"
},
  "geometry": {"coordinates":[-81.544439,38.229568],"type":"Point"}
}