{
  "type": "Feature",
  "properties": {
    "iso:country":"US",
    "sg:address":"5267 Dunkle Branch Rd",
    "sg:city":"Lavalette",
    "sg:classifiers":[
        {
            "category":"Retail",
            "subcategory":"Auto Repair",
            "type":"Services"
        }
    ],
    "sg:phone":"+1 304 272 5449",
    "sg:postcode":"25535",
    "sg:province":"WV",
    "sg:tags":[
        "automotive"
    ],
    "wof:name":"Maynards Wrecker Service",
    "wof:placetype":"venue"
},
  "geometry": {"coordinates":[-82.421654,38.319631],"type":"Point"}
}