{
  "type": "Feature",
  "properties": {
    "iso:country":"US",
    "sg:address":"838 Jefferson Ave",
    "sg:city":"Charles Town",
    "sg:classifiers":[
        {
            "category":"Food & Beverages",
            "subcategory":"Groceries & Convenience Stores",
            "type":"Retail Goods"
        }
    ],
    "sg:phone":"+1 304 728 8580",
    "sg:postcode":"25414",
    "sg:province":"WV",
    "wof:name":"7-Eleven",
    "wof:placetype":"venue"
},
  "geometry": {"coordinates":[-77.850601,39.279961],"type":"Point"}
}