{
  "type": "Feature",
  "properties": {
    "iso:country":"US",
    "sg:address":"298 Babbling Brook Ln",
    "sg:city":"Martinsburg",
    "sg:classifiers":[
        {
            "category":"Building & Trades",
            "subcategory":"Construction",
            "type":"Services"
        }
    ],
    "sg:phone":"+1 717 821 2057",
    "sg:postcode":"25403",
    "sg:province":"WV",
    "sg:tags":[
        "system",
        "contractor",
        "air conditioning"
    ],
    "wof:name":"Hauck Manufacturing Co",
    "wof:placetype":"venue"
},
  "geometry": {"coordinates":[-77.99615,39.471983],"type":"Point"}
}