{
  "type": "Feature",
  "properties": {
    "addr:full":"311 5th St Glen Dale WV 26038",
    "addr:housenumber":"311",
    "addr:postcode":"26038",
    "addr:street":"5Th St Glen Dale",
    "iso:country":"US",
    "sg:address":"311 5th St",
    "sg:city":"Glen Dale",
    "sg:classifiers":[
        {
            "category":"Manufacturing",
            "subcategory":"Printing",
            "type":"Manufacturing & Wholesale Goods"
        }
    ],
    "sg:phone":"+1 304 221 2700",
    "sg:postcode":"26038",
    "sg:province":"WV",
    "sg:tags":[
        "publisher"
    ],
    "wof:name":"West Virginia Executive",
    "wof:placetype":"venue"
},
  "geometry": {"coordinates":[-80.755645,39.950419],"type":"Point"}
}