{
  "type": "Feature",
  "properties": {
    "iso:country":"US",
    "sg:address":"2014 Glenmark Ave",
    "sg:city":"Morgantown",
    "sg:classifiers":[
        {
            "category":"Social Services",
            "type":"Services"
        }
    ],
    "sg:phone":"+1 304 599 7250",
    "sg:postcode":"26505",
    "sg:province":"WV",
    "wof:name":"Economic Analysis",
    "wof:placetype":"venue"
},
  "geometry": {"coordinates":[-79.934538,39.657988],"type":"Point"}
}