{
  "type": "Feature",
  "properties": {
    "addr:full":"1015 Bluefield Ave Bluefield WV 24701",
    "addr:housenumber":"1015",
    "addr:postcode":"24701",
    "addr:street":"Bluefield Ave",
    "iso:country":"US",
    "sg:address":"1015 Bluefield Ave",
    "sg:city":"Bluefield",
    "sg:classifiers":[
        {
            "category":"Autos & Motor Vehicles",
            "subcategory":"Automobile Sales",
            "type":"Retail Goods"
        }
    ],
    "sg:phone":"+1 304 327 2411",
    "sg:postcode":"24701",
    "sg:province":"WV",
    "sg:tags":[
        "car",
        "dealer"
    ],
    "wof:name":"T & T Pontiac Buick Jeep",
    "wof:placetype":"venue"
},
  "geometry": {"coordinates":[-81.235985,37.264598],"type":"Point"}
}