{
  "type": "Feature",
  "properties": {
    "iso:country":"US",
    "sg:address":"3315 Belmont St",
    "sg:city":"Bellaire",
    "sg:classifiers":[
        {
            "category":"Recreation",
            "subcategory":"Arcade",
            "type":"Entertainment"
        }
    ],
    "sg:phone":"+1 740 676 2714",
    "sg:postcode":"43906",
    "sg:province":"OH",
    "sg:tags":[
        "operated",
        "coin",
        "amusement"
    ],
    "wof:name":"Belmont Vending",
    "wof:placetype":"venue"
},
  "geometry": {"coordinates":[-80.742774,40.015223],"type":"Point"}
}