{
  "type": "Feature",
  "properties": {
    "iso:country":"US",
    "sg:address":"485 Fillmore St",
    "sg:city":"Harpers Ferry",
    "sg:classifiers":[
        {
            "category":"Recreation",
            "type":"Entertainment"
        }
    ],
    "sg:phone":"+1 304 535 6455",
    "sg:postcode":"25425",
    "sg:province":"WV",
    "sg:tags":[
        "parks"
    ],
    "wof:name":"National Park Ranger",
    "wof:placetype":"venue"
},
  "geometry": {"coordinates":[-77.74410899999999,39.325032],"type":"Point"}
}