{
  "type": "Feature",
  "properties": {
    "iso:country":"US",
    "sg:address":"1450 Old Athens Rd",
    "sg:city":"Princeton",
    "sg:classifiers":[
        {
            "category":"Building & Trades",
            "subcategory":"Plumbing",
            "type":"Services"
        }
    ],
    "sg:phone":"+1 304 425 7920",
    "sg:postcode":"24740",
    "sg:province":"WV",
    "sg:tags":[
        "conditioning",
        "air",
        "system",
        "contractor"
    ],
    "wof:name":"Wade & Miller Heating Inc",
    "wof:placetype":"venue"
},
  "geometry": {"coordinates":[-81.05316500000001,37.398885],"type":"Point"}
}