{
  "type": "Feature",
  "properties": {
    "addr:full":"1253 Gihon Rd Parkersburg WV 26101",
    "addr:housenumber":"1253",
    "addr:postcode":"26101",
    "addr:street":"Gihon Rd",
    "iso:country":"US",
    "sg:address":"1253 Gihon Rd",
    "sg:city":"Parkersburg",
    "sg:classifiers":[
        {
            "category":"Restaurant",
            "type":"Food & Drink"
        }
    ],
    "sg:phone":"+1 304 422 5901",
    "sg:postcode":"26101",
    "sg:province":"WV",
    "sg:tags":[
        "eating"
    ],
    "wof:name":"Prime Tyme Sports Restaurant",
    "wof:placetype":"venue"
},
  "geometry": {"coordinates":[-81.574547,39.241171],"type":"Point"}
}