{
  "type": "Feature",
  "properties": {
    "addr:full":"5843 Davis Creek Rd Barboursville WV 25504",
    "addr:housenumber":"5843",
    "addr:postcode":"25504",
    "addr:street":"Davis Creek Rd",
    "iso:country":"US",
    "sg:address":"5843 Davis Creek Rd",
    "sg:city":"Barboursville",
    "sg:classifiers":[
        {
            "category":"Shopping",
            "subcategory":"Used Merchandise",
            "type":"Retail Goods"
        }
    ],
    "sg:phone":"+1 304 736 6047",
    "sg:postcode":"25504",
    "sg:province":"WV",
    "sg:tags":[
        "shop",
        "consignment"
    ],
    "wof:name":"Treasure Chest",
    "wof:placetype":"venue"
},
  "geometry": {"coordinates":[-82.326435,38.395663],"type":"Point"}
}