{
  "type": "Feature",
  "properties": {
    "addr:full":"100 Rowan Rd White Slphr Spgs WV 24986",
    "addr:housenumber":"100",
    "addr:postcode":"24986",
    "addr:street":"Rowan Rd;Slphr Spgs",
    "iso:country":"US",
    "sg:address":"100 Rowan Rd",
    "sg:city":"White Slphr Spgs",
    "sg:classifiers":[
        {
            "category":"Banks & Credit Unions",
            "subcategory":"Investment Brokerage",
            "type":"Services"
        }
    ],
    "sg:phone":"+1 304 536 2097",
    "sg:postcode":"24986",
    "sg:province":"WV",
    "wof:name":"Whiting Investments",
    "wof:placetype":"venue"
},
  "geometry": {"coordinates":[-80.30853500000001,37.798077],"type":"Point"}
}