{
  "type": "Feature",
  "properties": {
    "iso:country":"US",
    "sg:address":"1124 Airport Rd",
    "sg:city":"Beaver",
    "sg:classifiers":[
        {
            "category":"Restaurant",
            "type":"Food & Drink"
        }
    ],
    "sg:phone":"+1 304 256 7549",
    "sg:postcode":"25813",
    "sg:province":"WV",
    "wof:name":"Dicks Yacht Club",
    "wof:placetype":"venue"
},
  "geometry": {"coordinates":[-81.07969,37.769076],"type":"Point"}
}