{
  "type": "Feature",
  "properties": {
    "iso:country":"US",
    "sg:address":"109 Grant Ave",
    "sg:city":"Morgantown",
    "sg:classifiers":[
        {
            "category":"Wholesale",
            "subcategory":"Machinery & Supplies",
            "type":"Manufacturing & Wholesale Goods"
        }
    ],
    "sg:phone":"+1 304 292 4970",
    "sg:postcode":"26505",
    "sg:province":"WV",
    "sg:tags":[
        "sprinkler"
    ],
    "wof:name":"Alliance Fire Systems Inc",
    "wof:placetype":"venue"
},
  "geometry": {"coordinates":[-79.956254,39.638496],"type":"Point"}
}