{
  "type": "Feature",
  "properties": {
    "addr:full":"1659 Hillcrest Rd Fairmont WV 26554",
    "addr:housenumber":"1659",
    "addr:postcode":"26554",
    "addr:street":"Hillcrest Rd",
    "iso:country":"US",
    "sg:address":"1659 Hillcrest Rd",
    "sg:city":"Fairmont",
    "sg:classifiers":[
        {
            "category":"Manufacturing",
            "subcategory":"Signs",
            "type":"Manufacturing & Wholesale Goods"
        }
    ],
    "sg:phone":"+1 304 368 9000",
    "sg:postcode":"26554",
    "sg:province":"WV",
    "sg:tags":[
        "specialty",
        "mfg"
    ],
    "wof:name":"Mountain Signs & Graphics Co",
    "wof:placetype":"venue"
},
  "geometry": {"coordinates":[-80.178416,39.491267],"type":"Point"}
}