{
  "type": "Feature",
  "properties": {
    "addr:full":"4013 Washington St SW Charleston WV 25309",
    "addr:housenumber":"4013",
    "addr:postcode":"25309",
    "addr:street":"Washington St Sw",
    "iso:country":"US",
    "sg:address":"4013 Washington St SW",
    "sg:city":"Charleston",
    "sg:classifiers":[
        {
            "category":"Professional",
            "subcategory":"Computer Services",
            "type":"Services"
        }
    ],
    "sg:phone":"+1 304 746 4434",
    "sg:postcode":"25309",
    "sg:province":"WV",
    "sg:tags":[
        "programing",
        "custom"
    ],
    "wof:name":"Commtec",
    "wof:placetype":"venue"
},
  "geometry": {"coordinates":[-81.71422800000001,38.356874],"type":"Point"}
}