{
  "type": "Feature",
  "properties": {
    "iso:country":"US",
    "sg:address":"3 Seneca Dr",
    "sg:city":"Buckhannon",
    "sg:classifiers":[
        {
            "category":"Building & Trades",
            "subcategory":"Construction",
            "type":"Services"
        }
    ],
    "sg:phone":"+1 304 472 5595",
    "sg:postcode":"26201",
    "sg:province":"WV",
    "sg:tags":[
        "general",
        "contractor"
    ],
    "wof:name":"High Point Construction LTD",
    "wof:placetype":"venue"
},
  "geometry": {"coordinates":[-80.22787,38.974752],"type":"Point"}
}