{
  "type": "Feature",
  "properties": {
    "iso:country":"US",
    "sg:address":"205 N Court St",
    "sg:city":"Lewisburg",
    "sg:classifiers":[
        {
            "category":"Professional",
            "subcategory":"Lawyer & Legal Services",
            "type":"Services"
        }
    ],
    "sg:phone":"+1 304 645 7111",
    "sg:postcode":"24901",
    "sg:province":"WV",
    "wof:name":"Douglas H Arbuckle",
    "wof:placetype":"venue"
},
  "geometry": {"coordinates":[-80.44459999999999,37.804248],"type":"Point"}
}