{
  "type": "Feature",
  "properties": {
    "iso:country":"US",
    "sg:address":"819 3rd Ave",
    "sg:city":"Marlinton",
    "sg:classifiers":[
        {
            "category":"Insurance",
            "subcategory":"Insurance Agent",
            "type":"Services"
        }
    ],
    "sg:phone":"+1 304 799 6909",
    "sg:postcode":"24954",
    "sg:province":"WV",
    "wof:name":"LA Mora Insurance Inc",
    "wof:placetype":"venue"
},
  "geometry": {"coordinates":[-80.09357900000001,38.222865],"type":"Point"}
}