{
  "type": "Feature",
  "properties": {
    "addr:full":"1803 Murdoch Ave Parkersburg WV 26101",
    "addr:housenumber":"1803",
    "addr:postcode":"26101",
    "addr:street":"Murdoch Ave",
    "iso:country":"US",
    "sg:address":"1803 Murdoch Ave",
    "sg:city":"Parkersburg",
    "sg:classifiers":[
        {
            "category":"Utilities",
            "subcategory":"Electric",
            "type":"Services"
        }
    ],
    "sg:phone":"+1 800 255 3443",
    "sg:postcode":"26101",
    "sg:province":"WV",
    "wof:name":"West Penn Power Company",
    "wof:placetype":"venue"
},
  "geometry": {"coordinates":[-81.55139200000001,39.278376],"type":"Point"}
}