{
  "type": "Feature",
  "properties": {
    "iso:country":"US",
    "sg:address":"137 Pleasant St",
    "sg:city":"Morgantown",
    "sg:classifiers":[
        {
            "category":"Shopping",
            "subcategory":"Bicycles & Sporting Goods",
            "type":"Retail Goods"
        }
    ],
    "sg:phone":"+1 304 292 2294",
    "sg:postcode":"26505",
    "sg:province":"WV",
    "sg:tags":[
        "equipment",
        "skateboard"
    ],
    "wof:name":"Wall Street Board Exchange",
    "wof:placetype":"venue"
},
  "geometry": {"coordinates":[-79.95794100000001,39.629462],"type":"Point"}
}