{
  "type": "Feature",
  "properties": {
    "iso:country":"US",
    "sg:address":"2002 Washington Blvd",
    "sg:city":"Belpre",
    "sg:classifiers":[
        {
            "category":"Professional",
            "subcategory":"Lawyer & Legal Services",
            "type":"Services"
        }
    ],
    "sg:phone":"+1 740 423 7569",
    "sg:postcode":"45714",
    "sg:province":"OH",
    "sg:tags":[
        "attorney"
    ],
    "wof:name":"Jim D Fox",
    "wof:placetype":"venue"
},
  "geometry": {"coordinates":[-81.603303,39.277847],"type":"Point"}
}