{
  "type": "Feature",
  "properties": {
    "iso:country":"US",
    "sg:address":"2050 3rd Ave",
    "sg:city":"Huntington",
    "sg:classifiers":[
        {
            "category":"Bars & Pubs",
            "type":"Food & Drink"
        }
    ],
    "sg:phone":"+1 304 523 8100",
    "sg:postcode":"25703",
    "sg:province":"WV",
    "sg:tags":[
        "club",
        "night"
    ],
    "wof:name":"Marleys Doghouse Inc",
    "wof:placetype":"venue"
},
  "geometry": {"coordinates":[-82.42225500000001,38.42576],"type":"Point"}
}