{
  "type": "Feature",
  "properties": {
    "iso:country":"US",
    "sg:address":"5242 Kanawha Blvd E",
    "sg:city":"Charleston",
    "sg:classifiers":[
        {
            "category":"Real Estate",
            "subcategory":"Real Estate Agent",
            "type":"Services"
        }
    ],
    "sg:phone":"+1 304 925 7888",
    "sg:postcode":"25312",
    "sg:province":"WV",
    "wof:name":"Raines Property Management LLC",
    "wof:placetype":"venue"
},
  "geometry": {"coordinates":[-81.562361,38.28334],"type":"Point"}
}