{
  "type": "Feature",
  "properties": {
    "iso:country":"US",
    "sg:address":"303 W Water St",
    "sg:city":"Harrisville",
    "sg:classifiers":[
        {
            "category":"Building & Trades",
            "subcategory":"Construction",
            "type":"Services"
        }
    ],
    "sg:phone":"+1 304 643 4368",
    "sg:postcode":"26362",
    "sg:province":"WV",
    "sg:tags":[
        "heavy"
    ],
    "wof:name":"Sewer Plant",
    "wof:placetype":"venue"
},
  "geometry": {"coordinates":[-81.056217,39.207778],"type":"Point"}
}