{
  "type": "Feature",
  "properties": {
    "iso:country":"US",
    "sg:address":"1 Market St",
    "sg:city":"Parkersburg",
    "sg:classifiers":[
        {
            "category":"Manufacturing",
            "subcategory":"Lumber",
            "type":"Manufacturing & Wholesale Goods"
        }
    ],
    "sg:phone":"+1 304 865 8777",
    "sg:postcode":"26101",
    "sg:province":"WV",
    "sg:tags":[
        "forester"
    ],
    "wof:name":"Natco Forestry Svc",
    "wof:placetype":"venue"
},
  "geometry": {"coordinates":[-81.562736,39.264568],"type":"Point"}
}