{
  "type": "Feature",
  "properties": {
    "iso:country":"US",
    "sg:address":"1306 5th St",
    "sg:city":"Moundsville",
    "sg:classifiers":[
        {
            "category":"Shopping",
            "subcategory":"Music",
            "type":"Retail Goods"
        }
    ],
    "sg:phone":"+1 304 845 0445",
    "sg:postcode":"26041",
    "sg:province":"WV",
    "sg:tags":[
        "video",
        "disc",
        "tape",
        "cassette"
    ],
    "wof:name":"Village Video",
    "wof:placetype":"venue"
},
  "geometry": {"coordinates":[-80.73635400000001,39.920082],"type":"Point"}
}