{
  "type": "Feature",
  "properties": {
    "iso:country":"US",
    "sg:address":"165 W Main St",
    "sg:city":"Bridgeport",
    "sg:classifiers":[
        {
            "category":"Retail",
            "subcategory":"Repair Shop",
            "type":"Services"
        }
    ],
    "sg:phone":"+1 304 848 0402",
    "sg:postcode":"26330",
    "sg:province":"WV",
    "sg:tags":[
        "related"
    ],
    "wof:name":"Kazmedic Repair & Spray",
    "wof:placetype":"venue"
},
  "geometry": {"coordinates":[-80.253326,39.284011],"type":"Point"}
}