{
  "type": "Feature",
  "properties": {
    "iso:country":"US",
    "sg:address":"77 Hospital Rd",
    "sg:city":"Logan",
    "sg:classifiers":[
        {
            "category":"Health Services",
            "subcategory":"Doctor",
            "type":"Services"
        }
    ],
    "sg:phone":"+1 304 792 1116",
    "sg:postcode":"25661",
    "sg:province":"WV",
    "sg:tags":[
        "physician",
        "surgeon"
    ],
    "wof:name":"Hematology & Oncology Inc",
    "wof:placetype":"venue"
},
  "geometry": {"coordinates":[-82.26772699999999,37.676146],"type":"Point"}
}