{
  "type": "Feature",
  "properties": {
    "iso:country":"US",
    "sg:address":"701 Division St",
    "sg:city":"Parkersburg",
    "sg:classifiers":[
        {
            "category":"Retail",
            "subcategory":"Auto Repair",
            "type":"Services"
        }
    ],
    "sg:phone":"+1 304 428 7158",
    "sg:postcode":"26101",
    "sg:province":"WV",
    "sg:tags":[
        "repairing",
        "automotive",
        "automobile"
    ],
    "wof:name":"A-1 Alignment & Automotive Svc",
    "wof:placetype":"venue"
},
  "geometry": {"coordinates":[-81.554406,39.2511],"type":"Point"}
}