{
  "type": "Feature",
  "properties": {
    "iso:country":"US",
    "sg:address":"5202 Purdy Dr",
    "sg:city":"Cross Lanes",
    "sg:classifiers":[
        {
            "category":"Professional",
            "subcategory":"Secretarial Services",
            "type":"Services"
        }
    ],
    "sg:phone":"+1 304 552 3587",
    "sg:postcode":"25313",
    "sg:province":"WV",
    "sg:tags":[
        "convention",
        "court",
        "reporter"
    ],
    "wof:name":"John Berkhouse",
    "wof:placetype":"venue"
},
  "geometry": {"coordinates":[-81.75621599999999,38.432451],"type":"Point"}
}