{
  "type": "Feature",
  "properties": {
    "addr:full":"733 Florida St Milton WV 25541",
    "addr:housenumber":"733",
    "addr:postcode":"25541",
    "addr:street":"Florida St",
    "iso:country":"US",
    "sg:address":"733 Florida St",
    "sg:city":"Milton",
    "sg:classifiers":[
        {
            "category":"Retail",
            "subcategory":"Auto Repair",
            "type":"Services"
        }
    ],
    "sg:phone":"+1 304 743 5230",
    "sg:postcode":"25541",
    "sg:province":"WV",
    "sg:tags":[
        "body"
    ],
    "wof:name":"Evans Body Shop",
    "wof:placetype":"venue"
},
  "geometry": {"coordinates":[-82.13012999999999,38.439921],"type":"Point"}
}