{
  "type": "Feature",
  "properties": {
    "addr:full":"1235 Parkview Dr Morgantown WV 26505",
    "addr:housenumber":"1235",
    "addr:postcode":"26505",
    "addr:street":"Parkview Dr",
    "iso:country":"US",
    "sg:address":"1235 Parkview Dr",
    "sg:city":"Morgantown",
    "sg:classifiers":[
        {
            "category":"Recreation",
            "subcategory":"Amusement Park",
            "type":"Entertainment"
        }
    ],
    "sg:phone":"+1 304 599 0478",
    "sg:postcode":"26505",
    "sg:province":"WV",
    "sg:tags":[
        "executive",
        "place",
        "se",
        "arcade"
    ],
    "wof:name":"Krepps Pool",
    "wof:placetype":"venue"
},
  "geometry": {"coordinates":[-79.977386,39.651147],"type":"Point"}
}