{
  "type": "Feature",
  "properties": {
    "iso:country":"US",
    "sg:address":"194 Wilson St",
    "sg:city":"Martinsburg",
    "sg:classifiers":[
        {
            "category":"Wholesale",
            "subcategory":"Electrical",
            "type":"Manufacturing & Wholesale Goods"
        }
    ],
    "sg:phone":"+1 304 263 9995",
    "sg:postcode":"25401",
    "sg:province":"WV",
    "sg:tags":[
        "electric",
        "motor"
    ],
    "wof:name":"Biedlers Electric Motor Repair",
    "wof:placetype":"venue"
},
  "geometry": {"coordinates":[-77.967551,39.445159],"type":"Point"}
}