{
  "type": "Feature",
  "properties": {
    "iso:country":"US",
    "sg:address":"475 Cranberry Dr",
    "sg:city":"Beckley",
    "sg:classifiers":[
        {
            "category":"Building & Trades",
            "subcategory":"Construction",
            "type":"Services"
        }
    ],
    "sg:phone":"+1 304 254 8601",
    "sg:postcode":"25801",
    "sg:province":"WV",
    "sg:tags":[
        "residential",
        "general",
        "commercial",
        "contractor"
    ],
    "wof:name":"Seneca Construction Inc",
    "wof:placetype":"venue"
},
  "geometry": {"coordinates":[-81.20370800000001,37.825882],"type":"Point"}
}