{
  "type": "Feature",
  "properties": {
    "iso:country":"US",
    "sg:address":"312 Echols Ln",
    "sg:city":"Lewisburg",
    "sg:classifiers":[
        {
            "category":"Building & Trades",
            "subcategory":"Cleaning & Sanitation",
            "type":"Services"
        }
    ],
    "sg:phone":"+1 304 647 5339",
    "sg:postcode":"24901",
    "sg:province":"WV",
    "sg:tags":[
        "maintenance"
    ],
    "wof:name":"Clemons Window Clg & Jantr Svc",
    "wof:placetype":"venue"
},
  "geometry": {"coordinates":[-80.445904,37.796686],"type":"Point"}
}