{
  "type": "Feature",
  "properties": {
    "iso:country":"US",
    "sg:address":"305 Main St",
    "sg:city":"Sutton",
    "sg:classifiers":[
        {
            "category":"Shopping",
            "subcategory":"Books",
            "type":"Retail Goods"
        }
    ],
    "sg:phone":"+1 304 765 3365",
    "sg:postcode":"26601",
    "sg:province":"WV",
    "sg:tags":[
        "dealer"
    ],
    "sg:website":"www.cbrbk.com",
    "wof:name":"Corporate Books",
    "wof:placetype":"venue"
},
  "geometry": {"coordinates":[-80.708606,38.664589],"type":"Point"}
}