{
  "type": "Feature",
  "properties": {
    "addr:full":"1 Craddock Way Poca WV 25159",
    "addr:housenumber":"1",
    "addr:postcode":"25159",
    "addr:street":"Craddock Way",
    "iso:country":"US",
    "sg:address":"1 Craddock Way",
    "sg:city":"Poca",
    "sg:classifiers":[
        {
            "category":"Wholesale",
            "subcategory":"Electrical",
            "type":"Manufacturing & Wholesale Goods"
        }
    ],
    "sg:phone":"+1 304 755 6860",
    "sg:postcode":"25159",
    "sg:province":"WV",
    "sg:tags":[
        "equipment"
    ],
    "wof:name":"GE",
    "wof:placetype":"venue"
},
  "geometry": {"coordinates":[-81.82080499999999,38.453964],"type":"Point"}
}