{
  "type": "Feature",
  "properties": {
    "addr:full":"35 E Benjamin Dr New Martinsville WV 26155",
    "addr:housenumber":"35",
    "addr:postcode":"26155",
    "addr:street":"E Benjamin Dr",
    "iso:country":"US",
    "sg:address":"35 E Benjamin Dr",
    "sg:city":"New Martinsville",
    "sg:classifiers":[
        {
            "category":"Health Services",
            "subcategory":"Doctor",
            "type":"Services"
        }
    ],
    "sg:phone":"+1 304 455 5644",
    "sg:postcode":"26155",
    "sg:province":"WV",
    "wof:name":"Cunningham Jay E",
    "wof:placetype":"venue"
},
  "geometry": {"coordinates":[-80.85735699999999,39.680479],"type":"Point"}
}