{
  "type": "Feature",
  "properties": {
    "addr:full":"1565 Smith Rd Charleston WV 25314",
    "addr:housenumber":"1565",
    "addr:postcode":"25314",
    "addr:street":"Smith Rd",
    "iso:country":"US",
    "sg:address":"1565 Smith Rd",
    "sg:city":"Charleston",
    "sg:classifiers":[
        {
            "category":"Organizations",
            "subcategory":"Religious Organization",
            "type":"Services"
        }
    ],
    "sg:phone":"+1 304 346 9530",
    "sg:postcode":"25314",
    "sg:province":"WV",
    "wof:name":"South Hills Church Of Nazarene",
    "wof:placetype":"venue"
},
  "geometry": {"coordinates":[-81.65947300000001,38.336457],"type":"Point"}
}