{
  "type": "Feature",
  "properties": {
    "addr:full":"1515 Grand Central Ave Vienna WV 26105",
    "addr:housenumber":"1515",
    "addr:postcode":"26105",
    "addr:street":"Grand Central Ave",
    "iso:country":"US",
    "sg:address":"1515 Grand Central Ave",
    "sg:city":"Vienna",
    "sg:classifiers":[
        {
            "category":"Ice Cream",
            "type":"Food & Drink"
        }
    ],
    "sg:menulink":"http://www.allmenus.com/wv/parkersburg/184515-cold-stone-creamery/menu/",
    "sg:phone":"+1 304 865 2653",
    "sg:postcode":"26105",
    "sg:province":"WV",
    "sg:tags":[
        "smoothy",
        "juice",
        "american"
    ],
    "wof:name":"Cold Stone Creamery",
    "wof:placetype":"venue"
},
  "geometry": {"coordinates":[-81.553511,39.314717],"type":"Point"}
}