{
  "type": "Feature",
  "properties": {
    "iso:country":"US",
    "sg:address":"339 Wright Ct",
    "sg:city":"Huntington",
    "sg:classifiers":[
        {
            "category":"Professional",
            "subcategory":"Engineering",
            "type":"Services"
        }
    ],
    "sg:phone":"+1 304 736 7843",
    "sg:postcode":"25705",
    "sg:province":"WV",
    "wof:name":"Peterson Engineering and Serv",
    "wof:placetype":"venue"
},
  "geometry": {"coordinates":[-82.36840100000001,38.406631],"type":"Point"}
}