{
  "type": "Feature",
  "properties": {
    "iso:country":"US",
    "sg:address":"200 Spring St",
    "sg:city":"White Slphr Spgs",
    "sg:classifiers":[
        {
            "category":"Government",
            "subcategory":"Police Station",
            "type":"Public Place"
        }
    ],
    "sg:phone":"+1 304 000 1111",
    "sg:postcode":"24986",
    "sg:province":"WV",
    "sg:tags":[
        "department"
    ],
    "wof:name":"White Sulphur Springs Police",
    "wof:placetype":"venue"
},
  "geometry": {"coordinates":[-80.30452699999999,37.791145],"type":"Point"}
}