{
  "type": "Feature",
  "properties": {
    "iso:country":"US",
    "sg:address":"261 Willey St",
    "sg:city":"Morgantown",
    "sg:classifiers":[
        {
            "category":"Organizations",
            "subcategory":"Community Association",
            "type":"Services"
        }
    ],
    "sg:phone":"+1 304 296 7623",
    "sg:postcode":"26505",
    "sg:province":"WV",
    "wof:name":"Alpha Phi Sorority",
    "wof:placetype":"venue"
},
  "geometry": {"coordinates":[-79.952804,39.631746],"type":"Point"}
}