{
  "type": "Feature",
  "properties": {
    "iso:country":"US",
    "sg:address":"212 N Chestnut St",
    "sg:city":"Barnesville",
    "sg:classifiers":[
        {
            "category":"Professional",
            "subcategory":"Lawyer & Legal Services",
            "type":"Services"
        }
    ],
    "sg:phone":"+1 740 425 3001",
    "sg:postcode":"43713",
    "sg:province":"OH",
    "sg:tags":[
        "attorney"
    ],
    "wof:name":"Barnesville Area Education",
    "wof:placetype":"venue"
},
  "geometry": {"coordinates":[-81.176721,39.989686],"type":"Point"}
}