{
  "type": "Feature",
  "properties": {
    "iso:country":"US",
    "sg:address":"1420 7th St",
    "sg:city":"Parkersburg",
    "sg:classifiers":[
        {
            "category":"Real Estate",
            "subcategory":"Real Estate Agent",
            "type":"Services"
        }
    ],
    "sg:phone":"+1 304 485 8483",
    "sg:postcode":"26101",
    "sg:province":"WV",
    "sg:tags":[
        "appraiser"
    ],
    "wof:name":"L Dean Schwartz Appraisel",
    "wof:placetype":"venue"
},
  "geometry": {"coordinates":[-81.538918,39.264382],"type":"Point"}
}