{
  "type": "Feature",
  "properties": {
    "addr:full":"28 Kings Hwy Huntington WV 25705",
    "addr:housenumber":"28",
    "addr:postcode":"25705",
    "addr:street":"Kings Hwy",
    "iso:country":"US",
    "sg:address":"28 Kings Hwy",
    "sg:city":"Huntington",
    "sg:classifiers":[
        {
            "category":"Wholesale",
            "subcategory":"Computers",
            "type":"Manufacturing & Wholesale Goods"
        }
    ],
    "sg:phone":"+1 304 697 1702",
    "sg:postcode":"25705",
    "sg:province":"WV",
    "wof:name":"Wholesale Computers Inc",
    "wof:placetype":"venue"
},
  "geometry": {"coordinates":[-82.406238,38.398252],"type":"Point"}
}