{
  "type": "Feature",
  "properties": {
    "iso:country":"US",
    "sg:address":"2309 Jackson Ave",
    "sg:city":"Point Pleasant",
    "sg:classifiers":[
        {
            "category":"Local Transit",
            "type":"Transportation"
        }
    ],
    "sg:phone":"+1 304 675 6134",
    "sg:postcode":"25550",
    "sg:province":"WV",
    "sg:tags":[
        "ambulance"
    ],
    "wof:name":"Mason County Emergency",
    "wof:placetype":"venue"
},
  "geometry": {"coordinates":[-82.12641600000001,38.866029],"type":"Point"}
}