{
  "type": "Feature",
  "properties": {
    "addr:full":"402 Jones Ave Oak Hill WV 25901",
    "addr:housenumber":"402",
    "addr:postcode":"25901",
    "addr:street":"Jones Ave",
    "iso:country":"US",
    "sg:address":"402 Jones Ave",
    "sg:city":"Oak Hill",
    "sg:classifiers":[
        {
            "category":"Food & Beverages",
            "subcategory":"Groceries & Convenience Stores",
            "type":"Retail Goods"
        }
    ],
    "sg:phone":"+1 304 469 3252",
    "sg:postcode":"25901",
    "sg:province":"WV",
    "wof:name":"Little General 104",
    "wof:placetype":"venue"
},
  "geometry": {"coordinates":[-81.15246,37.973966],"type":"Point"}
}