{
  "type": "Feature",
  "properties": {
    "addr:full":"301 S Raleigh St Martinsburg WV 25401",
    "addr:housenumber":"301",
    "addr:postcode":"25401",
    "addr:street":"S Raleigh St",
    "iso:country":"US",
    "sg:address":"301 S Raleigh St",
    "sg:city":"Martinsburg",
    "sg:classifiers":[
        {
            "category":"Manufacturing",
            "subcategory":"Printing",
            "type":"Manufacturing & Wholesale Goods"
        }
    ],
    "sg:phone":"+1 304 263 1455",
    "sg:postcode":"25401",
    "sg:province":"WV",
    "sg:tags":[
        "commercial",
        "b",
        "lithographic",
        "typesetting"
    ],
    "wof:name":"Berkeley Printing & Design LLC",
    "wof:placetype":"venue"
},
  "geometry": {"coordinates":[-77.969347,39.455892],"type":"Point"}
}