{
  "type": "Feature",
  "properties": {
    "iso:country":"US",
    "sg:address":"220 Court St",
    "sg:city":"Clarksburg",
    "sg:classifiers":[
        {
            "category":"Organizations",
            "subcategory":"Community Association",
            "type":"Services"
        }
    ],
    "sg:phone":"+1 304 623 7920",
    "sg:postcode":"26301",
    "sg:province":"WV",
    "sg:tags":[
        "fraternal"
    ],
    "wof:name":"FOP Mountaineer Lodge 78",
    "wof:placetype":"venue"
},
  "geometry": {"coordinates":[-80.339674,39.279089],"type":"Point"}
}