{
  "type": "Feature",
  "properties": {
    "iso:country":"US",
    "sg:address":"1504 Grosscup Ave",
    "sg:city":"Dunbar",
    "sg:classifiers":[
        {
            "category":"Organizations",
            "subcategory":"Religious Organization",
            "type":"Services"
        }
    ],
    "sg:phone":"+1 304 768 2527",
    "sg:postcode":"25064",
    "sg:province":"WV",
    "sg:tags":[
        "monastery",
        "convent"
    ],
    "wof:name":"Sisters Of Divine Providence",
    "wof:placetype":"venue"
},
  "geometry": {"coordinates":[-81.74571,38.358453],"type":"Point"}
}