{
  "type": "Feature",
  "properties": {
    "addr:full":"1750 7th Ave Huntington WV 25703",
    "addr:housenumber":"1750",
    "addr:postcode":"25703",
    "addr:street":"7Th Ave",
    "iso:country":"US",
    "sg:address":"1750 7th Ave",
    "sg:city":"Huntington",
    "sg:classifiers":[
        {
            "category":"Retail",
            "subcategory":"Repair Shop",
            "type":"Services"
        }
    ],
    "sg:phone":"+1 304 525 5201",
    "sg:postcode":"25703",
    "sg:province":"WV",
    "sg:tags":[
        "clocks",
        "parts"
    ],
    "wof:name":"Tri State Clock Repair",
    "wof:placetype":"venue"
},
  "geometry": {"coordinates":[-82.424153,38.419984],"type":"Point"}
}