{
  "type": "Feature",
  "properties": {
    "addr:full":"902 Augusta St Bluefield WV 24701",
    "addr:housenumber":"902",
    "addr:postcode":"24701",
    "addr:street":"Augusta St",
    "iso:country":"US",
    "sg:address":"902 Augusta St",
    "sg:city":"Bluefield",
    "sg:classifiers":[
        {
            "category":"Organizations",
            "subcategory":"Religious Organization",
            "type":"Services"
        }
    ],
    "sg:phone":"+1 304 327 5716",
    "sg:postcode":"24701",
    "sg:province":"WV",
    "wof:name":"Family Worship Chapel",
    "wof:placetype":"venue"
},
  "geometry": {"coordinates":[-81.227558,37.253224],"type":"Point"}
}