{
  "type": "Feature",
  "properties": {
    "iso:country":"US",
    "sg:address":"214 Mont Phillips Rd",
    "sg:city":"Shady Spring",
    "sg:classifiers":[
        {
            "category":"Recreation",
            "type":"Entertainment"
        }
    ],
    "sg:phone":"+1 304 763 4912",
    "sg:postcode":"25918",
    "sg:province":"WV",
    "wof:name":"Pikes",
    "wof:placetype":"venue"
},
  "geometry": {"coordinates":[-81.070516,37.702265],"type":"Point"}
}