{
  "type": "Feature",
  "properties": {
    "iso:country":"US",
    "sg:address":"4799 Riverside Dr",
    "sg:city":"Lavalette",
    "sg:classifiers":[
        {
            "category":"Manufacturing",
            "subcategory":"Signs",
            "type":"Manufacturing & Wholesale Goods"
        }
    ],
    "sg:phone":"+1 304 525 4017",
    "sg:postcode":"25535",
    "sg:province":"WV",
    "sg:tags":[
        "specialty",
        "mfg"
    ],
    "wof:name":"Alley Cat Signs",
    "wof:placetype":"venue"
},
  "geometry": {"coordinates":[-82.44956000000001,38.320161],"type":"Point"}
}