{
  "type": "Feature",
  "properties": {
    "addr:full":"3977 E Cumberland Rd Bluefield WV 24701",
    "addr:housenumber":"3977",
    "addr:postcode":"24701",
    "addr:street":"E Cumberland Rd",
    "iso:country":"US",
    "sg:address":"3977 E Cumberland Rd",
    "sg:city":"Bluefield",
    "sg:classifiers":[
        {
            "category":"Retail",
            "subcategory":"Portrait Studio",
            "type":"Services"
        }
    ],
    "sg:phone":"+1 304 323 3515",
    "sg:postcode":"24701",
    "sg:province":"WV",
    "sg:tags":[
        "photographer"
    ],
    "wof:name":"Olan Mills Portrait Studio",
    "wof:placetype":"venue"
},
  "geometry": {"coordinates":[-81.18831,37.261705],"type":"Point"}
}