{
  "type": "Feature",
  "properties": {
    "addr:full":"610 National Rd Wheeling WV 26003",
    "addr:housenumber":"610",
    "addr:postcode":"26003",
    "addr:street":"National Rd",
    "iso:country":"US",
    "sg:address":"610 National Rd",
    "sg:city":"Wheeling",
    "sg:classifiers":[
        {
            "category":"Bars & Pubs",
            "type":"Food & Drink"
        }
    ],
    "sg:phone":"+1 304 234 1193",
    "sg:postcode":"26003",
    "sg:province":"WV",
    "wof:name":"V Twin Tavern",
    "wof:placetype":"venue"
},
  "geometry": {"coordinates":[-80.704033,40.075146],"type":"Point"}
}