{
  "type": "Feature",
  "properties": {
    "iso:country":"US",
    "sg:address":"4316 Hughes Branch Rd",
    "sg:city":"Huntington",
    "sg:classifiers":[
        {
            "category":"Home & Garden",
            "subcategory":"Furniture",
            "type":"Retail Goods"
        }
    ],
    "sg:phone":"+1 304 302 0555",
    "sg:postcode":"25701",
    "sg:province":"WV",
    "sg:tags":[
        "cabinet"
    ],
    "wof:name":"Merritt Enterprises Inc Cabnt",
    "wof:placetype":"venue"
},
  "geometry": {"coordinates":[-82.346459,38.375049],"type":"Point"}
}