{
  "type": "Feature",
  "properties": {
    "iso:country":"US",
    "sg:address":"700 Hendricks St",
    "sg:city":"Wayne",
    "sg:classifiers":[
        {
            "category":"Government",
            "subcategory":"Office",
            "type":"Public Place"
        }
    ],
    "sg:phone":"+1 304 272 5783",
    "sg:postcode":"25570",
    "sg:province":"WV",
    "wof:name":"Honorable David Ferguson",
    "wof:placetype":"venue"
},
  "geometry": {"coordinates":[-82.441059,38.219668],"type":"Point"}
}