{
  "type": "Feature",
  "properties": {
    "addr:full":"129 E German St Shepherdstown WV 25443",
    "addr:housenumber":"129",
    "addr:postcode":"25443",
    "addr:street":"E German St",
    "iso:country":"US",
    "sg:address":"129 E German St",
    "sg:city":"Shepherdstown",
    "sg:classifiers":[
        {
            "category":"Museum",
            "type":"Entertainment"
        }
    ],
    "sg:phone":"+1 304 876 9245",
    "sg:postcode":"25443",
    "sg:province":"WV",
    "sg:tags":[
        "society",
        "historical"
    ],
    "wof:name":"Fofr",
    "wof:placetype":"venue"
},
  "geometry": {"coordinates":[-77.805663,39.430888],"type":"Point"}
}