{
  "type": "Feature",
  "properties": {
    "addr:full":"1050 Maple Dr Morgantown WV 26505",
    "addr:housenumber":"1050",
    "addr:postcode":"26505",
    "addr:street":"Maple Dr",
    "iso:country":"US",
    "sg:address":"1050 Maple Dr",
    "sg:city":"Morgantown",
    "sg:classifiers":[
        {
            "category":"Building & Trades",
            "subcategory":"Construction",
            "type":"Services"
        }
    ],
    "sg:phone":"+1 304 599 1907",
    "sg:postcode":"26505",
    "sg:province":"WV",
    "sg:tags":[
        "general",
        "contractor"
    ],
    "wof:name":"Culton Construction Inc",
    "wof:placetype":"venue"
},
  "geometry": {"coordinates":[-79.94826,39.656705],"type":"Point"}
}