{
  "type": "Feature",
  "properties": {
    "addr:full":"200 N Court St Lewisburg WV 24901",
    "addr:housenumber":"200",
    "addr:postcode":"24901",
    "addr:street":"N Court St",
    "iso:country":"US",
    "sg:address":"200 N Court St",
    "sg:city":"Lewisburg",
    "sg:classifiers":[
        {
            "category":"Government",
            "subcategory":"Office",
            "type":"Public Place"
        }
    ],
    "sg:phone":"+1 304 647 7500",
    "sg:postcode":"24901",
    "sg:province":"WV",
    "sg:tags":[
        "admin",
        "affairs",
        "state"
    ],
    "wof:name":"Veterans Affairs",
    "wof:placetype":"venue"
},
  "geometry": {"coordinates":[-80.44492700000001,37.803791],"type":"Point"}
}