{
  "type": "Feature",
  "properties": {
    "iso:country":"US",
    "sg:address":"107 Rosemary Ln",
    "sg:city":"Moorefield",
    "sg:classifiers":[
        {
            "category":"Professional",
            "subcategory":"Lawyer & Legal Services",
            "type":"Services"
        }
    ],
    "sg:phone":"+1 304 538 2375",
    "sg:postcode":"26836",
    "sg:province":"WV",
    "sg:tags":[
        "attorney"
    ],
    "wof:name":"Garrett & Garrett",
    "wof:placetype":"venue"
},
  "geometry": {"coordinates":[-78.966168,39.062948],"type":"Point"}
}