{
  "type": "Feature",
  "properties": {
    "iso:country":"US",
    "sg:address":"901 Fairmont Ave",
    "sg:city":"Fairmont",
    "sg:classifiers":[
        {
            "category":"Organizations",
            "subcategory":"Religious Organization",
            "type":"Services"
        }
    ],
    "sg:phone":"+1 304 366 2424",
    "sg:postcode":"26554",
    "sg:province":"WV",
    "sg:tags":[
        "baptist",
        "center",
        "church",
        "child",
        "day",
        "care"
    ],
    "wof:name":"First Bapt Church/Fairmont Cdc",
    "wof:placetype":"venue"
},
  "geometry": {"coordinates":[-80.15258300000001,39.473835],"type":"Point"}
}