{
  "type": "Feature",
  "properties": {
    "iso:country":"US",
    "sg:address":"1283 Tartan Ln",
    "sg:city":"Morgantown",
    "sg:classifiers":[
        {
            "category":"Organizations",
            "subcategory":"Professional Association",
            "type":"Services"
        }
    ],
    "sg:phone":"+1 304 599 8214",
    "sg:postcode":"26505",
    "sg:province":"WV",
    "wof:name":"Professional Womens Coun",
    "wof:placetype":"venue"
},
  "geometry": {"coordinates":[-79.95607800000001,39.662867],"type":"Point"}
}