{
  "type": "Feature",
  "properties": {
    "iso:country":"US",
    "sg:address":"325 High St",
    "sg:city":"Morgantown",
    "sg:classifiers":[
        {
            "category":"Professional",
            "type":"Services"
        }
    ],
    "sg:phone":"+1 304 292 2185",
    "sg:postcode":"26505",
    "sg:province":"WV",
    "sg:tags":[
        "establishment"
    ],
    "wof:name":"Sports Page The Ofc",
    "wof:placetype":"venue"
},
  "geometry": {"coordinates":[-79.955737,39.630012],"type":"Point"}
}