{
  "type": "Feature",
  "properties": {
    "addr:full":"106 Riverview St Fairmont WV 26554",
    "addr:housenumber":"106",
    "addr:postcode":"26554",
    "addr:street":"Riverview St",
    "iso:country":"US",
    "sg:address":"106 Riverview St",
    "sg:city":"Fairmont",
    "sg:classifiers":[
        {
            "category":"Building & Trades",
            "subcategory":"Landscaping Services",
            "type":"Services"
        }
    ],
    "sg:phone":"+1 304 366 6966",
    "sg:postcode":"26554",
    "sg:province":"WV",
    "sg:tags":[
        "landscape",
        "contractor"
    ],
    "wof:name":"Biafore's Landscaping & Nrsy",
    "wof:placetype":"venue"
},
  "geometry": {"coordinates":[-80.166915,39.466067],"type":"Point"}
}