{
  "type": "Feature",
  "properties": {
    "iso:country":"US",
    "sg:address":"2619 Roosevelt Ave",
    "sg:city":"St Albans",
    "sg:classifiers":[
        {
            "category":"Health Services",
            "subcategory":"Nursing And Care Facility",
            "type":"Services"
        }
    ],
    "sg:phone":"+1 304 722 6603",
    "sg:postcode":"25177",
    "sg:province":"WV",
    "sg:tags":[
        "personal",
        "home"
    ],
    "wof:name":"Belle's Residential Board",
    "wof:placetype":"venue"
},
  "geometry": {"coordinates":[-81.79934900000001,38.382589],"type":"Point"}
}