{
  "type": "Feature",
  "properties": {
    "iso:country":"US",
    "sg:address":"512 5th St",
    "sg:city":"New Haven",
    "sg:classifiers":[
        {
            "category":"Restaurant",
            "type":"Food & Drink"
        }
    ],
    "sg:phone":"+1 304 882 2868",
    "sg:postcode":"25265",
    "sg:province":"WV",
    "wof:name":"Hut",
    "wof:placetype":"venue"
},
  "geometry": {"coordinates":[-81.971476,38.986178],"type":"Point"}
}