{
  "type": "Feature",
  "properties": {
    "iso:country":"US",
    "sg:address":"153 Oakwood Ests",
    "sg:city":"Scott Depot",
    "sg:classifiers":[
        {
            "category":"Freight",
            "type":"Transportation"
        }
    ],
    "sg:phone":"+1 304 776 5616",
    "sg:postcode":"25560",
    "sg:province":"WV",
    "sg:tags":[
        "special"
    ],
    "wof:name":"JMJ Mini Storage",
    "wof:placetype":"venue"
},
  "geometry": {"coordinates":[-81.920789,38.45216],"type":"Point"}
}