{
  "type": "Feature",
  "properties": {
    "iso:country":"US",
    "sg:address":"515 Maple Ave",
    "sg:city":"New Martinsville",
    "sg:classifiers":[
        {
            "category":"Personal",
            "subcategory":"Beauty Salon",
            "type":"Services"
        }
    ],
    "sg:phone":"+1 304 455 2911",
    "sg:postcode":"26155",
    "sg:province":"WV",
    "sg:tags":[
        "spa",
        "day"
    ],
    "wof:name":"Jimmy Z Uniquely Yours",
    "wof:placetype":"venue"
},
  "geometry": {"coordinates":[-80.861799,39.644999],"type":"Point"}
}