{
  "type": "Feature",
  "properties": {
    "addr:full":"202 2nd Ave Logan WV 25601",
    "addr:housenumber":"202",
    "addr:postcode":"25601",
    "addr:street":"2Nd Ave",
    "iso:country":"US",
    "sg:address":"202 2nd Ave",
    "sg:city":"Logan",
    "sg:classifiers":[
        {
            "category":"Food & Beverages",
            "subcategory":"Groceries & Convenience Stores",
            "type":"Retail Goods"
        }
    ],
    "sg:phone":"+1 304 752 3352",
    "sg:postcode":"25601",
    "sg:province":"WV",
    "wof:name":"Stop N Go",
    "wof:placetype":"venue"
},
  "geometry": {"coordinates":[-81.99196600000001,37.892468],"type":"Point"}
}