{
  "type": "Feature",
  "properties": {
    "iso:country":"US",
    "sg:address":"2010 Tavern Rd",
    "sg:city":"Martinsburg",
    "sg:classifiers":[
        {
            "category":"Organizations",
            "subcategory":"Religious Organization",
            "type":"Services"
        }
    ],
    "sg:phone":"+1 304 267 8694",
    "sg:postcode":"25401",
    "sg:province":"WV",
    "sg:tags":[
        "church"
    ],
    "wof:name":"Bethel Assembly Of God",
    "wof:placetype":"venue"
},
  "geometry": {"coordinates":[-77.979936,39.478097],"type":"Point"}
}