{
  "type": "Feature",
  "properties": {
    "addr:full":"551 S Main St Moorefield WV 26836",
    "addr:housenumber":"551",
    "addr:postcode":"26836",
    "addr:street":"S Main St",
    "iso:country":"US",
    "sg:address":"551 S Main St",
    "sg:city":"Moorefield",
    "sg:classifiers":[
        {
            "category":"Autos & Motor Vehicles",
            "subcategory":"Auto Supplies",
            "type":"Retail Goods"
        }
    ],
    "sg:phone":"+1 304 538 6277",
    "sg:postcode":"26836",
    "sg:province":"WV",
    "sg:website":"www.advanceautoparts.com",
    "wof:name":"Advance Auto Parts",
    "wof:placetype":"venue"
},
  "geometry": {"coordinates":[-78.97455600000001,39.051725],"type":"Point"}
}