{
  "type": "Feature",
  "properties": {
    "addr:full":"116 N Main St Philippi WV 26416",
    "addr:housenumber":"116",
    "addr:postcode":"26416",
    "addr:street":"N Main St",
    "iso:country":"US",
    "sg:address":"116 N Main St",
    "sg:city":"Philippi",
    "sg:classifiers":[
        {
            "category":"Retail",
            "subcategory":"Auto Repair",
            "type":"Services"
        }
    ],
    "sg:phone":"+1 304 457 3027",
    "sg:postcode":"26416",
    "sg:province":"WV",
    "sg:tags":[
        "recreational",
        "vehicle"
    ],
    "wof:name":"Bill Kelley Racing",
    "wof:placetype":"venue"
},
  "geometry": {"coordinates":[-80.04001,39.152564],"type":"Point"}
}