{
  "type": "Feature",
  "properties": {
    "iso:country":"US",
    "sg:address":"2107 Pike St",
    "sg:city":"Parkersburg",
    "sg:classifiers":[
        {
            "category":"Cinema",
            "subcategory":"Movie Rental",
            "type":"Entertainment"
        }
    ],
    "sg:phone":"+1 304 485 5888",
    "sg:postcode":"26101",
    "sg:province":"WV",
    "sg:tags":[
        "video",
        "tape"
    ],
    "wof:name":"Daves Video",
    "wof:placetype":"venue"
},
  "geometry": {"coordinates":[-81.54182,39.234082],"type":"Point"}
}