{
  "type": "Feature",
  "properties": {
    "addr:full":"330 Keyser Ave Petersburg WV 26847",
    "addr:housenumber":"330",
    "addr:postcode":"26847",
    "addr:street":"Keyser Ave",
    "iso:country":"US",
    "sg:address":"330 Keyser Ave",
    "sg:city":"Petersburg",
    "sg:classifiers":[
        {
            "category":"Restaurant",
            "type":"Food & Drink"
        }
    ],
    "sg:menulink":"http://www.allmenus.com/wv/milroy/67921-foxs-pizza-den/menu/",
    "sg:phone":"+1 304 257 4342",
    "sg:postcode":"26847",
    "sg:province":"WV",
    "sg:tags":[
        "american",
        "pizza"
    ],
    "wof:name":"Fox's Pizza Den",
    "wof:placetype":"venue"
},
  "geometry": {"coordinates":[-79.128185,39.000377],"type":"Point"}
}