{
  "type": "Feature",
  "properties": {
    "addr:full":"150 Oakwood Ests Scott Depot WV 25560",
    "addr:housenumber":"150",
    "addr:postcode":"25560",
    "addr:street":"Oakwood Ests",
    "iso:country":"US",
    "sg:address":"150 Oakwood Ests",
    "sg:city":"Scott Depot",
    "sg:classifiers":[
        {
            "category":"Freight",
            "type":"Transportation"
        }
    ],
    "sg:phone":"+1 304 757 7835",
    "sg:postcode":"25560",
    "sg:province":"WV",
    "sg:tags":[
        "local",
        "hauling"
    ],
    "wof:name":"Mountain State Star Route Inc",
    "wof:placetype":"venue"
},
  "geometry": {"coordinates":[-81.922505,38.449669],"type":"Point"}
}