{
  "type": "Feature",
  "properties": {
    "addr:full":"505 S Eisenhower Dr Beckley WV 25801",
    "addr:housenumber":"505",
    "addr:postcode":"25801",
    "addr:street":"S Eisenhower Dr",
    "iso:country":"US",
    "sg:address":"505 S Eisenhower Dr",
    "sg:city":"Beckley",
    "sg:classifiers":[
        {
            "category":"Travel",
            "subcategory":"Hotels & Motels",
            "type":"Entertainment"
        }
    ],
    "sg:phone":"+1 304 253 3355",
    "sg:postcode":"25801",
    "sg:province":"WV",
    "sg:tags":[
        "operation",
        "commercial",
        "state",
        "bank"
    ],
    "wof:name":"Green Bank Motel",
    "wof:placetype":"venue"
},
  "geometry": {"coordinates":[-81.16277599999999,37.775976],"type":"Point"}
}