{
  "type": "Feature",
  "properties": {
    "addr:full":"640 4th Ave Huntington WV 25701",
    "addr:housenumber":"640",
    "addr:postcode":"25701",
    "addr:street":"4Th Ave",
    "iso:country":"US",
    "sg:address":"640 4th Ave",
    "sg:city":"Huntington",
    "sg:classifiers":[
        {
            "category":"Government",
            "subcategory":"Office",
            "type":"Public Place"
        }
    ],
    "sg:phone":"+1 304 529 5561",
    "sg:postcode":"25701",
    "sg:province":"WV",
    "sg:tags":[
        "federal",
        "human"
    ],
    "wof:name":"US Railroad Retirement Board",
    "wof:placetype":"venue"
},
  "geometry": {"coordinates":[-82.447864,38.420131],"type":"Point"}
}