{
  "type": "Feature",
  "properties": {
    "addr:full":"95 11th St Elkins WV 26241",
    "addr:housenumber":"95",
    "addr:postcode":"26241",
    "addr:street":"11Th St",
    "iso:country":"US",
    "sg:address":"95 11th St",
    "sg:city":"Elkins",
    "sg:classifiers":[
        {
            "category":"Retail",
            "subcategory":"Repair Shop",
            "type":"Services"
        }
    ],
    "sg:phone":"+1 304 637 7102",
    "sg:postcode":"26241",
    "sg:province":"WV",
    "wof:name":"Mountain Electronics",
    "wof:placetype":"venue"
},
  "geometry": {"coordinates":[-79.84879599999999,38.919112],"type":"Point"}
}