{
  "type": "Feature",
  "properties": {
    "addr:full":"1234 Payne Ave Dunbar WV 25064",
    "addr:housenumber":"1234",
    "addr:postcode":"25064",
    "addr:street":"Payne Ave",
    "iso:country":"US",
    "sg:address":"1234 Payne Ave",
    "sg:city":"Dunbar",
    "sg:classifiers":[
        {
            "category":"Organizations",
            "subcategory":"Religious Organization",
            "type":"Services"
        }
    ],
    "sg:phone":"+1 304 768 3656",
    "sg:postcode":"25064",
    "sg:province":"WV",
    "sg:website":"www.faithfulfollowers.org",
    "wof:name":"Dunbar First Church Of God",
    "wof:placetype":"venue"
},
  "geometry": {"coordinates":[-81.739436,38.36223],"type":"Point"}
}