{
  "type": "Feature",
  "properties": {
    "addr:full":"103 N Main St Franklin WV 26807",
    "addr:housenumber":"103",
    "addr:postcode":"26807",
    "addr:street":"N Main St",
    "iso:country":"US",
    "sg:address":"103 N Main St",
    "sg:city":"Franklin",
    "sg:classifiers":[
        {
            "category":"Professional",
            "subcategory":"Lawyer & Legal Services",
            "type":"Services"
        }
    ],
    "sg:phone":"+1 304 358 2208",
    "sg:postcode":"26807",
    "sg:province":"WV",
    "sg:tags":[
        "attorney"
    ],
    "wof:name":"Jerry D Moore",
    "wof:placetype":"venue"
},
  "geometry": {"coordinates":[-79.331157,38.642277],"type":"Point"}
}