{
  "type": "Feature",
  "properties": {
    "iso:country":"US",
    "sg:address":"501 8th St",
    "sg:city":"Huntington",
    "sg:classifiers":[
        {
            "category":"Manufacturing",
            "subcategory":"Petroleum Products",
            "type":"Manufacturing & Wholesale Goods"
        }
    ],
    "sg:phone":"+1 304 523 6400",
    "sg:postcode":"25701",
    "sg:province":"WV",
    "wof:name":"Petroleum Products Inc",
    "wof:placetype":"venue"
},
  "geometry": {"coordinates":[-82.44506199999999,38.418393],"type":"Point"}
}