{
  "type": "Feature",
  "properties": {
    "addr:full":"246 7th Ave South Charleston WV 25303",
    "addr:housenumber":"246",
    "addr:postcode":"25303",
    "addr:street":"7Th Ave",
    "iso:country":"US",
    "sg:address":"246 7th Ave",
    "sg:city":"South Charleston",
    "sg:classifiers":[
        {
            "category":"Shopping",
            "subcategory":"Gifts & Souvenirs",
            "type":"Retail Goods"
        }
    ],
    "sg:phone":"+1 304 746 8844",
    "sg:postcode":"25303",
    "sg:province":"WV",
    "sg:tags":[
        "basket",
        "parcel"
    ],
    "wof:name":"Sugarbaskets",
    "wof:placetype":"venue"
},
  "geometry": {"coordinates":[-81.69656000000001,38.368487],"type":"Point"}
}