{
  "type": "Feature",
  "properties": {
    "iso:country":"US",
    "sg:address":"943 Ritter Dr",
    "sg:city":"Beaver",
    "sg:classifiers":[
        {
            "category":"Autos & Motor Vehicles",
            "subcategory":"Fuel & Gas Station",
            "type":"Retail Goods"
        }
    ],
    "sg:phone":"+1 304 253 1818",
    "sg:postcode":"25813",
    "sg:province":"WV",
    "sg:tags":[
        "oil"
    ],
    "wof:name":"Link's Pennzoil",
    "wof:placetype":"venue"
},
  "geometry": {"coordinates":[-81.130577,37.748193],"type":"Point"}
}