{
  "type": "Feature",
  "properties": {
    "iso:country":"US",
    "sg:address":"5703 Maccorkle Ave SE",
    "sg:city":"Charleston",
    "sg:classifiers":[
        {
            "category":"Restaurant",
            "type":"Food & Drink"
        }
    ],
    "sg:phone":"+1 304 925 4590",
    "sg:postcode":"25304",
    "sg:province":"WV",
    "wof:name":"LA Carreta Mexican Restaurant",
    "wof:placetype":"venue"
},
  "geometry": {"coordinates":[-81.566942,38.312835],"type":"Point"}
}