{
  "type": "Feature",
  "properties": {
    "iso:country":"US",
    "sg:address":"271 Webster Ave",
    "sg:city":"Morgantown",
    "sg:classifiers":[
        {
            "category":"Real Estate",
            "subcategory":"Real Estate Agent",
            "type":"Services"
        }
    ],
    "sg:phone":"+1 304 296 1118",
    "sg:postcode":"26501",
    "sg:province":"WV",
    "wof:name":"Palmer Properties",
    "wof:placetype":"venue"
},
  "geometry": {"coordinates":[-79.95121,39.617481],"type":"Point"}
}