{
  "type": "Feature",
  "properties": {
    "iso:country":"US",
    "sg:address":"1 Madison St",
    "sg:city":"Buckhannon",
    "sg:classifiers":[
        {
            "category":"Organizations",
            "subcategory":"Non-profit Organization",
            "type":"Services"
        }
    ],
    "sg:phone":"+1 304 853 2432",
    "sg:postcode":"26201",
    "sg:province":"WV",
    "sg:tags":[
        "alternative",
        "abortion"
    ],
    "wof:name":"Linda Moore",
    "wof:placetype":"venue"
},
  "geometry": {"coordinates":[-80.229345,38.991777],"type":"Point"}
}