{
  "type": "Feature",
  "properties": {
    "iso:country":"US",
    "sg:address":"1337 Railroad St",
    "sg:city":"Grafton",
    "sg:classifiers":[
        {
            "category":"Building & Trades",
            "subcategory":"Cleaning & Sanitation",
            "type":"Services"
        }
    ],
    "sg:phone":"+1 304 265 3878",
    "sg:postcode":"26354",
    "sg:province":"WV",
    "sg:tags":[
        "janitorial"
    ],
    "wof:name":"Carol Evanovich",
    "wof:placetype":"venue"
},
  "geometry": {"coordinates":[-80.038327,39.354311],"type":"Point"}
}