{
  "type": "Feature",
  "properties": {
    "iso:country":"US",
    "sg:address":"1400 Eoff St",
    "sg:city":"Wheeling",
    "sg:classifiers":[
        {
            "category":"Retail",
            "subcategory":"Funeral Services",
            "type":"Services"
        }
    ],
    "sg:phone":"+1 304 232 0330",
    "sg:postcode":"26003",
    "sg:province":"WV",
    "sg:tags":[
        "director"
    ],
    "sg:website":"http://www.altmeyer.com",
    "wof:name":"Altmeyer Funeral Homes-Wheeling",
    "wof:placetype":"venue"
},
  "geometry": {"coordinates":[-80.719902,40.065899],"type":"Point"}
}