{
  "type": "Feature",
  "properties": {
    "addr:full":"543 5th St Parkersburg WV 26101",
    "addr:housenumber":"543",
    "addr:postcode":"26101",
    "addr:street":"5Th St",
    "iso:country":"US",
    "sg:address":"543 5th St",
    "sg:city":"Parkersburg",
    "sg:classifiers":[
        {
            "category":"Professional",
            "subcategory":"Lawyer & Legal Services",
            "type":"Services"
        }
    ],
    "sg:phone":"+1 304 485 3851",
    "sg:postcode":"26101",
    "sg:province":"WV",
    "sg:tags":[
        "attorney"
    ],
    "wof:name":"Golden & Amos",
    "wof:placetype":"venue"
},
  "geometry": {"coordinates":[-81.55874799999999,39.263877],"type":"Point"}
}