{
  "type": "Feature",
  "properties": {
    "addr:full":"810 Ewart Ave Beckley WV 25801",
    "addr:housenumber":"810",
    "addr:postcode":"25801",
    "addr:street":"Ewart Ave",
    "iso:country":"US",
    "sg:address":"810 Ewart Ave",
    "sg:city":"Beckley",
    "sg:classifiers":[
        {
            "category":"Organizations",
            "subcategory":"Religious Organization",
            "type":"Services"
        }
    ],
    "sg:phone":"+1 304 252 9983",
    "sg:postcode":"25801",
    "sg:province":"WV",
    "sg:tags":[
        "church"
    ],
    "wof:name":"Sprague Freewill Baptist Chr",
    "wof:placetype":"venue"
},
  "geometry": {"coordinates":[-81.193029,37.787039],"type":"Point"}
}