{
  "type": "Feature",
  "properties": {
    "iso:country":"US",
    "sg:address":"193 29th St",
    "sg:city":"Wheeling",
    "sg:classifiers":[
        {
            "category":"Organizations",
            "subcategory":"Professional Association",
            "type":"Services"
        }
    ],
    "sg:phone":"+1 304 232 0711",
    "sg:postcode":"26003",
    "sg:province":"WV",
    "wof:name":"American Red Cross",
    "wof:placetype":"venue"
},
  "geometry": {"coordinates":[-80.718739,40.051192],"type":"Point"}
}