{
  "type": "Feature",
  "properties": {
    "iso:country":"US",
    "sg:address":"103 Turnpike Rd",
    "sg:city":"Summersville",
    "sg:classifiers":[
        {
            "category":"Retail",
            "subcategory":"Auto Repair",
            "type":"Services"
        }
    ],
    "sg:phone":"+1 304 872 2155",
    "sg:postcode":"26651",
    "sg:province":"WV",
    "sg:tags":[
        "muffler",
        "exhaust",
        "system"
    ],
    "wof:name":"Paxton's Muffler & Brake Shop",
    "wof:placetype":"venue"
},
  "geometry": {"coordinates":[-80.856768,38.282568],"type":"Point"}
}