{
  "type": "Feature",
  "properties": {
    "iso:country":"US",
    "sg:address":"418 12th Ave",
    "sg:city":"Huntington",
    "sg:classifiers":[
        {
            "category":"Health Services",
            "subcategory":"Doctor",
            "type":"Services"
        }
    ],
    "sg:phone":"+1 304 522 9357",
    "sg:postcode":"25701",
    "sg:province":"WV",
    "sg:tags":[
        "medical"
    ],
    "wof:name":"Maurice A Mufson MD",
    "wof:placetype":"venue"
},
  "geometry": {"coordinates":[-82.44785400000001,38.408507],"type":"Point"}
}