{
  "type": "Feature",
  "properties": {
    "iso:country":"US",
    "sg:address":"1555 Ritter Dr",
    "sg:city":"Daniels",
    "sg:classifiers":[
        {
            "category":"Building & Trades",
            "subcategory":"Construction",
            "type":"Services"
        }
    ],
    "sg:phone":"+1 304 255 1870",
    "sg:postcode":"25832",
    "sg:province":"WV",
    "sg:tags":[
        "home",
        "improvement"
    ],
    "wof:name":"Sun Builders",
    "wof:placetype":"venue"
},
  "geometry": {"coordinates":[-81.12106900000001,37.742291],"type":"Point"}
}