{
  "type": "Feature",
  "properties": {
    "iso:country":"US",
    "sg:address":"5315 Koontz Dr",
    "sg:city":"Charleston",
    "sg:classifiers":[
        {
            "category":"Organizations",
            "subcategory":"Religious Organization",
            "type":"Services"
        }
    ],
    "sg:phone":"+1 304 776 5694",
    "sg:postcode":"25313",
    "sg:province":"WV",
    "wof:name":"Faith Presbyterian Church",
    "wof:placetype":"venue"
},
  "geometry": {"coordinates":[-81.77672,38.43393],"type":"Point"}
}