{
  "type": "Feature",
  "properties": {
    "iso:country":"US",
    "sg:address":"705 Pike St",
    "sg:city":"Parkersburg",
    "sg:classifiers":[
        {
            "category":"Building & Trades",
            "subcategory":"Cleaning & Sanitation",
            "type":"Services"
        }
    ],
    "sg:phone":"+1 304 424 6511",
    "sg:postcode":"26101",
    "sg:province":"WV",
    "sg:tags":[
        "janitor"
    ],
    "wof:name":"Patterson Cleaning & Supl Corp",
    "wof:placetype":"venue"
},
  "geometry": {"coordinates":[-81.545064,39.250896],"type":"Point"}
}