{
  "type": "Feature",
  "properties": {
    "iso:country":"US",
    "sg:address":"702 Avery St",
    "sg:city":"Fairmont",
    "sg:classifiers":[
        {
            "category":"Manufacturing",
            "subcategory":"Paper Products",
            "type":"Manufacturing & Wholesale Goods"
        }
    ],
    "sg:phone":"+1 304 368 0900",
    "sg:postcode":"26554",
    "sg:province":"WV",
    "sg:tags":[
        "pulp"
    ],
    "wof:name":"Beltech Recycling",
    "wof:placetype":"venue"
},
  "geometry": {"coordinates":[-80.170619,39.463911],"type":"Point"}
}