{
  "type": "Feature",
  "properties": {
    "iso:country":"US",
    "sg:address":"3100 Dudley Ave",
    "sg:city":"Parkersburg",
    "sg:classifiers":[
        {
            "category":"Organizations",
            "subcategory":"Labor Organization",
            "type":"Services"
        }
    ],
    "sg:phone":"+1 304 424 6443",
    "sg:postcode":"26104",
    "sg:province":"WV",
    "wof:name":"Parkersburg-Marietta Building",
    "wof:placetype":"venue"
},
  "geometry": {"coordinates":[-81.53527200000001,39.28468],"type":"Point"}
}