{
  "type": "Feature",
  "properties": {
    "iso:country":"US",
    "sg:address":"24 Commercial Ave",
    "sg:city":"Richwood",
    "sg:classifiers":[
        {
            "category":"Manufacturing",
            "subcategory":"Furniture",
            "type":"Manufacturing & Wholesale Goods"
        },
        {
            "category":"Wholesale",
            "subcategory":"Furniture",
            "type":"Manufacturing & Wholesale Goods"
        }
    ],
    "sg:phone":"+1 304 846 6020",
    "sg:postcode":"26261",
    "sg:province":"WV",
    "sg:tags":[
        "mfg"
    ],
    "wof:name":"Cherry Valley Furniture Inc",
    "wof:placetype":"venue"
},
  "geometry": {"coordinates":[-80.534622,38.222212],"type":"Point"}
}