{
  "type": "Feature",
  "properties": {
    "addr:full":"1701 Buckhannon Pike Clarksburg WV 26301",
    "addr:housenumber":"1701",
    "addr:postcode":"26301",
    "addr:street":"Buckhannon Pike",
    "iso:country":"US",
    "sg:address":"1701 Buckhannon Pike",
    "sg:city":"Clarksburg",
    "sg:classifiers":[
        {
            "category":"Restaurant",
            "type":"Food & Drink"
        }
    ],
    "sg:menulink":"http://www.allmenus.com/wv/southern/139719-sicilias-pizzeria/menu/",
    "sg:phone":"+1 304 622 6307",
    "sg:postcode":"26301",
    "sg:province":"WV",
    "sg:tags":[
        "wrap",
        "american",
        "sandwich",
        "pizza"
    ],
    "wof:name":"Sicilia's Pizzeria",
    "wof:placetype":"venue"
},
  "geometry": {"coordinates":[-80.31911599999999,39.254531],"type":"Point"}
}