{
  "type": "Feature",
  "properties": {
    "addr:full":"1500 Chapline St Wheeling WV 26003",
    "addr:housenumber":"1500",
    "addr:postcode":"26003",
    "addr:street":"Chapline St",
    "iso:country":"US",
    "sg:address":"1500 Chapline St",
    "sg:city":"Wheeling",
    "sg:classifiers":[
        {
            "category":"Government",
            "subcategory":"Office",
            "type":"Public Place"
        }
    ],
    "sg:phone":"+1 304 234 3626",
    "sg:postcode":"26003",
    "sg:province":"WV",
    "sg:tags":[
        "county",
        "taxation"
    ],
    "wof:name":"Ohio County Assessor",
    "wof:placetype":"venue"
},
  "geometry": {"coordinates":[-80.72080699999999,40.06404],"type":"Point"}
}