{
  "type": "Feature",
  "properties": {
    "iso:country":"US",
    "sg:address":"426 Van Gilder St",
    "sg:city":"Morgantown",
    "sg:classifiers":[
        {
            "category":"Social Services",
            "type":"Services"
        }
    ],
    "sg:phone":"+1 304 598 1088",
    "sg:postcode":"26505",
    "sg:province":"WV",
    "wof:name":"L June Morgn Adult Day Care CT",
    "wof:placetype":"venue"
},
  "geometry": {"coordinates":[-79.94640699999999,39.642201],"type":"Point"}
}