{
  "type": "Feature",
  "properties": {
    "addr:full":"486 Hampton Rd Fairmont WV 26554",
    "addr:housenumber":"486",
    "addr:postcode":"26554",
    "addr:street":"Hampton Rd",
    "iso:country":"US",
    "sg:address":"486 Hampton Rd",
    "sg:city":"Fairmont",
    "sg:classifiers":[
        {
            "category":"Wholesale",
            "subcategory":"Electrical",
            "type":"Manufacturing & Wholesale Goods"
        }
    ],
    "sg:phone":"+1 304 366 4088",
    "sg:postcode":"26554",
    "sg:province":"WV",
    "sg:tags":[
        "instrument",
        "electronic"
    ],
    "sg:website":"www.temp-inc.com",
    "wof:name":"Temp Inc",
    "wof:placetype":"venue"
},
  "geometry": {"coordinates":[-80.144925,39.498209],"type":"Point"}
}