{
  "type": "Feature",
  "properties": {
    "iso:country":"US",
    "sg:address":"122 Capitol St",
    "sg:city":"Charleston",
    "sg:classifiers":[
        {
            "category":"Professional",
            "subcategory":"Management & Consulting",
            "type":"Services"
        }
    ],
    "sg:phone":"+1 304 345 1161",
    "sg:postcode":"25301",
    "sg:province":"WV",
    "sg:tags":[
        "counselor",
        "public",
        "relations"
    ],
    "wof:name":"TSG Consulting",
    "wof:placetype":"venue"
},
  "geometry": {"coordinates":[-81.635595,38.349445],"type":"Point"}
}