{
  "type": "Feature",
  "properties": {
    "iso:country":"US",
    "sg:address":"1005 Village Dr",
    "sg:city":"Morgantown",
    "sg:classifiers":[
        {
            "category":"Professional",
            "subcategory":"Computer Services",
            "type":"Services"
        }
    ],
    "sg:phone":"+1 304 599 0586",
    "sg:postcode":"26505",
    "sg:province":"WV",
    "sg:tags":[
        "programing",
        "custom"
    ],
    "wof:name":"Iag LLC",
    "wof:placetype":"venue"
},
  "geometry": {"coordinates":[-79.95130399999999,39.653671],"type":"Point"}
}