{
  "type": "Feature",
  "properties": {
    "iso:country":"US",
    "sg:address":"400 Mayfield Rd",
    "sg:city":"Morgantown",
    "sg:classifiers":[
        {
            "category":"Retail",
            "subcategory":"Animal Services",
            "type":"Services"
        }
    ],
    "sg:phone":"+1 304 296 9400",
    "sg:postcode":"26508",
    "sg:province":"WV",
    "sg:tags":[
        "pet",
        "boarding",
        "sitting"
    ],
    "wof:name":"Mountain Laurel Kennels",
    "wof:placetype":"venue"
},
  "geometry": {"coordinates":[-79.881716,39.613487],"type":"Point"}
}