{
  "type": "Feature",
  "properties": {
    "iso:country":"US",
    "sg:address":"3313 Kanawha Blvd E",
    "sg:city":"Charleston",
    "sg:classifiers":[
        {
            "category":"Travel",
            "subcategory":"Hotels & Motels",
            "type":"Entertainment"
        }
    ],
    "sg:phone":"+1 304 925 2592",
    "sg:postcode":"25306",
    "sg:province":"WV",
    "sg:tags":[
        "real",
        "operation",
        "property",
        "lessor"
    ],
    "wof:name":"Budget Host Inn",
    "wof:placetype":"venue"
},
  "geometry": {"coordinates":[-81.56026,38.314944],"type":"Point"}
}