{
  "type": "Feature",
  "properties": {
    "iso:country":"US",
    "sg:address":"1402 Sweetbrier Rd",
    "sg:city":"Charleston",
    "sg:classifiers":[
        {
            "category":"Real Estate",
            "subcategory":"Real Estate Agent",
            "type":"Services"
        }
    ],
    "sg:phone":"+1 304 346 4826",
    "sg:postcode":"25314",
    "sg:province":"WV",
    "wof:name":"Rl Bliss & Assoc Inc",
    "wof:placetype":"venue"
},
  "geometry": {"coordinates":[-81.642529,38.323197],"type":"Point"}
}