{
  "type": "Feature",
  "properties": {
    "addr:full":"71 Main St St Albans WV 25177",
    "addr:housenumber":"71",
    "addr:postcode":"25177",
    "addr:street":"Main St",
    "iso:country":"US",
    "sg:address":"71 Main St",
    "sg:city":"St Albans",
    "sg:classifiers":[
        {
            "category":"Recreation",
            "type":"Entertainment"
        }
    ],
    "sg:phone":"+1 304 722 9222",
    "sg:postcode":"25177",
    "sg:province":"WV",
    "sg:tags":[
        "instruction",
        "gymnastic"
    ],
    "wof:name":"Mountain State Cheer & Tumble",
    "wof:placetype":"venue"
},
  "geometry": {"coordinates":[-81.838204,38.385502],"type":"Point"}
}