{
  "type": "Feature",
  "properties": {
    "addr:full":"3394 Irish Ridge Rd Tunnelton WV 26444",
    "addr:housenumber":"3394",
    "addr:postcode":"26444",
    "addr:street":"Irish Ridge Rd",
    "iso:country":"US",
    "sg:address":"3394 Irish Ridge Rd",
    "sg:city":"Tunnelton",
    "sg:classifiers":[
        {
            "category":"Building & Trades",
            "subcategory":"Landscaping Services",
            "type":"Services"
        }
    ],
    "sg:phone":"+1 304 216 1925",
    "sg:postcode":"26444",
    "sg:province":"WV",
    "sg:tags":[
        "tree"
    ],
    "wof:name":"Bills Tree Service",
    "wof:placetype":"venue"
},
  "geometry": {"coordinates":[-79.76785,39.445702],"type":"Point"}
}