{
  "type": "Feature",
  "properties": {
    "addr:full":"500 6th St Moundsville WV 26041",
    "addr:housenumber":"500",
    "addr:postcode":"26041",
    "addr:street":"6Th St",
    "iso:country":"US",
    "sg:address":"500 6th St",
    "sg:city":"Moundsville",
    "sg:classifiers":[
        {
            "category":"Personal",
            "type":"Services"
        },
        {
            "category":"Personal",
            "subcategory":"Beauty Salon",
            "type":"Services"
        }
    ],
    "sg:phone":"+1 304 845 3720",
    "sg:postcode":"26041",
    "sg:province":"WV",
    "sg:tags":[
        "shop"
    ],
    "wof:name":"Our Place For Family Hair Care",
    "wof:placetype":"venue"
},
  "geometry": {"coordinates":[-80.747185,39.919329],"type":"Point"}
}