{
  "type": "Feature",
  "properties": {
    "iso:country":"US",
    "sg:address":"2149 Greenbrier St",
    "sg:city":"Charleston",
    "sg:classifiers":[
        {
            "category":"Health Services",
            "subcategory":"Nursing And Care Facility",
            "type":"Services"
        }
    ],
    "sg:phone":"+1 304 344 4268",
    "sg:postcode":"25311",
    "sg:province":"WV",
    "sg:tags":[
        "home",
        "skilled",
        "convalescent"
    ],
    "wof:name":"Meadowbrook Acres Nursing Ctr",
    "wof:placetype":"venue"
},
  "geometry": {"coordinates":[-81.553072,38.397228],"type":"Point"}
}