{
  "type": "Feature",
  "properties": {
    "iso:country":"US",
    "sg:address":"23 Mountainview Rd",
    "sg:city":"Morgantown",
    "sg:classifiers":[
        {
            "category":"Retail",
            "subcategory":"Repair Shop",
            "type":"Services"
        }
    ],
    "sg:phone":"+1 304 296 6064",
    "sg:postcode":"26508",
    "sg:province":"WV",
    "sg:tags":[
        "armature",
        "rewinding",
        "mfg"
    ],
    "wof:name":"Halls Electric Motor Service",
    "wof:placetype":"venue"
},
  "geometry": {"coordinates":[-79.875896,39.545261],"type":"Point"}
}