{
  "type": "Feature",
  "properties": {
    "addr:full":"1621 Garfield Ave Parkersburg WV 26101",
    "addr:housenumber":"1621",
    "addr:postcode":"26101",
    "addr:street":"Garfield Ave",
    "iso:country":"US",
    "sg:address":"1621 Garfield Ave",
    "sg:city":"Parkersburg",
    "sg:classifiers":[
        {
            "category":"Home & Garden",
            "subcategory":"Carpets & Floor Coverings",
            "type":"Retail Goods"
        }
    ],
    "sg:phone":"+1 304 485 7847",
    "sg:postcode":"26101",
    "sg:province":"WV",
    "sg:tags":[
        "dealer",
        "rug"
    ],
    "wof:name":"3 B Carpet Co",
    "wof:placetype":"venue"
},
  "geometry": {"coordinates":[-81.555678,39.276635],"type":"Point"}
}