{
  "type": "Feature",
  "properties": {
    "iso:country":"US",
    "sg:address":"3775 Main St",
    "sg:city":"Weirton",
    "sg:classifiers":[
        {
            "category":"Autos & Motor Vehicles",
            "subcategory":"Fuel & Gas Station",
            "type":"Retail Goods"
        }
    ],
    "sg:phone":"+1 304 797 1560",
    "sg:postcode":"26062",
    "sg:province":"WV",
    "sg:tags":[
        "oil"
    ],
    "wof:name":"Weirton Main",
    "wof:placetype":"venue"
},
  "geometry": {"coordinates":[-80.591826,40.396904],"type":"Point"}
}