{
  "type": "Feature",
  "properties": {
    "iso:country":"US",
    "sg:address":"16 Elmcrest Dr",
    "sg:city":"Wheeling",
    "sg:classifiers":[
        {
            "category":"Professional",
            "subcategory":"Accounting & Tax Preparation",
            "type":"Services"
        }
    ],
    "sg:phone":"+1 304 242 7560",
    "sg:postcode":"26003",
    "sg:province":"WV",
    "sg:tags":[
        "return",
        "filing"
    ],
    "wof:name":"H & R Block Tax Svc",
    "wof:placetype":"venue"
},
  "geometry": {"coordinates":[-80.66354699999999,40.031897],"type":"Point"}
}