{
  "type": "Feature",
  "properties": {
    "addr:full":"3526 West St Weirton WV 26062",
    "addr:housenumber":"3526",
    "addr:postcode":"26062",
    "addr:street":"West St",
    "iso:country":"US",
    "sg:address":"3526 West St",
    "sg:city":"Weirton",
    "sg:classifiers":[
        {
            "category":"Organizations",
            "subcategory":"Professional Association",
            "type":"Services"
        }
    ],
    "sg:phone":"+1 304 748 8480",
    "sg:postcode":"26062",
    "sg:province":"WV",
    "wof:name":"Ahepa Temple",
    "wof:placetype":"venue"
},
  "geometry": {"coordinates":[-80.591465,40.400036],"type":"Point"}
}