{
  "type": "Feature",
  "properties": {
    "addr:full":"2107 Pike St Parkersburg WV 26101",
    "addr:housenumber":"2107",
    "addr:postcode":"26101",
    "addr:street":"Pike St",
    "iso:country":"US",
    "sg:address":"2107 Pike St",
    "sg:city":"Parkersburg",
    "sg:classifiers":[
        {
            "category":"Shopping",
            "subcategory":"Pharmacy",
            "type":"Retail Goods"
        }
    ],
    "sg:phone":"+1 304 485 5517",
    "sg:postcode":"26101",
    "sg:province":"WV",
    "wof:name":"Rite Aid Pharmacy",
    "wof:placetype":"venue"
},
  "geometry": {"coordinates":[-81.54182,39.234082],"type":"Point"}
}