{
  "type": "Feature",
  "properties": {
    "iso:country":"US",
    "sg:address":"3700 Staunton Ave SE",
    "sg:city":"Charleston",
    "sg:classifiers":[
        {
            "category":"Professional",
            "subcategory":"Business Services",
            "type":"Services"
        }
    ],
    "sg:phone":"+1 304 925 2456",
    "sg:postcode":"25304",
    "sg:province":"WV",
    "wof:name":"Marc A Kramer",
    "wof:placetype":"venue"
},
  "geometry": {"coordinates":[-81.592985,38.329409],"type":"Point"}
}