{
  "type": "Feature",
  "properties": {
    "addr:full":"8525 Upper Mud River Rd Branchland WV 25506",
    "addr:housenumber":"8525",
    "addr:postcode":"25506",
    "addr:street":"Upper Mud River Rd",
    "iso:country":"US",
    "sg:address":"8525 Upper Mud River Rd",
    "sg:city":"Branchland",
    "sg:classifiers":[
        {
            "category":"Food & Beverages",
            "subcategory":"Groceries & Convenience Stores",
            "type":"Retail Goods"
        }
    ],
    "sg:phone":"+1 304 524 2781",
    "sg:postcode":"25506",
    "sg:province":"WV",
    "wof:name":"Miller Virginia",
    "wof:placetype":"venue"
},
  "geometry": {"coordinates":[-82.04312,38.137999],"type":"Point"}
}