{
  "type": "Feature",
  "properties": {
    "addr:full":"120 Melrose Dr Glasgow WV 25086",
    "addr:housenumber":"120",
    "addr:postcode":"25086",
    "addr:street":"Melrose Dr",
    "iso:country":"US",
    "sg:address":"120 Melrose Dr",
    "sg:city":"Glasgow",
    "sg:classifiers":[
        {
            "category":"Health Services",
            "subcategory":"Nursing And Care Facility",
            "type":"Services"
        }
    ],
    "sg:phone":"+1 304 595 1155",
    "sg:postcode":"25086",
    "sg:province":"WV",
    "sg:tags":[
        "home",
        "convalescent"
    ],
    "sg:website":"www.beverlycares.com",
    "wof:name":"Beverly Healthcare",
    "wof:placetype":"venue"
},
  "geometry": {"coordinates":[-81.419201,38.211858],"type":"Point"}
}