{
  "type": "Feature",
  "properties": {
    "iso:country":"US",
    "sg:address":"71 Edmond Road Unit 5",
    "sg:city":"Kearneysville",
    "sg:classifiers":[
        {
            "category":"Professional",
            "subcategory":"Computer Services",
            "type":"Services"
        }
    ],
    "sg:phone":"+1 304 885 4193",
    "sg:postcode":"25430",
    "sg:province":"WV",
    "sg:website":"http://www.enterpriseinaflash.com",
    "wof:name":"Plethora Technology",
    "wof:placetype":"venue"
},
  "geometry": {"coordinates":[-77.886852,39.364285],"type":"Point"}
}