{
  "type": "Feature",
  "properties": {
    "addr:full":"124 Greenberry Dr Elkview WV 25071",
    "addr:housenumber":"124",
    "addr:postcode":"25071",
    "addr:street":"Greenberry Dr",
    "iso:country":"US",
    "sg:address":"124 Greenberry Dr",
    "sg:city":"Elkview",
    "sg:classifiers":[
        {
            "category":"Building & Trades",
            "subcategory":"Construction",
            "type":"Services"
        }
    ],
    "sg:phone":"+1 304 965 0597",
    "sg:postcode":"25071",
    "sg:province":"WV",
    "sg:tags":[
        "general",
        "contractor"
    ],
    "wof:name":"D L Mc Cune Contracting",
    "wof:placetype":"venue"
},
  "geometry": {"coordinates":[-81.50294700000001,38.402779],"type":"Point"}
}