{
  "type": "Feature",
  "properties": {
    "iso:country":"US",
    "sg:address":"106 Tolley Dr",
    "sg:city":"Bridgeport",
    "sg:classifiers":[
        {
            "category":"Health Services",
            "subcategory":"Doctor",
            "type":"Services"
        }
    ],
    "sg:phone":"+1 304 842 1995",
    "sg:postcode":"26330",
    "sg:province":"WV",
    "sg:tags":[
        "dentist"
    ],
    "wof:name":"Affordable Dentures",
    "wof:placetype":"venue"
},
  "geometry": {"coordinates":[-80.280676,39.281283],"type":"Point"}
}