{
  "type": "Feature",
  "properties": {
    "addr:full":"245 Washington Ave Huntington WV 25701",
    "addr:housenumber":"245",
    "addr:postcode":"25701",
    "addr:street":"Washington Ave",
    "iso:country":"US",
    "sg:address":"245 Washington Ave",
    "sg:city":"Huntington",
    "sg:classifiers":[
        {
            "category":"Autos & Motor Vehicles",
            "subcategory":"Automobile Sales",
            "type":"Retail Goods"
        }
    ],
    "sg:phone":"+1 304 525 0999",
    "sg:postcode":"25701",
    "sg:province":"WV",
    "sg:tags":[
        "car",
        "dealer"
    ],
    "wof:name":"Washington Ave Pre-Owned",
    "wof:placetype":"venue"
},
  "geometry": {"coordinates":[-82.460472,38.417695],"type":"Point"}
}