{
  "type": "Feature",
  "properties": {
    "iso:country":"US",
    "sg:address":"2900 1st Ave",
    "sg:city":"Huntington",
    "sg:classifiers":[
        {
            "category":"Health Services",
            "subcategory":"Doctor",
            "type":"Services"
        }
    ],
    "sg:phone":"+1 304 526 1114",
    "sg:postcode":"25702",
    "sg:province":"WV",
    "sg:tags":[
        "physician",
        "surgeon"
    ],
    "wof:name":"James F Spears II MD",
    "wof:placetype":"venue"
},
  "geometry": {"coordinates":[-82.401183,38.431587],"type":"Point"}
}