{
  "type": "Feature",
  "properties": {
    "addr:full":"2700 E Dupont Ave Belle WV 25015",
    "addr:housenumber":"2700",
    "addr:postcode":"25015",
    "addr:street":"E Dupont Ave",
    "iso:country":"US",
    "sg:address":"2700 E Dupont Ave",
    "sg:city":"Belle",
    "sg:classifiers":[
        {
            "category":"Home & Garden",
            "subcategory":"Building Materials",
            "type":"Retail Goods"
        }
    ],
    "sg:phone":"+1 304 949 5005",
    "sg:postcode":"25015",
    "sg:province":"WV",
    "wof:name":"Lowes",
    "wof:placetype":"venue"
},
  "geometry": {"coordinates":[-81.502184,38.203899],"type":"Point"}
}