{
  "type": "Feature",
  "properties": {
    "iso:country":"US",
    "sg:address":"1007 Division St",
    "sg:city":"Parkersburg",
    "sg:classifiers":[
        {
            "category":"Autos & Motor Vehicles",
            "subcategory":"Automobile Sales",
            "type":"Retail Goods"
        }
    ],
    "sg:phone":"+1 304 422 7520",
    "sg:postcode":"26101",
    "sg:province":"WV",
    "sg:tags":[
        "car",
        "used",
        "dealer"
    ],
    "wof:name":"J J's Auto Sales",
    "wof:placetype":"venue"
},
  "geometry": {"coordinates":[-81.554856,39.24901],"type":"Point"}
}