{
  "type": "Feature",
  "properties": {
    "addr:full":"331 Willey St Morgantown WV 26505",
    "addr:housenumber":"331",
    "addr:postcode":"26505",
    "addr:street":"Willey St",
    "iso:country":"US",
    "sg:address":"331 Willey St",
    "sg:city":"Morgantown",
    "sg:classifiers":[
        {
            "category":"Real Estate",
            "subcategory":"Real Estate Operator",
            "type":"Services"
        }
    ],
    "sg:phone":"+1 304 292 4333",
    "sg:postcode":"26505",
    "sg:province":"WV",
    "sg:tags":[
        "apartment"
    ],
    "wof:name":"Brownstone & Mountain View Mannner",
    "wof:placetype":"venue"
},
  "geometry": {"coordinates":[-79.952141,39.631481],"type":"Point"}
}