{
  "type": "Feature",
  "properties": {
    "addr:full":"1137 Van Voorhis Rd Morgantown WV 26505",
    "addr:housenumber":"1137",
    "addr:postcode":"26505",
    "addr:street":"Van Voorhis Rd",
    "iso:country":"US",
    "sg:address":"1137 Van Voorhis Rd",
    "sg:city":"Morgantown",
    "sg:classifiers":[
        {
            "category":"Restaurant",
            "type":"Food & Drink"
        }
    ],
    "sg:menulink":"http://www.allmenus.com/wv/central/139316-quiznos-sub/menu/",
    "sg:phone":"+1 304 599 4244",
    "sg:postcode":"26505",
    "sg:province":"WV",
    "sg:tags":[
        "wrap",
        "american",
        "sandwich"
    ],
    "wof:name":"Quiznos Sub",
    "wof:placetype":"venue"
},
  "geometry": {"coordinates":[-79.96335999999999,39.658797],"type":"Point"}
}