{
  "type": "Feature",
  "properties": {
    "addr:full":"1438 E Main St Princeton WV 24740",
    "addr:housenumber":"1438",
    "addr:postcode":"24740",
    "addr:street":"E Main St",
    "iso:country":"US",
    "sg:address":"1438 E Main St",
    "sg:city":"Princeton",
    "sg:classifiers":[
        {
            "category":"Professional",
            "subcategory":"Lawyer & Legal Services",
            "type":"Services"
        }
    ],
    "sg:phone":"+1 304 425 2103",
    "sg:postcode":"24740",
    "sg:province":"WV",
    "sg:tags":[
        "attorney"
    ],
    "wof:name":"Johnston Holroyd & Assoc",
    "wof:placetype":"venue"
},
  "geometry": {"coordinates":[-81.102001,37.365791],"type":"Point"}
}