{
  "type": "Feature",
  "properties": {
    "iso:country":"US",
    "sg:address":"645 Congress Ave",
    "sg:city":"Morgantown",
    "sg:classifiers":[
        {
            "category":"Professional",
            "subcategory":"Accounting & Tax Preparation",
            "type":"Services"
        }
    ],
    "sg:phone":"+1 304 599 1123",
    "sg:postcode":"26505",
    "sg:province":"WV",
    "wof:name":"Locator Billing Service",
    "wof:placetype":"venue"
},
  "geometry": {"coordinates":[-79.982714,39.665149],"type":"Point"}
}