{
  "type": "Feature",
  "properties": {
    "addr:full":"35 City View Ter Fairmont WV 26554",
    "addr:housenumber":"35",
    "addr:postcode":"26554",
    "addr:street":"City View Ter",
    "iso:country":"US",
    "sg:address":"35 City View Ter",
    "sg:city":"Fairmont",
    "sg:classifiers":[
        {
            "category":"Recreation",
            "type":"Entertainment"
        }
    ],
    "sg:phone":"+1 304 363 1249",
    "sg:postcode":"26554",
    "sg:province":"WV",
    "sg:tags":[
        "amusement"
    ],
    "wof:name":"Wave Tek Pool",
    "wof:placetype":"venue"
},
  "geometry": {"coordinates":[-80.128213,39.471426],"type":"Point"}
}