{
  "type": "Feature",
  "properties": {
    "addr:full":"866 Mercer St Princeton WV 24740",
    "addr:housenumber":"866",
    "addr:postcode":"24740",
    "addr:street":"Mercer St",
    "iso:country":"US",
    "sg:address":"866 Mercer St",
    "sg:city":"Princeton",
    "sg:classifiers":[
        {
            "category":"Shopping",
            "subcategory":"Optical Goods",
            "type":"Retail Goods"
        }
    ],
    "sg:phone":"+1 304 425 7265",
    "sg:postcode":"24740",
    "sg:province":"WV",
    "sg:tags":[
        "optician"
    ],
    "wof:name":"Taylor Optical Co",
    "wof:placetype":"venue"
},
  "geometry": {"coordinates":[-81.094959,37.369621],"type":"Point"}
}