{
  "type": "Feature",
  "properties": {
    "iso:country":"US",
    "sg:address":"1017 Rice Blvd",
    "sg:city":"Weirton",
    "sg:classifiers":[
        {
            "category":"Retail",
            "subcategory":"Auto Repair",
            "type":"Services"
        }
    ],
    "sg:phone":"+1 800 800 2727",
    "sg:postcode":"26062",
    "sg:province":"WV",
    "sg:tags":[
        "glass",
        "installation"
    ],
    "wof:name":"Safelite Autoglass",
    "wof:placetype":"venue"
},
  "geometry": {"coordinates":[-80.571966,40.39851],"type":"Point"}
}