{
  "type": "Feature",
  "properties": {
    "addr:full":"3135 Main St Weirton WV 26062",
    "addr:housenumber":"3135",
    "addr:postcode":"26062",
    "addr:street":"Main St",
    "iso:country":"US",
    "sg:address":"3135 Main St",
    "sg:city":"Weirton",
    "sg:classifiers":[
        {
            "category":"Retail",
            "subcategory":"Auto Repair",
            "type":"Services"
        }
    ],
    "sg:phone":"+1 304 748 3250",
    "sg:postcode":"26062",
    "sg:province":"WV",
    "sg:tags":[
        "repairing",
        "automobile"
    ],
    "wof:name":"Mike's Service Ctr",
    "wof:placetype":"venue"
},
  "geometry": {"coordinates":[-80.588594,40.406774],"type":"Point"}
}