{
  "type": "Feature",
  "properties": {
    "iso:country":"US",
    "sg:address":"2823 Poca River Rd",
    "sg:city":"Poca",
    "sg:classifiers":[
        {
            "category":"Building & Trades",
            "subcategory":"Construction",
            "type":"Services"
        }
    ],
    "sg:phone":"+1 304 776 3355",
    "sg:postcode":"25159",
    "sg:province":"WV",
    "sg:tags":[
        "house"
    ],
    "wof:name":"Timothy McClanahan",
    "wof:placetype":"venue"
},
  "geometry": {"coordinates":[-81.738463,38.484188],"type":"Point"}
}