{
  "type": "Feature",
  "properties": {
    "iso:country":"US",
    "sg:address":"39 Tyrone Rd",
    "sg:city":"Morgantown",
    "sg:classifiers":[
        {
            "category":"Professional",
            "subcategory":"Business Services",
            "type":"Services"
        }
    ],
    "sg:phone":"+1 304 594 1962",
    "sg:postcode":"26508",
    "sg:province":"WV",
    "wof:name":"Bhk Enterprises",
    "wof:placetype":"venue"
},
  "geometry": {"coordinates":[-79.863641,39.658471],"type":"Point"}
}