{
  "type": "Feature",
  "properties": {
    "iso:country":"US",
    "sg:address":"118 Adams St",
    "sg:city":"Fairmont",
    "sg:classifiers":[
        {
            "category":"Government",
            "subcategory":"Police Station",
            "type":"Public Place"
        }
    ],
    "sg:phone":"+1 304 367 0122",
    "sg:postcode":"26554",
    "sg:province":"WV",
    "sg:tags":[
        "federal"
    ],
    "wof:name":"Senator John D Rockefeller Iv",
    "wof:placetype":"venue"
},
  "geometry": {"coordinates":[-80.14403900000001,39.48421],"type":"Point"}
}