{
  "type": "Feature",
  "properties": {
    "iso:country":"US",
    "sg:address":"2424 Adams Ave",
    "sg:city":"Huntington",
    "sg:classifiers":[
        {
            "category":"Autos & Motor Vehicles",
            "subcategory":"Fuel & Gas Station",
            "type":"Retail Goods"
        }
    ],
    "sg:phone":"+1 304 429 3130",
    "sg:postcode":"25704",
    "sg:province":"WV",
    "sg:tags":[
        "station"
    ],
    "wof:name":"Loudermilk Chevron Service",
    "wof:placetype":"venue"
},
  "geometry": {"coordinates":[-82.495824,38.407688],"type":"Point"}
}