{
  "type": "Feature",
  "properties": {
    "iso:country":"US",
    "sg:address":"91 S High St",
    "sg:city":"Romney",
    "sg:classifiers":[
        {
            "category":"Organizations",
            "subcategory":"Membership Organization",
            "type":"Services"
        }
    ],
    "sg:phone":"+1 304 822 4320",
    "sg:postcode":"26757",
    "sg:province":"WV",
    "wof:name":"Ft Mill Ridge Foundation",
    "wof:placetype":"venue"
},
  "geometry": {"coordinates":[-78.756782,39.341461],"type":"Point"}
}