{
  "type": "Feature",
  "properties": {
    "iso:country":"US",
    "sg:address":"3410 Virginia Ave SE",
    "sg:city":"Charleston",
    "sg:classifiers":[
        {
            "category":"Social Services",
            "subcategory":"Child Care",
            "type":"Services"
        }
    ],
    "sg:phone":"+1 304 388 8866",
    "sg:postcode":"25304",
    "sg:province":"WV",
    "sg:website":"www.camc.org",
    "wof:name":"Lighthouse Child Care-Dev Ctr",
    "wof:placetype":"venue"
},
  "geometry": {"coordinates":[-81.5984,38.331082],"type":"Point"}
}