{
  "type": "Feature",
  "properties": {
    "iso:country":"US",
    "sg:address":"990 Dunbar Village Plz",
    "sg:city":"Dunbar",
    "sg:classifiers":[
        {
            "category":"Recreation",
            "subcategory":"Arcade",
            "type":"Entertainment"
        }
    ],
    "sg:phone":"+1 304 766 7271",
    "sg:postcode":"25064",
    "sg:province":"WV",
    "wof:name":"Max's Place",
    "wof:placetype":"venue"
},
  "geometry": {"coordinates":[-81.736847,38.358736],"type":"Point"}
}