{
  "type": "Feature",
  "properties": {
    "iso:country":"US",
    "sg:address":"104 Bridge St",
    "sg:city":"Matoaka",
    "sg:classifiers":[
        {
            "category":"Organizations",
            "subcategory":"Professional Association",
            "type":"Services"
        }
    ],
    "sg:phone":"+1 304 467 7900",
    "sg:postcode":"24736",
    "sg:province":"WV",
    "wof:name":"Loyal Order Of Moose",
    "wof:placetype":"venue"
},
  "geometry": {"coordinates":[-81.243909,37.418504],"type":"Point"}
}