{
  "type": "Feature",
  "properties": {
    "addr:full":"100 Broadway Ave Parkersburg WV 26101",
    "addr:housenumber":"100",
    "addr:postcode":"26101",
    "addr:street":"Broadway Ave",
    "iso:country":"US",
    "sg:address":"100 Broadway Ave",
    "sg:city":"Parkersburg",
    "sg:classifiers":[
        {
            "category":"Recreation",
            "subcategory":"Marina",
            "type":"Entertainment"
        }
    ],
    "sg:phone":"+1 304 424 7000",
    "sg:postcode":"26101",
    "sg:province":"WV",
    "wof:name":"Broadway Marina",
    "wof:placetype":"venue"
},
  "geometry": {"coordinates":[-81.526836,39.24668],"type":"Point"}
}