{
  "type": "Feature",
  "properties": {
    "iso:country":"US",
    "sg:address":"4727 Rte 152",
    "sg:city":"Lavalette",
    "sg:classifiers":[
        {
            "category":"Home & Garden",
            "subcategory":"Carpets & Floor Coverings",
            "type":"Retail Goods"
        }
    ],
    "sg:phone":"+1 304 525 0911",
    "sg:postcode":"25535",
    "sg:province":"WV",
    "wof:name":"Gordon McClellan Carpets",
    "wof:placetype":"venue"
},
  "geometry": {"coordinates":[-82.44847900000001,38.324298],"type":"Point"}
}