{
  "type": "Feature",
  "properties": {
    "addr:full":"2900 1st Ave Huntington WV 25702",
    "addr:housenumber":"2900",
    "addr:postcode":"25702",
    "addr:street":"1St Ave",
    "iso:country":"US",
    "sg:address":"2900 1st Ave",
    "sg:city":"Huntington",
    "sg:classifiers":[
        {
            "category":"Professional",
            "type":"Services"
        }
    ],
    "sg:phone":"+1 304 526 1037",
    "sg:postcode":"25702",
    "sg:province":"WV",
    "wof:name":"Social Services",
    "wof:placetype":"venue"
},
  "geometry": {"coordinates":[-82.401183,38.431587],"type":"Point"}
}