{
  "type": "Feature",
  "properties": {
    "addr:full":"103 Placid Dr Charleston WV 25312",
    "addr:housenumber":"103",
    "addr:postcode":"25312",
    "addr:street":"Placid Dr",
    "iso:country":"US",
    "sg:address":"103 Placid Dr",
    "sg:city":"Charleston",
    "sg:classifiers":[
        {
            "category":"Retail",
            "subcategory":"Repair Shop",
            "type":"Services"
        }
    ],
    "sg:phone":"+1 304 345 4767",
    "sg:postcode":"25312",
    "sg:province":"WV",
    "sg:tags":[
        "welding"
    ],
    "wof:name":"Welding Inc",
    "wof:placetype":"venue"
},
  "geometry": {"coordinates":[-81.616023,38.434869],"type":"Point"}
}