{
  "type": "Feature",
  "properties": {
    "iso:country":"US",
    "sg:address":"335 Oakvale Rd",
    "sg:city":"Princeton",
    "sg:classifiers":[
        {
            "category":"Autos & Motor Vehicles",
            "subcategory":"Automobile Sales",
            "type":"Retail Goods"
        }
    ],
    "sg:phone":"+1 304 425 7099",
    "sg:postcode":"24740",
    "sg:province":"WV",
    "sg:tags":[
        "car",
        "dealer"
    ],
    "wof:name":"Kenny Hendricks Used Cars",
    "wof:placetype":"venue"
},
  "geometry": {"coordinates":[-81.068904,37.365223],"type":"Point"}
}