{
  "type": "Feature",
  "properties": {
    "iso:country":"US",
    "sg:address":"322 Turnpike Rd",
    "sg:city":"Summersville",
    "sg:classifiers":[
        {
            "category":"Building & Trades",
            "subcategory":"Construction",
            "type":"Services"
        }
    ],
    "sg:phone":"+1 304 872 2911",
    "sg:postcode":"26651",
    "sg:province":"WV",
    "sg:tags":[
        "home",
        "commercial",
        "family"
    ],
    "wof:name":"Boso G L & Associates",
    "wof:placetype":"venue"
},
  "geometry": {"coordinates":[-80.856421,38.282061],"type":"Point"}
}