{
  "type": "Feature",
  "properties": {
    "addr:full":"707 Washington Ave Moundsville WV 26041",
    "addr:housenumber":"707",
    "addr:postcode":"26041",
    "addr:street":"Washington Ave",
    "iso:country":"US",
    "sg:address":"707 Washington Ave",
    "sg:city":"Moundsville",
    "sg:classifiers":[
        {
            "category":"Professional",
            "subcategory":"Secretarial Services",
            "type":"Services"
        }
    ],
    "sg:phone":"+1 304 845 8959",
    "sg:postcode":"26041",
    "sg:province":"WV",
    "sg:tags":[
        "writing"
    ],
    "wof:name":"Hands For Hope",
    "wof:placetype":"venue"
},
  "geometry": {"coordinates":[-80.741142,39.918543],"type":"Point"}
}