{
  "type": "Feature",
  "properties": {
    "iso:country":"US",
    "sg:address":"6308 Maccorkle Ave SE",
    "sg:city":"Charleston",
    "sg:classifiers":[
        {
            "category":"Restaurant",
            "type":"Food & Drink"
        }
    ],
    "sg:menulink":"http://www.allmenus.com/wv/belle/95448-ihop/menu/",
    "sg:phone":"+1 304 925 4467",
    "sg:postcode":"25304",
    "sg:province":"WV",
    "sg:tags":[
        "sandwich",
        "salad",
        "burger",
        "soup",
        "american",
        "steakhouse",
        "wrap"
    ],
    "wof:name":"IHOP",
    "wof:placetype":"venue"
},
  "geometry": {"coordinates":[-81.56326900000001,38.306455],"type":"Point"}
}