{
  "type": "Feature",
  "properties": {
    "addr:full":"3670 Main St Weirton WV 26062",
    "addr:housenumber":"3670",
    "addr:postcode":"26062",
    "addr:street":"Main St",
    "iso:country":"US",
    "sg:address":"3670 Main St",
    "sg:city":"Weirton",
    "sg:classifiers":[
        {
            "category":"Restaurant",
            "type":"Food & Drink"
        }
    ],
    "sg:phone":"+1 304 797 8240",
    "sg:postcode":"26062",
    "sg:province":"WV",
    "wof:name":"Hardee's",
    "wof:placetype":"venue"
},
  "geometry": {"coordinates":[-80.59166,40.397858],"type":"Point"}
}