{
  "type": "Feature",
  "properties": {
    "addr:full":"2933 Sissonville Dr Charleston WV 25312",
    "addr:housenumber":"2933",
    "addr:postcode":"25312",
    "addr:street":"Sissonville Dr",
    "iso:country":"US",
    "sg:address":"2933 Sissonville Dr",
    "sg:city":"Charleston",
    "sg:classifiers":[
        {
            "category":"Wholesale",
            "subcategory":"Vending Machines",
            "type":"Manufacturing & Wholesale Goods"
        }
    ],
    "sg:phone":"+1 304 343 6757",
    "sg:postcode":"25312",
    "sg:province":"WV",
    "wof:name":"Pittman Snax Sales Inc",
    "wof:placetype":"venue"
},
  "geometry": {"coordinates":[-81.66207,38.403179],"type":"Point"}
}