{
  "type": "Feature",
  "properties": {
    "iso:country":"US",
    "sg:address":"337 Jackson Ave",
    "sg:city":"Clarksburg",
    "sg:classifiers":[
        {
            "category":"Organizations",
            "subcategory":"Non-profit Organization",
            "type":"Services"
        },
        {
            "category":"Social Services",
            "type":"Services"
        }
    ],
    "sg:phone":"+1 304 622 5046",
    "sg:postcode":"26301",
    "sg:province":"WV",
    "sg:tags":[
        "human"
    ],
    "wof:name":"Habitat For Humanity Harrison",
    "wof:placetype":"venue"
},
  "geometry": {"coordinates":[-80.328763,39.280307],"type":"Point"}
}