{
  "type": "Feature",
  "properties": {
    "iso:country":"US",
    "sg:address":"1210 7th St",
    "sg:city":"Parkersburg",
    "sg:classifiers":[
        {
            "category":"Autos & Motor Vehicles",
            "subcategory":"Automobile Sales",
            "type":"Retail Goods"
        }
    ],
    "sg:phone":"+1 304 424 7280",
    "sg:postcode":"26101",
    "sg:province":"WV",
    "sg:tags":[
        "car",
        "dealer"
    ],
    "wof:name":"Mary's Used Cars",
    "wof:placetype":"venue"
},
  "geometry": {"coordinates":[-81.54198700000001,39.26358],"type":"Point"}
}