{
  "type": "Feature",
  "properties": {
    "iso:country":"US",
    "sg:address":"506 Chestnut St",
    "sg:city":"New Martinsville",
    "sg:classifiers":[
        {
            "category":"Building & Trades",
            "subcategory":"Plumbing",
            "type":"Services"
        }
    ],
    "sg:phone":"+1 304 455 1667",
    "sg:postcode":"26155",
    "sg:province":"WV",
    "sg:tags":[
        "heating",
        "contractor"
    ],
    "wof:name":"Miller Heating & Cooling",
    "wof:placetype":"venue"
},
  "geometry": {"coordinates":[-80.858891,39.644545],"type":"Point"}
}