{
  "type": "Feature",
  "properties": {
    "addr:full":"55 Strobridge Rd Inwood WV 25428",
    "addr:housenumber":"55",
    "addr:postcode":"25428",
    "addr:street":"Strobridge Rd",
    "iso:country":"US",
    "sg:address":"55 Strobridge Rd",
    "sg:city":"Inwood",
    "sg:classifiers":[
        {
            "category":"Retail",
            "subcategory":"Animal Services",
            "type":"Services"
        }
    ],
    "sg:phone":"+1 304 229 0844",
    "sg:postcode":"25428",
    "sg:province":"WV",
    "sg:tags":[
        "pet"
    ],
    "wof:name":"Sulphur Spring Stables",
    "wof:placetype":"venue"
},
  "geometry": {"coordinates":[-77.968738,39.353866],"type":"Point"}
}