{
  "type": "Feature",
  "properties": {
    "iso:country":"US",
    "sg:address":"116 Seneca Trl",
    "sg:city":"Lewisburg",
    "sg:classifiers":[
        {
            "category":"Professional",
            "subcategory":"Detective & Security Services",
            "type":"Services"
        }
    ],
    "sg:phone":"+1 304 645 4600",
    "sg:postcode":"24901",
    "sg:province":"WV",
    "sg:tags":[
        "guard",
        "patrol"
    ],
    "wof:name":"TEMAC Guard Svc",
    "wof:placetype":"venue"
},
  "geometry": {"coordinates":[-80.455185,37.783993],"type":"Point"}
}