{
  "type": "Feature",
  "properties": {
    "iso:country":"US",
    "sg:address":"1047 S Fayette St",
    "sg:city":"Beckley",
    "sg:classifiers":[
        {
            "category":"Personal",
            "subcategory":"Beauty Salon",
            "type":"Services"
        }
    ],
    "sg:phone":"+1 304 253 1412",
    "sg:postcode":"25801",
    "sg:province":"WV",
    "sg:tags":[
        "shop"
    ],
    "wof:name":"San's Hair Loft",
    "wof:placetype":"venue"
},
  "geometry": {"coordinates":[-81.177042,37.767638],"type":"Point"}
}