{
  "type": "Feature",
  "properties": {
    "iso:country":"US",
    "sg:address":"1110 Johnstown Rd",
    "sg:city":"Beckley",
    "sg:classifiers":[
        {
            "category":"Health Services",
            "subcategory":"Doctor",
            "type":"Services"
        }
    ],
    "sg:phone":"+1 304 255 0717",
    "sg:postcode":"25801",
    "sg:province":"WV",
    "sg:tags":[
        "dentist"
    ],
    "wof:name":"John Winkler DDS",
    "wof:placetype":"venue"
},
  "geometry": {"coordinates":[-81.169078,37.781168],"type":"Point"}
}