{
  "type": "Feature",
  "properties": {
    "addr:full":"1036 Ridgemont Dr Elkview WV 25071",
    "addr:housenumber":"1036",
    "addr:postcode":"25071",
    "addr:street":"Ridgemont Dr",
    "iso:country":"US",
    "sg:address":"1036 Ridgemont Dr",
    "sg:city":"Elkview",
    "sg:classifiers":[
        {
            "category":"Freight",
            "type":"Transportation"
        }
    ],
    "sg:phone":"+1 304 965 5040",
    "sg:postcode":"25071",
    "sg:province":"WV",
    "wof:name":"Jakes Freight",
    "wof:placetype":"venue"
},
  "geometry": {"coordinates":[-81.489467,38.410228],"type":"Point"}
}