{
  "type": "Feature",
  "properties": {
    "addr:full":"130 Braxton St Gassaway WV 26624",
    "addr:housenumber":"130",
    "addr:postcode":"26624",
    "addr:street":"Braxton St",
    "iso:country":"US",
    "sg:address":"130 Braxton St",
    "sg:city":"Gassaway",
    "sg:classifiers":[
        {
            "category":"Social Services",
            "subcategory":"Child Care",
            "type":"Services"
        }
    ],
    "sg:phone":"+1 304 364 8003",
    "sg:postcode":"26624",
    "sg:province":"WV",
    "sg:tags":[
        "day"
    ],
    "wof:name":"Ms Kaye's Day Care",
    "wof:placetype":"venue"
},
  "geometry": {"coordinates":[-80.77618699999999,38.66622],"type":"Point"}
}