{
  "type": "Feature",
  "properties": {
    "iso:country":"US",
    "sg:address":"4857 Maccorkle Ave",
    "sg:city":"South Charleston",
    "sg:classifiers":[
        {
            "category":"Health Services",
            "subcategory":"Health Practitioner",
            "type":"Services"
        }
    ],
    "sg:phone":"+1 304 766 6700",
    "sg:postcode":"25309",
    "sg:province":"WV",
    "sg:tags":[
        "psychologist"
    ],
    "wof:name":"ACP",
    "wof:placetype":"venue"
},
  "geometry": {"coordinates":[-81.730709,38.354562],"type":"Point"}
}