{
  "type": "Feature",
  "properties": {
    "iso:country":"US",
    "sg:address":"439 Jones Ave",
    "sg:city":"Oak Hill",
    "sg:classifiers":[
        {
            "category":"Autos & Motor Vehicles",
            "subcategory":"Fuel & Gas Station",
            "type":"Retail Goods"
        }
    ],
    "sg:phone":"+1 304 469 9621",
    "sg:postcode":"25901",
    "sg:province":"WV",
    "sg:tags":[
        "oil"
    ],
    "wof:name":"Nichols' Chevron",
    "wof:placetype":"venue"
},
  "geometry": {"coordinates":[-81.15422,37.974444],"type":"Point"}
}