{
  "type": "Feature",
  "properties": {
    "addr:full":"20 Kenton Dr Charleston WV 25311",
    "addr:housenumber":"20",
    "addr:postcode":"25311",
    "addr:street":"Kenton Dr",
    "iso:country":"US",
    "sg:address":"20 Kenton Dr",
    "sg:city":"Charleston",
    "sg:classifiers":[
        {
            "category":"Education",
            "subcategory":"Special Training",
            "type":"Public Place"
        }
    ],
    "sg:phone":"+1 304 345 7211",
    "sg:postcode":"25311",
    "sg:province":"WV",
    "sg:tags":[
        "educational"
    ],
    "wof:name":"American Education Svc",
    "wof:placetype":"venue"
},
  "geometry": {"coordinates":[-81.60317999999999,38.352786],"type":"Point"}
}