{
  "type": "Feature",
  "properties": {
    "iso:country":"US",
    "sg:address":"824 E Riverview Dr",
    "sg:city":"Belle",
    "sg:classifiers":[
        {
            "category":"Building & Trades",
            "subcategory":"Construction",
            "type":"Services"
        }
    ],
    "sg:phone":"+1 304 949 1511",
    "sg:postcode":"25015",
    "sg:province":"WV",
    "sg:tags":[
        "industrial"
    ],
    "wof:name":"ABC",
    "wof:placetype":"venue"
},
  "geometry": {"coordinates":[-81.538847,38.229607],"type":"Point"}
}