{
  "type": "Feature",
  "properties": {
    "addr:full":"1352 E Campbell Park Dr Huntington WV 25705",
    "addr:housenumber":"1352 e",
    "addr:postcode":"25705",
    "addr:street":"Campbell Park Dr",
    "iso:country":"US",
    "sg:address":"1352 E Campbell Park Dr",
    "sg:city":"Huntington",
    "sg:classifiers":[
        {
            "category":"Building & Trades",
            "subcategory":"Construction",
            "type":"Services"
        }
    ],
    "sg:phone":"+1 304 733 9005",
    "sg:postcode":"25705",
    "sg:province":"WV",
    "sg:tags":[
        "downspouts",
        "gutter"
    ],
    "wof:name":"A & A Continuous Gutters",
    "wof:placetype":"venue"
},
  "geometry": {"coordinates":[-82.361164,38.404851],"type":"Point"}
}