{
  "type": "Feature",
  "properties": {
    "iso:country":"US",
    "sg:address":"3099 Washington Ave",
    "sg:city":"Hurricane",
    "sg:classifiers":[
        {
            "category":"Restaurant",
            "type":"Food & Drink"
        }
    ],
    "sg:menulink":"http://www.allmenus.com/wv/curry/139763-sicilias-pizzeria/menu/",
    "sg:phone":"+1 304 562 7828",
    "sg:postcode":"25526",
    "sg:province":"WV",
    "sg:tags":[
        "wrap",
        "american",
        "sandwich",
        "pizza"
    ],
    "wof:name":"Sicilia's Pizzeria",
    "wof:placetype":"venue"
},
  "geometry": {"coordinates":[-82.020118,38.436372],"type":"Point"}
}