{
  "type": "Feature",
  "properties": {
    "iso:country":"US",
    "sg:address":"122 Davis Ave",
    "sg:city":"Elkins",
    "sg:classifiers":[
        {
            "category":"Professional",
            "type":"Services"
        }
    ],
    "sg:phone":"+1 304 637 2302",
    "sg:postcode":"26241",
    "sg:province":"WV",
    "sg:tags":[
        "establishment"
    ],
    "wof:name":"Jabberwock",
    "wof:placetype":"venue"
},
  "geometry": {"coordinates":[-79.84962,38.923321],"type":"Point"}
}