{
  "type": "Feature",
  "properties": {
    "iso:country":"US",
    "sg:address":"2010 Quarrier St E",
    "sg:city":"Charleston",
    "sg:classifiers":[
        {
            "category":"Shopping",
            "subcategory":"Gifts & Souvenirs",
            "type":"Retail Goods"
        }
    ],
    "sg:phone":"+1 304 347 2330",
    "sg:postcode":"25311",
    "sg:province":"WV",
    "sg:tags":[
        "shop"
    ],
    "wof:name":"Green Parrot Enterprises",
    "wof:placetype":"venue"
},
  "geometry": {"coordinates":[-81.609883,38.336279],"type":"Point"}
}