{
  "type": "Feature",
  "properties": {
    "iso:country":"US",
    "sg:address":"64 Hurricane Creek Rd",
    "sg:city":"Hurricane",
    "sg:classifiers":[
        {
            "category":"Home & Garden",
            "subcategory":"Carpets & Floor Coverings",
            "type":"Retail Goods"
        }
    ],
    "sg:phone":"+1 304 562 6977",
    "sg:postcode":"25526",
    "sg:province":"WV",
    "sg:tags":[
        "dealer",
        "rug"
    ],
    "wof:name":"Custom Carpets Outlet",
    "wof:placetype":"venue"
},
  "geometry": {"coordinates":[-82.015866,38.436589],"type":"Point"}
}