{
  "type": "Feature",
  "properties": {
    "addr:full":"270 S Washington St Berkeley Springs WV 25411",
    "addr:housenumber":"270",
    "addr:postcode":"25411",
    "addr:street":"S Washington St",
    "iso:country":"US",
    "sg:address":"270 S Washington St",
    "sg:city":"Berkeley Springs",
    "sg:classifiers":[
        {
            "category":"Building & Trades",
            "subcategory":"Construction",
            "type":"Services"
        }
    ],
    "sg:phone":"+1 304 258 1880",
    "sg:postcode":"25411",
    "sg:province":"WV",
    "sg:tags":[
        "general"
    ],
    "wof:name":"Cowles and Sons Construction",
    "wof:placetype":"venue"
},
  "geometry": {"coordinates":[-78.228607,39.62542],"type":"Point"}
}