{
  "type": "Feature",
  "properties": {
    "iso:country":"US",
    "sg:address":"17 Nell Jean Sq",
    "sg:city":"Beckley",
    "sg:classifiers":[
        {
            "category":"Personal",
            "subcategory":"Beauty Salon",
            "type":"Services"
        }
    ],
    "sg:phone":"+1 304 255 9400",
    "sg:postcode":"25801",
    "sg:province":"WV",
    "sg:tags":[
        "shop"
    ],
    "wof:name":"2001 Hair Designs",
    "wof:placetype":"venue"
},
  "geometry": {"coordinates":[-81.186168,37.810832],"type":"Point"}
}