{
  "type": "Feature",
  "properties": {
    "iso:country":"US",
    "sg:address":"1822 Morgantown Ave",
    "sg:city":"Fairmont",
    "sg:classifiers":[
        {
            "category":"Freight",
            "type":"Transportation"
        }
    ],
    "sg:phone":"+1 304 363 4400",
    "sg:postcode":"26554",
    "sg:province":"WV",
    "sg:tags":[
        "trucking"
    ],
    "wof:name":"General Delivery Inc",
    "wof:placetype":"venue"
},
  "geometry": {"coordinates":[-80.11129699999999,39.485715],"type":"Point"}
}