{
  "type": "Feature",
  "properties": {
    "iso:country":"US",
    "sg:address":"26 Davis St",
    "sg:city":"Petersburg",
    "sg:classifiers":[
        {
            "category":"Social Services",
            "subcategory":"Adult Care",
            "type":"Services"
        }
    ],
    "sg:phone":"+1 304 257 4474",
    "sg:postcode":"26847",
    "sg:province":"WV",
    "sg:tags":[
        "home",
        "group"
    ],
    "wof:name":"Res-Care Health Svc",
    "wof:placetype":"venue"
},
  "geometry": {"coordinates":[-79.12801399999999,38.993311],"type":"Point"}
}