{
  "type": "Feature",
  "properties": {
    "iso:country":"US",
    "sg:address":"283 Spring St",
    "sg:city":"Morgantown",
    "sg:classifiers":[
        {
            "category":"Building & Trades",
            "subcategory":"Construction",
            "type":"Services"
        }
    ],
    "sg:phone":"+1 304 598 0769",
    "sg:postcode":"26505",
    "sg:province":"WV",
    "sg:tags":[
        "contractor"
    ],
    "sg:website":"www.icynene.com",
    "wof:name":"Art Ford Builder Contractor",
    "wof:placetype":"venue"
},
  "geometry": {"coordinates":[-79.949479,39.64509],"type":"Point"}
}