{
  "type": "Feature",
  "properties": {
    "addr:full":"612 N Eisenhower Dr Beckley WV 25801",
    "addr:housenumber":"612",
    "addr:postcode":"25801",
    "addr:street":"N Eisenhower Dr",
    "iso:country":"US",
    "sg:address":"612 N Eisenhower Dr",
    "sg:city":"Beckley",
    "sg:classifiers":[
        {
            "category":"Shopping",
            "subcategory":"Florist",
            "type":"Retail Goods"
        }
    ],
    "sg:phone":"+1 304 252 3569",
    "sg:postcode":"25801",
    "sg:province":"WV",
    "wof:name":"Flowers By Nancy",
    "wof:placetype":"venue"
},
  "geometry": {"coordinates":[-81.172583,37.792398],"type":"Point"}
}