{
  "type": "Feature",
  "properties": {
    "iso:country":"US",
    "sg:address":"640 W Race St",
    "sg:city":"Martinsburg",
    "sg:classifiers":[
        {
            "category":"Autos & Motor Vehicles",
            "subcategory":"Fuel & Gas Station",
            "type":"Retail Goods"
        },
        {
            "category":"Utilities",
            "subcategory":"Fuel Oil & Lpg",
            "type":"Services"
        }
    ],
    "sg:phone":"+1 304 263 3333",
    "sg:postcode":"25401",
    "sg:province":"WV",
    "sg:tags":[
        "oils-fuel"
    ],
    "wof:name":"Griffith Energy Services",
    "wof:placetype":"venue"
},
  "geometry": {"coordinates":[-77.971098,39.462003],"type":"Point"}
}