{
  "type": "Feature",
  "properties": {
    "addr:full":"200 Patrick St Charleston WV 25312",
    "addr:housenumber":"200",
    "addr:postcode":"25312",
    "addr:street":"Patrick St",
    "iso:country":"US",
    "sg:address":"200 Patrick St",
    "sg:city":"Charleston",
    "sg:classifiers":[
        {
            "category":"Education",
            "subcategory":"Special Training",
            "type":"Public Place"
        }
    ],
    "sg:phone":"+1 304 345 2550",
    "sg:postcode":"25312",
    "sg:province":"WV",
    "sg:tags":[
        "instruction",
        "driving"
    ],
    "wof:name":"Capitol Driving School",
    "wof:placetype":"venue"
},
  "geometry": {"coordinates":[-81.667554,38.367886],"type":"Point"}
}