{
  "type": "Feature",
  "properties": {
    "iso:country":"US",
    "sg:address":"200 Wedgewood Dr Ste 106",
    "sg:city":"Morgantown",
    "sg:classifiers":[
        {
            "category":"Community Center",
            "type":"Public Place"
        }
    ],
    "sg:phone":"+1 866 873 0879",
    "sg:postcode":"26505",
    "sg:province":"WV",
    "sg:tags":[
        "medical"
    ],
    "sg:website":"http://www.rapidstdtesting.com",
    "wof:name":"Rapid STD/HIV Testing",
    "wof:placetype":"venue"
},
  "geometry": {"coordinates":[-79.963005,39.663683],"type":"Point"}
}