{
  "type": "Feature",
  "properties": {
    "iso:country":"US",
    "sg:address":"5 Erwin Ln",
    "sg:city":"Fairmont",
    "sg:classifiers":[
        {
            "category":"Health Services",
            "subcategory":"Doctor",
            "type":"Services"
        }
    ],
    "sg:phone":"+1 304 366 7611",
    "sg:postcode":"26554",
    "sg:province":"WV",
    "sg:tags":[
        "physician",
        "surgeon",
        "clinic",
        "medical"
    ],
    "wof:name":"Peter L Ang M D",
    "wof:placetype":"venue"
},
  "geometry": {"coordinates":[-80.176399,39.472865],"type":"Point"}
}