{
  "type": "Feature",
  "properties": {
    "iso:country":"US",
    "sg:address":"318 Buffalo St",
    "sg:city":"Elkins",
    "sg:classifiers":[
        {
            "category":"Professional",
            "subcategory":"Computer Services",
            "type":"Services"
        }
    ],
    "sg:phone":"+1 304 636 4343",
    "sg:postcode":"26241",
    "sg:province":"WV",
    "wof:name":"Mountain State Information",
    "wof:placetype":"venue"
},
  "geometry": {"coordinates":[-79.844888,38.927792],"type":"Point"}
}