{
  "type": "Feature",
  "properties": {
    "iso:country":"US",
    "sg:address":"148 Main St",
    "sg:city":"Spencer",
    "sg:classifiers":[
        {
            "category":"Shopping",
            "subcategory":"Florist",
            "type":"Retail Goods"
        }
    ],
    "sg:phone":"+1 304 927 1224",
    "sg:postcode":"25276",
    "sg:province":"WV",
    "wof:name":"Taylor's Floral",
    "wof:placetype":"venue"
},
  "geometry": {"coordinates":[-81.35007,38.801603],"type":"Point"}
}