{
  "type": "Feature",
  "properties": {
    "addr:full":"4962 Teays Valley Rd Scott Depot WV 25560",
    "addr:housenumber":"4962",
    "addr:postcode":"25560",
    "addr:street":"Teays Valley Rd",
    "iso:country":"US",
    "sg:address":"4962 Teays Valley Rd",
    "sg:city":"Scott Depot",
    "sg:classifiers":[
        {
            "category":"Social Services",
            "type":"Services"
        }
    ],
    "sg:phone":"+1 304 204 5800",
    "sg:postcode":"25560",
    "sg:province":"WV",
    "sg:tags":[
        "worker"
    ],
    "wof:name":"Rosey Futures Social Work Svc",
    "wof:placetype":"venue"
},
  "geometry": {"coordinates":[-81.85428400000001,38.435937],"type":"Point"}
}