{
  "type": "Feature",
  "properties": {
    "addr:full":"1400 Roy Ave Bluefield WV 24701",
    "addr:housenumber":"1400",
    "addr:postcode":"24701",
    "addr:street":"Roy Ave",
    "iso:country":"US",
    "sg:address":"1400 Roy Ave",
    "sg:city":"Bluefield",
    "sg:classifiers":[
        {
            "category":"Organizations",
            "subcategory":"Community Association",
            "type":"Services"
        }
    ],
    "sg:phone":"+1 304 327 7626",
    "sg:postcode":"24701",
    "sg:province":"WV",
    "sg:tags":[
        "fraternal"
    ],
    "wof:name":"Loyal Order Of Moose",
    "wof:placetype":"venue"
},
  "geometry": {"coordinates":[-81.223726,37.260154],"type":"Point"}
}