{
  "type": "Feature",
  "properties": {
    "addr:full":"405 Cabela Dr Triadelphia WV 26059",
    "addr:housenumber":"405",
    "addr:postcode":"26059",
    "addr:street":"Cabela Dr",
    "iso:country":"US",
    "sg:address":"405 Cabela Dr",
    "sg:city":"Triadelphia",
    "sg:classifiers":[
        {
            "category":"Utilities",
            "subcategory":"Mobile Phone",
            "type":"Services"
        },
        {
            "category":"Shopping",
            "subcategory":"Mobile Phones",
            "type":"Retail Goods"
        },
        {
            "category":"Communications",
            "type":"Services"
        },
        {
            "category":"Internet Cafe",
            "subcategory":"None",
            "type":"Food & Drink"
        }
    ],
    "sg:phone":"+1 304 547 1378",
    "sg:postcode":"26059",
    "sg:province":"WV",
    "sg:tags":[
        "supply",
        "telephone",
        "wireless",
        "equipment",
        "paging",
        "signaling",
        "cellular",
        "provider"
    ],
    "sg:website":"http://www.att.com",
    "wof:name":"AT&T",
    "wof:placetype":"venue"
},
  "geometry": {"coordinates":[-80.601106,40.057721],"type":"Point"}
}