{
  "type": "Feature",
  "properties": {
    "iso:country":"US",
    "sg:address":"577 Boggs Run Rd",
    "sg:city":"Benwood",
    "sg:classifiers":[
        {
            "category":"Shopping",
            "subcategory":"Clothing, Apparel, & Fashions",
            "type":"Retail Goods"
        }
    ],
    "sg:phone":"+1 304 233 1031",
    "sg:postcode":"26031",
    "sg:province":"WV",
    "sg:tags":[
        "theatrical",
        "costume"
    ],
    "wof:name":"Castle Halloween",
    "wof:placetype":"venue"
},
  "geometry": {"coordinates":[-80.72542199999999,40.008936],"type":"Point"}
}