{
  "type": "Feature",
  "properties": {
    "addr:full":"822 Broad St Summersville WV 26651",
    "addr:housenumber":"822",
    "addr:postcode":"26651",
    "addr:street":"Broad St",
    "iso:country":"US",
    "sg:address":"822 Broad St",
    "sg:city":"Summersville",
    "sg:classifiers":[
        {
            "category":"Personal",
            "subcategory":"Beauty Salon",
            "type":"Services"
        }
    ],
    "sg:phone":"+1 304 872 1799",
    "sg:postcode":"26651",
    "sg:province":"WV",
    "sg:tags":[
        "shop"
    ],
    "wof:name":"Vital Link",
    "wof:placetype":"venue"
},
  "geometry": {"coordinates":[-80.85075999999999,38.275701],"type":"Point"}
}