{
  "type": "Feature",
  "properties": {
    "addr:full":"409 6th Ave St Albans WV 25177",
    "addr:housenumber":"409",
    "addr:postcode":"25177",
    "addr:street":"6Th Ave",
    "iso:country":"US",
    "sg:address":"409 6th Ave",
    "sg:city":"St Albans",
    "sg:classifiers":[
        {
            "category":"Retail",
            "subcategory":"Funeral Services",
            "type":"Services"
        }
    ],
    "sg:phone":"+1 304 727 4325",
    "sg:postcode":"25177",
    "sg:province":"WV",
    "sg:tags":[
        "director",
        "crematory"
    ],
    "wof:name":"Bartlett Chapman Funeral Home",
    "wof:placetype":"venue"
},
  "geometry": {"coordinates":[-81.832729,38.385513],"type":"Point"}
}