{
  "type": "Feature",
  "properties": {
    "addr:full":"165 Pikeside St Martinsburg WV 25401",
    "addr:housenumber":"165",
    "addr:postcode":"25401",
    "addr:street":"Pikeside St",
    "iso:country":"US",
    "sg:address":"165 Pikeside St",
    "sg:city":"Martinsburg",
    "sg:classifiers":[
        {
            "category":"Freight",
            "type":"Transportation"
        }
    ],
    "sg:phone":"+1 304 262 6725",
    "sg:postcode":"25401",
    "sg:province":"WV",
    "sg:tags":[
        "hauling",
        "trucking"
    ],
    "wof:name":"Mtc Corp",
    "wof:placetype":"venue"
},
  "geometry": {"coordinates":[-77.988749,39.419653],"type":"Point"}
}