{
  "type": "Feature",
  "properties": {
    "iso:country":"US",
    "sg:address":"1537 7th Ave",
    "sg:city":"Huntington",
    "sg:classifiers":[
        {
            "category":"Autos & Motor Vehicles",
            "subcategory":"Auto Supplies",
            "type":"Retail Goods"
        }
    ],
    "sg:phone":"+1 304 525 6664",
    "sg:postcode":"25701",
    "sg:province":"WV",
    "sg:tags":[
        "tire"
    ],
    "wof:name":"Mohr's Tire Farm",
    "wof:placetype":"venue"
},
  "geometry": {"coordinates":[-82.43119299999999,38.418595],"type":"Point"}
}