{
  "type": "Feature",
  "properties": {
    "addr:full":"432 3rd Ave SW South Charleston WV 25303",
    "addr:housenumber":"432",
    "addr:postcode":"25303",
    "addr:street":"3Rd Ave Sw",
    "iso:country":"US",
    "sg:address":"432 3rd Ave SW",
    "sg:city":"South Charleston",
    "sg:classifiers":[
        {
            "category":"Manufacturing",
            "subcategory":"Glass & Minerals",
            "type":"Manufacturing & Wholesale Goods"
        }
    ],
    "sg:phone":"+1 304 744 9486",
    "sg:postcode":"25303",
    "sg:province":"WV",
    "sg:tags":[
        "prod",
        "made"
    ],
    "wof:name":"Cyclops Industries Inc",
    "wof:placetype":"venue"
},
  "geometry": {"coordinates":[-81.691542,38.366365],"type":"Point"}
}