{
  "type": "Feature",
  "properties": {
    "iso:country":"US",
    "sg:address":"407 Parkersburg Rd",
    "sg:city":"Spencer",
    "sg:classifiers":[
        {
            "category":"Real Estate",
            "subcategory":"Real Estate Operator",
            "type":"Services"
        }
    ],
    "sg:phone":"+1 304 927 5909",
    "sg:postcode":"25276",
    "sg:province":"WV",
    "sg:tags":[
        "apartment"
    ],
    "wof:name":"Imperial Gardens",
    "wof:placetype":"venue"
},
  "geometry": {"coordinates":[-81.363979,38.814932],"type":"Point"}
}