{
  "type": "Feature",
  "properties": {
    "iso:country":"US",
    "sg:address":"1624 Kanawha Blvd E",
    "sg:city":"Charleston",
    "sg:classifiers":[
        {
            "category":"Organizations",
            "subcategory":"Professional Association",
            "type":"Services"
        }
    ],
    "sg:phone":"+1 304 342 1060",
    "sg:postcode":"25311",
    "sg:province":"WV",
    "sg:website":"www.wvchamber.com",
    "wof:name":"West VIRGINIA Chamber-Commerce",
    "wof:placetype":"venue"
},
  "geometry": {"coordinates":[-81.618843,38.337526],"type":"Point"}
}