{
  "type": "Feature",
  "properties": {
    "iso:country":"US",
    "sg:address":"213 Roosevelt Blvd",
    "sg:city":"Eleanor",
    "sg:classifiers":[
        {
            "category":"Wholesale",
            "subcategory":"Auto Parts",
            "type":"Manufacturing & Wholesale Goods"
        }
    ],
    "sg:phone":"+1 304 586 2132",
    "sg:postcode":"25070",
    "sg:province":"WV",
    "sg:tags":[
        "supply"
    ],
    "wof:name":"Eleanor Auto Supply",
    "wof:placetype":"venue"
},
  "geometry": {"coordinates":[-81.922419,38.533752],"type":"Point"}
}