{
  "type": "Feature",
  "properties": {
    "iso:country":"US",
    "sg:address":"112 31st St",
    "sg:city":"Wheeling",
    "sg:classifiers":[
        {
            "category":"Wholesale",
            "subcategory":"Machinery & Supplies",
            "type":"Manufacturing & Wholesale Goods"
        }
    ],
    "sg:phone":"+1 304 232 8211",
    "sg:postcode":"26003",
    "sg:province":"WV",
    "sg:tags":[
        "equipment",
        "industrial"
    ],
    "wof:name":"Specialty Supply Co",
    "wof:placetype":"venue"
},
  "geometry": {"coordinates":[-80.723744,40.050147],"type":"Point"}
}