{
  "type": "Feature",
  "properties": {
    "iso:country":"US",
    "sg:address":"474 N Main St",
    "sg:city":"Weston",
    "sg:classifiers":[
        {
            "category":"Health Services",
            "subcategory":"Doctor",
            "type":"Services"
        }
    ],
    "sg:phone":"+1 304 269 6666",
    "sg:postcode":"26452",
    "sg:province":"WV",
    "sg:tags":[
        "physician",
        "surgeon"
    ],
    "wof:name":"Arnold F Gruspe Inc",
    "wof:placetype":"venue"
},
  "geometry": {"coordinates":[-80.46353999999999,39.041793],"type":"Point"}
}