{
  "type": "Feature",
  "properties": {
    "addr:full":"1336 Stafford Dr Princeton WV 24740",
    "addr:housenumber":"1336",
    "addr:postcode":"24740",
    "addr:street":"Stafford Dr",
    "iso:country":"US",
    "sg:address":"1336 Stafford Dr",
    "sg:city":"Princeton",
    "sg:classifiers":[
        {
            "category":"Shopping",
            "subcategory":"Discount & Variety Stores",
            "type":"Retail Goods"
        }
    ],
    "sg:phone":"+1 304 425 2137",
    "sg:postcode":"24740",
    "sg:province":"WV",
    "wof:name":"Roses",
    "wof:placetype":"venue"
},
  "geometry": {"coordinates":[-81.100899,37.360489],"type":"Point"}
}