{
  "type": "Feature",
  "properties": {
    "iso:country":"US",
    "sg:address":"205 Marshall St",
    "sg:city":"Mc Mechen",
    "sg:classifiers":[
        {
            "category":"Shopping",
            "subcategory":"Pharmacy",
            "type":"Retail Goods"
        }
    ],
    "sg:phone":"+1 304 232 6103",
    "sg:postcode":"26040",
    "sg:province":"WV",
    "wof:name":"Rite Aid",
    "wof:placetype":"venue"
},
  "geometry": {"coordinates":[-80.72973500000001,39.99421],"type":"Point"}
}