{
  "type": "Feature",
  "properties": {
    "iso:country":"US",
    "sg:address":"1237 Kings Rd",
    "sg:city":"Morgantown",
    "sg:classifiers":[
        {
            "category":"Real Estate",
            "subcategory":"Real Estate Agent",
            "type":"Services"
        }
    ],
    "sg:phone":"+1 304 292 6513",
    "sg:postcode":"26508",
    "sg:province":"WV",
    "sg:tags":[
        "appraiser"
    ],
    "wof:name":"Spiker Appraisals LLC",
    "wof:placetype":"venue"
},
  "geometry": {"coordinates":[-79.87207600000001,39.626407],"type":"Point"}
}