{
  "type": "Feature",
  "properties": {
    "addr:full":"504 Campbells Creek Dr Charleston WV 25306",
    "addr:housenumber":"504",
    "addr:postcode":"25306",
    "addr:street":"Campbells Creek Dr",
    "iso:country":"US",
    "sg:address":"504 Campbells Creek Dr",
    "sg:city":"Charleston",
    "sg:classifiers":[
        {
            "category":"Shopping",
            "subcategory":"Department Store",
            "type":"Retail Goods"
        }
    ],
    "sg:phone":"+1 304 925 6137",
    "sg:postcode":"25306",
    "sg:province":"WV",
    "sg:tags":[
        "shop"
    ],
    "wof:name":"Dollar General",
    "wof:placetype":"venue"
},
  "geometry": {"coordinates":[-81.52067099999999,38.317316],"type":"Point"}
}