{
  "type": "Feature",
  "properties": {
    "iso:country":"US",
    "sg:address":"110 New River Dr",
    "sg:city":"Beckley",
    "sg:classifiers":[
        {
            "category":"Retail",
            "subcategory":"Auto Repair",
            "type":"Services"
        }
    ],
    "sg:phone":"+1 304 255 2845",
    "sg:postcode":"25801",
    "sg:province":"WV",
    "sg:tags":[
        "body",
        "automobile",
        "painting"
    ],
    "wof:name":"Ken Williams Body Shop",
    "wof:placetype":"venue"
},
  "geometry": {"coordinates":[-81.185355,37.7895],"type":"Point"}
}