{
  "type": "Feature",
  "properties": {
    "addr:full":"122 Keller Ln Beckley WV 25801",
    "addr:housenumber":"122",
    "addr:postcode":"25801",
    "addr:street":"Keller Ln",
    "iso:country":"US",
    "sg:address":"122 Keller Ln",
    "sg:city":"Beckley",
    "sg:classifiers":[
        {
            "category":"Utilities",
            "subcategory":"Sewage",
            "type":"Services"
        },
        {
            "category":"Government",
            "subcategory":"Office",
            "type":"Public Place"
        }
    ],
    "sg:phone":"+1 304 253 2191",
    "sg:postcode":"25801",
    "sg:province":"WV",
    "sg:tags":[
        "company",
        "sewer"
    ],
    "wof:name":"North Beckley Public Svc Dist",
    "wof:placetype":"venue"
},
  "geometry": {"coordinates":[-81.314018,37.851551],"type":"Point"}
}