{
  "type": "Feature",
  "properties": {
    "iso:country":"US",
    "sg:address":"139 W Main St",
    "sg:city":"Bridgeport",
    "sg:classifiers":[
        {
            "category":"Insurance",
            "subcategory":"Insurance Agent",
            "type":"Services"
        }
    ],
    "sg:phone":"+1 304 842 3314",
    "sg:postcode":"26330",
    "sg:province":"WV",
    "sg:website":"www.unitedsecurityagency.com",
    "wof:name":"United Security Agency",
    "wof:placetype":"venue"
},
  "geometry": {"coordinates":[-80.252679,39.284408],"type":"Point"}
}