{
  "type": "Feature",
  "properties": {
    "iso:country":"US",
    "sg:address":"115 N 9th St",
    "sg:city":"Wheeling",
    "sg:classifiers":[
        {
            "category":"Shopping",
            "subcategory":"Gifts & Souvenirs",
            "type":"Retail Goods"
        }
    ],
    "sg:phone":"+1 304 277 4093",
    "sg:postcode":"26003",
    "sg:province":"WV",
    "sg:tags":[
        "shop",
        "novelty"
    ],
    "wof:name":"Jewelry By Terresa",
    "wof:placetype":"venue"
},
  "geometry": {"coordinates":[-80.69899100000001,40.111654],"type":"Point"}
}