{
  "type": "Feature",
  "properties": {
    "iso:country":"US",
    "sg:address":"160 Spring St",
    "sg:city":"Charleston",
    "sg:classifiers":[
        {
            "category":"Wholesale",
            "subcategory":"Hardware",
            "type":"Manufacturing & Wholesale Goods"
        }
    ],
    "sg:phone":"+1 304 342 4784",
    "sg:postcode":"25301",
    "sg:province":"WV",
    "sg:tags":[
        "plumbing",
        "fixture",
        "supply"
    ],
    "wof:name":"Ferguson Enterprises Inc",
    "wof:placetype":"venue"
},
  "geometry": {"coordinates":[-81.627224,38.356982],"type":"Point"}
}