{
  "type": "Feature",
  "properties": {
    "iso:country":"US",
    "sg:address":"107 Lancaster Cir",
    "sg:city":"Ranson",
    "sg:classifiers":[
        {
            "category":"Government",
            "subcategory":"Office",
            "type":"Public Place"
        }
    ],
    "sg:phone":"+1 304 725 2028",
    "sg:postcode":"25438",
    "sg:province":"WV",
    "sg:tags":[
        "government-united",
        "state"
    ],
    "sg:website":"http://www.hhs.gov",
    "wof:name":"Wic Office",
    "wof:placetype":"venue"
},
  "geometry": {"coordinates":[-77.860336,39.295055],"type":"Point"}
}