{
  "type": "Feature",
  "properties": {
    "addr:full":"180 Willey St Morgantown WV 26505",
    "addr:housenumber":"180",
    "addr:postcode":"26505",
    "addr:street":"Willey St",
    "iso:country":"US",
    "sg:address":"180 Willey St",
    "sg:city":"Morgantown",
    "sg:classifiers":[
        {
            "category":"Personal",
            "subcategory":"Tanning Parlor",
            "type":"Services"
        },
        {
            "category":"Personal",
            "type":"Services"
        }
    ],
    "sg:phone":"+1 304 296 0660",
    "sg:postcode":"26505",
    "sg:province":"WV",
    "sg:tags":[
        "salon"
    ],
    "wof:name":"T'Eaz Tanning",
    "wof:placetype":"venue"
},
  "geometry": {"coordinates":[-79.95428099999999,39.632329],"type":"Point"}
}