{
  "type": "Feature",
  "properties": {
    "addr:full":"1431 Chestnut St Kenova WV 25530",
    "addr:housenumber":"1431",
    "addr:postcode":"25530",
    "addr:street":"Chestnut St",
    "iso:country":"US",
    "sg:address":"1431 Chestnut St",
    "sg:city":"Kenova",
    "sg:classifiers":[
        {
            "category":"Shopping",
            "type":"Retail Goods"
        }
    ],
    "sg:phone":"+1 304 453 3171",
    "sg:postcode":"25530",
    "sg:province":"WV",
    "sg:tags":[
        "hearing",
        "equipment",
        "supply",
        "merchandise",
        "impaired"
    ],
    "wof:name":"Hearing Aid Store The",
    "wof:placetype":"venue"
},
  "geometry": {"coordinates":[-82.57826799999999,38.39944],"type":"Point"}
}