{
  "type": "Feature",
  "properties": {
    "iso:country":"US",
    "sg:address":"1543 Fairmont Ave",
    "sg:city":"Fairmont",
    "sg:classifiers":[
        {
            "category":"Insurance",
            "subcategory":"Insurance Agent",
            "type":"Services"
        }
    ],
    "sg:phone":"+1 304 622 5484",
    "sg:postcode":"26554",
    "sg:province":"WV",
    "wof:name":"Citizens Against Lawsuits",
    "wof:placetype":"venue"
},
  "geometry": {"coordinates":[-80.161816,39.461687],"type":"Point"}
}