{
  "type": "Feature",
  "properties": {
    "iso:country":"US",
    "sg:address":"209 3rd St Lilly Park Addition",
    "sg:city":"Rainelle",
    "sg:classifiers":[
        {
            "category":"Insurance",
            "subcategory":"Insurance Agent",
            "type":"Services"
        }
    ],
    "sg:phone":"+1 304 438 7221",
    "sg:postcode":"25962",
    "sg:province":"WV",
    "wof:name":"State Farm Insurance",
    "wof:placetype":"venue"
},
  "geometry": {"coordinates":[-80.798081,37.948699],"type":"Point"}
}