{
  "type": "Feature",
  "properties": {
    "addr:full":"447 Fairchance Rd Morgantown WV 26508",
    "addr:housenumber":"447",
    "addr:postcode":"26508",
    "addr:street":"Fairchance Rd",
    "iso:country":"US",
    "sg:address":"447 Fairchance Rd",
    "sg:city":"Morgantown",
    "sg:classifiers":[
        {
            "category":"Retail",
            "subcategory":"Auto Repair",
            "type":"Services"
        }
    ],
    "sg:phone":"+1 304 594 3735",
    "sg:postcode":"26508",
    "sg:province":"WV",
    "sg:tags":[
        "body"
    ],
    "wof:name":"Independent Auto Body",
    "wof:placetype":"venue"
},
  "geometry": {"coordinates":[-79.82761000000001,39.690842],"type":"Point"}
}