{
  "type": "Feature",
  "properties": {
    "iso:country":"US",
    "sg:address":"204 Market St",
    "sg:city":"Marietta",
    "sg:classifiers":[
        {
            "category":"Building & Trades",
            "subcategory":"Construction",
            "type":"Services"
        }
    ],
    "sg:phone":"+1 740 374 7160",
    "sg:postcode":"45750",
    "sg:province":"OH",
    "sg:tags":[
        "maker",
        "cabinet"
    ],
    "wof:name":"Carriage House Assoc",
    "wof:placetype":"venue"
},
  "geometry": {"coordinates":[-81.461204,39.409461],"type":"Point"}
}