{
  "type": "Feature",
  "properties": {
    "addr:full":"8709 Maccorkle Ave Charleston WV 25315",
    "addr:housenumber":"8709",
    "addr:postcode":"25315",
    "addr:street":"Maccorkle Ave",
    "iso:country":"US",
    "sg:address":"8709 Maccorkle Ave",
    "sg:city":"Charleston",
    "sg:classifiers":[
        {
            "category":"Home & Garden",
            "subcategory":"Hardware",
            "type":"Retail Goods"
        },
        {
            "category":"Home & Garden",
            "subcategory":"Garden Supply",
            "type":"Retail Goods"
        }
    ],
    "sg:phone":"+1 304 949 4151",
    "sg:postcode":"25315",
    "sg:province":"WV",
    "sg:tags":[
        "engine"
    ],
    "wof:name":"Ace Hardware",
    "wof:placetype":"venue"
},
  "geometry": {"coordinates":[-81.56990999999999,38.249074],"type":"Point"}
}