{
  "type": "Feature",
  "properties": {
    "iso:country":"US",
    "sg:address":"3323 Pennsylvania Ave",
    "sg:city":"Weirton",
    "sg:classifiers":[
        {
            "category":"Shopping",
            "subcategory":"Used Merchandise",
            "type":"Retail Goods"
        }
    ],
    "sg:phone":"+1 304 723 7109",
    "sg:postcode":"26062",
    "sg:province":"WV",
    "sg:tags":[
        "shop",
        "thrift"
    ],
    "wof:name":"Weirton Community Thrift Store",
    "wof:placetype":"venue"
},
  "geometry": {"coordinates":[-80.537796,40.408675],"type":"Point"}
}