{
  "type": "Feature",
  "properties": {
    "iso:country":"US",
    "sg:address":"3 Blueville Dr",
    "sg:city":"Grafton",
    "sg:classifiers":[
        {
            "category":"Autos & Motor Vehicles",
            "subcategory":"Auto Supplies",
            "type":"Retail Goods"
        }
    ],
    "sg:phone":"+1 304 265 5408",
    "sg:postcode":"26354",
    "sg:province":"WV",
    "sg:tags":[
        "tire"
    ],
    "wof:name":"Phil's Tire & Auto Repair",
    "wof:placetype":"venue"
},
  "geometry": {"coordinates":[-80.002579,39.346414],"type":"Point"}
}