{
  "type": "Feature",
  "properties": {
    "iso:country":"US",
    "sg:address":"2500 Fairmont Ave",
    "sg:city":"Fairmont",
    "sg:classifiers":[
        {
            "category":"Government",
            "subcategory":"Office",
            "type":"Public Place"
        }
    ],
    "sg:phone":"+1 304 366 6925",
    "sg:postcode":"26554",
    "sg:province":"WV",
    "sg:tags":[
        "program",
        "administrative"
    ],
    "wof:name":"Social Security Administration",
    "wof:placetype":"venue"
},
  "geometry": {"coordinates":[-80.17507500000001,39.450448],"type":"Point"}
}