{
  "type": "Feature",
  "properties": {
    "iso:country":"US",
    "sg:address":"645 Kanawha Ave",
    "sg:city":"Rainelle",
    "sg:classifiers":[
        {
            "category":"Shopping",
            "type":"Retail Goods"
        }
    ],
    "sg:phone":"+1 304 438 6142",
    "sg:postcode":"25962",
    "sg:province":"WV",
    "sg:tags":[
        "hearing",
        "equipment",
        "supply",
        "impaired"
    ],
    "wof:name":"Heritage Hearing Aid Ctr",
    "wof:placetype":"venue"
},
  "geometry": {"coordinates":[-80.77722,37.967703],"type":"Point"}
}