{
  "type": "Feature",
  "properties": {
    "iso:country":"US",
    "sg:address":"303 Hill St",
    "sg:city":"Williamson",
    "sg:classifiers":[
        {
            "category":"Professional",
            "subcategory":"Management & Consulting",
            "type":"Services"
        }
    ],
    "sg:phone":"+1 304 235 1893",
    "sg:postcode":"25661",
    "sg:province":"WV",
    "sg:tags":[
        "consultant",
        "mining"
    ],
    "wof:name":"B & B Mine Safety",
    "wof:placetype":"venue"
},
  "geometry": {"coordinates":[-82.291826,37.671457],"type":"Point"}
}