{
  "type": "Feature",
  "properties": {
    "iso:country":"US",
    "sg:address":"5149 Heath Creek Rd",
    "sg:city":"Barboursville",
    "sg:classifiers":[
        {
            "category":"Building & Trades",
            "subcategory":"Construction",
            "type":"Services"
        }
    ],
    "sg:phone":"+1 304 733 2216",
    "sg:postcode":"25504",
    "sg:province":"WV",
    "sg:tags":[
        "concrete",
        "contractor"
    ],
    "wof:name":"Start To Finish Concrete Cnstr",
    "wof:placetype":"venue"
},
  "geometry": {"coordinates":[-82.29095100000001,38.351237],"type":"Point"}
}