{
  "type": "Feature",
  "properties": {
    "addr:full":"317 31st St Huntington WV 25702",
    "addr:housenumber":"317",
    "addr:postcode":"25702",
    "addr:street":"31St St",
    "iso:country":"US",
    "sg:address":"317 31st St",
    "sg:city":"Huntington",
    "sg:classifiers":[
        {
            "category":"Banks & Credit Unions",
            "subcategory":"Bank",
            "type":"Services"
        }
    ],
    "sg:phone":"+1 304 697 2919",
    "sg:postcode":"25702",
    "sg:province":"WV",
    "sg:tags":[
        "federal"
    ],
    "wof:name":"Cabell County School Employees",
    "wof:placetype":"venue"
},
  "geometry": {"coordinates":[-82.394458,38.430208],"type":"Point"}
}