{
  "type": "Feature",
  "properties": {
    "iso:country":"US",
    "sg:address":"718 W Main St",
    "sg:city":"Grafton",
    "sg:classifiers":[
        {
            "category":"Government",
            "subcategory":"Office",
            "type":"Public Place"
        }
    ],
    "sg:phone":"+1 304 265 1288",
    "sg:postcode":"26354",
    "sg:province":"WV",
    "sg:tags":[
        "county",
        "program",
        "health"
    ],
    "wof:name":"Taylor County Health Dept",
    "wof:placetype":"venue"
},
  "geometry": {"coordinates":[-80.04006099999999,39.34157],"type":"Point"}
}