{
  "type": "Feature",
  "properties": {
    "iso:country":"US",
    "sg:address":"549 Center Ave",
    "sg:city":"Romney",
    "sg:classifiers":[
        {
            "category":"Health Services",
            "subcategory":"Hospital",
            "type":"Services"
        }
    ],
    "sg:phone":"+1 304 822 4561",
    "sg:postcode":"26757",
    "sg:province":"WV",
    "wof:name":"Hampshire Memorial Hospital",
    "wof:placetype":"venue"
},
  "geometry": {"coordinates":[-78.758359,39.349338],"type":"Point"}
}