{
  "type": "Feature",
  "properties": {
    "iso:country":"US",
    "sg:address":"3407 Jackson Ave",
    "sg:city":"Point Pleasant",
    "sg:classifiers":[
        {
            "category":"Retail",
            "subcategory":"Repair Shop",
            "type":"Services"
        }
    ],
    "sg:phone":"+1 304 675 7388",
    "sg:postcode":"25550",
    "sg:province":"WV",
    "sg:tags":[
        "electrical"
    ],
    "wof:name":"Thompson Appliance Repair",
    "wof:placetype":"venue"
},
  "geometry": {"coordinates":[-82.123976,38.881049],"type":"Point"}
}