{
  "type": "Feature",
  "properties": {
    "addr:full":"1611 Virginia St E Charleston WV 25311",
    "addr:housenumber":"1611",
    "addr:postcode":"25311",
    "addr:street":"Virginia St E",
    "iso:country":"US",
    "sg:address":"1611 Virginia St E",
    "sg:city":"Charleston",
    "sg:classifiers":[
        {
            "category":"Travel",
            "subcategory":"Hotels & Motels",
            "type":"Entertainment"
        }
    ],
    "sg:phone":"+1 304 344 0748",
    "sg:postcode":"25311",
    "sg:province":"WV",
    "sg:tags":[
        "breakfast",
        "accommodation",
        "bed"
    ],
    "wof:name":"Brass Pineapple B & B",
    "wof:placetype":"venue"
},
  "geometry": {"coordinates":[-81.615773,38.337365],"type":"Point"}
}