{
  "type": "Feature",
  "properties": {
    "iso:country":"US",
    "sg:address":"23 8th St",
    "sg:city":"Mcmechen",
    "sg:classifiers":[
        {
            "category":"Social Services",
            "subcategory":"Child Care",
            "type":"Services"
        }
    ],
    "sg:phone":"+1 304 233 4734",
    "sg:postcode":"26040",
    "sg:province":"WV",
    "sg:tags":[
        "day"
    ],
    "wof:name":"Klowns Korner",
    "wof:placetype":"venue"
},
  "geometry": {"coordinates":[-80.73079799999999,39.989055],"type":"Point"}
}