{
  "type": "Feature",
  "properties": {
    "iso:country":"US",
    "sg:address":"5522 Elk River Rd",
    "sg:city":"Elkview",
    "sg:classifiers":[
        {
            "category":"Home & Garden",
            "subcategory":"Garden Supply",
            "type":"Retail Goods"
        }
    ],
    "sg:phone":"+1 304 548 7183",
    "sg:postcode":"25071",
    "sg:province":"WV",
    "sg:tags":[
        "engine"
    ],
    "wof:name":"Rope Inc",
    "wof:placetype":"venue"
},
  "geometry": {"coordinates":[-81.40116399999999,38.469664],"type":"Point"}
}