{
  "type": "Feature",
  "properties": {
    "iso:country":"US",
    "sg:address":"104 Rolling Acres",
    "sg:city":"Winfield",
    "sg:classifiers":[
        {
            "category":"Real Estate",
            "subcategory":"Real Estate Agent",
            "type":"Services"
        }
    ],
    "sg:phone":"+1 304 755 0390",
    "sg:postcode":"25213",
    "sg:province":"WV",
    "wof:name":"Alice Townson Realtr",
    "wof:placetype":"venue"
},
  "geometry": {"coordinates":[-81.842163,38.487202],"type":"Point"}
}