{
  "type": "Feature",
  "properties": {
    "iso:country":"US",
    "sg:address":"2302 Bland Rd",
    "sg:city":"Bluefield",
    "sg:classifiers":[
        {
            "category":"Organizations",
            "subcategory":"Religious Organization",
            "type":"Services"
        }
    ],
    "sg:phone":"+1 304 327 5605",
    "sg:postcode":"24701",
    "sg:province":"WV",
    "sg:tags":[
        "church"
    ],
    "wof:name":"Covenant Reformed Baptist",
    "wof:placetype":"venue"
},
  "geometry": {"coordinates":[-81.21550000000001,37.25697],"type":"Point"}
}