{
  "type": "Feature",
  "properties": {
    "iso:country":"US",
    "sg:address":"501 W Main St",
    "sg:city":"Clarksburg",
    "sg:classifiers":[
        {
            "category":"Education",
            "subcategory":"College",
            "type":"Public Place"
        }
    ],
    "sg:phone":"+1 304 623 5721",
    "sg:postcode":"26301",
    "sg:province":"WV",
    "sg:tags":[
        "academic",
        "school"
    ],
    "sg:website":"www.fscwv.edu",
    "wof:name":"Clarksburg Center Of Fairmont",
    "wof:placetype":"venue"
},
  "geometry": {"coordinates":[-80.342748,39.280038],"type":"Point"}
}