{
  "type": "Feature",
  "properties": {
    "addr:full":"416 9th St Huntington WV 25701",
    "addr:housenumber":"416",
    "addr:postcode":"25701",
    "addr:street":"9Th St",
    "iso:country":"US",
    "sg:address":"416 9th St",
    "sg:city":"Huntington",
    "sg:classifiers":[
        {
            "category":"Travel",
            "subcategory":"Travel Agent",
            "type":"Entertainment"
        }
    ],
    "sg:phone":"+1 304 523 3627",
    "sg:postcode":"25701",
    "sg:province":"WV",
    "sg:tags":[
        "bureau",
        "passenger",
        "agency",
        "transportation",
        "arrangement"
    ],
    "sg:website":"www.traveldoctors.com",
    "wof:name":"Travel Doctors Travel Agency",
    "wof:placetype":"venue"
},
  "geometry": {"coordinates":[-82.443686,38.420347],"type":"Point"}
}