{
  "type": "Feature",
  "properties": {
    "addr:full":"25 Tressel St White Slphr Spgs WV 24986",
    "addr:housenumber":"25",
    "addr:postcode":"24986",
    "addr:street":"Tressel St;Slphr Spgs",
    "iso:country":"US",
    "sg:address":"25 Tressel St",
    "sg:city":"White Slphr Spgs",
    "sg:classifiers":[
        {
            "category":"Organizations",
            "subcategory":"Religious Organization",
            "type":"Services"
        }
    ],
    "sg:phone":"+1 304 536 1291",
    "sg:postcode":"24986",
    "sg:province":"WV",
    "sg:tags":[
        "church"
    ],
    "wof:name":"Emmanuel United Methodist",
    "wof:placetype":"venue"
},
  "geometry": {"coordinates":[-80.30000800000001,37.793129],"type":"Point"}
}