{
  "type": "Feature",
  "properties": {
    "iso:country":"US",
    "sg:address":"3081C Point Marion Rd",
    "sg:city":"Morgantown",
    "sg:classifiers":[
        {
            "category":"Autos & Motor Vehicles",
            "subcategory":"Automobile Sales",
            "type":"Retail Goods"
        },
        {
            "category":"Retail",
            "subcategory":"Auto Repair",
            "type":"Services"
        }
    ],
    "sg:phone":"+1 304 292 0355",
    "sg:postcode":"26505",
    "sg:province":"WV",
    "sg:tags":[
        "body",
        "repairing",
        "cars-wholesale",
        "used",
        "car",
        "dealers-used",
        "painting"
    ],
    "wof:name":"Auto Detail Plus",
    "wof:placetype":"venue"
},
  "geometry": {"coordinates":[-79.914879,39.662024],"type":"Point"}
}