{
  "type": "Feature",
  "properties": {
    "addr:full":"910 Sheridan Ave Martinsburg WV 25401",
    "addr:housenumber":"910",
    "addr:postcode":"25401",
    "addr:street":"Sheridan Ave",
    "iso:country":"US",
    "sg:address":"910 Sheridan Ave",
    "sg:city":"Martinsburg",
    "sg:classifiers":[
        {
            "category":"Building & Trades",
            "subcategory":"Construction",
            "type":"Services"
        }
    ],
    "sg:phone":"+1 304 267 4063",
    "sg:postcode":"25401",
    "sg:province":"WV",
    "sg:tags":[
        "altering",
        "remodeling",
        "contractor"
    ],
    "wof:name":"Minor Home Repairs",
    "wof:placetype":"venue"
},
  "geometry": {"coordinates":[-77.978059,39.442148],"type":"Point"}
}