{
  "type": "Feature",
  "properties": {
    "iso:country":"US",
    "sg:address":"4630 Maccorkle Ave",
    "sg:city":"Spring Hill",
    "sg:classifiers":[
        {
            "category":"Restaurant",
            "type":"Food & Drink"
        }
    ],
    "sg:phone":"+1 304 768 7210",
    "sg:postcode":"25309",
    "sg:province":"WV",
    "wof:name":"Long John Silver's",
    "wof:placetype":"venue"
},
  "geometry": {"coordinates":[-81.72703799999999,38.355477],"type":"Point"}
}