{
  "type": "Feature",
  "properties": {
    "iso:country":"US",
    "sg:address":"58884 Wright Rd",
    "sg:city":"Barnesville",
    "sg:classifiers":[
        {
            "category":"Professional",
            "subcategory":"Lawyer & Legal Services",
            "type":"Services"
        }
    ],
    "sg:phone":"+1 740 425 1023",
    "sg:postcode":"43713",
    "sg:province":"OH",
    "sg:tags":[
        "attorney"
    ],
    "wof:name":"Paul B Jefferis",
    "wof:placetype":"venue"
},
  "geometry": {"coordinates":[-81.188342,39.952179],"type":"Point"}
}