{
  "type": "Feature",
  "properties": {
    "addr:full":"132 Barleywood Ln Bradley WV 25818",
    "addr:housenumber":"132",
    "addr:postcode":"25818",
    "addr:street":"Barleywood Ln",
    "iso:country":"US",
    "sg:address":"132 Barleywood Ln",
    "sg:city":"Bradley",
    "sg:classifiers":[
        {
            "category":"Organizations",
            "subcategory":"Non-profit Organization",
            "type":"Services"
        }
    ],
    "sg:phone":"+1 304 877 3700",
    "sg:postcode":"25818",
    "sg:province":"WV",
    "wof:name":"Eastern Star",
    "wof:placetype":"venue"
},
  "geometry": {"coordinates":[-81.19261299999999,37.873931],"type":"Point"}
}