{
  "type": "Feature",
  "properties": {
    "iso:country":"US",
    "sg:address":"2111 Kanawha Ave SE",
    "sg:city":"Charleston",
    "sg:classifiers":[
        {
            "category":"Government",
            "subcategory":"Office",
            "type":"Public Place"
        }
    ],
    "sg:phone":"+1 304 346 5330",
    "sg:postcode":"25304",
    "sg:province":"WV",
    "wof:name":"US Rowing",
    "wof:placetype":"venue"
},
  "geometry": {"coordinates":[-81.61808499999999,38.334004],"type":"Point"}
}