{
  "type": "Feature",
  "properties": {
    "addr:full":"12 America Ave Wheeling WV 26003",
    "addr:housenumber":"12",
    "addr:postcode":"26003",
    "addr:street":"America Ave",
    "iso:country":"US",
    "sg:address":"12 America Ave",
    "sg:city":"Wheeling",
    "sg:classifiers":[
        {
            "category":"Freight",
            "type":"Transportation"
        }
    ],
    "sg:phone":"+1 304 243 1728",
    "sg:postcode":"26003",
    "sg:province":"WV",
    "sg:tags":[
        "trucking"
    ],
    "wof:name":"Landstar Ranger Inc",
    "wof:placetype":"venue"
},
  "geometry": {"coordinates":[-80.686491,40.076673],"type":"Point"}
}