{
  "type": "Feature",
  "properties": {
    "addr:full":"64421 Hilltop Ave Bellaire OH 43906",
    "addr:housenumber":"64421",
    "addr:postcode":"43906",
    "addr:street":"Hilltop Ave",
    "iso:country":"US",
    "sg:address":"64421 Hilltop Ave",
    "sg:city":"Bellaire",
    "sg:classifiers":[
        {
            "category":"Utilities",
            "subcategory":"Cable",
            "type":"Services"
        }
    ],
    "sg:phone":"+1 740 676 6377",
    "sg:postcode":"43906",
    "sg:province":"OH",
    "sg:tags":[
        "television"
    ],
    "wof:name":"Bellaire Television Cable Co",
    "wof:placetype":"venue"
},
  "geometry": {"coordinates":[-80.757775,40.019462],"type":"Point"}
}