{
  "type": "Feature",
  "properties": {
    "iso:country":"US",
    "sg:address":"706 Belrock Ave",
    "sg:city":"Belpre",
    "sg:classifiers":[
        {
            "category":"Personal",
            "subcategory":"Beauty Salon",
            "type":"Services"
        }
    ],
    "sg:phone":"+1 740 423 9554",
    "sg:postcode":"45714",
    "sg:province":"OH",
    "sg:tags":[
        "shop"
    ],
    "wof:name":"Head Quarters",
    "wof:placetype":"venue"
},
  "geometry": {"coordinates":[-81.589904,39.277464],"type":"Point"}
}