{
  "type": "Feature",
  "properties": {
    "iso:country":"US",
    "sg:address":"110 Rossmore Rd",
    "sg:city":"Rossmore",
    "sg:classifiers":[
        {
            "category":"Personal",
            "subcategory":"Beauty Salon",
            "type":"Services"
        }
    ],
    "sg:phone":"+1 304 946 4414",
    "sg:postcode":"25601",
    "sg:province":"WV",
    "wof:name":"Jenny's One More Time Beauty",
    "wof:placetype":"venue"
},
  "geometry": {"coordinates":[-81.98210899999999,37.809545],"type":"Point"}
}