{
  "type": "Feature",
  "properties": {
    "addr:full":"13107 Maccorkle Ave Charleston WV 25315",
    "addr:housenumber":"13107",
    "addr:postcode":"25315",
    "addr:street":"Maccorkle Ave",
    "iso:country":"US",
    "sg:address":"13107 Maccorkle Ave",
    "sg:city":"Charleston",
    "sg:classifiers":[
        {
            "category":"Shopping",
            "subcategory":"Florist",
            "type":"Retail Goods"
        }
    ],
    "sg:phone":"+1 304 595 2233",
    "sg:postcode":"25315",
    "sg:province":"WV",
    "wof:name":"Sherrys Forget ME Not Flrl",
    "wof:placetype":"venue"
},
  "geometry": {"coordinates":[-81.530895,38.219383],"type":"Point"}
}