{
  "type": "Feature",
  "properties": {
    "iso:country":"US",
    "sg:address":"300 Capitol St",
    "sg:city":"Charleston",
    "sg:classifiers":[
        {
            "category":"Real Estate",
            "subcategory":"Real Estate Operator",
            "type":"Services"
        }
    ],
    "sg:phone":"+1 304 346 3661",
    "sg:postcode":"25301",
    "sg:province":"WV",
    "sg:tags":[
        "property",
        "b",
        "dwelling",
        "lessor",
        "nonresidential"
    ],
    "wof:name":"Quincy Center",
    "wof:placetype":"venue"
},
  "geometry": {"coordinates":[-81.632177,38.351355],"type":"Point"}
}