{
  "type": "Feature",
  "properties": {
    "iso:country":"US",
    "sg:address":"450 Carolina Ave",
    "sg:city":"Chester",
    "sg:classifiers":[
        {
            "category":"Food & Beverages",
            "subcategory":"Bakery",
            "type":"Retail Goods"
        }
    ],
    "sg:phone":"+1 304 387 3565",
    "sg:postcode":"26034",
    "sg:province":"WV",
    "sg:tags":[
        "pie"
    ],
    "wof:name":"Gene's Sugar Pressed Pies",
    "wof:placetype":"venue"
},
  "geometry": {"coordinates":[-80.563097,40.612812],"type":"Point"}
}