{
  "type": "Feature",
  "properties": {
    "iso:country":"US",
    "sg:address":"320 Washington St W",
    "sg:city":"Charleston",
    "sg:classifiers":[
        {
            "category":"Personal",
            "subcategory":"Beauty Salon",
            "type":"Services"
        }
    ],
    "sg:phone":"+1 304 342 0402",
    "sg:postcode":"25302",
    "sg:province":"WV",
    "sg:tags":[
        "manicuring"
    ],
    "wof:name":"Love Yo Nails",
    "wof:placetype":"venue"
},
  "geometry": {"coordinates":[-81.641347,38.36173],"type":"Point"}
}