{
  "type": "Feature",
  "properties": {
    "addr:full":"3064 Pennsylvania Ave Weirton WV 26062",
    "addr:housenumber":"3064",
    "addr:postcode":"26062",
    "addr:street":"Pennsylvania Ave",
    "iso:country":"US",
    "sg:address":"3064 Pennsylvania Ave",
    "sg:city":"Weirton",
    "sg:classifiers":[
        {
            "category":"Health Services",
            "subcategory":"Doctor",
            "type":"Services"
        }
    ],
    "sg:phone":"+1 304 723 5120",
    "sg:postcode":"26062",
    "sg:province":"WV",
    "sg:tags":[
        "dentist"
    ],
    "wof:name":"Ronald C Ard DDS",
    "wof:placetype":"venue"
},
  "geometry": {"coordinates":[-80.546897,40.411711],"type":"Point"}
}