{
  "type": "Feature",
  "properties": {
    "iso:country":"US",
    "sg:address":"138 E Baker St",
    "sg:city":"Lewisburg",
    "sg:classifiers":[
        {
            "category":"Building & Trades",
            "subcategory":"Construction",
            "type":"Services"
        }
    ],
    "sg:phone":"+1 304 645 3822",
    "sg:postcode":"24901",
    "sg:province":"WV",
    "sg:tags":[
        "general",
        "contractor"
    ],
    "wof:name":"Bryant Builders",
    "wof:placetype":"venue"
},
  "geometry": {"coordinates":[-80.453487,37.777224],"type":"Point"}
}