{
  "type": "Feature",
  "properties": {
    "iso:country":"US",
    "sg:address":"33 Eagles Rd",
    "sg:city":"Beckley",
    "sg:classifiers":[
        {
            "category":"Health Services",
            "subcategory":"Hospital",
            "type":"Services"
        }
    ],
    "sg:phone":"+1 304 255 7723",
    "sg:postcode":"25801",
    "sg:province":"WV",
    "sg:tags":[
        "clinic",
        "specialty",
        "psychiatric",
        "outpatient"
    ],
    "wof:name":"Timberline Health Group",
    "wof:placetype":"venue"
},
  "geometry": {"coordinates":[-81.16224200000001,37.799315],"type":"Point"}
}