{
  "type": "Feature",
  "properties": {
    "iso:country":"US",
    "sg:address":"747 Market St",
    "sg:city":"Wheeling",
    "sg:classifiers":[
        {
            "category":"Food & Beverages",
            "subcategory":"Liquor & Beverages",
            "type":"Retail Goods"
        }
    ],
    "sg:phone":"+1 304 232 9464",
    "sg:postcode":"26003",
    "sg:province":"WV",
    "sg:tags":[
        "beer",
        "ale"
    ],
    "wof:name":"Ray's Place",
    "wof:placetype":"venue"
},
  "geometry": {"coordinates":[-80.72376300000001,40.074685],"type":"Point"}
}