{
  "type": "Feature",
  "properties": {
    "addr:full":"8319 Sissonville Dr Charleston WV 25320",
    "addr:housenumber":"8319",
    "addr:postcode":"25320",
    "addr:street":"Sissonville Dr",
    "iso:country":"US",
    "sg:address":"8319 Sissonville Dr",
    "sg:city":"Charleston",
    "sg:classifiers":[
        {
            "category":"Building & Trades",
            "subcategory":"Plumbing",
            "type":"Services"
        }
    ],
    "sg:phone":"+1 304 988 1710",
    "sg:postcode":"25320",
    "sg:province":"WV",
    "sg:tags":[
        "air",
        "conditioning",
        "contractor",
        "system",
        "heating"
    ],
    "wof:name":"Thomas Heating & Cooling",
    "wof:placetype":"venue"
},
  "geometry": {"coordinates":[-81.630943,38.526576],"type":"Point"}
}