{
  "type": "Feature",
  "properties": {
    "addr:full":"973 Dunbar Village Plz Dunbar WV 25064",
    "addr:housenumber":"973",
    "addr:postcode":"25064",
    "addr:street":"Dunbar Village Plz",
    "iso:country":"US",
    "sg:address":"973 Dunbar Village Plz",
    "sg:city":"Dunbar",
    "sg:classifiers":[
        {
            "category":"Shopping",
            "subcategory":"Gifts & Souvenirs",
            "type":"Retail Goods"
        }
    ],
    "sg:phone":"+1 304 768 3330",
    "sg:postcode":"25064",
    "sg:province":"WV",
    "wof:name":"Hello Shop The",
    "wof:placetype":"venue"
},
  "geometry": {"coordinates":[-81.73695600000001,38.358708],"type":"Point"}
}