{
  "type": "Feature",
  "properties": {
    "addr:full":"3302 Hemlock Ave Parkersburg WV 26104",
    "addr:housenumber":"3302",
    "addr:postcode":"26104",
    "addr:street":"Hemlock Ave",
    "iso:country":"US",
    "sg:address":"3302 Hemlock Ave",
    "sg:city":"Parkersburg",
    "sg:classifiers":[
        {
            "category":"Home & Garden",
            "subcategory":"Building Materials",
            "type":"Retail Goods"
        }
    ],
    "sg:phone":"+1 304 422 7060",
    "sg:postcode":"26104",
    "sg:province":"WV",
    "sg:tags":[
        "windows"
    ],
    "wof:name":"Siding & Window Solutions-WV",
    "wof:placetype":"venue"
},
  "geometry": {"coordinates":[-81.538437,39.28781],"type":"Point"}
}