{
  "type": "Feature",
  "properties": {
    "addr:full":"201 Monongahela Ave Morgantown WV 26501",
    "addr:housenumber":"201",
    "addr:postcode":"26501",
    "addr:street":"Monongahela Ave",
    "iso:country":"US",
    "sg:address":"201 Monongahela Ave",
    "sg:city":"Morgantown",
    "sg:classifiers":[
        {
            "category":"Manufacturing",
            "subcategory":"Signs",
            "type":"Manufacturing & Wholesale Goods"
        }
    ],
    "sg:phone":"+1 304 291 5044",
    "sg:postcode":"26501",
    "sg:province":"WV",
    "wof:name":"Bluebird Lane LLC",
    "wof:placetype":"venue"
},
  "geometry": {"coordinates":[-79.977363,39.639384],"type":"Point"}
}