{
  "type": "Feature",
  "properties": {
    "iso:country":"US",
    "sg:address":"1402 1st Ave",
    "sg:city":"Charleston",
    "sg:classifiers":[
        {
            "category":"Organizations",
            "subcategory":"Religious Organization",
            "type":"Services"
        }
    ],
    "sg:phone":"+1 304 343 6360",
    "sg:postcode":"25312",
    "sg:province":"WV",
    "sg:tags":[
        "clergy"
    ],
    "wof:name":"James D Ealy",
    "wof:placetype":"venue"
},
  "geometry": {"coordinates":[-81.66327699999999,38.365554],"type":"Point"}
}