{
  "type": "Feature",
  "properties": {
    "iso:country":"US",
    "sg:address":"327 State St",
    "sg:city":"Madison",
    "sg:classifiers":[
        {
            "category":"Wholesale",
            "subcategory":"Medical Equipment & Supplies",
            "type":"Manufacturing & Wholesale Goods"
        }
    ],
    "sg:phone":"+1 304 369 7964",
    "sg:postcode":"25130",
    "sg:province":"WV",
    "wof:name":"Boone Homecare Supplies",
    "wof:placetype":"venue"
},
  "geometry": {"coordinates":[-81.82113699999999,38.064206],"type":"Point"}
}