{
  "type": "Feature",
  "properties": {
    "iso:country":"US",
    "sg:address":"410 6th Ave",
    "sg:city":"St Albans",
    "sg:classifiers":[
        {
            "category":"Organizations",
            "subcategory":"Professional Association",
            "type":"Services"
        }
    ],
    "sg:phone":"+1 304 722 0065",
    "sg:postcode":"25177",
    "sg:province":"WV",
    "wof:name":"St Albans Renaissance Group",
    "wof:placetype":"venue"
},
  "geometry": {"coordinates":[-81.832702,38.385662],"type":"Point"}
}