{
  "type": "Feature",
  "properties": {
    "addr:full":"1222 W Main St Grafton WV 26354",
    "addr:housenumber":"1222",
    "addr:postcode":"26354",
    "addr:street":"W Main St",
    "iso:country":"US",
    "sg:address":"1222 W Main St",
    "sg:city":"Grafton",
    "sg:classifiers":[
        {
            "category":"Retail",
            "subcategory":"Auto Repair",
            "type":"Services"
        }
    ],
    "sg:phone":"+1 304 265 3448",
    "sg:postcode":"26354",
    "sg:province":"WV",
    "sg:tags":[
        "repairing",
        "automobile",
        "exhaust"
    ],
    "wof:name":"Morgans Muffler and Brakes",
    "wof:placetype":"venue"
},
  "geometry": {"coordinates":[-80.038202,39.349678],"type":"Point"}
}