{
  "type": "Feature",
  "properties": {
    "iso:country":"US",
    "sg:address":"101 Lee St",
    "sg:city":"Ripley",
    "sg:classifiers":[
        {
            "category":"Organizations",
            "subcategory":"Religious Organization",
            "type":"Services"
        }
    ],
    "sg:phone":"+1 304 372 8440",
    "sg:postcode":"25271",
    "sg:province":"WV",
    "wof:name":"Grace Gospel Church",
    "wof:placetype":"venue"
},
  "geometry": {"coordinates":[-81.695334,38.818912],"type":"Point"}
}