{
  "type": "Feature",
  "properties": {
    "iso:country":"US",
    "sg:address":"119 Lincoln St",
    "sg:city":"Grafton",
    "sg:classifiers":[
        {
            "category":"Food & Beverages",
            "subcategory":"Groceries & Convenience Stores",
            "type":"Retail Goods"
        }
    ],
    "sg:phone":"+1 304 265 3475",
    "sg:postcode":"26354",
    "sg:province":"WV",
    "sg:tags":[
        "gasoline"
    ],
    "wof:name":"Williams Grocery",
    "wof:placetype":"venue"
},
  "geometry": {"coordinates":[-80.00601,39.342674],"type":"Point"}
}