{
  "type": "Feature",
  "properties": {
    "addr:full":"2617 Hugh St Parkersburg WV 26101",
    "addr:housenumber":"2617",
    "addr:postcode":"26101",
    "addr:street":"Hugh St",
    "iso:country":"US",
    "sg:address":"2617 Hugh St",
    "sg:city":"Parkersburg",
    "sg:classifiers":[
        {
            "category":"Real Estate",
            "subcategory":"Developer",
            "type":"Services"
        }
    ],
    "sg:phone":"+1 304 422 5226",
    "sg:postcode":"26101",
    "sg:province":"WV",
    "sg:tags":[
        "cemetery"
    ],
    "wof:name":"Ew King Cemetery",
    "wof:placetype":"venue"
},
  "geometry": {"coordinates":[-81.551423,39.231149],"type":"Point"}
}