{
  "type": "Feature",
  "properties": {
    "iso:country":"US",
    "sg:address":"2233 S Kanawha St",
    "sg:city":"Beckley",
    "sg:classifiers":[
        {
            "category":"Health Services",
            "subcategory":"Doctor",
            "type":"Services"
        }
    ],
    "sg:phone":"+1 304 255 9248",
    "sg:postcode":"25801",
    "sg:province":"WV",
    "sg:tags":[
        "physician",
        "surgeon"
    ],
    "wof:name":"Yasar J Aksoy MD",
    "wof:placetype":"venue"
},
  "geometry": {"coordinates":[-81.162139,37.767919],"type":"Point"}
}