{
  "type": "Feature",
  "properties": {
    "iso:country":"US",
    "sg:address":"118 Lafayette Ave",
    "sg:city":"Moundsville",
    "sg:classifiers":[
        {
            "category":"Restaurant",
            "type":"Food & Drink"
        }
    ],
    "sg:phone":"+1 304 845 4500",
    "sg:postcode":"26041",
    "sg:province":"WV",
    "sg:tags":[
        "shop",
        "coffee"
    ],
    "wof:name":"Coffee Talk Etc",
    "wof:placetype":"venue"
},
  "geometry": {"coordinates":[-80.752073,39.931846],"type":"Point"}
}