{
  "type": "Feature",
  "properties": {
    "addr:full":"231 Capitol St Charleston WV 25301",
    "addr:housenumber":"231",
    "addr:postcode":"25301",
    "addr:street":"Capitol St",
    "iso:country":"US",
    "sg:address":"231 Capitol St",
    "sg:city":"Charleston",
    "sg:classifiers":[
        {
            "category":"Shopping",
            "type":"Retail Goods"
        }
    ],
    "sg:phone":"+1 304 342 1033",
    "sg:postcode":"25301",
    "sg:province":"WV",
    "sg:tags":[
        "plant",
        "flower",
        "tree",
        "artificial"
    ],
    "wof:name":"Dynamic Displays Inc",
    "wof:placetype":"venue"
},
  "geometry": {"coordinates":[-81.63359199999999,38.350754],"type":"Point"}
}