{
  "type": "Feature",
  "properties": {
    "addr:full":"303 Water St Peterstown WV 24963",
    "addr:housenumber":"303",
    "addr:postcode":"24963",
    "addr:street":"Water St",
    "iso:country":"US",
    "sg:address":"303 Water St",
    "sg:city":"Peterstown",
    "sg:classifiers":[
        {
            "category":"Professional",
            "subcategory":"Engineering",
            "type":"Services"
        }
    ],
    "sg:phone":"+1 304 753 5509",
    "sg:postcode":"24963",
    "sg:province":"WV",
    "sg:tags":[
        "engineer"
    ],
    "wof:name":"Anderson & Assoc",
    "wof:placetype":"venue"
},
  "geometry": {"coordinates":[-80.797433,37.399715],"type":"Point"}
}