{
  "type": "Feature",
  "properties": {
    "addr:full":"115 Gordon Dr Hedgesville WV 25427",
    "addr:housenumber":"115",
    "addr:postcode":"25427",
    "addr:street":"Gordon Dr",
    "iso:country":"US",
    "sg:address":"115 Gordon Dr",
    "sg:city":"Hedgesville",
    "sg:classifiers":[
        {
            "category":"Autos & Motor Vehicles",
            "subcategory":"Automobile Sales",
            "type":"Retail Goods"
        }
    ],
    "sg:phone":"+1 304 754 9166",
    "sg:postcode":"25427",
    "sg:province":"WV",
    "sg:tags":[
        "dealers-used",
        "car",
        "used",
        "cars-wholesale"
    ],
    "wof:name":"Got Your Back Pilot Cars",
    "wof:placetype":"venue"
},
  "geometry": {"coordinates":[-77.984278,39.54621],"type":"Point"}
}