{
  "type": "Feature",
  "properties": {
    "iso:country":"US",
    "sg:address":"1919 Hamill Ave",
    "sg:city":"Clarksburg",
    "sg:classifiers":[
        {
            "category":"Personal",
            "subcategory":"Beauty Salon",
            "type":"Services"
        }
    ],
    "sg:phone":"+1 304 622 4090",
    "sg:postcode":"26301",
    "sg:province":"WV",
    "wof:name":"Hair Shanty",
    "wof:placetype":"venue"
},
  "geometry": {"coordinates":[-80.35005200000001,39.293411],"type":"Point"}
}