{
  "type": "Feature",
  "properties": {
    "iso:country":"US",
    "sg:address":"5915 Ohio River Rd",
    "sg:city":"Huntington",
    "sg:classifiers":[
        {
            "category":"Professional",
            "subcategory":"Secretarial Services",
            "type":"Services"
        }
    ],
    "sg:phone":"+1 304 529 1009",
    "sg:postcode":"25702",
    "sg:province":"WV",
    "sg:tags":[
        "reporting",
        "resume",
        "typesetting"
    ],
    "wof:name":"ASAP Typing & Re'Sume' Svc",
    "wof:placetype":"venue"
},
  "geometry": {"coordinates":[-82.3163,38.446895],"type":"Point"}
}