{
  "type": "Feature",
  "properties": {
    "iso:country":"US",
    "sg:address":"1338 Ritter Dr",
    "sg:city":"Daniels",
    "sg:classifiers":[
        {
            "category":"Social Services",
            "type":"Services"
        }
    ],
    "sg:phone":"+1 304 253 5872",
    "sg:postcode":"25832",
    "sg:province":"WV",
    "sg:tags":[
        "organization",
        "welfare"
    ],
    "wof:name":"Children's Home Society Of WV",
    "wof:placetype":"venue"
},
  "geometry": {"coordinates":[-81.124157,37.74406],"type":"Point"}
}