{
  "type": "Feature",
  "properties": {
    "iso:country":"US",
    "sg:address":"123 E Main St",
    "sg:city":"Ansted",
    "sg:classifiers":[
        {
            "category":"Autos & Motor Vehicles",
            "subcategory":"Fuel & Gas Station",
            "type":"Retail Goods"
        }
    ],
    "sg:phone":"+1 304 658 9100",
    "sg:postcode":"25812",
    "sg:province":"WV",
    "sg:tags":[
        "station",
        "gasoline"
    ],
    "wof:name":"In Shell Stop",
    "wof:placetype":"venue"
},
  "geometry": {"coordinates":[-81.097527,38.135086],"type":"Point"}
}