{
  "type": "Feature",
  "properties": {
    "addr:full":"2910 Emerson Ave Parkersburg WV 26104",
    "addr:housenumber":"2910",
    "addr:postcode":"26104",
    "addr:street":"Emerson Ave",
    "iso:country":"US",
    "sg:address":"2910 Emerson Ave",
    "sg:city":"Parkersburg",
    "sg:classifiers":[
        {
            "category":"Health Services",
            "subcategory":"Doctor",
            "type":"Services"
        }
    ],
    "sg:phone":"+1 304 428 1900",
    "sg:postcode":"26104",
    "sg:province":"WV",
    "sg:tags":[
        "physician",
        "surgeon"
    ],
    "wof:name":"Emerson Health Care",
    "wof:placetype":"venue"
},
  "geometry": {"coordinates":[-81.540237,39.284202],"type":"Point"}
}