{
  "type": "Feature",
  "properties": {
    "iso:country":"US",
    "sg:address":"212 Riverside Dr",
    "sg:city":"Logan",
    "sg:classifiers":[
        {
            "category":"Restaurant",
            "type":"Food & Drink"
        }
    ],
    "sg:menulink":"http://www.allmenus.com/wv/central/214066-taco-bell/menu/",
    "sg:phone":"+1 304 752 4397",
    "sg:postcode":"25601",
    "sg:province":"WV",
    "sg:tags":[
        "mexican"
    ],
    "wof:name":"Taco Bell",
    "wof:placetype":"venue"
},
  "geometry": {"coordinates":[-81.97172500000001,37.842798],"type":"Point"}
}