{
  "type": "Feature",
  "properties": {
    "iso:country":"US",
    "sg:address":"401 Buckhannon Pike",
    "sg:city":"Clarksburg",
    "sg:classifiers":[
        {
            "category":"Food & Beverages",
            "subcategory":"Groceries & Convenience Stores",
            "type":"Retail Goods"
        }
    ],
    "sg:phone":"+1 304 623 4803",
    "sg:postcode":"26301",
    "sg:province":"WV",
    "sg:tags":[
        "grocer"
    ],
    "wof:name":"Shop & Save",
    "wof:placetype":"venue"
},
  "geometry": {"coordinates":[-80.327254,39.264761],"type":"Point"}
}