{
  "type": "Feature",
  "properties": {
    "addr:full":"37 Eagles Rd Beckley WV 25801",
    "addr:housenumber":"37",
    "addr:postcode":"25801",
    "addr:street":"Eagles Rd",
    "iso:country":"US",
    "sg:address":"37 Eagles Rd",
    "sg:city":"Beckley",
    "sg:classifiers":[
        {
            "category":"Professional",
            "type":"Services"
        }
    ],
    "sg:phone":"+1 304 255 0700",
    "sg:postcode":"25801",
    "sg:province":"WV",
    "sg:tags":[
        "establishment"
    ],
    "wof:name":"Mystic LLC",
    "wof:placetype":"venue"
},
  "geometry": {"coordinates":[-81.16221400000001,37.799396],"type":"Point"}
}