{
  "type": "Feature",
  "properties": {
    "iso:country":"US",
    "sg:address":"311 16th St",
    "sg:city":"Dunbar",
    "sg:classifiers":[
        {
            "category":"Organizations",
            "subcategory":"Religious Organization",
            "type":"Services"
        }
    ],
    "sg:phone":"+1 304 768 1891",
    "sg:postcode":"25064",
    "sg:province":"WV",
    "sg:tags":[
        "church"
    ],
    "wof:name":"First Baptist Church Of Dunbar",
    "wof:placetype":"venue"
},
  "geometry": {"coordinates":[-81.746388,38.35914],"type":"Point"}
}