{
  "type": "Feature",
  "properties": {
    "addr:full":"122 Capitol St Charleston WV 25301",
    "addr:housenumber":"122",
    "addr:postcode":"25301",
    "addr:street":"Capitol St",
    "iso:country":"US",
    "sg:address":"122 Capitol St",
    "sg:city":"Charleston",
    "sg:classifiers":[
        {
            "category":"Professional",
            "subcategory":"Lawyer & Legal Services",
            "type":"Services"
        }
    ],
    "sg:phone":"+1 304 352 4529",
    "sg:postcode":"25301",
    "sg:province":"WV",
    "sg:tags":[
        "attorney"
    ],
    "wof:name":"Patrick Lane",
    "wof:placetype":"venue"
},
  "geometry": {"coordinates":[-81.635595,38.349445],"type":"Point"}
}