{
  "type": "Feature",
  "properties": {
    "addr:full":"300 W 4th St Williamstown WV 26187",
    "addr:housenumber":"300",
    "addr:postcode":"26187",
    "addr:street":"W 4Th St",
    "iso:country":"US",
    "sg:address":"300 W 4th St",
    "sg:city":"Williamstown",
    "sg:classifiers":[
        {
            "category":"Banks & Credit Unions",
            "subcategory":"Financial Services",
            "type":"Services"
        }
    ],
    "sg:phone":"+1 304 375 7717",
    "sg:postcode":"26187",
    "sg:province":"WV",
    "sg:tags":[
        "trust",
        "management"
    ],
    "wof:name":"Jaj LLC",
    "wof:placetype":"venue"
},
  "geometry": {"coordinates":[-81.453755,39.403479],"type":"Point"}
}