{
  "type": "Feature",
  "properties": {
    "addr:full":"1 Railroad St Ripley WV 25271",
    "addr:housenumber":"1",
    "addr:postcode":"25271",
    "addr:street":"Railroad St",
    "iso:country":"US",
    "sg:address":"1 Railroad St",
    "sg:city":"Ripley",
    "sg:classifiers":[
        {
            "category":"Shopping",
            "subcategory":"Gifts & Souvenirs",
            "type":"Retail Goods"
        }
    ],
    "sg:phone":"+1 304 372 2266",
    "sg:postcode":"25271",
    "sg:province":"WV",
    "wof:name":"Millcreek Trading Co",
    "wof:placetype":"venue"
},
  "geometry": {"coordinates":[-81.71623099999999,38.819966],"type":"Point"}
}