{
  "type": "Feature",
  "properties": {
    "addr:full":"832 W 2nd St Weston WV 26452",
    "addr:housenumber":"832",
    "addr:postcode":"26452",
    "addr:street":"W 2Nd St",
    "iso:country":"US",
    "sg:address":"832 W 2nd St",
    "sg:city":"Weston",
    "sg:classifiers":[
        {
            "category":"Shopping",
            "subcategory":"Clothing, Apparel, & Fashions",
            "type":"Retail Goods"
        }
    ],
    "sg:phone":"+1 304 269 7497",
    "sg:postcode":"26452",
    "sg:province":"WV",
    "sg:tags":[
        "textile",
        "machinery",
        "mfg"
    ],
    "wof:name":"Quality TS & Sweats",
    "wof:placetype":"venue"
},
  "geometry": {"coordinates":[-80.48889699999999,39.050022],"type":"Point"}
}