{
  "type": "Feature",
  "properties": {
    "iso:country":"US",
    "sg:address":"125 18th St",
    "sg:city":"Wheeling",
    "sg:classifiers":[
        {
            "category":"Organizations",
            "subcategory":"Non-profit Organization",
            "type":"Services"
        }
    ],
    "sg:phone":"+1 304 232 7157",
    "sg:postcode":"26003",
    "sg:province":"WV",
    "wof:name":"Catholic Neighborhood Ctr",
    "wof:placetype":"venue"
},
  "geometry": {"coordinates":[-80.71657999999999,40.062703],"type":"Point"}
}