{
  "type": "Feature",
  "properties": {
    "addr:full":"1500 Maccorkle Ave SE Charleston WV 25314",
    "addr:housenumber":"1500",
    "addr:postcode":"25314",
    "addr:street":"Maccorkle Ave Se",
    "iso:country":"US",
    "sg:address":"1500 Maccorkle Ave SE",
    "sg:city":"Charleston",
    "sg:classifiers":[
        {
            "category":"Retail",
            "subcategory":"Auto Rental",
            "type":"Services"
        }
    ],
    "sg:phone":"+1 304 757 5259",
    "sg:postcode":"25314",
    "sg:province":"WV",
    "sg:tags":[
        "renting",
        "automobile"
    ],
    "wof:name":"Enterprise Rent-A-Car",
    "wof:placetype":"venue"
},
  "geometry": {"coordinates":[-81.622311,38.334018],"type":"Point"}
}