{
  "type": "Feature",
  "properties": {
    "iso:country":"US",
    "sg:address":"1315 N Lewis St",
    "sg:city":"Glenville",
    "sg:classifiers":[
        {
            "category":"Organizations",
            "subcategory":"Religious Organization",
            "type":"Services"
        }
    ],
    "sg:phone":"+1 304 462 8748",
    "sg:postcode":"26351",
    "sg:province":"WV",
    "sg:tags":[
        "church"
    ],
    "wof:name":"Little Kanawha Indpendent Chr",
    "wof:placetype":"venue"
},
  "geometry": {"coordinates":[-80.81082499999999,38.950174],"type":"Point"}
}