{
  "type": "Feature",
  "properties": {
    "iso:country":"US",
    "sg:address":"525 Cove Rd",
    "sg:city":"Weirton",
    "sg:classifiers":[
        {
            "category":"Social Services",
            "type":"Services"
        }
    ],
    "sg:phone":"+1 304 748 1427",
    "sg:postcode":"26062",
    "sg:province":"WV",
    "sg:tags":[
        "support",
        "group"
    ],
    "wof:name":"Family Service Geriatric In HM",
    "wof:placetype":"venue"
},
  "geometry": {"coordinates":[-80.581422,40.401485],"type":"Point"}
}