{
  "type": "Feature",
  "properties": {
    "iso:country":"US",
    "sg:address":"315 Morgantown Ave",
    "sg:city":"Fairmont",
    "sg:classifiers":[
        {
            "category":"Autos & Motor Vehicles",
            "subcategory":"Automobile Sales",
            "type":"Retail Goods"
        }
    ],
    "sg:phone":"+1 304 363 6157",
    "sg:postcode":"26554",
    "sg:province":"WV",
    "sg:tags":[
        "dealers-used",
        "car",
        "used",
        "cars-wholesale",
        "new"
    ],
    "wof:name":"S & S Auto Sales",
    "wof:placetype":"venue"
},
  "geometry": {"coordinates":[-80.132752,39.480407],"type":"Point"}
}