{
  "type": "Feature",
  "properties": {
    "iso:country":"US",
    "sg:address":"1021 Stafford Dr",
    "sg:city":"Princeton",
    "sg:classifiers":[
        {
            "category":"Insurance",
            "subcategory":"Insurance Agent",
            "type":"Services"
        }
    ],
    "sg:phone":"+1 304 325 2160",
    "sg:postcode":"24740",
    "sg:province":"WV",
    "wof:name":"Guardian Insurance Co",
    "wof:placetype":"venue"
},
  "geometry": {"coordinates":[-81.092275,37.364626],"type":"Point"}
}