{
  "type": "Feature",
  "properties": {
    "iso:country":"US",
    "sg:address":"2000 Eoff St",
    "sg:city":"Wheeling",
    "sg:classifiers":[
        {
            "category":"Professional",
            "type":"Services"
        }
    ],
    "sg:phone":"+1 304 234 8519",
    "sg:postcode":"26003",
    "sg:province":"WV",
    "sg:tags":[
        "establishment"
    ],
    "wof:name":"Sexual Assault Help Ctr",
    "wof:placetype":"venue"
},
  "geometry": {"coordinates":[-80.721739,40.059332],"type":"Point"}
}