{
  "type": "Feature",
  "properties": {
    "iso:country":"US",
    "sg:address":"54 Ansley Ct",
    "sg:city":"Inwood",
    "sg:classifiers":[
        {
            "category":"Building & Trades",
            "subcategory":"Construction",
            "type":"Services"
        }
    ],
    "sg:phone":"+1 304 229 5541",
    "sg:postcode":"25428",
    "sg:province":"WV",
    "sg:tags":[
        "residential"
    ],
    "wof:name":"Arndt Contracting",
    "wof:placetype":"venue"
},
  "geometry": {"coordinates":[-78.076686,39.402065],"type":"Point"}
}