{
  "type": "Feature",
  "properties": {
    "addr:full":"401 Kingmont Rd Fairmont WV 26554",
    "addr:housenumber":"401",
    "addr:postcode":"26554",
    "addr:street":"Kingmont Rd",
    "iso:country":"US",
    "sg:address":"401 Kingmont Rd",
    "sg:city":"Fairmont",
    "sg:classifiers":[
        {
            "category":"Government",
            "subcategory":"Office",
            "type":"Public Place"
        }
    ],
    "sg:phone":"+1 304 363 2400",
    "sg:postcode":"26554",
    "sg:province":"WV",
    "sg:tags":[
        "village"
    ],
    "wof:name":"Pleasant Valley City Office",
    "wof:placetype":"venue"
},
  "geometry": {"coordinates":[-80.17778,39.448162],"type":"Point"}
}