{
  "type": "Feature",
  "properties": {
    "addr:full":"183 Homewood Ave Fairmont WV 26554",
    "addr:housenumber":"183",
    "addr:postcode":"26554",
    "addr:street":"Homewood Ave",
    "iso:country":"US",
    "sg:address":"183 Homewood Ave",
    "sg:city":"Fairmont",
    "sg:classifiers":[
        {
            "category":"Autos & Motor Vehicles",
            "subcategory":"Automobile Sales",
            "type":"Retail Goods"
        }
    ],
    "sg:phone":"+1 304 366 3980",
    "sg:postcode":"26554",
    "sg:province":"WV",
    "sg:tags":[
        "car",
        "dealer"
    ],
    "wof:name":"Smallwood's Used Cars",
    "wof:placetype":"venue"
},
  "geometry": {"coordinates":[-80.126256,39.474685],"type":"Point"}
}