{
  "type": "Feature",
  "properties": {
    "iso:country":"US",
    "sg:address":"307 Adams St",
    "sg:city":"Montgomery",
    "sg:classifiers":[
        {
            "category":"Government",
            "subcategory":"Office",
            "type":"Public Place"
        }
    ],
    "sg:phone":"+1 304 442 5834",
    "sg:postcode":"25136",
    "sg:province":"WV",
    "sg:tags":[
        "federal",
        "human"
    ],
    "wof:name":"US Social Security Adm",
    "wof:placetype":"venue"
},
  "geometry": {"coordinates":[-81.32536500000001,38.181085],"type":"Point"}
}