{
  "type": "Feature",
  "properties": {
    "addr:full":"118 Carolina Ave Chester WV 26034",
    "addr:housenumber":"118",
    "addr:postcode":"26034",
    "addr:street":"Carolina Ave",
    "iso:country":"US",
    "sg:address":"118 Carolina Ave",
    "sg:city":"Chester",
    "sg:classifiers":[
        {
            "category":"Health Services",
            "subcategory":"Doctor",
            "type":"Services"
        }
    ],
    "sg:phone":"+1 304 387 0409",
    "sg:postcode":"26034",
    "sg:province":"WV",
    "sg:tags":[
        "medical"
    ],
    "wof:name":"Mercado Milagros L",
    "wof:placetype":"venue"
},
  "geometry": {"coordinates":[-80.573155,40.609586],"type":"Point"}
}