{
  "type": "Feature",
  "properties": {
    "addr:full":"6 N Walnut St Philippi WV 26416",
    "addr:housenumber":"6",
    "addr:postcode":"26416",
    "addr:street":"N Walnut St",
    "iso:country":"US",
    "sg:address":"6 N Walnut St",
    "sg:city":"Philippi",
    "sg:classifiers":[
        {
            "category":"Personal",
            "subcategory":"Beauty Salon",
            "type":"Services"
        }
    ],
    "sg:phone":"+1 304 457 2354",
    "sg:postcode":"26416",
    "sg:province":"WV",
    "sg:tags":[
        "shop"
    ],
    "wof:name":"Hair Works",
    "wof:placetype":"venue"
},
  "geometry": {"coordinates":[-80.039214,39.153142],"type":"Point"}
}