{
  "type": "Feature",
  "properties": {
    "addr:full":"100 Railroad Ave Sophia WV 25801",
    "addr:housenumber":"100",
    "addr:postcode":"25801",
    "addr:street":"Railroad Ave",
    "iso:country":"US",
    "sg:address":"100 Railroad Ave",
    "sg:city":"Sophia",
    "sg:classifiers":[
        {
            "category":"Government",
            "subcategory":"Office",
            "type":"Public Place"
        }
    ],
    "sg:phone":"+1 304 683 4456",
    "sg:postcode":"25801",
    "sg:province":"WV",
    "sg:tags":[
        "city"
    ],
    "wof:name":"Sophia Mayor's Office",
    "wof:placetype":"venue"
},
  "geometry": {"coordinates":[-81.247958,37.706894],"type":"Point"}
}