{
  "type": "Feature",
  "properties": {
    "iso:country":"US",
    "sg:address":"6433 US Hwy 60",
    "sg:city":"Barboursville",
    "sg:classifiers":[
        {
            "category":"Building & Trades",
            "subcategory":"Cleaning & Sanitation",
            "type":"Services"
        }
    ],
    "sg:phone":"+1 304 733 2549",
    "sg:postcode":"25504",
    "sg:province":"WV",
    "sg:tags":[
        "janitor"
    ],
    "sg:website":"www.dirtbusterswv.com",
    "wof:name":"Dirtbusters Services",
    "wof:placetype":"venue"
},
  "geometry": {"coordinates":[-82.297938,38.415145],"type":"Point"}
}