{
  "type": "Feature",
  "properties": {
    "iso:country":"US",
    "sg:address":"1140 Steeplechase Dr",
    "sg:city":"Morgantown",
    "sg:classifiers":[
        {
            "category":"Banks & Credit Unions",
            "subcategory":"Financial Services",
            "type":"Services"
        }
    ],
    "sg:phone":"+1 304 594 0793",
    "sg:postcode":"26508",
    "sg:province":"WV",
    "sg:tags":[
        "company",
        "holding"
    ],
    "wof:name":"Nextgen Holdings LLC",
    "wof:placetype":"venue"
},
  "geometry": {"coordinates":[-79.881432,39.650093],"type":"Point"}
}