{
  "type": "Feature",
  "properties": {
    "addr:full":"4415 Maccorkle Ave SE Charleston WV 25304",
    "addr:housenumber":"4415",
    "addr:postcode":"25304",
    "addr:street":"Maccorkle Ave Se",
    "iso:country":"US",
    "sg:address":"4415 Maccorkle Ave SE",
    "sg:city":"Charleston",
    "sg:classifiers":[
        {
            "category":"Health Services",
            "subcategory":"Doctor",
            "type":"Services"
        }
    ],
    "sg:phone":"+1 304 346 1022",
    "sg:postcode":"25304",
    "sg:province":"WV",
    "sg:tags":[
        "clinic"
    ],
    "wof:name":"NEU Aesthetic Clinic",
    "wof:placetype":"venue"
},
  "geometry": {"coordinates":[-81.584521,38.322988],"type":"Point"}
}