{
  "type": "Feature",
  "properties": {
    "addr:full":"1031 National Rd Wheeling WV 26003",
    "addr:housenumber":"1031",
    "addr:postcode":"26003",
    "addr:street":"National Rd",
    "iso:country":"US",
    "sg:address":"1031 National Rd",
    "sg:city":"Wheeling",
    "sg:classifiers":[
        {
            "category":"Real Estate",
            "subcategory":"Real Estate Agent",
            "type":"Services"
        }
    ],
    "sg:phone":"+1 304 242 0800",
    "sg:postcode":"26003",
    "sg:province":"WV",
    "wof:name":"Joseph Realty",
    "wof:placetype":"venue"
},
  "geometry": {"coordinates":[-80.69056,40.077881],"type":"Point"}
}