{
  "type": "Feature",
  "properties": {
    "iso:country":"US",
    "sg:address":"106 Bellewood Ln",
    "sg:city":"Beckley",
    "sg:classifiers":[
        {
            "category":"Freight",
            "type":"Transportation"
        }
    ],
    "sg:phone":"+1 304 252 6797",
    "sg:postcode":"25801",
    "sg:province":"WV",
    "sg:tags":[
        "mini",
        "rental"
    ],
    "wof:name":"Rural Acres Mini-Storage",
    "wof:placetype":"venue"
},
  "geometry": {"coordinates":[-81.20295900000001,37.812194],"type":"Point"}
}