{
  "type": "Feature",
  "properties": {
    "iso:country":"US",
    "sg:address":"2425 Us Route 60",
    "sg:city":"Hurricane",
    "sg:classifiers":[
        {
            "category":"Ice Cream",
            "type":"Food & Drink"
        }
    ],
    "sg:menulink":"http://www.allmenus.com/wv/curry/192401-dairy-queen/menu/",
    "sg:phone":"+1 304 562 6421",
    "sg:postcode":"25526",
    "sg:province":"WV",
    "sg:tags":[
        "burger",
        "american"
    ],
    "wof:name":"Dairy Queen",
    "wof:placetype":"venue"
},
  "geometry": {"coordinates":[-82.03205800000001,38.418943],"type":"Point"}
}