{
  "type": "Feature",
  "properties": {
    "addr:full":"2123 University Ave Morgantown WV 26505",
    "addr:housenumber":"2123",
    "addr:postcode":"26505",
    "addr:street":"University Ave",
    "iso:country":"US",
    "sg:address":"2123 University Ave",
    "sg:city":"Morgantown",
    "sg:classifiers":[
        {
            "category":"Real Estate",
            "subcategory":"Real Estate Operator",
            "type":"Services"
        }
    ],
    "sg:phone":"+1 304 296 7400",
    "sg:postcode":"26505",
    "sg:province":"WV",
    "sg:tags":[
        "apartment"
    ],
    "wof:name":"Scott Properties LLC",
    "wof:placetype":"venue"
},
  "geometry": {"coordinates":[-79.95586299999999,39.639923],"type":"Point"}
}