{
  "type": "Feature",
  "properties": {
    "iso:country":"US",
    "sg:address":"210 N Sturmer St",
    "sg:city":"Belington",
    "sg:classifiers":[
        {
            "category":"Health Services",
            "subcategory":"Doctor",
            "type":"Services"
        }
    ],
    "sg:phone":"+1 304 823 2800",
    "sg:postcode":"26250",
    "sg:province":"WV",
    "sg:tags":[
        "clinic",
        "medical"
    ],
    "wof:name":"Belington Medical Clinic",
    "wof:placetype":"venue"
},
  "geometry": {"coordinates":[-79.938535,39.02813],"type":"Point"}
}