{
  "type": "Feature",
  "properties": {
    "addr:full":"435 Stratton St Logan WV 25601",
    "addr:housenumber":"435",
    "addr:postcode":"25601",
    "addr:street":"Stratton St",
    "iso:country":"US",
    "sg:address":"435 Stratton St",
    "sg:city":"Logan",
    "sg:classifiers":[
        {
            "category":"Manufacturing",
            "subcategory":"Printing",
            "type":"Manufacturing & Wholesale Goods"
        }
    ],
    "sg:phone":"+1 304 752 6950",
    "sg:postcode":"25601",
    "sg:province":"WV",
    "sg:tags":[
        "newspaper"
    ],
    "sg:website":"www.loganbanner.com",
    "wof:name":"Logan Banner",
    "wof:placetype":"venue"
},
  "geometry": {"coordinates":[-81.989052,37.846545],"type":"Point"}
}