{
  "type": "Feature",
  "properties": {
    "iso:country":"US",
    "sg:address":"105 Union St",
    "sg:city":"West Union",
    "sg:classifiers":[
        {
            "category":"Banks & Credit Unions",
            "subcategory":"Bank",
            "type":"Services"
        }
    ],
    "sg:phone":"+1 304 873 2361",
    "sg:postcode":"26456",
    "sg:province":"WV",
    "sg:website":"www.westunionbank.com",
    "wof:name":"West Union Bank",
    "wof:placetype":"venue"
},
  "geometry": {"coordinates":[-80.76811600000001,39.292603],"type":"Point"}
}