{
  "type": "Feature",
  "properties": {
    "iso:country":"US",
    "sg:address":"202 Mc Graw Ave",
    "sg:city":"Grafton",
    "sg:classifiers":[
        {
            "category":"Retail",
            "subcategory":"Funeral Services",
            "type":"Services"
        }
    ],
    "sg:phone":"+1 304 265 0489",
    "sg:postcode":"26354",
    "sg:province":"WV",
    "sg:tags":[
        "director"
    ],
    "wof:name":"Bartlett Funeral Home",
    "wof:placetype":"venue"
},
  "geometry": {"coordinates":[-80.02850100000001,39.33869],"type":"Point"}
}