{
  "type": "Feature",
  "properties": {
    "iso:country":"US",
    "sg:address":"801 E State Ave",
    "sg:city":"Terra Alta",
    "sg:classifiers":[
        {
            "category":"Shopping",
            "subcategory":"Pharmacy",
            "type":"Retail Goods"
        }
    ],
    "sg:phone":"+1 304 789 5898",
    "sg:postcode":"26764",
    "sg:province":"WV",
    "sg:tags":[
        "drug",
        "store"
    ],
    "wof:name":"Rite Aid",
    "wof:placetype":"venue"
},
  "geometry": {"coordinates":[-79.54057400000001,39.443756],"type":"Point"}
}