{
  "type": "Feature",
  "properties": {
    "addr:full":"801 Dunbar Ave Dunbar WV 25064",
    "addr:housenumber":"801",
    "addr:postcode":"25064",
    "addr:street":"Dunbar Ave",
    "iso:country":"US",
    "sg:address":"801 Dunbar Ave",
    "sg:city":"Dunbar",
    "sg:classifiers":[
        {
            "category":"Insurance",
            "subcategory":"Insurance Agent",
            "type":"Services"
        }
    ],
    "sg:phone":"+1 304 766 7166",
    "sg:postcode":"25064",
    "sg:province":"WV",
    "wof:name":"State Farm Insurance",
    "wof:placetype":"venue"
},
  "geometry": {"coordinates":[-81.732389,38.360431],"type":"Point"}
}