{
  "type": "Feature",
  "properties": {
    "addr:full":"2889 3rd Ave Huntington WV 25702",
    "addr:housenumber":"2889",
    "addr:postcode":"25702",
    "addr:street":"3Rd Ave",
    "iso:country":"US",
    "sg:address":"2889 3rd Ave",
    "sg:city":"Huntington",
    "sg:classifiers":[
        {
            "category":"Banks & Credit Unions",
            "subcategory":"Bank",
            "type":"Services"
        }
    ],
    "sg:phone":"+1 304 781 2362",
    "sg:postcode":"25702",
    "sg:province":"WV",
    "sg:website":"www.unitedbank.com",
    "wof:name":"United Bank",
    "wof:placetype":"venue"
},
  "geometry": {"coordinates":[-82.401056,38.429238],"type":"Point"}
}