{
  "type": "Feature",
  "properties": {
    "iso:country":"US",
    "sg:address":"105 Washington St",
    "sg:city":"Paden City",
    "sg:classifiers":[
        {
            "category":"Professional",
            "subcategory":"Accounting & Tax Preparation",
            "type":"Services"
        }
    ],
    "sg:phone":"+1 304 337 8488",
    "sg:postcode":"26159",
    "sg:province":"WV",
    "sg:tags":[
        "return",
        "filing"
    ],
    "wof:name":"Huffman Tax Svc Inc",
    "wof:placetype":"venue"
},
  "geometry": {"coordinates":[-80.93926999999999,39.600366],"type":"Point"}
}