{
  "type": "Feature",
  "properties": {
    "addr:full":"314 College Ave Bluefield WV 24701",
    "addr:housenumber":"314",
    "addr:postcode":"24701",
    "addr:street":"College Ave",
    "iso:country":"US",
    "sg:address":"314 College Ave",
    "sg:city":"Bluefield",
    "sg:classifiers":[
        {
            "category":"Insurance",
            "subcategory":"Insurance Agent",
            "type":"Services"
        }
    ],
    "sg:phone":"+1 304 327 7631",
    "sg:postcode":"24701",
    "sg:province":"WV",
    "wof:name":"State Farm Insurance",
    "wof:placetype":"venue"
},
  "geometry": {"coordinates":[-81.219747,37.256454],"type":"Point"}
}