{
  "type": "Feature",
  "properties": {
    "iso:country":"US",
    "sg:address":"220 Denese Dr",
    "sg:city":"Weirton",
    "sg:classifiers":[
        {
            "category":"Organizations",
            "subcategory":"Religious Organization",
            "type":"Services"
        }
    ],
    "sg:phone":"+1 304 723 5581",
    "sg:postcode":"26062",
    "sg:province":"WV",
    "sg:tags":[
        "clergy"
    ],
    "wof:name":"Robert Tate",
    "wof:placetype":"venue"
},
  "geometry": {"coordinates":[-80.524348,40.406308],"type":"Point"}
}