{
  "type": "Feature",
  "properties": {
    "iso:country":"US",
    "sg:address":"624 Stanaford Rd",
    "sg:city":"Beckley",
    "sg:classifiers":[
        {
            "category":"Wholesale",
            "subcategory":"Machinery & Supplies",
            "type":"Manufacturing & Wholesale Goods"
        }
    ],
    "sg:phone":"+1 304 254 0443",
    "sg:postcode":"25801",
    "sg:province":"WV",
    "sg:tags":[
        "industrial"
    ],
    "wof:name":"Motion Industries Inc",
    "wof:placetype":"venue"
},
  "geometry": {"coordinates":[-81.16259100000001,37.806849],"type":"Point"}
}