{
  "type": "Feature",
  "properties": {
    "addr:full":"834 Adams Ave Huntington WV 25704",
    "addr:housenumber":"834",
    "addr:postcode":"25704",
    "addr:street":"Adams Ave",
    "iso:country":"US",
    "sg:address":"834 Adams Ave",
    "sg:city":"Huntington",
    "sg:classifiers":[
        {
            "category":"Freight",
            "type":"Transportation"
        }
    ],
    "sg:phone":"+1 304 523 6573",
    "sg:postcode":"25704",
    "sg:province":"WV",
    "sg:tags":[
        "commercial",
        "storage"
    ],
    "wof:name":"Rollyson's Car Wash & Mini",
    "wof:placetype":"venue"
},
  "geometry": {"coordinates":[-82.470484,38.414436],"type":"Point"}
}