{
  "type": "Feature",
  "properties": {
    "iso:country":"US",
    "sg:address":"1404 Morgantown Ave",
    "sg:city":"Fairmont",
    "sg:classifiers":[
        {
            "category":"Wholesale",
            "subcategory":"Hardware",
            "type":"Manufacturing & Wholesale Goods"
        }
    ],
    "sg:phone":"+1 304 366 4943",
    "sg:postcode":"26554",
    "sg:province":"WV",
    "sg:tags":[
        "refrigerating"
    ],
    "wof:name":"Bob Freme Refrigeration",
    "wof:placetype":"venue"
},
  "geometry": {"coordinates":[-80.11645300000001,39.481873],"type":"Point"}
}