{
  "type": "Feature",
  "properties": {
    "iso:country":"US",
    "sg:address":"422 Shrewsbury St",
    "sg:city":"Charleston",
    "sg:classifiers":[
        {
            "category":"Insurance",
            "subcategory":"Insurance Agent",
            "type":"Services"
        }
    ],
    "sg:phone":"+1 304 345 8300",
    "sg:postcode":"25301",
    "sg:province":"WV",
    "wof:name":"Insurance R Us Agency",
    "wof:placetype":"venue"
},
  "geometry": {"coordinates":[-81.62949,38.35076],"type":"Point"}
}