{
  "type": "Feature",
  "properties": {
    "iso:country":"US",
    "sg:address":"1329 Old Courthouse Sq",
    "sg:city":"Martinsburg",
    "sg:classifiers":[
        {
            "category":"Retail",
            "subcategory":"Laundry & Dry Cleaning",
            "type":"Services"
        }
    ],
    "sg:phone":"+1 304 263 2872",
    "sg:postcode":"25401",
    "sg:province":"WV",
    "sg:tags":[
        "cleaners"
    ],
    "wof:name":"Quality Cleaners",
    "wof:placetype":"venue"
},
  "geometry": {"coordinates":[-77.95693799999999,39.47391],"type":"Point"}
}