{
  "type": "Feature",
  "properties": {
    "iso:country":"US",
    "sg:address":"328 Washington St",
    "sg:city":"Newell",
    "sg:classifiers":[
        {
            "category":"Restaurant",
            "type":"Food & Drink"
        }
    ],
    "sg:phone":"+1 304 387 3100",
    "sg:postcode":"26050",
    "sg:province":"WV",
    "wof:name":"Soups On",
    "wof:placetype":"venue"
},
  "geometry": {"coordinates":[-80.59991599999999,40.61896],"type":"Point"}
}