{
  "type": "Feature",
  "properties": {
    "addr:full":"1916 Jefferson St Bluefield WV 24701",
    "addr:housenumber":"1916",
    "addr:postcode":"24701",
    "addr:street":"Jefferson St",
    "iso:country":"US",
    "sg:address":"1916 Jefferson St",
    "sg:city":"Bluefield",
    "sg:classifiers":[
        {
            "category":"Social Services",
            "type":"Services"
        }
    ],
    "sg:phone":"+1 304 327 9181",
    "sg:postcode":"24701",
    "sg:province":"WV",
    "sg:tags":[
        "organization",
        "welfare"
    ],
    "wof:name":"Mothers Against Drunk Driving",
    "wof:placetype":"venue"
},
  "geometry": {"coordinates":[-81.219083,37.255984],"type":"Point"}
}