{
  "type": "Feature",
  "properties": {
    "addr:full":"1005 5th St W Huntington WV 25701",
    "addr:housenumber":"1005",
    "addr:postcode":"25701",
    "addr:street":"5Th St W",
    "iso:country":"US",
    "sg:address":"1005 5th St W",
    "sg:city":"Huntington",
    "sg:classifiers":[
        {
            "category":"Social Services",
            "type":"Services"
        }
    ],
    "sg:phone":"+1 304 523 9673",
    "sg:postcode":"25701",
    "sg:province":"WV",
    "wof:name":"Word House",
    "wof:placetype":"venue"
},
  "geometry": {"coordinates":[-82.46047299999999,38.407245],"type":"Point"}
}