{
  "type": "Feature",
  "properties": {
    "addr:full":"37 S Mill Ave Mount Hope WV 25880",
    "addr:housenumber":"37",
    "addr:postcode":"25880",
    "addr:street":"S Mill Ave",
    "iso:country":"US",
    "sg:address":"37 S Mill Ave",
    "sg:city":"Mount Hope",
    "sg:classifiers":[
        {
            "category":"Shopping",
            "subcategory":"Clothing, Apparel, & Fashions",
            "type":"Retail Goods"
        }
    ],
    "sg:phone":"+1 304 254 0318",
    "sg:postcode":"25880",
    "sg:province":"WV",
    "sg:tags":[
        "style",
        "family"
    ],
    "wof:name":"American Eagle Outfitters",
    "wof:placetype":"venue"
},
  "geometry": {"coordinates":[-81.16901900000001,37.891876],"type":"Point"}
}