{
  "type": "Feature",
  "properties": {
    "iso:country":"US",
    "sg:address":"2 Forest Park",
    "sg:city":"Wheeling",
    "sg:classifiers":[
        {
            "category":"Personal",
            "subcategory":"Beauty Salon",
            "type":"Services"
        }
    ],
    "sg:phone":"+1 304 233 1737",
    "sg:postcode":"26003",
    "sg:province":"WV",
    "wof:name":"LA Boutique",
    "wof:placetype":"venue"
},
  "geometry": {"coordinates":[-80.70592499999999,40.053121],"type":"Point"}
}