{
  "type": "Feature",
  "properties": {
    "addr:full":"304 Venture Dr Morgantown WV 26508",
    "addr:housenumber":"304",
    "addr:postcode":"26508",
    "addr:street":"Venture Dr",
    "iso:country":"US",
    "sg:address":"304 Venture Dr",
    "sg:city":"Morgantown",
    "sg:classifiers":[
        {
            "category":"Ice Cream",
            "type":"Food & Drink"
        }
    ],
    "sg:menulink":"http://www.allmenus.com/wv/eastern/209444-tcby/menu/",
    "sg:phone":"+1 304 292 5375",
    "sg:postcode":"26508",
    "sg:province":"WV",
    "sg:tags":[
        "smoothy",
        "juice",
        "american"
    ],
    "wof:name":"TCBY",
    "wof:placetype":"venue"
},
  "geometry": {"coordinates":[-79.89942600000001,39.649051],"type":"Point"}
}