{
  "type": "Feature",
  "properties": {
    "addr:full":"3045 Martha Rd Barboursville WV 25504",
    "addr:housenumber":"3045",
    "addr:postcode":"25504",
    "addr:street":"Martha Rd",
    "iso:country":"US",
    "sg:address":"3045 Martha Rd",
    "sg:city":"Barboursville",
    "sg:classifiers":[
        {
            "category":"Organizations",
            "subcategory":"Religious Organization",
            "type":"Services"
        }
    ],
    "sg:phone":"+1 304 736 1793",
    "sg:postcode":"25504",
    "sg:province":"WV",
    "sg:tags":[
        "church"
    ],
    "wof:name":"Elmwood Baptist Church",
    "wof:placetype":"venue"
},
  "geometry": {"coordinates":[-82.28406200000001,38.381616],"type":"Point"}
}