{
  "type": "Feature",
  "properties": {
    "iso:country":"US",
    "sg:address":"1517 Fairmont Ave",
    "sg:city":"Fairmont",
    "sg:classifiers":[
        {
            "category":"Wholesale",
            "subcategory":"Electrical",
            "type":"Manufacturing & Wholesale Goods"
        }
    ],
    "sg:phone":"+1 304 366 0711",
    "sg:postcode":"26554",
    "sg:province":"WV",
    "sg:tags":[
        "equipment",
        "electric",
        "supply"
    ],
    "wof:name":"V & W Electrical Sales & Supls",
    "wof:placetype":"venue"
},
  "geometry": {"coordinates":[-80.15990600000001,39.463885],"type":"Point"}
}