{
  "type": "Feature",
  "properties": {
    "iso:country":"US",
    "sg:address":"1120 Poplar St",
    "sg:city":"Kenova",
    "sg:classifiers":[
        {
            "category":"Organizations",
            "subcategory":"Religious Organization",
            "type":"Services"
        }
    ],
    "sg:phone":"+1 304 453 1811",
    "sg:postcode":"25530",
    "sg:province":"WV",
    "sg:tags":[
        "church"
    ],
    "sg:website":"www.firstbaptistonline.org",
    "wof:name":"First Baptist Church Of Kenova",
    "wof:placetype":"venue"
},
  "geometry": {"coordinates":[-82.573275,38.398679],"type":"Point"}
}