{
  "type": "Feature",
  "properties": {
    "iso:country":"US",
    "sg:address":"1917 Washington Blvd",
    "sg:city":"Huntington",
    "sg:classifiers":[
        {
            "category":"Real Estate",
            "subcategory":"Real Estate Operator",
            "type":"Services"
        }
    ],
    "sg:phone":"+1 304 525 1806",
    "sg:postcode":"25701",
    "sg:province":"WV",
    "sg:tags":[
        "building",
        "device",
        "apartment",
        "amusement"
    ],
    "wof:name":"G and L Land Co",
    "wof:placetype":"venue"
},
  "geometry": {"coordinates":[-82.41742499999999,38.401943],"type":"Point"}
}