{
  "type": "Feature",
  "properties": {
    "addr:full":"1151 Courtland Rd Weirton WV 26062",
    "addr:housenumber":"1151",
    "addr:postcode":"26062",
    "addr:street":"Courtland Rd",
    "iso:country":"US",
    "sg:address":"1151 Courtland Rd",
    "sg:city":"Weirton",
    "sg:classifiers":[
        {
            "category":"Autos & Motor Vehicles",
            "subcategory":"Boat Sales",
            "type":"Retail Goods"
        }
    ],
    "sg:phone":"+1 304 748 1672",
    "sg:postcode":"26062",
    "sg:province":"WV",
    "sg:tags":[
        "accessory"
    ],
    "wof:name":"Weirton Boat Sales Inc",
    "wof:placetype":"venue"
},
  "geometry": {"coordinates":[-80.607882,40.395195],"type":"Point"}
}