{
  "type": "Feature",
  "properties": {
    "addr:full":"30 Capitol St Charleston WV 25301",
    "addr:housenumber":"30",
    "addr:postcode":"25301",
    "addr:street":"Capitol St",
    "iso:country":"US",
    "sg:address":"30 Capitol St",
    "sg:city":"Charleston",
    "sg:classifiers":[
        {
            "category":"Professional",
            "subcategory":"Lawyer & Legal Services",
            "type":"Services"
        }
    ],
    "sg:phone":"+1 304 345 1700",
    "sg:postcode":"25301",
    "sg:province":"WV",
    "sg:tags":[
        "attorney"
    ],
    "wof:name":"Bell & Bands",
    "wof:placetype":"venue"
},
  "geometry": {"coordinates":[-81.63663,38.348694],"type":"Point"}
}