{
  "type": "Feature",
  "properties": {
    "iso:country":"US",
    "sg:address":"1600 Murdoch Ave",
    "sg:city":"Parkersburg",
    "sg:classifiers":[
        {
            "category":"Social Services",
            "subcategory":"Child Care",
            "type":"Services"
        }
    ],
    "sg:phone":"+1 304 422 5416",
    "sg:postcode":"26101",
    "sg:province":"WV",
    "sg:tags":[
        "school"
    ],
    "wof:name":"De Sales Heights Academy",
    "wof:placetype":"venue"
},
  "geometry": {"coordinates":[-81.553543,39.2763],"type":"Point"}
}