{
  "type": "Feature",
  "properties": {
    "iso:country":"US",
    "sg:address":"1960 Main St",
    "sg:city":"Follansbee",
    "sg:classifiers":[
        {
            "category":"Building & Trades",
            "subcategory":"Construction",
            "type":"Services"
        }
    ],
    "sg:phone":"+1 304 527 5070",
    "sg:postcode":"26037",
    "sg:province":"WV",
    "sg:tags":[
        "nonresidential"
    ],
    "wof:name":"Mashuda Corp",
    "wof:placetype":"venue"
},
  "geometry": {"coordinates":[-80.59604,40.33522],"type":"Point"}
}