{
  "type": "Feature",
  "properties": {
    "addr:full":"1 Waterfront Pl Morgantown WV 26501",
    "addr:housenumber":"1",
    "addr:postcode":"26501",
    "addr:street":"Waterfront Pl",
    "iso:country":"US",
    "sg:address":"1 Waterfront Pl",
    "sg:city":"Morgantown",
    "sg:classifiers":[
        {
            "category":"Science Facility",
            "type":"Public Place"
        }
    ],
    "sg:phone":"+1 304 293 3792",
    "sg:postcode":"26501",
    "sg:province":"WV",
    "sg:tags":[
        "development",
        "laboratories-research"
    ],
    "sg:website":"http://www.wvit.wvnet.edu",
    "wof:name":"Environmental Health & Safety",
    "wof:placetype":"venue"
},
  "geometry": {"coordinates":[-79.963013,39.624081],"type":"Point"}
}