{
  "type": "Feature",
  "properties": {
    "iso:country":"US",
    "sg:address":"343 Pond Rd",
    "sg:city":"Morgantown",
    "sg:classifiers":[
        {
            "category":"Organizations",
            "subcategory":"Labor Organization",
            "type":"Services"
        }
    ],
    "sg:phone":"+1 304 292 7105",
    "sg:postcode":"26508",
    "sg:province":"WV",
    "wof:name":"Highland Dove Releases LLC",
    "wof:placetype":"venue"
},
  "geometry": {"coordinates":[-79.885464,39.533387],"type":"Point"}
}