{
  "type": "Feature",
  "properties": {
    "iso:country":"US",
    "sg:address":"332 Campbells Creek Dr",
    "sg:city":"Charleston",
    "sg:classifiers":[
        {
            "category":"Food & Beverages",
            "subcategory":"Groceries & Convenience Stores",
            "type":"Retail Goods"
        }
    ],
    "sg:phone":"+1 304 925 7593",
    "sg:postcode":"25306",
    "sg:province":"WV",
    "sg:tags":[
        "grocer"
    ],
    "wof:name":"Campbells Creek Food Shop",
    "wof:placetype":"venue"
},
  "geometry": {"coordinates":[-81.535546,38.313855],"type":"Point"}
}