{
  "type": "Feature",
  "properties": {
    "iso:country":"US",
    "sg:address":"105 Mercer Ave",
    "sg:city":"Matoaka",
    "sg:classifiers":[
        {
            "category":"Professional",
            "subcategory":"Computer Services",
            "type":"Services"
        }
    ],
    "sg:phone":"+1 304 467 7856",
    "sg:postcode":"24736",
    "sg:province":"WV",
    "sg:tags":[
        "development",
        "software"
    ],
    "wof:name":"Coal Software and Systems Inc",
    "wof:placetype":"venue"
},
  "geometry": {"coordinates":[-81.244175,37.420438],"type":"Point"}
}