{
  "type": "Feature",
  "properties": {
    "iso:country":"US",
    "sg:address":"121 Central Ave",
    "sg:city":"Oak Hill",
    "sg:classifiers":[
        {
            "category":"Shopping",
            "subcategory":"Used Merchandise",
            "type":"Retail Goods"
        }
    ],
    "sg:phone":"+1 304 469 4331",
    "sg:postcode":"25901",
    "sg:province":"WV",
    "sg:tags":[
        "shop",
        "sporting",
        "pawnbroker",
        "pawn"
    ],
    "wof:name":"Roy's Loans & Sporting Goods",
    "wof:placetype":"venue"
},
  "geometry": {"coordinates":[-81.147263,37.974206],"type":"Point"}
}