{
  "type": "Feature",
  "properties": {
    "addr:full":"2645 Charles St Wellsburg WV 26070",
    "addr:housenumber":"2645",
    "addr:postcode":"26070",
    "addr:street":"Charles St",
    "iso:country":"US",
    "sg:address":"2645 Charles St",
    "sg:city":"Wellsburg",
    "sg:classifiers":[
        {
            "category":"Shopping",
            "subcategory":"Florist",
            "type":"Retail Goods"
        }
    ],
    "sg:phone":"+1 304 737 4844",
    "sg:postcode":"26070",
    "sg:province":"WV",
    "wof:name":"Jackies Florist",
    "wof:placetype":"venue"
},
  "geometry": {"coordinates":[-80.61076799999999,40.288523],"type":"Point"}
}