{
  "type": "Feature",
  "properties": {
    "iso:country":"US",
    "sg:address":"2660 5th Ave",
    "sg:city":"Huntington",
    "sg:classifiers":[
        {
            "category":"Restaurant",
            "type":"Food & Drink"
        }
    ],
    "sg:phone":"+1 304 525 6194",
    "sg:postcode":"25702",
    "sg:province":"WV",
    "sg:tags":[
        "parlor",
        "ice",
        "cream"
    ],
    "wof:name":"Dairy Queen",
    "wof:placetype":"venue"
},
  "geometry": {"coordinates":[-82.405591,38.426045],"type":"Point"}
}