{
  "type": "Feature",
  "properties": {
    "iso:country":"US",
    "sg:address":"1990 Fairmont Ave",
    "sg:city":"Fairmont",
    "sg:classifiers":[
        {
            "category":"Shopping",
            "subcategory":"Bicycles & Sporting Goods",
            "type":"Retail Goods"
        }
    ],
    "sg:phone":"+1 304 367 9300",
    "sg:postcode":"26554",
    "sg:province":"WV",
    "sg:tags":[
        "equipment",
        "golf",
        "supply"
    ],
    "wof:name":"Golf Etc",
    "wof:placetype":"venue"
},
  "geometry": {"coordinates":[-80.17481100000001,39.450613],"type":"Point"}
}