{
  "type": "Feature",
  "properties": {
    "addr:full":"5001 Maccorkle Ave Charleston WV 25309",
    "addr:housenumber":"5001",
    "addr:postcode":"25309",
    "addr:street":"Maccorkle Ave",
    "iso:country":"US",
    "sg:address":"5001 Maccorkle Ave",
    "sg:city":"Charleston",
    "sg:classifiers":[
        {
            "category":"Health Services",
            "subcategory":"Doctor",
            "type":"Services"
        }
    ],
    "sg:phone":"+1 304 768 5721",
    "sg:postcode":"25309",
    "sg:province":"WV",
    "wof:name":"Drs Lake & Lake",
    "wof:placetype":"venue"
},
  "geometry": {"coordinates":[-81.735308,38.353843],"type":"Point"}
}