{
  "type": "Feature",
  "properties": {
    "iso:country":"US",
    "sg:address":"256 Court St",
    "sg:city":"Grantsville",
    "sg:classifiers":[
        {
            "category":"Health Services",
            "subcategory":"Optometrist",
            "type":"Services"
        }
    ],
    "sg:phone":"+1 304 354 7505",
    "sg:postcode":"26147",
    "sg:province":"WV",
    "wof:name":"Calhoun Eye Clinic",
    "wof:placetype":"venue"
},
  "geometry": {"coordinates":[-81.096797,38.924864],"type":"Point"}
}