{
  "type": "Feature",
  "properties": {
    "iso:country":"US",
    "sg:address":"50 Circle Dr",
    "sg:city":"White Slphr Spgs",
    "sg:classifiers":[
        {
            "category":"Real Estate",
            "subcategory":"Real Estate Operator",
            "type":"Services"
        }
    ],
    "sg:phone":"+1 304 536 9232",
    "sg:postcode":"24986",
    "sg:province":"WV",
    "sg:tags":[
        "apartment"
    ],
    "wof:name":"Veronica Apartments",
    "wof:placetype":"venue"
},
  "geometry": {"coordinates":[-80.29067499999999,37.799813],"type":"Point"}
}