{
  "type": "Feature",
  "properties": {
    "addr:full":"1220 Morgantown Ave Fairmont WV 26554",
    "addr:housenumber":"1220",
    "addr:postcode":"26554",
    "addr:street":"Morgantown Ave",
    "iso:country":"US",
    "sg:address":"1220 Morgantown Ave",
    "sg:city":"Fairmont",
    "sg:classifiers":[
        {
            "category":"Personal",
            "subcategory":"Barber",
            "type":"Services"
        }
    ],
    "sg:phone":"+1 304 366 9966",
    "sg:postcode":"26554",
    "sg:province":"WV",
    "sg:tags":[
        "shop"
    ],
    "wof:name":"Guiseppes Barber & Styling Sp",
    "wof:placetype":"venue"
},
  "geometry": {"coordinates":[-80.11873300000001,39.481182],"type":"Point"}
}