{
  "type": "Feature",
  "properties": {
    "iso:country":"US",
    "sg:address":"411 Main St",
    "sg:city":"Mt Hope",
    "sg:classifiers":[
        {
            "category":"Manufacturing",
            "subcategory":"Lumber",
            "type":"Manufacturing & Wholesale Goods"
        }
    ],
    "sg:phone":"+1 304 877 5900",
    "sg:postcode":"25880",
    "sg:province":"WV",
    "sg:tags":[
        "forester"
    ],
    "wof:name":"Keiling Forestry Consulting",
    "wof:placetype":"venue"
},
  "geometry": {"coordinates":[-81.16443099999999,37.895478],"type":"Point"}
}