{
  "type": "Feature",
  "properties": {
    "iso:country":"US",
    "sg:address":"2417 Grant Ave",
    "sg:city":"St Albans",
    "sg:classifiers":[
        {
            "category":"Bars & Pubs",
            "type":"Food & Drink"
        },
        {
            "category":"Organizations",
            "subcategory":"Community Association",
            "type":"Services"
        }
    ],
    "sg:phone":"+1 304 727 2651",
    "sg:postcode":"25177",
    "sg:province":"WV",
    "sg:tags":[
        "club",
        "drinking",
        "eating"
    ],
    "wof:name":"Club El Dorado",
    "wof:placetype":"venue"
},
  "geometry": {"coordinates":[-81.80396399999999,38.382267],"type":"Point"}
}