{
  "type": "Feature",
  "properties": {
    "iso:country":"US",
    "sg:address":"100 Kanawha Blvd W",
    "sg:city":"Charleston",
    "sg:classifiers":[
        {
            "category":"Professional",
            "subcategory":"Lawyer & Legal Services",
            "type":"Services"
        }
    ],
    "sg:phone":"+1 304 342 6000",
    "sg:postcode":"25302",
    "sg:province":"WV",
    "sg:tags":[
        "attorney"
    ],
    "sg:website":"www.currytolliver.com",
    "wof:name":"Curry & Tolliver",
    "wof:placetype":"venue"
},
  "geometry": {"coordinates":[-81.64712,38.356992],"type":"Point"}
}