{
  "type": "Feature",
  "properties": {
    "addr:full":"2007 Grand Central Ave Parkersburg WV 26105",
    "addr:housenumber":"2007",
    "addr:postcode":"26105",
    "addr:street":"Grand Central Ave",
    "iso:country":"US",
    "sg:address":"2007 Grand Central Ave",
    "sg:city":"Parkersburg",
    "sg:classifiers":[
        {
            "category":"Professional",
            "subcategory":"Accounting & Tax Preparation",
            "type":"Services"
        }
    ],
    "sg:phone":"+1 304 295 7191",
    "sg:postcode":"26105",
    "sg:province":"WV",
    "sg:tags":[
        "accountant"
    ],
    "wof:name":"Richard F Sterling",
    "wof:placetype":"venue"
},
  "geometry": {"coordinates":[-81.55303600000001,39.320556],"type":"Point"}
}