{
  "type": "Feature",
  "properties": {
    "addr:full":"1196 Winchester Ave Martinsburg WV 25401",
    "addr:housenumber":"1196",
    "addr:postcode":"25401",
    "addr:street":"Winchester Ave",
    "iso:country":"US",
    "sg:address":"1196 Winchester Ave",
    "sg:city":"Martinsburg",
    "sg:classifiers":[
        {
            "category":"Retail",
            "subcategory":"Auto Repair",
            "type":"Services"
        }
    ],
    "sg:phone":"+1 304 263 1400",
    "sg:postcode":"25401",
    "sg:province":"WV",
    "sg:tags":[
        "repairing",
        "automobile"
    ],
    "wof:name":"Duncan Bros Tire Co & Svc Ctr",
    "wof:placetype":"venue"
},
  "geometry": {"coordinates":[-77.984889,39.436937],"type":"Point"}
}