{
  "type": "Feature",
  "properties": {
    "addr:full":"882 Oakwood Rd Charleston WV 25314",
    "addr:housenumber":"882",
    "addr:postcode":"25314",
    "addr:street":"Oakwood Rd",
    "iso:country":"US",
    "sg:address":"882 Oakwood Rd",
    "sg:city":"Charleston",
    "sg:classifiers":[
        {
            "category":"Shopping",
            "subcategory":"Bicycles & Sporting Goods",
            "type":"Retail Goods"
        }
    ],
    "sg:phone":"+1 304 344 9815",
    "sg:postcode":"25314",
    "sg:province":"WV",
    "sg:tags":[
        "screen",
        "printing"
    ],
    "wof:name":"Absolute Soccer",
    "wof:placetype":"venue"
},
  "geometry": {"coordinates":[-81.66322700000001,38.342873],"type":"Point"}
}