{
  "type": "Feature",
  "properties": {
    "iso:country":"US",
    "sg:address":"419 Rockcliff Rd",
    "sg:city":"Rupert",
    "sg:classifiers":[
        {
            "category":"Organizations",
            "subcategory":"Labor Organization",
            "type":"Services"
        }
    ],
    "sg:phone":"+1 304 392 2489",
    "sg:postcode":"25984",
    "sg:province":"WV",
    "wof:name":"United Mine Workers of Am",
    "wof:placetype":"venue"
},
  "geometry": {"coordinates":[-80.64753899999999,37.965121],"type":"Point"}
}