{
  "type": "Feature",
  "properties": {
    "addr:full":"7 River Walk Mall South Charleston WV 25303",
    "addr:housenumber":"7",
    "addr:postcode":"25303",
    "addr:street":"River Walk Mall",
    "iso:country":"US",
    "sg:address":"7 River Walk Mall",
    "sg:city":"South Charleston",
    "sg:classifiers":[
        {
            "category":"Food & Beverages",
            "subcategory":"Specialty",
            "type":"Retail Goods"
        }
    ],
    "sg:phone":"+1 304 744 7436",
    "sg:postcode":"25303",
    "sg:province":"WV",
    "sg:tags":[
        "health",
        "diet"
    ],
    "wof:name":"General Nutrition Ctr",
    "wof:placetype":"venue"
},
  "geometry": {"coordinates":[-81.713983,38.363556],"type":"Point"}
}