{
  "type": "Feature",
  "properties": {
    "addr:full":"663 7th St Parkersburg WV 26101",
    "addr:housenumber":"663",
    "addr:postcode":"26101",
    "addr:street":"7Th St",
    "iso:country":"US",
    "sg:address":"663 7th St",
    "sg:city":"Parkersburg",
    "sg:classifiers":[
        {
            "category":"Retail",
            "subcategory":"Auto Repair",
            "type":"Services"
        }
    ],
    "sg:phone":"+1 304 485 0221",
    "sg:postcode":"26101",
    "sg:province":"WV",
    "sg:tags":[
        "installs",
        "automotive",
        "glass"
    ],
    "wof:name":"Triumph Auto Glass",
    "wof:placetype":"venue"
},
  "geometry": {"coordinates":[-81.55100299999999,39.263724],"type":"Point"}
}