{
  "type": "Feature",
  "properties": {
    "iso:country":"US",
    "sg:address":"300 Court St",
    "sg:city":"Morgantown",
    "sg:classifiers":[
        {
            "category":"Organizations",
            "subcategory":"Non-profit Organization",
            "type":"Services"
        }
    ],
    "sg:phone":"+1 304 292 7510",
    "sg:postcode":"26505",
    "sg:province":"WV",
    "sg:tags":[
        "social"
    ],
    "wof:name":"Mountaineer Boys & Girls Club",
    "wof:placetype":"venue"
},
  "geometry": {"coordinates":[-79.958015,39.63014],"type":"Point"}
}