{
  "type": "Feature",
  "properties": {
    "iso:country":"US",
    "sg:address":"1400 7th St",
    "sg:city":"Moundsville",
    "sg:classifiers":[
        {
            "category":"Building & Trades",
            "subcategory":"Landscaping Services",
            "type":"Services"
        }
    ],
    "sg:phone":"+1 304 845 5481",
    "sg:postcode":"26041",
    "sg:province":"WV",
    "sg:tags":[
        "tree"
    ],
    "wof:name":"Steve's Tree Svc",
    "wof:placetype":"venue"
},
  "geometry": {"coordinates":[-80.737517,39.918403],"type":"Point"}
}