{
  "type": "Feature",
  "properties": {
    "iso:country":"US",
    "sg:address":"136 E German St",
    "sg:city":"Shepherdstown",
    "sg:classifiers":[
        {
            "category":"Professional",
            "subcategory":"Lawyer & Legal Services",
            "type":"Services"
        }
    ],
    "sg:phone":"+1 304 876 9333",
    "sg:postcode":"25443",
    "sg:province":"WV",
    "sg:tags":[
        "attorney"
    ],
    "wof:name":"D Frank Hill III",
    "wof:placetype":"venue"
},
  "geometry": {"coordinates":[-77.805272,39.430589],"type":"Point"}
}