{
  "type": "Feature",
  "properties": {
    "iso:country":"US",
    "sg:address":"429 Carriage Dr",
    "sg:city":"Beckley",
    "sg:classifiers":[
        {
            "category":"Health Services",
            "subcategory":"Doctor",
            "type":"Services"
        }
    ],
    "sg:phone":"+1 304 253 0849",
    "sg:postcode":"25801",
    "sg:province":"WV",
    "sg:tags":[
        "physician",
        "surgeon"
    ],
    "wof:name":"Appalachian Gastroenterology",
    "wof:placetype":"venue"
},
  "geometry": {"coordinates":[-81.199389,37.788721],"type":"Point"}
}