{
  "type": "Feature",
  "properties": {
    "addr:full":"15 Main St Cameron WV 26033",
    "addr:housenumber":"15",
    "addr:postcode":"26033",
    "addr:street":"Main St",
    "iso:country":"US",
    "sg:address":"15 Main St",
    "sg:city":"Cameron",
    "sg:classifiers":[
        {
            "category":"Social Services",
            "subcategory":"Adult Care",
            "type":"Services"
        },
        {
            "category":"Social Services",
            "type":"Services"
        }
    ],
    "sg:phone":"+1 304 686 2119",
    "sg:postcode":"26033",
    "sg:province":"WV",
    "sg:tags":[
        "organization",
        "senior",
        "citizen"
    ],
    "wof:name":"Cameron Senior Citizens Center",
    "wof:placetype":"venue"
},
  "geometry": {"coordinates":[-80.56594699999999,39.827096],"type":"Point"}
}