{
  "type": "Feature",
  "properties": {
    "iso:country":"US",
    "sg:address":"200 Washington St",
    "sg:city":"Ravenswood",
    "sg:classifiers":[
        {
            "category":"Personal",
            "subcategory":"Beauty Salon",
            "type":"Services"
        }
    ],
    "sg:phone":"+1 304 273 2259",
    "sg:postcode":"26164",
    "sg:province":"WV",
    "sg:tags":[
        "shop"
    ],
    "wof:name":"Vivian's Beauty Salon",
    "wof:placetype":"venue"
},
  "geometry": {"coordinates":[-81.76155799999999,38.948926],"type":"Point"}
}