{
  "type": "Feature",
  "properties": {
    "addr:full":"9009 California Ave Charleston WV 25315",
    "addr:housenumber":"9009",
    "addr:postcode":"25315",
    "addr:street":"California Ave",
    "iso:country":"US",
    "sg:address":"9009 California Ave",
    "sg:city":"Charleston",
    "sg:classifiers":[
        {
            "category":"Organizations",
            "subcategory":"Community Association",
            "type":"Services"
        }
    ],
    "sg:phone":"+1 304 949 2958",
    "sg:postcode":"25315",
    "sg:province":"WV",
    "wof:name":"Independent Order of Odd",
    "wof:placetype":"venue"
},
  "geometry": {"coordinates":[-81.567165,38.248695],"type":"Point"}
}