{
  "type": "Feature",
  "properties": {
    "iso:country":"US",
    "sg:address":"1001 Virginia Ave",
    "sg:city":"Follansbee",
    "sg:classifiers":[
        {
            "category":"Health Services",
            "subcategory":"Doctor",
            "type":"Services"
        }
    ],
    "sg:phone":"+1 304 527 1207",
    "sg:postcode":"26037",
    "sg:province":"WV",
    "sg:tags":[
        "medical"
    ],
    "wof:name":"Lifecare Medical Associates",
    "wof:placetype":"venue"
},
  "geometry": {"coordinates":[-80.59547499999999,40.33094],"type":"Point"}
}