{
  "type": "Feature",
  "properties": {
    "iso:country":"US",
    "sg:address":"1404 State Rte 41",
    "sg:city":"Summersville",
    "sg:classifiers":[
        {
            "category":"Restaurant",
            "type":"Food & Drink"
        }
    ],
    "sg:phone":"+1 304 872 7335",
    "sg:postcode":"26651",
    "sg:province":"WV",
    "wof:name":"Up The Creek Smokehouse",
    "wof:placetype":"venue"
},
  "geometry": {"coordinates":[-80.844836,38.283524],"type":"Point"}
}