{
  "type": "Feature",
  "properties": {
    "iso:country":"US",
    "sg:address":"2571 Sweeneysburg Rd",
    "sg:city":"Beckley",
    "sg:classifiers":[
        {
            "category":"Organizations",
            "subcategory":"Religious Organization",
            "type":"Services"
        }
    ],
    "sg:phone":"+1 304 877 6532",
    "sg:postcode":"25801",
    "sg:province":"WV",
    "sg:tags":[
        "clergy"
    ],
    "wof:name":"Harry Miller",
    "wof:placetype":"venue"
},
  "geometry": {"coordinates":[-81.270088,37.863036],"type":"Point"}
}