{
  "type": "Feature",
  "properties": {
    "addr:full":"109 W Myles Ave Pennsboro WV 26415",
    "addr:housenumber":"109",
    "addr:postcode":"26415",
    "addr:street":"W Myles Ave",
    "iso:country":"US",
    "sg:address":"109 W Myles Ave",
    "sg:city":"Pennsboro",
    "sg:classifiers":[
        {
            "category":"Manufacturing",
            "subcategory":"Metals",
            "type":"Manufacturing & Wholesale Goods"
        }
    ],
    "sg:phone":"+1 304 659 2931",
    "sg:postcode":"26415",
    "sg:province":"WV",
    "sg:tags":[
        "stamping"
    ],
    "wof:name":"Ken Mac Inc",
    "wof:placetype":"venue"
},
  "geometry": {"coordinates":[-80.968923,39.283683],"type":"Point"}
}