{
  "type": "Feature",
  "properties": {
    "addr:full":"431 B St St Albans WV 25177",
    "addr:housenumber":"431",
    "addr:postcode":"25177",
    "addr:street":"B St",
    "iso:country":"US",
    "sg:address":"431 B St",
    "sg:city":"St Albans",
    "sg:classifiers":[
        {
            "category":"Government",
            "subcategory":"Post Office",
            "type":"Public Place"
        }
    ],
    "sg:phone":"+1 304 722 2198",
    "sg:postcode":"25177",
    "sg:province":"WV",
    "wof:name":"US Post Office",
    "wof:placetype":"venue"
},
  "geometry": {"coordinates":[-81.83840600000001,38.388005],"type":"Point"}
}