{
  "type": "Feature",
  "properties": {
    "iso:country":"US",
    "sg:address":"1305 Dunbar Ave",
    "sg:city":"Dunbar",
    "sg:classifiers":[
        {
            "category":"Restaurant",
            "type":"Food & Drink"
        }
    ],
    "sg:phone":"+1 304 766 9426",
    "sg:postcode":"25064",
    "sg:province":"WV",
    "wof:name":"Lighthouse Emporium & Country",
    "wof:placetype":"venue"
},
  "geometry": {"coordinates":[-81.741721,38.360582],"type":"Point"}
}