{
  "type": "Feature",
  "properties": {
    "iso:country":"US",
    "sg:address":"115 Oak St",
    "sg:city":"Hurricane",
    "sg:classifiers":[
        {
            "category":"Building & Trades",
            "subcategory":"Plumbing",
            "type":"Services"
        }
    ],
    "sg:phone":"+1 304 757 7622",
    "sg:postcode":"25526",
    "sg:province":"WV",
    "sg:tags":[
        "conditioning",
        "air",
        "system",
        "contractor"
    ],
    "wof:name":"Ab-Ble Air",
    "wof:placetype":"venue"
},
  "geometry": {"coordinates":[-81.97420700000001,38.447514],"type":"Point"}
}