{
  "type": "Feature",
  "properties": {
    "iso:country":"US",
    "sg:address":"701 Marshall St",
    "sg:city":"Mcmechen",
    "sg:classifiers":[
        {
            "category":"Food & Beverages",
            "subcategory":"Groceries & Convenience Stores",
            "type":"Retail Goods"
        }
    ],
    "sg:phone":"+1 304 233 1650",
    "sg:postcode":"26040",
    "sg:province":"WV",
    "wof:name":"Convenient Food Mart",
    "wof:placetype":"venue"
},
  "geometry": {"coordinates":[-80.72891199999999,39.989317],"type":"Point"}
}