{
  "type": "Feature",
  "properties": {
    "addr:full":"1554 Kanawha Blvd E Charleston WV 25311",
    "addr:housenumber":"1554",
    "addr:postcode":"25311",
    "addr:street":"Kanawha Blvd E",
    "iso:country":"US",
    "sg:address":"1554 Kanawha Blvd E",
    "sg:city":"Charleston",
    "sg:classifiers":[
        {
            "category":"Professional",
            "subcategory":"Lawyer & Legal Services",
            "type":"Services"
        }
    ],
    "sg:phone":"+1 304 342 4508",
    "sg:postcode":"25311",
    "sg:province":"WV",
    "sg:tags":[
        "attorney"
    ],
    "wof:name":"Freeman & Chiartas",
    "wof:placetype":"venue"
},
  "geometry": {"coordinates":[-81.622871,38.339255],"type":"Point"}
}