{
  "type": "Feature",
  "properties": {
    "addr:full":"551 Robert C Byrd Dr Sophia WV 25921",
    "addr:housenumber":"551",
    "addr:postcode":"25921",
    "addr:street":"Robert C Byrd Dr",
    "iso:country":"US",
    "sg:address":"551 Robert C Byrd Dr",
    "sg:city":"Sophia",
    "sg:classifiers":[
        {
            "category":"Home & Garden",
            "subcategory":"Hardware",
            "type":"Retail Goods"
        }
    ],
    "sg:phone":"+1 304 683 3206",
    "sg:postcode":"25921",
    "sg:province":"WV",
    "wof:name":"Priddy's Campers & Buildings",
    "wof:placetype":"venue"
},
  "geometry": {"coordinates":[-81.25165699999999,37.720101],"type":"Point"}
}