{
  "type": "Feature",
  "properties": {
    "iso:country":"US",
    "sg:address":"302 Park Ave",
    "sg:city":"Charleston",
    "sg:classifiers":[
        {
            "category":"Health Services",
            "subcategory":"Clinic",
            "type":"Services"
        }
    ],
    "sg:phone":"+1 304 925 7001",
    "sg:postcode":"25309",
    "sg:province":"WV",
    "wof:name":"Pozega Wellness Center Inc",
    "wof:placetype":"venue"
},
  "geometry": {"coordinates":[-81.723963,38.357049],"type":"Point"}
}