{
  "type": "Feature",
  "properties": {
    "iso:country":"US",
    "sg:address":"705 Industrial Park Rd",
    "sg:city":"Beaver",
    "sg:classifiers":[
        {
            "category":"Personal",
            "type":"Services"
        }
    ],
    "sg:phone":"+1 304 929 2430",
    "sg:postcode":"25813",
    "sg:province":"WV",
    "wof:name":"Sound Ideas Inc",
    "wof:placetype":"venue"
},
  "geometry": {"coordinates":[-81.12773900000001,37.811168],"type":"Point"}
}