{
  "type": "Feature",
  "properties": {
    "iso:country":"US",
    "sg:address":"346 Rural Acres Dr",
    "sg:city":"Beckley",
    "sg:classifiers":[
        {
            "category":"Home & Garden",
            "subcategory":"Household Appliances",
            "type":"Retail Goods"
        }
    ],
    "sg:phone":"+1 304 255 4876",
    "sg:postcode":"25801",
    "sg:province":"WV",
    "wof:name":"Universal Systems Of Beckley",
    "wof:placetype":"venue"
},
  "geometry": {"coordinates":[-81.1777,37.792301],"type":"Point"}
}