{
  "type": "Feature",
  "properties": {
    "iso:country":"US",
    "sg:address":"480 Leonard Ave",
    "sg:city":"Fairmont",
    "sg:classifiers":[
        {
            "category":"Social Services",
            "type":"Services"
        }
    ],
    "sg:phone":"+1 304 366 6493",
    "sg:postcode":"26554",
    "sg:province":"WV",
    "wof:name":"Neighborhood Network Center",
    "wof:placetype":"venue"
},
  "geometry": {"coordinates":[-80.137753,39.473107],"type":"Point"}
}