{
  "type": "Feature",
  "properties": {
    "iso:country":"US",
    "sg:address":"365 Sunset Pl",
    "sg:city":"Keyser",
    "sg:classifiers":[
        {
            "category":"Wholesale",
            "subcategory":"Toys & Hobbies",
            "type":"Manufacturing & Wholesale Goods"
        }
    ],
    "sg:phone":"+1 304 788 5310",
    "sg:postcode":"26726",
    "sg:province":"WV",
    "wof:name":"K & M Sales Inc",
    "wof:placetype":"venue"
},
  "geometry": {"coordinates":[-78.98724199999999,39.437117],"type":"Point"}
}