{
  "type": "Feature",
  "properties": {
    "addr:full":"6 N Broadway St Wheeling WV 26003",
    "addr:housenumber":"6",
    "addr:postcode":"26003",
    "addr:street":"N Broadway St",
    "iso:country":"US",
    "sg:address":"6 N Broadway St",
    "sg:city":"Wheeling",
    "sg:classifiers":[
        {
            "category":"Professional",
            "subcategory":"Business Services",
            "type":"Services"
        }
    ],
    "sg:phone":"+1 304 336 7462",
    "sg:postcode":"26003",
    "sg:province":"WV",
    "sg:tags":[
        "real estate"
    ],
    "wof:name":"Advanced Auctioneers",
    "wof:placetype":"venue"
},
  "geometry": {"coordinates":[-80.732838,40.071926],"type":"Point"}
}