{
  "type": "Feature",
  "properties": {
    "iso:country":"US",
    "sg:address":"1412 W Pike St",
    "sg:city":"Clarksburg",
    "sg:classifiers":[
        {
            "category":"Shopping",
            "subcategory":"Books",
            "type":"Retail Goods"
        }
    ],
    "sg:phone":"+1 304 623 4510",
    "sg:postcode":"26301",
    "sg:province":"WV",
    "sg:tags":[
        "comic"
    ],
    "wof:name":"Gateway Comics",
    "wof:placetype":"venue"
},
  "geometry": {"coordinates":[-80.35594399999999,39.290662],"type":"Point"}
}