{
  "type": "Feature",
  "properties": {
    "addr:full":"700 Princeton Ave Princeton WV 24740",
    "addr:housenumber":"700",
    "addr:postcode":"24740",
    "addr:street":"Princeton Ave",
    "iso:country":"US",
    "sg:address":"700 Princeton Ave",
    "sg:city":"Princeton",
    "sg:classifiers":[
        {
            "category":"Personal",
            "subcategory":"Beauty Salon",
            "type":"Services"
        }
    ],
    "sg:phone":"+1 304 487 3992",
    "sg:postcode":"24740",
    "sg:province":"WV",
    "wof:name":"Ken's House Of Hair Design",
    "wof:placetype":"venue"
},
  "geometry": {"coordinates":[-81.090898,37.366588],"type":"Point"}
}