{
  "type": "Feature",
  "properties": {
    "iso:country":"US",
    "sg:address":"331 Court St",
    "sg:city":"Welch",
    "sg:classifiers":[
        {
            "category":"Organizations",
            "subcategory":"Membership Organization",
            "type":"Services"
        }
    ],
    "sg:phone":"+1 304 436 6337",
    "sg:postcode":"24801",
    "sg:province":"WV",
    "sg:tags":[
        "environmental",
        "ecological",
        "conservation"
    ],
    "wof:name":"Land & Mines Reclamation",
    "wof:placetype":"venue"
},
  "geometry": {"coordinates":[-81.58323,37.433135],"type":"Point"}
}