{
  "type": "Feature",
  "properties": {
    "iso:country":"US",
    "sg:address":"357 Stewart St",
    "sg:city":"Welch",
    "sg:classifiers":[
        {
            "category":"Organizations",
            "subcategory":"Religious Organization",
            "type":"Services"
        }
    ],
    "sg:phone":"+1 304 436 4606",
    "sg:postcode":"24801",
    "sg:province":"WV",
    "wof:name":"Indian Creek Community Church",
    "wof:placetype":"venue"
},
  "geometry": {"coordinates":[-81.580169,37.441],"type":"Point"}
}