{
  "type": "Feature",
  "properties": {
    "addr:full":"484 Outlaw Trl Maysville WV 26833",
    "addr:housenumber":"484",
    "addr:postcode":"26833",
    "addr:street":"Outlaw Trl",
    "iso:country":"US",
    "sg:address":"484 Outlaw Trl",
    "sg:city":"Maysville",
    "sg:classifiers":[
        {
            "category":"Freight",
            "type":"Transportation"
        }
    ],
    "sg:phone":"+1 304 749 8222",
    "sg:postcode":"26833",
    "sg:province":"WV",
    "sg:tags":[
        "operator",
        "local",
        "trucking"
    ],
    "wof:name":"Dunsmore Trucking",
    "wof:placetype":"venue"
},
  "geometry": {"coordinates":[-79.106514,39.121468],"type":"Point"}
}