{
  "type": "Feature",
  "properties": {
    "iso:country":"US",
    "sg:address":"300 Summers St",
    "sg:city":"Charleston",
    "sg:classifiers":[
        {
            "category":"Banks & Credit Unions",
            "subcategory":"Investment Brokerage",
            "type":"Services"
        }
    ],
    "sg:phone":"+1 304 347 2500",
    "sg:postcode":"25301",
    "sg:province":"WV",
    "sg:tags":[
        "stock",
        "bond"
    ],
    "wof:name":"Merrill Lynch",
    "wof:placetype":"venue"
},
  "geometry": {"coordinates":[-81.632515,38.352366],"type":"Point"}
}