{
  "type": "Feature",
  "properties": {
    "iso:country":"US",
    "sg:address":"1408 6th Ave",
    "sg:city":"Huntington",
    "sg:classifiers":[
        {
            "category":"Professional",
            "subcategory":"Accounting & Tax Preparation",
            "type":"Services"
        }
    ],
    "sg:phone":"+1 304 525 6830",
    "sg:postcode":"25701",
    "sg:province":"WV",
    "sg:tags":[
        "return",
        "filing"
    ],
    "wof:name":"P & E Accounting & Tax Svcs",
    "wof:placetype":"venue"
},
  "geometry": {"coordinates":[-82.432911,38.419847],"type":"Point"}
}