{
  "type": "Feature",
  "properties": {
    "addr:full":"106 Thorne Ave Princeton WV 24740",
    "addr:housenumber":"106",
    "addr:postcode":"24740",
    "addr:street":"Thorne Ave",
    "iso:country":"US",
    "sg:address":"106 Thorne Ave",
    "sg:city":"Princeton",
    "sg:classifiers":[
        {
            "category":"Organizations",
            "subcategory":"Religious Organization",
            "type":"Services"
        }
    ],
    "sg:phone":"+1 304 425 7222",
    "sg:postcode":"24740",
    "sg:province":"WV",
    "sg:tags":[
        "church"
    ],
    "wof:name":"Princeton Apostolic Church",
    "wof:placetype":"venue"
},
  "geometry": {"coordinates":[-81.060659,37.362538],"type":"Point"}
}