{
  "type": "Feature",
  "properties": {
    "iso:country":"US",
    "sg:address":"4922 Maccorkle Ave SE",
    "sg:city":"Charleston",
    "sg:classifiers":[
        {
            "category":"Health Services",
            "subcategory":"Doctor",
            "type":"Services"
        }
    ],
    "sg:phone":"+1 304 925 0923",
    "sg:postcode":"25304",
    "sg:province":"WV",
    "sg:tags":[
        "medical"
    ],
    "wof:name":"Lee Ann Skaff",
    "wof:placetype":"venue"
},
  "geometry": {"coordinates":[-81.577899,38.319358],"type":"Point"}
}