{
  "type": "Feature",
  "properties": {
    "iso:country":"US",
    "sg:address":"5007 W Pea Ridge Rd",
    "sg:city":"Huntington",
    "sg:classifiers":[
        {
            "category":"Farming",
            "subcategory":"Farm",
            "type":"Manufacturing & Wholesale Goods"
        }
    ],
    "sg:phone":"+1 304 736 8281",
    "sg:postcode":"25705",
    "sg:province":"WV",
    "sg:tags":[
        "crop",
        "general"
    ],
    "wof:name":"Rodney Easthom",
    "wof:placetype":"venue"
},
  "geometry": {"coordinates":[-82.35529699999999,38.411835],"type":"Point"}
}