{
  "type": "Feature",
  "properties": {
    "iso:country":"US",
    "sg:address":"812 S Carroll St",
    "sg:city":"St Albans",
    "sg:classifiers":[
        {
            "category":"Organizations",
            "subcategory":"Religious Organization",
            "type":"Services"
        }
    ],
    "sg:phone":"+1 304 722 4307",
    "sg:postcode":"25177",
    "sg:province":"WV",
    "sg:tags":[
        "church"
    ],
    "wof:name":"Salvation Army Outpost",
    "wof:placetype":"venue"
},
  "geometry": {"coordinates":[-81.81370099999999,38.377995],"type":"Point"}
}