{
  "type": "Feature",
  "properties": {
    "iso:country":"US",
    "sg:address":"5 Moran Cir",
    "sg:city":"Fairmont",
    "sg:classifiers":[
        {
            "category":"Personal",
            "subcategory":"Tanning Parlor",
            "type":"Services"
        }
    ],
    "sg:phone":"+1 304 333 4826",
    "sg:postcode":"26554",
    "sg:province":"WV",
    "sg:tags":[
        "salon"
    ],
    "wof:name":"Mistic Tanning",
    "wof:placetype":"venue"
},
  "geometry": {"coordinates":[-80.19716699999999,39.403635],"type":"Point"}
}