{
  "type": "Feature",
  "properties": {
    "iso:country":"US",
    "sg:address":"1231 Stafford Dr",
    "sg:city":"Princeton",
    "sg:classifiers":[
        {
            "category":"Home & Garden",
            "subcategory":"Household Appliances",
            "type":"Retail Goods"
        }
    ],
    "sg:phone":"+1 304 487 2481",
    "sg:postcode":"24740",
    "sg:province":"WV",
    "sg:tags":[
        "repair",
        "electrical"
    ],
    "wof:name":"Aerus Electrolux 3742",
    "wof:placetype":"venue"
},
  "geometry": {"coordinates":[-81.09577299999999,37.362947],"type":"Point"}
}