{
  "type": "Feature",
  "properties": {
    "addr:full":"651 Water St Summersville WV 26651",
    "addr:housenumber":"651",
    "addr:postcode":"26651",
    "addr:street":"Water St",
    "iso:country":"US",
    "sg:address":"651 Water St",
    "sg:city":"Summersville",
    "sg:classifiers":[
        {
            "category":"Health Services",
            "subcategory":"Optometrist",
            "type":"Services"
        }
    ],
    "sg:phone":"+1 304 872 5678",
    "sg:postcode":"26651",
    "sg:province":"WV",
    "wof:name":"Eddie Prendergast OD",
    "wof:placetype":"venue"
},
  "geometry": {"coordinates":[-80.85128400000001,38.281801],"type":"Point"}
}