{
  "type": "Feature",
  "properties": {
    "iso:country":"US",
    "sg:address":"125 Sinclair Ave",
    "sg:city":"Weirton",
    "sg:classifiers":[
        {
            "category":"Education",
            "subcategory":"School",
            "type":"Public Place"
        }
    ],
    "sg:phone":"+1 304 748 6080",
    "sg:postcode":"26062",
    "sg:province":"WV",
    "wof:name":"Weir Middle School Inc",
    "wof:placetype":"venue"
},
  "geometry": {"coordinates":[-80.577804,40.407931],"type":"Point"}
}