{
  "type": "Feature",
  "properties": {
    "addr:full":"500 Cedar Green Ln Bunker Hill WV 25413",
    "addr:housenumber":"500",
    "addr:postcode":"25413",
    "addr:street":"Cedar Green Ln",
    "iso:country":"US",
    "sg:address":"500 Cedar Green Ln",
    "sg:city":"Bunker Hill",
    "sg:classifiers":[
        {
            "category":"Real Estate",
            "subcategory":"Real Estate Operator",
            "type":"Services"
        }
    ],
    "sg:phone":"+1 304 229 3758",
    "sg:postcode":"25413",
    "sg:province":"WV",
    "sg:tags":[
        "apartment"
    ],
    "wof:name":"Cedar Green Apartments",
    "wof:placetype":"venue"
},
  "geometry": {"coordinates":[-78.05239899999999,39.340801],"type":"Point"}
}