{
  "type": "Feature",
  "properties": {
    "addr:full":"3318 West St Weirton WV 26062",
    "addr:housenumber":"3318",
    "addr:postcode":"26062",
    "addr:street":"West St",
    "iso:country":"US",
    "sg:address":"3318 West St",
    "sg:city":"Weirton",
    "sg:classifiers":[
        {
            "category":"Insurance",
            "subcategory":"Insurance Agent",
            "type":"Services"
        }
    ],
    "sg:phone":"+1 304 748 3535",
    "sg:postcode":"26062",
    "sg:province":"WV",
    "wof:name":"State Farm Insurance",
    "wof:placetype":"venue"
},
  "geometry": {"coordinates":[-80.58985800000001,40.403626],"type":"Point"}
}