{
  "type": "Feature",
  "properties": {
    "addr:full":"1 Old Wilderness Rd Summersville WV 26651",
    "addr:housenumber":"1",
    "addr:postcode":"26651",
    "addr:street":"Old Wilderness Rd",
    "iso:country":"US",
    "sg:address":"1 Old Wilderness Rd",
    "sg:city":"Summersville",
    "sg:classifiers":[
        {
            "category":"Travel",
            "subcategory":"Travel Agent",
            "type":"Entertainment"
        }
    ],
    "sg:phone":"+1 304 872 3722",
    "sg:postcode":"26651",
    "sg:province":"WV",
    "sg:tags":[
        "information",
        "tourist"
    ],
    "wof:name":"Summersville Convention Bureau",
    "wof:placetype":"venue"
},
  "geometry": {"coordinates":[-80.850641,38.276604],"type":"Point"}
}