{
  "type": "Feature",
  "properties": {
    "iso:country":"US",
    "sg:address":"723 Cunningham St",
    "sg:city":"Saint Albans",
    "sg:classifiers":[
        {
            "category":"Building & Trades",
            "subcategory":"Plumbing",
            "type":"Services"
        }
    ],
    "sg:phone":"+1 304 722 6776",
    "sg:postcode":"25177",
    "sg:province":"WV",
    "sg:tags":[
        "contractor"
    ],
    "wof:name":"Fischer Plbg Htg & A Condition",
    "wof:placetype":"venue"
},
  "geometry": {"coordinates":[-81.817821,38.379329],"type":"Point"}
}