{
  "type": "Feature",
  "properties": {
    "addr:full":"3443 16th St Huntington WV 25701",
    "addr:housenumber":"3443",
    "addr:postcode":"25701",
    "addr:street":"16Th St",
    "iso:country":"US",
    "sg:address":"3443 16th St",
    "sg:city":"Huntington",
    "sg:classifiers":[
        {
            "category":"Manufacturing",
            "subcategory":"Chemicals & Compounds",
            "type":"Manufacturing & Wholesale Goods"
        }
    ],
    "sg:phone":"+1 304 525 7340",
    "sg:postcode":"25701",
    "sg:province":"WV",
    "sg:tags":[
        "mfg"
    ],
    "wof:name":"M Ted Wallace Co",
    "wof:placetype":"venue"
},
  "geometry": {"coordinates":[-82.389877,38.388414],"type":"Point"}
}