{
  "type": "Feature",
  "properties": {
    "addr:full":"5513 Church Dr Charleston WV 25306",
    "addr:housenumber":"5513",
    "addr:postcode":"25306",
    "addr:street":"Church Dr",
    "iso:country":"US",
    "sg:address":"5513 Church Dr",
    "sg:city":"Charleston",
    "sg:classifiers":[
        {
            "category":"Real Estate",
            "subcategory":"Real Estate Agent",
            "type":"Services"
        }
    ],
    "sg:phone":"+1 304 925 4342",
    "sg:postcode":"25306",
    "sg:province":"WV",
    "wof:name":"Cornwell Tool Dealer",
    "wof:placetype":"venue"
},
  "geometry": {"coordinates":[-81.565623,38.277577],"type":"Point"}
}