{
  "type": "Feature",
  "properties": {
    "iso:country":"US",
    "sg:address":"1131 Berwood Dr",
    "sg:city":"Morgantown",
    "sg:classifiers":[
        {
            "category":"Retail",
            "subcategory":"Portrait Studio",
            "type":"Services"
        }
    ],
    "sg:phone":"+1 304 284 8811",
    "sg:postcode":"26505",
    "sg:province":"WV",
    "sg:tags":[
        "photographer"
    ],
    "wof:name":"C Mc Daniel & Co",
    "wof:placetype":"venue"
},
  "geometry": {"coordinates":[-79.92954,39.640178],"type":"Point"}
}