{
  "type": "Feature",
  "properties": {
    "iso:country":"US",
    "sg:address":"3989 Lincoln Ave",
    "sg:city":"Shadyside",
    "sg:classifiers":[
        {
            "category":"Government",
            "subcategory":"Post Office",
            "type":"Public Place"
        }
    ],
    "sg:phone":"+1 740 676 1231",
    "sg:postcode":"43947",
    "sg:province":"OH",
    "wof:name":"US Post Office",
    "wof:placetype":"venue"
},
  "geometry": {"coordinates":[-80.747944,39.971157],"type":"Point"}
}