{
  "type": "Feature",
  "properties": {
    "addr:full":"42 River Walk Mall South Charleston WV 25303",
    "addr:housenumber":"42",
    "addr:postcode":"25303",
    "addr:street":"River Walk Mall",
    "iso:country":"US",
    "sg:address":"42 River Walk Mall",
    "sg:city":"South Charleston",
    "sg:classifiers":[
        {
            "category":"Food & Beverages",
            "subcategory":"Bakery",
            "type":"Retail Goods"
        }
    ],
    "sg:phone":"+1 304 746 4441",
    "sg:postcode":"25303",
    "sg:province":"WV",
    "sg:tags":[
        "doughnut"
    ],
    "wof:name":"Krispy Kreme Doughnuts",
    "wof:placetype":"venue"
},
  "geometry": {"coordinates":[-81.711496,38.365169],"type":"Point"}
}