{
  "type": "Feature",
  "properties": {
    "iso:country":"US",
    "sg:address":"354 Norway Ave",
    "sg:city":"Huntington",
    "sg:classifiers":[
        {
            "category":"Shopping",
            "subcategory":"Clothing, Apparel, & Fashions",
            "type":"Retail Goods"
        }
    ],
    "sg:phone":"+1 304 697 4314",
    "sg:postcode":"25705",
    "sg:province":"WV",
    "wof:name":"Sheilas Buddha Shop",
    "wof:placetype":"venue"
},
  "geometry": {"coordinates":[-82.406128,38.406784],"type":"Point"}
}