{
  "type": "Feature",
  "properties": {
    "iso:country":"US",
    "sg:address":"5879 Davis Creek Rd",
    "sg:city":"Barboursville",
    "sg:classifiers":[
        {
            "category":"Autos & Motor Vehicles",
            "subcategory":"Fuel & Gas Station",
            "type":"Retail Goods"
        }
    ],
    "sg:phone":"+1 304 736 8434",
    "sg:postcode":"25504",
    "sg:province":"WV",
    "sg:tags":[
        "station",
        "gasoline"
    ],
    "wof:name":"Rich Oil Station",
    "wof:placetype":"venue"
},
  "geometry": {"coordinates":[-82.320019,38.400242],"type":"Point"}
}