{
  "type": "Feature",
  "properties": {
    "iso:country":"US",
    "sg:address":"610 Crestlyn Dr",
    "sg:city":"Charleston",
    "sg:classifiers":[
        {
            "category":"Freight",
            "type":"Transportation"
        }
    ],
    "sg:phone":"+1 304 343 5268",
    "sg:postcode":"25302",
    "sg:province":"WV",
    "sg:tags":[
        "operator",
        "trucking"
    ],
    "wof:name":"T & D Trk1ng LLC",
    "wof:placetype":"venue"
},
  "geometry": {"coordinates":[-81.631889,38.381914],"type":"Point"}
}