{
  "type": "Feature",
  "properties": {
    "iso:country":"US",
    "sg:address":"208 Kanawha Dr",
    "sg:city":"Weirton",
    "sg:classifiers":[
        {
            "category":"Shopping",
            "subcategory":"Bicycles & Sporting Goods",
            "type":"Retail Goods"
        }
    ],
    "sg:phone":"+1 304 723 4223",
    "sg:postcode":"26062",
    "sg:province":"WV",
    "wof:name":"G & S Miller's Enterprises Inc",
    "wof:placetype":"venue"
},
  "geometry": {"coordinates":[-80.538793,40.403344],"type":"Point"}
}