{
  "type": "Feature",
  "properties": {
    "iso:country":"US",
    "sg:address":"5151 Maccorkle Ave",
    "sg:city":"Spring Hill",
    "sg:classifiers":[
        {
            "category":"Banks & Credit Unions",
            "subcategory":"Bank",
            "type":"Services"
        }
    ],
    "sg:phone":"+1 304 768 9782",
    "sg:postcode":"25309",
    "sg:province":"WV",
    "wof:name":"United Bank",
    "wof:placetype":"venue"
},
  "geometry": {"coordinates":[-81.738766,38.353664],"type":"Point"}
}