{
  "type": "Feature",
  "properties": {
    "addr:full":"712 Victoria Ave Williamstown WV 26187",
    "addr:housenumber":"712",
    "addr:postcode":"26187",
    "addr:street":"Victoria Ave",
    "iso:country":"US",
    "sg:address":"712 Victoria Ave",
    "sg:city":"Williamstown",
    "sg:classifiers":[
        {
            "category":"Wholesale",
            "subcategory":"Groceries",
            "type":"Manufacturing & Wholesale Goods"
        }
    ],
    "sg:phone":"+1 304 375 2468",
    "sg:postcode":"26187",
    "sg:province":"WV",
    "sg:tags":[
        "food",
        "product"
    ],
    "wof:name":"Watkins Products",
    "wof:placetype":"venue"
},
  "geometry": {"coordinates":[-81.4542,39.396836],"type":"Point"}
}