{
  "type": "Feature",
  "properties": {
    "iso:country":"US",
    "sg:address":"37 Skyline Trl",
    "sg:city":"Charles Town",
    "sg:classifiers":[
        {
            "category":"Building & Trades",
            "subcategory":"Pest Control",
            "type":"Services"
        }
    ],
    "sg:phone":"+1 304 728 5090",
    "sg:postcode":"25438",
    "sg:province":"WV",
    "wof:name":"Accurate Pest Management LLC",
    "wof:placetype":"venue"
},
  "geometry": {"coordinates":[-77.79380999999999,39.221623],"type":"Point"}
}