{
  "type": "Feature",
  "properties": {
    "iso:country":"US",
    "sg:address":"1200 Fairmont Ave",
    "sg:city":"Fairmont",
    "sg:classifiers":[
        {
            "category":"Restaurant",
            "type":"Food & Drink"
        }
    ],
    "sg:menulink":"http://www.allmenus.com/wv/middletown/86207-little-caesars-pizza/menu/",
    "sg:phone":"+1 304 366 3366",
    "sg:postcode":"26554",
    "sg:province":"WV",
    "sg:tags":[
        "american",
        "pizza"
    ],
    "wof:name":"Little Caesar's Pizza",
    "wof:placetype":"venue"
},
  "geometry": {"coordinates":[-80.155058,39.470095],"type":"Point"}
}