{
  "type": "Feature",
  "properties": {
    "iso:country":"US",
    "sg:address":"2413 Grant Ave",
    "sg:city":"St Albans",
    "sg:classifiers":[
        {
            "category":"Health Services",
            "subcategory":"Doctor",
            "type":"Services"
        }
    ],
    "sg:phone":"+1 304 722 2211",
    "sg:postcode":"25177",
    "sg:province":"WV",
    "sg:tags":[
        "dentist"
    ],
    "wof:name":"M H Conley DDS",
    "wof:placetype":"venue"
},
  "geometry": {"coordinates":[-81.803916,38.382252],"type":"Point"}
}