{
  "type": "Feature",
  "properties": {
    "addr:full":"928 Bluefield Ave Bluefield WV 24701",
    "addr:housenumber":"928",
    "addr:postcode":"24701",
    "addr:street":"Bluefield Ave",
    "iso:country":"US",
    "sg:address":"928 Bluefield Ave",
    "sg:city":"Bluefield",
    "sg:classifiers":[
        {
            "category":"Manufacturing",
            "subcategory":"Printing",
            "type":"Manufacturing & Wholesale Goods"
        }
    ],
    "sg:phone":"+1 304 327 2800",
    "sg:postcode":"24701",
    "sg:province":"WV",
    "sg:tags":[
        "newspaper"
    ],
    "wof:name":"Bluefield Daily Telegraph",
    "wof:placetype":"venue"
},
  "geometry": {"coordinates":[-81.23515999999999,37.265129],"type":"Point"}
}