{
  "type": "Feature",
  "properties": {
    "iso:country":"US",
    "sg:address":"203 Willow Ridge",
    "sg:city":"Scott Depot",
    "sg:classifiers":[
        {
            "category":"Farming",
            "subcategory":"Livestock Farm",
            "type":"Manufacturing & Wholesale Goods"
        }
    ],
    "sg:phone":"+1 304 727 2156",
    "sg:postcode":"25560",
    "sg:province":"WV",
    "sg:tags":[
        "animal",
        "general"
    ],
    "wof:name":"Douglas Spradling",
    "wof:placetype":"venue"
},
  "geometry": {"coordinates":[-81.887862,38.454299],"type":"Point"}
}