{
  "type": "Feature",
  "properties": {
    "addr:full":"326 Railroad Ave Elkins WV 26241",
    "addr:housenumber":"326",
    "addr:postcode":"26241",
    "addr:street":"Railroad Ave",
    "iso:country":"US",
    "sg:address":"326 Railroad Ave",
    "sg:city":"Elkins",
    "sg:classifiers":[
        {
            "category":"Organizations",
            "subcategory":"Community Association",
            "type":"Services"
        }
    ],
    "sg:phone":"+1 304 636 3930",
    "sg:postcode":"26241",
    "sg:province":"WV",
    "sg:tags":[
        "military"
    ],
    "wof:name":"American Legion",
    "wof:placetype":"venue"
},
  "geometry": {"coordinates":[-79.850779,38.925688],"type":"Point"}
}