{
  "type": "Feature",
  "properties": {
    "iso:country":"US",
    "sg:address":"2415 Jackson Ave",
    "sg:city":"Point Pleasant",
    "sg:classifiers":[
        {
            "category":"Health Services",
            "subcategory":"Doctor",
            "type":"Services"
        }
    ],
    "sg:phone":"+1 304 675 6090",
    "sg:postcode":"25550",
    "sg:province":"WV",
    "sg:tags":[
        "physician",
        "surgeon"
    ],
    "wof:name":"Agnes Enrico-Simon MD",
    "wof:placetype":"venue"
},
  "geometry": {"coordinates":[-82.12619599999999,38.867195],"type":"Point"}
}