{
  "type": "Feature",
  "properties": {
    "iso:country":"US",
    "sg:address":"1803 Jacklin St",
    "sg:city":"Fairmont",
    "sg:classifiers":[
        {
            "category":"Communications",
            "subcategory":"Film & Video Production",
            "type":"Services"
        }
    ],
    "sg:phone":"+1 304 366 7676",
    "sg:postcode":"26554",
    "sg:province":"WV",
    "sg:tags":[
        "taping"
    ],
    "wof:name":"Spartan Production Video",
    "wof:placetype":"venue"
},
  "geometry": {"coordinates":[-80.177087,39.417691],"type":"Point"}
}