{
  "type": "Feature",
  "properties": {
    "iso:country":"US",
    "sg:address":"73 Industrial Cir",
    "sg:city":"Kearneysville",
    "sg:classifiers":[
        {
            "category":"Manufacturing",
            "subcategory":"Printing",
            "type":"Manufacturing & Wholesale Goods"
        }
    ],
    "sg:phone":"+1 304 725 0300",
    "sg:postcode":"25403",
    "sg:province":"WV",
    "sg:tags":[
        "lithograph",
        "commercial",
        "specialty",
        "mfg"
    ],
    "sg:website":"www.dalb.com",
    "wof:name":"Dalb Inc",
    "wof:placetype":"venue"
},
  "geometry": {"coordinates":[-79.494767,39.553143],"type":"Point"}
}