{
  "type": "Feature",
  "properties": {
    "addr:full":"4 Springhaven Rd Wheeling WV 26003",
    "addr:housenumber":"4",
    "addr:postcode":"26003",
    "addr:street":"Springhaven Rd",
    "iso:country":"US",
    "sg:address":"4 Springhaven Rd",
    "sg:city":"Wheeling",
    "sg:classifiers":[
        {
            "category":"Building & Trades",
            "subcategory":"Construction",
            "type":"Services"
        }
    ],
    "sg:phone":"+1 304 243 4762",
    "sg:postcode":"26003",
    "sg:province":"WV",
    "sg:tags":[
        "hanging",
        "contractor"
    ],
    "wof:name":"Perfection Painting",
    "wof:placetype":"venue"
},
  "geometry": {"coordinates":[-80.681288,40.081298],"type":"Point"}
}