{
  "type": "Feature",
  "properties": {
    "addr:full":"28 Capitol St Charleston WV 25301",
    "addr:housenumber":"28",
    "addr:postcode":"25301",
    "addr:street":"Capitol St",
    "iso:country":"US",
    "sg:address":"28 Capitol St",
    "sg:city":"Charleston",
    "sg:classifiers":[
        {
            "category":"Restaurant",
            "type":"Food & Drink"
        }
    ],
    "sg:phone":"+1 304 346 6222",
    "sg:postcode":"25301",
    "sg:province":"WV",
    "wof:name":"Sam's Uptown Cafe",
    "wof:placetype":"venue"
},
  "geometry": {"coordinates":[-81.63661399999999,38.348709],"type":"Point"}
}