{
  "type": "Feature",
  "properties": {
    "iso:country":"US",
    "sg:address":"308 Carleton St",
    "sg:city":"Beckley",
    "sg:classifiers":[
        {
            "category":"Professional",
            "subcategory":"Detective & Security Services",
            "type":"Services"
        }
    ],
    "sg:phone":"+1 304 252 2514",
    "sg:postcode":"25801",
    "sg:province":"WV",
    "sg:tags":[
        "car"
    ],
    "wof:name":"National Security Services",
    "wof:placetype":"venue"
},
  "geometry": {"coordinates":[-81.203247,37.76881],"type":"Point"}
}