{
  "type": "Feature",
  "properties": {
    "addr:full":"519 Warm Springs Ave Martinsburg WV 25404",
    "addr:housenumber":"519",
    "addr:postcode":"25404",
    "addr:street":"Warm Springs Ave",
    "iso:country":"US",
    "sg:address":"519 Warm Springs Ave",
    "sg:city":"Martinsburg",
    "sg:classifiers":[
        {
            "category":"Retail",
            "subcategory":"Veterinary Services",
            "type":"Services"
        }
    ],
    "sg:phone":"+1 304 267 7468",
    "sg:postcode":"25404",
    "sg:province":"WV",
    "sg:tags":[
        "specialty"
    ],
    "wof:name":"Byers, Michelle",
    "wof:placetype":"venue"
},
  "geometry": {"coordinates":[-77.95477099999999,39.485742],"type":"Point"}
}