{
  "type": "Feature",
  "properties": {
    "iso:country":"US",
    "sg:address":"101 Mylan Park Ln",
    "sg:city":"Morgantown",
    "sg:classifiers":[
        {
            "category":"Education",
            "subcategory":"School",
            "type":"Public Place"
        }
    ],
    "sg:phone":"+1 304 983 8204",
    "sg:postcode":"26501",
    "sg:province":"WV",
    "wof:name":"Monongalia - Bus Garage",
    "wof:placetype":"venue"
},
  "geometry": {"coordinates":[-80.035383,39.639747],"type":"Point"}
}