{
  "type": "Feature",
  "properties": {
    "iso:country":"US",
    "sg:address":"916 W Pike St",
    "sg:city":"Clarksburg",
    "sg:classifiers":[
        {
            "category":"Health Services",
            "subcategory":"Doctor",
            "type":"Services"
        }
    ],
    "sg:phone":"+1 304 622 2708",
    "sg:postcode":"26301",
    "sg:province":"WV",
    "sg:tags":[
        "clinic",
        "care",
        "medical",
        "primary"
    ],
    "wof:name":"Health Access Inc",
    "wof:placetype":"venue"
},
  "geometry": {"coordinates":[-80.35509999999999,39.283691],"type":"Point"}
}