{
  "type": "Feature",
  "properties": {
    "addr:full":"485 High St Morgantown WV 26505",
    "addr:housenumber":"485",
    "addr:postcode":"26505",
    "addr:street":"High St",
    "iso:country":"US",
    "sg:address":"485 High St",
    "sg:city":"Morgantown",
    "sg:classifiers":[
        {
            "category":"Restaurant",
            "type":"Food & Drink"
        }
    ],
    "sg:menulink":"http://www.allmenus.com/wv/central/241921-casa-damici/menu/",
    "sg:phone":"+1 304 292 4400",
    "sg:postcode":"26505",
    "sg:province":"WV",
    "sg:tags":[
        "italian"
    ],
    "wof:name":"Casa D'amici",
    "wof:placetype":"venue"
},
  "geometry": {"coordinates":[-79.95404000000001,39.631965],"type":"Point"}
}