{
  "type": "Feature",
  "properties": {
    "iso:country":"US",
    "sg:address":"2419 Stewartstown Rd",
    "sg:city":"Morgantown",
    "sg:classifiers":[
        {
            "category":"Structure",
            "subcategory":"Office Building",
            "type":"Public Place"
        }
    ],
    "sg:phone":"+1 304 319 1498",
    "sg:postcode":"26508",
    "sg:province":"WV",
    "sg:tags":[
        "park"
    ],
    "wof:name":"Scott Properties",
    "wof:placetype":"venue"
},
  "geometry": {"coordinates":[-79.902084,39.702171],"type":"Point"}
}