{
  "type": "Feature",
  "properties": {
    "addr:full":"5479 Elk River Rd Elkview WV 25071",
    "addr:housenumber":"5479",
    "addr:postcode":"25071",
    "addr:street":"Elk River Rd",
    "iso:country":"US",
    "sg:address":"5479 Elk River Rd",
    "sg:city":"Elkview",
    "sg:classifiers":[
        {
            "category":"Retail",
            "subcategory":"Repair Shop",
            "type":"Services"
        }
    ],
    "sg:phone":"+1 304 548 7887",
    "sg:postcode":"25071",
    "sg:province":"WV",
    "sg:tags":[
        "repairing",
        "saw"
    ],
    "wof:name":"Harper's Sharpening Shop",
    "wof:placetype":"venue"
},
  "geometry": {"coordinates":[-81.40284699999999,38.46759],"type":"Point"}
}