{
  "type": "Feature",
  "properties": {
    "addr:full":"1217 Princeton Ave Princeton WV 24740",
    "addr:housenumber":"1217",
    "addr:postcode":"24740",
    "addr:street":"Princeton Ave",
    "iso:country":"US",
    "sg:address":"1217 Princeton Ave",
    "sg:city":"Princeton",
    "sg:classifiers":[
        {
            "category":"Professional",
            "subcategory":"Computer Services",
            "type":"Services"
        }
    ],
    "sg:phone":"+1 304 487 9417",
    "sg:postcode":"24740",
    "sg:province":"WV",
    "sg:tags":[
        "repair"
    ],
    "wof:name":"Computer Station",
    "wof:placetype":"venue"
},
  "geometry": {"coordinates":[-81.096386,37.363659],"type":"Point"}
}