{
  "type": "Feature",
  "properties": {
    "iso:country":"US",
    "sg:address":"110 Springwood Dr",
    "sg:city":"Sophia",
    "sg:classifiers":[
        {
            "category":"Retail",
            "subcategory":"Repair Shop",
            "type":"Services"
        }
    ],
    "sg:phone":"+1 304 683 4959",
    "sg:postcode":"25921",
    "sg:province":"WV",
    "sg:tags":[
        "communication",
        "radio",
        "sales"
    ],
    "wof:name":"Jaycom",
    "wof:placetype":"venue"
},
  "geometry": {"coordinates":[-81.247359,37.711681],"type":"Point"}
}