{
  "type": "Feature",
  "properties": {
    "iso:country":"US",
    "sg:address":"969 National Rd",
    "sg:city":"Wheeling",
    "sg:classifiers":[
        {
            "category":"Health Services",
            "subcategory":"Doctor",
            "type":"Services"
        }
    ],
    "sg:phone":"+1 304 233 3020",
    "sg:postcode":"26003",
    "sg:province":"WV",
    "sg:tags":[
        "dentist"
    ],
    "wof:name":"Joseph B Grubler DDS",
    "wof:placetype":"venue"
},
  "geometry": {"coordinates":[-80.68804799999999,40.078523],"type":"Point"}
}