{
  "type": "Feature",
  "properties": {
    "addr:full":"107 Pleasant Ave Kingwood WV 26537",
    "addr:housenumber":"107",
    "addr:postcode":"26537",
    "addr:street":"Pleasant Ave",
    "iso:country":"US",
    "sg:address":"107 Pleasant Ave",
    "sg:city":"Kingwood",
    "sg:classifiers":[
        {
            "category":"Professional",
            "subcategory":"Business Services",
            "type":"Services"
        }
    ],
    "sg:phone":"+1 304 329 1360",
    "sg:postcode":"26537",
    "sg:province":"WV",
    "wof:name":"Cablevision Communications",
    "wof:placetype":"venue"
},
  "geometry": {"coordinates":[-79.67227800000001,39.468701],"type":"Point"}
}