{
  "type": "Feature",
  "properties": {
    "addr:full":"238 W Main St Grafton WV 26354",
    "addr:housenumber":"238",
    "addr:postcode":"26354",
    "addr:street":"W Main St",
    "iso:country":"US",
    "sg:address":"238 W Main St",
    "sg:city":"Grafton",
    "sg:classifiers":[
        {
            "category":"Restaurant",
            "type":"Food & Drink"
        }
    ],
    "sg:phone":"+1 304 265 0740",
    "sg:postcode":"26354",
    "sg:province":"WV",
    "sg:tags":[
        "eating",
        "caterer"
    ],
    "wof:name":"Leonard's Grocery",
    "wof:placetype":"venue"
},
  "geometry": {"coordinates":[-80.01988900000001,39.340933],"type":"Point"}
}