{
  "type": "Feature",
  "properties": {
    "addr:full":"420 Main St Summersville WV 26651",
    "addr:housenumber":"420",
    "addr:postcode":"26651",
    "addr:street":"Main St",
    "iso:country":"US",
    "sg:address":"420 Main St",
    "sg:city":"Summersville",
    "sg:classifiers":[
        {
            "category":"Organizations",
            "subcategory":"Professional Association",
            "type":"Services"
        }
    ],
    "sg:phone":"+1 304 872 8199",
    "sg:postcode":"26651",
    "sg:province":"WV",
    "wof:name":"Allegheny Association-Baptist",
    "wof:placetype":"venue"
},
  "geometry": {"coordinates":[-80.855718,38.281379],"type":"Point"}
}