{
  "type": "Feature",
  "properties": {
    "iso:country":"US",
    "sg:address":"205 New River Dr",
    "sg:city":"Beckley",
    "sg:classifiers":[
        {
            "category":"Banks & Credit Unions",
            "subcategory":"Bank",
            "type":"Services"
        }
    ],
    "sg:phone":"+1 304 256 4712",
    "sg:postcode":"25801",
    "sg:province":"WV",
    "wof:name":"Raleigh Cnty Educators Fed CU",
    "wof:placetype":"venue"
},
  "geometry": {"coordinates":[-81.187361,37.789848],"type":"Point"}
}