{
  "type": "Feature",
  "properties": {
    "iso:country":"US",
    "sg:address":"32 20th St",
    "sg:city":"Wheeling",
    "sg:classifiers":[
        {
            "category":"Real Estate",
            "subcategory":"Architect",
            "type":"Services"
        }
    ],
    "sg:phone":"+1 304 233 0140",
    "sg:postcode":"26003",
    "sg:province":"WV",
    "sg:website":"www.mckinleyassoc.com",
    "wof:name":"Mc Kinley & Assoc Inc",
    "wof:placetype":"venue"
},
  "geometry": {"coordinates":[-80.722047,40.061385],"type":"Point"}
}