{
  "type": "Feature",
  "properties": {
    "iso:country":"US",
    "sg:address":"210 N Elm St",
    "sg:city":"Moorefield",
    "sg:classifiers":[
        {
            "category":"Insurance",
            "subcategory":"Insurance Agent",
            "type":"Services"
        }
    ],
    "sg:phone":"+1 304 538 2932",
    "sg:postcode":"26836",
    "sg:province":"WV",
    "wof:name":"Mid-Atlantic Group",
    "wof:placetype":"venue"
},
  "geometry": {"coordinates":[-78.96829,39.064187],"type":"Point"}
}