{
  "type": "Feature",
  "properties": {
    "addr:full":"2000 Mount Vernon Rd Hurricane WV 25526",
    "addr:housenumber":"2000",
    "addr:postcode":"25526",
    "addr:street":"Mount Vernon Rd",
    "iso:country":"US",
    "sg:address":"2000 Mount Vernon Rd",
    "sg:city":"Hurricane",
    "sg:classifiers":[
        {
            "category":"Organizations",
            "subcategory":"Community Association",
            "type":"Services"
        }
    ],
    "sg:phone":"+1 304 757 9893",
    "sg:postcode":"25526",
    "sg:province":"WV",
    "wof:name":"Administrative Support Inc",
    "wof:placetype":"venue"
},
  "geometry": {"coordinates":[-81.95820399999999,38.446871],"type":"Point"}
}