{
  "type": "Feature",
  "properties": {
    "iso:country":"US",
    "sg:address":"3459 Fairmont Ave",
    "sg:city":"Fairmont",
    "sg:classifiers":[
        {
            "category":"Autos & Motor Vehicles",
            "subcategory":"Automobile Sales",
            "type":"Retail Goods"
        }
    ],
    "sg:phone":"+1 304 366 6985",
    "sg:postcode":"26554",
    "sg:province":"WV",
    "sg:tags":[
        "used"
    ],
    "wof:name":"Nustalgia Preowned Auto Sales",
    "wof:placetype":"venue"
},
  "geometry": {"coordinates":[-80.17585,39.450325],"type":"Point"}
}