{
  "type": "Feature",
  "properties": {
    "iso:country":"US",
    "sg:address":"1201 S Davis Ave",
    "sg:city":"Elkins",
    "sg:classifiers":[
        {
            "category":"Retail",
            "subcategory":"Auto Repair",
            "type":"Services"
        }
    ],
    "sg:phone":"+1 304 636 2897",
    "sg:postcode":"26241",
    "sg:province":"WV",
    "sg:tags":[
        "body",
        "automobile",
        "painting"
    ],
    "wof:name":"Bill's Auto Repair Inc",
    "wof:placetype":"venue"
},
  "geometry": {"coordinates":[-79.851253,38.918327],"type":"Point"}
}