{
  "type": "Feature",
  "properties": {
    "iso:country":"US",
    "sg:address":"524 Clayton Ave",
    "sg:city":"Hurricane",
    "sg:classifiers":[
        {
            "category":"Building & Trades",
            "subcategory":"Plumbing",
            "type":"Services"
        }
    ],
    "sg:phone":"+1 304 562 2005",
    "sg:postcode":"25526",
    "sg:province":"WV",
    "sg:tags":[
        "plumbing",
        "contractor"
    ],
    "wof:name":"Clark Plumbing & General Rpr",
    "wof:placetype":"venue"
},
  "geometry": {"coordinates":[-82.032483,38.423223],"type":"Point"}
}