{
  "type": "Feature",
  "properties": {
    "addr:full":"5401 Maccorkle Ave Charleston WV 25309",
    "addr:housenumber":"5401",
    "addr:postcode":"25309",
    "addr:street":"Maccorkle Ave",
    "iso:country":"US",
    "sg:address":"5401 Maccorkle Ave",
    "sg:city":"Charleston",
    "sg:classifiers":[
        {
            "category":"Building & Trades",
            "subcategory":"Pest Control",
            "type":"Services"
        }
    ],
    "sg:phone":"+1 304 768 5637",
    "sg:postcode":"25309",
    "sg:province":"WV",
    "wof:name":"House Doctor Handyman",
    "wof:placetype":"venue"
},
  "geometry": {"coordinates":[-81.743589,38.353697],"type":"Point"}
}