{
  "type": "Feature",
  "properties": {
    "iso:country":"US",
    "sg:address":"1400 Johnson Ave",
    "sg:city":"Bridgeport",
    "sg:classifiers":[
        {
            "category":"Social Services",
            "type":"Services"
        }
    ],
    "sg:phone":"+1 304 842 1609",
    "sg:postcode":"26330",
    "sg:province":"WV",
    "sg:tags":[
        "probation"
    ],
    "wof:name":"Probation & Parole Office",
    "wof:placetype":"venue"
},
  "geometry": {"coordinates":[-80.277558,39.300293],"type":"Point"}
}