{
  "type": "Feature",
  "properties": {
    "iso:country":"US",
    "sg:address":"144 Oleander Dr",
    "sg:city":"Beckley",
    "sg:classifiers":[
        {
            "category":"Professional",
            "subcategory":"Engineering",
            "type":"Services"
        }
    ],
    "sg:phone":"+1 304 252 5906",
    "sg:postcode":"25801",
    "sg:province":"WV",
    "sg:tags":[
        "engineer"
    ],
    "wof:name":"Lawson Engineering & Technical",
    "wof:placetype":"venue"
},
  "geometry": {"coordinates":[-81.18983900000001,37.791481],"type":"Point"}
}