{
  "type": "Feature",
  "properties": {
    "iso:country":"US",
    "sg:address":"615 Ohio Ave",
    "sg:city":"Charleston",
    "sg:classifiers":[
        {
            "category":"Insurance",
            "subcategory":"Insurance Agent",
            "type":"Services"
        }
    ],
    "sg:phone":"+1 304 342 2111",
    "sg:postcode":"25302",
    "sg:province":"WV",
    "wof:name":"State Farm Insurance",
    "wof:placetype":"venue"
},
  "geometry": {"coordinates":[-81.64189,38.362273],"type":"Point"}
}