{
  "type": "Feature",
  "properties": {
    "addr:full":"110 Professional Park Beckley WV 25801",
    "addr:housenumber":"110",
    "addr:postcode":"25801",
    "addr:street":"Professional Park",
    "iso:country":"US",
    "sg:address":"110 Professional Park",
    "sg:city":"Beckley",
    "sg:classifiers":[
        {
            "category":"Health Services",
            "subcategory":"Doctor",
            "type":"Services"
        }
    ],
    "sg:phone":"+1 304 252 0931",
    "sg:postcode":"25801",
    "sg:province":"WV",
    "sg:tags":[
        "medical"
    ],
    "wof:name":"Southern Physician Medical",
    "wof:placetype":"venue"
},
  "geometry": {"coordinates":[-81.172173,37.794643],"type":"Point"}
}