{
  "type": "Feature",
  "properties": {
    "addr:full":"3677 US Hwy 60 Barboursville WV 25504",
    "addr:housenumber":"3677",
    "addr:postcode":"25504",
    "addr:street":"Us Hwy 60",
    "iso:country":"US",
    "sg:address":"3677 US Hwy 60",
    "sg:city":"Barboursville",
    "sg:classifiers":[
        {
            "category":"Banks & Credit Unions",
            "subcategory":"Bank",
            "type":"Services"
        }
    ],
    "sg:phone":"+1 304 733 1978",
    "sg:postcode":"25504",
    "sg:province":"WV",
    "sg:tags":[
        "mortgage"
    ],
    "wof:name":"SunTrust",
    "wof:placetype":"venue"
},
  "geometry": {"coordinates":[-82.309675,38.412878],"type":"Point"}
}