{
  "type": "Feature",
  "properties": {
    "addr:full":"501 Washington Pike Wellsburg WV 26070",
    "addr:housenumber":"501",
    "addr:postcode":"26070",
    "addr:street":"Washington Pike",
    "iso:country":"US",
    "sg:address":"501 Washington Pike",
    "sg:city":"Wellsburg",
    "sg:classifiers":[
        {
            "category":"Real Estate",
            "subcategory":"Developer",
            "type":"Services"
        }
    ],
    "sg:phone":"+1 304 737 2700",
    "sg:postcode":"26070",
    "sg:province":"WV",
    "sg:tags":[
        "mobile",
        "home"
    ],
    "wof:name":"Virginia Manor",
    "wof:placetype":"venue"
},
  "geometry": {"coordinates":[-80.59212100000001,40.268026],"type":"Point"}
}