{
  "type": "Feature",
  "properties": {
    "addr:full":"33 S Florida St Buckhannon WV 26201",
    "addr:housenumber":"33",
    "addr:postcode":"26201",
    "addr:street":"S Florida St",
    "iso:country":"US",
    "sg:address":"33 S Florida St",
    "sg:city":"Buckhannon",
    "sg:classifiers":[
        {
            "category":"Personal",
            "subcategory":"Beauty Salon",
            "type":"Services"
        }
    ],
    "sg:phone":"+1 304 472 9003",
    "sg:postcode":"26201",
    "sg:province":"WV",
    "wof:name":"Edna's Hair Studio",
    "wof:placetype":"venue"
},
  "geometry": {"coordinates":[-80.226984,38.991419],"type":"Point"}
}