{
  "type": "Feature",
  "properties": {
    "iso:country":"US",
    "sg:address":"56224 High Ridge Rd",
    "sg:city":"Bellaire",
    "sg:classifiers":[
        {
            "category":"Organizations",
            "subcategory":"Religious Organization",
            "type":"Services"
        }
    ],
    "sg:phone":"+1 740 676 4912",
    "sg:postcode":"43906",
    "sg:province":"OH",
    "sg:tags":[
        "church"
    ],
    "wof:name":"Rock Hill United Presby Church",
    "wof:placetype":"venue"
},
  "geometry": {"coordinates":[-80.771774,40.035417],"type":"Point"}
}