{
  "type": "Feature",
  "properties": {
    "addr:full":"212 E High St Shepherdstown WV 25443",
    "addr:housenumber":"212",
    "addr:postcode":"25443",
    "addr:street":"E High St",
    "iso:country":"US",
    "sg:address":"212 E High St",
    "sg:city":"Shepherdstown",
    "sg:classifiers":[
        {
            "category":"Building & Trades",
            "subcategory":"Landscaping Services",
            "type":"Services"
        }
    ],
    "sg:phone":"+1 304 876 2494",
    "sg:postcode":"25443",
    "sg:province":"WV",
    "sg:tags":[
        "lawn",
        "maintenance",
        "grounds"
    ],
    "wof:name":"Lawn Medic",
    "wof:placetype":"venue"
},
  "geometry": {"coordinates":[-77.803239,39.431292],"type":"Point"}
}