{
  "type": "Feature",
  "properties": {
    "iso:country":"US",
    "sg:address":"870 Middleway Rd",
    "sg:city":"Inwood",
    "sg:classifiers":[
        {
            "category":"Retail",
            "subcategory":"Auto Repair",
            "type":"Services"
        }
    ],
    "sg:phone":"+1 304 229 4877",
    "sg:postcode":"25413",
    "sg:province":"WV",
    "sg:tags":[
        "general"
    ],
    "wof:name":"Powerflow Auto & Truck Repair",
    "wof:placetype":"venue"
},
  "geometry": {"coordinates":[-78.04306,39.307799],"type":"Point"}
}