{
  "type": "Feature",
  "properties": {
    "iso:country":"US",
    "sg:address":"22 Crestview Ln",
    "sg:city":"Fairmont",
    "sg:classifiers":[
        {
            "category":"Professional",
            "subcategory":"Advertising",
            "type":"Services"
        }
    ],
    "sg:phone":"+1 304 368 0020",
    "sg:postcode":"26554",
    "sg:province":"WV",
    "wof:name":"Micro Outdoor Advertising",
    "wof:placetype":"venue"
},
  "geometry": {"coordinates":[-80.159193,39.411509],"type":"Point"}
}