{
  "type": "Feature",
  "properties": {
    "iso:country":"US",
    "sg:address":"6 Ridge Pl",
    "sg:city":"Morgantown",
    "sg:classifiers":[
        {
            "category":"Real Estate",
            "subcategory":"Real Estate Agent",
            "type":"Services"
        }
    ],
    "sg:phone":"+1 304 599 2730",
    "sg:postcode":"26505",
    "sg:province":"WV",
    "wof:name":"Rich Venturse",
    "wof:placetype":"venue"
},
  "geometry": {"coordinates":[-79.93521200000001,39.655046],"type":"Point"}
}