{
  "type": "Feature",
  "properties": {
    "iso:country":"US",
    "sg:address":"112 N 20th St",
    "sg:city":"Wheeling",
    "sg:classifiers":[
        {
            "category":"Building & Trades",
            "subcategory":"Construction",
            "type":"Services"
        }
    ],
    "sg:phone":"+1 304 242 0065",
    "sg:postcode":"26003",
    "sg:province":"WV",
    "sg:tags":[
        "painter"
    ],
    "wof:name":"A Brush Above",
    "wof:placetype":"venue"
},
  "geometry": {"coordinates":[-80.70085400000001,40.120382],"type":"Point"}
}