{
  "type": "Feature",
  "properties": {
    "iso:country":"US",
    "sg:address":"520 20th St",
    "sg:city":"Huntington",
    "sg:classifiers":[
        {
            "category":"Restaurant",
            "type":"Food & Drink"
        }
    ],
    "sg:phone":"+1 304 529 2006",
    "sg:postcode":"25703",
    "sg:province":"WV",
    "sg:tags":[
        "eating"
    ],
    "wof:name":"Tudor's Biscuit World",
    "wof:placetype":"venue"
},
  "geometry": {"coordinates":[-82.422391,38.422752],"type":"Point"}
}