{
  "type": "Feature",
  "properties": {
    "addr:full":"305 N Sturmer St Belington WV 26250",
    "addr:housenumber":"305",
    "addr:postcode":"26250",
    "addr:street":"N Sturmer St",
    "iso:country":"US",
    "sg:address":"305 N Sturmer St",
    "sg:city":"Belington",
    "sg:classifiers":[
        {
            "category":"Health Services",
            "subcategory":"Doctor",
            "type":"Services"
        }
    ],
    "sg:phone":"+1 304 823 2100",
    "sg:postcode":"26250",
    "sg:province":"WV",
    "wof:name":"H Darrell Milem",
    "wof:placetype":"venue"
},
  "geometry": {"coordinates":[-79.93850399999999,39.028919],"type":"Point"}
}