{
  "type": "Feature",
  "properties": {
    "iso:country":"US",
    "sg:address":"1348 Hornbeck Rd",
    "sg:city":"Morgantown",
    "sg:classifiers":[
        {
            "category":"Building & Trades",
            "subcategory":"Equipment Rental",
            "type":"Services"
        }
    ],
    "sg:phone":"+1 304 291 8064",
    "sg:postcode":"26508",
    "sg:province":"WV",
    "wof:name":"Roncon Rentals",
    "wof:placetype":"venue"
},
  "geometry": {"coordinates":[-79.968228,39.552059],"type":"Point"}
}