{
  "type": "Feature",
  "properties": {
    "addr:full":"3545 Collins Ferry Rd Morgantown WV 26505",
    "addr:housenumber":"3545",
    "addr:postcode":"26505",
    "addr:street":"Collins Ferry Rd",
    "iso:country":"US",
    "sg:address":"3545 Collins Ferry Rd",
    "sg:city":"Morgantown",
    "sg:classifiers":[
        {
            "category":"Freight",
            "type":"Transportation"
        }
    ],
    "sg:phone":"+1 304 363 2414",
    "sg:postcode":"26505",
    "sg:province":"WV",
    "sg:tags":[
        "commercial",
        "storage",
        "special"
    ],
    "wof:name":"Mountaineer Self Storage LLC",
    "wof:placetype":"venue"
},
  "geometry": {"coordinates":[-79.97758899999999,39.666183],"type":"Point"}
}