{
  "type": "Feature",
  "properties": {
    "iso:country":"US",
    "sg:address":"205 Church St",
    "sg:city":"Spencer",
    "sg:classifiers":[
        {
            "category":"Professional",
            "subcategory":"Lawyer & Legal Services",
            "type":"Services"
        }
    ],
    "sg:phone":"+1 304 927 1670",
    "sg:postcode":"25276",
    "sg:province":"WV",
    "sg:tags":[
        "attorney"
    ],
    "wof:name":"Palmer & Titus",
    "wof:placetype":"venue"
},
  "geometry": {"coordinates":[-81.349639,38.802192],"type":"Point"}
}