{
  "type": "Feature",
  "properties": {
    "addr:full":"913 Dunbar Ave Dunbar WV 25064",
    "addr:housenumber":"913",
    "addr:postcode":"25064",
    "addr:street":"Dunbar Ave",
    "iso:country":"US",
    "sg:address":"913 Dunbar Ave",
    "sg:city":"Dunbar",
    "sg:classifiers":[
        {
            "category":"Restaurant",
            "type":"Food & Drink"
        }
    ],
    "sg:menulink":"http://www.allmenus.com/wv/davis-creek/195881-wendys/menu/",
    "sg:phone":"+1 304 768 8592",
    "sg:postcode":"25064",
    "sg:province":"WV",
    "sg:tags":[
        "burger",
        "american",
        "soup"
    ],
    "wof:name":"Wendy's",
    "wof:placetype":"venue"
},
  "geometry": {"coordinates":[-81.733465,38.360343],"type":"Point"}
}