{
  "type": "Feature",
  "properties": {
    "iso:country":"US",
    "sg:address":"5308 Williamsport Pike",
    "sg:city":"Martinsburg",
    "sg:phone":"+1 304 274 6592",
    "sg:postcode":"25404",
    "sg:province":"WV",
    "sg:website":"http://www.mhsbb.com",
    "wof:name":"Potomack Intermediate School",
    "wof:placetype":"venue"
},
  "geometry": {"coordinates":[-77.90732199999999,39.541902],"type":"Point"}
}