{
  "type": "Feature",
  "properties": {
    "addr:full":"207 Water Ave Weston WV 26452",
    "addr:housenumber":"207",
    "addr:postcode":"26452",
    "addr:street":"Water Ave",
    "iso:country":"US",
    "sg:address":"207 Water Ave",
    "sg:city":"Weston",
    "sg:classifiers":[
        {
            "category":"Retail",
            "subcategory":"Animal Services",
            "type":"Services"
        }
    ],
    "sg:phone":"+1 304 269 5799",
    "sg:postcode":"26452",
    "sg:province":"WV",
    "sg:tags":[
        "pet",
        "grooming",
        "washing"
    ],
    "wof:name":"Doggy Den",
    "wof:placetype":"venue"
},
  "geometry": {"coordinates":[-80.46510000000001,39.041343],"type":"Point"}
}