{
  "type": "Feature",
  "properties": {
    "addr:full":"211 Pleasant St Hinton WV 25951",
    "addr:housenumber":"211",
    "addr:postcode":"25951",
    "addr:street":"Pleasant St",
    "iso:country":"US",
    "sg:address":"211 Pleasant St",
    "sg:city":"Hinton",
    "sg:classifiers":[
        {
            "category":"Insurance",
            "subcategory":"Insurance Agent",
            "type":"Services"
        }
    ],
    "sg:phone":"+1 304 466 3290",
    "sg:postcode":"25951",
    "sg:province":"WV",
    "wof:name":"State Farm Insurance",
    "wof:placetype":"venue"
},
  "geometry": {"coordinates":[-80.893455,37.66445],"type":"Point"}
}