{
  "type": "Feature",
  "properties": {
    "iso:country":"US",
    "sg:address":"401 Tomlinson Ave",
    "sg:city":"Moundsville",
    "sg:classifiers":[
        {
            "category":"Recreation",
            "type":"Entertainment"
        }
    ],
    "sg:phone":"+1 304 845 9175",
    "sg:postcode":"26041",
    "sg:province":"WV",
    "sg:tags":[
        "pool",
        "swimming"
    ],
    "wof:name":"Spurr Memorial Playground Inc",
    "wof:placetype":"venue"
},
  "geometry": {"coordinates":[-80.745099,39.920708],"type":"Point"}
}