{
  "type": "Feature",
  "properties": {
    "addr:full":"1241 W Main St Bridgeport WV 26330",
    "addr:housenumber":"1241",
    "addr:postcode":"26330",
    "addr:street":"W Main St",
    "iso:country":"US",
    "sg:address":"1241 W Main St",
    "sg:city":"Bridgeport",
    "sg:classifiers":[
        {
            "category":"Restaurant",
            "type":"Food & Drink"
        }
    ],
    "sg:phone":"+1 304 842 4917",
    "sg:postcode":"26330",
    "sg:province":"WV",
    "sg:tags":[
        "eating"
    ],
    "wof:name":"Wendys",
    "wof:placetype":"venue"
},
  "geometry": {"coordinates":[-80.27766800000001,39.28089],"type":"Point"}
}