{
  "type": "Feature",
  "properties": {
    "iso:country":"US",
    "sg:address":"58 16th St",
    "sg:city":"Wheeling",
    "sg:classifiers":[
        {
            "category":"Health Services",
            "subcategory":"Hospital",
            "type":"Services"
        }
    ],
    "sg:phone":"+1 304 243 4663",
    "sg:postcode":"26003",
    "sg:province":"WV",
    "wof:name":"VNA Of Medical Park",
    "wof:placetype":"venue"
},
  "geometry": {"coordinates":[-80.71848300000001,40.064232],"type":"Point"}
}