{
  "type": "Feature",
  "properties": {
    "iso:country":"US",
    "sg:address":"130 Goff Mountain Rd",
    "sg:city":"Charleston",
    "sg:classifiers":[
        {
            "category":"Shopping",
            "subcategory":"Optical Goods",
            "type":"Retail Goods"
        }
    ],
    "sg:phone":"+1 304 776 5594",
    "sg:postcode":"25313",
    "sg:province":"WV",
    "wof:name":"Maxwell Eyecare Center In",
    "wof:placetype":"venue"
},
  "geometry": {"coordinates":[-81.7936,38.417594],"type":"Point"}
}