{
  "type": "Feature",
  "properties": {
    "addr:full":"839 N Jefferson St Lewisburg WV 24901",
    "addr:housenumber":"839",
    "addr:postcode":"24901",
    "addr:street":"N Jefferson St",
    "iso:country":"US",
    "sg:address":"839 N Jefferson St",
    "sg:city":"Lewisburg",
    "sg:classifiers":[
        {
            "category":"Retail",
            "subcategory":"Car Wash",
            "type":"Services"
        }
    ],
    "sg:phone":"+1 304 645 1445",
    "sg:postcode":"24901",
    "sg:province":"WV",
    "sg:tags":[
        "polishing",
        "washing"
    ],
    "wof:name":"Car Wash Consultants",
    "wof:placetype":"venue"
},
  "geometry": {"coordinates":[-80.423742,37.82088],"type":"Point"}
}