{
  "type": "Feature",
  "properties": {
    "addr:full":"204 Cyrus Pt Charleston WV 25314",
    "addr:housenumber":"204",
    "addr:postcode":"25314",
    "addr:street":"Cyrus Pt",
    "iso:country":"US",
    "sg:address":"204 Cyrus Pt",
    "sg:city":"Charleston",
    "sg:classifiers":[
        {
            "category":"Professional",
            "type":"Services"
        }
    ],
    "sg:phone":"+1 304 343 3277",
    "sg:postcode":"25314",
    "sg:province":"WV",
    "wof:name":"Cmd Plus Inc",
    "wof:placetype":"venue"
},
  "geometry": {"coordinates":[-81.67313900000001,38.333759],"type":"Point"}
}