{
  "type": "Feature",
  "properties": {
    "iso:country":"US",
    "sg:address":"216 Washington St W",
    "sg:city":"Charleston",
    "sg:classifiers":[
        {
            "category":"Restaurant",
            "type":"Food & Drink"
        }
    ],
    "sg:phone":"+1 304 342 2621",
    "sg:postcode":"25302",
    "sg:province":"WV",
    "wof:name":"Big Daddy's Family Restaurant",
    "wof:placetype":"venue"
},
  "geometry": {"coordinates":[-81.640922,38.360484],"type":"Point"}
}