{
  "type": "Feature",
  "properties": {
    "iso:country":"US",
    "sg:address":"101 W Main St",
    "sg:city":"Paden City",
    "sg:classifiers":[
        {
            "category":"Health Services",
            "subcategory":"Doctor",
            "type":"Services"
        }
    ],
    "sg:phone":"+1 304 337 2626",
    "sg:postcode":"26159",
    "sg:province":"WV",
    "sg:tags":[
        "dentist"
    ],
    "wof:name":"Kelvin W Feather DDS",
    "wof:placetype":"venue"
},
  "geometry": {"coordinates":[-80.934538,39.60417],"type":"Point"}
}