{
  "type": "Feature",
  "properties": {
    "addr:full":"111 Wedgewood Dr Parkersburg WV 26104",
    "addr:housenumber":"111",
    "addr:postcode":"26104",
    "addr:street":"Wedgewood Dr",
    "iso:country":"US",
    "sg:address":"111 Wedgewood Dr",
    "sg:city":"Parkersburg",
    "sg:classifiers":[
        {
            "category":"Real Estate",
            "subcategory":"Real Estate Agent",
            "type":"Services"
        }
    ],
    "sg:phone":"+1 304 422 4969",
    "sg:postcode":"26104",
    "sg:province":"WV",
    "sg:tags":[
        "appraiser"
    ],
    "wof:name":"Randy D Reed MAI & Assoc",
    "wof:placetype":"venue"
},
  "geometry": {"coordinates":[-81.509417,39.318733],"type":"Point"}
}