{
  "type": "Feature",
  "properties": {
    "iso:country":"US",
    "sg:address":"7000 Webster St",
    "sg:city":"Cowen",
    "sg:classifiers":[
        {
            "category":"Retail",
            "subcategory":"Funeral Services",
            "type":"Services"
        }
    ],
    "sg:phone":"+1 304 226 3000",
    "sg:postcode":"26206",
    "sg:province":"WV",
    "sg:tags":[
        "director"
    ],
    "wof:name":"Adams-Reed Funeral Home",
    "wof:placetype":"venue"
},
  "geometry": {"coordinates":[-80.555376,38.409124],"type":"Point"}
}