{
  "type": "Feature",
  "properties": {
    "iso:country":"US",
    "sg:address":"702 Grand Central Ave",
    "sg:city":"Vienna",
    "sg:classifiers":[
        {
            "category":"Shopping",
            "subcategory":"Shoes",
            "type":"Retail Goods"
        }
    ],
    "sg:phone":"+1 304 295 8333",
    "sg:postcode":"26105",
    "sg:province":"WV",
    "wof:name":"Bee-Gee Shoes Corp",
    "wof:placetype":"venue"
},
  "geometry": {"coordinates":[-81.55049,39.305115],"type":"Point"}
}