{
  "type": "Feature",
  "properties": {
    "iso:country":"US",
    "sg:address":"1006 US Hwy 33",
    "sg:city":"Weston",
    "sg:classifiers":[
        {
            "category":"Home & Garden",
            "subcategory":"Garden Supply",
            "type":"Retail Goods"
        }
    ],
    "sg:phone":"+1 304 269 3472",
    "sg:postcode":"26452",
    "sg:province":"WV",
    "wof:name":"Plant Seed LLC",
    "wof:placetype":"venue"
},
  "geometry": {"coordinates":[-80.46553400000001,39.039283],"type":"Point"}
}