{
  "type": "Feature",
  "properties": {
    "iso:country":"US",
    "sg:address":"3509 Maccorkle Ave SE",
    "sg:city":"Charleston",
    "sg:classifiers":[
        {
            "category":"Coffee & Tea",
            "type":"Food & Drink"
        },
        {
            "category":"Bakery",
            "type":"Food & Drink"
        },
        {
            "category":"Donuts",
            "type":"Food & Drink"
        }
    ],
    "sg:menulink":"http://www.allmenus.com/wv/davis-creek/222523-donut-connection/menu/",
    "sg:phone":"+1 304 925 4261",
    "sg:postcode":"25304",
    "sg:province":"WV",
    "sg:tags":[
        "american",
        "pastry"
    ],
    "wof:name":"Donut Connection",
    "wof:placetype":"venue"
},
  "geometry": {"coordinates":[-81.59843499999999,38.328264],"type":"Point"}
}