{
  "type": "Feature",
  "properties": {
    "iso:country":"US",
    "sg:address":"3927 Palisades Dr",
    "sg:city":"Weirton",
    "sg:classifiers":[
        {
            "category":"Real Estate",
            "subcategory":"Real Estate Agent",
            "type":"Services"
        }
    ],
    "sg:phone":"+1 304 797 0020",
    "sg:postcode":"26062",
    "sg:province":"WV",
    "wof:name":"Donna Fante Realty",
    "wof:placetype":"venue"
},
  "geometry": {"coordinates":[-80.610187,40.398958],"type":"Point"}
}