{
  "type": "Feature",
  "properties": {
    "iso:country":"US",
    "sg:address":"1101 Olde Pine Dr",
    "sg:city":"Hurricane",
    "sg:classifiers":[
        {
            "category":"Building & Trades",
            "subcategory":"Construction",
            "type":"Services"
        }
    ],
    "sg:phone":"+1 304 757 9422",
    "sg:postcode":"25526",
    "sg:province":"WV",
    "sg:tags":[
        "general",
        "contractor"
    ],
    "wof:name":"Danlin Homes Inc",
    "wof:placetype":"venue"
},
  "geometry": {"coordinates":[-81.97674000000001,38.451031],"type":"Point"}
}