{
  "type": "Feature",
  "properties": {
    "addr:full":"1573 Nottingham Rd Charleston WV 25314",
    "addr:housenumber":"1573",
    "addr:postcode":"25314",
    "addr:street":"Nottingham Rd",
    "iso:country":"US",
    "sg:address":"1573 Nottingham Rd",
    "sg:city":"Charleston",
    "sg:classifiers":[
        {
            "category":"Shopping",
            "subcategory":"Clothing, Apparel, & Fashions",
            "type":"Retail Goods"
        }
    ],
    "sg:phone":"+1 304 744 4315",
    "sg:postcode":"25314",
    "sg:province":"WV",
    "sg:tags":[
        "woman",
        "maternity",
        "wear",
        "child"
    ],
    "wof:name":"Mom & ME",
    "wof:placetype":"venue"
},
  "geometry": {"coordinates":[-81.697935,38.33607],"type":"Point"}
}