{
  "type": "Feature",
  "properties": {
    "iso:country":"US",
    "sg:address":"2276 Harper Rd",
    "sg:city":"Beckley",
    "sg:classifiers":[
        {
            "category":"Building & Trades",
            "subcategory":"Construction",
            "type":"Services"
        }
    ],
    "sg:phone":"+1 304 252 3652",
    "sg:postcode":"25801",
    "sg:province":"WV",
    "sg:tags":[
        "excavation",
        "wholesaler",
        "material",
        "contractor"
    ],
    "wof:name":"Sam Shrewsbury Excavating",
    "wof:placetype":"venue"
},
  "geometry": {"coordinates":[-81.230746,37.79849],"type":"Point"}
}