{
  "type": "Feature",
  "properties": {
    "addr:full":"807 Oak St Kenova WV 25530",
    "addr:housenumber":"807",
    "addr:postcode":"25530",
    "addr:street":"Oak St",
    "iso:country":"US",
    "sg:address":"807 Oak St",
    "sg:city":"Kenova",
    "sg:classifiers":[
        {
            "category":"Home & Garden",
            "subcategory":"Carpets & Floor Coverings",
            "type":"Retail Goods"
        }
    ],
    "sg:phone":"+1 304 453 6706",
    "sg:postcode":"25530",
    "sg:province":"WV",
    "wof:name":"Tri State Floor Covering",
    "wof:placetype":"venue"
},
  "geometry": {"coordinates":[-82.56943099999999,38.398751],"type":"Point"}
}