{
  "type": "Feature",
  "properties": {
    "iso:country":"US",
    "sg:address":"184 Central St",
    "sg:city":"Lester",
    "sg:classifiers":[
        {
            "category":"Autos & Motor Vehicles",
            "subcategory":"Auto Supplies",
            "type":"Retail Goods"
        }
    ],
    "sg:phone":"+1 304 934 5972",
    "sg:postcode":"25865",
    "sg:province":"WV",
    "sg:tags":[
        "automobile",
        "parts"
    ],
    "wof:name":"Garage On Wheels",
    "wof:placetype":"venue"
},
  "geometry": {"coordinates":[-81.30320399999999,37.738662],"type":"Point"}
}