{
  "type": "Feature",
  "properties": {
    "iso:country":"US",
    "sg:address":"2 High Point Dr",
    "sg:city":"Buckhannon",
    "sg:classifiers":[
        {
            "category":"Building & Trades",
            "subcategory":"Construction",
            "type":"Services"
        }
    ],
    "sg:phone":"+1 304 472 6705",
    "sg:postcode":"26201",
    "sg:province":"WV",
    "sg:tags":[
        "contracting",
        "commercial",
        "general"
    ],
    "wof:name":"Tks Contracting Inc",
    "wof:placetype":"venue"
},
  "geometry": {"coordinates":[-80.22738,38.975374],"type":"Point"}
}