{
  "type": "Feature",
  "properties": {
    "addr:full":"1197 Van Voorhis Rd Morgantown WV 26505",
    "addr:housenumber":"1197",
    "addr:postcode":"26505",
    "addr:street":"Van Voorhis Rd",
    "iso:country":"US",
    "sg:address":"1197 Van Voorhis Rd",
    "sg:city":"Morgantown",
    "sg:classifiers":[
        {
            "category":"Health Services",
            "subcategory":"Doctor",
            "type":"Services"
        }
    ],
    "sg:phone":"+1 304 599 9400",
    "sg:postcode":"26505",
    "sg:province":"WV",
    "sg:tags":[
        "physician",
        "family",
        "practice",
        "surgeons",
        "medicine",
        "psychiatry",
        "surgeon"
    ],
    "sg:website":"http://www.wedgewood-fp.com",
    "wof:name":"Wedgewood Family Practice Inc",
    "wof:placetype":"venue"
},
  "geometry": {"coordinates":[-79.963375,39.657373],"type":"Point"}
}