{
  "type": "Feature",
  "properties": {
    "iso:country":"US",
    "sg:address":"700 Charles St",
    "sg:city":"Wellsburg",
    "sg:classifiers":[
        {
            "category":"Insurance",
            "subcategory":"Hazard Insurance",
            "type":"Services"
        }
    ],
    "sg:phone":"+1 304 737 0713",
    "sg:postcode":"26070",
    "sg:province":"WV",
    "sg:website":"http://statefarm.mqgroup.com/url.asp?usr=481482",
    "wof:name":"State Farm Insurance Agent-Bill Garvey",
    "wof:placetype":"venue"
},
  "geometry": {"coordinates":[-80.614407,40.263996],"type":"Point"}
}