{
  "type": "Feature",
  "properties": {
    "iso:country":"US",
    "sg:address":"128 Industrial Cir",
    "sg:city":"Kearneysville",
    "sg:classifiers":[
        {
            "category":"Home & Garden",
            "subcategory":"Building Materials",
            "type":"Retail Goods"
        },
        {
            "category":"Manufacturing",
            "subcategory":"Lumber",
            "type":"Manufacturing & Wholesale Goods"
        }
    ],
    "sg:phone":"+1 304 728 0120",
    "sg:postcode":"25403",
    "sg:province":"WV",
    "sg:tags":[
        "hardwood"
    ],
    "wof:name":"McDaniel Hardwood Products LLC",
    "wof:placetype":"venue"
},
  "geometry": {"coordinates":[-79.494767,39.553143],"type":"Point"}
}