{
  "type": "Feature",
  "properties": {
    "iso:country":"US",
    "sg:address":"104 4th St",
    "sg:city":"Charles Town",
    "sg:classifiers":[
        {
            "category":"Organizations",
            "subcategory":"Non-profit Organization",
            "type":"Services"
        }
    ],
    "sg:phone":"+1 304 725 3935",
    "sg:postcode":"25414",
    "sg:province":"WV",
    "sg:tags":[
        "breastfeeding",
        "information",
        "supply"
    ],
    "wof:name":"LA Leche League-Jefferson Cnty",
    "wof:placetype":"venue"
},
  "geometry": {"coordinates":[-77.85002299999999,39.288432],"type":"Point"}
}