{
  "type": "Feature",
  "properties": {
    "iso:country":"US",
    "sg:address":"201 N Court St",
    "sg:city":"Glenville",
    "sg:classifiers":[
        {
            "category":"Education",
            "subcategory":"School",
            "type":"Public Place"
        }
    ],
    "sg:phone":"+1 304 462 7386",
    "sg:postcode":"26351",
    "sg:province":"WV",
    "wof:name":"Gilmer County Board-Education",
    "wof:placetype":"venue"
},
  "geometry": {"coordinates":[-80.835346,38.934872],"type":"Point"}
}