{
  "type": "Feature",
  "properties": {
    "iso:country":"US",
    "sg:address":"120 Franklin Hts",
    "sg:city":"Fayetteville",
    "sg:classifiers":[
        {
            "category":"Building & Trades",
            "subcategory":"Construction",
            "type":"Services"
        }
    ],
    "sg:phone":"+1 304 574 1979",
    "sg:postcode":"25840",
    "sg:province":"WV",
    "sg:tags":[
        "excavation",
        "contractor"
    ],
    "wof:name":"Steves Escavating",
    "wof:placetype":"venue"
},
  "geometry": {"coordinates":[-81.11563700000001,38.054438],"type":"Point"}
}