{
  "type": "Feature",
  "properties": {
    "iso:country":"US",
    "sg:address":"1012 University Ave",
    "sg:city":"Morgantown",
    "sg:classifiers":[
        {
            "category":"Autos & Motor Vehicles",
            "subcategory":"Automobile Sales",
            "type":"Retail Goods"
        },
        {
            "category":"Retail",
            "subcategory":"Auto Repair",
            "type":"Services"
        }
    ],
    "sg:phone":"+1 304 906 4811",
    "sg:postcode":"26505",
    "sg:province":"WV",
    "sg:tags":[
        "car",
        "used",
        "new"
    ],
    "sg:website":"http://www.gmofwv.com/",
    "wof:name":"Premier Buick Pontiac & GMC",
    "wof:placetype":"venue"
},
  "geometry": {"coordinates":[-79.959643,39.628318],"type":"Point"}
}