{
  "type": "Feature",
  "properties": {
    "addr:full":"7400 Maccorkle Ave SE Charleston WV 25304",
    "addr:housenumber":"7400",
    "addr:postcode":"25304",
    "addr:street":"Maccorkle Ave Se",
    "iso:country":"US",
    "sg:address":"7400 Maccorkle Ave SE",
    "sg:city":"Charleston",
    "sg:classifiers":[
        {
            "category":"Food & Beverages",
            "subcategory":"Bakery",
            "type":"Retail Goods"
        },
        {
            "category":"Wholesale",
            "subcategory":"Groceries",
            "type":"Manufacturing & Wholesale Goods"
        }
    ],
    "sg:phone":"+1 304 925 4149",
    "sg:postcode":"25304",
    "sg:province":"WV",
    "sg:tags":[
        "product",
        "baker",
        "mfg"
    ],
    "wof:name":"Flowers Baking Co",
    "wof:placetype":"venue"
},
  "geometry": {"coordinates":[-81.57261,38.279229],"type":"Point"}
}