{
  "type": "Feature",
  "properties": {
    "iso:country":"US",
    "sg:address":"212 Main St",
    "sg:city":"Parsons",
    "sg:classifiers":[
        {
            "category":"Manufacturing",
            "subcategory":"Printing",
            "type":"Manufacturing & Wholesale Goods"
        }
    ],
    "sg:phone":"+1 304 478 3533",
    "sg:postcode":"26287",
    "sg:province":"WV",
    "sg:tags":[
        "newspaper"
    ],
    "wof:name":"Parsons Advocate Newspaper",
    "wof:placetype":"venue"
},
  "geometry": {"coordinates":[-79.68218400000001,39.098005],"type":"Point"}
}