{
  "type": "Feature",
  "properties": {
    "addr:full":"1501 University Town Centre Dr Morgantown WV 26501",
    "addr:housenumber":"1501",
    "addr:postcode":"26501",
    "addr:street":"University Town Centre Dr",
    "iso:country":"US",
    "sg:address":"1501 University Town Centre Dr",
    "sg:city":"Morgantown",
    "sg:classifiers":[
        {
            "category":"Restaurant",
            "type":"Food & Drink"
        }
    ],
    "sg:menulink":"http://www.allmenus.com/wv/western/246886-cheddars/menu/",
    "sg:phone":"+1 304 598 3233",
    "sg:postcode":"26501",
    "sg:province":"WV",
    "sg:tags":[
        "american"
    ],
    "wof:name":"Cheddars",
    "wof:placetype":"venue"
},
  "geometry": {"coordinates":[-80.006225,39.653597],"type":"Point"}
}