{
  "type": "Feature",
  "properties": {
    "addr:full":"20 Medical Park Wheeling WV 26003",
    "addr:housenumber":"20",
    "addr:postcode":"26003",
    "addr:street":"Medical Park",
    "iso:country":"US",
    "sg:address":"20 Medical Park",
    "sg:city":"Wheeling",
    "sg:classifiers":[
        {
            "category":"Health Services",
            "subcategory":"Doctor",
            "type":"Services"
        }
    ],
    "sg:phone":"+1 304 242 9245",
    "sg:postcode":"26003",
    "sg:province":"WV",
    "sg:tags":[
        "physician",
        "surgeon"
    ],
    "wof:name":"Raymond A Bannan LLC",
    "wof:placetype":"venue"
},
  "geometry": {"coordinates":[-80.695402,40.067187],"type":"Point"}
}