{
  "type": "Feature",
  "properties": {
    "iso:country":"US",
    "sg:address":"705 Garfield Ave",
    "sg:city":"Parkersburg",
    "sg:classifiers":[
        {
            "category":"Health Services",
            "subcategory":"Doctor",
            "type":"Services"
        }
    ],
    "sg:phone":"+1 304 485 2387",
    "sg:postcode":"26101",
    "sg:province":"WV",
    "sg:tags":[
        "physician",
        "surgeon",
        "medical"
    ],
    "wof:name":"Peter P Filozof MD Facog",
    "wof:placetype":"venue"
},
  "geometry": {"coordinates":[-81.561319,39.269394],"type":"Point"}
}