{
  "type": "Feature",
  "properties": {
    "iso:country":"US",
    "sg:address":"1200 J D Anderson Dr",
    "sg:city":"Morgantown",
    "sg:classifiers":[
        {
            "category":"Shopping",
            "subcategory":"Gifts & Souvenirs",
            "type":"Retail Goods"
        }
    ],
    "sg:phone":"+1 304 598 1322",
    "sg:postcode":"26505",
    "sg:province":"WV",
    "wof:name":"Auxiliary of Monogalia General",
    "wof:placetype":"venue"
},
  "geometry": {"coordinates":[-79.946704,39.661943],"type":"Point"}
}