{
  "type": "Feature",
  "properties": {
    "addr:full":"1401 6th Ave Huntington WV 25701",
    "addr:housenumber":"1401",
    "addr:postcode":"25701",
    "addr:street":"6Th Ave",
    "iso:country":"US",
    "sg:address":"1401 6th Ave",
    "sg:city":"Huntington",
    "sg:classifiers":[
        {
            "category":"Health Services",
            "subcategory":"Doctor",
            "type":"Services"
        }
    ],
    "sg:phone":"+1 304 523 8800",
    "sg:postcode":"25701",
    "sg:province":"WV",
    "sg:tags":[
        "medical"
    ],
    "wof:name":"Sharma Tara C",
    "wof:placetype":"venue"
},
  "geometry": {"coordinates":[-82.432785,38.419796],"type":"Point"}
}