{
  "type": "Feature",
  "properties": {
    "iso:country":"US",
    "sg:address":"4804 4th Ave",
    "sg:city":"Parkersburg",
    "sg:classifiers":[
        {
            "category":"Organizations",
            "subcategory":"Religious Organization",
            "type":"Services"
        }
    ],
    "sg:phone":"+1 304 428 9777",
    "sg:postcode":"26101",
    "sg:province":"WV",
    "wof:name":"Edgelawn United Methdst Church",
    "wof:placetype":"venue"
},
  "geometry": {"coordinates":[-81.51633099999999,39.230107],"type":"Point"}
}