{
  "type": "Feature",
  "properties": {
    "iso:country":"US",
    "sg:address":"303 Lafayette Ave",
    "sg:city":"Moundsville",
    "sg:classifiers":[
        {
            "category":"Recreation",
            "subcategory":"Picnic Area",
            "type":"Entertainment"
        }
    ],
    "sg:phone":"+1 304 843 1009",
    "sg:postcode":"26041",
    "sg:province":"WV",
    "sg:tags":[
        "place",
        "arcade",
        "amusement"
    ],
    "wof:name":"Ohio Valley Amusement",
    "wof:placetype":"venue"
},
  "geometry": {"coordinates":[-80.757324,39.90551],"type":"Point"}
}