{
  "type": "Feature",
  "properties": {
    "iso:country":"US",
    "sg:address":"203 12th St Exd",
    "sg:city":"Princeton",
    "sg:classifiers":[
        {
            "category":"Health Services",
            "subcategory":"Clinic",
            "type":"Services"
        }
    ],
    "sg:phone":"+1 800 442 3270",
    "sg:postcode":"24740",
    "sg:province":"WV",
    "sg:tags":[
        "home",
        "care"
    ],
    "wof:name":"P C H Home Health",
    "wof:placetype":"venue"
},
  "geometry": {"coordinates":[-81.11432000000001,37.362078],"type":"Point"}
}