{
  "type": "Feature",
  "properties": {
    "iso:country":"US",
    "sg:address":"101 Smitherman Rd",
    "sg:city":"Washington",
    "sg:classifiers":[
        {
            "category":"Retail",
            "subcategory":"Repair Shop",
            "type":"Services"
        }
    ],
    "sg:phone":"+1 304 863 5178",
    "sg:postcode":"26181",
    "sg:province":"WV",
    "sg:tags":[
        "sheet",
        "mfg",
        "trucking",
        "operator",
        "local",
        "welding"
    ],
    "wof:name":"Woodys Welding",
    "wof:placetype":"venue"
},
  "geometry": {"coordinates":[-81.645887,39.248025],"type":"Point"}
}