{
  "type": "Feature",
  "properties": {
    "iso:country":"US",
    "sg:address":"3538 Haneys Branch Rd",
    "sg:city":"Huntington",
    "sg:classifiers":[
        {
            "category":"Professional",
            "subcategory":"Computer Services",
            "type":"Services"
        }
    ],
    "sg:phone":"+1 304 429 5264",
    "sg:postcode":"25704",
    "sg:province":"WV",
    "sg:tags":[
        "datum"
    ],
    "wof:name":"Isaacs John",
    "wof:placetype":"venue"
},
  "geometry": {"coordinates":[-82.491766,38.353477],"type":"Point"}
}