{
  "type": "Feature",
  "properties": {
    "addr:full":"1440 National Rd Wheeling WV 26003",
    "addr:housenumber":"1440",
    "addr:postcode":"26003",
    "addr:street":"National Rd",
    "iso:country":"US",
    "sg:address":"1440 National Rd",
    "sg:city":"Wheeling",
    "sg:classifiers":[
        {
            "category":"Professional",
            "subcategory":"Lawyer & Legal Services",
            "type":"Services"
        }
    ],
    "sg:phone":"+1 304 242 2900",
    "sg:postcode":"26003",
    "sg:province":"WV",
    "sg:tags":[
        "attorney",
        "law",
        "malpractice"
    ],
    "wof:name":"Gregory A Gellner",
    "wof:placetype":"venue"
},
  "geometry": {"coordinates":[-80.679024,40.066292],"type":"Point"}
}