{
  "type": "Feature",
  "properties": {
    "iso:country":"US",
    "sg:address":"110 E Main St",
    "sg:city":"Glenville",
    "sg:classifiers":[
        {
            "category":"Real Estate",
            "subcategory":"Real Estate Agent",
            "type":"Services"
        }
    ],
    "sg:phone":"+1 304 462 7039",
    "sg:postcode":"26351",
    "sg:province":"WV",
    "wof:name":"Town & Country Agency Inc",
    "wof:placetype":"venue"
},
  "geometry": {"coordinates":[-80.837086,38.933642],"type":"Point"}
}