{
  "type": "Feature",
  "properties": {
    "addr:full":"28 Main St Cameron WV 26033",
    "addr:housenumber":"28",
    "addr:postcode":"26033",
    "addr:street":"Main St",
    "iso:country":"US",
    "sg:address":"28 Main St",
    "sg:city":"Cameron",
    "sg:classifiers":[
        {
            "category":"Personal",
            "subcategory":"Beauty Salon",
            "type":"Services"
        }
    ],
    "sg:phone":"+1 304 686 3117",
    "sg:postcode":"26033",
    "sg:province":"WV",
    "wof:name":"Shear Pleasure",
    "wof:placetype":"venue"
},
  "geometry": {"coordinates":[-80.567128,39.826893],"type":"Point"}
}