{
  "type": "Feature",
  "properties": {
    "iso:country":"US",
    "sg:address":"625 8th St",
    "sg:city":"Huntington",
    "sg:classifiers":[
        {
            "category":"Organizations",
            "subcategory":"Non-profit Organization",
            "type":"Services"
        }
    ],
    "sg:phone":"+1 304 697 1269",
    "sg:postcode":"25701",
    "sg:province":"WV",
    "sg:tags":[
        "information",
        "alcoholism",
        "treatment"
    ],
    "wof:name":"Prestera's Addictions Recovery",
    "wof:placetype":"venue"
},
  "geometry": {"coordinates":[-82.444805,38.417363],"type":"Point"}
}