{
  "type": "Feature",
  "properties": {
    "iso:country":"US",
    "sg:address":"310 Battle St",
    "sg:city":"Philippi",
    "sg:classifiers":[
        {
            "category":"Building & Trades",
            "subcategory":"Plumbing",
            "type":"Services"
        }
    ],
    "sg:phone":"+1 304 457 2821",
    "sg:postcode":"26416",
    "sg:province":"WV",
    "sg:tags":[
        "septic"
    ],
    "wof:name":"A-1 Septic Tank Cleaning Svc",
    "wof:placetype":"venue"
},
  "geometry": {"coordinates":[-80.036987,39.145922],"type":"Point"}
}