{
  "type": "Feature",
  "properties": {
    "addr:full":"6202 Maccorkle Ave Saint Albans WV 25177",
    "addr:housenumber":"6202",
    "addr:postcode":"25177",
    "addr:street":"Maccorkle Ave",
    "iso:country":"US",
    "sg:address":"6202 Maccorkle Ave",
    "sg:city":"Saint Albans",
    "sg:classifiers":[
        {
            "category":"Wholesale",
            "subcategory":"Electrical",
            "type":"Manufacturing & Wholesale Goods"
        }
    ],
    "sg:phone":"+1 304 768 9422",
    "sg:postcode":"25177",
    "sg:province":"WV",
    "sg:tags":[
        "equipment",
        "mfr",
        "lighting",
        "representative"
    ],
    "wof:name":"Repco II Inc",
    "wof:placetype":"venue"
},
  "geometry": {"coordinates":[-81.759411,38.361511],"type":"Point"}
}