{
  "type": "Feature",
  "properties": {
    "iso:country":"US",
    "sg:address":"4818 Rosemar Rd",
    "sg:city":"Parkersburg",
    "sg:classifiers":[
        {
            "category":"Building & Trades",
            "subcategory":"Cleaning & Sanitation",
            "type":"Services"
        }
    ],
    "sg:phone":"+1 304 424 5220",
    "sg:postcode":"26104",
    "sg:province":"WV",
    "sg:tags":[
        "house"
    ],
    "wof:name":"Housecleaning Plus",
    "wof:placetype":"venue"
},
  "geometry": {"coordinates":[-81.52532600000001,39.299701],"type":"Point"}
}