{
  "type": "Feature",
  "properties": {
    "iso:country":"US",
    "sg:address":"3626 Central Ave",
    "sg:city":"Shadyside",
    "sg:classifiers":[
        {
            "category":"Autos & Motor Vehicles",
            "subcategory":"Motorcycle Sales",
            "type":"Retail Goods"
        }
    ],
    "sg:phone":"+1 740 676 4722",
    "sg:postcode":"43947",
    "sg:province":"OH",
    "sg:tags":[
        "scooter"
    ],
    "wof:name":"Honda Direct Line",
    "wof:placetype":"venue"
},
  "geometry": {"coordinates":[-80.744873,39.975032],"type":"Point"}
}