{
  "type": "Feature",
  "properties": {
    "addr:full":"124 E 4th St Weston WV 26452",
    "addr:housenumber":"124",
    "addr:postcode":"26452",
    "addr:street":"E 4Th St",
    "iso:country":"US",
    "sg:address":"124 E 4th St",
    "sg:city":"Weston",
    "sg:classifiers":[
        {
            "category":"Organizations",
            "subcategory":"Religious Organization",
            "type":"Services"
        }
    ],
    "sg:phone":"+1 304 269 2947",
    "sg:postcode":"26452",
    "sg:province":"WV",
    "sg:tags":[
        "church"
    ],
    "wof:name":"Church Of God",
    "wof:placetype":"venue"
},
  "geometry": {"coordinates":[-80.463959,39.040606],"type":"Point"}
}