{
  "type": "Feature",
  "properties": {
    "addr:full":"508 30th St Vienna WV 26105",
    "addr:housenumber":"508",
    "addr:postcode":"26105",
    "addr:street":"30Th St",
    "iso:country":"US",
    "sg:address":"508 30th St",
    "sg:city":"Vienna",
    "sg:classifiers":[
        {
            "category":"Professional",
            "subcategory":"Research",
            "type":"Services"
        }
    ],
    "sg:phone":"+1 304 580 9090",
    "sg:postcode":"26105",
    "sg:province":"WV",
    "sg:tags":[
        "environmental",
        "ecological"
    ],
    "wof:name":"Guardian Environmental Svc",
    "wof:placetype":"venue"
},
  "geometry": {"coordinates":[-81.54888200000001,39.325483],"type":"Point"}
}