{
  "type": "Feature",
  "properties": {
    "addr:full":"250 White Bell Cir Wellsburg WV 26070",
    "addr:housenumber":"250",
    "addr:postcode":"26070",
    "addr:street":"White Bell Cir",
    "iso:country":"US",
    "sg:address":"250 White Bell Cir",
    "sg:city":"Wellsburg",
    "sg:classifiers":[
        {
            "category":"Restaurant",
            "type":"Food & Drink"
        }
    ],
    "sg:phone":"+1 304 737 2491",
    "sg:postcode":"26070",
    "sg:province":"WV",
    "sg:tags":[
        "eating"
    ],
    "wof:name":"De Felice Brothers Pizza",
    "wof:placetype":"venue"
},
  "geometry": {"coordinates":[-80.598268,40.279254],"type":"Point"}
}