{
  "type": "Feature",
  "properties": {
    "iso:country":"US",
    "sg:address":"2 Granville Dr",
    "sg:city":"Elkview",
    "sg:classifiers":[
        {
            "category":"Professional",
            "subcategory":"Management & Consulting",
            "type":"Services"
        }
    ],
    "sg:phone":"+1 304 965 3371",
    "sg:postcode":"25071",
    "sg:province":"WV",
    "sg:tags":[
        "consultant",
        "business"
    ],
    "wof:name":"Pyramid Consulting & Mgt",
    "wof:placetype":"venue"
},
  "geometry": {"coordinates":[-81.501223,38.402001],"type":"Point"}
}