{
  "type": "Feature",
  "properties": {
    "iso:country":"US",
    "sg:address":"412 Glenns Run Rd",
    "sg:city":"Wheeling",
    "sg:classifiers":[
        {
            "category":"Autos & Motor Vehicles",
            "subcategory":"Auto Supplies",
            "type":"Retail Goods"
        }
    ],
    "sg:phone":"+1 304 277 4077",
    "sg:postcode":"26003",
    "sg:province":"WV",
    "sg:tags":[
        "equipment",
        "air",
        "conditioning",
        "automobile"
    ],
    "wof:name":"B & T Auto Truck Repair",
    "wof:placetype":"venue"
},
  "geometry": {"coordinates":[-80.69441500000001,40.124136],"type":"Point"}
}