{
  "type": "Feature",
  "properties": {
    "addr:full":"2200 Main St Wheeling WV 26003",
    "addr:housenumber":"2200",
    "addr:postcode":"26003",
    "addr:street":"Main St",
    "iso:country":"US",
    "sg:address":"2200 Main St",
    "sg:city":"Wheeling",
    "sg:classifiers":[
        {
            "category":"Bakery",
            "type":"Food & Drink"
        }
    ],
    "sg:phone":"+1 304 233 2239",
    "sg:postcode":"26003",
    "sg:province":"WV",
    "sg:website":"http://www.interstatebakeriescorp.com",
    "wof:name":"Wonder & Hostess",
    "wof:placetype":"venue"
},
  "geometry": {"coordinates":[-80.72502900000001,40.060379],"type":"Point"}
}