{
  "type": "Feature",
  "properties": {
    "iso:country":"US",
    "sg:address":"504 Kirby St",
    "sg:city":"Princeton",
    "sg:classifiers":[
        {
            "category":"Wholesale",
            "subcategory":"Electrical",
            "type":"Manufacturing & Wholesale Goods"
        }
    ],
    "sg:phone":"+1 304 425 1759",
    "sg:postcode":"24740",
    "sg:province":"WV",
    "sg:tags":[
        "parts",
        "electric",
        "motor"
    ],
    "wof:name":"D C Motor Parts Inc",
    "wof:placetype":"venue"
},
  "geometry": {"coordinates":[-81.07745300000001,37.373302],"type":"Point"}
}