{
  "type": "Feature",
  "properties": {
    "addr:full":"108 N Mildred St Ranson WV 25438",
    "addr:housenumber":"108",
    "addr:postcode":"25438",
    "addr:street":"N Mildred St",
    "iso:country":"US",
    "sg:address":"108 N Mildred St",
    "sg:city":"Ranson",
    "sg:classifiers":[
        {
            "category":"Home & Garden",
            "subcategory":"Building Materials",
            "type":"Retail Goods"
        }
    ],
    "sg:phone":"+1 304 725 4181",
    "sg:postcode":"25438",
    "sg:province":"WV",
    "sg:tags":[
        "counter",
        "floor",
        "covering"
    ],
    "wof:name":"Laflorco Inc",
    "wof:placetype":"venue"
},
  "geometry": {"coordinates":[-77.861732,39.297693],"type":"Point"}
}