{
  "type": "Feature",
  "properties": {
    "iso:country":"US",
    "sg:address":"1290 National Rd Apt 409",
    "sg:city":"Wheeling",
    "sg:classifiers":[
        {
            "category":"Professional",
            "type":"Services"
        },
        {
            "category":"Personal",
            "type":"Services"
        }
    ],
    "sg:phone":"+1 304 233 7532",
    "sg:postcode":"26003",
    "sg:province":"WV",
    "sg:tags":[
        "mover",
        "material",
        "moving",
        "services-labor"
    ],
    "wof:name":"Larrys Proffessional Moving Service",
    "wof:placetype":"venue"
},
  "geometry": {"coordinates":[-80.681113,40.06981],"type":"Point"}
}