{
  "type": "Feature",
  "properties": {
    "iso:country":"US",
    "sg:address":"118 Washington St W",
    "sg:city":"Charleston",
    "sg:classifiers":[
        {
            "category":"Shopping",
            "subcategory":"Clothing, Apparel, & Fashions",
            "type":"Retail Goods"
        }
    ],
    "sg:phone":"+1 304 343 3060",
    "sg:postcode":"25302",
    "sg:province":"WV",
    "sg:tags":[
        "tailor"
    ],
    "wof:name":"D'Alessio & Son",
    "wof:placetype":"venue"
},
  "geometry": {"coordinates":[-81.640671,38.360033],"type":"Point"}
}