{
  "type": "Feature",
  "properties": {
    "iso:country":"US",
    "sg:address":"4502 Teays Valley Rd",
    "sg:city":"Scott Depot",
    "sg:classifiers":[
        {
            "category":"Organizations",
            "subcategory":"Religious Organization",
            "type":"Services"
        }
    ],
    "sg:phone":"+1 304 757 8543",
    "sg:postcode":"25560",
    "sg:province":"WV",
    "sg:tags":[
        "church"
    ],
    "wof:name":"Pine Grove Church Of Christ",
    "wof:placetype":"venue"
},
  "geometry": {"coordinates":[-81.89531599999999,38.451893],"type":"Point"}
}