{
  "type": "Feature",
  "properties": {
    "iso:country":"US",
    "sg:address":"106 Glenwood Ln",
    "sg:city":"Tornado",
    "sg:classifiers":[
        {
            "category":"Manufacturing",
            "subcategory":"Tools & Machinery",
            "type":"Manufacturing & Wholesale Goods"
        }
    ],
    "sg:phone":"+1 304 248 8543",
    "sg:postcode":"25202",
    "sg:province":"WV",
    "wof:name":"Robinette Instrumentation",
    "wof:placetype":"venue"
},
  "geometry": {"coordinates":[-81.849525,38.343108],"type":"Point"}
}