{
  "type": "Feature",
  "properties": {
    "iso:country":"US",
    "sg:address":"200 Woodlawn Ave",
    "sg:city":"Beckley",
    "sg:classifiers":[
        {
            "category":"Professional",
            "type":"Services"
        }
    ],
    "sg:phone":"+1 304 253 5115",
    "sg:postcode":"25801",
    "sg:province":"WV",
    "sg:tags":[
        "establishment"
    ],
    "wof:name":"Wolfe Enterprises",
    "wof:placetype":"venue"
},
  "geometry": {"coordinates":[-81.189455,37.774169],"type":"Point"}
}