{
  "type": "Feature",
  "properties": {
    "iso:country":"US",
    "sg:address":"105 Oak St",
    "sg:city":"St Albans",
    "sg:classifiers":[
        {
            "category":"Shopping",
            "subcategory":"Used Merchandise",
            "type":"Retail Goods"
        }
    ],
    "sg:phone":"+1 304 201 2007",
    "sg:postcode":"25177",
    "sg:province":"WV",
    "sg:tags":[
        "flea",
        "market"
    ],
    "wof:name":"Oak Street Station Trading Pst",
    "wof:placetype":"venue"
},
  "geometry": {"coordinates":[-81.79472,38.381216],"type":"Point"}
}