{
  "type": "Feature",
  "properties": {
    "iso:country":"US",
    "sg:address":"3120 US Hwy 60",
    "sg:city":"Ona",
    "sg:classifiers":[
        {
            "category":"Utilities",
            "subcategory":"Natural Gas",
            "type":"Services"
        }
    ],
    "sg:phone":"+1 304 733 2151",
    "sg:postcode":"25545",
    "sg:province":"WV",
    "sg:tags":[
        "company"
    ],
    "wof:name":"Holland Supply Co Inc",
    "wof:placetype":"venue"
},
  "geometry": {"coordinates":[-82.215912,38.42412],"type":"Point"}
}