{
  "type": "Feature",
  "properties": {
    "iso:country":"US",
    "sg:address":"99 Arbogast Ln",
    "sg:city":"Morgantown",
    "sg:classifiers":[
        {
            "category":"Real Estate",
            "subcategory":"Real Estate Agent",
            "type":"Services"
        }
    ],
    "sg:phone":"+1 304 826 0603",
    "sg:postcode":"26508",
    "sg:province":"WV",
    "sg:tags":[
        "appraiser"
    ],
    "wof:name":"KAJAE Appraisal",
    "wof:placetype":"venue"
},
  "geometry": {"coordinates":[-79.942277,39.543734],"type":"Point"}
}