{
  "type": "Feature",
  "properties": {
    "addr:full":"501 Main St Man WV 25635",
    "addr:housenumber":"501",
    "addr:postcode":"25635",
    "addr:street":"Main St",
    "iso:country":"US",
    "sg:address":"501 Main St",
    "sg:city":"Man",
    "sg:classifiers":[
        {
            "category":"Retail",
            "subcategory":"Car Wash",
            "type":"Services"
        }
    ],
    "sg:phone":"+1 304 583 2485",
    "sg:postcode":"25635",
    "sg:province":"WV",
    "sg:tags":[
        "carwash"
    ],
    "wof:name":"Car Wash & Detail Shop",
    "wof:placetype":"venue"
},
  "geometry": {"coordinates":[-81.870711,37.745777],"type":"Point"}
}