{
  "type": "Feature",
  "properties": {
    "addr:full":"2423 Jackson Ave Point Pleasant WV 25550",
    "addr:housenumber":"2423",
    "addr:postcode":"25550",
    "addr:street":"Jackson Ave",
    "iso:country":"US",
    "sg:address":"2423 Jackson Ave",
    "sg:city":"Point Pleasant",
    "sg:classifiers":[
        {
            "category":"Organizations",
            "subcategory":"Religious Organization",
            "type":"Services"
        }
    ],
    "sg:phone":"+1 304 675 5452",
    "sg:postcode":"25550",
    "sg:province":"WV",
    "wof:name":"Saint Paul Untd Methdst Church",
    "wof:placetype":"venue"
},
  "geometry": {"coordinates":[-82.126214,38.867075],"type":"Point"}
}