{
  "type": "Feature",
  "properties": {
    "iso:country":"US",
    "sg:address":"5963 US Hwy 60",
    "sg:city":"Barboursville",
    "sg:classifiers":[
        {
            "category":"Autos & Motor Vehicles",
            "subcategory":"Auto Supplies",
            "type":"Retail Goods"
        }
    ],
    "sg:phone":"+1 304 733 2673",
    "sg:postcode":"25504",
    "sg:province":"WV",
    "sg:tags":[
        "recreational"
    ],
    "wof:name":"Days Camper Sales",
    "wof:placetype":"venue"
},
  "geometry": {"coordinates":[-82.302008,38.414424],"type":"Point"}
}