{
  "type": "Feature",
  "properties": {
    "iso:country":"US",
    "sg:address":"514 Quail Valley Dr",
    "sg:city":"Princeton",
    "sg:classifiers":[
        {
            "category":"Real Estate",
            "subcategory":"Real Estate Agent",
            "type":"Services"
        }
    ],
    "sg:phone":"+1 304 425 9240",
    "sg:postcode":"24740",
    "sg:province":"WV",
    "sg:tags":[
        "executive"
    ],
    "wof:name":"Mercer County Mls",
    "wof:placetype":"venue"
},
  "geometry": {"coordinates":[-81.12172200000001,37.366922],"type":"Point"}
}