{
  "type": "Feature",
  "properties": {
    "addr:full":"105 W Maple Ave Fayetteville WV 25840",
    "addr:housenumber":"105",
    "addr:postcode":"25840",
    "addr:street":"W Maple Ave",
    "iso:country":"US",
    "sg:address":"105 W Maple Ave",
    "sg:city":"Fayetteville",
    "sg:classifiers":[
        {
            "category":"Restaurant",
            "type":"Food & Drink"
        }
    ],
    "sg:menulink":"http://www.allmenus.com/wv/new-haven/139689-sicilias-pizzeria/menu/",
    "sg:phone":"+1 304 574 3359",
    "sg:postcode":"25840",
    "sg:province":"WV",
    "sg:tags":[
        "wrap",
        "american",
        "sandwich",
        "pizza"
    ],
    "wof:name":"Sicilia's Pizzeria",
    "wof:placetype":"venue"
},
  "geometry": {"coordinates":[-81.103784,38.052778],"type":"Point"}
}