{
  "type": "Feature",
  "properties": {
    "addr:full":"80 Industrial Ln Huntington WV 25702",
    "addr:housenumber":"80",
    "addr:postcode":"25702",
    "addr:street":"Industrial Ln",
    "iso:country":"US",
    "sg:address":"80 Industrial Ln",
    "sg:city":"Huntington",
    "sg:classifiers":[
        {
            "category":"Manufacturing",
            "subcategory":"Tools & Machinery",
            "type":"Manufacturing & Wholesale Goods"
        }
    ],
    "sg:phone":"+1 304 523 5700",
    "sg:postcode":"25702",
    "sg:province":"WV",
    "sg:tags":[
        "bearing"
    ],
    "wof:name":"American Babbitt Bearing",
    "wof:placetype":"venue"
},
  "geometry": {"coordinates":[-82.30937900000001,38.455564],"type":"Point"}
}