{
  "type": "Feature",
  "properties": {
    "addr:full":"297 Rock Cliff Dr Martinsburg WV 25401",
    "addr:housenumber":"297",
    "addr:postcode":"25401",
    "addr:street":"Rock Cliff Dr",
    "iso:country":"US",
    "sg:address":"297 Rock Cliff Dr",
    "sg:city":"Martinsburg",
    "sg:classifiers":[
        {
            "category":"Food & Beverages",
            "subcategory":"Groceries & Convenience Stores",
            "type":"Retail Goods"
        }
    ],
    "sg:phone":"+1 304 264 3700",
    "sg:postcode":"25401",
    "sg:province":"WV",
    "wof:name":"Village Market",
    "wof:placetype":"venue"
},
  "geometry": {"coordinates":[-77.97053099999999,39.472322],"type":"Point"}
}