{
  "type": "Feature",
  "properties": {
    "addr:full":"4201 5th St Rd Huntington WV 25701",
    "addr:housenumber":"4201",
    "addr:postcode":"25701",
    "addr:street":"5Th St Rd",
    "iso:country":"US",
    "sg:address":"4201 5th St Rd",
    "sg:city":"Huntington",
    "sg:classifiers":[
        {
            "category":"Autos & Motor Vehicles",
            "subcategory":"Fuel & Gas Station",
            "type":"Retail Goods"
        }
    ],
    "sg:phone":"+1 304 523 6285",
    "sg:postcode":"25701",
    "sg:province":"WV",
    "sg:tags":[
        "station",
        "gasoline"
    ],
    "wof:name":"Dotties Tiger Shop",
    "wof:placetype":"venue"
},
  "geometry": {"coordinates":[-82.45272300000001,38.350645],"type":"Point"}
}