{
  "type": "Feature",
  "properties": {
    "addr:full":"1211 Ellen Dr Charleston WV 25303",
    "addr:housenumber":"1211",
    "addr:postcode":"25303",
    "addr:street":"Ellen Dr",
    "iso:country":"US",
    "sg:address":"1211 Ellen Dr",
    "sg:city":"Charleston",
    "sg:classifiers":[
        {
            "category":"Professional",
            "subcategory":"Secretarial Services",
            "type":"Services"
        }
    ],
    "sg:phone":"+1 304 744 4318",
    "sg:postcode":"25303",
    "sg:province":"WV",
    "sg:tags":[
        "business"
    ],
    "wof:name":"Bonnie K Wolfe",
    "wof:placetype":"venue"
},
  "geometry": {"coordinates":[-81.679232,38.349883],"type":"Point"}
}