{
  "type": "Feature",
  "properties": {
    "addr:full":"271 Main St Madison WV 25130",
    "addr:housenumber":"271",
    "addr:postcode":"25130",
    "addr:street":"Main St",
    "iso:country":"US",
    "sg:address":"271 Main St",
    "sg:city":"Madison",
    "sg:classifiers":[
        {
            "category":"Autos & Motor Vehicles",
            "subcategory":"Motorcycle Sales",
            "type":"Retail Goods"
        }
    ],
    "sg:phone":"+1 304 369 5811",
    "sg:postcode":"25130",
    "sg:province":"WV",
    "sg:tags":[
        "repair",
        "parts",
        "accessory"
    ],
    "wof:name":"Macs Cycle Supply Inc",
    "wof:placetype":"venue"
},
  "geometry": {"coordinates":[-81.82033699999999,38.066169],"type":"Point"}
}