{
  "type": "Feature",
  "properties": {
    "addr:full":"3407 Kanawha Blvd E Charleston WV 25306",
    "addr:housenumber":"3407",
    "addr:postcode":"25306",
    "addr:street":"Kanawha Blvd E",
    "iso:country":"US",
    "sg:address":"3407 Kanawha Blvd E",
    "sg:city":"Charleston",
    "sg:classifiers":[
        {
            "category":"Social Services",
            "subcategory":"Child Care",
            "type":"Services"
        }
    ],
    "sg:phone":"+1 304 925 1176",
    "sg:postcode":"25306",
    "sg:province":"WV",
    "sg:tags":[
        "day"
    ],
    "wof:name":"Lil Lamb Daycare",
    "wof:placetype":"venue"
},
  "geometry": {"coordinates":[-81.55916999999999,38.313248],"type":"Point"}
}