{
  "type": "Feature",
  "properties": {
    "iso:country":"US",
    "sg:address":"2660 Derricks Creek Rd",
    "sg:city":"Charleston",
    "sg:classifiers":[
        {
            "category":"Building & Trades",
            "subcategory":"Construction",
            "type":"Services"
        }
    ],
    "sg:phone":"+1 304 984 0445",
    "sg:postcode":"25320",
    "sg:province":"WV",
    "sg:tags":[
        "floor",
        "laying",
        "contractor"
    ],
    "wof:name":"Natures Flooring",
    "wof:placetype":"venue"
},
  "geometry": {"coordinates":[-81.696372,38.543785],"type":"Point"}
}