{
  "type": "Feature",
  "properties": {
    "iso:country":"US",
    "sg:address":"2003 Harper Rd",
    "sg:city":"Beckley",
    "sg:classifiers":[
        {
            "category":"Restaurant",
            "type":"Food & Drink"
        }
    ],
    "sg:phone":"+1 304 254 0444",
    "sg:postcode":"25801",
    "sg:province":"WV",
    "sg:tags":[
        "eating"
    ],
    "wof:name":"Hibachi Japanese Steak House",
    "wof:placetype":"venue"
},
  "geometry": {"coordinates":[-81.215592,37.792122],"type":"Point"}
}