{
  "type": "Feature",
  "properties": {
    "iso:country":"US",
    "sg:address":"1414 N Eisenhower Dr",
    "sg:city":"Beckley",
    "sg:classifiers":[
        {
            "category":"Food & Beverages",
            "subcategory":"Groceries & Convenience Stores",
            "type":"Retail Goods"
        }
    ],
    "sg:phone":"+1 304 256 3011",
    "sg:postcode":"25801",
    "sg:province":"WV",
    "wof:name":"One Stop Shoppe",
    "wof:placetype":"venue"
},
  "geometry": {"coordinates":[-81.18306,37.804397],"type":"Point"}
}