{
  "type": "Feature",
  "properties": {
    "iso:country":"US",
    "sg:address":"3205 Pennsylvania Ave Ste 102",
    "sg:city":"Weirton",
    "sg:classifiers":[
        {
            "category":"Professional",
            "subcategory":"Management & Consulting",
            "type":"Services"
        },
        {
            "category":"Banks & Credit Unions",
            "subcategory":"Investment Brokerage",
            "type":"Services"
        },
        {
            "category":"Banks & Credit Unions",
            "subcategory":"Financial Services",
            "type":"Services"
        }
    ],
    "sg:phone":"+1 304 723 6700",
    "sg:postcode":"26062",
    "sg:province":"WV",
    "sg:tags":[
        "planning",
        "advisory",
        "financing",
        "planner",
        "consultant"
    ],
    "wof:name":"Steeloaks Investment Advise Inc",
    "wof:placetype":"venue"
},
  "geometry": {"coordinates":[-80.541838,40.409753],"type":"Point"}
}