{
  "type": "Feature",
  "properties": {
    "iso:country":"US",
    "sg:address":"230 N Eisenhower Dr",
    "sg:city":"Beckley",
    "sg:classifiers":[
        {
            "category":"Travel",
            "subcategory":"Hotels & Motels",
            "type":"Entertainment"
        }
    ],
    "sg:phone":"+1 304 255 1577",
    "sg:postcode":"25801",
    "sg:province":"WV",
    "wof:name":"Pinecrest Motel",
    "wof:placetype":"venue"
},
  "geometry": {"coordinates":[-81.169603,37.783839],"type":"Point"}
}