{
  "type": "Feature",
  "properties": {
    "addr:full":"103 Main Ave Nitro WV 25143",
    "addr:housenumber":"103",
    "addr:postcode":"25143",
    "addr:street":"Main Ave",
    "iso:country":"US",
    "sg:address":"103 Main Ave",
    "sg:city":"Nitro",
    "sg:classifiers":[
        {
            "category":"Banks & Credit Unions",
            "subcategory":"Investment Brokerage",
            "type":"Services"
        }
    ],
    "sg:phone":"+1 304 757 9673",
    "sg:postcode":"25143",
    "sg:province":"WV",
    "sg:tags":[
        "consultant",
        "planning",
        "financial"
    ],
    "wof:name":"Michael E Greenleaf",
    "wof:placetype":"venue"
},
  "geometry": {"coordinates":[-81.843996,38.408741],"type":"Point"}
}