{
  "type": "Feature",
  "properties": {
    "addr:full":"7830 Ohio River Rd Lesage WV 25537",
    "addr:housenumber":"7830",
    "addr:postcode":"25537",
    "addr:street":"Ohio River Rd",
    "iso:country":"US",
    "sg:address":"7830 Ohio River Rd",
    "sg:city":"Lesage",
    "sg:classifiers":[
        {
            "category":"Food & Beverages",
            "subcategory":"Specialty",
            "type":"Retail Goods"
        }
    ],
    "sg:phone":"+1 304 762 2522",
    "sg:postcode":"25537",
    "sg:province":"WV",
    "sg:tags":[
        "water",
        "bulk",
        "company"
    ],
    "wof:name":"Green Acres Regional Ctr",
    "wof:placetype":"venue"
},
  "geometry": {"coordinates":[-82.251623,38.585342],"type":"Point"}
}