{
  "type": "Feature",
  "properties": {
    "iso:country":"US",
    "sg:address":"384 US Hwy 19",
    "sg:city":"Weston",
    "sg:classifiers":[
        {
            "category":"Wholesale",
            "subcategory":"Metals & Minerals",
            "type":"Manufacturing & Wholesale Goods"
        }
    ],
    "sg:phone":"+1 304 269 7809",
    "sg:postcode":"26452",
    "sg:province":"WV",
    "sg:tags":[
        "foundry",
        "center",
        "iron",
        "malleable"
    ],
    "wof:name":"HK Castings Inc",
    "wof:placetype":"venue"
},
  "geometry": {"coordinates":[-80.46460500000001,39.040715],"type":"Point"}
}