{
  "type": "Feature",
  "properties": {
    "addr:full":"78 Holland Ave Morgantown WV 26501",
    "addr:housenumber":"78",
    "addr:postcode":"26501",
    "addr:street":"Holland Ave",
    "iso:country":"US",
    "sg:address":"78 Holland Ave",
    "sg:city":"Morgantown",
    "sg:classifiers":[
        {
            "category":"Insurance",
            "subcategory":"Insurance Agent",
            "type":"Services"
        }
    ],
    "sg:phone":"+1 304 291 6260",
    "sg:postcode":"26501",
    "sg:province":"WV",
    "wof:name":"David A Boone",
    "wof:placetype":"venue"
},
  "geometry": {"coordinates":[-79.962231,39.63369],"type":"Point"}
}