{
  "type": "Feature",
  "properties": {
    "iso:country":"US",
    "sg:address":"507 4th St",
    "sg:city":"St Albans",
    "sg:classifiers":[
        {
            "category":"Retail",
            "subcategory":"Animal Services",
            "type":"Services"
        }
    ],
    "sg:phone":"+1 304 727 1455",
    "sg:postcode":"25177",
    "sg:province":"WV",
    "sg:tags":[
        "pet",
        "grooming",
        "washing"
    ],
    "wof:name":"Riptide Grooming",
    "wof:placetype":"venue"
},
  "geometry": {"coordinates":[-81.833668,38.386431],"type":"Point"}
}