{
  "type": "Feature",
  "properties": {
    "iso:country":"US",
    "sg:address":"1101 Commerce St",
    "sg:city":"Wellsburg",
    "sg:classifiers":[
        {
            "category":"Ice Cream",
            "type":"Food & Drink"
        }
    ],
    "sg:menulink":"http://www.allmenus.com/wv/wellsburg/192430-dairy-queen/menu/",
    "sg:phone":"+1 304 737 3682",
    "sg:postcode":"26070",
    "sg:province":"WV",
    "sg:tags":[
        "burger",
        "american"
    ],
    "wof:name":"Dairy Queen",
    "wof:placetype":"venue"
},
  "geometry": {"coordinates":[-80.609365,40.273017],"type":"Point"}
}