{
  "type": "Feature",
  "properties": {
    "addr:full":"450 Depot St Romney WV 26757",
    "addr:housenumber":"450",
    "addr:postcode":"26757",
    "addr:street":"Depot St",
    "iso:country":"US",
    "sg:address":"450 Depot St",
    "sg:city":"Romney",
    "sg:classifiers":[
        {
            "category":"Real Estate",
            "subcategory":"Real Estate Operator",
            "type":"Services"
        }
    ],
    "sg:phone":"+1 304 822 6045",
    "sg:postcode":"26757",
    "sg:province":"WV",
    "sg:tags":[
        "building",
        "apartment"
    ],
    "wof:name":"Silver Tree Apartments",
    "wof:placetype":"venue"
},
  "geometry": {"coordinates":[-78.758144,39.348963],"type":"Point"}
}