{
  "type": "Feature",
  "properties": {
    "addr:full":"139 Maple Ave Franklin WV 26836",
    "addr:housenumber":"139",
    "addr:postcode":"26836",
    "addr:street":"Maple Ave",
    "iso:country":"US",
    "sg:address":"139 Maple Ave",
    "sg:city":"Franklin",
    "sg:classifiers":[
        {
            "category":"Insurance",
            "subcategory":"Insurance Agent",
            "type":"Services"
        }
    ],
    "sg:phone":"+1 304 358 2566",
    "sg:postcode":"26836",
    "sg:province":"WV",
    "wof:name":"Nationwide Insurance",
    "wof:placetype":"venue"
},
  "geometry": {"coordinates":[-78.966168,39.065238],"type":"Point"}
}