{
  "type": "Feature",
  "properties": {
    "iso:country":"US",
    "sg:address":"5950 Robert C Byrd Dr",
    "sg:city":"Bradley",
    "sg:classifiers":[
        {
            "category":"Restaurant",
            "type":"Food & Drink"
        }
    ],
    "sg:phone":"+1 304 877 2838",
    "sg:postcode":"25880",
    "sg:province":"WV",
    "wof:name":"Firehouse Pizza & Subs",
    "wof:placetype":"venue"
},
  "geometry": {"coordinates":[-81.19599100000001,37.861028],"type":"Point"}
}