{
  "type": "Feature",
  "properties": {
    "addr:full":"329 Main St Spencer WV 25276",
    "addr:housenumber":"329",
    "addr:postcode":"25276",
    "addr:street":"Main St",
    "iso:country":"US",
    "sg:address":"329 Main St",
    "sg:city":"Spencer",
    "sg:classifiers":[
        {
            "category":"Shopping",
            "subcategory":"Used Merchandise",
            "type":"Retail Goods"
        }
    ],
    "sg:phone":"+1 304 927 2010",
    "sg:postcode":"25276",
    "sg:province":"WV",
    "sg:tags":[
        "pawnbroker"
    ],
    "wof:name":"T J's Swap Shop",
    "wof:placetype":"venue"
},
  "geometry": {"coordinates":[-81.35098499999999,38.801961],"type":"Point"}
}