{
  "type": "Feature",
  "properties": {
    "addr:full":"1030 E Bethlehem Blvd Wheeling WV 26003",
    "addr:housenumber":"1030",
    "addr:postcode":"26003",
    "addr:street":"E Bethlehem Blvd",
    "iso:country":"US",
    "sg:address":"1030 E Bethlehem Blvd",
    "sg:city":"Wheeling",
    "sg:classifiers":[
        {
            "category":"Home & Garden",
            "subcategory":"Building Materials",
            "type":"Retail Goods"
        }
    ],
    "sg:phone":"+1 304 242 9730",
    "sg:postcode":"26003",
    "sg:province":"WV",
    "sg:tags":[
        "glass",
        "window",
        "plate"
    ],
    "wof:name":"Auto Glass Specialists LLC",
    "wof:placetype":"venue"
},
  "geometry": {"coordinates":[-80.679917,40.040022],"type":"Point"}
}