{
  "type": "Feature",
  "properties": {
    "iso:country":"US",
    "sg:address":"601 57th St SE",
    "sg:city":"Charleston",
    "sg:classifiers":[
        {
            "category":"Government",
            "subcategory":"Office",
            "type":"Public Place"
        }
    ],
    "sg:phone":"+1 304 558 2107",
    "sg:postcode":"25304",
    "sg:province":"WV",
    "sg:tags":[
        "state",
        "program"
    ],
    "wof:name":"Water Resources",
    "wof:placetype":"venue"
},
  "geometry": {"coordinates":[-81.570592,38.311609],"type":"Point"}
}