{
  "type": "Feature",
  "properties": {
    "iso:country":"US",
    "sg:address":"100 Parkway Dr",
    "sg:city":"Clarksburg",
    "sg:classifiers":[
        {
            "category":"Health Services",
            "subcategory":"Nursing And Care Facility",
            "type":"Services"
        }
    ],
    "sg:phone":"+1 304 624 6401",
    "sg:postcode":"26301",
    "sg:province":"WV",
    "sg:tags":[
        "skilled"
    ],
    "wof:name":"Heartland Of Clarksburg",
    "wof:placetype":"venue"
},
  "geometry": {"coordinates":[-80.326606,39.26685],"type":"Point"}
}