{
  "type": "Feature",
  "properties": {
    "iso:country":"US",
    "sg:address":"92 Palomino Dr",
    "sg:city":"Weirton",
    "sg:classifiers":[
        {
            "category":"Real Estate",
            "subcategory":"Real Estate Operator",
            "type":"Services"
        }
    ],
    "sg:phone":"+1 304 723 5251",
    "sg:postcode":"26062",
    "sg:province":"WV",
    "sg:tags":[
        "apartment"
    ],
    "wof:name":"Alpine Plaza",
    "wof:placetype":"venue"
},
  "geometry": {"coordinates":[-80.553667,40.400188],"type":"Point"}
}