{
  "type": "Feature",
  "properties": {
    "addr:full":"302 Goller Hill Ln Hedgesville WV 25427",
    "addr:housenumber":"302",
    "addr:postcode":"25427",
    "addr:street":"Goller Hill Ln",
    "iso:country":"US",
    "sg:address":"302 Goller Hill Ln",
    "sg:city":"Hedgesville",
    "sg:classifiers":[
        {
            "category":"Place Of Worship",
            "subcategory":"Church",
            "type":"Public Place"
        },
        {
            "category":"Place Of Worship",
            "type":"Public Place"
        }
    ],
    "sg:phone":"+1 304 754 8245",
    "sg:postcode":"25427",
    "sg:province":"WV",
    "sg:tags":[
        "churches-non-denominational"
    ],
    "wof:name":"Open Arms Ministry",
    "wof:placetype":"venue"
},
  "geometry": {"coordinates":[-78.091599,39.616699],"type":"Point"}
}