{
  "type": "Feature",
  "properties": {
    "iso:country":"US",
    "sg:address":"891 Stewart St",
    "sg:city":"Welch",
    "sg:classifiers":[
        {
            "category":"Government",
            "subcategory":"Office",
            "type":"Public Place"
        }
    ],
    "sg:phone":"+1 304 436 8421",
    "sg:postcode":"24801",
    "sg:province":"WV",
    "sg:tags":[
        "safety",
        "inspection"
    ],
    "wof:name":"Office Mners Hlth Sfety Trning",
    "wof:placetype":"venue"
},
  "geometry": {"coordinates":[-81.572332,37.441266],"type":"Point"}
}