{
  "type": "Feature",
  "properties": {
    "iso:country":"US",
    "sg:address":"3400 Teays Valley Rd",
    "sg:city":"Hurricane",
    "sg:classifiers":[
        {
            "category":"Utilities",
            "type":"Services"
        }
    ],
    "sg:phone":"+1 304 562 2382",
    "sg:postcode":"25526",
    "sg:province":"WV",
    "sg:tags":[
        "locating"
    ],
    "wof:name":"Pipemasters Inc",
    "wof:placetype":"venue"
},
  "geometry": {"coordinates":[-82.000103,38.437385],"type":"Point"}
}