{
  "type": "Feature",
  "properties": {
    "iso:country":"US",
    "sg:address":"3772 Teays Valley Rd",
    "sg:city":"Hurricane",
    "sg:classifiers":[
        {
            "category":"Professional",
            "subcategory":"Employment Agencies",
            "type":"Services"
        }
    ],
    "sg:phone":"+1 304 757 4399",
    "sg:postcode":"25526",
    "sg:province":"WV",
    "wof:name":"Management Recruiters Intl",
    "wof:placetype":"venue"
},
  "geometry": {"coordinates":[-81.96316899999999,38.446466],"type":"Point"}
}