{
  "type": "Feature",
  "properties": {
    "iso:country":"US",
    "sg:address":"228 Windsor Dr",
    "sg:city":"Mineral Wells",
    "sg:classifiers":[
        {
            "category":"Wholesale",
            "subcategory":"Machinery & Supplies",
            "type":"Manufacturing & Wholesale Goods"
        }
    ],
    "sg:phone":"+1 304 489 3330",
    "sg:postcode":"26150",
    "sg:province":"WV",
    "sg:tags":[
        "industrial",
        "miscellaneous"
    ],
    "wof:name":"Randolph Rig & Equipment",
    "wof:placetype":"venue"
},
  "geometry": {"coordinates":[-81.50990299999999,39.187963],"type":"Point"}
}