{
  "type": "Feature",
  "properties": {
    "iso:country":"US",
    "sg:address":"1413 7th Ave",
    "sg:city":"Charleston",
    "sg:classifiers":[
        {
            "category":"Organizations",
            "subcategory":"Religious Organization",
            "type":"Services"
        }
    ],
    "sg:phone":"+1 304 347 9421",
    "sg:postcode":"25312",
    "sg:province":"WV",
    "sg:tags":[
        "clergy"
    ],
    "wof:name":"Jerry Ernst",
    "wof:placetype":"venue"
},
  "geometry": {"coordinates":[-81.66024299999999,38.37023],"type":"Point"}
}