{
  "type": "Feature",
  "properties": {
    "iso:country":"US",
    "sg:address":"300 Harrison St",
    "sg:city":"Newell",
    "sg:classifiers":[
        {
            "category":"Building & Trades",
            "subcategory":"Construction",
            "type":"Services"
        }
    ],
    "sg:phone":"+1 304 387 0944",
    "sg:postcode":"26050",
    "sg:province":"WV",
    "sg:tags":[
        "excavation",
        "contractor"
    ],
    "wof:name":"Six Enterprises Ltd",
    "wof:placetype":"venue"
},
  "geometry": {"coordinates":[-80.59935299999999,40.620673],"type":"Point"}
}