{
  "type": "Feature",
  "properties": {
    "addr:full":"513 7th St Moundsville WV 26041",
    "addr:housenumber":"513",
    "addr:postcode":"26041",
    "addr:street":"7Th St",
    "iso:country":"US",
    "sg:address":"513 7th St",
    "sg:city":"Moundsville",
    "sg:classifiers":[
        {
            "category":"Manufacturing",
            "subcategory":"Printing",
            "type":"Manufacturing & Wholesale Goods"
        }
    ],
    "sg:phone":"+1 304 845 3911",
    "sg:postcode":"26041",
    "sg:province":"WV",
    "sg:tags":[
        "commercial"
    ],
    "wof:name":"Crescent Print Shop",
    "wof:placetype":"venue"
},
  "geometry": {"coordinates":[-80.746211,39.918493],"type":"Point"}
}