{
  "type": "Feature",
  "properties": {
    "iso:country":"US",
    "sg:address":"404 Waynewood St",
    "sg:city":"Parsons",
    "sg:classifiers":[
        {
            "category":"Building & Trades",
            "subcategory":"Electrical",
            "type":"Services"
        }
    ],
    "sg:phone":"+1 304 478 3205",
    "sg:postcode":"26287",
    "sg:province":"WV",
    "sg:tags":[
        "electric",
        "contractor"
    ],
    "wof:name":"Southpaw Electric Inc",
    "wof:placetype":"venue"
},
  "geometry": {"coordinates":[-79.68580900000001,39.100413],"type":"Point"}
}