{
  "type": "Feature",
  "properties": {
    "iso:country":"US",
    "sg:address":"304 Washington Ave",
    "sg:city":"Wheeling",
    "sg:classifiers":[
        {
            "category":"Building & Trades",
            "subcategory":"Construction",
            "type":"Services"
        }
    ],
    "sg:phone":"+1 304 242 9728",
    "sg:postcode":"26003",
    "sg:province":"WV",
    "sg:tags":[
        "contractor"
    ],
    "wof:name":"Doyle Construction",
    "wof:placetype":"venue"
},
  "geometry": {"coordinates":[-80.69027699999999,40.068205],"type":"Point"}
}