{
  "type": "Feature",
  "properties": {
    "addr:full":"2082 Harper Rd Beckley WV 25801",
    "addr:housenumber":"2082",
    "addr:postcode":"25801",
    "addr:street":"Harper Rd",
    "iso:country":"US",
    "sg:address":"2082 Harper Rd",
    "sg:city":"Beckley",
    "sg:classifiers":[
        {
            "category":"Restaurant",
            "type":"Food & Drink"
        }
    ],
    "sg:menulink":"http://www.allmenus.com/wv/pax/104084-ruby-tuesdays/menu/",
    "sg:phone":"+1 304 254 0481",
    "sg:postcode":"25801",
    "sg:province":"WV",
    "sg:tags":[
        "burger",
        "american"
    ],
    "wof:name":"Ruby Tuesdays",
    "wof:placetype":"venue"
},
  "geometry": {"coordinates":[-81.218394,37.796007],"type":"Point"}
}