{
  "type": "Feature",
  "properties": {
    "addr:full":"716 7th Ave Huntington WV 25701",
    "addr:housenumber":"716",
    "addr:postcode":"25701",
    "addr:street":"7Th Ave",
    "iso:country":"US",
    "sg:address":"716 7th Ave",
    "sg:city":"Huntington",
    "sg:classifiers":[
        {
            "category":"Retail",
            "subcategory":"Auto Repair",
            "type":"Services"
        }
    ],
    "sg:phone":"+1 304 525 8885",
    "sg:postcode":"25701",
    "sg:province":"WV",
    "sg:tags":[
        "general"
    ],
    "wof:name":"Import Works",
    "wof:placetype":"venue"
},
  "geometry": {"coordinates":[-82.444693,38.416414],"type":"Point"}
}