{
  "type": "Feature",
  "properties": {
    "iso:country":"US",
    "sg:address":"5132 Maccorkle Ave SE",
    "sg:city":"Charleston",
    "sg:classifiers":[
        {
            "category":"Shopping",
            "subcategory":"Clothing, Apparel, & Fashions",
            "type":"Retail Goods"
        }
    ],
    "sg:phone":"+1 304 925 3553",
    "sg:postcode":"25304",
    "sg:province":"WV",
    "sg:tags":[
        "item",
        "boutique"
    ],
    "sg:website":"www.bombayboutique.com",
    "wof:name":"Bombay Boutique",
    "wof:placetype":"venue"
},
  "geometry": {"coordinates":[-81.575228,38.317825],"type":"Point"}
}