{
  "type": "Feature",
  "properties": {
    "iso:country":"US",
    "sg:address":"114 W Liberty St",
    "sg:city":"Charles Town",
    "sg:classifiers":[
        {
            "category":"Government",
            "subcategory":"Police Station",
            "type":"Public Place"
        }
    ],
    "sg:phone":"+1 304 725 2714",
    "sg:postcode":"25414",
    "sg:province":"WV",
    "sg:tags":[
        "department"
    ],
    "wof:name":"Charles Town Police Dept",
    "wof:placetype":"venue"
},
  "geometry": {"coordinates":[-77.860553,39.289887],"type":"Point"}
}