{
  "type": "Feature",
  "properties": {
    "iso:country":"US",
    "sg:address":"2808 Lincoln Ave",
    "sg:city":"Saint Albans",
    "sg:classifiers":[
        {
            "category":"Banks & Credit Unions",
            "subcategory":"Financial Services",
            "type":"Services"
        }
    ],
    "sg:phone":"+1 304 472 5233",
    "sg:postcode":"25177",
    "sg:province":"WV",
    "sg:tags":[
        "investor"
    ],
    "wof:name":"Tumbleweed Investments",
    "wof:placetype":"venue"
},
  "geometry": {"coordinates":[-81.795901,38.377989],"type":"Point"}
}