{
  "type": "Feature",
  "properties": {
    "iso:country":"US",
    "sg:address":"131 Blue Angel Ln",
    "sg:city":"Beaver",
    "sg:classifiers":[
        {
            "category":"Wholesale",
            "subcategory":"Electrical",
            "type":"Manufacturing & Wholesale Goods"
        }
    ],
    "sg:phone":"+1 304 255 1016",
    "sg:postcode":"25813",
    "sg:province":"WV",
    "sg:tags":[
        "telecommunication"
    ],
    "wof:name":"Southern Telecom Inc",
    "wof:placetype":"venue"
},
  "geometry": {"coordinates":[-81.11188199999999,37.791934],"type":"Point"}
}