{
  "type": "Feature",
  "properties": {
    "addr:full":"1702 River Rd Morgantown WV 26501",
    "addr:housenumber":"1702",
    "addr:postcode":"26501",
    "addr:street":"River Rd",
    "iso:country":"US",
    "sg:address":"1702 River Rd",
    "sg:city":"Morgantown",
    "sg:classifiers":[
        {
            "category":"Social Services",
            "type":"Services"
        }
    ],
    "sg:phone":"+1 304 983 2432",
    "sg:postcode":"26501",
    "sg:province":"WV",
    "wof:name":"Starting Pt Fmly Resource Ctr",
    "wof:placetype":"venue"
},
  "geometry": {"coordinates":[-80.00987600000001,39.598982],"type":"Point"}
}