{
  "type": "Feature",
  "properties": {
    "iso:country":"US",
    "sg:address":"2086 Sulpher Springs School Rd",
    "sg:city":"Inwood",
    "sg:classifiers":[
        {
            "category":"Arts & Performance",
            "subcategory":"Theater",
            "type":"Entertainment"
        }
    ],
    "sg:phone":"+1 304 229 2802",
    "sg:postcode":"25427",
    "sg:province":"WV",
    "sg:tags":[
        "band"
    ],
    "wof:name":"Patent Pending",
    "wof:placetype":"venue"
},
  "geometry": {"coordinates":[-78.130821,39.4685],"type":"Point"}
}