{
  "type": "Feature",
  "properties": {
    "iso:country":"US",
    "sg:address":"603 Grand Central Ave",
    "sg:city":"Vienna",
    "sg:classifiers":[
        {
            "category":"Shopping",
            "subcategory":"Shoes",
            "type":"Retail Goods"
        }
    ],
    "sg:phone":"+1 304 422 5316",
    "sg:postcode":"26105",
    "sg:province":"WV",
    "wof:name":"Shoe Carnival",
    "wof:placetype":"venue"
},
  "geometry": {"coordinates":[-81.550505,39.304865],"type":"Point"}
}