{
  "type": "Feature",
  "properties": {
    "iso:country":"US",
    "sg:address":"747 Chestnut Ridge Rd",
    "sg:city":"Morgantown",
    "sg:classifiers":[
        {
            "category":"Personal",
            "subcategory":"Beauty Salon",
            "type":"Services"
        }
    ],
    "sg:phone":"+1 304 599 6101",
    "sg:postcode":"26505",
    "sg:province":"WV",
    "sg:tags":[
        "manicuring"
    ],
    "wof:name":"Nail 2",
    "wof:placetype":"venue"
},
  "geometry": {"coordinates":[-79.96038,39.657935],"type":"Point"}
}