{
  "type": "Feature",
  "properties": {
    "iso:country":"US",
    "sg:address":"3450 16th St",
    "sg:city":"Huntington",
    "sg:classifiers":[
        {
            "category":"Building & Trades",
            "subcategory":"Construction",
            "type":"Services"
        }
    ],
    "sg:phone":"+1 304 529 3328",
    "sg:postcode":"25701",
    "sg:province":"WV",
    "sg:tags":[
        "general",
        "contractor"
    ],
    "wof:name":"FAMCO Inc",
    "wof:placetype":"venue"
},
  "geometry": {"coordinates":[-82.385831,38.387241],"type":"Point"}
}