{
  "type": "Feature",
  "properties": {
    "addr:full":"1460 7th St Parkersburg WV 26101",
    "addr:housenumber":"1460",
    "addr:postcode":"26101",
    "addr:street":"7Th St",
    "iso:country":"US",
    "sg:address":"1460 7th St",
    "sg:city":"Parkersburg",
    "sg:classifiers":[
        {
            "category":"Home & Garden",
            "subcategory":"Building Materials",
            "type":"Retail Goods"
        }
    ],
    "sg:phone":"+1 304 424 6269",
    "sg:postcode":"26101",
    "sg:province":"WV",
    "sg:tags":[
        "glass",
        "window",
        "plate"
    ],
    "wof:name":"Glass Wholesalers",
    "wof:placetype":"venue"
},
  "geometry": {"coordinates":[-81.53681400000001,39.265009],"type":"Point"}
}