{
  "type": "Feature",
  "properties": {
    "iso:country":"US",
    "sg:address":"1812 Vineyard St",
    "sg:city":"Bluefield",
    "sg:classifiers":[
        {
            "category":"Professional",
            "subcategory":"Lawyer & Legal Services",
            "type":"Services"
        }
    ],
    "sg:phone":"+1 304 327 0474",
    "sg:postcode":"24701",
    "sg:province":"WV",
    "sg:tags":[
        "attorney"
    ],
    "wof:name":"David M Katz",
    "wof:placetype":"venue"
},
  "geometry": {"coordinates":[-81.219643,37.257731],"type":"Point"}
}