{
  "type": "Feature",
  "properties": {
    "iso:country":"US",
    "sg:address":"2243 Market St",
    "sg:city":"Wheeling",
    "sg:classifiers":[
        {
            "category":"Shopping",
            "subcategory":"Gifts & Souvenirs",
            "type":"Retail Goods"
        }
    ],
    "sg:phone":"+1 304 232 8939",
    "sg:postcode":"26003",
    "sg:province":"WV",
    "sg:tags":[
        "shop"
    ],
    "wof:name":"Puddleducks",
    "wof:placetype":"venue"
},
  "geometry": {"coordinates":[-80.72442100000001,40.059094],"type":"Point"}
}