{
  "type": "Feature",
  "properties": {
    "iso:country":"US",
    "sg:address":"880 Sherwood Rd",
    "sg:city":"Charleston",
    "sg:classifiers":[
        {
            "category":"Organizations",
            "subcategory":"Community Association",
            "type":"Services"
        }
    ],
    "sg:phone":"+1 304 342 0357",
    "sg:postcode":"25314",
    "sg:province":"WV",
    "wof:name":"West Vrgnia Mus Educators Assn",
    "wof:placetype":"venue"
},
  "geometry": {"coordinates":[-81.660478,38.341286],"type":"Point"}
}