{
  "type": "Feature",
  "properties": {
    "iso:country":"US",
    "sg:address":"126 E Race St",
    "sg:city":"Martinsburg",
    "sg:classifiers":[
        {
            "category":"Museum",
            "type":"Entertainment"
        }
    ],
    "sg:phone":"+1 304 267 4713",
    "sg:postcode":"25401",
    "sg:province":"WV",
    "wof:name":"Belle Boyd House",
    "wof:placetype":"venue"
},
  "geometry": {"coordinates":[-77.96213400000001,39.459794],"type":"Point"}
}