{
  "type": "Feature",
  "properties": {
    "iso:country":"US",
    "sg:address":"4607 Baxter Dr",
    "sg:city":"Charleston",
    "sg:classifiers":[
        {
            "category":"Manufacturing",
            "subcategory":"Electronics",
            "type":"Manufacturing & Wholesale Goods"
        }
    ],
    "sg:phone":"+1 304 965 5349",
    "sg:postcode":"25302",
    "sg:province":"WV",
    "sg:tags":[
        "equipment",
        "mfg",
        "home"
    ],
    "wof:name":"J D Productions",
    "wof:placetype":"venue"
},
  "geometry": {"coordinates":[-81.536608,38.405914],"type":"Point"}
}