{
  "type": "Feature",
  "properties": {
    "iso:country":"US",
    "sg:address":"401 Brentwood Ave",
    "sg:city":"Moundsville",
    "sg:classifiers":[
        {
            "category":"Building & Trades",
            "subcategory":"Construction",
            "type":"Services"
        }
    ],
    "sg:phone":"+1 304 845 1112",
    "sg:postcode":"26041",
    "sg:province":"WV",
    "sg:tags":[
        "hanging",
        "painter",
        "contractor"
    ],
    "wof:name":"A Better Brush Pntng & Contr",
    "wof:placetype":"venue"
},
  "geometry": {"coordinates":[-80.721161,39.919408],"type":"Point"}
}