{
  "type": "Feature",
  "properties": {
    "iso:country":"US",
    "sg:address":"5200 US Hwy 60",
    "sg:city":"Huntington",
    "sg:classifiers":[
        {
            "category":"Autos & Motor Vehicles",
            "subcategory":"Automobile Sales",
            "type":"Retail Goods"
        }
    ],
    "sg:phone":"+1 304 736 5294",
    "sg:postcode":"25705",
    "sg:province":"WV",
    "wof:name":"Moses Auto Mall",
    "wof:placetype":"venue"
},
  "geometry": {"coordinates":[-82.34089,38.412171],"type":"Point"}
}