{
  "type": "Feature",
  "properties": {
    "iso:country":"US",
    "sg:address":"502 Berry St",
    "sg:city":"Martinsburg",
    "sg:classifiers":[
        {
            "category":"Personal",
            "subcategory":"Beauty Salon",
            "type":"Services"
        }
    ],
    "sg:phone":"+1 304 263 3916",
    "sg:postcode":"25401",
    "sg:province":"WV",
    "sg:tags":[
        "shop"
    ],
    "wof:name":"Beauty Boutique",
    "wof:placetype":"venue"
},
  "geometry": {"coordinates":[-77.978281,39.449885],"type":"Point"}
}