{
  "type": "Feature",
  "properties": {
    "iso:country":"US",
    "sg:address":"21156 State Rte 243",
    "sg:city":"Proctorville",
    "sg:classifiers":[
        {
            "category":"Retail",
            "subcategory":"Repair Shop",
            "type":"Services"
        }
    ],
    "sg:phone":"+1 740 886 9000",
    "sg:postcode":"45669",
    "sg:province":"OH",
    "sg:tags":[
        "equipment",
        "telephone",
        "system"
    ],
    "sg:website":"www.servicetel.com",
    "wof:name":"Service Telecommunications",
    "wof:placetype":"venue"
},
  "geometry": {"coordinates":[-82.362518,38.4467],"type":"Point"}
}