{
  "type": "Feature",
  "properties": {
    "addr:full":"402 Jefferson Ave Glen Dale WV 26038",
    "addr:housenumber":"402",
    "addr:postcode":"26038",
    "addr:street":"Jefferson Ave Glen Dale",
    "iso:country":"US",
    "sg:address":"402 Jefferson Ave",
    "sg:city":"Glen Dale",
    "sg:classifiers":[
        {
            "category":"Health Services",
            "subcategory":"Health Practitioner",
            "type":"Services"
        }
    ],
    "sg:phone":"+1 304 845 6455",
    "sg:postcode":"26038",
    "sg:province":"WV",
    "sg:tags":[
        "nurse",
        "registry"
    ],
    "wof:name":"Elizabeth T Stankus",
    "wof:placetype":"venue"
},
  "geometry": {"coordinates":[-80.75097700000001,39.951564],"type":"Point"}
}