{
  "type": "Feature",
  "properties": {
    "iso:country":"US",
    "sg:address":"1097 Greenbag Rd",
    "sg:city":"Morgantown",
    "sg:classifiers":[
        {
            "category":"Professional",
            "subcategory":"Management & Consulting",
            "type":"Services"
        }
    ],
    "sg:phone":"+1 304 291 3996",
    "sg:postcode":"26508",
    "sg:province":"WV",
    "wof:name":"Mulberry Street Mgmt Svc Inc",
    "wof:placetype":"venue"
},
  "geometry": {"coordinates":[-79.93341700000001,39.611994],"type":"Point"}
}