{
  "type": "Feature",
  "properties": {
    "iso:country":"US",
    "sg:address":"1102 3rd Ave",
    "sg:city":"Huntington",
    "sg:classifiers":[
        {
            "category":"Health Services",
            "subcategory":"Clinic",
            "type":"Services"
        }
    ],
    "sg:phone":"+1 304 697 7242",
    "sg:postcode":"25701",
    "sg:province":"WV",
    "wof:name":"Us Army Health Care Recruit Tm",
    "wof:placetype":"venue"
},
  "geometry": {"coordinates":[-82.439105,38.422886],"type":"Point"}
}