{
  "type": "Feature",
  "properties": {
    "addr:full":"1507 Main St E Oak Hill WV 25901",
    "addr:housenumber":"1507",
    "addr:postcode":"25901",
    "addr:street":"Main St E",
    "iso:country":"US",
    "sg:address":"1507 Main St E",
    "sg:city":"Oak Hill",
    "sg:classifiers":[
        {
            "category":"Banks & Credit Unions",
            "subcategory":"Bank",
            "type":"Services"
        }
    ],
    "sg:phone":"+1 304 465 2040",
    "sg:postcode":"25901",
    "sg:province":"WV",
    "wof:name":"Pioneer WV Fed Credit Union",
    "wof:placetype":"venue"
},
  "geometry": {"coordinates":[-81.134305,37.989385],"type":"Point"}
}