{
  "type": "Feature",
  "properties": {
    "iso:country":"US",
    "sg:address":"701 Rogers St",
    "sg:city":"Princeton",
    "sg:classifiers":[
        {
            "category":"Autos & Motor Vehicles",
            "subcategory":"Fuel & Gas Station",
            "type":"Retail Goods"
        }
    ],
    "sg:phone":"+1 304 425 6117",
    "sg:postcode":"24740",
    "sg:province":"WV",
    "sg:tags":[
        "grocery",
        "station",
        "gasoline"
    ],
    "wof:name":"Center 197",
    "wof:placetype":"venue"
},
  "geometry": {"coordinates":[-81.07577499999999,37.366572],"type":"Point"}
}