{
  "type": "Feature",
  "properties": {
    "iso:country":"US",
    "sg:address":"106 N Bridge St",
    "sg:city":"New Martinsville",
    "sg:classifiers":[
        {
            "category":"Autos & Motor Vehicles",
            "subcategory":"Auto Supplies",
            "type":"Retail Goods"
        }
    ],
    "sg:phone":"+1 304 455 0165",
    "sg:postcode":"26155",
    "sg:province":"WV",
    "sg:tags":[
        "tire"
    ],
    "wof:name":"Red's Tire & Truck Svc",
    "wof:placetype":"venue"
},
  "geometry": {"coordinates":[-80.859066,39.660058],"type":"Point"}
}