{
  "type": "Feature",
  "properties": {
    "iso:country":"US",
    "sg:address":"228 N Fayette St",
    "sg:city":"Beckley",
    "sg:classifiers":[
        {
            "category":"Professional",
            "subcategory":"Lawyer & Legal Services",
            "type":"Services"
        }
    ],
    "sg:phone":"+1 304 253 7405",
    "sg:postcode":"25801",
    "sg:province":"WV",
    "sg:tags":[
        "attorney"
    ],
    "wof:name":"Public Defender Corp",
    "wof:placetype":"venue"
},
  "geometry": {"coordinates":[-81.189904,37.779174],"type":"Point"}
}