{
  "type": "Feature",
  "properties": {
    "iso:country":"US",
    "sg:address":"743 Washington St W",
    "sg:city":"Charleston",
    "sg:classifiers":[
        {
            "category":"Building & Trades",
            "subcategory":"Construction",
            "type":"Services"
        }
    ],
    "sg:phone":"+1 304 346 0462",
    "sg:postcode":"25302",
    "sg:province":"WV",
    "sg:tags":[
        "general",
        "contractor"
    ],
    "wof:name":"Mdi",
    "wof:placetype":"venue"
},
  "geometry": {"coordinates":[-81.65054000000001,38.366949],"type":"Point"}
}