{
  "type": "Feature",
  "properties": {
    "addr:full":"329 E Main St Clarksburg WV 26301",
    "addr:housenumber":"329",
    "addr:postcode":"26301",
    "addr:street":"E Main St",
    "iso:country":"US",
    "sg:address":"329 E Main St",
    "sg:city":"Clarksburg",
    "sg:classifiers":[
        {
            "category":"Retail",
            "subcategory":"Funeral Services",
            "type":"Services"
        }
    ],
    "sg:phone":"+1 304 624 5404",
    "sg:postcode":"26301",
    "sg:province":"WV",
    "sg:tags":[
        "director"
    ],
    "wof:name":"Davison & Weaver Funeral Home",
    "wof:placetype":"venue"
},
  "geometry": {"coordinates":[-80.329286,39.277575],"type":"Point"}
}