{
  "type": "Feature",
  "properties": {
    "iso:country":"US",
    "sg:address":"107 Doctors Dr",
    "sg:city":"Bridgeport",
    "sg:classifiers":[
        {
            "category":"Health Services",
            "subcategory":"Optometrist",
            "type":"Services"
        }
    ],
    "sg:phone":"+1 304 842 6226",
    "sg:postcode":"26330",
    "sg:province":"WV",
    "wof:name":"Murray Murray & Groves",
    "wof:placetype":"venue"
},
  "geometry": {"coordinates":[-80.25268199999999,39.283392],"type":"Point"}
}