{
  "type": "Feature",
  "properties": {
    "addr:full":"1500 Blizzard Dr Parkersburg WV 26101",
    "addr:housenumber":"1500",
    "addr:postcode":"26101",
    "addr:street":"Blizzard Dr",
    "iso:country":"US",
    "sg:address":"1500 Blizzard Dr",
    "sg:city":"Parkersburg",
    "sg:classifiers":[
        {
            "category":"Government",
            "subcategory":"Office",
            "type":"Public Place"
        }
    ],
    "sg:phone":"+1 304 485 8511",
    "sg:postcode":"26101",
    "sg:province":"WV",
    "sg:tags":[
        "state",
        "security"
    ],
    "wof:name":"Army National Guard",
    "wof:placetype":"venue"
},
  "geometry": {"coordinates":[-81.549679,39.242317],"type":"Point"}
}