{
  "type": "Feature",
  "properties": {
    "iso:country":"US",
    "sg:address":"154 E Pike St",
    "sg:city":"Clarksburg",
    "sg:classifiers":[
        {
            "category":"Shopping",
            "subcategory":"Musical Instruments",
            "type":"Retail Goods"
        }
    ],
    "sg:phone":"+1 304 622 1171",
    "sg:postcode":"26301",
    "sg:province":"WV",
    "wof:name":"Bandland LLC & Percussion Ctr",
    "wof:placetype":"venue"
},
  "geometry": {"coordinates":[-80.33275399999999,39.279804],"type":"Point"}
}