{
  "type": "Feature",
  "properties": {
    "addr:full":"7510 State Rte 7 Proctorville OH 45669",
    "addr:housenumber":"7510",
    "addr:postcode":"45669",
    "addr:street":"State Rte 7",
    "iso:country":"US",
    "sg:address":"7510 State Rte 7",
    "sg:city":"Proctorville",
    "sg:classifiers":[
        {
            "category":"Banks & Credit Unions",
            "subcategory":"Bank",
            "type":"Services"
        }
    ],
    "sg:phone":"+1 740 886 9171",
    "sg:postcode":"45669",
    "sg:province":"OH",
    "wof:name":"Oak Hill Banks",
    "wof:placetype":"venue"
},
  "geometry": {"coordinates":[-82.358495,38.442272],"type":"Point"}
}