{
  "type": "Feature",
  "properties": {
    "iso:country":"US",
    "sg:address":"904 Dickel Ave",
    "sg:city":"Parkersburg",
    "sg:classifiers":[
        {
            "category":"Banks & Credit Unions",
            "subcategory":"Financial Services",
            "type":"Services"
        },
        {
            "category":"Professional",
            "subcategory":"Management & Consulting",
            "type":"Services"
        }
    ],
    "sg:phone":"+1 304 422 4077",
    "sg:postcode":"26101",
    "sg:province":"WV",
    "sg:tags":[
        "consultant",
        "open",
        "investment",
        "business"
    ],
    "wof:name":"Sherry Debarr Enterprises LLC",
    "wof:placetype":"venue"
},
  "geometry": {"coordinates":[-81.52502699999999,39.270648],"type":"Point"}
}