{
  "type": "Feature",
  "properties": {
    "iso:country":"US",
    "sg:address":"602 8th Ave",
    "sg:city":"Huntington",
    "sg:classifiers":[
        {
            "category":"Wholesale",
            "subcategory":"Groceries",
            "type":"Manufacturing & Wholesale Goods"
        }
    ],
    "sg:phone":"+1 304 525 9192",
    "sg:postcode":"25701",
    "sg:province":"WV",
    "sg:tags":[
        "confectionery",
        "candy"
    ],
    "wof:name":"Goldsmit-Sydnor Inc",
    "wof:placetype":"venue"
},
  "geometry": {"coordinates":[-82.445753,38.414502],"type":"Point"}
}