{
  "type": "Feature",
  "properties": {
    "addr:full":"1352 Old Eccles Rd Beckley WV 25801",
    "addr:housenumber":"1352",
    "addr:postcode":"25801",
    "addr:street":"Old Eccles Rd",
    "iso:country":"US",
    "sg:address":"1352 Old Eccles Rd",
    "sg:city":"Beckley",
    "sg:classifiers":[
        {
            "category":"Building & Trades",
            "subcategory":"Construction",
            "type":"Services"
        }
    ],
    "sg:phone":"+1 304 253 0420",
    "sg:postcode":"25801",
    "sg:province":"WV",
    "sg:tags":[
        "house"
    ],
    "wof:name":"Bc Builders LLC",
    "wof:placetype":"venue"
},
  "geometry": {"coordinates":[-81.24510600000001,37.779627],"type":"Point"}
}