{
  "type": "Feature",
  "properties": {
    "iso:country":"US",
    "sg:address":"2210 Washington St E",
    "sg:city":"Charleston",
    "sg:classifiers":[
        {
            "category":"Health Services",
            "subcategory":"Doctor",
            "type":"Services"
        }
    ],
    "sg:phone":"+1 304 345 9219",
    "sg:postcode":"25311",
    "sg:province":"WV",
    "sg:tags":[
        "medical",
        "legal"
    ],
    "wof:name":"West Virginia Chiropractic Soc",
    "wof:placetype":"venue"
},
  "geometry": {"coordinates":[-81.607938,38.336706],"type":"Point"}
}