{
  "type": "Feature",
  "properties": {
    "iso:country":"US",
    "sg:address":"126 S Raleigh St",
    "sg:city":"Martinsburg",
    "sg:classifiers":[
        {
            "category":"Wholesale",
            "subcategory":"Furniture",
            "type":"Manufacturing & Wholesale Goods"
        }
    ],
    "sg:phone":"+1 304 263 8416",
    "sg:postcode":"25401",
    "sg:province":"WV",
    "sg:tags":[
        "wholesaler",
        "mattress"
    ],
    "wof:name":"Grove Furniture",
    "wof:placetype":"venue"
},
  "geometry": {"coordinates":[-77.96854399999999,39.458058],"type":"Point"}
}