{
  "type": "Feature",
  "properties": {
    "iso:country":"US",
    "sg:address":"133 Cranes Ln",
    "sg:city":"Inwood",
    "sg:classifiers":[
        {
            "category":"Manufacturing",
            "subcategory":"Tools & Machinery",
            "type":"Manufacturing & Wholesale Goods"
        }
    ],
    "sg:phone":"+1 304 229 8610",
    "sg:postcode":"25414",
    "sg:province":"WV",
    "sg:tags":[
        "cleaning"
    ],
    "wof:name":"East Coast Cleaning",
    "wof:placetype":"venue"
},
  "geometry": {"coordinates":[-77.865889,39.302356],"type":"Point"}
}