{
  "type": "Feature",
  "properties": {
    "iso:country":"US",
    "sg:address":"219 2nd St",
    "sg:city":"Marietta",
    "sg:classifiers":[
        {
            "category":"Restaurant",
            "type":"Food & Drink"
        }
    ],
    "sg:phone":"+1 740 374 7377",
    "sg:postcode":"45750",
    "sg:province":"OH",
    "wof:name":"Loose Ties Cafe",
    "wof:placetype":"venue"
},
  "geometry": {"coordinates":[-81.452885,39.413388],"type":"Point"}
}