{
  "type": "Feature",
  "properties": {
    "addr:full":"1015 N Queen St Martinsburg WV 25404",
    "addr:housenumber":"1015",
    "addr:postcode":"25404",
    "addr:street":"N Queen St",
    "iso:country":"US",
    "sg:address":"1015 N Queen St",
    "sg:city":"Martinsburg",
    "sg:classifiers":[
        {
            "category":"Autos & Motor Vehicles",
            "subcategory":"Fuel & Gas Station",
            "type":"Retail Goods"
        },
        {
            "category":"Food & Beverages",
            "subcategory":"Groceries & Convenience Stores",
            "type":"Retail Goods"
        }
    ],
    "sg:phone":"+1 304 264 0394",
    "sg:postcode":"25404",
    "sg:province":"WV",
    "sg:website":"http://www.7-eleven.com",
    "wof:name":"7-Eleven - Market Recruiter",
    "wof:placetype":"venue"
},
  "geometry": {"coordinates":[-77.955738,39.4688],"type":"Point"}
}