{
  "type": "Feature",
  "properties": {
    "iso:country":"US",
    "sg:address":"1104 51st St",
    "sg:city":"Vienna",
    "sg:classifiers":[
        {
            "category":"Recreation",
            "type":"Entertainment"
        }
    ],
    "sg:phone":"+1 304 295 4899",
    "sg:postcode":"26105",
    "sg:province":"WV",
    "sg:tags":[
        "club",
        "membership"
    ],
    "wof:name":"Mid Ohio Valley Swim Asso",
    "wof:placetype":"venue"
},
  "geometry": {"coordinates":[-81.53370099999999,39.337808],"type":"Point"}
}