{
  "type": "Feature",
  "properties": {
    "addr:full":"20 Stewart Park Charleston WV 25313",
    "addr:housenumber":"20",
    "addr:postcode":"25313",
    "addr:street":"Stewart Park",
    "iso:country":"US",
    "sg:address":"20 Stewart Park",
    "sg:city":"Charleston",
    "sg:classifiers":[
        {
            "category":"Organizations",
            "subcategory":"Religious Organization",
            "type":"Services"
        }
    ],
    "sg:phone":"+1 304 776 4952",
    "sg:postcode":"25313",
    "sg:province":"WV",
    "wof:name":"Stewart Park Church of Christ",
    "wof:placetype":"venue"
},
  "geometry": {"coordinates":[-81.79710799999999,38.424127],"type":"Point"}
}