{
  "type": "Feature",
  "properties": {
    "iso:country":"US",
    "sg:address":"103 Valley View Dr",
    "sg:city":"Beckley",
    "sg:classifiers":[
        {
            "category":"Building & Trades",
            "subcategory":"Cleaning & Sanitation",
            "type":"Services"
        }
    ],
    "sg:phone":"+1 304 252 8125",
    "sg:postcode":"25801",
    "sg:province":"WV",
    "sg:tags":[
        "maintenance"
    ],
    "wof:name":"Ultra Window Cleaning",
    "wof:placetype":"venue"
},
  "geometry": {"coordinates":[-81.19067099999999,37.785606],"type":"Point"}
}