{
  "type": "Feature",
  "properties": {
    "iso:country":"US",
    "sg:address":"104 Park St",
    "sg:city":"Bluefield",
    "sg:classifiers":[
        {
            "category":"Organizations",
            "subcategory":"Religious Organization",
            "type":"Services"
        }
    ],
    "sg:phone":"+1 304 327 5908",
    "sg:postcode":"24701",
    "sg:province":"WV",
    "sg:tags":[
        "church"
    ],
    "wof:name":"Greater Mount Zion Pentecostal",
    "wof:placetype":"venue"
},
  "geometry": {"coordinates":[-81.232539,37.268443],"type":"Point"}
}