{
  "type": "Feature",
  "properties": {
    "iso:country":"US",
    "sg:address":"127 Maccorkle Ave",
    "sg:city":"St Albans",
    "sg:classifiers":[
        {
            "category":"Retail",
            "subcategory":"Auto Repair",
            "type":"Services"
        }
    ],
    "sg:phone":"+1 304 727 6760",
    "sg:postcode":"25177",
    "sg:province":"WV",
    "sg:tags":[
        "muffler",
        "exhaust",
        "system"
    ],
    "wof:name":"Quality Exhaust Inc",
    "wof:placetype":"venue"
},
  "geometry": {"coordinates":[-81.83498299999999,38.389728],"type":"Point"}
}