{
  "type": "Feature",
  "properties": {
    "iso:country":"US",
    "sg:address":"423 3rd St",
    "sg:city":"Marietta",
    "sg:classifiers":[
        {
            "category":"Shopping",
            "subcategory":"Musical Instruments",
            "type":"Retail Goods"
        }
    ],
    "sg:phone":"+1 740 373 8558",
    "sg:postcode":"45750",
    "sg:province":"OH",
    "wof:name":"Third Street Music",
    "wof:placetype":"venue"
},
  "geometry": {"coordinates":[-81.457019,39.419615],"type":"Point"}
}