{
  "type": "Feature",
  "properties": {
    "iso:country":"US",
    "sg:address":"4208 Malden Dr",
    "sg:city":"Charleston",
    "sg:classifiers":[
        {
            "category":"Home & Garden",
            "subcategory":"Home Furnishings",
            "type":"Retail Goods"
        },
        {
            "category":"Shopping",
            "subcategory":"Crafts & Fabrics",
            "type":"Retail Goods"
        }
    ],
    "sg:phone":"+1 304 925 9499",
    "sg:postcode":"25306",
    "sg:province":"WV",
    "sg:tags":[
        "p",
        "blanket",
        "sewing",
        "household",
        "mfg"
    ],
    "wof:name":"Cabin Creek Quilts",
    "wof:placetype":"venue"
},
  "geometry": {"coordinates":[-81.557294,38.29939],"type":"Point"}
}