{
  "type": "Feature",
  "properties": {
    "addr:full":"808 B St St Albans WV 25177",
    "addr:housenumber":"808",
    "addr:postcode":"25177",
    "addr:street":"B St",
    "iso:country":"US",
    "sg:address":"808 B St",
    "sg:city":"St Albans",
    "sg:classifiers":[
        {
            "category":"Health Services",
            "subcategory":"Health Practitioner",
            "type":"Services"
        }
    ],
    "sg:phone":"+1 304 727 7293",
    "sg:postcode":"25177",
    "sg:province":"WV",
    "sg:tags":[
        "therapist",
        "physical"
    ],
    "wof:name":"Teays Physical Therapy Center",
    "wof:placetype":"venue"
},
  "geometry": {"coordinates":[-81.83831000000001,38.385473],"type":"Point"}
}