{
  "type": "Feature",
  "properties": {
    "iso:country":"US",
    "sg:address":"106 Howard St",
    "sg:city":"Berkeley Springs",
    "sg:classifiers":[
        {
            "category":"Manufacturing",
            "subcategory":"Food",
            "type":"Manufacturing & Wholesale Goods"
        }
    ],
    "sg:phone":"+1 304 258 2400",
    "sg:postcode":"25411",
    "sg:province":"WV",
    "sg:tags":[
        "bottler"
    ],
    "wof:name":"West Virginia Spring Water Co",
    "wof:placetype":"venue"
},
  "geometry": {"coordinates":[-78.221412,39.633211],"type":"Point"}
}