{
  "type": "Feature",
  "properties": {
    "iso:country":"US",
    "sg:address":"301 4th Ave",
    "sg:city":"Huntington",
    "sg:classifiers":[
        {
            "category":"Retail",
            "subcategory":"Auto Repair",
            "type":"Services"
        }
    ],
    "sg:phone":"+1 304 522 1915",
    "sg:postcode":"25701",
    "sg:province":"WV",
    "sg:tags":[
        "transmission",
        "automotive"
    ],
    "wof:name":"A&A Transmission Service",
    "wof:placetype":"venue"
},
  "geometry": {"coordinates":[-82.45242399999999,38.419289],"type":"Point"}
}