{
  "type": "Feature",
  "properties": {
    "iso:country":"US",
    "sg:address":"101 Three Springs Dr",
    "sg:city":"Weirton",
    "sg:classifiers":[
        {
            "category":"Autos & Motor Vehicles",
            "subcategory":"Fuel & Gas Station",
            "type":"Retail Goods"
        }
    ],
    "sg:phone":"+1 304 723 3380",
    "sg:postcode":"26062",
    "sg:province":"WV",
    "sg:tags":[
        "oil"
    ],
    "wof:name":"BFS 27",
    "wof:placetype":"venue"
},
  "geometry": {"coordinates":[-80.54948400000001,40.399054],"type":"Point"}
}