{
  "type": "Feature",
  "properties": {
    "iso:country":"US",
    "sg:address":"598 Old Taylortown Rd",
    "sg:city":"Maidsville",
    "sg:classifiers":[
        {
            "category":"Professional",
            "type":"Services"
        }
    ],
    "sg:phone":"+1 304 328 4607",
    "sg:postcode":"26541",
    "sg:province":"WV",
    "wof:name":"Pondarosa Co",
    "wof:placetype":"venue"
},
  "geometry": {"coordinates":[-80.005526,39.720124],"type":"Point"}
}