{
  "type": "Feature",
  "properties": {
    "addr:full":"225 Thorn Ave Moundsville WV 26041",
    "addr:housenumber":"225",
    "addr:postcode":"26041",
    "addr:street":"Thorn Ave",
    "iso:country":"US",
    "sg:address":"225 Thorn Ave",
    "sg:city":"Moundsville",
    "sg:classifiers":[
        {
            "category":"Professional",
            "subcategory":"Management & Consulting",
            "type":"Services"
        }
    ],
    "sg:phone":"+1 304 845 5168",
    "sg:postcode":"26041",
    "sg:province":"WV",
    "sg:tags":[
        "business"
    ],
    "wof:name":"Don Wasmuth",
    "wof:placetype":"venue"
},
  "geometry": {"coordinates":[-80.724593,39.926634],"type":"Point"}
}