{
  "type": "Feature",
  "properties": {
    "addr:full":"927 Foxcroft Ave Martinsburg WV 25401",
    "addr:housenumber":"927",
    "addr:postcode":"25401",
    "addr:street":"Foxcroft Ave",
    "iso:country":"US",
    "sg:address":"927 Foxcroft Ave",
    "sg:city":"Martinsburg",
    "sg:classifiers":[
        {
            "category":"Restaurant",
            "type":"Food & Drink"
        }
    ],
    "sg:phone":"+1 304 267 0800",
    "sg:postcode":"25401",
    "sg:province":"WV",
    "wof:name":"Texas Steakhouse",
    "wof:placetype":"venue"
},
  "geometry": {"coordinates":[-77.987656,39.458589],"type":"Point"}
}