{
  "type": "Feature",
  "properties": {
    "addr:full":"370 Patteson Dr Morgantown WV 26505",
    "addr:housenumber":"370",
    "addr:postcode":"26505",
    "addr:street":"Patteson Dr",
    "iso:country":"US",
    "sg:address":"370 Patteson Dr",
    "sg:city":"Morgantown",
    "sg:classifiers":[
        {
            "category":"Shopping",
            "subcategory":"Computers & Home Electronics",
            "type":"Retail Goods"
        }
    ],
    "sg:phone":"+1 304 598 0683",
    "sg:postcode":"26505",
    "sg:province":"WV",
    "sg:tags":[
        "equipment",
        "electronic",
        "supply"
    ],
    "wof:name":"Radio Shack",
    "wof:placetype":"venue"
},
  "geometry": {"coordinates":[-79.968172,39.651179],"type":"Point"}
}