{
  "type": "Feature",
  "properties": {
    "iso:country":"US",
    "sg:address":"134 Bel Aire Dr",
    "sg:city":"Tornado",
    "sg:classifiers":[
        {
            "category":"Freight",
            "type":"Transportation"
        }
    ],
    "sg:phone":"+1 304 722 1003",
    "sg:postcode":"25202",
    "sg:province":"WV",
    "sg:tags":[
        "mover"
    ],
    "wof:name":"Dunbar Transfer",
    "wof:placetype":"venue"
},
  "geometry": {"coordinates":[-81.844036,38.343634],"type":"Point"}
}