{
  "type": "Feature",
  "properties": {
    "iso:country":"US",
    "sg:address":"220 N Pinch Rd",
    "sg:city":"Elkview",
    "sg:classifiers":[
        {
            "category":"Organizations",
            "subcategory":"Religious Organization",
            "type":"Services"
        }
    ],
    "sg:phone":"+1 304 965 1402",
    "sg:postcode":"25071",
    "sg:province":"WV",
    "wof:name":"Bible Christian Chapel",
    "wof:placetype":"venue"
},
  "geometry": {"coordinates":[-81.490191,38.418293],"type":"Point"}
}