{
  "type": "Feature",
  "properties": {
    "iso:country":"US",
    "sg:address":"4 River Walk Mall",
    "sg:city":"South Charleston",
    "sg:classifiers":[
        {
            "category":"Banks & Credit Unions",
            "subcategory":"Bank",
            "type":"Services"
        }
    ],
    "sg:phone":"+1 304 744 8918",
    "sg:postcode":"25303",
    "sg:province":"WV",
    "wof:name":"B B & T",
    "wof:placetype":"venue"
},
  "geometry": {"coordinates":[-81.713672,38.36365],"type":"Point"}
}