{
  "type": "Feature",
  "properties": {
    "iso:country":"US",
    "sg:address":"808 Main Ave",
    "sg:city":"Nitro",
    "sg:classifiers":[
        {
            "category":"Shopping",
            "subcategory":"Computers & Home Electronics",
            "type":"Retail Goods"
        }
    ],
    "sg:phone":"+1 304 755 3588",
    "sg:postcode":"25143",
    "sg:province":"WV",
    "sg:tags":[
        "equipment",
        "satellite",
        "system"
    ],
    "wof:name":"Satellite Technologies",
    "wof:placetype":"venue"
},
  "geometry": {"coordinates":[-81.84151900000001,38.403228],"type":"Point"}
}