{
  "type": "Feature",
  "properties": {
    "iso:country":"US",
    "sg:address":"181 Fleming St",
    "sg:city":"Fairmont",
    "sg:classifiers":[
        {
            "category":"Building & Trades",
            "subcategory":"Construction",
            "type":"Services"
        }
    ],
    "sg:phone":"+1 304 534 3086",
    "sg:postcode":"26554",
    "sg:province":"WV",
    "sg:tags":[
        "excavation",
        "contractor"
    ],
    "wof:name":"Vincents Excavating LLC",
    "wof:placetype":"venue"
},
  "geometry": {"coordinates":[-80.21104,39.457579],"type":"Point"}
}