{
  "type": "Feature",
  "properties": {
    "iso:country":"US",
    "sg:address":"931 23rd St",
    "sg:city":"Point Pleasant",
    "sg:classifiers":[
        {
            "category":"School Buses",
            "type":"Transportation"
        }
    ],
    "sg:phone":"+1 304 675 2740",
    "sg:postcode":"25550",
    "sg:province":"WV",
    "wof:name":"Mason County Schools",
    "wof:placetype":"venue"
},
  "geometry": {"coordinates":[-82.12615599999999,38.864926],"type":"Point"}
}