{
  "type": "Feature",
  "properties": {
    "addr:full":"107 Fream St Pennsboro WV 26415",
    "addr:housenumber":"107",
    "addr:postcode":"26415",
    "addr:street":"Fream St",
    "iso:country":"US",
    "sg:address":"107 Fream St",
    "sg:city":"Pennsboro",
    "sg:classifiers":[
        {
            "category":"Organizations",
            "subcategory":"Religious Organization",
            "type":"Services"
        }
    ],
    "sg:phone":"+1 304 659 2292",
    "sg:postcode":"26415",
    "sg:province":"WV",
    "wof:name":"Pennsboro Church of God",
    "wof:placetype":"venue"
},
  "geometry": {"coordinates":[-80.964744,39.285863],"type":"Point"}
}