{
  "type": "Feature",
  "properties": {
    "iso:country":"US",
    "sg:address":"203 Springdale Ave",
    "sg:city":"Princeton",
    "sg:classifiers":[
        {
            "category":"Autos & Motor Vehicles",
            "subcategory":"Automobile Sales",
            "type":"Retail Goods"
        }
    ],
    "sg:phone":"+1 304 425 2111",
    "sg:postcode":"24740",
    "sg:province":"WV",
    "sg:tags":[
        "used"
    ],
    "wof:name":"S & S Auto Sales",
    "wof:placetype":"venue"
},
  "geometry": {"coordinates":[-81.05974399999999,37.365645],"type":"Point"}
}