{
  "type": "Feature",
  "properties": {
    "addr:full":"5304 Edgebrook Dr Charleston WV 25313",
    "addr:housenumber":"5304",
    "addr:postcode":"25313",
    "addr:street":"Edgebrook Dr",
    "iso:country":"US",
    "sg:address":"5304 Edgebrook Dr",
    "sg:city":"Charleston",
    "sg:classifiers":[
        {
            "category":"Insurance",
            "subcategory":"Insurance Agent",
            "type":"Services"
        }
    ],
    "sg:phone":"+1 304 776 4557",
    "sg:postcode":"25313",
    "sg:province":"WV",
    "wof:name":"Ballard Insurance Agency LLC",
    "wof:placetype":"venue"
},
  "geometry": {"coordinates":[-81.776949,38.425851],"type":"Point"}
}