{
  "type": "Feature",
  "properties": {
    "addr:full":"221 Pike St Shinnston WV 26431",
    "addr:housenumber":"221",
    "addr:postcode":"26431",
    "addr:street":"Pike St",
    "iso:country":"US",
    "sg:address":"221 Pike St",
    "sg:city":"Shinnston",
    "sg:classifiers":[
        {
            "category":"Professional",
            "subcategory":"Computer Services",
            "type":"Services"
        }
    ],
    "sg:phone":"+1 304 592 5565",
    "sg:postcode":"26431",
    "sg:province":"WV",
    "sg:tags":[
        "design",
        "system"
    ],
    "wof:name":"Wolfes Computer Den",
    "wof:placetype":"venue"
},
  "geometry": {"coordinates":[-80.301508,39.395219],"type":"Point"}
}