{
  "type": "Feature",
  "properties": {
    "iso:country":"US",
    "sg:address":"107 E German St",
    "sg:city":"Shepherdstown",
    "sg:classifiers":[
        {
            "category":"Shopping",
            "subcategory":"Jewelry",
            "type":"Retail Goods"
        }
    ],
    "sg:phone":"+1 304 876 2681",
    "sg:postcode":"25443",
    "sg:province":"WV",
    "sg:tags":[
        "jeweler"
    ],
    "wof:name":"Sky's The Limit",
    "wof:placetype":"venue"
},
  "geometry": {"coordinates":[-77.805774,39.430925],"type":"Point"}
}