{
  "type": "Feature",
  "properties": {
    "iso:country":"US",
    "sg:address":"4216 Maccorkle Ave SE",
    "sg:city":"Charleston",
    "sg:classifiers":[
        {
            "category":"Shopping",
            "type":"Retail Goods"
        }
    ],
    "sg:phone":"+1 304 925 8100",
    "sg:postcode":"25304",
    "sg:province":"WV",
    "sg:tags":[
        "limb",
        "artificial"
    ],
    "wof:name":"Hanger Prosthetics & Orthotics",
    "wof:placetype":"venue"
},
  "geometry": {"coordinates":[-81.587024,38.324607],"type":"Point"}
}