{
  "type": "Feature",
  "properties": {
    "addr:full":"1041 8th Ave Huntington WV 25701",
    "addr:housenumber":"1041",
    "addr:postcode":"25701",
    "addr:street":"8Th Ave",
    "iso:country":"US",
    "sg:address":"1041 8th Ave",
    "sg:city":"Huntington",
    "sg:classifiers":[
        {
            "category":"Shopping",
            "subcategory":"Stationery & Office Supplies",
            "type":"Retail Goods"
        }
    ],
    "sg:phone":"+1 304 522 7022",
    "sg:postcode":"25701",
    "sg:province":"WV",
    "wof:name":"Aaron's Products Inc",
    "wof:placetype":"venue"
},
  "geometry": {"coordinates":[-82.439391,38.415446],"type":"Point"}
}