{
  "type": "Feature",
  "properties": {
    "addr:full":"999 11th St Moundsville WV 26041",
    "addr:housenumber":"999",
    "addr:postcode":"26041",
    "addr:street":"11Th St",
    "iso:country":"US",
    "sg:address":"999 11th St",
    "sg:city":"Moundsville",
    "sg:classifiers":[
        {
            "category":"Government",
            "subcategory":"Office",
            "type":"Public Place"
        }
    ],
    "sg:phone":"+1 304 843 4142",
    "sg:postcode":"26041",
    "sg:province":"WV",
    "sg:website":"http://www.wvchar.ang.af.mil",
    "wof:name":"Northern District Office",
    "wof:placetype":"venue"
},
  "geometry": {"coordinates":[-80.74147000000001,39.914371],"type":"Point"}
}