{
  "type": "Feature",
  "properties": {
    "iso:country":"US",
    "sg:address":"246 Kruger St",
    "sg:city":"Wheeling",
    "sg:classifiers":[
        {
            "category":"Professional",
            "subcategory":"Accounting & Tax Preparation",
            "type":"Services"
        }
    ],
    "sg:phone":"+1 304 242 0985",
    "sg:postcode":"26003",
    "sg:province":"WV",
    "sg:tags":[
        "accountant"
    ],
    "wof:name":"Yourkovich & Associates",
    "wof:placetype":"venue"
},
  "geometry": {"coordinates":[-80.658119,40.037101],"type":"Point"}
}