{
  "type": "Feature",
  "properties": {
    "iso:country":"US",
    "sg:address":"801 Pennsylvania Ave",
    "sg:city":"Fairmont",
    "sg:classifiers":[
        {
            "category":"Retail",
            "subcategory":"Auto Repair",
            "type":"Services"
        }
    ],
    "sg:phone":"+1 304 363 1860",
    "sg:postcode":"26554",
    "sg:province":"WV",
    "sg:tags":[
        "repairing",
        "automobile"
    ],
    "wof:name":"M & M Merrifield Auto",
    "wof:placetype":"venue"
},
  "geometry": {"coordinates":[-80.138999,39.497872],"type":"Point"}
}