{
  "type": "Feature",
  "properties": {
    "iso:country":"US",
    "sg:address":"5900 Maccorkle Ave",
    "sg:city":"St Albans",
    "sg:classifiers":[
        {
            "category":"Wholesale",
            "subcategory":"Machinery & Supplies",
            "type":"Manufacturing & Wholesale Goods"
        }
    ],
    "sg:phone":"+1 304 768 5965",
    "sg:postcode":"25177",
    "sg:province":"WV",
    "sg:tags":[
        "contractor"
    ],
    "wof:name":"Vermeer Sales & Svc Of",
    "wof:placetype":"venue"
},
  "geometry": {"coordinates":[-81.753013,38.356456],"type":"Point"}
}