{
  "type": "Feature",
  "properties": {
    "iso:country":"US",
    "sg:address":"5298 David Dr",
    "sg:city":"Charleston",
    "sg:classifiers":[
        {
            "category":"Shopping",
            "subcategory":"Computers & Home Electronics",
            "type":"Retail Goods"
        }
    ],
    "sg:phone":"+1 304 769 2202",
    "sg:postcode":"25313",
    "sg:province":"WV",
    "wof:name":"Computec Sales & Service",
    "wof:placetype":"venue"
},
  "geometry": {"coordinates":[-81.758633,38.435385],"type":"Point"}
}