{
  "type": "Feature",
  "properties": {
    "iso:country":"US",
    "sg:address":"215 Meadow Ln",
    "sg:city":"Petersburg",
    "sg:classifiers":[
        {
            "category":"Organizations",
            "subcategory":"Religious Organization",
            "type":"Services"
        }
    ],
    "sg:phone":"+1 304 257 4257",
    "sg:postcode":"26807",
    "sg:province":"WV",
    "sg:tags":[
        "church"
    ],
    "wof:name":"Bethel Church Of The Brethren",
    "wof:placetype":"venue"
},
  "geometry": {"coordinates":[-79.328564,38.644704],"type":"Point"}
}