{
  "type": "Feature",
  "properties": {
    "addr:full":"213 Washington St Ravenswood WV 26164",
    "addr:housenumber":"213",
    "addr:postcode":"26164",
    "addr:street":"Washington St",
    "iso:country":"US",
    "sg:address":"213 Washington St",
    "sg:city":"Ravenswood",
    "sg:classifiers":[
        {
            "category":"Home & Garden",
            "subcategory":"Household Appliances",
            "type":"Retail Goods"
        }
    ],
    "sg:phone":"+1 304 273 1188",
    "sg:postcode":"26164",
    "sg:province":"WV",
    "wof:name":"T & T Used Appliances",
    "wof:placetype":"venue"
},
  "geometry": {"coordinates":[-81.761385,38.948689],"type":"Point"}
}