{
  "type": "Feature",
  "properties": {
    "iso:country":"US",
    "sg:address":"115 S 5th St",
    "sg:city":"Clarksburg",
    "sg:classifiers":[
        {
            "category":"Professional",
            "subcategory":"Lawyer & Legal Services",
            "type":"Services"
        }
    ],
    "sg:phone":"+1 304 326 2600",
    "sg:postcode":"26301",
    "sg:province":"WV",
    "sg:tags":[
        "attorney"
    ],
    "wof:name":"Edmund J Matko",
    "wof:placetype":"venue"
},
  "geometry": {"coordinates":[-80.341249,39.279576],"type":"Point"}
}