{
  "type": "Feature",
  "properties": {
    "iso:country":"US",
    "sg:address":"729 Bakers Ridge Rd",
    "sg:city":"Morgantown",
    "sg:classifiers":[
        {
            "category":"Real Estate",
            "subcategory":"Real Estate Operator",
            "type":"Services"
        }
    ],
    "sg:phone":"+1 304 599 2751",
    "sg:postcode":"26508",
    "sg:province":"WV",
    "sg:tags":[
        "building",
        "ope",
        "apartment",
        "nonresidential"
    ],
    "wof:name":"Morgantown Engineer & Cnstr Co",
    "wof:placetype":"venue"
},
  "geometry": {"coordinates":[-79.93623100000001,39.672229],"type":"Point"}
}