{
  "type": "Feature",
  "properties": {
    "addr:full":"194 Willey St Morgantown WV 26505",
    "addr:housenumber":"194",
    "addr:postcode":"26505",
    "addr:street":"Willey St",
    "iso:country":"US",
    "sg:address":"194 Willey St",
    "sg:city":"Morgantown",
    "sg:classifiers":[
        {
            "category":"Shopping",
            "subcategory":"Clothing, Apparel, & Fashions",
            "type":"Retail Goods"
        }
    ],
    "sg:phone":"+1 304 296 7265",
    "sg:postcode":"26505",
    "sg:province":"WV",
    "sg:tags":[
        "made",
        "t",
        "shirt"
    ],
    "wof:name":"Fan's Choice",
    "wof:placetype":"venue"
},
  "geometry": {"coordinates":[-79.954109,39.632194],"type":"Point"}
}