{
  "type": "Feature",
  "properties": {
    "iso:country":"US",
    "sg:address":"1424 6th Ave",
    "sg:city":"Huntington",
    "sg:classifiers":[
        {
            "category":"Health Services",
            "subcategory":"Clinic",
            "type":"Services"
        }
    ],
    "sg:phone":"+1 304 522 3740",
    "sg:postcode":"25701",
    "sg:province":"WV",
    "sg:tags":[
        "a",
        "operates",
        "provides",
        "out"
    ],
    "wof:name":"Crisis Residential Unit",
    "wof:placetype":"venue"
},
  "geometry": {"coordinates":[-82.43313499999999,38.419802],"type":"Point"}
}