{
  "type": "Feature",
  "properties": {
    "iso:country":"US",
    "sg:address":"704 Lincoln St",
    "sg:city":"Mcmechen",
    "sg:classifiers":[
        {
            "category":"Building & Trades",
            "subcategory":"Construction",
            "type":"Services"
        }
    ],
    "sg:phone":"+1 304 233 4377",
    "sg:postcode":"26040",
    "sg:province":"WV",
    "sg:tags":[
        "house",
        "general",
        "contractor"
    ],
    "wof:name":"Bartsch Construction",
    "wof:placetype":"venue"
},
  "geometry": {"coordinates":[-80.732918,39.988062],"type":"Point"}
}