{
  "type": "Feature",
  "properties": {
    "addr:full":"2151 Cedar Lakes Dr Ripley WV 25271",
    "addr:housenumber":"2151",
    "addr:postcode":"25271",
    "addr:street":"Cedar Lakes Dr",
    "iso:country":"US",
    "sg:address":"2151 Cedar Lakes Dr",
    "sg:city":"Ripley",
    "sg:classifiers":[
        {
            "category":"Restaurant",
            "type":"Food & Drink"
        }
    ],
    "sg:menulink":"http://www.allmenus.com/wv/eastern/167491-burger-king/menu/",
    "sg:phone":"+1 304 372 1022",
    "sg:postcode":"25271",
    "sg:province":"WV",
    "sg:tags":[
        "american"
    ],
    "wof:name":"Burger King",
    "wof:placetype":"venue"
},
  "geometry": {"coordinates":[-81.696826,38.802078],"type":"Point"}
}