{
  "type": "Feature",
  "properties": {
    "addr:full":"253 W Main St Grafton WV 26354",
    "addr:housenumber":"253",
    "addr:postcode":"26354",
    "addr:street":"W Main St",
    "iso:country":"US",
    "sg:address":"253 W Main St",
    "sg:city":"Grafton",
    "sg:classifiers":[
        {
            "category":"Home & Garden",
            "subcategory":"Building Materials",
            "type":"Retail Goods"
        }
    ],
    "sg:phone":"+1 304 265 3800",
    "sg:postcode":"26354",
    "sg:province":"WV",
    "sg:tags":[
        "paint"
    ],
    "wof:name":"Big Sky Paint LLC",
    "wof:placetype":"venue"
},
  "geometry": {"coordinates":[-80.02239,39.341507],"type":"Point"}
}