{
  "type": "Feature",
  "properties": {
    "iso:country":"US",
    "sg:address":"1600 Jefferson St",
    "sg:city":"Bluefield",
    "sg:classifiers":[
        {
            "category":"Real Estate",
            "subcategory":"Real Estate Agent",
            "type":"Services"
        }
    ],
    "sg:phone":"+1 304 325 3522",
    "sg:postcode":"24701",
    "sg:province":"WV",
    "wof:name":"Elliott Inc",
    "wof:placetype":"venue"
},
  "geometry": {"coordinates":[-81.22162299999999,37.258055],"type":"Point"}
}