{
  "type": "Feature",
  "properties": {
    "iso:country":"US",
    "sg:address":"100 Taylor Ln",
    "sg:city":"Fairlea",
    "sg:classifiers":[
        {
            "category":"Health Services",
            "subcategory":"Doctor",
            "type":"Services"
        }
    ],
    "sg:phone":"+1 304 645 7806",
    "sg:postcode":"24970",
    "sg:province":"WV",
    "sg:tags":[
        "physician",
        "surgeon"
    ],
    "wof:name":"Skin & Vein Laser Ctr",
    "wof:placetype":"venue"
},
  "geometry": {"coordinates":[-80.46420999999999,37.768302],"type":"Point"}
}