{
  "type": "Feature",
  "properties": {
    "addr:full":"851 E Moler Ave Martinsburg WV 25404",
    "addr:housenumber":"851",
    "addr:postcode":"25404",
    "addr:street":"E Moler Ave",
    "iso:country":"US",
    "sg:address":"851 E Moler Ave",
    "sg:city":"Martinsburg",
    "sg:classifiers":[
        {
            "category":"Fast Food",
            "type":"Food & Drink"
        },
        {
            "category":"Restaurant",
            "type":"Food & Drink"
        },
        {
            "category":"Food & Beverages",
            "subcategory":"Meat & Fish",
            "type":"Retail Goods"
        }
    ],
    "sg:phone":"+1 304 267 6145",
    "sg:postcode":"25404",
    "sg:province":"WV",
    "sg:tags":[
        "seafood",
        "take",
        "market"
    ],
    "wof:name":"Season's Best Seafood",
    "wof:placetype":"venue"
},
  "geometry": {"coordinates":[-77.94650900000001,39.464931],"type":"Point"}
}