{
  "type": "Feature",
  "properties": {
    "iso:country":"US",
    "sg:address":"109 Fairmont Ave",
    "sg:city":"Fairmont",
    "sg:classifiers":[
        {
            "category":"Social Services",
            "type":"Services"
        }
    ],
    "sg:phone":"+1 304 367 1098",
    "sg:postcode":"26554",
    "sg:province":"WV",
    "wof:name":"Sabrina Soup Kitchen",
    "wof:placetype":"venue"
},
  "geometry": {"coordinates":[-80.14622199999999,39.482659],"type":"Point"}
}