{
  "type": "Feature",
  "properties": {
    "iso:country":"US",
    "sg:address":"1704 Rayon Dr",
    "sg:city":"Parkersburg",
    "sg:classifiers":[
        {
            "category":"Education",
            "subcategory":"Dance Studio",
            "type":"Public Place"
        }
    ],
    "sg:phone":"+1 304 485 4398",
    "sg:postcode":"26101",
    "sg:province":"WV",
    "sg:tags":[
        "instruction",
        "dancing"
    ],
    "wof:name":"Tina's Dance Studio One",
    "wof:placetype":"venue"
},
  "geometry": {"coordinates":[-81.53953,39.233854],"type":"Point"}
}