{
  "type": "Feature",
  "properties": {
    "iso:country":"US",
    "sg:address":"106 Rockcrest Dr",
    "sg:city":"Charleston",
    "sg:classifiers":[
        {
            "category":"Social Services",
            "subcategory":"Job Training",
            "type":"Services"
        }
    ],
    "sg:phone":"+1 304 768 1824",
    "sg:postcode":"25309",
    "sg:province":"WV",
    "sg:tags":[
        "vocational",
        "expert"
    ],
    "wof:name":"Ted Tanzey",
    "wof:placetype":"venue"
},
  "geometry": {"coordinates":[-81.748739,38.344034],"type":"Point"}
}