{
  "type": "Feature",
  "properties": {
    "addr:full":"120 E Main St Wardensville WV 26851",
    "addr:housenumber":"120",
    "addr:postcode":"26851",
    "addr:street":"E Main St",
    "iso:country":"US",
    "sg:address":"120 E Main St",
    "sg:city":"Wardensville",
    "sg:classifiers":[
        {
            "category":"Personal",
            "subcategory":"Beauty Salon",
            "type":"Services"
        }
    ],
    "sg:phone":"+1 304 874 3576",
    "sg:postcode":"26851",
    "sg:province":"WV",
    "wof:name":"Cutting Edge",
    "wof:placetype":"venue"
},
  "geometry": {"coordinates":[-78.594329,39.07705],"type":"Point"}
}