{
  "type": "Feature",
  "properties": {
    "addr:full":"579 Rocky Step Rd Winfield WV 25213",
    "addr:housenumber":"579",
    "addr:postcode":"25213",
    "addr:street":"Rocky Step Rd",
    "iso:country":"US",
    "sg:address":"579 Rocky Step Rd",
    "sg:city":"Winfield",
    "sg:classifiers":[
        {
            "category":"Travel",
            "subcategory":"Campground",
            "type":"Entertainment"
        }
    ],
    "sg:phone":"+1 304 586 4259",
    "sg:postcode":"25213",
    "sg:province":"WV",
    "sg:tags":[
        "camp"
    ],
    "wof:name":"Ultra Quest Sports Training",
    "wof:placetype":"venue"
},
  "geometry": {"coordinates":[-81.90219399999999,38.514018],"type":"Point"}
}