{
  "type": "Feature",
  "properties": {
    "addr:full":"393 Monroe St Weston WV 26452",
    "addr:housenumber":"393",
    "addr:postcode":"26452",
    "addr:street":"Monroe St",
    "iso:country":"US",
    "sg:address":"393 Monroe St",
    "sg:city":"Weston",
    "sg:classifiers":[
        {
            "category":"Freight",
            "type":"Transportation"
        }
    ],
    "sg:phone":"+1 304 269 5120",
    "sg:postcode":"26452",
    "sg:province":"WV",
    "sg:tags":[
        "trucking"
    ],
    "wof:name":"K&M Trucking Inc",
    "wof:placetype":"venue"
},
  "geometry": {"coordinates":[-80.470483,39.04998],"type":"Point"}
}