{
  "type": "Feature",
  "properties": {
    "addr:full":"12 Mall Rd Barboursville WV 25504",
    "addr:housenumber":"12",
    "addr:postcode":"25504",
    "addr:street":"Mall Rd",
    "iso:country":"US",
    "sg:address":"12 Mall Rd",
    "sg:city":"Barboursville",
    "sg:classifiers":[
        {
            "category":"Restaurant",
            "type":"Food & Drink"
        }
    ],
    "sg:menulink":"http://www.allmenus.com/wv/barboursville/13835-olive-garden-italian-restaurant/menu/",
    "sg:phone":"+1 304 733 6481",
    "sg:postcode":"25504",
    "sg:province":"WV",
    "sg:tags":[
        "italian"
    ],
    "wof:name":"Olive Garden Italian Restaurant",
    "wof:placetype":"venue"
},
  "geometry": {"coordinates":[-82.25960000000001,38.415263],"type":"Point"}
}