{
  "type": "Feature",
  "properties": {
    "iso:country":"US",
    "sg:address":"2705 Riverside Dr",
    "sg:city":"Saint Albans",
    "sg:classifiers":[
        {
            "category":"Building & Trades",
            "subcategory":"Construction",
            "type":"Services"
        }
    ],
    "sg:phone":"+1 304 727 2059",
    "sg:postcode":"25177",
    "sg:province":"WV",
    "sg:tags":[
        "residential"
    ],
    "wof:name":"Jericho Contracting LLC",
    "wof:placetype":"venue"
},
  "geometry": {"coordinates":[-81.853003,38.369789],"type":"Point"}
}