{
  "type": "Feature",
  "properties": {
    "iso:country":"US",
    "sg:address":"205 Counts Rd",
    "sg:city":"Spencer",
    "sg:classifiers":[
        {
            "category":"Building & Trades",
            "subcategory":"Construction",
            "type":"Services"
        }
    ],
    "sg:phone":"+1 304 927 3007",
    "sg:postcode":"25276",
    "sg:province":"WV",
    "sg:tags":[
        "house",
        "nonresidential"
    ],
    "wof:name":"Randolph Construction Company",
    "wof:placetype":"venue"
},
  "geometry": {"coordinates":[-81.33813000000001,38.80479],"type":"Point"}
}