{
  "type": "Feature",
  "properties": {
    "addr:full":"805 E Washington St Charles Town WV 25414",
    "addr:housenumber":"805",
    "addr:postcode":"25414",
    "addr:street":"E Washington St Charles Town",
    "iso:country":"US",
    "sg:address":"805 E Washington St",
    "sg:city":"Charles Town",
    "sg:classifiers":[
        {
            "category":"Autos & Motor Vehicles",
            "subcategory":"Fuel & Gas Station",
            "type":"Retail Goods"
        }
    ],
    "sg:phone":"+1 304 725 2285",
    "sg:postcode":"25414",
    "sg:province":"WV",
    "sg:tags":[
        "automotive",
        "repair",
        "station",
        "gasoline",
        "towing"
    ],
    "wof:name":"Chevron",
    "wof:placetype":"venue"
},
  "geometry": {"coordinates":[-77.847195,39.293389],"type":"Point"}
}