{
  "type": "Feature",
  "properties": {
    "iso:country":"US",
    "sg:address":"1103 Jefferson Rd",
    "sg:city":"Charleston",
    "sg:classifiers":[
        {
            "category":"Building & Trades",
            "subcategory":"Construction",
            "type":"Services"
        }
    ],
    "sg:phone":"+1 304 744 5532",
    "sg:postcode":"25309",
    "sg:province":"WV",
    "sg:tags":[
        "marking",
        "maintenance",
        "parking"
    ],
    "wof:name":"South Charleston Public Works",
    "wof:placetype":"venue"
},
  "geometry": {"coordinates":[-81.70950000000001,38.344423],"type":"Point"}
}