{
  "type": "Feature",
  "properties": {
    "iso:country":"US",
    "sg:address":"141 Frame Rd",
    "sg:city":"Elkview",
    "sg:classifiers":[
        {
            "category":"Restaurant",
            "type":"Food & Drink"
        }
    ],
    "sg:phone":"+1 304 965 2226",
    "sg:postcode":"25071",
    "sg:province":"WV",
    "wof:name":"Feed House",
    "wof:placetype":"venue"
},
  "geometry": {"coordinates":[-81.497236,38.458019],"type":"Point"}
}