{
  "type": "Feature",
  "properties": {
    "iso:country":"US",
    "sg:address":"64 Valley St",
    "sg:city":"Salem",
    "sg:classifiers":[
        {
            "category":"Autos & Motor Vehicles",
            "subcategory":"Auto Supplies",
            "type":"Retail Goods"
        },
        {
            "category":"Retail",
            "subcategory":"Auto Repair",
            "type":"Services"
        }
    ],
    "sg:phone":"+1 304 782 3462",
    "sg:postcode":"26426",
    "sg:province":"WV",
    "sg:tags":[
        "tire",
        "general"
    ],
    "wof:name":"B & B Tire & Auto Repair Inc",
    "wof:placetype":"venue"
},
  "geometry": {"coordinates":[-80.55998700000001,39.283678],"type":"Point"}
}