{
  "type": "Feature",
  "properties": {
    "addr:full":"2004 Harper Rd Beckley WV 25801",
    "addr:housenumber":"2004",
    "addr:postcode":"25801",
    "addr:street":"Harper Rd",
    "iso:country":"US",
    "sg:address":"2004 Harper Rd",
    "sg:city":"Beckley",
    "sg:classifiers":[
        {
            "category":"Restaurant",
            "type":"Food & Drink"
        }
    ],
    "sg:menulink":"http://www.allmenus.com/wv/mcalpin/155260-hardees/menu/",
    "sg:phone":"+1 304 252 4221",
    "sg:postcode":"25801",
    "sg:province":"WV",
    "sg:tags":[
        "burger",
        "american"
    ],
    "wof:name":"Hardee's",
    "wof:placetype":"venue"
},
  "geometry": {"coordinates":[-81.21772900000001,37.794721],"type":"Point"}
}