{
  "type": "Feature",
  "properties": {
    "iso:country":"US",
    "sg:address":"101 Ramey Ct",
    "sg:city":"Beckley",
    "sg:classifiers":[
        {
            "category":"Professional",
            "type":"Services"
        }
    ],
    "sg:phone":"+1 304 929 9233",
    "sg:postcode":"25801",
    "sg:province":"WV",
    "sg:tags":[
        "establishment"
    ],
    "wof:name":"Era Zaferatos & Assoc",
    "wof:placetype":"venue"
},
  "geometry": {"coordinates":[-81.191625,37.777445],"type":"Point"}
}