{
  "type": "Feature",
  "properties": {
    "addr:full":"200 W Main St Salem WV 26426",
    "addr:housenumber":"200",
    "addr:postcode":"26426",
    "addr:street":"W Main St",
    "iso:country":"US",
    "sg:address":"200 W Main St",
    "sg:city":"Salem",
    "sg:classifiers":[
        {
            "category":"Restaurant",
            "type":"Food & Drink"
        },
        {
            "category":"Ice Cream",
            "type":"Food & Drink"
        }
    ],
    "sg:menulink":"http://www.allmenus.com/wv/southwest/192390-dairy-queen/menu/",
    "sg:phone":"+1 304 782 1197",
    "sg:postcode":"26426",
    "sg:province":"WV",
    "sg:tags":[
        "burger",
        "american",
        "ice",
        "cream"
    ],
    "wof:name":"Dairy Queen",
    "wof:placetype":"venue"
},
  "geometry": {"coordinates":[-80.564767,39.283192],"type":"Point"}
}