{
  "type": "Feature",
  "properties": {
    "iso:country":"US",
    "sg:address":"215 Wilson Ave",
    "sg:city":"Morgantown",
    "sg:classifiers":[
        {
            "category":"Banks & Credit Unions",
            "subcategory":"Financial Services",
            "type":"Services"
        }
    ],
    "sg:phone":"+1 304 598 8265",
    "sg:postcode":"26501",
    "sg:province":"WV",
    "sg:tags":[
        "investor"
    ],
    "wof:name":"Petitte Properties LLC",
    "wof:placetype":"venue"
},
  "geometry": {"coordinates":[-79.95534499999999,39.62375],"type":"Point"}
}