{
  "type": "Feature",
  "properties": {
    "iso:country":"US",
    "sg:address":"34 Rebecca St",
    "sg:city":"Shinnston",
    "sg:classifiers":[
        {
            "category":"Shopping",
            "subcategory":"Bicycles & Sporting Goods",
            "type":"Retail Goods"
        }
    ],
    "sg:phone":"+1 304 592 1302",
    "sg:postcode":"26431",
    "sg:province":"WV",
    "wof:name":"J & R Sporting Goods & Pawn",
    "wof:placetype":"venue"
},
  "geometry": {"coordinates":[-80.30033400000001,39.39703],"type":"Point"}
}