{
  "type": "Feature",
  "properties": {
    "iso:country":"US",
    "sg:address":"102 Oak St",
    "sg:city":"Oak Hill",
    "sg:classifiers":[
        {
            "category":"Professional",
            "type":"Services"
        }
    ],
    "sg:phone":"+1 304 469 8757",
    "sg:postcode":"25901",
    "sg:province":"WV",
    "wof:name":"Mineral Development Consultant",
    "wof:placetype":"venue"
},
  "geometry": {"coordinates":[-81.139625,37.983246],"type":"Point"}
}