{
  "type": "Feature",
  "properties": {
    "iso:country":"US",
    "sg:address":"295 Adams Ave",
    "sg:city":"Hurricane",
    "sg:classifiers":[
        {
            "category":"Freight",
            "type":"Transportation"
        }
    ],
    "sg:phone":"+1 304 562 9846",
    "sg:postcode":"25526",
    "sg:province":"WV",
    "sg:tags":[
        "local",
        "storage",
        "trucking"
    ],
    "wof:name":"Chris Hogstan Trucking",
    "wof:placetype":"venue"
},
  "geometry": {"coordinates":[-82.01754099999999,38.430881],"type":"Point"}
}