{
  "type": "Feature",
  "properties": {
    "iso:country":"US",
    "sg:address":"1105 US Rte 33",
    "sg:city":"Elkins",
    "sg:classifiers":[
        {
            "category":"Manufacturing",
            "subcategory":"Lumber",
            "type":"Manufacturing & Wholesale Goods"
        }
    ],
    "sg:phone":"+1 304 636 2081",
    "sg:postcode":"26241",
    "sg:province":"WV",
    "sg:tags":[
        "mill",
        "wood",
        "pres",
        "mfg"
    ],
    "wof:name":"Coastal Forest Resources Co",
    "wof:placetype":"venue"
},
  "geometry": {"coordinates":[-79.862043,38.931084],"type":"Point"}
}