{
  "type": "Feature",
  "properties": {
    "iso:country":"US",
    "sg:address":"116 N Chester St",
    "sg:city":"New Cumberland",
    "sg:classifiers":[
        {
            "category":"Shopping",
            "subcategory":"Florist",
            "type":"Retail Goods"
        }
    ],
    "sg:phone":"+1 304 564 3803",
    "sg:postcode":"26047",
    "sg:province":"WV",
    "wof:name":"Dunlevy's Florist",
    "wof:placetype":"venue"
},
  "geometry": {"coordinates":[-80.609551,40.498536],"type":"Point"}
}