{
  "type": "Feature",
  "properties": {
    "addr:full":"300 Cheat Rd Morgantown WV 26508",
    "addr:housenumber":"300",
    "addr:postcode":"26508",
    "addr:street":"Cheat Rd",
    "iso:country":"US",
    "sg:address":"300 Cheat Rd",
    "sg:city":"Morgantown",
    "sg:classifiers":[
        {
            "category":"Food & Beverages",
            "subcategory":"Groceries & Convenience Stores",
            "type":"Retail Goods"
        }
    ],
    "sg:phone":"+1 304 292 1610",
    "sg:postcode":"26508",
    "sg:province":"WV",
    "wof:name":"Ashebrooke Express Mart",
    "wof:placetype":"venue"
},
  "geometry": {"coordinates":[-79.88554999999999,39.654325],"type":"Point"}
}