{
  "type": "Feature",
  "properties": {
    "iso:country":"US",
    "sg:address":"1706 Greenbrier St",
    "sg:city":"Charleston",
    "sg:classifiers":[
        {
            "category":"Organizations",
            "subcategory":"Community Association",
            "type":"Services"
        }
    ],
    "sg:phone":"+1 304 346 3557",
    "sg:postcode":"25311",
    "sg:province":"WV",
    "sg:tags":[
        "fraternal"
    ],
    "wof:name":"Elks Lodge",
    "wof:placetype":"venue"
},
  "geometry": {"coordinates":[-81.570471,38.375293],"type":"Point"}
}