{
  "type": "Feature",
  "properties": {
    "addr:full":"83 Evergreen Cir Nitro WV 25159",
    "addr:housenumber":"83",
    "addr:postcode":"25159",
    "addr:street":"Evergreen Cir",
    "iso:country":"US",
    "sg:address":"83 Evergreen Cir",
    "sg:city":"Nitro",
    "sg:classifiers":[
        {
            "category":"Organizations",
            "subcategory":"Religious Organization",
            "type":"Services"
        }
    ],
    "sg:phone":"+1 304 755 4003",
    "sg:postcode":"25159",
    "sg:province":"WV",
    "sg:tags":[
        "clergy"
    ],
    "wof:name":"Benny Bess",
    "wof:placetype":"venue"
},
  "geometry": {"coordinates":[-81.801731,38.463809],"type":"Point"}
}