{
  "type": "Feature",
  "properties": {
    "iso:country":"US",
    "sg:address":"100 Kanawha Ter",
    "sg:city":"St Albans",
    "sg:classifiers":[
        {
            "category":"Communications",
            "subcategory":"Radio Station",
            "type":"Services"
        }
    ],
    "sg:phone":"+1 304 743 1051",
    "sg:postcode":"25177",
    "sg:province":"WV",
    "sg:tags":[
        "company",
        "broadcasting"
    ],
    "wof:name":"Rock 105 WKLC",
    "wof:placetype":"venue"
},
  "geometry": {"coordinates":[-81.83750000000001,38.385279],"type":"Point"}
}