{
  "type": "Feature",
  "properties": {
    "iso:country":"US",
    "sg:address":"4438 Ohio River Rd",
    "sg:city":"Huntington",
    "sg:classifiers":[
        {
            "category":"Shopping",
            "type":"Retail Goods"
        }
    ],
    "sg:phone":"+1 304 522 7029",
    "sg:postcode":"25702",
    "sg:province":"WV",
    "sg:tags":[
        "trophy",
        "medal",
        "award"
    ],
    "wof:name":"A & J Trophy Mfg Co",
    "wof:placetype":"venue"
},
  "geometry": {"coordinates":[-82.36425800000001,38.432925],"type":"Point"}
}