{
  "type": "Feature",
  "properties": {
    "iso:country":"US",
    "sg:address":"182 Seneca Trl",
    "sg:city":"Lewisburg",
    "sg:classifiers":[
        {
            "category":"Bars & Pubs",
            "type":"Food & Drink"
        }
    ],
    "sg:phone":"+1 304 645 0203",
    "sg:postcode":"24901",
    "sg:province":"WV",
    "wof:name":"Lottery Lounge",
    "wof:placetype":"venue"
},
  "geometry": {"coordinates":[-80.46213299999999,37.773012],"type":"Point"}
}