{
  "type": "Feature",
  "properties": {
    "iso:country":"US",
    "sg:address":"3131 Main St",
    "sg:city":"Weirton",
    "sg:classifiers":[
        {
            "category":"Shopping",
            "subcategory":"Florist",
            "type":"Retail Goods"
        }
    ],
    "sg:phone":"+1 304 748 4525",
    "sg:postcode":"26062",
    "sg:province":"WV",
    "wof:name":"Mc Causlen's Florist",
    "wof:placetype":"venue"
},
  "geometry": {"coordinates":[-80.588596,40.406743],"type":"Point"}
}