{
  "type": "Feature",
  "properties": {
    "iso:country":"US",
    "sg:address":"611 Lakeview Dr",
    "sg:city":"Parkersburg",
    "sg:classifiers":[
        {
            "category":"Building & Trades",
            "subcategory":"Landscaping Services",
            "type":"Services"
        }
    ],
    "sg:phone":"+1 304 422 5871",
    "sg:postcode":"26104",
    "sg:province":"WV",
    "sg:tags":[
        "landscape"
    ],
    "wof:name":"Mw Services",
    "wof:placetype":"venue"
},
  "geometry": {"coordinates":[-81.54510500000001,39.294624],"type":"Point"}
}