{
  "type": "Feature",
  "properties": {
    "addr:full":"1210 Johnson Ave Bridgeport WV 26330",
    "addr:housenumber":"1210",
    "addr:postcode":"26330",
    "addr:street":"Johnson Ave",
    "iso:country":"US",
    "sg:address":"1210 Johnson Ave",
    "sg:city":"Bridgeport",
    "sg:classifiers":[
        {
            "category":"Insurance",
            "subcategory":"Insurance Agent",
            "type":"Services"
        }
    ],
    "sg:phone":"+1 304 842 3923",
    "sg:postcode":"26330",
    "sg:province":"WV",
    "wof:name":"Andrew Formica",
    "wof:placetype":"venue"
},
  "geometry": {"coordinates":[-80.27758900000001,39.300034],"type":"Point"}
}