{
  "type": "Feature",
  "properties": {
    "iso:country":"US",
    "sg:address":"1 Rainell Dr",
    "sg:city":"Huntington",
    "sg:classifiers":[
        {
            "category":"Building & Trades",
            "subcategory":"Construction",
            "type":"Services"
        }
    ],
    "sg:phone":"+1 304 697 8238",
    "sg:postcode":"25704",
    "sg:province":"WV",
    "sg:tags":[
        "general",
        "contractor"
    ],
    "wof:name":"M and J Construction",
    "wof:placetype":"venue"
},
  "geometry": {"coordinates":[-82.484212,38.334168],"type":"Point"}
}