{
  "type": "Feature",
  "properties": {
    "iso:country":"US",
    "sg:address":"2844 Ritter Dr",
    "sg:city":"Shady Spring",
    "sg:classifiers":[
        {
            "category":"Real Estate",
            "subcategory":"Real Estate Agent",
            "type":"Services"
        }
    ],
    "sg:phone":"+1 304 763 4844",
    "sg:postcode":"25918",
    "sg:province":"WV",
    "wof:name":"Beckley Homes LLC",
    "wof:placetype":"venue"
},
  "geometry": {"coordinates":[-81.098682,37.711851],"type":"Point"}
}