{
  "type": "Feature",
  "properties": {
    "addr:full":"30 Green St Piedmont WV 26750",
    "addr:housenumber":"30",
    "addr:postcode":"26750",
    "addr:street":"Green St",
    "iso:country":"US",
    "sg:address":"30 Green St",
    "sg:city":"Piedmont",
    "sg:classifiers":[
        {
            "category":"Personal",
            "subcategory":"Beauty Salon",
            "type":"Services"
        }
    ],
    "sg:phone":"+1 304 355 8900",
    "sg:postcode":"26750",
    "sg:province":"WV",
    "wof:name":"Judy's",
    "wof:placetype":"venue"
},
  "geometry": {"coordinates":[-79.047343,39.481625],"type":"Point"}
}