{
  "type": "Feature",
  "properties": {
    "iso:country":"US",
    "sg:address":"8200 Maccorkle Ave",
    "sg:city":"Charleston",
    "sg:classifiers":[
        {
            "category":"Restaurant",
            "type":"Food & Drink"
        }
    ],
    "sg:phone":"+1 304 949 1797",
    "sg:postcode":"25315",
    "sg:province":"WV",
    "wof:name":"Pizza Express",
    "wof:placetype":"venue"
},
  "geometry": {"coordinates":[-81.572473,38.253598],"type":"Point"}
}