{
  "type": "Feature",
  "properties": {
    "iso:country":"US",
    "sg:address":"401 Rockdale Rd",
    "sg:city":"Follansbee",
    "sg:classifiers":[
        {
            "category":"Real Estate",
            "subcategory":"Real Estate Operator",
            "type":"Services"
        }
    ],
    "sg:phone":"+1 304 527 2090",
    "sg:postcode":"26037",
    "sg:province":"WV",
    "sg:tags":[
        "apartment"
    ],
    "wof:name":"Rockdale Village Apartments",
    "wof:placetype":"venue"
},
  "geometry": {"coordinates":[-80.576922,40.315253],"type":"Point"}
}