{
  "type": "Feature",
  "properties": {
    "iso:country":"US",
    "sg:address":"2620 Fairmont Ave",
    "sg:city":"Fairmont",
    "sg:classifiers":[
        {
            "category":"Real Estate",
            "subcategory":"Real Estate Agent",
            "type":"Services"
        },
        {
            "category":"Real Estate",
            "subcategory":"Real Estate Operator",
            "type":"Services"
        }
    ],
    "sg:phone":"+1 304 292 9600",
    "sg:postcode":"26554",
    "sg:province":"WV",
    "sg:tags":[
        "apartment"
    ],
    "wof:name":"Kingdom Properties LLC",
    "wof:placetype":"venue"
},
  "geometry": {"coordinates":[-80.17524,39.450411],"type":"Point"}
}