{
  "type": "Feature",
  "properties": {
    "iso:country":"US",
    "sg:address":"252 Delta Rd 4",
    "sg:city":"Cameron",
    "sg:classifiers":[
        {
            "category":"Farming",
            "subcategory":"Livestock Farm",
            "type":"Manufacturing & Wholesale Goods"
        }
    ],
    "sg:phone":"+1 304 686 2850",
    "sg:postcode":"26003",
    "sg:province":"WV",
    "sg:tags":[
        "equine"
    ],
    "wof:name":"3d Ranch",
    "wof:placetype":"venue"
},
  "geometry": {"coordinates":[-80.68150199999999,40.023196],"type":"Point"}
}