{
  "type": "Feature",
  "properties": {
    "iso:country":"US",
    "sg:address":"2349 Washington St",
    "sg:city":"Bluefield",
    "sg:classifiers":[
        {
            "category":"Professional",
            "subcategory":"Accounting & Tax Preparation",
            "type":"Services"
        }
    ],
    "sg:phone":"+1 304 327 2453",
    "sg:postcode":"24701",
    "sg:province":"WV",
    "sg:tags":[
        "accountant"
    ],
    "wof:name":"Burnette & Burnette",
    "wof:placetype":"venue"
},
  "geometry": {"coordinates":[-81.214332,37.251119],"type":"Point"}
}