{
  "type": "Feature",
  "properties": {
    "addr:full":"217 Austin Ave Clarksburg WV 26301",
    "addr:housenumber":"217",
    "addr:postcode":"26301",
    "addr:street":"Austin Ave",
    "iso:country":"US",
    "sg:address":"217 Austin Ave",
    "sg:city":"Clarksburg",
    "sg:classifiers":[
        {
            "category":"Professional",
            "subcategory":"Advertising",
            "type":"Services"
        }
    ],
    "sg:phone":"+1 304 622 7594",
    "sg:postcode":"26301",
    "sg:province":"WV",
    "sg:tags":[
        "outdoor"
    ],
    "wof:name":"Signups",
    "wof:placetype":"venue"
},
  "geometry": {"coordinates":[-80.330516,39.270917],"type":"Point"}
}