{
  "type": "Feature",
  "properties": {
    "addr:full":"5 N Kanawha St Buckhannon WV 26201",
    "addr:housenumber":"5",
    "addr:postcode":"26201",
    "addr:street":"N Kanawha St",
    "iso:country":"US",
    "sg:address":"5 N Kanawha St",
    "sg:city":"Buckhannon",
    "sg:classifiers":[
        {
            "category":"Real Estate",
            "subcategory":"Real Estate Agent",
            "type":"Services"
        }
    ],
    "sg:phone":"+1 304 472 5622",
    "sg:postcode":"26201",
    "sg:province":"WV",
    "wof:name":"Robert L Manley Real Estate",
    "wof:placetype":"venue"
},
  "geometry": {"coordinates":[-80.230591,38.994309],"type":"Point"}
}