{
  "type": "Feature",
  "properties": {
    "addr:full":"1105 Bridge Rd Charleston WV 25314",
    "addr:housenumber":"1105",
    "addr:postcode":"25314",
    "addr:street":"Bridge Rd",
    "iso:country":"US",
    "sg:address":"1105 Bridge Rd",
    "sg:city":"Charleston",
    "sg:classifiers":[
        {
            "category":"Health Services",
            "subcategory":"Chiropractor",
            "type":"Services"
        }
    ],
    "sg:phone":"+1 304 342 8800",
    "sg:postcode":"25314",
    "sg:province":"WV",
    "wof:name":"South Hills Chiropractic Inc",
    "wof:placetype":"venue"
},
  "geometry": {"coordinates":[-81.645352,38.339667],"type":"Point"}
}