{
  "type": "Feature",
  "properties": {
    "addr:full":"312 Brooke Ave Morgantown WV 26505",
    "addr:housenumber":"312",
    "addr:postcode":"26505",
    "addr:street":"Brooke Ave",
    "iso:country":"US",
    "sg:address":"312 Brooke Ave",
    "sg:city":"Morgantown",
    "sg:classifiers":[
        {
            "category":"Personal",
            "type":"Services"
        }
    ],
    "sg:phone":"+1 304 284 0479",
    "sg:postcode":"26505",
    "sg:province":"WV",
    "wof:name":"Daniel House Inc",
    "wof:placetype":"venue"
},
  "geometry": {"coordinates":[-79.921088,39.621272],"type":"Point"}
}