{
  "type": "Feature",
  "properties": {
    "iso:country":"US",
    "sg:address":"406 Market St",
    "sg:city":"Hamlin",
    "sg:classifiers":[
        {
            "category":"Education",
            "subcategory":"College",
            "type":"Public Place"
        }
    ],
    "sg:phone":"+1 304 824 7911",
    "sg:postcode":"25523",
    "sg:province":"WV",
    "sg:tags":[
        "academic",
        "school"
    ],
    "wof:name":"West Virginia University Ext",
    "wof:placetype":"venue"
},
  "geometry": {"coordinates":[-82.104732,38.27998],"type":"Point"}
}