{
  "type": "Feature",
  "properties": {
    "addr:full":"5700 Maccorkle Ave SE Charleston WV 25304",
    "addr:housenumber":"5700",
    "addr:postcode":"25304",
    "addr:street":"Maccorkle Ave Se",
    "iso:country":"US",
    "sg:address":"5700 Maccorkle Ave SE",
    "sg:city":"Charleston",
    "sg:classifiers":[
        {
            "category":"Shopping",
            "subcategory":"Department Store",
            "type":"Retail Goods"
        }
    ],
    "sg:phone":"+1 304 414 2238",
    "sg:postcode":"25304",
    "sg:province":"WV",
    "wof:name":"Charleston Department Store",
    "wof:placetype":"venue"
},
  "geometry": {"coordinates":[-81.56682600000001,38.312842],"type":"Point"}
}