{
  "type": "Feature",
  "properties": {
    "iso:country":"US",
    "sg:address":"116 E Circle Dr",
    "sg:city":"Weirton",
    "sg:classifiers":[
        {
            "category":"Manufacturing",
            "subcategory":"Signs",
            "type":"Manufacturing & Wholesale Goods"
        }
    ],
    "sg:phone":"+1 304 723 4241",
    "sg:postcode":"26062",
    "sg:province":"WV",
    "sg:tags":[
        "advertising",
        "specialty"
    ],
    "wof:name":"Manny & Associates",
    "wof:placetype":"venue"
},
  "geometry": {"coordinates":[-80.51956800000001,40.413244],"type":"Point"}
}