{
  "type": "Feature",
  "properties": {
    "iso:country":"US",
    "sg:address":"2019 Washington St E",
    "sg:city":"Charleston",
    "sg:classifiers":[
        {
            "category":"Government",
            "subcategory":"Office",
            "type":"Public Place"
        }
    ],
    "sg:phone":"+1 304 558 2306",
    "sg:postcode":"25311",
    "sg:province":"WV",
    "sg:tags":[
        "administrative"
    ],
    "wof:name":"Administration West VA Dept",
    "wof:placetype":"venue"
},
  "geometry": {"coordinates":[-81.609829,38.337104],"type":"Point"}
}