{
  "type": "Feature",
  "properties": {
    "addr:full":"934 Little Coal River Alum Creek WV 25003",
    "addr:housenumber":"934",
    "addr:postcode":"25003",
    "addr:street":"Little Coal",
    "iso:country":"US",
    "sg:address":"934 Little Coal River",
    "sg:city":"Alum Creek",
    "sg:classifiers":[
        {
            "category":"Professional",
            "subcategory":"Testing Lab",
            "type":"Services"
        }
    ],
    "sg:phone":"+1 304 756 3171",
    "sg:postcode":"25003",
    "sg:province":"WV",
    "sg:tags":[
        "laboratory"
    ],
    "wof:name":"Southern Hydrocarbon Corp",
    "wof:placetype":"venue"
},
  "geometry": {"coordinates":[-81.804728,38.260102],"type":"Point"}
}