{
  "type": "Feature",
  "properties": {
    "addr:full":"688 Gordon Dr Charleston WV 25314",
    "addr:housenumber":"688",
    "addr:postcode":"25314",
    "addr:street":"Gordon Dr",
    "iso:country":"US",
    "sg:address":"688 Gordon Dr",
    "sg:city":"Charleston",
    "sg:classifiers":[
        {
            "category":"Food & Beverages",
            "subcategory":"Specialty",
            "type":"Retail Goods"
        }
    ],
    "sg:phone":"+1 304 342 1234",
    "sg:postcode":"25314",
    "sg:province":"WV",
    "sg:tags":[
        "herb"
    ],
    "wof:name":"Herbal World",
    "wof:placetype":"venue"
},
  "geometry": {"coordinates":[-81.66231399999999,38.350777],"type":"Point"}
}