{
  "type": "Feature",
  "properties": {
    "addr:full":"957 Jefferson Ave Huntington WV 25704",
    "addr:housenumber":"957",
    "addr:postcode":"25704",
    "addr:street":"Jefferson Ave",
    "iso:country":"US",
    "sg:address":"957 Jefferson Ave",
    "sg:city":"Huntington",
    "sg:classifiers":[
        {
            "category":"Building & Trades",
            "subcategory":"Plumbing",
            "type":"Services"
        }
    ],
    "sg:phone":"+1 304 525 8271",
    "sg:postcode":"25704",
    "sg:province":"WV",
    "sg:tags":[
        "sheet",
        "work",
        "metal",
        "contractor"
    ],
    "wof:name":"P & G Sheet Metal Inc",
    "wof:placetype":"venue"
},
  "geometry": {"coordinates":[-82.47160599999999,38.412282],"type":"Point"}
}