{
  "type": "Feature",
  "properties": {
    "iso:country":"US",
    "sg:address":"122 S High St",
    "sg:city":"Morgantown",
    "sg:classifiers":[
        {
            "category":"Real Estate",
            "subcategory":"Real Estate Agent",
            "type":"Services"
        }
    ],
    "sg:phone":"+1 304 284 8030",
    "sg:postcode":"26501",
    "sg:province":"WV",
    "wof:name":"Waterfront Place",
    "wof:placetype":"venue"
},
  "geometry": {"coordinates":[-79.959839,39.625344],"type":"Point"}
}