{
  "type": "Feature",
  "properties": {
    "addr:full":"206 Cedar Cir Scott Depot WV 25560",
    "addr:housenumber":"206",
    "addr:postcode":"25560",
    "addr:street":"Cedar Cir",
    "iso:country":"US",
    "sg:address":"206 Cedar Cir",
    "sg:city":"Scott Depot",
    "sg:classifiers":[
        {
            "category":"Autos & Motor Vehicles",
            "subcategory":"Recreational Vehicle Sales",
            "type":"Retail Goods"
        }
    ],
    "sg:phone":"+1 304 755 0600",
    "sg:postcode":"25560",
    "sg:province":"WV",
    "sg:tags":[
        "mfg"
    ],
    "wof:name":"Mount Top & Truck",
    "wof:placetype":"venue"
},
  "geometry": {"coordinates":[-81.853061,38.441249],"type":"Point"}
}