{
  "type": "Feature",
  "properties": {
    "addr:full":"900 Keypoint Dr Summersville WV 26651",
    "addr:housenumber":"900",
    "addr:postcode":"26651",
    "addr:street":"Keypoint Dr",
    "iso:country":"US",
    "sg:address":"900 Keypoint Dr",
    "sg:city":"Summersville",
    "sg:classifiers":[
        {
            "category":"Mining & Drilling",
            "type":"Manufacturing & Wholesale Goods"
        }
    ],
    "sg:phone":"+1 304 872 6822",
    "sg:postcode":"26651",
    "sg:province":"WV",
    "sg:tags":[
        "bituminous",
        "surface"
    ],
    "wof:name":"Missouri Creek Coal Company",
    "wof:placetype":"venue"
},
  "geometry": {"coordinates":[-80.844995,38.268274],"type":"Point"}
}