{
  "type": "Feature",
  "properties": {
    "addr:full":"3915 Washington St W Charleston WV 25312",
    "addr:housenumber":"3915",
    "addr:postcode":"25312",
    "addr:street":"Washington St W",
    "iso:country":"US",
    "sg:address":"3915 Washington St W",
    "sg:city":"Charleston",
    "sg:classifiers":[
        {
            "category":"Recreation",
            "subcategory":"Marina",
            "type":"Entertainment"
        }
    ],
    "sg:phone":"+1 304 746 4495",
    "sg:postcode":"25312",
    "sg:province":"WV",
    "wof:name":"Pier 54 Marina",
    "wof:placetype":"venue"
},
  "geometry": {"coordinates":[-81.694593,38.376509],"type":"Point"}
}