{
  "type": "Feature",
  "properties": {
    "iso:country":"US",
    "sg:address":"5104 Noyes Ave",
    "sg:city":"Charleston",
    "sg:classifiers":[
        {
            "category":"Personal",
            "subcategory":"Beauty Salon",
            "type":"Services"
        }
    ],
    "sg:phone":"+1 304 746 0666",
    "sg:postcode":"25304",
    "sg:province":"WV",
    "sg:tags":[
        "shop"
    ],
    "wof:name":"CAM Tran",
    "wof:placetype":"venue"
},
  "geometry": {"coordinates":[-81.574173,38.318453],"type":"Point"}
}