{
  "type": "Feature",
  "properties": {
    "iso:country":"US",
    "sg:address":"3304 Grand Central Ave",
    "sg:city":"Parkersburg",
    "sg:classifiers":[
        {
            "category":"Personal",
            "subcategory":"Beauty Salon",
            "type":"Services"
        }
    ],
    "sg:phone":"+1 304 295 9161",
    "sg:postcode":"26105",
    "sg:province":"WV",
    "sg:tags":[
        "shop"
    ],
    "wof:name":"My Place Family Hair Styling",
    "wof:placetype":"venue"
},
  "geometry": {"coordinates":[-81.547741,39.32829],"type":"Point"}
}