{
  "type": "Feature",
  "properties": {
    "iso:country":"US",
    "sg:address":"1750 Fairmont Ave",
    "sg:city":"Fairmont",
    "sg:classifiers":[
        {
            "category":"Food & Beverages",
            "subcategory":"Groceries & Convenience Stores",
            "type":"Retail Goods"
        }
    ],
    "sg:phone":"+1 304 366 1391",
    "sg:postcode":"26554",
    "sg:province":"WV",
    "wof:name":"Highlights Lounge",
    "wof:placetype":"venue"
},
  "geometry": {"coordinates":[-80.174441,39.450802],"type":"Point"}
}