{
  "type": "Feature",
  "properties": {
    "iso:country":"US",
    "sg:address":"112 Miller St",
    "sg:city":"Beckley",
    "sg:classifiers":[
        {
            "category":"Organizations",
            "subcategory":"Religious Organization",
            "type":"Services"
        }
    ],
    "sg:phone":"+1 304 253 1728",
    "sg:postcode":"25801",
    "sg:province":"WV",
    "sg:tags":[
        "clergy"
    ],
    "wof:name":"Gladys Bragg",
    "wof:placetype":"venue"
},
  "geometry": {"coordinates":[-81.174745,37.769332],"type":"Point"}
}