{
  "type": "Feature",
  "properties": {
    "iso:country":"US",
    "sg:address":"4925 Tabler Station Rd",
    "sg:city":"Inwood",
    "sg:classifiers":[
        {
            "category":"Professional",
            "subcategory":"Management & Consulting",
            "type":"Services"
        }
    ],
    "sg:phone":"+1 304 262 0101",
    "sg:postcode":"25428",
    "sg:province":"WV",
    "sg:tags":[
        "consultant"
    ],
    "wof:name":"Orgill Distribution Center",
    "wof:placetype":"venue"
},
  "geometry": {"coordinates":[-78.022094,39.405542],"type":"Point"}
}