{
  "type": "Feature",
  "properties": {
    "iso:country":"US",
    "sg:address":"119 Appalachian Dr",
    "sg:city":"Beckley",
    "sg:classifiers":[
        {
            "category":"Professional",
            "subcategory":"Management & Consulting",
            "type":"Services"
        }
    ],
    "sg:phone":"+1 304 929 2013",
    "sg:postcode":"25801",
    "sg:province":"WV",
    "sg:tags":[
        "fuel"
    ],
    "wof:name":"Employee Management Solutions",
    "wof:placetype":"venue"
},
  "geometry": {"coordinates":[-81.185176,37.817973],"type":"Point"}
}