{
  "type": "Feature",
  "properties": {
    "iso:country":"US",
    "sg:address":"1425 Jackson Ave",
    "sg:city":"Huntington",
    "sg:classifiers":[
        {
            "category":"Wholesale",
            "subcategory":"Groceries",
            "type":"Manufacturing & Wholesale Goods"
        }
    ],
    "sg:phone":"+1 304 523 6731",
    "sg:postcode":"25704",
    "sg:province":"WV",
    "sg:tags":[
        "food",
        "product"
    ],
    "wof:name":"Frito-Lay Inc",
    "wof:placetype":"venue"
},
  "geometry": {"coordinates":[-82.479,38.406872],"type":"Point"}
}