{
  "type": "Feature",
  "properties": {
    "iso:country":"US",
    "sg:address":"40 Twp Rd 1348",
    "sg:city":"Chesapeake",
    "sg:classifiers":[
        {
            "category":"Manufacturing",
            "subcategory":"Motor Vehicles & Parts",
            "type":"Manufacturing & Wholesale Goods"
        }
    ],
    "sg:phone":"+1 740 867 8787",
    "sg:postcode":"45619",
    "sg:province":"OH",
    "sg:tags":[
        "mfg"
    ],
    "wof:name":"Bryan Black",
    "wof:placetype":"venue"
},
  "geometry": {"coordinates":[-82.431776,38.462911],"type":"Point"}
}