{
  "type": "Feature",
  "properties": {
    "iso:country":"US",
    "sg:address":"73 Dawn St",
    "sg:city":"Wellsburg",
    "sg:classifiers":[
        {
            "category":"Shopping",
            "subcategory":"Florist",
            "type":"Retail Goods"
        }
    ],
    "sg:phone":"+1 304 737 0621",
    "sg:postcode":"26003",
    "sg:province":"WV",
    "wof:name":"Wilkin Flower Shop",
    "wof:placetype":"venue"
},
  "geometry": {"coordinates":[-80.683302,40.088847],"type":"Point"}
}