{
  "type": "Feature",
  "properties": {
    "addr:full":"1327 Market St Parkersburg WV 26101",
    "addr:housenumber":"1327",
    "addr:postcode":"26101",
    "addr:street":"Market St",
    "iso:country":"US",
    "sg:address":"1327 Market St",
    "sg:city":"Parkersburg",
    "sg:classifiers":[
        {
            "category":"Professional",
            "subcategory":"Detective & Security Services",
            "type":"Services"
        },
        {
            "category":"Insurance",
            "subcategory":"Hazard Insurance",
            "type":"Services"
        }
    ],
    "sg:phone":"+1 304 428 2666",
    "sg:postcode":"26101",
    "sg:province":"WV",
    "sg:tags":[
        "car",
        "bond"
    ],
    "wof:name":"Atkinson Bonding",
    "wof:placetype":"venue"
},
  "geometry": {"coordinates":[-81.55183100000001,39.273569],"type":"Point"}
}