{
  "type": "Feature",
  "properties": {
    "addr:full":"711 Indiana Ave Charleston WV 25302",
    "addr:housenumber":"711",
    "addr:postcode":"25302",
    "addr:street":"Indiana Ave",
    "iso:country":"US",
    "sg:address":"711 Indiana Ave",
    "sg:city":"Charleston",
    "sg:classifiers":[
        {
            "category":"Shopping",
            "subcategory":"Stationery & Office Supplies",
            "type":"Retail Goods"
        }
    ],
    "sg:phone":"+1 304 343 7551",
    "sg:postcode":"25302",
    "sg:province":"WV",
    "wof:name":"Capitol Business Interiors",
    "wof:placetype":"venue"
},
  "geometry": {"coordinates":[-81.639008,38.361477],"type":"Point"}
}