{
  "type": "Feature",
  "properties": {
    "iso:country":"US",
    "sg:address":"8 Cherry St",
    "sg:city":"Richwood",
    "sg:classifiers":[
        {
            "category":"Organizations",
            "subcategory":"Community Association",
            "type":"Services"
        }
    ],
    "sg:phone":"+1 304 846 9129",
    "sg:postcode":"26261",
    "sg:province":"WV",
    "sg:tags":[
        "fraternal"
    ],
    "wof:name":"Knights Of Columbus",
    "wof:placetype":"venue"
},
  "geometry": {"coordinates":[-80.525795,38.230467],"type":"Point"}
}