{
  "type": "Feature",
  "properties": {
    "iso:country":"US",
    "sg:address":"224 Kanawha Blvd E",
    "sg:city":"Charleston",
    "sg:classifiers":[
        {
            "category":"Retail",
            "subcategory":"Car Wash",
            "type":"Services"
        }
    ],
    "sg:phone":"+1 304 344 3650",
    "sg:postcode":"25301",
    "sg:province":"WV",
    "sg:tags":[
        "polishing",
        "washing"
    ],
    "wof:name":"Center Of Town Car Wash",
    "wof:placetype":"venue"
},
  "geometry": {"coordinates":[-81.64152300000001,38.35243],"type":"Point"}
}