{
  "type": "Feature",
  "properties": {
    "iso:country":"US",
    "sg:address":"365 Hill Valley Dr",
    "sg:city":"Julian",
    "sg:classifiers":[
        {
            "category":"Shopping",
            "subcategory":"Computers & Home Electronics",
            "type":"Retail Goods"
        }
    ],
    "sg:phone":"+1 304 369 5765",
    "sg:postcode":"25529",
    "sg:province":"WV",
    "wof:name":"Centrifuge Computers",
    "wof:placetype":"venue"
},
  "geometry": {"coordinates":[-81.858108,38.16099],"type":"Point"}
}