{
  "type": "Feature",
  "properties": {
    "iso:country":"US",
    "sg:address":"290 E Main St",
    "sg:city":"Milton",
    "sg:classifiers":[
        {
            "category":"Shopping",
            "subcategory":"Discount & Variety Stores",
            "type":"Retail Goods"
        }
    ],
    "sg:phone":"+1 304 743 4938",
    "sg:postcode":"25541",
    "sg:province":"WV",
    "wof:name":"Family Dollar Stores",
    "wof:placetype":"venue"
},
  "geometry": {"coordinates":[-82.124009,38.434126],"type":"Point"}
}