{
  "type": "Feature",
  "properties": {
    "addr:full":"257 State Rte 2 New Martinsville WV 26155",
    "addr:housenumber":"257",
    "addr:postcode":"26155",
    "addr:street":"State Rte 2 New",
    "iso:country":"US",
    "sg:address":"257 State Rte 2",
    "sg:city":"New Martinsville",
    "sg:classifiers":[
        {
            "category":"Social Services",
            "subcategory":"Job Training",
            "type":"Services"
        }
    ],
    "sg:phone":"+1 304 455 6184",
    "sg:postcode":"26155",
    "sg:province":"WV",
    "sg:tags":[
        "career",
        "counseling",
        "vocational"
    ],
    "wof:name":"Work Force Career Ctr",
    "wof:placetype":"venue"
},
  "geometry": {"coordinates":[-80.857395,39.674201],"type":"Point"}
}