{
  "type": "Feature",
  "properties": {
    "iso:country":"US",
    "sg:address":"1682 11th Ave",
    "sg:city":"Huntington",
    "sg:classifiers":[
        {
            "category":"Education",
            "subcategory":"Special Training",
            "type":"Public Place"
        }
    ],
    "sg:phone":"+1 304 697 5883",
    "sg:postcode":"25701",
    "sg:province":"WV",
    "wof:name":"Simms Headstart",
    "wof:placetype":"venue"
},
  "geometry": {"coordinates":[-82.425539,38.413879],"type":"Point"}
}