{
  "type": "Feature",
  "properties": {
    "iso:country":"US",
    "sg:address":"8 Ryan Dr",
    "sg:city":"Charleston",
    "sg:classifiers":[
        {
            "category":"Arts & Performance",
            "subcategory":"Theater",
            "type":"Entertainment"
        }
    ],
    "sg:phone":"+1 304 346 6740",
    "sg:postcode":"25311",
    "sg:province":"WV",
    "sg:tags":[
        "entertainer"
    ],
    "sg:website":"www.russmccubbin.com",
    "wof:name":"Russ Mc Cubbin",
    "wof:placetype":"venue"
},
  "geometry": {"coordinates":[-81.579745,38.344956],"type":"Point"}
}