{
  "type": "Feature",
  "properties": {
    "addr:full":"147 Manor Dr Martinsburg WV 25403",
    "addr:housenumber":"147",
    "addr:postcode":"25403",
    "addr:street":"Manor Dr",
    "iso:country":"US",
    "sg:address":"147 Manor Dr",
    "sg:city":"Martinsburg",
    "sg:classifiers":[
        {
            "category":"Shopping",
            "type":"Retail Goods"
        }
    ],
    "sg:phone":"+1 304 263 9595",
    "sg:postcode":"25403",
    "sg:province":"WV",
    "sg:tags":[
        "equipment",
        "medical"
    ],
    "wof:name":"Rotech",
    "wof:placetype":"venue"
},
  "geometry": {"coordinates":[-78.006224,39.380023],"type":"Point"}
}