{
  "type": "Feature",
  "properties": {
    "iso:country":"US",
    "sg:address":"4910 Church Dr",
    "sg:city":"Charleston",
    "sg:classifiers":[
        {
            "category":"Wholesale",
            "subcategory":"Motor Vehicles",
            "type":"Manufacturing & Wholesale Goods"
        }
    ],
    "sg:phone":"+1 304 925 6300",
    "sg:postcode":"25306",
    "sg:province":"WV",
    "sg:tags":[
        "body",
        "equipment",
        "truck"
    ],
    "wof:name":"Mountaineer Truck Equipment",
    "wof:placetype":"venue"
},
  "geometry": {"coordinates":[-81.563802,38.287672],"type":"Point"}
}