{
  "type": "Feature",
  "properties": {
    "iso:country":"US",
    "sg:address":"600 Lower Sandlick Rd",
    "sg:city":"Beckley",
    "sg:classifiers":[
        {
            "category":"Professional",
            "subcategory":"Engineering",
            "type":"Services"
        }
    ],
    "sg:phone":"+1 304 934 5850",
    "sg:postcode":"25801",
    "sg:province":"WV",
    "sg:tags":[
        "engineer"
    ],
    "wof:name":"Mining Consulting Co",
    "wof:placetype":"venue"
},
  "geometry": {"coordinates":[-81.35203300000001,37.833499],"type":"Point"}
}