{
  "type": "Feature",
  "properties": {
    "iso:country":"US",
    "sg:address":"602 Tennessee Ave",
    "sg:city":"Charleston",
    "sg:classifiers":[
        {
            "category":"Social Services",
            "type":"Services"
        }
    ],
    "sg:phone":"+1 304 345 5552",
    "sg:postcode":"25302",
    "sg:province":"WV",
    "sg:tags":[
        "senior",
        "citizen"
    ],
    "wof:name":"West Virginia Senior Sports",
    "wof:placetype":"venue"
},
  "geometry": {"coordinates":[-81.64111800000001,38.360927],"type":"Point"}
}