{
  "type": "Feature",
  "properties": {
    "addr:full":"211 N Lewis St Glenville WV 26351",
    "addr:housenumber":"211",
    "addr:postcode":"26351",
    "addr:street":"N Lewis St",
    "iso:country":"US",
    "sg:address":"211 N Lewis St",
    "sg:city":"Glenville",
    "sg:classifiers":[
        {
            "category":"Food & Beverages",
            "subcategory":"Specialty",
            "type":"Retail Goods"
        }
    ],
    "sg:phone":"+1 304 462 8157",
    "sg:postcode":"26351",
    "sg:province":"WV",
    "wof:name":"Country Life Natural Foods",
    "wof:placetype":"venue"
},
  "geometry": {"coordinates":[-80.835227,38.93649],"type":"Point"}
}