{
  "type": "Feature",
  "properties": {
    "addr:full":"58 Hunter Ln Alum Creek WV 25003",
    "addr:housenumber":"58",
    "addr:postcode":"25003",
    "addr:street":"Hunter Ln",
    "iso:country":"US",
    "sg:address":"58 Hunter Ln",
    "sg:city":"Alum Creek",
    "sg:classifiers":[
        {
            "category":"Retail",
            "subcategory":"Repair Shop",
            "type":"Services"
        }
    ],
    "sg:phone":"+1 304 756 3521",
    "sg:postcode":"25003",
    "sg:province":"WV",
    "wof:name":"Woods Custom Gunsmithing",
    "wof:placetype":"venue"
},
  "geometry": {"coordinates":[-81.80085800000001,38.27656],"type":"Point"}
}