{
  "type": "Feature",
  "properties": {
    "addr:full":"265 Prospect St Morgantown WV 26505",
    "addr:housenumber":"265",
    "addr:postcode":"26505",
    "addr:street":"Prospect St",
    "iso:country":"US",
    "sg:address":"265 Prospect St",
    "sg:city":"Morgantown",
    "sg:classifiers":[
        {
            "category":"Organizations",
            "subcategory":"Community Association",
            "type":"Services"
        }
    ],
    "sg:phone":"+1 304 292 9214",
    "sg:postcode":"26505",
    "sg:province":"WV",
    "wof:name":"Kappa Kappa Gamma",
    "wof:placetype":"venue"
},
  "geometry": {"coordinates":[-79.95200199999999,39.632569],"type":"Point"}
}