{
  "type": "Feature",
  "properties": {
    "iso:country":"US",
    "sg:address":"2096 National Rd",
    "sg:city":"Wheeling",
    "sg:classifiers":[
        {
            "category":"Autos & Motor Vehicles",
            "subcategory":"Fuel & Gas Station",
            "type":"Retail Goods"
        },
        {
            "category":"Retail",
            "subcategory":"Auto Repair",
            "type":"Services"
        }
    ],
    "sg:phone":"+1 304 242 6100",
    "sg:postcode":"26003",
    "sg:province":"WV",
    "sg:tags":[
        "station",
        "oil",
        "gasoline",
        "automotive",
        "general"
    ],
    "wof:name":"Wharton's Amoco",
    "wof:placetype":"venue"
},
  "geometry": {"coordinates":[-80.662755,40.047719],"type":"Point"}
}