{
  "type": "Feature",
  "properties": {
    "iso:country":"US",
    "sg:address":"963 Betty Zane Rd",
    "sg:city":"Wheeling",
    "sg:classifiers":[
        {
            "category":"Building & Trades",
            "subcategory":"Construction",
            "type":"Services"
        }
    ],
    "sg:phone":"+1 304 277 1644",
    "sg:postcode":"26003",
    "sg:province":"WV",
    "sg:tags":[
        "house"
    ],
    "wof:name":"Betty Zane Services Ltd",
    "wof:placetype":"venue"
},
  "geometry": {"coordinates":[-80.653935,40.139931],"type":"Point"}
}