{
  "type": "Feature",
  "properties": {
    "iso:country":"US",
    "sg:address":"819 B St",
    "sg:city":"Saint Albans",
    "sg:classifiers":[
        {
            "category":"Organizations",
            "subcategory":"Religious Organization",
            "type":"Services"
        }
    ],
    "sg:phone":"+1 304 727 1742",
    "sg:postcode":"25177",
    "sg:province":"WV",
    "wof:name":"St Paul Ministry Baptst Church",
    "wof:placetype":"venue"
},
  "geometry": {"coordinates":[-81.838472,38.384499],"type":"Point"}
}