{
  "type": "Feature",
  "properties": {
    "iso:country":"US",
    "sg:address":"397 Rensford Star Rte",
    "sg:city":"Charleston",
    "sg:classifiers":[
        {
            "category":"Autos & Motor Vehicles",
            "subcategory":"Motorcycle Sales",
            "type":"Retail Goods"
        }
    ],
    "sg:phone":"+1 304 925 6071",
    "sg:postcode":"25306",
    "sg:province":"WV",
    "wof:name":"D & L Motorcycle Salvage",
    "wof:placetype":"venue"
},
  "geometry": {"coordinates":[-81.531228,38.316713],"type":"Point"}
}