{
  "type": "Feature",
  "properties": {
    "addr:full":"22 Casdorph Ln Charleston WV 25312",
    "addr:housenumber":"22",
    "addr:postcode":"25312",
    "addr:street":"Casdorph Ln",
    "iso:country":"US",
    "sg:address":"22 Casdorph Ln",
    "sg:city":"Charleston",
    "sg:classifiers":[
        {
            "category":"Building & Trades",
            "subcategory":"Plumbing",
            "type":"Services"
        }
    ],
    "sg:phone":"+1 304 342 2502",
    "sg:postcode":"25312",
    "sg:province":"WV",
    "sg:tags":[
        "excavation",
        "contractor"
    ],
    "wof:name":"Kanawha Property Mgt Excvtg",
    "wof:placetype":"venue"
},
  "geometry": {"coordinates":[-81.682367,38.416802],"type":"Point"}
}