{
  "type": "Feature",
  "properties": {
    "iso:country":"US",
    "sg:address":"3 Mockingbird Dr",
    "sg:city":"Milton",
    "sg:classifiers":[
        {
            "category":"Professional",
            "subcategory":"Credit Reporting & Collection",
            "type":"Services"
        }
    ],
    "sg:phone":"+1 304 743 3666",
    "sg:postcode":"25541",
    "sg:province":"WV",
    "wof:name":"In Eagle Account Recovery",
    "wof:placetype":"venue"
},
  "geometry": {"coordinates":[-82.15313399999999,38.437431],"type":"Point"}
}