{
  "type": "Feature",
  "properties": {
    "addr:full":"39 S Main St Petersburg WV 26847",
    "addr:housenumber":"39",
    "addr:postcode":"26847",
    "addr:street":"S Main",
    "iso:country":"US",
    "sg:address":"39 S Main St",
    "sg:city":"Petersburg",
    "sg:classifiers":[
        {
            "category":"Professional",
            "subcategory":"Management & Consulting",
            "type":"Services"
        }
    ],
    "sg:phone":"+1 304 257 4747",
    "sg:postcode":"26847",
    "sg:province":"WV",
    "wof:name":"Tyson A Michael Office",
    "wof:placetype":"venue"
},
  "geometry": {"coordinates":[-79.12447,38.989134],"type":"Point"}
}