{
  "type": "Feature",
  "properties": {
    "iso:country":"US",
    "sg:address":"910 E Park Ave",
    "sg:city":"Fairmont",
    "sg:classifiers":[
        {
            "category":"Professional",
            "subcategory":"Computer Services",
            "type":"Services"
        }
    ],
    "sg:phone":"+1 304 363 2758",
    "sg:postcode":"26554",
    "sg:province":"WV",
    "sg:tags":[
        "information",
        "technology",
        "database"
    ],
    "wof:name":"N J Associates",
    "wof:placetype":"venue"
},
  "geometry": {"coordinates":[-80.125941,39.48186],"type":"Point"}
}