{
  "type": "Feature",
  "properties": {
    "iso:country":"US",
    "sg:address":"6 Ave C",
    "sg:city":"Madison",
    "sg:classifiers":[
        {
            "category":"Cinema",
            "subcategory":"Movie Rental",
            "type":"Entertainment"
        }
    ],
    "sg:phone":"+1 304 369 4693",
    "sg:postcode":"25130",
    "sg:province":"WV",
    "sg:tags":[
        "leasing",
        "video",
        "disc",
        "tape"
    ],
    "wof:name":"Mom's Country Store & Kitchen",
    "wof:placetype":"venue"
},
  "geometry": {"coordinates":[-81.820756,38.067394],"type":"Point"}
}