{
  "type": "Feature",
  "properties": {
    "addr:full":"2567 University Ave Morgantown WV 26505",
    "addr:housenumber":"2567",
    "addr:postcode":"26505",
    "addr:street":"University Ave",
    "iso:country":"US",
    "sg:address":"2567 University Ave",
    "sg:city":"Morgantown",
    "sg:classifiers":[
        {
            "category":"Professional",
            "subcategory":"Advertising",
            "type":"Services"
        }
    ],
    "sg:phone":"+1 304 292 1050",
    "sg:postcode":"26505",
    "sg:province":"WV",
    "sg:tags":[
        "mailing",
        "list"
    ],
    "wof:name":"Cohen Enterprises",
    "wof:placetype":"venue"
},
  "geometry": {"coordinates":[-79.957911,39.643751],"type":"Point"}
}