{
  "type": "Feature",
  "properties": {
    "iso:country":"US",
    "sg:address":"1012 7th St",
    "sg:city":"Parkersburg",
    "sg:classifiers":[
        {
            "category":"Retail",
            "subcategory":"Car Wash",
            "type":"Services"
        }
    ],
    "sg:phone":"+1 304 428 4443",
    "sg:postcode":"26101",
    "sg:province":"WV",
    "sg:tags":[
        "automobile",
        "detail",
        "clean"
    ],
    "wof:name":"Wax Works",
    "wof:placetype":"venue"
},
  "geometry": {"coordinates":[-81.545789,39.263499],"type":"Point"}
}