{
  "type": "Feature",
  "properties": {
    "iso:country":"US",
    "sg:address":"114 Beech St",
    "sg:city":"Philippi",
    "sg:classifiers":[
        {
            "category":"Building & Trades",
            "subcategory":"Construction",
            "type":"Services"
        }
    ],
    "sg:phone":"+1 304 457 5607",
    "sg:postcode":"26416",
    "sg:province":"WV",
    "sg:tags":[
        "general",
        "contractor"
    ],
    "wof:name":"Daycon Construction",
    "wof:placetype":"venue"
},
  "geometry": {"coordinates":[-80.042367,39.158315],"type":"Point"}
}