{
  "type": "Feature",
  "properties": {
    "addr:full":"1405 E Main St Milton WV 25541",
    "addr:housenumber":"1405",
    "addr:postcode":"25541",
    "addr:street":"E Main St",
    "iso:country":"US",
    "sg:address":"1405 E Main St",
    "sg:city":"Milton",
    "sg:classifiers":[
        {
            "category":"Home & Garden",
            "subcategory":"Building Materials",
            "type":"Retail Goods"
        }
    ],
    "sg:phone":"+1 304 743 9973",
    "sg:postcode":"25541",
    "sg:province":"WV",
    "wof:name":"Builders Discount LLC",
    "wof:placetype":"venue"
},
  "geometry": {"coordinates":[-82.12273500000001,38.433998],"type":"Point"}
}