{
  "type": "Feature",
  "properties": {
    "addr:full":"1104 Main St Charleston WV 25302",
    "addr:housenumber":"1104",
    "addr:postcode":"25302",
    "addr:street":"Main St",
    "iso:country":"US",
    "sg:address":"1104 Main St",
    "sg:city":"Charleston",
    "sg:classifiers":[
        {
            "category":"Retail",
            "subcategory":"Auto Repair",
            "type":"Services"
        }
    ],
    "sg:phone":"+1 304 345 4157",
    "sg:postcode":"25302",
    "sg:province":"WV",
    "sg:tags":[
        "engine"
    ],
    "wof:name":"Headmasters",
    "wof:placetype":"venue"
},
  "geometry": {"coordinates":[-81.65902,38.366098],"type":"Point"}
}