{
  "type": "Feature",
  "properties": {
    "iso:country":"US",
    "sg:address":"3000 W Dupont Ave",
    "sg:city":"Belle",
    "sg:classifiers":[
        {
            "category":"Freight",
            "type":"Transportation"
        }
    ],
    "sg:phone":"+1 304 595 6464",
    "sg:postcode":"25015",
    "sg:province":"WV",
    "sg:tags":[
        "commercial",
        "storage"
    ],
    "wof:name":"S & B Mini Storage",
    "wof:placetype":"venue"
},
  "geometry": {"coordinates":[-81.565355,38.263783],"type":"Point"}
}