{
  "type": "Feature",
  "properties": {
    "iso:country":"US",
    "sg:address":"212 Court St",
    "sg:city":"Clarksburg",
    "sg:classifiers":[
        {
            "category":"Professional",
            "subcategory":"Accounting & Tax Preparation",
            "type":"Services"
        }
    ],
    "sg:phone":"+1 304 623 5657",
    "sg:postcode":"26301",
    "sg:province":"WV",
    "wof:name":"Larry Cann",
    "wof:placetype":"venue"
},
  "geometry": {"coordinates":[-80.339647,39.279186],"type":"Point"}
}