{
  "type": "Feature",
  "properties": {
    "iso:country":"US",
    "sg:address":"110 Woodbridge Dr",
    "sg:city":"Charleston",
    "sg:classifiers":[
        {
            "category":"Social Services",
            "type":"Services"
        }
    ],
    "sg:phone":"+1 304 342 4861",
    "sg:postcode":"25311",
    "sg:province":"WV",
    "sg:tags":[
        "vocational",
        "witness"
    ],
    "wof:name":"Patricia Mc Fann",
    "wof:placetype":"venue"
},
  "geometry": {"coordinates":[-81.582007,38.352719],"type":"Point"}
}