{
  "type": "Feature",
  "properties": {
    "iso:country":"US",
    "sg:address":"1007 Division St",
    "sg:city":"Parkersburg",
    "sg:classifiers":[
        {
            "category":"Insurance",
            "subcategory":"Insurance Agent",
            "type":"Services"
        }
    ],
    "sg:phone":"+1 304 485 4307",
    "sg:postcode":"26101",
    "sg:province":"WV",
    "wof:name":"George E Farley",
    "wof:placetype":"venue"
},
  "geometry": {"coordinates":[-81.554856,39.24901],"type":"Point"}
}