{
  "type": "Feature",
  "properties": {
    "addr:full":"62 Athens Rd Princeton WV 24740",
    "addr:housenumber":"62",
    "addr:postcode":"24740",
    "addr:street":"Athens Rd",
    "iso:country":"US",
    "sg:address":"62 Athens Rd",
    "sg:city":"Princeton",
    "sg:classifiers":[
        {
            "category":"Personal",
            "subcategory":"Beauty Salon",
            "type":"Services"
        }
    ],
    "sg:phone":"+1 304 425 7773",
    "sg:postcode":"24740",
    "sg:province":"WV",
    "sg:tags":[
        "shop"
    ],
    "wof:name":"Stunning Styles Buty Barbr Sp",
    "wof:placetype":"venue"
},
  "geometry": {"coordinates":[-81.072333,37.36949],"type":"Point"}
}