{
  "type": "Feature",
  "properties": {
    "addr:full":"410 Main St Spencer WV 25276",
    "addr:housenumber":"410",
    "addr:postcode":"25276",
    "addr:street":"Main St",
    "iso:country":"US",
    "sg:address":"410 Main St",
    "sg:city":"Spencer",
    "sg:classifiers":[
        {
            "category":"Restaurant",
            "type":"Food & Drink"
        }
    ],
    "sg:phone":"+1 304 927 1763",
    "sg:postcode":"25276",
    "sg:province":"WV",
    "sg:tags":[
        "eating"
    ],
    "wof:name":"Bee Queen",
    "wof:placetype":"venue"
},
  "geometry": {"coordinates":[-81.355099,38.80385],"type":"Point"}
}