{
  "type": "Feature",
  "properties": {
    "iso:country":"US",
    "sg:address":"104 Union St",
    "sg:city":"West Union",
    "sg:classifiers":[
        {
            "category":"Professional",
            "subcategory":"Lawyer & Legal Services",
            "type":"Services"
        }
    ],
    "sg:phone":"+1 304 873 1088",
    "sg:postcode":"26456",
    "sg:province":"WV",
    "sg:tags":[
        "attorney"
    ],
    "wof:name":"Heather Molessa",
    "wof:placetype":"venue"
},
  "geometry": {"coordinates":[-80.76792399999999,39.292928],"type":"Point"}
}