{
  "type": "Feature",
  "properties": {
    "iso:country":"US",
    "sg:address":"800 Byus Dr",
    "sg:city":"Charleston",
    "sg:classifiers":[
        {
            "category":"Mining & Drilling",
            "type":"Manufacturing & Wholesale Goods"
        }
    ],
    "sg:phone":"+1 304 346 2080",
    "sg:postcode":"25311",
    "sg:province":"WV",
    "sg:tags":[
        "oil",
        "well"
    ],
    "wof:name":"IHS Energy",
    "wof:placetype":"venue"
},
  "geometry": {"coordinates":[-81.60019200000001,38.348574],"type":"Point"}
}