{
  "type": "Feature",
  "properties": {
    "iso:country":"US",
    "sg:address":"659 Central Ave",
    "sg:city":"Barboursville",
    "sg:classifiers":[
        {
            "category":"Health Services",
            "subcategory":"Doctor",
            "type":"Services"
        }
    ],
    "sg:phone":"+1 304 736 5247",
    "sg:postcode":"25504",
    "sg:province":"WV",
    "sg:tags":[
        "medical"
    ],
    "wof:name":"Village Medical Center",
    "wof:placetype":"venue"
},
  "geometry": {"coordinates":[-82.295267,38.40889],"type":"Point"}
}