{
  "type": "Feature",
  "properties": {
    "iso:country":"US",
    "sg:address":"120 Angel Ter",
    "sg:city":"Charleston",
    "sg:classifiers":[
        {
            "category":"Building & Trades",
            "subcategory":"Plumbing",
            "type":"Services"
        }
    ],
    "sg:phone":"+1 304 344 4847",
    "sg:postcode":"25314",
    "sg:province":"WV",
    "sg:tags":[
        "plumbing",
        "contractor"
    ],
    "wof:name":"Solberg John Plumbing",
    "wof:placetype":"venue"
},
  "geometry": {"coordinates":[-81.680691,38.342107],"type":"Point"}
}