{
  "type": "Feature",
  "properties": {
    "iso:country":"US",
    "sg:address":"3884 Grand Ave",
    "sg:city":"Shadyside",
    "sg:classifiers":[
        {
            "category":"Real Estate",
            "subcategory":"Real Estate Agent",
            "type":"Services"
        }
    ],
    "sg:phone":"+1 740 676 5317",
    "sg:postcode":"43947",
    "sg:province":"OH",
    "wof:name":"Jann L Poe",
    "wof:placetype":"venue"
},
  "geometry": {"coordinates":[-80.74611899999999,39.969868],"type":"Point"}
}