{
  "type": "Feature",
  "properties": {
    "addr:full":"490 Cherry St Bluefield WV 24701",
    "addr:housenumber":"490",
    "addr:postcode":"24701",
    "addr:street":"Cherry St",
    "iso:country":"US",
    "sg:address":"490 Cherry St",
    "sg:city":"Bluefield",
    "sg:classifiers":[
        {
            "category":"Health Services",
            "subcategory":"Doctor",
            "type":"Services"
        }
    ],
    "sg:phone":"+1 304 327 2475",
    "sg:postcode":"24701",
    "sg:province":"WV",
    "sg:tags":[
        "medical"
    ],
    "wof:name":"Edward M Litz MD PC",
    "wof:placetype":"venue"
},
  "geometry": {"coordinates":[-81.23400100000001,37.256211],"type":"Point"}
}