{
  "type": "Feature",
  "properties": {
    "iso:country":"US",
    "sg:address":"601 Avery St",
    "sg:city":"Parkersburg",
    "sg:classifiers":[
        {
            "category":"Wholesale",
            "subcategory":"Electrical",
            "type":"Manufacturing & Wholesale Goods"
        }
    ],
    "sg:phone":"+1 304 485 5655",
    "sg:postcode":"26101",
    "sg:province":"WV",
    "sg:tags":[
        "control",
        "security",
        "system"
    ],
    "wof:name":"Psa Security & Investigation",
    "wof:placetype":"venue"
},
  "geometry": {"coordinates":[-81.558435,39.265405],"type":"Point"}
}