{
  "type": "Feature",
  "properties": {
    "iso:country":"US",
    "sg:address":"945 4th Ave",
    "sg:city":"Huntington",
    "sg:classifiers":[
        {
            "category":"Professional",
            "subcategory":"Printing & Photocopies",
            "type":"Services"
        }
    ],
    "sg:phone":"+1 304 522 6161",
    "sg:postcode":"25701",
    "sg:province":"WV",
    "sg:tags":[
        "duplicating",
        "copying"
    ],
    "wof:name":"Copy Shoppe",
    "wof:placetype":"venue"
},
  "geometry": {"coordinates":[-82.442797,38.420853],"type":"Point"}
}