{
  "type": "Feature",
  "properties": {
    "addr:full":"318 5th Ave SW Charleston WV 25303",
    "addr:housenumber":"318",
    "addr:postcode":"25303",
    "addr:street":"5Th Ave Sw",
    "iso:country":"US",
    "sg:address":"318 5th Ave SW",
    "sg:city":"Charleston",
    "sg:classifiers":[
        {
            "category":"Wholesale",
            "subcategory":"Chemicals & Plastics",
            "type":"Manufacturing & Wholesale Goods"
        }
    ],
    "sg:phone":"+1 877 871 0054",
    "sg:postcode":"25303",
    "sg:province":"WV",
    "wof:name":"Hercules Incorporated",
    "wof:placetype":"venue"
},
  "geometry": {"coordinates":[-81.695078,38.366985],"type":"Point"}
}