{
  "type": "Feature",
  "properties": {
    "iso:country":"US",
    "sg:address":"121 Main St",
    "sg:city":"Beckley",
    "sg:classifiers":[
        {
            "category":"Bars & Pubs",
            "subcategory":"Sports Bar",
            "type":"Food & Drink"
        }
    ],
    "sg:menulink":"http://www.allmenus.com/wv/pax/114134-fosters-sports-bar-and-restaurant/menu/",
    "sg:phone":"+1 304 253 1439",
    "sg:postcode":"25801",
    "sg:province":"WV",
    "sg:tags":[
        "american"
    ],
    "wof:name":"Fosters Sports Bar And Restaurant",
    "wof:placetype":"venue"
},
  "geometry": {"coordinates":[-81.189097,37.777478],"type":"Point"}
}