{
  "type": "Feature",
  "properties": {
    "addr:full":"620 Virginia St E Charleston WV 25301",
    "addr:housenumber":"620",
    "addr:postcode":"25301",
    "addr:street":"Virginia St E",
    "iso:country":"US",
    "sg:address":"620 Virginia St E",
    "sg:city":"Charleston",
    "sg:classifiers":[
        {
            "category":"Banks & Credit Unions",
            "subcategory":"Bank",
            "type":"Services"
        }
    ],
    "sg:phone":"+1 304 343 9200",
    "sg:postcode":"25301",
    "sg:province":"WV",
    "wof:name":"Capital State Bank",
    "wof:placetype":"venue"
},
  "geometry": {"coordinates":[-81.636819,38.350059],"type":"Point"}
}