{
  "type": "Feature",
  "properties": {
    "addr:full":"1009 1st Ave Parkersburg WV 26101",
    "addr:housenumber":"1009",
    "addr:postcode":"26101",
    "addr:street":"1St Ave",
    "iso:country":"US",
    "sg:address":"1009 1st Ave",
    "sg:city":"Parkersburg",
    "sg:classifiers":[
        {
            "category":"Restaurant",
            "type":"Food & Drink"
        }
    ],
    "sg:phone":"+1 304 422 7717",
    "sg:postcode":"26101",
    "sg:province":"WV",
    "wof:name":"Kokomos",
    "wof:placetype":"venue"
},
  "geometry": {"coordinates":[-81.561644,39.259755],"type":"Point"}
}