{
  "type": "Feature",
  "properties": {
    "iso:country":"US",
    "sg:address":"5402 Valley Rd",
    "sg:city":"Berkeley Springs",
    "sg:classifiers":[
        {
            "category":"Freight",
            "type":"Transportation"
        }
    ],
    "sg:phone":"+1 304 258 7600",
    "sg:postcode":"25411",
    "sg:province":"WV",
    "sg:tags":[
        "commercial",
        "storage"
    ],
    "wof:name":"Berkeley Springs Self Storage",
    "wof:placetype":"venue"
},
  "geometry": {"coordinates":[-78.24909599999999,39.587224],"type":"Point"}
}