{
  "type": "Feature",
  "properties": {
    "iso:country":"US",
    "sg:address":"1412 Kanawha Blvd W",
    "sg:city":"Charleston",
    "sg:classifiers":[
        {
            "category":"Wholesale",
            "subcategory":"Office Equipment",
            "type":"Manufacturing & Wholesale Goods"
        }
    ],
    "sg:phone":"+1 304 345 6864",
    "sg:postcode":"25312",
    "sg:province":"WV",
    "sg:tags":[
        "machine",
        "duplicating",
        "copying"
    ],
    "wof:name":"Danka",
    "wof:placetype":"venue"
},
  "geometry": {"coordinates":[-81.66367700000001,38.364788],"type":"Point"}
}