{
  "type": "Feature",
  "properties": {
    "iso:country":"US",
    "sg:address":"620 E Washington St",
    "sg:city":"Charles Town",
    "sg:classifiers":[
        {
            "category":"Real Estate",
            "subcategory":"Real Estate Agent",
            "type":"Services"
        }
    ],
    "sg:phone":"+1 304 724 2000",
    "sg:postcode":"25414",
    "sg:province":"WV",
    "wof:name":"Coldwell Banker Premier Homes",
    "wof:placetype":"venue"
},
  "geometry": {"coordinates":[-77.853088,39.291292],"type":"Point"}
}