{
  "type": "Feature",
  "properties": {
    "addr:full":"897 Chestnut Ridge Rd Morgantown WV 26505",
    "addr:housenumber":"897",
    "addr:postcode":"26505",
    "addr:street":"Chestnut Ridge Rd",
    "iso:country":"US",
    "sg:address":"897 Chestnut Ridge Rd",
    "sg:city":"Morgantown",
    "sg:classifiers":[
        {
            "category":"Personal",
            "subcategory":"Beauty Salon",
            "type":"Services"
        }
    ],
    "sg:phone":"+1 304 598 3440",
    "sg:postcode":"26505",
    "sg:province":"WV",
    "sg:tags":[
        "shop"
    ],
    "wof:name":"Tonique Haute Hair",
    "wof:placetype":"venue"
},
  "geometry": {"coordinates":[-79.954795,39.658135],"type":"Point"}
}