{
  "type": "Feature",
  "properties": {
    "addr:full":"119 Thomas Ln Parkersburg WV 26101",
    "addr:housenumber":"119",
    "addr:postcode":"26101",
    "addr:street":"Thomas Ln",
    "iso:country":"US",
    "sg:address":"119 Thomas Ln",
    "sg:city":"Parkersburg",
    "sg:classifiers":[
        {
            "category":"Building & Trades",
            "subcategory":"Landscaping Services",
            "type":"Services"
        },
        {
            "category":"Home & Garden",
            "subcategory":"Garden Supply",
            "type":"Retail Goods"
        },
        {
            "category":"Autos & Motor Vehicles",
            "subcategory":"Auto Supplies",
            "type":"Retail Goods"
        },
        {
            "category":"Manufacturing",
            "subcategory":"Tools & Machinery",
            "type":"Manufacturing & Wholesale Goods"
        }
    ],
    "sg:phone":"+1 304 428 2240",
    "sg:postcode":"26101",
    "sg:province":"WV",
    "sg:tags":[
        "engine",
        "repairing",
        "lawn",
        "mowers-sharpening",
        "gasoline",
        "mower",
        "equipment"
    ],
    "wof:name":"Thomas Lawn Mower Svc Inc",
    "wof:placetype":"venue"
},
  "geometry": {"coordinates":[-81.578198,39.219754],"type":"Point"}
}