{
  "type": "Feature",
  "properties": {
    "iso:country":"US",
    "sg:address":"701 6th Ave",
    "sg:city":"Huntington",
    "sg:classifiers":[
        {
            "category":"Retail",
            "subcategory":"Auto Repair",
            "type":"Services"
        }
    ],
    "sg:phone":"+1 304 523 4723",
    "sg:postcode":"25701",
    "sg:province":"WV",
    "sg:tags":[
        "repairing",
        "automobile"
    ],
    "wof:name":"Quality Services",
    "wof:placetype":"venue"
},
  "geometry": {"coordinates":[-82.44485899999999,38.417708],"type":"Point"}
}