{
  "type": "Feature",
  "properties": {
    "addr:full":"118 Straight St Ripley WV 25271",
    "addr:housenumber":"118",
    "addr:postcode":"25271",
    "addr:street":"Straight St",
    "iso:country":"US",
    "sg:address":"118 Straight St",
    "sg:city":"Ripley",
    "sg:classifiers":[
        {
            "category":"Education",
            "subcategory":"Dance Studio",
            "type":"Public Place"
        }
    ],
    "sg:phone":"+1 304 372 3599",
    "sg:postcode":"25271",
    "sg:province":"WV",
    "sg:tags":[
        "instruction",
        "dancing"
    ],
    "wof:name":"Courtney's Dance Academy",
    "wof:placetype":"venue"
},
  "geometry": {"coordinates":[-81.716317,38.820592],"type":"Point"}
}