{
  "type": "Feature",
  "properties": {
    "addr:full":"1 Columbia St West Columbia WV 25260",
    "addr:housenumber":"1",
    "addr:postcode":"25260",
    "addr:street":"Columbia St",
    "iso:country":"US",
    "sg:address":"1 Columbia St",
    "sg:city":"West Columbia",
    "sg:classifiers":[
        {
            "category":"Health Services",
            "subcategory":"Hospital",
            "type":"Services"
        }
    ],
    "sg:phone":"+1 304 675 0860",
    "sg:postcode":"25260",
    "sg:province":"WV",
    "sg:tags":[
        "public",
        "psychiatric"
    ],
    "wof:name":"Lakin Hospital",
    "wof:placetype":"venue"
},
  "geometry": {"coordinates":[-82.04077100000001,39.001996],"type":"Point"}
}