{
  "type": "Feature",
  "properties": {
    "iso:country":"US",
    "sg:address":"1226 Myers Ave",
    "sg:city":"Dunbar",
    "sg:classifiers":[
        {
            "category":"Real Estate",
            "subcategory":"Real Estate Operator",
            "type":"Services"
        }
    ],
    "sg:phone":"+1 304 768 9022",
    "sg:postcode":"25064",
    "sg:province":"WV",
    "sg:tags":[
        "apartment"
    ],
    "wof:name":"Myers Avenue Apartments",
    "wof:placetype":"venue"
},
  "geometry": {"coordinates":[-81.73989899999999,38.359028],"type":"Point"}
}