{
  "type": "Feature",
  "properties": {
    "iso:country":"US",
    "sg:address":"1200 3rd St",
    "sg:city":"Martinsburg",
    "sg:classifiers":[
        {
            "category":"Building & Trades",
            "subcategory":"Landscaping Services",
            "type":"Services"
        }
    ],
    "sg:phone":"+1 304 263 4742",
    "sg:postcode":"25404",
    "sg:province":"WV",
    "sg:tags":[
        "aged",
        "homes-institutional"
    ],
    "wof:name":"Res-Care Health Svcs",
    "wof:placetype":"venue"
},
  "geometry": {"coordinates":[-77.953018,39.470261],"type":"Point"}
}