{
  "type": "Feature",
  "properties": {
    "iso:country":"US",
    "sg:address":"353 Patteson Dr",
    "sg:city":"Morgantown",
    "sg:classifiers":[
        {
            "category":"Restaurant",
            "type":"Food & Drink"
        }
    ],
    "sg:menulink":"http://www.allmenus.com/wv/central/27710-eat-n-park/menu/",
    "sg:phone":"+1 304 598 0020",
    "sg:postcode":"26505",
    "sg:province":"WV",
    "sg:tags":[
        "american",
        "diner"
    ],
    "wof:name":"Eat N' Park",
    "wof:placetype":"venue"
},
  "geometry": {"coordinates":[-79.97154500000001,39.650682],"type":"Point"}
}