{
  "type": "Feature",
  "properties": {
    "iso:country":"US",
    "sg:address":"1578 Kanawha Blvd E",
    "sg:city":"Charleston",
    "sg:classifiers":[
        {
            "category":"Organizations",
            "subcategory":"Community Association",
            "type":"Services"
        }
    ],
    "sg:phone":"+1 304 342 4533",
    "sg:postcode":"25311",
    "sg:province":"WV",
    "wof:name":"Parkside Place Inc",
    "wof:placetype":"venue"
},
  "geometry": {"coordinates":[-81.619237,38.337644],"type":"Point"}
}