{
  "type": "Feature",
  "properties": {
    "iso:country":"US",
    "sg:address":"2506 Pike St",
    "sg:city":"Parkersburg",
    "sg:classifiers":[
        {
            "category":"Shopping",
            "subcategory":"Gifts & Souvenirs",
            "type":"Retail Goods"
        }
    ],
    "sg:phone":"+1 304 420 0982",
    "sg:postcode":"26101",
    "sg:province":"WV",
    "sg:tags":[
        "personal"
    ],
    "wof:name":"Cloud 9",
    "wof:placetype":"venue"
},
  "geometry": {"coordinates":[-81.54124400000001,39.230764],"type":"Point"}
}