{
  "type": "Feature",
  "properties": {
    "iso:country":"US",
    "sg:address":"405 28th St",
    "sg:city":"Dunbar",
    "sg:classifiers":[
        {
            "category":"Mining & Drilling",
            "type":"Manufacturing & Wholesale Goods"
        }
    ],
    "sg:phone":"+1 304 768 4933",
    "sg:postcode":"25064",
    "sg:province":"WV",
    "sg:tags":[
        "perforating",
        "well",
        "oil",
        "logging"
    ],
    "wof:name":"Allegheny Wireline Svc",
    "wof:placetype":"venue"
},
  "geometry": {"coordinates":[-81.754831,38.366703],"type":"Point"}
}