{
  "type": "Feature",
  "properties": {
    "addr:full":"105 Dodd St Middlebourne WV 26149",
    "addr:housenumber":"105",
    "addr:postcode":"26149",
    "addr:street":"Dodd St",
    "iso:country":"US",
    "sg:address":"105 Dodd St",
    "sg:city":"Middlebourne",
    "sg:classifiers":[
        {
            "category":"Government",
            "subcategory":"Post Office",
            "type":"Public Place"
        }
    ],
    "sg:phone":"+1 304 758 4021",
    "sg:postcode":"26149",
    "sg:province":"WV",
    "sg:tags":[
        "postal",
        "us"
    ],
    "sg:website":"www.usps.gov",
    "wof:name":"US Post Office",
    "wof:placetype":"venue"
},
  "geometry": {"coordinates":[-80.904561,39.492717],"type":"Point"}
}