{
  "type": "Feature",
  "properties": {
    "iso:country":"US",
    "sg:address":"956 Donegal Dr E",
    "sg:city":"Follansbee",
    "sg:classifiers":[
        {
            "category":"Real Estate",
            "subcategory":"Real Estate Agent",
            "type":"Services"
        }
    ],
    "sg:phone":"+1 304 748 8273",
    "sg:postcode":"26037",
    "sg:province":"WV",
    "wof:name":"Ed Dipino Appraisal Service",
    "wof:placetype":"venue"
},
  "geometry": {"coordinates":[-80.59835099999999,40.355348],"type":"Point"}
}