{
  "type": "Feature",
  "properties": {
    "iso:country":"US",
    "sg:address":"609 S Kanawha St",
    "sg:city":"Beckley",
    "sg:classifiers":[
        {
            "category":"Education",
            "subcategory":"Library",
            "type":"Public Place"
        }
    ],
    "sg:phone":"+1 304 253 7351",
    "sg:postcode":"25801",
    "sg:province":"WV",
    "sg:website":"www.mountainstate.edu",
    "wof:name":"Mountain State University",
    "wof:placetype":"venue"
},
  "geometry": {"coordinates":[-81.18258400000001,37.775558],"type":"Point"}
}