{
  "type": "Feature",
  "properties": {
    "iso:country":"US",
    "sg:address":"6112 York Ave",
    "sg:city":"Martinsburg",
    "sg:classifiers":[
        {
            "category":"Building & Trades",
            "subcategory":"Cleaning & Sanitation",
            "type":"Services"
        }
    ],
    "sg:phone":"+1 304 263 7167",
    "sg:postcode":"25401",
    "sg:province":"WV",
    "wof:name":"Precision Powerwashing",
    "wof:placetype":"venue"
},
  "geometry": {"coordinates":[-78.009794,39.502269],"type":"Point"}
}