{
  "type": "Feature",
  "properties": {
    "iso:country":"US",
    "sg:address":"100 Ridge Run Rd",
    "sg:city":"Culloden",
    "sg:classifiers":[
        {
            "category":"Real Estate",
            "subcategory":"Real Estate Operator",
            "type":"Services"
        }
    ],
    "sg:phone":"+1 304 743 3536",
    "sg:postcode":"25510",
    "sg:province":"WV",
    "sg:tags":[
        "apartment"
    ],
    "wof:name":"Culloden Manor LTD",
    "wof:placetype":"venue"
},
  "geometry": {"coordinates":[-82.061837,38.413053],"type":"Point"}
}