{
  "type": "Feature",
  "properties": {
    "addr:full":"43 Hafer Dr Elkview WV 25071",
    "addr:housenumber":"43",
    "addr:postcode":"25071",
    "addr:street":"Hafer Dr",
    "iso:country":"US",
    "sg:address":"43 Hafer Dr",
    "sg:city":"Elkview",
    "sg:classifiers":[
        {
            "category":"Building & Trades",
            "subcategory":"Electrical",
            "type":"Services"
        }
    ],
    "sg:phone":"+1 304 965 0968",
    "sg:postcode":"25071",
    "sg:province":"WV",
    "sg:tags":[
        "sound",
        "equipment",
        "retail"
    ],
    "wof:name":"Millenium Duplicating LLC",
    "wof:placetype":"venue"
},
  "geometry": {"coordinates":[-81.48461,38.438462],"type":"Point"}
}