{
  "type": "Feature",
  "properties": {
    "iso:country":"US",
    "sg:address":"1626 Grafton Rd",
    "sg:city":"Morgantown",
    "sg:classifiers":[
        {
            "category":"Education",
            "subcategory":"Special Training",
            "type":"Public Place"
        }
    ],
    "sg:phone":"+1 304 265 3308",
    "sg:postcode":"26508",
    "sg:province":"WV",
    "sg:tags":[
        "center"
    ],
    "wof:name":"Webster Head Start",
    "wof:placetype":"venue"
},
  "geometry": {"coordinates":[-79.949608,39.575941],"type":"Point"}
}