{
  "type": "Feature",
  "properties": {
    "iso:country":"US",
    "sg:address":"1801 Locust Ave",
    "sg:city":"Fairmont",
    "sg:classifiers":[
        {
            "category":"Bars & Pubs",
            "type":"Food & Drink"
        }
    ],
    "sg:phone":"+1 304 333 2672",
    "sg:postcode":"26554",
    "sg:province":"WV",
    "sg:tags":[
        "lounge",
        "cocktail"
    ],
    "wof:name":"Copa Lounge",
    "wof:placetype":"venue"
},
  "geometry": {"coordinates":[-80.180218,39.472276],"type":"Point"}
}