{
  "type": "Feature",
  "properties": {
    "iso:country":"US",
    "sg:address":"2075 Lester Hwy",
    "sg:city":"Lester",
    "sg:classifiers":[
        {
            "category":"Manufacturing",
            "subcategory":"Tools & Machinery",
            "type":"Manufacturing & Wholesale Goods"
        }
    ],
    "sg:phone":"+1 304 934 5361",
    "sg:postcode":"25865",
    "sg:province":"WV",
    "sg:tags":[
        "trencher"
    ],
    "sg:website":"www.alleecorp.com",
    "wof:name":"A L Lee Corp",
    "wof:placetype":"venue"
},
  "geometry": {"coordinates":[-81.346059,37.683605],"type":"Point"}
}