{
  "type": "Feature",
  "properties": {
    "iso:country":"US",
    "sg:address":"2814 Collis Ave",
    "sg:city":"Huntington",
    "sg:classifiers":[
        {
            "category":"Organizations",
            "subcategory":"Religious Organization",
            "type":"Services"
        }
    ],
    "sg:phone":"+1 304 522 1676",
    "sg:postcode":"25702",
    "sg:province":"WV",
    "sg:website":"www.highlawnpc.org",
    "wof:name":"Highlawn Presbyterian Church",
    "wof:placetype":"venue"
},
  "geometry": {"coordinates":[-82.402658,38.430497],"type":"Point"}
}