{
  "type": "Feature",
  "properties": {
    "iso:country":"US",
    "sg:address":"115 Moran Ave",
    "sg:city":"Mullens",
    "sg:classifiers":[
        {
            "category":"Cinema",
            "subcategory":"Movie Rental",
            "type":"Entertainment"
        }
    ],
    "sg:phone":"+1 304 294 0335",
    "sg:postcode":"25882",
    "sg:province":"WV",
    "sg:tags":[
        "leasing",
        "video",
        "disc",
        "tape"
    ],
    "wof:name":"Movie Store",
    "wof:placetype":"venue"
},
  "geometry": {"coordinates":[-81.38036700000001,37.582352],"type":"Point"}
}