{
  "type": "Feature",
  "properties": {
    "iso:country":"US",
    "sg:address":"305 S George St",
    "sg:city":"Ranson",
    "sg:classifiers":[
        {
            "category":"Home & Garden",
            "subcategory":"Household Appliances",
            "type":"Retail Goods"
        },
        {
            "category":"Building & Trades",
            "subcategory":"Electrical",
            "type":"Services"
        }
    ],
    "sg:phone":"+1 304 725 5516",
    "sg:postcode":"25438",
    "sg:province":"WV",
    "sg:tags":[
        "major",
        "industrial",
        "electrician",
        "electric",
        "appliances-small",
        "contractors-commercial"
    ],
    "wof:name":"Magaha Incorporated",
    "wof:placetype":"venue"
},
  "geometry": {"coordinates":[-77.862903,39.294336],"type":"Point"}
}