{
  "type": "Feature",
  "properties": {
    "iso:country":"US",
    "sg:address":"321 W Main St",
    "sg:city":"Clarksburg",
    "sg:classifiers":[
        {
            "category":"Personal",
            "type":"Services"
        }
    ],
    "sg:phone":"+1 304 624 9495",
    "sg:postcode":"26301",
    "sg:province":"WV",
    "sg:tags":[
        "electrolysis"
    ],
    "wof:name":"Smooth Look",
    "wof:placetype":"venue"
},
  "geometry": {"coordinates":[-80.340379,39.279439],"type":"Point"}
}