{
  "type": "Feature",
  "properties": {
    "addr:full":"298 Ragland Rd Beckley WV 25801",
    "addr:housenumber":"298",
    "addr:postcode":"25801",
    "addr:street":"Ragland Rd",
    "iso:country":"US",
    "sg:address":"298 Ragland Rd",
    "sg:city":"Beckley",
    "sg:classifiers":[
        {
            "category":"Government",
            "subcategory":"Office",
            "type":"Public Place"
        }
    ],
    "sg:phone":"+1 304 252 8644",
    "sg:postcode":"25801",
    "sg:province":"WV",
    "sg:tags":[
        "federal",
        "planning",
        "dev"
    ],
    "wof:name":"USDA Rural Development",
    "wof:placetype":"venue"
},
  "geometry": {"coordinates":[-81.17972899999999,37.808004],"type":"Point"}
}