{
  "type": "Feature",
  "properties": {
    "addr:full":"1210 S Kanawha St Beckley WV 25801",
    "addr:housenumber":"1210",
    "addr:postcode":"25801",
    "addr:street":"S Kanawha St",
    "iso:country":"US",
    "sg:address":"1210 S Kanawha St",
    "sg:city":"Beckley",
    "sg:classifiers":[
        {
            "category":"Wholesale",
            "subcategory":"Machinery & Supplies",
            "type":"Manufacturing & Wholesale Goods"
        }
    ],
    "sg:phone":"+1 304 255 1367",
    "sg:postcode":"25801",
    "sg:province":"WV",
    "sg:tags":[
        "salon",
        "beauty"
    ],
    "wof:name":"Twin State Beauty Supply",
    "wof:placetype":"venue"
},
  "geometry": {"coordinates":[-81.17499599999999,37.772812],"type":"Point"}
}