{
  "type": "Feature",
  "properties": {
    "addr:full":"124 Hatchery Rd Inwood WV 25428",
    "addr:housenumber":"124",
    "addr:postcode":"25428",
    "addr:street":"Hatchery Rd",
    "iso:country":"US",
    "sg:address":"124 Hatchery Rd",
    "sg:city":"Inwood",
    "sg:classifiers":[
        {
            "category":"Building & Trades",
            "subcategory":"Landscaping Services",
            "type":"Services"
        },
        {
            "category":"Home & Garden",
            "subcategory":"Garden Supply",
            "type":"Retail Goods"
        },
        {
            "category":"Manufacturing",
            "subcategory":"Paper Products",
            "type":"Manufacturing & Wholesale Goods"
        }
    ],
    "sg:phone":"+1 304 229 6699",
    "sg:postcode":"25428",
    "sg:province":"WV",
    "sg:tags":[
        "lawn",
        "designer",
        "consultant",
        "contractor",
        "bamboo",
        "landscape"
    ],
    "wof:name":"Jpm Landscaping",
    "wof:placetype":"venue"
},
  "geometry": {"coordinates":[-78.02451000000001,39.369689],"type":"Point"}
}