{
  "type": "Feature",
  "properties": {
    "iso:country":"US",
    "sg:address":"3319 Pennsylvania Ave",
    "sg:city":"Weirton",
    "sg:classifiers":[
        {
            "category":"Insurance",
            "subcategory":"Hazard Insurance",
            "type":"Services"
        }
    ],
    "sg:phone":"+1 304 723 3311",
    "sg:postcode":"26062",
    "sg:province":"WV",
    "sg:tags":[
        "commercial",
        "business"
    ],
    "wof:name":"Boehm Insurance Agency",
    "wof:placetype":"venue"
},
  "geometry": {"coordinates":[-80.537785,40.408783],"type":"Point"}
}