{
  "type": "Feature",
  "properties": {
    "addr:full":"340 Patrick Henry Way Charles Town WV 25414",
    "addr:housenumber":"340",
    "addr:postcode":"25414",
    "addr:street":"Patrick Henry Way",
    "iso:country":"US",
    "sg:address":"340 Patrick Henry Way",
    "sg:city":"Charles Town",
    "sg:classifiers":[
        {
            "category":"Shopping",
            "subcategory":"Clothing, Apparel, & Fashions",
            "type":"Retail Goods"
        }
    ],
    "sg:phone":"+1 304 728 0257",
    "sg:postcode":"25414",
    "sg:province":"WV",
    "wof:name":"Cato",
    "wof:placetype":"venue"
},
  "geometry": {"coordinates":[-77.830759,39.300146],"type":"Point"}
}