{
  "type": "Feature",
  "properties": {
    "addr:full":"140 School St Oak Hill WV 25901",
    "addr:housenumber":"140",
    "addr:postcode":"25901",
    "addr:street":"School St",
    "iso:country":"US",
    "sg:address":"140 School St",
    "sg:city":"Oak Hill",
    "sg:classifiers":[
        {
            "category":"Education",
            "subcategory":"School",
            "type":"Public Place"
        }
    ],
    "sg:phone":"+1 304 469 4541",
    "sg:postcode":"25901",
    "sg:province":"WV",
    "sg:tags":[
        "elementary"
    ],
    "wof:name":"Oak Hill Elementary School",
    "wof:placetype":"venue"
},
  "geometry": {"coordinates":[-81.14832199999999,37.974933],"type":"Point"}
}