{
  "type": "Feature",
  "properties": {
    "iso:country":"US",
    "sg:address":"409 Pike St",
    "sg:city":"Barrackville",
    "sg:classifiers":[
        {
            "category":"Organizations",
            "subcategory":"Religious Organization",
            "type":"Services"
        }
    ],
    "sg:phone":"+1 304 366 8342",
    "sg:postcode":"26559",
    "sg:province":"WV",
    "sg:tags":[
        "church"
    ],
    "wof:name":"Barrackville United Methodist",
    "wof:placetype":"venue"
},
  "geometry": {"coordinates":[-80.166014,39.50303],"type":"Point"}
}