{
  "type": "Feature",
  "properties": {
    "iso:country":"US",
    "sg:address":"2119 Fairmont Ave",
    "sg:city":"Fairmont",
    "sg:classifiers":[
        {
            "category":"Government",
            "subcategory":"Office",
            "type":"Public Place"
        }
    ],
    "sg:phone":"+1 304 367 1687",
    "sg:postcode":"26554",
    "sg:province":"WV",
    "sg:tags":[
        "village"
    ],
    "wof:name":"Town Of White Hall",
    "wof:placetype":"venue"
},
  "geometry": {"coordinates":[-80.17495700000001,39.450699],"type":"Point"}
}