{
  "type": "Feature",
  "properties": {
    "addr:full":"314 Campbells Creek Dr Charleston WV 25306",
    "addr:housenumber":"314",
    "addr:postcode":"25306",
    "addr:street":"Campbells Creek Dr",
    "iso:country":"US",
    "sg:address":"314 Campbells Creek Dr",
    "sg:city":"Charleston",
    "sg:classifiers":[
        {
            "category":"Organizations",
            "subcategory":"Religious Organization",
            "type":"Services"
        }
    ],
    "sg:phone":"+1 304 925 7469",
    "sg:postcode":"25306",
    "sg:province":"WV",
    "sg:tags":[
        "clergy"
    ],
    "wof:name":"Mike Long",
    "wof:placetype":"venue"
},
  "geometry": {"coordinates":[-81.536592,38.313214],"type":"Point"}
}