{
  "type": "Feature",
  "properties": {
    "addr:full":"1206 Chapline St Wheeling WV 26003",
    "addr:housenumber":"1206",
    "addr:postcode":"26003",
    "addr:street":"Chapline St",
    "iso:country":"US",
    "sg:address":"1206 Chapline St",
    "sg:city":"Wheeling",
    "sg:classifiers":[
        {
            "category":"Government",
            "subcategory":"Office",
            "type":"Public Place"
        }
    ],
    "sg:phone":"+1 304 232 0587",
    "sg:postcode":"26003",
    "sg:province":"WV",
    "sg:tags":[
        "vet",
        "center"
    ],
    "wof:name":"Wheeling Vet Center",
    "wof:placetype":"venue"
},
  "geometry": {"coordinates":[-80.721001,40.065774],"type":"Point"}
}