{
  "type": "Feature",
  "properties": {
    "iso:country":"US",
    "sg:address":"1425 Old Athens Rd",
    "sg:city":"Princeton",
    "sg:classifiers":[
        {
            "category":"Shopping",
            "subcategory":"Used Merchandise",
            "type":"Retail Goods"
        }
    ],
    "sg:phone":"+1 304 425 4860",
    "sg:postcode":"24740",
    "sg:province":"WV",
    "sg:tags":[
        "shop",
        "consignment"
    ],
    "wof:name":"Repeat Performance",
    "wof:placetype":"venue"
},
  "geometry": {"coordinates":[-81.058463,37.395331],"type":"Point"}
}