{
  "type": "Feature",
  "properties": {
    "iso:country":"US",
    "sg:address":"1719 Washington St W",
    "sg:city":"Charleston",
    "sg:classifiers":[
        {
            "category":"Retail",
            "subcategory":"Repair Shop",
            "type":"Services"
        }
    ],
    "sg:phone":"+1 304 949 6565",
    "sg:postcode":"25312",
    "sg:province":"WV",
    "sg:tags":[
        "electrical"
    ],
    "wof:name":"White Appliance & Repair",
    "wof:placetype":"venue"
},
  "geometry": {"coordinates":[-81.66455499999999,38.373896],"type":"Point"}
}