{
  "type": "Feature",
  "properties": {
    "addr:full":"430 Mount View Rd Cool Ridge WV 25825",
    "addr:housenumber":"430",
    "addr:postcode":"25825",
    "addr:street":"Mount View Rd",
    "iso:country":"US",
    "sg:address":"430 Mount View Rd",
    "sg:city":"Cool Ridge",
    "sg:classifiers":[
        {
            "category":"Wholesale",
            "subcategory":"Chemicals & Plastics",
            "type":"Manufacturing & Wholesale Goods"
        }
    ],
    "sg:phone":"+1 304 787 5550",
    "sg:postcode":"25825",
    "sg:province":"WV",
    "wof:name":"Ammonia Inc",
    "wof:placetype":"venue"
},
  "geometry": {"coordinates":[-81.08816899999999,37.654098],"type":"Point"}
}