{
  "type": "Feature",
  "properties": {
    "iso:country":"US",
    "sg:address":"616 6th Ave",
    "sg:city":"Huntington",
    "sg:classifiers":[
        {
            "category":"Retail",
            "subcategory":"Auto Repair",
            "type":"Services"
        }
    ],
    "sg:phone":"+1 304 529 6533",
    "sg:postcode":"25701",
    "sg:province":"WV",
    "sg:tags":[
        "repairing",
        "automobile"
    ],
    "wof:name":"Ernie's Automotive Ctr",
    "wof:placetype":"venue"
},
  "geometry": {"coordinates":[-82.446788,38.41744],"type":"Point"}
}