{
  "type": "Feature",
  "properties": {
    "addr:full":"313 D St Charleston WV 25303",
    "addr:housenumber":"313",
    "addr:postcode":"25303",
    "addr:street":"D St",
    "iso:country":"US",
    "sg:address":"313 D St",
    "sg:city":"Charleston",
    "sg:classifiers":[
        {
            "category":"Shopping",
            "subcategory":"Used Merchandise",
            "type":"Retail Goods"
        }
    ],
    "sg:phone":"+1 304 744 8975",
    "sg:postcode":"25303",
    "sg:province":"WV",
    "sg:tags":[
        "antique"
    ],
    "wof:name":"Attic Antiques",
    "wof:placetype":"venue"
},
  "geometry": {"coordinates":[-81.69470699999999,38.366019],"type":"Point"}
}