{
  "type": "Feature",
  "properties": {
    "iso:country":"US",
    "sg:address":"4 Rosemar Cir",
    "sg:city":"Parkersburg",
    "sg:classifiers":[
        {
            "category":"Professional",
            "subcategory":"Lawyer & Legal Services",
            "type":"Services"
        }
    ],
    "sg:phone":"+1 304 422 3925",
    "sg:postcode":"26104",
    "sg:province":"WV",
    "sg:tags":[
        "attorney"
    ],
    "wof:name":"J D Beane",
    "wof:placetype":"venue"
},
  "geometry": {"coordinates":[-81.522949,39.294172],"type":"Point"}
}