{
  "type": "Feature",
  "properties": {
    "iso:country":"US",
    "sg:address":"1003 Wyoming St",
    "sg:city":"Bluefield",
    "sg:classifiers":[
        {
            "category":"Organizations",
            "subcategory":"Religious Organization",
            "type":"Services"
        }
    ],
    "sg:phone":"+1 304 327 5623",
    "sg:postcode":"24701",
    "sg:province":"WV",
    "sg:tags":[
        "church"
    ],
    "sg:website":"www.sacredheartblfd.org",
    "wof:name":"Sacred Heart Church",
    "wof:placetype":"venue"
},
  "geometry": {"coordinates":[-81.216998,37.270755],"type":"Point"}
}