{
  "type": "Feature",
  "properties": {
    "addr:full":"105 N Main St Petersburg WV 26847",
    "addr:housenumber":"105",
    "addr:postcode":"26847",
    "addr:street":"N Main St",
    "iso:country":"US",
    "sg:address":"105 N Main St",
    "sg:city":"Petersburg",
    "sg:classifiers":[
        {
            "category":"Shopping",
            "subcategory":"Books",
            "type":"Retail Goods"
        }
    ],
    "sg:phone":"+1 304 257 2144",
    "sg:postcode":"26847",
    "sg:province":"WV",
    "wof:name":"Davis House Bookstore",
    "wof:placetype":"venue"
},
  "geometry": {"coordinates":[-79.12444000000001,38.996241],"type":"Point"}
}