{
  "type": "Feature",
  "properties": {
    "addr:full":"54 Reedyville Rd Spencer WV 25276",
    "addr:housenumber":"54",
    "addr:postcode":"25276",
    "addr:street":"Reedyville Rd",
    "iso:country":"US",
    "sg:address":"54 Reedyville Rd",
    "sg:city":"Spencer",
    "sg:classifiers":[
        {
            "category":"Professional",
            "subcategory":"Business Services",
            "type":"Services"
        }
    ],
    "sg:phone":"+1 304 927 2278",
    "sg:postcode":"25276",
    "sg:province":"WV",
    "wof:name":"Boggs Auction Co",
    "wof:placetype":"venue"
},
  "geometry": {"coordinates":[-81.437091,38.812699],"type":"Point"}
}