{
  "type": "Feature",
  "properties": {
    "addr:full":"110 Laurel St Moorefield WV 26836",
    "addr:housenumber":"110",
    "addr:postcode":"26836",
    "addr:street":"Laurel St",
    "iso:country":"US",
    "sg:address":"110 Laurel St",
    "sg:city":"Moorefield",
    "sg:classifiers":[
        {
            "category":"Professional",
            "subcategory":"Computer Services",
            "type":"Services"
        }
    ],
    "sg:phone":"+1 304 538 7452",
    "sg:postcode":"26836",
    "sg:province":"WV",
    "sg:tags":[
        "datum"
    ],
    "wof:name":"My House Publishing",
    "wof:placetype":"venue"
},
  "geometry": {"coordinates":[-78.949094,39.072537],"type":"Point"}
}