{
  "type": "Feature",
  "properties": {
    "addr:full":"602 Division St Parkersburg WV 26101",
    "addr:housenumber":"602",
    "addr:postcode":"26101",
    "addr:street":"Division St",
    "iso:country":"US",
    "sg:address":"602 Division St",
    "sg:city":"Parkersburg",
    "sg:classifiers":[
        {
            "category":"Autos & Motor Vehicles",
            "subcategory":"Automobile Sales",
            "type":"Retail Goods"
        }
    ],
    "sg:phone":"+1 304 485 4111",
    "sg:postcode":"26101",
    "sg:province":"WV",
    "sg:tags":[
        "used"
    ],
    "wof:name":"Kanawha Motor Co",
    "wof:placetype":"venue"
},
  "geometry": {"coordinates":[-81.554259,39.252593],"type":"Point"}
}