{
  "type": "Feature",
  "properties": {
    "iso:country":"US",
    "sg:address":"403 E Washington St",
    "sg:city":"Lewisburg",
    "sg:classifiers":[
        {
            "category":"Travel",
            "subcategory":"Hotels & Motels",
            "type":"Entertainment"
        }
    ],
    "sg:phone":"+1 304 647 4096",
    "sg:postcode":"24901",
    "sg:province":"WV",
    "sg:tags":[
        "operation"
    ],
    "wof:name":"Minnie Manor Bed & Breakfast",
    "wof:placetype":"venue"
},
  "geometry": {"coordinates":[-80.440872,37.79893],"type":"Point"}
}