{
  "type": "Feature",
  "properties": {
    "iso:country":"US",
    "sg:address":"830 Pennsylvania Ave",
    "sg:city":"Charleston",
    "sg:classifiers":[
        {
            "category":"Health Services",
            "subcategory":"Medical Lab",
            "type":"Services"
        }
    ],
    "sg:phone":"+1 304 345 5215",
    "sg:postcode":"25302",
    "sg:province":"WV",
    "sg:tags":[
        "laboratory"
    ],
    "wof:name":"SVI Laboratory Svc",
    "wof:placetype":"venue"
},
  "geometry": {"coordinates":[-81.639003,38.359331],"type":"Point"}
}