{
  "type": "Feature",
  "properties": {
    "iso:country":"US",
    "sg:address":"1925 Pennsylvania Ave",
    "sg:city":"Weirton",
    "sg:classifiers":[
        {
            "category":"Restaurant",
            "type":"Food & Drink"
        }
    ],
    "sg:menulink":"http://www.allmenus.com/wv/butler/43681-vocelli-pizza/menu/",
    "sg:phone":"+1 800 707 1111",
    "sg:postcode":"26062",
    "sg:province":"WV",
    "sg:tags":[
        "american",
        "italian",
        "pizza"
    ],
    "wof:name":"Vocelli Pizza",
    "wof:placetype":"venue"
},
  "geometry": {"coordinates":[-80.56409600000001,40.421588],"type":"Point"}
}