{
  "type": "Feature",
  "properties": {
    "iso:country":"US",
    "sg:address":"1105 Quarrier St",
    "sg:city":"Charleston",
    "sg:classifiers":[
        {
            "category":"Social Services",
            "type":"Services"
        }
    ],
    "sg:phone":"+1 304 344 3853",
    "sg:postcode":"25301",
    "sg:province":"WV",
    "sg:tags":[
        "counseling"
    ],
    "wof:name":"Diane Brier Hendricks",
    "wof:placetype":"venue"
},
  "geometry": {"coordinates":[-81.630399,38.346342],"type":"Point"}
}