{
  "type": "Feature",
  "properties": {
    "iso:country":"US",
    "sg:address":"232 W Main St",
    "sg:city":"Bridgeport",
    "sg:classifiers":[
        {
            "category":"Restaurant",
            "type":"Food & Drink"
        }
    ],
    "sg:phone":"+1 304 842 5970",
    "sg:postcode":"26330",
    "sg:province":"WV",
    "wof:name":"Angelo's Pizza",
    "wof:placetype":"venue"
},
  "geometry": {"coordinates":[-80.25455700000001,39.283702],"type":"Point"}
}