{
  "type": "Feature",
  "properties": {
    "iso:country":"US",
    "sg:address":"209 Putnam Ave",
    "sg:city":"Marietta",
    "sg:classifiers":[
        {
            "category":"Building & Trades",
            "subcategory":"Construction",
            "type":"Services"
        }
    ],
    "sg:phone":"+1 740 374 8485",
    "sg:postcode":"45750",
    "sg:province":"OH",
    "sg:tags":[
        "house"
    ],
    "wof:name":"John Lough Builders",
    "wof:placetype":"venue"
},
  "geometry": {"coordinates":[-81.460229,39.413427],"type":"Point"}
}