{
  "type": "Feature",
  "properties": {
    "iso:country":"US",
    "sg:address":"8153 Court Ave",
    "sg:city":"Hamlin",
    "sg:classifiers":[
        {
            "category":"Food & Beverages",
            "subcategory":"Groceries & Convenience Stores",
            "type":"Retail Goods"
        }
    ],
    "sg:phone":"+1 304 824 7098",
    "sg:postcode":"25523",
    "sg:province":"WV",
    "wof:name":"Pit Stop Inc",
    "wof:placetype":"venue"
},
  "geometry": {"coordinates":[-82.102485,38.278551],"type":"Point"}
}