{
  "type": "Feature",
  "properties": {
    "iso:country":"US",
    "sg:address":"3107 E Cumberland Rd",
    "sg:city":"Bluefield",
    "sg:classifiers":[
        {
            "category":"Professional",
            "subcategory":"Lawyer & Legal Services",
            "type":"Services"
        }
    ],
    "sg:phone":"+1 304 327 0730",
    "sg:postcode":"24701",
    "sg:province":"WV",
    "sg:tags":[
        "attorney"
    ],
    "wof:name":"Henderson & Fuda Atty",
    "wof:placetype":"venue"
},
  "geometry": {"coordinates":[-81.203937,37.254326],"type":"Point"}
}