{
  "type": "Feature",
  "properties": {
    "iso:country":"US",
    "sg:address":"7 Pleasant Dr",
    "sg:city":"Wheeling",
    "sg:classifiers":[
        {
            "category":"Professional",
            "type":"Services"
        }
    ],
    "sg:phone":"+1 304 242 7777",
    "sg:postcode":"26003",
    "sg:province":"WV",
    "wof:name":"L W Postlewait & Sons Inc",
    "wof:placetype":"venue"
},
  "geometry": {"coordinates":[-80.682512,40.068003],"type":"Point"}
}