{
  "type": "Feature",
  "properties": {
    "iso:country":"US",
    "sg:address":"3032 West St",
    "sg:city":"Weirton",
    "sg:classifiers":[
        {
            "category":"Health Services",
            "subcategory":"Doctor",
            "type":"Services"
        }
    ],
    "sg:phone":"+1 304 748 2828",
    "sg:postcode":"26062",
    "sg:province":"WV",
    "sg:tags":[
        "physician",
        "surgeon"
    ],
    "wof:name":"Family Medical Care",
    "wof:placetype":"venue"
},
  "geometry": {"coordinates":[-80.589479,40.407878],"type":"Point"}
}