{
  "type": "Feature",
  "properties": {
    "iso:country":"US",
    "sg:address":"910 4th St W",
    "sg:city":"Huntington",
    "sg:classifiers":[
        {
            "category":"Professional",
            "subcategory":"Lawyer & Legal Services",
            "type":"Services"
        }
    ],
    "sg:phone":"+1 304 522 0508",
    "sg:postcode":"25701",
    "sg:province":"WV",
    "wof:name":"Underwood Law Office",
    "wof:placetype":"venue"
},
  "geometry": {"coordinates":[-82.459287,38.40905],"type":"Point"}
}