{
  "type": "Feature",
  "properties": {
    "iso:country":"US",
    "sg:address":"4009 E Cumberland Rd",
    "sg:city":"Bluefield",
    "sg:classifiers":[
        {
            "category":"Shopping",
            "subcategory":"Bicycles & Sporting Goods",
            "type":"Retail Goods"
        }
    ],
    "sg:phone":"+1 304 323 3576",
    "sg:postcode":"24701",
    "sg:province":"WV",
    "wof:name":"Adventures",
    "wof:placetype":"venue"
},
  "geometry": {"coordinates":[-81.185484,37.263489],"type":"Point"}
}