{
  "type": "Feature",
  "properties": {
    "addr:full":"3962 Teays Valley Rd Hurricane WV 25526",
    "addr:housenumber":"3962",
    "addr:postcode":"25526",
    "addr:street":"Teays Valley Rd",
    "iso:country":"US",
    "sg:address":"3962 Teays Valley Rd",
    "sg:city":"Hurricane",
    "sg:classifiers":[
        {
            "category":"Insurance",
            "subcategory":"Insurance Agent",
            "type":"Services"
        }
    ],
    "sg:phone":"+1 304 757 7700",
    "sg:postcode":"25526",
    "sg:province":"WV",
    "wof:name":"State Farm Insurance",
    "wof:placetype":"venue"
},
  "geometry": {"coordinates":[-81.940326,38.448583],"type":"Point"}
}