{
  "type": "Feature",
  "properties": {
    "addr:full":"3109 University Ave Morgantown WV 26505",
    "addr:housenumber":"3109",
    "addr:postcode":"26505",
    "addr:street":"University Ave",
    "iso:country":"US",
    "sg:address":"3109 University Ave",
    "sg:city":"Morgantown",
    "sg:classifiers":[
        {
            "category":"Manufacturing",
            "subcategory":"Printing",
            "type":"Manufacturing & Wholesale Goods"
        }
    ],
    "sg:phone":"+1 304 598 8060",
    "sg:postcode":"26505",
    "sg:province":"WV",
    "sg:tags":[
        "design",
        "layout",
        "photocopying"
    ],
    "wof:name":"Nextprint Inc",
    "wof:placetype":"venue"
},
  "geometry": {"coordinates":[-79.969593,39.654111],"type":"Point"}
}