{
  "type": "Feature",
  "properties": {
    "iso:country":"US",
    "sg:address":"508 10th St",
    "sg:city":"Huntington",
    "sg:classifiers":[
        {
            "category":"Health Services",
            "subcategory":"Doctor",
            "type":"Services"
        }
    ],
    "sg:phone":"+1 304 525 7471",
    "sg:postcode":"25701",
    "sg:province":"WV",
    "sg:tags":[
        "medical"
    ],
    "wof:name":"Levine Leighann",
    "wof:placetype":"venue"
},
  "geometry": {"coordinates":[-82.441613,38.419118],"type":"Point"}
}