{
  "type": "Feature",
  "properties": {
    "iso:country":"US",
    "sg:address":"1000 16th St",
    "sg:city":"Parkersburg",
    "sg:classifiers":[
        {
            "category":"Organizations",
            "subcategory":"Religious Organization",
            "type":"Services"
        }
    ],
    "sg:phone":"+1 304 422 6001",
    "sg:postcode":"26101",
    "sg:province":"WV",
    "wof:name":"End Time Harvest Church",
    "wof:placetype":"venue"
},
  "geometry": {"coordinates":[-81.543019,39.271809],"type":"Point"}
}