{
  "type": "Feature",
  "properties": {
    "iso:country":"US",
    "sg:address":"409 Spring Ave",
    "sg:city":"Moorefield",
    "sg:classifiers":[
        {
            "category":"Government",
            "subcategory":"Office",
            "type":"Public Place"
        }
    ],
    "sg:phone":"+1 304 538 2256",
    "sg:postcode":"26836",
    "sg:province":"WV",
    "sg:tags":[
        "county",
        "resource"
    ],
    "wof:name":"Hardy County Aging Commission",
    "wof:placetype":"venue"
},
  "geometry": {"coordinates":[-78.961347,39.070395],"type":"Point"}
}