{
  "type": "Feature",
  "properties": {
    "iso:country":"US",
    "sg:address":"1305 Washington Pike",
    "sg:city":"Wellsburg",
    "sg:classifiers":[
        {
            "category":"Education",
            "subcategory":"School",
            "type":"Public Place"
        }
    ],
    "sg:phone":"+1 304 737 1760",
    "sg:postcode":"26070",
    "sg:province":"WV",
    "wof:name":"Franklin Elementary School",
    "wof:placetype":"venue"
},
  "geometry": {"coordinates":[-80.542846,40.274882],"type":"Point"}
}