{
  "type": "Feature",
  "properties": {
    "iso:country":"US",
    "sg:address":"347 Ridge Ave",
    "sg:city":"Martinsburg",
    "sg:classifiers":[
        {
            "category":"Professional",
            "subcategory":"Management & Consulting",
            "type":"Services"
        }
    ],
    "sg:phone":"+1 304 262 3755",
    "sg:postcode":"25401",
    "sg:province":"WV",
    "sg:tags":[
        "retail",
        "direct",
        "sales"
    ],
    "wof:name":"Twm Enterprises",
    "wof:placetype":"venue"
},
  "geometry": {"coordinates":[-77.9871,39.436351],"type":"Point"}
}