{
  "type": "Feature",
  "properties": {
    "iso:country":"US",
    "sg:address":"962 W Pike St",
    "sg:city":"Clarksburg",
    "sg:classifiers":[
        {
            "category":"Building & Trades",
            "subcategory":"Landscaping Services",
            "type":"Services"
        }
    ],
    "sg:phone":"+1 304 622 7988",
    "sg:postcode":"26301",
    "sg:province":"WV",
    "wof:name":"All Season Lawn Care & Maint",
    "wof:placetype":"venue"
},
  "geometry": {"coordinates":[-80.355733,39.284673],"type":"Point"}
}