{
  "type": "Feature",
  "properties": {
    "addr:full":"400 S Washington St Berkeley Springs WV 25411",
    "addr:housenumber":"400",
    "addr:postcode":"25411",
    "addr:street":"S Washington St",
    "iso:country":"US",
    "sg:address":"400 S Washington St",
    "sg:city":"Berkeley Springs",
    "sg:classifiers":[
        {
            "category":"Personal",
            "type":"Services"
        }
    ],
    "sg:phone":"+1 304 258 5711",
    "sg:postcode":"25411",
    "sg:province":"WV",
    "wof:name":"Tropical Rayz",
    "wof:placetype":"venue"
},
  "geometry": {"coordinates":[-78.229467,39.624424],"type":"Point"}
}