{
  "type": "Feature",
  "properties": {
    "addr:full":"1218 5th Ave Huntington WV 25701",
    "addr:housenumber":"1218",
    "addr:postcode":"25701",
    "addr:street":"5Th Ave",
    "iso:country":"US",
    "sg:address":"1218 5th Ave",
    "sg:city":"Huntington",
    "sg:classifiers":[
        {
            "category":"Health Services",
            "subcategory":"Health Practitioner",
            "type":"Services"
        }
    ],
    "sg:phone":"+1 304 525 9959",
    "sg:postcode":"25701",
    "sg:province":"WV",
    "sg:tags":[
        "psychologist"
    ],
    "wof:name":"Argus Psychological Services",
    "wof:placetype":"venue"
},
  "geometry": {"coordinates":[-82.43685600000001,38.420606],"type":"Point"}
}