{
  "type": "Feature",
  "properties": {
    "iso:country":"US",
    "sg:address":"406 Washington St W",
    "sg:city":"Charleston",
    "sg:classifiers":[
        {
            "category":"Shopping",
            "subcategory":"Pharmacy",
            "type":"Retail Goods"
        }
    ],
    "sg:phone":"+1 304 343 8807",
    "sg:postcode":"25302",
    "sg:province":"WV",
    "sg:tags":[
        "drug",
        "store"
    ],
    "wof:name":"Rite Aid",
    "wof:placetype":"venue"
},
  "geometry": {"coordinates":[-81.641507,38.362091],"type":"Point"}
}