{
  "type": "Feature",
  "properties": {
    "iso:country":"US",
    "sg:address":"1407 Washington Blvd",
    "sg:city":"Belpre",
    "sg:classifiers":[
        {
            "category":"Shopping",
            "subcategory":"Pharmacy",
            "type":"Retail Goods"
        },
        {
            "category":"Shopping",
            "subcategory":"Gifts & Souvenirs",
            "type":"Retail Goods"
        }
    ],
    "sg:phone":"+1 740 423 9561",
    "sg:postcode":"45714",
    "sg:province":"OH",
    "sg:tags":[
        "shop"
    ],
    "wof:name":"Fruth Pharmacy 15",
    "wof:placetype":"venue"
},
  "geometry": {"coordinates":[-81.59276300000001,39.276449],"type":"Point"}
}