{
  "type": "Feature",
  "properties": {
    "iso:country":"US",
    "sg:address":"1142 S Bridge St",
    "sg:city":"New Martinsville",
    "sg:classifiers":[
        {
            "category":"Restaurant",
            "type":"Food & Drink"
        }
    ],
    "sg:menulink":"http://www.allmenus.com/wv/new-martinsville/139696-sicilias-pizzeria/menu/",
    "sg:phone":"+1 304 455 1911",
    "sg:postcode":"26155",
    "sg:province":"WV",
    "sg:tags":[
        "wrap",
        "american",
        "sandwich",
        "pizza"
    ],
    "wof:name":"Sicilia's Pizzeria",
    "wof:placetype":"venue"
},
  "geometry": {"coordinates":[-80.85863000000001,39.655333],"type":"Point"}
}