{
  "type": "Feature",
  "properties": {
    "iso:country":"US",
    "sg:address":"2001 Bluefield Ave",
    "sg:city":"Bluefield",
    "sg:classifiers":[
        {
            "category":"Food & Beverages",
            "subcategory":"Groceries & Convenience Stores",
            "type":"Retail Goods"
        }
    ],
    "sg:phone":"+1 304 325 3379",
    "sg:postcode":"24701",
    "sg:province":"WV",
    "wof:name":"Joy Foods Inc",
    "wof:placetype":"venue"
},
  "geometry": {"coordinates":[-81.24596699999999,37.260732],"type":"Point"}
}