{
  "type": "Feature",
  "properties": {
    "addr:full":"751 Pleasant Hill Rd Morgantown WV 26508",
    "addr:housenumber":"751",
    "addr:postcode":"26508",
    "addr:street":"Pleasant Hill Rd",
    "iso:country":"US",
    "sg:address":"751 Pleasant Hill Rd",
    "sg:city":"Morgantown",
    "sg:classifiers":[
        {
            "category":"Health Services",
            "subcategory":"Doctor",
            "type":"Services"
        }
    ],
    "sg:phone":"+1 304 598 4835",
    "sg:postcode":"26508",
    "sg:province":"WV",
    "sg:tags":[
        "physician",
        "surgeon"
    ],
    "wof:name":"Kathaleen C Perkins MD",
    "wof:placetype":"venue"
},
  "geometry": {"coordinates":[-79.904292,39.622193],"type":"Point"}
}