{
  "type": "Feature",
  "properties": {
    "iso:country":"US",
    "sg:address":"101 6th Ave",
    "sg:city":"Huntington",
    "sg:classifiers":[
        {
            "category":"Shopping",
            "subcategory":"Pharmacy",
            "type":"Retail Goods"
        }
    ],
    "sg:phone":"+1 304 697 2151",
    "sg:postcode":"25701",
    "sg:province":"WV",
    "wof:name":"Fruth Pharmacy 2",
    "wof:placetype":"venue"
},
  "geometry": {"coordinates":[-82.455612,38.415889],"type":"Point"}
}