{
  "type": "Feature",
  "properties": {
    "iso:country":"US",
    "sg:address":"156 Spring St",
    "sg:city":"Charleston",
    "sg:classifiers":[
        {
            "category":"Wholesale",
            "subcategory":"Auto Parts",
            "type":"Manufacturing & Wholesale Goods"
        }
    ],
    "sg:phone":"+1 304 345 0975",
    "sg:postcode":"25301",
    "sg:province":"WV",
    "sg:tags":[
        "automotive",
        "glass"
    ],
    "wof:name":"Pilkington North America Inc",
    "wof:placetype":"venue"
},
  "geometry": {"coordinates":[-81.627223,38.35696],"type":"Point"}
}