{
  "type": "Feature",
  "properties": {
    "iso:country":"US",
    "sg:address":"1609 Washington St E",
    "sg:city":"Charleston",
    "sg:classifiers":[
        {
            "category":"Restaurant",
            "type":"Food & Drink"
        }
    ],
    "sg:menulink":"http://www.allmenus.com/wv/belle/139714-sicilias-pizzeria/menu/",
    "sg:phone":"+1 304 346 3468",
    "sg:postcode":"25311",
    "sg:province":"WV",
    "sg:tags":[
        "wrap",
        "american",
        "sandwich",
        "pizza"
    ],
    "wof:name":"Sicilia's Pizzeria",
    "wof:placetype":"venue"
},
  "geometry": {"coordinates":[-81.61627300000001,38.340367],"type":"Point"}
}