{
  "type": "Feature",
  "properties": {
    "iso:country":"US",
    "sg:address":"316 N 2nd Ave",
    "sg:city":"Paden City",
    "sg:classifiers":[
        {
            "category":"Shopping",
            "subcategory":"Musical Instruments",
            "type":"Retail Goods"
        }
    ],
    "sg:phone":"+1 304 337 9360",
    "sg:postcode":"26159",
    "sg:province":"WV",
    "wof:name":"Shepherd Piano",
    "wof:placetype":"venue"
},
  "geometry": {"coordinates":[-80.929525,39.608281],"type":"Point"}
}