{
  "type": "Feature",
  "properties": {
    "iso:country":"US",
    "sg:address":"196 Spruce Ln",
    "sg:city":"Poca",
    "sg:classifiers":[
        {
            "category":"Wholesale",
            "subcategory":"Machinery & Supplies",
            "type":"Manufacturing & Wholesale Goods"
        }
    ],
    "sg:phone":"+1 304 755 4804",
    "sg:postcode":"25159",
    "sg:province":"WV",
    "sg:tags":[
        "equipment",
        "industrial"
    ],
    "wof:name":"Micro Motion Inc",
    "wof:placetype":"venue"
},
  "geometry": {"coordinates":[-81.802249,38.466996],"type":"Point"}
}