{
  "type": "Feature",
  "properties": {
    "addr:full":"11 Lincoln Plz Branchland WV 25506",
    "addr:housenumber":"11",
    "addr:postcode":"25506",
    "addr:street":"Lincoln Plz",
    "iso:country":"US",
    "sg:address":"11 Lincoln Plz",
    "sg:city":"Branchland",
    "sg:classifiers":[
        {
            "category":"Local Transit",
            "type":"Transportation"
        }
    ],
    "sg:phone":"+1 304 824 2944",
    "sg:postcode":"25506",
    "sg:province":"WV",
    "sg:tags":[
        "bus",
        "line"
    ],
    "wof:name":"Tri River Transit Authority",
    "wof:placetype":"venue"
},
  "geometry": {"coordinates":[-82.19971099999999,38.269728],"type":"Point"}
}