{
  "type": "Feature",
  "properties": {
    "addr:full":"1116 Mercer St Princeton WV 24740",
    "addr:housenumber":"1116",
    "addr:postcode":"24740",
    "addr:street":"Mercer St",
    "iso:country":"US",
    "sg:address":"1116 Mercer St",
    "sg:city":"Princeton",
    "sg:classifiers":[
        {
            "category":"Organizations",
            "subcategory":"Religious Organization",
            "type":"Services"
        }
    ],
    "sg:phone":"+1 304 425 8174",
    "sg:postcode":"24740",
    "sg:province":"WV",
    "sg:tags":[
        "church"
    ],
    "wof:name":"First Baptist Church",
    "wof:placetype":"venue"
},
  "geometry": {"coordinates":[-81.09765400000001,37.368648],"type":"Point"}
}