{
  "type": "Feature",
  "properties": {
    "addr:full":"7864 Winchester Ave Inwood WV 25428",
    "addr:housenumber":"7864",
    "addr:postcode":"25428",
    "addr:street":"Winchester Ave",
    "iso:country":"US",
    "sg:address":"7864 Winchester Ave",
    "sg:city":"Inwood",
    "sg:classifiers":[
        {
            "category":"Education",
            "subcategory":"School",
            "type":"Public Place"
        }
    ],
    "sg:phone":"+1 304 229 1990",
    "sg:postcode":"25428",
    "sg:province":"WV",
    "sg:tags":[
        "high",
        "middle",
        "elementary"
    ],
    "wof:name":"Inwood Primary School",
    "wof:placetype":"venue"
},
  "geometry": {"coordinates":[-78.037372,39.361098],"type":"Point"}
}