{
  "type": "Feature",
  "properties": {
    "iso:country":"US",
    "sg:address":"308 Walnut St",
    "sg:city":"Ravenswood",
    "sg:classifiers":[
        {
            "category":"Sports & Exercise",
            "subcategory":"Gym",
            "type":"Entertainment"
        }
    ],
    "sg:phone":"+1 304 273 9500",
    "sg:postcode":"26164",
    "sg:province":"WV",
    "sg:tags":[
        "club",
        "health",
        "studio",
        "gymnasium"
    ],
    "wof:name":"Curves For Women",
    "wof:placetype":"venue"
},
  "geometry": {"coordinates":[-81.75961599999999,38.948361],"type":"Point"}
}