{
  "type": "Feature",
  "properties": {
    "iso:country":"US",
    "sg:address":"166 Kruger St",
    "sg:city":"Wheeling",
    "sg:classifiers":[
        {
            "category":"Retail",
            "subcategory":"Funeral Services",
            "type":"Services"
        }
    ],
    "sg:phone":"+1 304 242 2311",
    "sg:postcode":"26003",
    "sg:province":"WV",
    "sg:tags":[
        "director"
    ],
    "wof:name":"Kepner Funeral Homes",
    "wof:placetype":"venue"
},
  "geometry": {"coordinates":[-80.657946,40.038869],"type":"Point"}
}