{
  "type": "Feature",
  "properties": {
    "iso:country":"US",
    "sg:address":"1371 Indian Rock Rd",
    "sg:city":"Reedsville",
    "sg:classifiers":[
        {
            "category":"Home & Garden",
            "subcategory":"Building Materials",
            "type":"Retail Goods"
        },
        {
            "category":"Building & Trades",
            "subcategory":"Construction",
            "type":"Services"
        }
    ],
    "sg:phone":"+1 304 864 2261",
    "sg:postcode":"26547",
    "sg:province":"WV",
    "sg:tags":[
        "fence-sales",
        "fence",
        "contractor"
    ],
    "wof:name":"Goldstrom Fencing",
    "wof:placetype":"venue"
},
  "geometry": {"coordinates":[-79.779734,39.524493],"type":"Point"}
}