{
  "type": "Feature",
  "properties": {
    "iso:country":"US",
    "sg:address":"1310 Oakhurst Ave",
    "sg:city":"Parkersburg",
    "sg:classifiers":[
        {
            "category":"Retail",
            "subcategory":"Auto Repair",
            "type":"Services"
        }
    ],
    "sg:phone":"+1 304 485 7563",
    "sg:postcode":"26101",
    "sg:province":"WV",
    "sg:tags":[
        "automobile",
        "customizing"
    ],
    "wof:name":"Arts Customs Shop",
    "wof:placetype":"venue"
},
  "geometry": {"coordinates":[-81.539551,39.265173],"type":"Point"}
}