{
  "type": "Feature",
  "properties": {
    "iso:country":"US",
    "sg:address":"1100 Avalon Rd",
    "sg:city":"Fairmont",
    "sg:classifiers":[
        {
            "category":"Real Estate",
            "subcategory":"Real Estate Agent",
            "type":"Services"
        }
    ],
    "sg:phone":"+1 304 366 3692",
    "sg:postcode":"26554",
    "sg:province":"WV",
    "sg:tags":[
        "investment"
    ],
    "wof:name":"Mann Vest",
    "wof:placetype":"venue"
},
  "geometry": {"coordinates":[-80.159255,39.476422],"type":"Point"}
}