{
  "type": "Feature",
  "properties": {
    "iso:country":"US",
    "sg:address":"109 E 3rd Ave",
    "sg:city":"Ranson",
    "sg:classifiers":[
        {
            "category":"Personal",
            "subcategory":"Beauty Salon",
            "type":"Services"
        }
    ],
    "sg:phone":"+1 304 724 7001",
    "sg:postcode":"25438",
    "sg:province":"WV",
    "wof:name":"Salon W",
    "wof:placetype":"venue"
},
  "geometry": {"coordinates":[-77.859532,39.29462],"type":"Point"}
}