{
  "type": "Feature",
  "properties": {
    "iso:country":"US",
    "sg:address":"33 Hidden Valley Rd",
    "sg:city":"Chapmanville",
    "sg:classifiers":[
        {
            "category":"Professional",
            "subcategory":"Employment Agencies",
            "type":"Services"
        }
    ],
    "sg:phone":"+1 304 342 3210",
    "sg:postcode":"25508",
    "sg:province":"WV",
    "sg:tags":[
        "help",
        "contractor"
    ],
    "wof:name":"Volt Telecom Group",
    "wof:placetype":"venue"
},
  "geometry": {"coordinates":[-82.02435699999999,37.949487],"type":"Point"}
}