{
  "type": "Feature",
  "properties": {
    "addr:full":"210 Virginia St W Charleston WV 25302",
    "addr:housenumber":"210",
    "addr:postcode":"25302",
    "addr:street":"Virginia St W",
    "iso:country":"US",
    "sg:address":"210 Virginia St W",
    "sg:city":"Charleston",
    "sg:classifiers":[
        {
            "category":"Health Services",
            "subcategory":"Clinic",
            "type":"Services"
        }
    ],
    "sg:phone":"+1 304 342 2500",
    "sg:postcode":"25302",
    "sg:province":"WV",
    "sg:tags":[
        "banks",
        "blood",
        "center"
    ],
    "wof:name":"Alpha Therapeutic Corp",
    "wof:placetype":"venue"
},
  "geometry": {"coordinates":[-81.646249,38.35884],"type":"Point"}
}