{
  "type": "Feature",
  "properties": {
    "iso:country":"US",
    "sg:address":"1008 Bridge Rd",
    "sg:city":"Charleston",
    "sg:classifiers":[
        {
            "category":"Shopping",
            "subcategory":"Clothing, Apparel, & Fashions",
            "type":"Retail Goods"
        }
    ],
    "sg:phone":"+1 304 346 7855",
    "sg:postcode":"25314",
    "sg:province":"WV",
    "sg:tags":[
        "wear"
    ],
    "wof:name":"Twice As Nice",
    "wof:placetype":"venue"
},
  "geometry": {"coordinates":[-81.642613,38.340693],"type":"Point"}
}