{
  "type": "Feature",
  "properties": {
    "iso:country":"US",
    "sg:address":"214 D St",
    "sg:city":"Charleston",
    "sg:classifiers":[
        {
            "category":"Recreation",
            "type":"Entertainment"
        }
    ],
    "sg:phone":"+1 304 744 9298",
    "sg:postcode":"25303",
    "sg:province":"WV",
    "sg:tags":[
        "club",
        "membership"
    ],
    "wof:name":"Womens Club South Charlston",
    "wof:placetype":"venue"
},
  "geometry": {"coordinates":[-81.693955,38.365237],"type":"Point"}
}