{
  "type": "Feature",
  "properties": {
    "iso:country":"US",
    "sg:address":"3515 Staunton Ave SE",
    "sg:city":"Charleston",
    "sg:classifiers":[
        {
            "category":"Insurance",
            "subcategory":"Insurance Agent",
            "type":"Services"
        }
    ],
    "sg:phone":"+1 304 926 6662",
    "sg:postcode":"25304",
    "sg:province":"WV",
    "wof:name":"White Insurance & Assoc",
    "wof:placetype":"venue"
},
  "geometry": {"coordinates":[-81.59698299999999,38.329955],"type":"Point"}
}