{
  "type": "Feature",
  "properties": {
    "addr:full":"117 Limestone Ln Martinsburg WV 25403",
    "addr:housenumber":"117",
    "addr:postcode":"25403",
    "addr:street":"Limestone Ln",
    "iso:country":"US",
    "sg:address":"117 Limestone Ln",
    "sg:city":"Martinsburg",
    "sg:classifiers":[
        {
            "category":"Wholesale",
            "subcategory":"Construction Materials",
            "type":"Manufacturing & Wholesale Goods"
        }
    ],
    "sg:phone":"+1 304 229 0365",
    "sg:postcode":"25403",
    "sg:province":"WV",
    "sg:tags":[
        "equipment",
        "masonry",
        "supply"
    ],
    "wof:name":"Stuart M Perry Incorporated",
    "wof:placetype":"venue"
},
  "geometry": {"coordinates":[-77.955956,39.549243],"type":"Point"}
}