{
  "type": "Feature",
  "properties": {
    "iso:country":"US",
    "sg:address":"4421 16th St",
    "sg:city":"Huntington",
    "sg:classifiers":[
        {
            "category":"Organizations",
            "subcategory":"Religious Organization",
            "type":"Services"
        }
    ],
    "sg:phone":"+1 304 736 5853",
    "sg:postcode":"25701",
    "sg:province":"WV",
    "sg:tags":[
        "church"
    ],
    "wof:name":"Dillon Chapel Methodist Church",
    "wof:placetype":"venue"
},
  "geometry": {"coordinates":[-82.336083,38.380073],"type":"Point"}
}