{
  "type": "Feature",
  "properties": {
    "iso:country":"US",
    "sg:address":"6083 Sissonville Dr",
    "sg:city":"Charleston",
    "sg:classifiers":[
        {
            "category":"Food & Beverages",
            "subcategory":"Groceries & Convenience Stores",
            "type":"Retail Goods"
        }
    ],
    "sg:phone":"+1 304 984 9410",
    "sg:postcode":"25312",
    "sg:province":"WV",
    "sg:tags":[
        "grocer"
    ],
    "wof:name":"Buddy B's Fruit & Grocery Mkt",
    "wof:placetype":"venue"
},
  "geometry": {"coordinates":[-81.66945,38.467459],"type":"Point"}
}