{
  "type": "Feature",
  "properties": {
    "iso:country":"US",
    "sg:address":"201 Washington St",
    "sg:city":"Ravenswood",
    "sg:classifiers":[
        {
            "category":"Restaurant",
            "type":"Food & Drink"
        }
    ],
    "sg:phone":"+1 304 273 9367",
    "sg:postcode":"26164",
    "sg:province":"WV",
    "sg:tags":[
        "eating"
    ],
    "wof:name":"Ginos Pizza & Spaghetti House",
    "wof:placetype":"venue"
},
  "geometry": {"coordinates":[-81.76155799999999,38.948926],"type":"Point"}
}