{
  "type": "Feature",
  "properties": {
    "iso:country":"US",
    "sg:address":"405 W Prince St",
    "sg:city":"Beckley",
    "sg:classifiers":[
        {
            "category":"Shopping",
            "type":"Retail Goods"
        }
    ],
    "sg:phone":"+1 304 253 3389",
    "sg:postcode":"25801",
    "sg:province":"WV",
    "sg:tags":[
        "feed",
        "farm",
        "hardware",
        "supply"
    ],
    "sg:website":"www.beckleyfeed.com",
    "wof:name":"Beckley Feed & Hardware Co",
    "wof:placetype":"venue"
},
  "geometry": {"coordinates":[-81.194214,37.77645],"type":"Point"}
}