{
  "type": "Feature",
  "properties": {
    "addr:full":"1305 Washington St W Charleston WV 25302",
    "addr:housenumber":"1305",
    "addr:postcode":"25302",
    "addr:street":"Washington St W",
    "iso:country":"US",
    "sg:address":"1305 Washington St W",
    "sg:city":"Charleston",
    "sg:classifiers":[
        {
            "category":"Education",
            "subcategory":"Dance Studio",
            "type":"Public Place"
        }
    ],
    "sg:phone":"+1 304 343 7750",
    "sg:postcode":"25302",
    "sg:province":"WV",
    "sg:tags":[
        "instruction",
        "dancing"
    ],
    "wof:name":"Dance Zone",
    "wof:placetype":"venue"
},
  "geometry": {"coordinates":[-81.657725,38.370217],"type":"Point"}
}