{
  "type": "Feature",
  "properties": {
    "addr:full":"140 Sharon Dr Weirton WV 26062",
    "addr:housenumber":"140",
    "addr:postcode":"26062",
    "addr:street":"Sharon Dr",
    "iso:country":"US",
    "sg:address":"140 Sharon Dr",
    "sg:city":"Weirton",
    "sg:classifiers":[
        {
            "category":"Restaurant",
            "type":"Food & Drink"
        }
    ],
    "sg:phone":"+1 304 723 4437",
    "sg:postcode":"26062",
    "sg:province":"WV",
    "sg:tags":[
        "eating"
    ],
    "wof:name":"Triple 7s Cafe & Slots LLC",
    "wof:placetype":"venue"
},
  "geometry": {"coordinates":[-80.54174500000001,40.424866],"type":"Point"}
}