{
  "type": "Feature",
  "properties": {
    "iso:country":"US",
    "sg:address":"1 Players Club Dr",
    "sg:city":"Charleston",
    "sg:classifiers":[
        {
            "category":"Government",
            "subcategory":"Court House",
            "type":"Public Place"
        }
    ],
    "sg:phone":"+1 304 558 6100",
    "sg:postcode":"25311",
    "sg:province":"WV",
    "sg:tags":[
        "state",
        "counsel"
    ],
    "wof:name":"State Of WV Worker Compensatio",
    "wof:placetype":"venue"
},
  "geometry": {"coordinates":[-81.60347899999999,38.339057],"type":"Point"}
}