{
  "type": "Feature",
  "properties": {
    "iso:country":"US",
    "sg:address":"5932 Sissonville Dr",
    "sg:city":"Charleston",
    "sg:classifiers":[
        {
            "category":"Personal",
            "type":"Services"
        }
    ],
    "sg:phone":"+1 304 984 1488",
    "sg:postcode":"25312",
    "sg:province":"WV",
    "sg:tags":[
        "therapist",
        "massage"
    ],
    "wof:name":"Almost Heaven Therapeutic Mssg",
    "wof:placetype":"venue"
},
  "geometry": {"coordinates":[-81.666432,38.463993],"type":"Point"}
}