{
  "type": "Feature",
  "properties": {
    "iso:country":"US",
    "sg:address":"600 Ann St",
    "sg:city":"Parkersburg",
    "sg:classifiers":[
        {
            "category":"Professional",
            "subcategory":"Computer Services",
            "type":"Services"
        }
    ],
    "sg:phone":"+1 304 485 0845",
    "sg:postcode":"26101",
    "sg:province":"WV",
    "sg:tags":[
        "consultant",
        "designer"
    ],
    "sg:website":"www.fwnco.com",
    "wof:name":"F W Newton Co",
    "wof:placetype":"venue"
},
  "geometry": {"coordinates":[-81.560942,39.268301],"type":"Point"}
}