{
  "type": "Feature",
  "properties": {
    "addr:full":"207 E 5th Ave Ranson WV 25438",
    "addr:housenumber":"207",
    "addr:postcode":"25438",
    "addr:street":"E 5Th Ave",
    "iso:country":"US",
    "sg:address":"207 E 5th Ave",
    "sg:city":"Ranson",
    "sg:classifiers":[
        {
            "category":"Health Services",
            "subcategory":"Doctor",
            "type":"Services"
        }
    ],
    "sg:phone":"+1 304 725 6777",
    "sg:postcode":"25438",
    "sg:province":"WV",
    "sg:tags":[
        "physician",
        "pediatrics-emergency",
        "pediatrics",
        "surgeons",
        "medicine",
        "surgeon"
    ],
    "wof:name":"Jefferson Med Tysom Pdtricians",
    "wof:placetype":"venue"
},
  "geometry": {"coordinates":[-77.857916,39.297104],"type":"Point"}
}