{
  "type": "Feature",
  "properties": {
    "iso:country":"US",
    "sg:address":"206 Lovell Dr",
    "sg:city":"Charleston",
    "sg:classifiers":[
        {
            "category":"Building & Trades",
            "subcategory":"Construction",
            "type":"Services"
        }
    ],
    "sg:phone":"+1 304 344 0455",
    "sg:postcode":"25302",
    "sg:province":"WV",
    "sg:tags":[
        "concrete",
        "contractor"
    ],
    "wof:name":"Drumheler Painting",
    "wof:placetype":"venue"
},
  "geometry": {"coordinates":[-81.655068,38.36228],"type":"Point"}
}