{
  "type": "Feature",
  "properties": {
    "iso:country":"US",
    "sg:address":"1005 Chestnut St",
    "sg:city":"Charleston",
    "sg:classifiers":[
        {
            "category":"Building & Trades",
            "subcategory":"Plumbing",
            "type":"Services"
        }
    ],
    "sg:phone":"+1 304 768 9440",
    "sg:postcode":"25309",
    "sg:province":"WV",
    "sg:tags":[
        "family",
        "heating",
        "general",
        "plumbing",
        "home",
        "contractor"
    ],
    "wof:name":"A-Ace Plumbing",
    "wof:placetype":"venue"
},
  "geometry": {"coordinates":[-81.72901299999999,38.343828],"type":"Point"}
}