{
  "type": "Feature",
  "properties": {
    "iso:country":"US",
    "sg:address":"1370 Brickyard Rd",
    "sg:city":"Princeton",
    "sg:classifiers":[
        {
            "category":"Manufacturing",
            "subcategory":"Buildings",
            "type":"Manufacturing & Wholesale Goods"
        },
        {
            "category":"Building & Trades",
            "subcategory":"Construction",
            "type":"Services"
        }
    ],
    "sg:phone":"+1 304 425 8611",
    "sg:postcode":"24740",
    "sg:province":"WV",
    "sg:tags":[
        "home",
        "builder",
        "contractor"
    ],
    "wof:name":"Qualified Home Improvements",
    "wof:placetype":"venue"
},
  "geometry": {"coordinates":[-81.075275,37.407848],"type":"Point"}
}