{
  "type": "Feature",
  "properties": {
    "iso:country":"US",
    "sg:address":"1050 Maple Dr",
    "sg:city":"Morgantown",
    "sg:classifiers":[
        {
            "category":"Home & Garden",
            "subcategory":"Hardware",
            "type":"Retail Goods"
        }
    ],
    "sg:phone":"+1 304 599 0803",
    "sg:postcode":"26505",
    "sg:province":"WV",
    "wof:name":"Ace Hardware",
    "wof:placetype":"venue"
},
  "geometry": {"coordinates":[-79.94826,39.656705],"type":"Point"}
}