{
  "type": "Feature",
  "properties": {
    "iso:country":"US",
    "sg:address":"264 New Hope Rd",
    "sg:city":"Princeton",
    "sg:classifiers":[
        {
            "category":"Organizations",
            "subcategory":"Religious Organization",
            "type":"Services"
        }
    ],
    "sg:phone":"+1 304 425 0651",
    "sg:postcode":"24740",
    "sg:province":"WV",
    "wof:name":"Covenant Community Church",
    "wof:placetype":"venue"
},
  "geometry": {"coordinates":[-81.122625,37.363185],"type":"Point"}
}