{
  "type": "Feature",
  "properties": {
    "addr:full":"244 7th Ave Charleston WV 25303",
    "addr:housenumber":"244",
    "addr:postcode":"25303",
    "addr:street":"7Th Ave",
    "iso:country":"US",
    "sg:address":"244 7th Ave",
    "sg:city":"Charleston",
    "sg:classifiers":[
        {
            "category":"Restaurant",
            "type":"Food & Drink"
        }
    ],
    "sg:phone":"+1 304 744 9244",
    "sg:postcode":"25303",
    "sg:province":"WV",
    "sg:tags":[
        "drinking",
        "eating"
    ],
    "wof:name":"Romeo's Grill",
    "wof:placetype":"venue"
},
  "geometry": {"coordinates":[-81.69654800000001,38.368494],"type":"Point"}
}