{
  "type": "Feature",
  "properties": {
    "addr:full":"1420 Fairmont Rd Morgantown WV 26501",
    "addr:housenumber":"1420",
    "addr:postcode":"26501",
    "addr:street":"Fairmont Rd",
    "iso:country":"US",
    "sg:address":"1420 Fairmont Rd",
    "sg:city":"Morgantown",
    "sg:classifiers":[
        {
            "category":"Education",
            "subcategory":"School",
            "type":"Public Place"
        }
    ],
    "sg:phone":"+1 304 278 5584",
    "sg:postcode":"26501",
    "sg:province":"WV",
    "wof:name":"Arnettsville Elementary School",
    "wof:placetype":"venue"
},
  "geometry": {"coordinates":[-79.99018100000001,39.623464],"type":"Point"}
}