{
  "type": "Feature",
  "properties": {
    "addr:full":"610 Glenmore Loop Elkins WV 26241",
    "addr:housenumber":"610",
    "addr:postcode":"26241",
    "addr:street":"Glenmore Loop",
    "iso:country":"US",
    "sg:address":"610 Glenmore Loop",
    "sg:city":"Elkins",
    "sg:classifiers":[
        {
            "category":"Wholesale",
            "subcategory":"Office Equipment",
            "type":"Manufacturing & Wholesale Goods"
        }
    ],
    "sg:phone":"+1 304 636 0504",
    "sg:postcode":"26241",
    "sg:province":"WV",
    "sg:tags":[
        "machine",
        "duplicating",
        "copying"
    ],
    "wof:name":"Valley Business Systems",
    "wof:placetype":"venue"
},
  "geometry": {"coordinates":[-79.844426,38.900256],"type":"Point"}
}