{
  "type": "Feature",
  "properties": {
    "iso:country":"US",
    "sg:address":"53 Walnut Grove",
    "sg:city":"Washington",
    "sg:classifiers":[
        {
            "category":"Building & Trades",
            "subcategory":"Construction",
            "type":"Services"
        }
    ],
    "sg:phone":"+1 304 863 3999",
    "sg:postcode":"26181",
    "sg:province":"WV",
    "sg:tags":[
        "house"
    ],
    "wof:name":"Holdren Construction",
    "wof:placetype":"venue"
},
  "geometry": {"coordinates":[-81.67786599999999,39.235663],"type":"Point"}
}