{
  "type": "Feature",
  "properties": {
    "iso:country":"US",
    "sg:address":"64650 Patterson Hill Rd",
    "sg:city":"Bellaire",
    "sg:classifiers":[
        {
            "category":"Professional",
            "type":"Services"
        }
    ],
    "sg:phone":"+1 740 671 3267",
    "sg:postcode":"43906",
    "sg:province":"OH",
    "wof:name":"Dr Richard L Martin",
    "wof:placetype":"venue"
},
  "geometry": {"coordinates":[-80.78189500000001,40.028729],"type":"Point"}
}