{
  "type": "Feature",
  "properties": {
    "addr:full":"165 Diamond Cove Bridgeport WV 26330",
    "addr:housenumber":"165",
    "addr:postcode":"26330",
    "addr:street":"Diamond Cove",
    "iso:country":"US",
    "sg:address":"165 Diamond Cove",
    "sg:city":"Bridgeport",
    "sg:classifiers":[
        {
            "category":"Building & Trades",
            "subcategory":"Construction",
            "type":"Services"
        }
    ],
    "sg:phone":"+1 304 842 7894",
    "sg:postcode":"26330",
    "sg:province":"WV",
    "sg:tags":[
        "contractor"
    ],
    "wof:name":"White Lightning Contracting",
    "wof:placetype":"venue"
},
  "geometry": {"coordinates":[-80.21524599999999,39.32518],"type":"Point"}
}