{
  "type": "Feature",
  "properties": {
    "addr:full":"131 3rd St Marietta OH 45750",
    "addr:housenumber":"131",
    "addr:postcode":"45750",
    "addr:street":"3Rd St",
    "iso:country":"US",
    "sg:address":"131 3rd St",
    "sg:city":"Marietta",
    "sg:classifiers":[
        {
            "category":"Shopping",
            "subcategory":"Pharmacy",
            "type":"Retail Goods"
        }
    ],
    "sg:phone":"+1 740 373 2961",
    "sg:postcode":"45750",
    "sg:province":"OH",
    "wof:name":"CVS Pharmacy",
    "wof:placetype":"venue"
},
  "geometry": {"coordinates":[-81.44937899999999,39.412279],"type":"Point"}
}