{
  "type": "Feature",
  "properties": {
    "addr:full":"409 Sycamore St Ravenswood WV 26164",
    "addr:housenumber":"409",
    "addr:postcode":"26164",
    "addr:street":"Sycamore St",
    "iso:country":"US",
    "sg:address":"409 Sycamore St",
    "sg:city":"Ravenswood",
    "sg:classifiers":[
        {
            "category":"Education",
            "subcategory":"School",
            "type":"Public Place"
        }
    ],
    "sg:phone":"+1 304 273 5480",
    "sg:postcode":"26164",
    "sg:province":"WV",
    "wof:name":"Ravenswood Middle School",
    "wof:placetype":"venue"
},
  "geometry": {"coordinates":[-81.758398,38.950292],"type":"Point"}
}