{
  "type": "Feature",
  "properties": {
    "iso:country":"US",
    "sg:address":"2095 Mount Vernon Rd",
    "sg:city":"Hurricane",
    "sg:classifiers":[
        {
            "category":"Shopping",
            "subcategory":"Florist",
            "type":"Retail Goods"
        }
    ],
    "sg:phone":"+1 304 760 2114",
    "sg:postcode":"25526",
    "sg:province":"WV",
    "wof:name":"Sweet Expressions",
    "wof:placetype":"venue"
},
  "geometry": {"coordinates":[-81.946067,38.45545],"type":"Point"}
}