{
  "type": "Feature",
  "properties": {
    "iso:country":"US",
    "sg:address":"125 Kruger St",
    "sg:city":"Wheeling",
    "sg:classifiers":[
        {
            "category":"Organizations",
            "subcategory":"Religious Organization",
            "type":"Services"
        }
    ],
    "sg:phone":"+1 304 242 1206",
    "sg:postcode":"26003",
    "sg:province":"WV",
    "sg:tags":[
        "church"
    ],
    "wof:name":"Elm Grove United Methodist Chr",
    "wof:placetype":"venue"
},
  "geometry": {"coordinates":[-80.657855,40.040124],"type":"Point"}
}