{
  "type": "Feature",
  "properties": {
    "addr:full":"603 S Raleigh St Martinsburg WV 25401",
    "addr:housenumber":"603",
    "addr:postcode":"25401",
    "addr:street":"S Raleigh St",
    "iso:country":"US",
    "sg:address":"603 S Raleigh St",
    "sg:city":"Martinsburg",
    "sg:classifiers":[
        {
            "category":"Real Estate",
            "subcategory":"Real Estate Agent",
            "type":"Services"
        }
    ],
    "sg:phone":"+1 304 262 6900",
    "sg:postcode":"25401",
    "sg:province":"WV",
    "wof:name":"Triple State Realtors",
    "wof:placetype":"venue"
},
  "geometry": {"coordinates":[-77.970626,39.452172],"type":"Point"}
}