{
  "type": "Feature",
  "properties": {
    "addr:full":"1401 Saratoga Ave Morgantown WV 26505",
    "addr:housenumber":"1401",
    "addr:postcode":"26505",
    "addr:street":"Saratoga Ave",
    "iso:country":"US",
    "sg:address":"1401 Saratoga Ave",
    "sg:city":"Morgantown",
    "sg:classifiers":[
        {
            "category":"Professional",
            "subcategory":"Advertising",
            "type":"Services"
        }
    ],
    "sg:phone":"+1 304 599 5900",
    "sg:postcode":"26505",
    "sg:province":"WV",
    "sg:tags":[
        "agency"
    ],
    "sg:website":"www.btadigital.com",
    "wof:name":"Blaine Turner Advertising",
    "wof:placetype":"venue"
},
  "geometry": {"coordinates":[-79.986687,39.654128],"type":"Point"}
}