{
  "type": "Feature",
  "properties": {
    "addr:full":"1200 Mary St Parkersburg WV 26101",
    "addr:housenumber":"1200",
    "addr:postcode":"26101",
    "addr:street":"Mary St",
    "iso:country":"US",
    "sg:address":"1200 Mary St",
    "sg:city":"Parkersburg",
    "sg:classifiers":[
        {
            "category":"Organizations",
            "subcategory":"Community Association",
            "type":"Services"
        }
    ],
    "sg:phone":"+1 304 485 6435",
    "sg:postcode":"26101",
    "sg:province":"WV",
    "sg:tags":[
        "club"
    ],
    "wof:name":"Boy's Club Of Parkersburg Inc",
    "wof:placetype":"venue"
},
  "geometry": {"coordinates":[-81.543154,39.262484],"type":"Point"}
}