{
  "type": "Feature",
  "properties": {
    "iso:country":"US",
    "sg:address":"485 Colliers Way Ste K",
    "sg:city":"Weirton",
    "sg:classifiers":[
        {
            "category":"Health Services",
            "subcategory":"Doctor",
            "type":"Services"
        }
    ],
    "sg:phone":"+1 304 723 3360",
    "sg:postcode":"26062",
    "sg:province":"WV",
    "sg:tags":[
        "physician",
        "cardiology",
        "thoracic",
        "surgeons",
        "surgeon",
        "surgery",
        "cardiovascular"
    ],
    "wof:name":"Mannino, Stanley",
    "wof:placetype":"venue"
},
  "geometry": {"coordinates":[-80.53922,40.378319],"type":"Point"}
}