{
  "type": "Feature",
  "properties": {
    "iso:country":"US",
    "sg:address":"2110 Main St",
    "sg:city":"Wheeling",
    "sg:classifiers":[
        {
            "category":"Wholesale",
            "subcategory":"Machinery & Supplies",
            "type":"Manufacturing & Wholesale Goods"
        }
    ],
    "sg:phone":"+1 304 232 8280",
    "sg:postcode":"26003",
    "sg:province":"WV",
    "sg:tags":[
        "equipment",
        "industrial"
    ],
    "wof:name":"Wheeling Rubber Products Inc",
    "wof:placetype":"venue"
},
  "geometry": {"coordinates":[-80.72393700000001,40.061097],"type":"Point"}
}