{
  "type": "Feature",
  "properties": {
    "iso:country":"US",
    "sg:address":"98 Adams St",
    "sg:city":"Fairmont",
    "sg:classifiers":[
        {
            "category":"Shopping",
            "subcategory":"Florist",
            "type":"Retail Goods"
        }
    ],
    "sg:phone":"+1 304 363 2900",
    "sg:postcode":"26554",
    "sg:province":"WV",
    "wof:name":"Weber's Flowers Inc",
    "wof:placetype":"venue"
},
  "geometry": {"coordinates":[-80.14576099999999,39.483095],"type":"Point"}
}