{
  "type": "Feature",
  "properties": {
    "iso:country":"US",
    "sg:address":"145 Kenova Ave",
    "sg:city":"Wayne",
    "sg:classifiers":[
        {
            "category":"Organizations",
            "subcategory":"Non-profit Organization",
            "type":"Services"
        }
    ],
    "sg:phone":"+1 304 272 3466",
    "sg:postcode":"25570",
    "sg:province":"WV",
    "sg:tags":[
        "information",
        "alcoholism",
        "treatment"
    ],
    "wof:name":"Wayne Mental Health-Prestera",
    "wof:placetype":"venue"
},
  "geometry": {"coordinates":[-82.444698,38.224175],"type":"Point"}
}