{
  "type": "Feature",
  "properties": {
    "iso:country":"US",
    "sg:address":"635 N Jefferson St",
    "sg:city":"Lewisburg",
    "sg:classifiers":[
        {
            "category":"Travel",
            "subcategory":"Hotels & Motels",
            "type":"Entertainment"
        }
    ],
    "sg:phone":"+1 304 645 2345",
    "sg:postcode":"24901",
    "sg:province":"WV",
    "sg:tags":[
        "operation"
    ],
    "wof:name":"Days Inn",
    "wof:placetype":"venue"
},
  "geometry": {"coordinates":[-80.424121,37.820603],"type":"Point"}
}