{
  "type": "Feature",
  "properties": {
    "addr:full":"246 McEldowny Ave New Martinsville WV 26155",
    "addr:housenumber":"246",
    "addr:postcode":"26155",
    "addr:street":"Mceldowny Ave",
    "iso:country":"US",
    "sg:address":"246 McEldowny Ave",
    "sg:city":"New Martinsville",
    "sg:classifiers":[
        {
            "category":"Personal",
            "subcategory":"Beauty Salon",
            "type":"Services"
        }
    ],
    "sg:phone":"+1 304 455 1397",
    "sg:postcode":"26155",
    "sg:province":"WV",
    "sg:tags":[
        "manicuring"
    ],
    "wof:name":"Shearly Unique Family Hair",
    "wof:placetype":"venue"
},
  "geometry": {"coordinates":[-80.858823,39.647971],"type":"Point"}
}