{
  "type": "Feature",
  "properties": {
    "iso:country":"US",
    "sg:address":"857 Jakes Run Rd",
    "sg:city":"Fairview",
    "sg:classifiers":[
        {
            "category":"Personal",
            "subcategory":"Beauty Salon",
            "type":"Services"
        }
    ],
    "sg:phone":"+1 304 879 4040",
    "sg:postcode":"26541",
    "sg:province":"WV",
    "sg:tags":[
        "shop"
    ],
    "wof:name":"Saggs",
    "wof:placetype":"venue"
},
  "geometry": {"coordinates":[-80.152863,39.686063],"type":"Point"}
}