{
  "type": "Feature",
  "properties": {
    "iso:country":"US",
    "sg:address":"1408 Woodmere Dr",
    "sg:city":"Charleston",
    "sg:classifiers":[
        {
            "category":"Shopping",
            "subcategory":"Used Merchandise",
            "type":"Retail Goods"
        }
    ],
    "sg:phone":"+1 304 344 8422",
    "sg:postcode":"25314",
    "sg:province":"WV",
    "sg:tags":[
        "antique"
    ],
    "wof:name":"Faye's Bittersweet Sales",
    "wof:placetype":"venue"
},
  "geometry": {"coordinates":[-81.646681,38.323768],"type":"Point"}
}