{
  "type": "Feature",
  "properties": {
    "iso:country":"US",
    "sg:address":"227 Walker Dr",
    "sg:city":"Dunbar",
    "sg:classifiers":[
        {
            "category":"Health Services",
            "subcategory":"Doctor",
            "type":"Services"
        }
    ],
    "sg:phone":"+1 304 766 8905",
    "sg:postcode":"25064",
    "sg:province":"WV",
    "sg:tags":[
        "medical"
    ],
    "wof:name":"Angum Khan",
    "wof:placetype":"venue"
},
  "geometry": {"coordinates":[-81.723668,38.374827],"type":"Point"}
}