{
  "type": "Feature",
  "properties": {
    "iso:country":"US",
    "sg:address":"1500 Chapline St",
    "sg:city":"Wheeling",
    "sg:classifiers":[
        {
            "category":"Government",
            "subcategory":"Office",
            "type":"Public Place"
        }
    ],
    "sg:phone":"+1 304 234 3676",
    "sg:postcode":"26003",
    "sg:province":"WV",
    "sg:tags":[
        "finance"
    ],
    "wof:name":"Treasury Department",
    "wof:placetype":"venue"
},
  "geometry": {"coordinates":[-80.72080699999999,40.06404],"type":"Point"}
}