{
  "type": "Feature",
  "properties": {
    "iso:country":"US",
    "sg:address":"140 Harper Park Dr",
    "sg:city":"Beckley",
    "sg:classifiers":[
        {
            "category":"Restaurant",
            "type":"Food & Drink"
        }
    ],
    "sg:phone":"+1 304 253 1436",
    "sg:postcode":"25801",
    "sg:province":"WV",
    "sg:website":"www.texassteakhouse.com",
    "wof:name":"Texas Steakhouse",
    "wof:placetype":"venue"
},
  "geometry": {"coordinates":[-81.21778399999999,37.794052],"type":"Point"}
}