{
  "type": "Feature",
  "properties": {
    "addr:full":"748 S Fayette St Beckley WV 25801",
    "addr:housenumber":"748",
    "addr:postcode":"25801",
    "addr:street":"S Fayette St",
    "iso:country":"US",
    "sg:address":"748 S Fayette St",
    "sg:city":"Beckley",
    "sg:classifiers":[
        {
            "category":"Retail",
            "subcategory":"Funeral Services",
            "type":"Services"
        }
    ],
    "sg:phone":"+1 304 252 4115",
    "sg:postcode":"25801",
    "sg:province":"WV",
    "wof:name":"Ritchie & Johnson Fnrl Parlor",
    "wof:placetype":"venue"
},
  "geometry": {"coordinates":[-81.182812,37.768922],"type":"Point"}
}