{
  "type": "Feature",
  "properties": {
    "addr:full":"1005 Virginia Ave W Huntington WV 25704",
    "addr:housenumber":"1005",
    "addr:postcode":"25704",
    "addr:street":"Virginia Ave W",
    "iso:country":"US",
    "sg:address":"1005 Virginia Ave W",
    "sg:city":"Huntington",
    "sg:classifiers":[
        {
            "category":"Social Services",
            "type":"Services"
        }
    ],
    "sg:phone":"+1 304 523 9454",
    "sg:postcode":"25704",
    "sg:province":"WV",
    "sg:tags":[
        "counseling"
    ],
    "sg:website":"www.goodwillhunting.org",
    "wof:name":"Goodwill/Family Svc",
    "wof:placetype":"venue"
},
  "geometry": {"coordinates":[-82.476119,38.415062],"type":"Point"}
}