{
  "type": "Feature",
  "properties": {
    "iso:country":"US",
    "sg:address":"187 Old Leetown Pike",
    "sg:city":"Kearneysville",
    "sg:classifiers":[
        {
            "category":"Building & Trades",
            "subcategory":"Plumbing",
            "type":"Services"
        }
    ],
    "sg:phone":"+1 304 728 4972",
    "sg:postcode":"25430",
    "sg:province":"WV",
    "sg:tags":[
        "plumber",
        "industrial",
        "contractors-commercial"
    ],
    "wof:name":"Shenandoah Builders & Excavating",
    "wof:placetype":"venue"
},
  "geometry": {"coordinates":[-77.931275,39.345512],"type":"Point"}
}