{
  "type": "Feature",
  "properties": {
    "iso:country":"US",
    "sg:address":"122 East Rd",
    "sg:city":"Martinsburg",
    "sg:classifiers":[
        {
            "category":"Health Services",
            "subcategory":"Clinic",
            "type":"Services"
        }
    ],
    "sg:phone":"+1 304 596 2492",
    "sg:postcode":"25401",
    "sg:province":"WV",
    "wof:name":"East Ridge Health Systems",
    "wof:placetype":"venue"
},
  "geometry": {"coordinates":[-77.950762,39.473208],"type":"Point"}
}