{
  "type": "Feature",
  "properties": {
    "iso:country":"US",
    "sg:address":"8 Hale St",
    "sg:city":"Charleston",
    "sg:classifiers":[
        {
            "category":"Professional",
            "subcategory":"Lawyer & Legal Services",
            "type":"Services"
        }
    ],
    "sg:phone":"+1 304 346 1054",
    "sg:postcode":"25301",
    "sg:province":"WV",
    "wof:name":"Benedict Haid Farm",
    "wof:placetype":"venue"
},
  "geometry": {"coordinates":[-81.63516199999999,38.348496],"type":"Point"}
}