{
  "type": "Feature",
  "properties": {
    "iso:country":"US",
    "sg:address":"529 Fairmont Ave",
    "sg:city":"Fairmont",
    "sg:classifiers":[
        {
            "category":"Real Estate",
            "subcategory":"Real Estate Agent",
            "type":"Services"
        }
    ],
    "sg:phone":"+1 304 363 2721",
    "sg:postcode":"26554",
    "sg:province":"WV",
    "wof:name":"Iron Gate Properties Co",
    "wof:placetype":"venue"
},
  "geometry": {"coordinates":[-80.149428,39.47886],"type":"Point"}
}