{
  "type": "Feature",
  "properties": {
    "iso:country":"US",
    "sg:address":"1017 Jefferson St",
    "sg:city":"Follansbee",
    "sg:classifiers":[
        {
            "category":"Place Of Worship",
            "subcategory":"Church",
            "type":"Public Place"
        },
        {
            "category":"Place Of Worship",
            "type":"Public Place"
        }
    ],
    "sg:phone":"+1 304 527 2286",
    "sg:postcode":"26037",
    "sg:province":"WV",
    "sg:tags":[
        "churches-catholic-traditional",
        "churches-catholic"
    ],
    "wof:name":"Saint Anthony Church",
    "wof:placetype":"venue"
},
  "geometry": {"coordinates":[-80.59428699999999,40.329646],"type":"Point"}
}