{
  "type": "Feature",
  "properties": {
    "addr:full":"102 Sharon St Beckley WV 25801",
    "addr:housenumber":"102",
    "addr:postcode":"25801",
    "addr:street":"Sharon St",
    "iso:country":"US",
    "sg:address":"102 Sharon St",
    "sg:city":"Beckley",
    "sg:classifiers":[
        {
            "category":"Building & Trades",
            "subcategory":"Cleaning & Sanitation",
            "type":"Services"
        },
        {
            "category":"Building & Trades",
            "subcategory":"Construction",
            "type":"Services"
        }
    ],
    "sg:phone":"+1 304 255 5813",
    "sg:postcode":"25801",
    "sg:province":"WV",
    "sg:tags":[
        "fire",
        "restoration",
        "damage",
        "maintenance"
    ],
    "wof:name":"Pristine Cleaning Svc",
    "wof:placetype":"venue"
},
  "geometry": {"coordinates":[-81.232496,37.779376],"type":"Point"}
}