{
  "type": "Feature",
  "properties": {
    "iso:country":"US",
    "sg:address":"1038 Smith St",
    "sg:city":"Milton",
    "sg:classifiers":[
        {
            "category":"Social Services",
            "type":"Services"
        }
    ],
    "sg:phone":"+1 304 743 9238",
    "sg:postcode":"25541",
    "sg:province":"WV",
    "sg:tags":[
        "food",
        "banks"
    ],
    "wof:name":"ECCHO",
    "wof:placetype":"venue"
},
  "geometry": {"coordinates":[-82.132773,38.435531],"type":"Point"}
}