{
  "type": "Feature",
  "properties": {
    "iso:country":"US",
    "sg:address":"510 Haymond Hwy",
    "sg:city":"Clarksburg",
    "sg:classifiers":[
        {
            "category":"Professional",
            "type":"Services"
        }
    ],
    "sg:phone":"+1 304 622 6488",
    "sg:postcode":"26301",
    "sg:province":"WV",
    "wof:name":"Joseph M Minard",
    "wof:placetype":"venue"
},
  "geometry": {"coordinates":[-80.327862,39.271277],"type":"Point"}
}