{
  "type": "Feature",
  "properties": {
    "iso:country":"US",
    "sg:address":"170 Thompson Dr",
    "sg:city":"Bridgeport",
    "sg:classifiers":[
        {
            "category":"Wholesale",
            "subcategory":"Construction Materials",
            "type":"Manufacturing & Wholesale Goods"
        }
    ],
    "sg:phone":"+1 304 842 7910",
    "sg:postcode":"26330",
    "sg:province":"WV",
    "sg:tags":[
        "installs",
        "window",
        "siding",
        "kitchen"
    ],
    "wof:name":"Sears",
    "wof:placetype":"venue"
},
  "geometry": {"coordinates":[-80.271298,39.28438],"type":"Point"}
}