{
  "type": "Feature",
  "properties": {
    "iso:country":"US",
    "sg:address":"1332 Bland St",
    "sg:city":"Bluefield",
    "sg:classifiers":[
        {
            "category":"Professional",
            "subcategory":"Business Services",
            "type":"Services"
        }
    ],
    "sg:phone":"+1 304 325 3122",
    "sg:postcode":"24701",
    "sg:province":"WV",
    "sg:tags":[
        "interior",
        "consultant",
        "design",
        "decorator"
    ],
    "wof:name":"Interior Motives",
    "wof:placetype":"venue"
},
  "geometry": {"coordinates":[-81.220337,37.260062],"type":"Point"}
}