{
  "type": "Feature",
  "properties": {
    "iso:country":"US",
    "sg:address":"811 Washington St W",
    "sg:city":"Charleston",
    "sg:classifiers":[
        {
            "category":"Food & Beverages",
            "subcategory":"Groceries & Convenience Stores",
            "type":"Retail Goods"
        }
    ],
    "sg:phone":"+1 304 342 6451",
    "sg:postcode":"25302",
    "sg:province":"WV",
    "sg:tags":[
        "station",
        "gas"
    ],
    "wof:name":"Go-Mart 54",
    "wof:placetype":"venue"
},
  "geometry": {"coordinates":[-81.651113,38.367024],"type":"Point"}
}