{
  "type": "Feature",
  "properties": {
    "addr:full":"402 7th Ave Huntington WV 25701",
    "addr:housenumber":"402",
    "addr:postcode":"25701",
    "addr:street":"7Th Ave",
    "iso:country":"US",
    "sg:address":"402 7th Ave",
    "sg:city":"Huntington",
    "sg:classifiers":[
        {
            "category":"Social Services",
            "subcategory":"Adult Care",
            "type":"Services"
        }
    ],
    "sg:phone":"+1 304 525 6199",
    "sg:postcode":"25701",
    "sg:province":"WV",
    "sg:tags":[
        "residential",
        "facility"
    ],
    "wof:name":"Prestera Cntr Mental Hlth Svcs",
    "wof:placetype":"venue"
},
  "geometry": {"coordinates":[-82.449637,38.415558],"type":"Point"}
}