{
  "type": "Feature",
  "properties": {
    "addr:full":"117 Society Hill Rd Mineral Wells WV 26150",
    "addr:housenumber":"117",
    "addr:postcode":"26150",
    "addr:street":"Society Hill Rd",
    "iso:country":"US",
    "sg:address":"117 Society Hill Rd",
    "sg:city":"Mineral Wells",
    "sg:classifiers":[
        {
            "category":"Building & Trades",
            "subcategory":"Construction",
            "type":"Services"
        }
    ],
    "sg:phone":"+1 304 485 7711",
    "sg:postcode":"26150",
    "sg:province":"WV",
    "sg:tags":[
        "general",
        "contractor"
    ],
    "wof:name":"Welcome Additions Inc",
    "wof:placetype":"venue"
},
  "geometry": {"coordinates":[-81.501392,39.187777],"type":"Point"}
}