{
  "type": "Feature",
  "properties": {
    "addr:full":"108 Damon Ln Mount Hope WV 25880",
    "addr:housenumber":"108",
    "addr:postcode":"25880",
    "addr:street":"Damon Ln",
    "iso:country":"US",
    "sg:address":"108 Damon Ln",
    "sg:city":"Mount Hope",
    "sg:classifiers":[
        {
            "category":"Shopping",
            "subcategory":"Gifts & Souvenirs",
            "type":"Retail Goods"
        }
    ],
    "sg:phone":"+1 304 877 9624",
    "sg:postcode":"25880",
    "sg:province":"WV",
    "wof:name":"B P R Gifts",
    "wof:placetype":"venue"
},
  "geometry": {"coordinates":[-81.232949,37.855193],"type":"Point"}
}