{
  "type": "Feature",
  "properties": {
    "iso:country":"US",
    "sg:address":"194 Paynes Fork Rd",
    "sg:city":"Princeton",
    "sg:classifiers":[
        {
            "category":"Shopping",
            "subcategory":"Department Store",
            "type":"Retail Goods"
        }
    ],
    "sg:phone":"+1 304 431 3445",
    "sg:postcode":"24740",
    "sg:province":"WV",
    "wof:name":"Hi 5 Outlet",
    "wof:placetype":"venue"
},
  "geometry": {"coordinates":[-80.966306,37.345608],"type":"Point"}
}