{
  "type": "Feature",
  "properties": {
    "iso:country":"US",
    "sg:address":"74 Kingwood St Frnt",
    "sg:city":"Morgantown",
    "sg:classifiers":[
        {
            "category":"Real Estate",
            "subcategory":"Real Estate Operator",
            "type":"Services"
        }
    ],
    "sg:phone":"+1 304 292 7171",
    "sg:postcode":"26501",
    "sg:province":"WV",
    "sg:tags":[
        "apartment"
    ],
    "wof:name":"Pearand Corporation",
    "wof:placetype":"venue"
},
  "geometry": {"coordinates":[-79.952299,39.628036],"type":"Point"}
}