{
  "type": "Feature",
  "properties": {
    "iso:country":"US",
    "sg:address":"114 N Chester St",
    "sg:city":"New Cumberland",
    "sg:classifiers":[
        {
            "category":"Restaurant",
            "type":"Food & Drink"
        }
    ],
    "sg:phone":"+1 304 564 4300",
    "sg:postcode":"26047",
    "sg:province":"WV",
    "wof:name":"Corinne Subs",
    "wof:placetype":"venue"
},
  "geometry": {"coordinates":[-80.609544,40.498521],"type":"Point"}
}