{
  "type": "Feature",
  "properties": {
    "iso:country":"US",
    "sg:address":"141 Key Ave",
    "sg:city":"Wheeling",
    "sg:classifiers":[
        {
            "category":"Organizations",
            "subcategory":"Non-profit Organization",
            "type":"Services"
        }
    ],
    "sg:phone":"+1 304 242 5633",
    "sg:postcode":"26003",
    "sg:province":"WV",
    "wof:name":"St John's Home For Children",
    "wof:placetype":"venue"
},
  "geometry": {"coordinates":[-80.65455900000001,40.041174],"type":"Point"}
}