{
  "type": "Feature",
  "properties": {
    "addr:full":"297 Seneca Trl Ronceverte WV 24970",
    "addr:housenumber":"297",
    "addr:postcode":"24970",
    "addr:street":"Seneca Trl",
    "iso:country":"US",
    "sg:address":"297 Seneca Trl",
    "sg:city":"Ronceverte",
    "sg:classifiers":[
        {
            "category":"Restaurant",
            "type":"Food & Drink"
        }
    ],
    "sg:menulink":"http://www.allmenus.com/wv/central/71722-pizza-hut/menu/",
    "sg:phone":"+1 304 645 7501",
    "sg:postcode":"24970",
    "sg:province":"WV",
    "sg:tags":[
        "american",
        "pizza"
    ],
    "wof:name":"Pizza Hut",
    "wof:placetype":"venue"
},
  "geometry": {"coordinates":[-80.46210600000001,37.773216],"type":"Point"}
}