{
  "type": "Feature",
  "properties": {
    "iso:country":"US",
    "sg:address":"205 Monroe St",
    "sg:city":"Alderson",
    "sg:classifiers":[
        {
            "category":"Retail",
            "subcategory":"Funeral Services",
            "type":"Services"
        }
    ],
    "sg:phone":"+1 304 445 2700",
    "sg:postcode":"24910",
    "sg:province":"WV",
    "sg:tags":[
        "director"
    ],
    "wof:name":"Lobban Funeral Home",
    "wof:placetype":"venue"
},
  "geometry": {"coordinates":[-80.64208600000001,37.727223],"type":"Point"}
}