{
  "type": "Feature",
  "properties": {
    "iso:country":"US",
    "sg:address":"123 Beaver Plz",
    "sg:city":"Beaver",
    "sg:classifiers":[
        {
            "category":"Banks & Credit Unions",
            "subcategory":"Financial Services",
            "type":"Services"
        }
    ],
    "sg:phone":"+1 304 461 0017",
    "sg:postcode":"25813",
    "sg:province":"WV",
    "sg:website":"http://www.primerica.com/public/",
    "wof:name":"Primerica",
    "wof:placetype":"venue"
},
  "geometry": {"coordinates":[-81.127212,37.748632],"type":"Point"}
}