{
  "type": "Feature",
  "properties": {
    "iso:country":"US",
    "sg:address":"2118 Market St",
    "sg:city":"Wheeling",
    "sg:classifiers":[
        {
            "category":"Cinema",
            "subcategory":"Movie Theater",
            "type":"Entertainment"
        }
    ],
    "sg:phone":"+1 304 233 0820",
    "sg:postcode":"26003",
    "sg:province":"WV",
    "sg:tags":[
        "motion",
        "picture"
    ],
    "wof:name":"Town Gate Theatre",
    "wof:placetype":"venue"
},
  "geometry": {"coordinates":[-80.72335,40.060995],"type":"Point"}
}