{
  "type": "Feature",
  "properties": {
    "iso:country":"US",
    "sg:address":"2717 Roosevelt Ave",
    "sg:city":"St Albans",
    "sg:classifiers":[
        {
            "category":"Health Services",
            "subcategory":"Nursing And Care Facility",
            "type":"Services"
        }
    ],
    "sg:phone":"+1 304 722 4110",
    "sg:postcode":"25177",
    "sg:province":"WV",
    "sg:tags":[
        "personal",
        "home"
    ],
    "wof:name":"Vineyard's Care Home",
    "wof:placetype":"venue"
},
  "geometry": {"coordinates":[-81.79668700000001,38.381938],"type":"Point"}
}