{
  "type": "Feature",
  "properties": {
    "addr:full":"198 Ragland Rd Beckley WV 25801",
    "addr:housenumber":"198",
    "addr:postcode":"25801",
    "addr:street":"Ragland Rd",
    "iso:country":"US",
    "sg:address":"198 Ragland Rd",
    "sg:city":"Beckley",
    "sg:classifiers":[
        {
            "category":"Retail",
            "subcategory":"Veterinary Services",
            "type":"Services"
        }
    ],
    "sg:phone":"+1 304 253 4787",
    "sg:postcode":"25801",
    "sg:province":"WV",
    "wof:name":"Ben Dorsey",
    "wof:placetype":"venue"
},
  "geometry": {"coordinates":[-81.181443,37.806725],"type":"Point"}
}