{
  "type": "Feature",
  "properties": {
    "addr:full":"100 N Wickham Ave Princeton WV 24740",
    "addr:housenumber":"100",
    "addr:postcode":"24740",
    "addr:street":"N Wickham Ave",
    "iso:country":"US",
    "sg:address":"100 N Wickham Ave",
    "sg:city":"Princeton",
    "sg:classifiers":[
        {
            "category":"Personal",
            "subcategory":"Beauty Salon",
            "type":"Services"
        }
    ],
    "sg:phone":"+1 304 425 5735",
    "sg:postcode":"24740",
    "sg:province":"WV",
    "sg:tags":[
        "shop"
    ],
    "wof:name":"Hair Hut Beauty Salon Inc",
    "wof:placetype":"venue"
},
  "geometry": {"coordinates":[-81.080416,37.370131],"type":"Point"}
}