{
  "type": "Feature",
  "properties": {
    "iso:country":"US",
    "sg:address":"1415 Buckhannon Pike",
    "sg:city":"Clarksburg",
    "sg:classifiers":[
        {
            "category":"Government",
            "subcategory":"Office",
            "type":"Public Place"
        }
    ],
    "sg:phone":"+1 304 623 9460",
    "sg:postcode":"26301",
    "sg:province":"WV",
    "sg:tags":[
        "executive"
    ],
    "wof:name":"Maintence Shop",
    "wof:placetype":"venue"
},
  "geometry": {"coordinates":[-80.32319099999999,39.258914],"type":"Point"}
}