{
  "type": "Feature",
  "properties": {
    "iso:country":"US",
    "sg:address":"224 Pinewood Dr",
    "sg:city":"Beckley",
    "sg:classifiers":[
        {
            "category":"Education",
            "subcategory":"School",
            "type":"Public Place"
        }
    ],
    "sg:phone":"+1 304 254 9600",
    "sg:postcode":"25801",
    "sg:province":"WV",
    "wof:name":"Trinity Christian Academy",
    "wof:placetype":"venue"
},
  "geometry": {"coordinates":[-81.192091,37.809137],"type":"Point"}
}