{
  "type": "Feature",
  "properties": {
    "iso:country":"US",
    "sg:address":"115 S Price St",
    "sg:city":"Kingwood",
    "sg:classifiers":[
        {
            "category":"Shopping",
            "subcategory":"Used Merchandise",
            "type":"Retail Goods"
        }
    ],
    "sg:phone":"+1 304 329 1679",
    "sg:postcode":"26537",
    "sg:province":"WV",
    "sg:tags":[
        "shop",
        "consignment"
    ],
    "wof:name":"Dianna's Closet",
    "wof:placetype":"venue"
},
  "geometry": {"coordinates":[-79.687242,39.471609],"type":"Point"}
}