{
  "type": "Feature",
  "properties": {
    "iso:country":"US",
    "sg:address":"214 Mid Atlantic Parkway",
    "sg:city":"Martinsburg",
    "sg:classifiers":[
        {
            "category":"Bars & Pubs",
            "subcategory":"Sports Bar",
            "type":"Food & Drink"
        },
        {
            "category":"Restaurant",
            "type":"Food & Drink"
        },
        {
            "category":"Bars & Pubs",
            "subcategory":"Nightclub",
            "type":"Food & Drink"
        },
        {
            "category":"Internet Cafe",
            "subcategory":"None",
            "type":"Food & Drink"
        }
    ],
    "sg:phone":"+1 304 264 2304",
    "sg:postcode":"25404",
    "sg:province":"WV",
    "sg:tags":[
        "grill",
        "american",
        "club",
        "night"
    ],
    "wof:name":"The Brickhouse Bar and Grill",
    "wof:placetype":"venue"
},
  "geometry": {"coordinates":[-77.95826,39.493409],"type":"Point"}
}