{
  "type": "Feature",
  "properties": {
    "addr:full":"102 E Main St Glenville WV 26351",
    "addr:housenumber":"102",
    "addr:postcode":"26351",
    "addr:street":"E Main St",
    "iso:country":"US",
    "sg:address":"102 E Main St",
    "sg:city":"Glenville",
    "sg:classifiers":[
        {
            "category":"Cinema",
            "subcategory":"Movie Rental",
            "type":"Entertainment"
        }
    ],
    "sg:phone":"+1 304 462 8055",
    "sg:postcode":"26351",
    "sg:province":"WV",
    "sg:tags":[
        "leasing",
        "disc",
        "tape",
        "video",
        "recorder",
        "cassette"
    ],
    "wof:name":"Towne Bookstore The",
    "wof:placetype":"venue"
},
  "geometry": {"coordinates":[-80.83711700000001,38.933677],"type":"Point"}
}