{
  "type": "Feature",
  "properties": {
    "iso:country":"US",
    "sg:address":"124 Mc Dougal Dr",
    "sg:city":"Pennsboro",
    "sg:classifiers":[
        {
            "category":"Building & Trades",
            "subcategory":"Construction",
            "type":"Services"
        }
    ],
    "sg:phone":"+1 304 659 3000",
    "sg:postcode":"26415",
    "sg:province":"WV",
    "sg:tags":[
        "contractor"
    ],
    "wof:name":"Mountaineer Concrete Cutting",
    "wof:placetype":"venue"
},
  "geometry": {"coordinates":[-80.95812599999999,39.290824],"type":"Point"}
}