{
  "type": "Feature",
  "properties": {
    "iso:country":"US",
    "sg:address":"1100 Grand Central Ave",
    "sg:city":"Vienna",
    "sg:classifiers":[
        {
            "category":"Utilities",
            "subcategory":"Mobile Phone",
            "type":"Services"
        }
    ],
    "sg:phone":"+1 304 580 8009",
    "sg:postcode":"26105",
    "sg:province":"WV",
    "sg:tags":[
        "telephone",
        "cellular"
    ],
    "wof:name":"Sc Kiosk Inc",
    "wof:placetype":"venue"
},
  "geometry": {"coordinates":[-81.55323799999999,39.311944],"type":"Point"}
}