{
  "type": "Feature",
  "properties": {
    "iso:country":"US",
    "sg:address":"519 Washington St W",
    "sg:city":"Charleston",
    "sg:classifiers":[
        {
            "category":"Restaurant",
            "type":"Food & Drink"
        }
    ],
    "sg:phone":"+1 304 347 2020",
    "sg:postcode":"25302",
    "sg:province":"WV",
    "sg:tags":[
        "pizza"
    ],
    "wof:name":"Mama Rosas Pizzeria",
    "wof:placetype":"venue"
},
  "geometry": {"coordinates":[-81.64255900000001,38.363599],"type":"Point"}
}