{
  "type": "Feature",
  "properties": {
    "iso:country":"US",
    "sg:address":"2085 National Rd",
    "sg:city":"Wheeling",
    "sg:classifiers":[
        {
            "category":"Restaurant",
            "type":"Food & Drink"
        }
    ],
    "sg:phone":"+1 304 242 3694",
    "sg:postcode":"26003",
    "sg:province":"WV",
    "wof:name":"Enzio",
    "wof:placetype":"venue"
},
  "geometry": {"coordinates":[-80.662457,40.047639],"type":"Point"}
}