{
  "type": "Feature",
  "properties": {
    "iso:country":"US",
    "sg:address":"1000 Central Ave",
    "sg:city":"Charleston",
    "sg:classifiers":[
        {
            "category":"Professional",
            "subcategory":"Engineering",
            "type":"Services"
        }
    ],
    "sg:phone":"+1 304 344 4749",
    "sg:postcode":"25302",
    "sg:province":"WV",
    "sg:tags":[
        "engineer"
    ],
    "wof:name":"Jarrett Corp",
    "wof:placetype":"venue"
},
  "geometry": {"coordinates":[-81.656994,38.36586],"type":"Point"}
}