{
  "type": "Feature",
  "properties": {
    "addr:full":"713 Bigley Ave Charleston WV 25302",
    "addr:housenumber":"713",
    "addr:postcode":"25302",
    "addr:street":"Bigley Ave",
    "iso:country":"US",
    "sg:address":"713 Bigley Ave",
    "sg:city":"Charleston",
    "sg:classifiers":[
        {
            "category":"Real Estate",
            "subcategory":"Real Estate Agent",
            "type":"Services"
        }
    ],
    "sg:phone":"+1 304 343 2400",
    "sg:postcode":"25302",
    "sg:province":"WV",
    "wof:name":"RBM Commercial",
    "wof:placetype":"venue"
},
  "geometry": {"coordinates":[-81.638992,38.360632],"type":"Point"}
}