{
  "type": "Feature",
  "properties": {
    "iso:country":"US",
    "sg:address":"209 Roane St",
    "sg:city":"Charleston",
    "sg:classifiers":[
        {
            "category":"Real Estate",
            "subcategory":"Real Estate Agent",
            "type":"Services"
        }
    ],
    "sg:phone":"+1 304 342 2323",
    "sg:postcode":"25302",
    "sg:province":"WV",
    "wof:name":"Real Estate Connection",
    "wof:placetype":"venue"
},
  "geometry": {"coordinates":[-81.643657,38.360157],"type":"Point"}
}