{
  "type": "Feature",
  "properties": {
    "addr:full":"201 2nd St St Marys WV 26170",
    "addr:housenumber":"201",
    "addr:postcode":"26170",
    "addr:street":"2Nd St",
    "iso:country":"US",
    "sg:address":"201 2nd St",
    "sg:city":"St Marys",
    "sg:classifiers":[
        {
            "category":"Government",
            "subcategory":"Office",
            "type":"Public Place"
        }
    ],
    "sg:phone":"+1 304 684 9244",
    "sg:postcode":"26170",
    "sg:province":"WV",
    "sg:tags":[
        "county",
        "resource"
    ],
    "wof:name":"Pleasants Human Svc Dept",
    "wof:placetype":"venue"
},
  "geometry": {"coordinates":[-81.206682,39.390113],"type":"Point"}
}