{
  "type": "Feature",
  "properties": {
    "iso:country":"US",
    "sg:address":"310 3rd Ave",
    "sg:city":"Beckley",
    "sg:classifiers":[
        {
            "category":"Government",
            "subcategory":"Fire Station",
            "type":"Public Place"
        }
    ],
    "sg:phone":"+1 304 256 1781",
    "sg:postcode":"25801",
    "sg:province":"WV",
    "sg:tags":[
        "department"
    ],
    "wof:name":"Beckley Fire Dept",
    "wof:placetype":"venue"
},
  "geometry": {"coordinates":[-81.194548,37.773241],"type":"Point"}
}