{
  "type": "Feature",
  "properties": {
    "addr:full":"110 Dunkard Ave Morgantown WV 26501",
    "addr:housenumber":"110",
    "addr:postcode":"26501",
    "addr:street":"Dunkard Ave",
    "iso:country":"US",
    "sg:address":"110 Dunkard Ave",
    "sg:city":"Morgantown",
    "sg:classifiers":[
        {
            "category":"Wholesale",
            "subcategory":"Hardware",
            "type":"Manufacturing & Wholesale Goods"
        }
    ],
    "sg:phone":"+1 304 296 0496",
    "sg:postcode":"26501",
    "sg:province":"WV",
    "sg:tags":[
        "plumbing"
    ],
    "wof:name":"Danzer Inc",
    "wof:placetype":"venue"
},
  "geometry": {"coordinates":[-79.97639100000001,39.63794],"type":"Point"}
}