{
  "type": "Feature",
  "properties": {
    "iso:country":"US",
    "sg:address":"790 N Jefferson St",
    "sg:city":"Lewisburg",
    "sg:classifiers":[
        {
            "category":"Banks & Credit Unions",
            "subcategory":"Bank",
            "type":"Services"
        }
    ],
    "sg:phone":"+1 304 645 2000",
    "sg:postcode":"24901",
    "sg:province":"WV",
    "wof:name":"Bank Of Monroe",
    "wof:placetype":"venue"
},
  "geometry": {"coordinates":[-80.423452,37.821027],"type":"Point"}
}