{
  "type": "Feature",
  "properties": {
    "iso:country":"US",
    "sg:address":"369 Main St",
    "sg:city":"Madison",
    "sg:classifiers":[
        {
            "category":"Shopping",
            "subcategory":"Used Merchandise",
            "type":"Retail Goods"
        }
    ],
    "sg:phone":"+1 304 369 7170",
    "sg:postcode":"25130",
    "sg:province":"WV",
    "sg:tags":[
        "antique"
    ],
    "wof:name":"Drug N & C",
    "wof:placetype":"venue"
},
  "geometry": {"coordinates":[-81.82159,38.065068],"type":"Point"}
}