{
  "type": "Feature",
  "properties": {
    "iso:country":"US",
    "sg:address":"6255 Grand Central Ave",
    "sg:city":"Parkersburg",
    "sg:classifiers":[
        {
            "category":"Restaurant",
            "type":"Food & Drink"
        }
    ],
    "sg:phone":"+1 304 295 8648",
    "sg:postcode":"26105",
    "sg:province":"WV",
    "wof:name":"Veterans Of Foreign Wars",
    "wof:placetype":"venue"
},
  "geometry": {"coordinates":[-81.52928300000001,39.346659],"type":"Point"}
}