{
  "type": "Feature",
  "properties": {
    "iso:country":"US",
    "sg:address":"2 Dairy Rd",
    "sg:city":"Poca",
    "sg:classifiers":[
        {
            "category":"Recreation",
            "type":"Entertainment"
        }
    ],
    "sg:phone":"+1 304 755 0408",
    "sg:postcode":"25159",
    "sg:province":"WV",
    "sg:tags":[
        "club",
        "country"
    ],
    "wof:name":"Solco Incorporated",
    "wof:placetype":"venue"
},
  "geometry": {"coordinates":[-81.804574,38.461681],"type":"Point"}
}