{
  "type": "Feature",
  "properties": {
    "iso:country":"US",
    "sg:address":"871 Baker Rd",
    "sg:city":"Martinsburg",
    "sg:classifiers":[
        {
            "category":"Professional",
            "subcategory":"Printing & Photocopies",
            "type":"Services"
        }
    ],
    "sg:phone":"+1 304 267 3600",
    "sg:postcode":"25405",
    "sg:province":"WV",
    "sg:tags":[
        "services-commercial"
    ],
    "wof:name":"Quebecor Printing Martinsburg",
    "wof:placetype":"venue"
},
  "geometry": {"coordinates":[-77.90243599999999,39.413466],"type":"Point"}
}