{
  "type": "Feature",
  "properties": {
    "iso:country":"US",
    "sg:address":"110 Oxford Dr",
    "sg:city":"Charles Town",
    "sg:classifiers":[
        {
            "category":"Local Transit",
            "type":"Transportation"
        }
    ],
    "sg:phone":"+1 703 847 8700",
    "sg:postcode":"25414",
    "sg:province":"WV",
    "sg:tags":[
        "airport"
    ],
    "wof:name":"Continental Sedan Inc",
    "wof:placetype":"venue"
},
  "geometry": {"coordinates":[-77.840413,39.212557],"type":"Point"}
}