{
  "type": "Feature",
  "properties": {
    "addr:full":"1414 Eastern Ave Morgantown WV 26505",
    "addr:housenumber":"1414",
    "addr:postcode":"26505",
    "addr:street":"Eastern Ave",
    "iso:country":"US",
    "sg:address":"1414 Eastern Ave",
    "sg:city":"Morgantown",
    "sg:classifiers":[
        {
            "category":"Real Estate",
            "subcategory":"Real Estate Operator",
            "type":"Services"
        }
    ],
    "sg:phone":"+1 304 598 3050",
    "sg:postcode":"26505",
    "sg:province":"WV",
    "sg:tags":[
        "property",
        "lessor"
    ],
    "wof:name":"Dakota Partnership Ltd",
    "wof:placetype":"venue"
},
  "geometry": {"coordinates":[-79.972815,39.663139],"type":"Point"}
}