{
  "type": "Feature",
  "properties": {
    "addr:full":"300 Market St Man WV 25635",
    "addr:housenumber":"300",
    "addr:postcode":"25635",
    "addr:street":"Market St",
    "iso:country":"US",
    "sg:address":"300 Market St",
    "sg:city":"Man",
    "sg:classifiers":[
        {
            "category":"Banks & Credit Unions",
            "subcategory":"Bank",
            "type":"Services"
        }
    ],
    "sg:phone":"+1 304 583 2200",
    "sg:postcode":"25635",
    "sg:province":"WV",
    "wof:name":"United Bank",
    "wof:placetype":"venue"
},
  "geometry": {"coordinates":[-81.87247000000001,37.743856],"type":"Point"}
}