{
  "type": "Feature",
  "properties": {
    "addr:full":"4968 Elk River Rd S Elkview WV 25071",
    "addr:housenumber":"4968",
    "addr:postcode":"25071",
    "addr:street":"Elk River Rd S",
    "iso:country":"US",
    "sg:address":"4968 Elk River Rd S",
    "sg:city":"Elkview",
    "sg:classifiers":[
        {
            "category":"Health Services",
            "subcategory":"Doctor",
            "type":"Services"
        }
    ],
    "sg:phone":"+1 304 965 6661",
    "sg:postcode":"25071",
    "sg:province":"WV",
    "sg:tags":[
        "dentist"
    ],
    "wof:name":"Elk Family Dentistry Inc",
    "wof:placetype":"venue"
},
  "geometry": {"coordinates":[-81.49982199999999,38.413762],"type":"Point"}
}