{
  "type": "Feature",
  "properties": {
    "iso:country":"US",
    "sg:address":"725 Wells St",
    "sg:city":"Sistersville",
    "sg:classifiers":[
        {
            "category":"Shopping",
            "subcategory":"Books",
            "type":"Retail Goods"
        }
    ],
    "sg:phone":"+1 304 652 5080",
    "sg:postcode":"26175",
    "sg:province":"WV",
    "wof:name":"Book House",
    "wof:placetype":"venue"
},
  "geometry": {"coordinates":[-80.996014,39.563938],"type":"Point"}
}