{
  "type": "Feature",
  "properties": {
    "iso:country":"US",
    "sg:address":"36197 Johnson Ridge Rd",
    "sg:city":"Barnesville",
    "sg:classifiers":[
        {
            "category":"Building & Trades",
            "subcategory":"Electrical",
            "type":"Services"
        }
    ],
    "sg:phone":"+1 740 757 2363",
    "sg:postcode":"43713",
    "sg:province":"OH",
    "sg:tags":[
        "electrical",
        "contractor"
    ],
    "wof:name":"Johnson Electric",
    "wof:placetype":"venue"
},
  "geometry": {"coordinates":[-81.153672,39.902362],"type":"Point"}
}