{
  "type": "Feature",
  "properties": {
    "iso:country":"US",
    "sg:address":"115 Jackson St",
    "sg:city":"Fairmont",
    "sg:classifiers":[
        {
            "category":"Autos & Motor Vehicles",
            "subcategory":"Auto Supplies",
            "type":"Retail Goods"
        }
    ],
    "sg:phone":"+1 304 363 1773",
    "sg:postcode":"26554",
    "sg:province":"WV",
    "sg:tags":[
        "automobile",
        "parts"
    ],
    "wof:name":"Morgan Auto Parts Inc",
    "wof:placetype":"venue"
},
  "geometry": {"coordinates":[-80.144657,39.485381],"type":"Point"}
}