{
  "type": "Feature",
  "properties": {
    "iso:country":"US",
    "sg:address":"1312 Rayon Dr",
    "sg:city":"Parkersburg",
    "sg:classifiers":[
        {
            "category":"Food & Beverages",
            "subcategory":"Liquor & Beverages",
            "type":"Retail Goods"
        },
        {
            "category":"Organizations",
            "subcategory":"Community Association",
            "type":"Services"
        }
    ],
    "sg:phone":"+1 304 485 2344",
    "sg:postcode":"26101",
    "sg:province":"WV",
    "sg:tags":[
        "club",
        "eating",
        "alcoholic"
    ],
    "wof:name":"Audrey's Grill",
    "wof:placetype":"venue"
},
  "geometry": {"coordinates":[-81.535471,39.234418],"type":"Point"}
}