{
  "type": "Feature",
  "properties": {
    "addr:full":"128 Main St Clay WV 25043",
    "addr:housenumber":"128",
    "addr:postcode":"25043",
    "addr:street":"Main St",
    "iso:country":"US",
    "sg:address":"128 Main St",
    "sg:city":"Clay",
    "sg:classifiers":[
        {
            "category":"Food & Beverages",
            "subcategory":"Fruits & Vegetables",
            "type":"Retail Goods"
        }
    ],
    "sg:phone":"+1 304 587 2064",
    "sg:postcode":"25043",
    "sg:province":"WV",
    "sg:tags":[
        "produce"
    ],
    "wof:name":"B & A Produce",
    "wof:placetype":"venue"
},
  "geometry": {"coordinates":[-81.085877,38.460716],"type":"Point"}
}