{
  "type": "Feature",
  "properties": {
    "iso:country":"US",
    "sg:address":"144 Main St",
    "sg:city":"Spencer",
    "sg:classifiers":[
        {
            "category":"Shopping",
            "subcategory":"Jewelry",
            "type":"Retail Goods"
        }
    ],
    "sg:phone":"+1 304 927 1620",
    "sg:postcode":"25276",
    "sg:province":"WV",
    "sg:tags":[
        "jeweler"
    ],
    "wof:name":"Hughes Jewelry",
    "wof:placetype":"venue"
},
  "geometry": {"coordinates":[-81.350106,38.801628],"type":"Point"}
}