{
  "type": "Feature",
  "properties": {
    "addr:full":"4513 Grand Central Ave Vienna WV 26105",
    "addr:housenumber":"4513",
    "addr:postcode":"26105",
    "addr:street":"Grand Central Ave",
    "iso:country":"US",
    "sg:address":"4513 Grand Central Ave",
    "sg:city":"Vienna",
    "sg:classifiers":[
        {
            "category":"Organizations",
            "subcategory":"Religious Organization",
            "type":"Services"
        }
    ],
    "sg:phone":"+1 304 295 9241",
    "sg:postcode":"26105",
    "sg:province":"WV",
    "wof:name":"Christ Lutheran Church",
    "wof:placetype":"venue"
},
  "geometry": {"coordinates":[-81.54313500000001,39.335653],"type":"Point"}
}