{
  "type": "Feature",
  "properties": {
    "iso:country":"US",
    "sg:address":"651 Buckhannon Pike",
    "sg:city":"Clarksburg",
    "sg:classifiers":[
        {
            "category":"Food & Beverages",
            "subcategory":"Groceries & Convenience Stores",
            "type":"Retail Goods"
        }
    ],
    "sg:phone":"+1 304 624 7276",
    "sg:postcode":"26301",
    "sg:province":"WV",
    "sg:tags":[
        "station",
        "gasoline"
    ],
    "wof:name":"Mountaineer Mart 22",
    "wof:placetype":"venue"
},
  "geometry": {"coordinates":[-80.325396,39.262179],"type":"Point"}
}