{
  "type": "Feature",
  "properties": {
    "iso:country":"US",
    "sg:address":"517 Fairmont Ave",
    "sg:city":"Fairmont",
    "sg:classifiers":[
        {
            "category":"Real Estate",
            "subcategory":"Real Estate Agent",
            "type":"Services"
        }
    ],
    "sg:phone":"+1 304 363 0860",
    "sg:postcode":"26554",
    "sg:province":"WV",
    "sg:tags":[
        "authorities",
        "housing"
    ],
    "wof:name":"Fairmont Housing Authority",
    "wof:placetype":"venue"
},
  "geometry": {"coordinates":[-80.14936,39.478994],"type":"Point"}
}