{
  "type": "Feature",
  "properties": {
    "addr:full":"526 14th St W Huntington WV 25704",
    "addr:housenumber":"526",
    "addr:postcode":"25704",
    "addr:street":"14Th St W",
    "iso:country":"US",
    "sg:address":"526 14th St W",
    "sg:city":"Huntington",
    "sg:classifiers":[
        {
            "category":"Personal",
            "subcategory":"Beauty Salon",
            "type":"Services"
        }
    ],
    "sg:phone":"+1 304 697 4500",
    "sg:postcode":"25704",
    "sg:province":"WV",
    "wof:name":"Dimensions",
    "wof:placetype":"venue"
},
  "geometry": {"coordinates":[-82.479631,38.411373],"type":"Point"}
}