{
  "type": "Feature",
  "properties": {
    "iso:country":"US",
    "sg:address":"4507 Staunton Ave SE",
    "sg:city":"Charleston",
    "sg:classifiers":[
        {
            "category":"Arena",
            "subcategory":"Sports Club",
            "type":"Entertainment"
        }
    ],
    "sg:phone":"+1 304 925 2561",
    "sg:postcode":"25304",
    "sg:province":"WV",
    "sg:tags":[
        "manager",
        "recruiter",
        "promoter"
    ],
    "sg:website":"www.boxingcontest.com",
    "wof:name":"ACR Promotions Inc",
    "wof:placetype":"venue"
},
  "geometry": {"coordinates":[-81.581751,38.323731],"type":"Point"}
}