{
  "type": "Feature",
  "properties": {
    "iso:country":"US",
    "sg:address":"785 Oakland Dr",
    "sg:city":"Princeton",
    "sg:classifiers":[
        {
            "category":"Restaurant",
            "type":"Food & Drink"
        }
    ],
    "sg:phone":"+1 304 425 9865",
    "sg:postcode":"24740",
    "sg:province":"WV",
    "sg:tags":[
        "eating"
    ],
    "wof:name":"Quiznos Subs",
    "wof:placetype":"venue"
},
  "geometry": {"coordinates":[-81.167372,37.346393],"type":"Point"}
}