{
  "type": "Feature",
  "properties": {
    "iso:country":"US",
    "sg:address":"5572 Hubbards Branch Rd",
    "sg:city":"Huntington",
    "sg:classifiers":[
        {
            "category":"Professional",
            "subcategory":"Management & Consulting",
            "type":"Services"
        },
        {
            "category":"Building & Trades",
            "subcategory":"Plumbing",
            "type":"Services"
        }
    ],
    "sg:phone":"+1 304 453 6404",
    "sg:postcode":"25704",
    "sg:province":"WV",
    "sg:tags":[
        "fire",
        "consultant",
        "protection",
        "contractor"
    ],
    "wof:name":"Pratt Fire Protection LLC",
    "wof:placetype":"venue"
},
  "geometry": {"coordinates":[-82.546318,38.388897],"type":"Point"}
}