{
  "type": "Feature",
  "properties": {
    "iso:country":"US",
    "sg:address":"136 Stewart St",
    "sg:city":"Welch",
    "sg:classifiers":[
        {
            "category":"Organizations",
            "subcategory":"Religious Organization",
            "type":"Services"
        }
    ],
    "sg:phone":"+1 304 436 4433",
    "sg:postcode":"24801",
    "sg:province":"WV",
    "wof:name":"First Church of God",
    "wof:placetype":"venue"
},
  "geometry": {"coordinates":[-81.586828,37.439192],"type":"Point"}
}