{
  "type": "Feature",
  "properties": {
    "addr:full":"1016 Market St Parkersburg WV 26101",
    "addr:housenumber":"1016",
    "addr:postcode":"26101",
    "addr:street":"Market St",
    "iso:country":"US",
    "sg:address":"1016 Market St",
    "sg:city":"Parkersburg",
    "sg:classifiers":[
        {
            "category":"Professional",
            "type":"Services"
        }
    ],
    "sg:phone":"+1 304 422 4277",
    "sg:postcode":"26101",
    "sg:province":"WV",
    "sg:tags":[
        "establishment"
    ],
    "wof:name":"Manor",
    "wof:placetype":"venue"
},
  "geometry": {"coordinates":[-81.553845,39.270316],"type":"Point"}
}