{
  "type": "Feature",
  "properties": {
    "addr:full":"203 Austin St Lewisburg WV 24901",
    "addr:housenumber":"203",
    "addr:postcode":"24901",
    "addr:street":"Austin St",
    "iso:country":"US",
    "sg:address":"203 Austin St",
    "sg:city":"Lewisburg",
    "sg:classifiers":[
        {
            "category":"Retail",
            "subcategory":"Repair Shop",
            "type":"Services"
        }
    ],
    "sg:phone":"+1 304 645 1375",
    "sg:postcode":"24901",
    "sg:province":"WV",
    "wof:name":"Fine Tuning",
    "wof:placetype":"venue"
},
  "geometry": {"coordinates":[-80.447457,37.798055],"type":"Point"}
}