{
  "type": "Feature",
  "properties": {
    "addr:full":"201 S Eisenhower Dr Beckley WV 25801",
    "addr:housenumber":"201",
    "addr:postcode":"25801",
    "addr:street":"S Eisenhower Dr",
    "iso:country":"US",
    "sg:address":"201 S Eisenhower Dr",
    "sg:city":"Beckley",
    "sg:classifiers":[
        {
            "category":"Government",
            "subcategory":"Police Station",
            "type":"Public Place"
        }
    ],
    "sg:phone":"+1 304 255 9310",
    "sg:postcode":"25801",
    "sg:province":"WV",
    "sg:tags":[
        "protection",
        "sheriff"
    ],
    "wof:name":"Raleigh County Sheriff's Dept",
    "wof:placetype":"venue"
},
  "geometry": {"coordinates":[-81.166105,37.779815],"type":"Point"}
}