{
  "type": "Feature",
  "properties": {
    "iso:country":"US",
    "sg:address":"103 Hope Ln",
    "sg:city":"Princeton",
    "sg:classifiers":[
        {
            "category":"Building & Trades",
            "subcategory":"Construction",
            "type":"Services"
        }
    ],
    "sg:phone":"+1 304 425 0226",
    "sg:postcode":"24740",
    "sg:province":"WV",
    "sg:tags":[
        "contractor"
    ],
    "wof:name":"T J Pressure Washing",
    "wof:placetype":"venue"
},
  "geometry": {"coordinates":[-81.121923,37.365562],"type":"Point"}
}