{
  "type": "Feature",
  "properties": {
    "iso:country":"US",
    "sg:address":"1109 Pocahontas Ave",
    "sg:city":"Ronceverte",
    "sg:classifiers":[
        {
            "category":"Cinema",
            "subcategory":"Movie Rental",
            "type":"Entertainment"
        }
    ],
    "sg:phone":"+1 304 645 5210",
    "sg:postcode":"24970",
    "sg:province":"WV",
    "sg:tags":[
        "video",
        "tape"
    ],
    "wof:name":"Video Resources Unlimited Inc",
    "wof:placetype":"venue"
},
  "geometry": {"coordinates":[-80.47563700000001,37.746255],"type":"Point"}
}