{
  "type": "Feature",
  "properties": {
    "addr:full":"225 Don Knotts Blvd Morgantown WV 26501",
    "addr:housenumber":"225",
    "addr:postcode":"26501",
    "addr:street":"Don Knotts Blvd",
    "iso:country":"US",
    "sg:address":"225 Don Knotts Blvd",
    "sg:city":"Morgantown",
    "sg:classifiers":[
        {
            "category":"Autos & Motor Vehicles",
            "subcategory":"Automobile Sales",
            "type":"Retail Goods"
        },
        {
            "category":"Autos & Motor Vehicles",
            "subcategory":"Fuel & Gas Station",
            "type":"Retail Goods"
        },
        {
            "category":"Autos & Motor Vehicles",
            "subcategory":"Auto Supplies",
            "type":"Retail Goods"
        },
        {
            "category":"Retail",
            "subcategory":"Auto Repair",
            "type":"Services"
        }
    ],
    "sg:phone":"+1 304 212 4406",
    "sg:postcode":"26501",
    "sg:province":"WV",
    "sg:tags":[
        "wheel",
        "exhaust",
        "oil",
        "muffler",
        "balancing",
        "wheels-aligning",
        "servicing-automotive",
        "system",
        "accessory",
        "equipment",
        "lube",
        "electrical",
        "axle",
        "equipment-service",
        "alignment-frame",
        "brake",
        "inspection",
        "air conditioning"
    ],
    "sg:website":"http://www.tomtracker.com/redirect.cfm?bID=4837&hID=111353",
    "wof:name":"Meineke Car Care Center",
    "wof:placetype":"venue"
},
  "geometry": {"coordinates":[-79.96955199999999,39.612654],"type":"Point"}
}