{
  "type": "Feature",
  "properties": {
    "addr:full":"14 Grant St Petersburg WV 26847",
    "addr:housenumber":"14",
    "addr:postcode":"26847",
    "addr:street":"Grant",
    "iso:country":"US",
    "sg:address":"14 Grant St",
    "sg:city":"Petersburg",
    "sg:classifiers":[
        {
            "category":"Manufacturing",
            "subcategory":"Lumber",
            "type":"Manufacturing & Wholesale Goods"
        }
    ],
    "sg:phone":"+1 304 257 2625",
    "sg:postcode":"26847",
    "sg:province":"WV",
    "sg:tags":[
        "forestry"
    ],
    "wof:name":"Donald Eskridge Consultan",
    "wof:placetype":"venue"
},
  "geometry": {"coordinates":[-79.11807899999999,38.99489],"type":"Point"}
}