{
  "type": "Feature",
  "properties": {
    "iso:country":"US",
    "sg:address":"457 Main St",
    "sg:city":"Madison",
    "sg:classifiers":[
        {
            "category":"Communications",
            "subcategory":"Radio Station",
            "type":"Services"
        }
    ],
    "sg:phone":"+1 304 369 5200",
    "sg:postcode":"25130",
    "sg:province":"WV",
    "sg:tags":[
        "company",
        "broadcasting"
    ],
    "wof:name":"WZAC",
    "wof:placetype":"venue"
},
  "geometry": {"coordinates":[-81.822953,38.062402],"type":"Point"}
}