{
  "type": "Feature",
  "properties": {
    "addr:full":"112 S 5th St Clarksburg WV 26301",
    "addr:housenumber":"112",
    "addr:postcode":"26301",
    "addr:street":"S 5Th St",
    "iso:country":"US",
    "sg:address":"112 S 5th St",
    "sg:city":"Clarksburg",
    "sg:classifiers":[
        {
            "category":"Insurance",
            "subcategory":"Insurance Agent",
            "type":"Services"
        }
    ],
    "sg:phone":"+1 304 624 5400",
    "sg:postcode":"26301",
    "sg:province":"WV",
    "wof:name":"Northwestern Mutual Financial",
    "wof:placetype":"venue"
},
  "geometry": {"coordinates":[-80.341508,39.279341],"type":"Point"}
}