{
  "type": "Feature",
  "properties": {
    "addr:full":"132 Beckley Crossing Shpg Center Beckley WV 25801",
    "addr:housenumber":"132",
    "addr:postcode":"25801",
    "addr:street":"Beckley Crossing Shpg Center",
    "iso:country":"US",
    "sg:address":"132 Beckley Crossing Shpg Center",
    "sg:city":"Beckley",
    "sg:classifiers":[
        {
            "category":"Utilities",
            "subcategory":"Mobile Phone",
            "type":"Services"
        }
    ],
    "sg:phone":"+1 304 255 3990",
    "sg:postcode":"25801",
    "sg:province":"WV",
    "sg:tags":[
        "telephone",
        "cellular"
    ],
    "sg:website":"www.uscellular.com",
    "wof:name":"US Cellular",
    "wof:placetype":"venue"
},
  "geometry": {"coordinates":[-81.181562,37.802541],"type":"Point"}
}