{
  "type": "Feature",
  "properties": {
    "iso:country":"US",
    "sg:address":"500 Morris St",
    "sg:city":"Charleston",
    "sg:classifiers":[
        {
            "category":"Health Services",
            "subcategory":"Hospital",
            "type":"Services"
        }
    ],
    "sg:phone":"+1 304 341 0164",
    "sg:postcode":"25301",
    "sg:province":"WV",
    "sg:tags":[
        "mental"
    ],
    "wof:name":"Prestera Center For Mental",
    "wof:placetype":"venue"
},
  "geometry": {"coordinates":[-81.625227,38.347746],"type":"Point"}
}