{
  "type": "Feature",
  "properties": {
    "iso:country":"US",
    "sg:address":"1428 E Main St",
    "sg:city":"Princeton",
    "sg:classifiers":[
        {
            "category":"Government",
            "subcategory":"Office",
            "type":"Public Place"
        }
    ],
    "sg:phone":"+1 304 425 7799",
    "sg:postcode":"24740",
    "sg:province":"WV",
    "wof:name":"Honorable Roy Compton",
    "wof:placetype":"venue"
},
  "geometry": {"coordinates":[-81.101223,37.365633],"type":"Point"}
}