{
  "type": "Feature",
  "properties": {
    "iso:country":"US",
    "sg:address":"530 6th Ave",
    "sg:city":"Huntington",
    "sg:classifiers":[
        {
            "category":"Insurance",
            "subcategory":"Insurance Agent",
            "type":"Services"
        }
    ],
    "sg:phone":"+1 304 523 9079",
    "sg:postcode":"25701",
    "sg:province":"WV",
    "wof:name":"Young Insurance Inc",
    "wof:placetype":"venue"
},
  "geometry": {"coordinates":[-82.448686,38.417108],"type":"Point"}
}