{
  "type": "Feature",
  "properties": {
    "iso:country":"US",
    "sg:address":"710 Churchill Dr",
    "sg:city":"Charleston",
    "sg:classifiers":[
        {
            "category":"Professional",
            "subcategory":"Business Services",
            "type":"Services"
        }
    ],
    "sg:phone":"+1 304 344 2033",
    "sg:postcode":"25314",
    "sg:province":"WV",
    "wof:name":"Buffalo Crossing Enterprises",
    "wof:placetype":"venue"
},
  "geometry": {"coordinates":[-81.66520300000001,38.350304],"type":"Point"}
}