{
  "type": "Feature",
  "properties": {
    "iso:country":"US",
    "sg:address":"965 Maple Dr",
    "sg:city":"Morgantown",
    "sg:classifiers":[
        {
            "category":"Health Services",
            "subcategory":"Nursing And Care Facility",
            "type":"Services"
        }
    ],
    "sg:phone":"+1 304 285 2777",
    "sg:postcode":"26505",
    "sg:province":"WV",
    "sg:tags":[
        "hospice"
    ],
    "sg:website":"www.monhealthsys.org",
    "wof:name":"Morgantown Hospice",
    "wof:placetype":"venue"
},
  "geometry": {"coordinates":[-79.949921,39.657124],"type":"Point"}
}