{
  "type": "Feature",
  "properties": {
    "iso:country":"US",
    "sg:address":"113 Oak St",
    "sg:city":"Hurricane",
    "sg:classifiers":[
        {
            "category":"Shopping",
            "subcategory":"Computers & Home Electronics",
            "type":"Retail Goods"
        }
    ],
    "sg:phone":"+1 304 757 7786",
    "sg:postcode":"25526",
    "sg:province":"WV",
    "sg:tags":[
        "equipment",
        "dealer"
    ],
    "wof:name":"Geran Technologies LLC",
    "wof:placetype":"venue"
},
  "geometry": {"coordinates":[-81.97420700000001,38.447514],"type":"Point"}
}