{
  "type": "Feature",
  "properties": {
    "iso:country":"US",
    "sg:address":"1275 Warwood Ave",
    "sg:city":"Wheeling",
    "sg:classifiers":[
        {
            "category":"Social Services",
            "subcategory":"Job Training",
            "type":"Services"
        }
    ],
    "sg:phone":"+1 304 238 1045",
    "sg:postcode":"26003",
    "sg:province":"WV",
    "sg:tags":[
        "rehab",
        "government"
    ],
    "wof:name":"Employment Security Dept",
    "wof:placetype":"venue"
},
  "geometry": {"coordinates":[-80.69828800000001,40.114301],"type":"Point"}
}