{
  "type": "Feature",
  "properties": {
    "addr:full":"508 Old Goff Mountain Rd Charleston WV 25313",
    "addr:housenumber":"508",
    "addr:postcode":"25313",
    "addr:street":"Old Goff Mountain Rd",
    "iso:country":"US",
    "sg:address":"508 Old Goff Mountain Rd",
    "sg:city":"Charleston",
    "sg:classifiers":[
        {
            "category":"Wholesale",
            "subcategory":"Construction Materials",
            "type":"Manufacturing & Wholesale Goods"
        }
    ],
    "sg:phone":"+1 304 776 7589",
    "sg:postcode":"25313",
    "sg:province":"WV",
    "sg:tags":[
        "interior",
        "drywall"
    ],
    "wof:name":"Crosslannes Acoustics",
    "wof:placetype":"venue"
},
  "geometry": {"coordinates":[-81.78689900000001,38.401761],"type":"Point"}
}