{
  "type": "Feature",
  "properties": {
    "iso:country":"US",
    "sg:address":"290 Gain St",
    "sg:city":"Salem",
    "sg:classifiers":[
        {
            "category":"Social Services",
            "subcategory":"Child Care",
            "type":"Services"
        }
    ],
    "sg:phone":"+1 304 782 4678",
    "sg:postcode":"26426",
    "sg:province":"WV",
    "sg:tags":[
        "day"
    ],
    "wof:name":"Quality Childcare",
    "wof:placetype":"venue"
},
  "geometry": {"coordinates":[-80.555209,39.280923],"type":"Point"}
}