{
  "type": "Feature",
  "properties": {
    "iso:country":"US",
    "sg:address":"2995 University Ave",
    "sg:city":"Morgantown",
    "sg:classifiers":[
        {
            "category":"Professional",
            "subcategory":"Printing & Photocopies",
            "type":"Services"
        }
    ],
    "sg:phone":"+1 304 599 6066",
    "sg:postcode":"26505",
    "sg:province":"WV",
    "sg:tags":[
        "duplicating",
        "copying"
    ],
    "wof:name":"Pronto Print & Copy Ctr",
    "wof:placetype":"venue"
},
  "geometry": {"coordinates":[-79.965405,39.650029],"type":"Point"}
}