{
  "type": "Feature",
  "properties": {
    "addr:full":"243 Three Springs Dr Weirton WV 26062",
    "addr:housenumber":"243",
    "addr:postcode":"26062",
    "addr:street":"Three Springs Dr",
    "iso:country":"US",
    "sg:address":"243 Three Springs Dr",
    "sg:city":"Weirton",
    "sg:classifiers":[
        {
            "category":"Retail",
            "subcategory":"Photofinishing",
            "type":"Services"
        }
    ],
    "sg:phone":"+1 304 723 5236",
    "sg:postcode":"26062",
    "sg:province":"WV",
    "sg:tags":[
        "photo",
        "finishing"
    ],
    "wof:name":"1 Hour Photo",
    "wof:placetype":"venue"
},
  "geometry": {"coordinates":[-80.549989,40.405801],"type":"Point"}
}