{
  "type": "Feature",
  "properties": {
    "addr:full":"525 Sherwood Dr Huntington WV 25704",
    "addr:housenumber":"525",
    "addr:postcode":"25704",
    "addr:street":"Sherwood Dr",
    "iso:country":"US",
    "sg:address":"525 Sherwood Dr",
    "sg:city":"Huntington",
    "sg:classifiers":[
        {
            "category":"Real Estate",
            "subcategory":"Real Estate Agent",
            "type":"Services"
        }
    ],
    "sg:phone":"+1 304 429 0000",
    "sg:postcode":"25704",
    "sg:province":"WV",
    "sg:tags":[
        "appraiser"
    ],
    "wof:name":"Smith Appraisals",
    "wof:placetype":"venue"
},
  "geometry": {"coordinates":[-82.49909100000001,38.375394],"type":"Point"}
}