{
  "type": "Feature",
  "properties": {
    "iso:country":"US",
    "sg:address":"918 W Main St",
    "sg:city":"Grafton",
    "sg:classifiers":[
        {
            "category":"Personal",
            "subcategory":"Beauty Salon",
            "type":"Services"
        }
    ],
    "sg:phone":"+1 304 265 2225",
    "sg:postcode":"26354",
    "sg:province":"WV",
    "sg:tags":[
        "shop"
    ],
    "wof:name":"Patsy's Styling Station",
    "wof:placetype":"venue"
},
  "geometry": {"coordinates":[-80.04090100000001,39.342667],"type":"Point"}
}