{
  "type": "Feature",
  "properties": {
    "iso:country":"US",
    "sg:address":"5331 Edgebrook Dr",
    "sg:city":"Charleston",
    "sg:classifiers":[
        {
            "category":"Health Services",
            "subcategory":"Nursing And Care Facility",
            "type":"Services"
        }
    ],
    "sg:phone":"+1 304 757 2592",
    "sg:postcode":"25313",
    "sg:province":"WV",
    "sg:tags":[
        "intermediate"
    ],
    "wof:name":"Canadas Tender Touch",
    "wof:placetype":"venue"
},
  "geometry": {"coordinates":[-81.773882,38.427703],"type":"Point"}
}