{
  "type": "Feature",
  "properties": {
    "iso:country":"US",
    "sg:address":"1323 Lakeview Dr",
    "sg:city":"Parkersburg",
    "sg:classifiers":[
        {
            "category":"Restaurant",
            "type":"Food & Drink"
        }
    ],
    "sg:menulink":"http://www.allmenus.com/wv/parkersburg/71716-pizza-hut/menu/",
    "sg:phone":"+1 304 422 7135",
    "sg:postcode":"26104",
    "sg:province":"WV",
    "sg:tags":[
        "american",
        "pizza"
    ],
    "wof:name":"Pizza Hut",
    "wof:placetype":"venue"
},
  "geometry": {"coordinates":[-81.534605,39.288329],"type":"Point"}
}