{
  "type": "Feature",
  "properties": {
    "addr:full":"3 Cavalier Dr Huntington WV 25701",
    "addr:housenumber":"3",
    "addr:postcode":"25701",
    "addr:street":"Cavalier Dr",
    "iso:country":"US",
    "sg:address":"3 Cavalier Dr",
    "sg:city":"Huntington",
    "sg:classifiers":[
        {
            "category":"Real Estate",
            "subcategory":"Real Estate Operator",
            "type":"Services"
        }
    ],
    "sg:phone":"+1 304 523 4441",
    "sg:postcode":"25701",
    "sg:province":"WV",
    "sg:tags":[
        "building",
        "apartment"
    ],
    "wof:name":"Aldan Rentals Inc",
    "wof:placetype":"venue"
},
  "geometry": {"coordinates":[-82.449389,38.405217],"type":"Point"}
}