{
  "type": "Feature",
  "properties": {
    "addr:full":"101 Red Deer Dr Hurricane WV 25526",
    "addr:housenumber":"101",
    "addr:postcode":"25526",
    "addr:street":"Red Deer Dr",
    "iso:country":"US",
    "sg:address":"101 Red Deer Dr",
    "sg:city":"Hurricane",
    "sg:classifiers":[
        {
            "category":"Real Estate",
            "subcategory":"Real Estate Operator",
            "type":"Services"
        }
    ],
    "sg:phone":"+1 304 757 7804",
    "sg:postcode":"25526",
    "sg:province":"WV",
    "sg:tags":[
        "apartment"
    ],
    "wof:name":"Red Deer Apartments",
    "wof:placetype":"venue"
},
  "geometry": {"coordinates":[-81.94768500000001,38.456306],"type":"Point"}
}