{
  "type": "Feature",
  "properties": {
    "addr:full":"3966 Teays Valley Rd Hurricane WV 25526",
    "addr:housenumber":"3966",
    "addr:postcode":"25526",
    "addr:street":"Teays Valley Rd",
    "iso:country":"US",
    "sg:address":"3966 Teays Valley Rd",
    "sg:city":"Hurricane",
    "sg:classifiers":[
        {
            "category":"Professional",
            "subcategory":"Business Services",
            "type":"Services"
        }
    ],
    "sg:phone":"+1 304 757 8931",
    "sg:postcode":"25526",
    "sg:province":"WV",
    "wof:name":"Meadows Art Design",
    "wof:placetype":"venue"
},
  "geometry": {"coordinates":[-81.940421,38.448558],"type":"Point"}
}