{
  "type": "Feature",
  "properties": {
    "iso:country":"US",
    "sg:address":"4545 Daybrook Rd",
    "sg:city":"Fairview",
    "sg:classifiers":[
        {
            "category":"Manufacturing",
            "subcategory":"Wood Products",
            "type":"Manufacturing & Wholesale Goods"
        }
    ],
    "sg:phone":"+1 304 449 1876",
    "sg:postcode":"26570",
    "sg:province":"WV",
    "sg:tags":[
        "mfg"
    ],
    "wof:name":"TCS Wood Shack",
    "wof:placetype":"venue"
},
  "geometry": {"coordinates":[-80.24326000000001,39.603063],"type":"Point"}
}