{
  "type": "Feature",
  "properties": {
    "addr:full":"420 Oakwood Ave Williamstown WV 26187",
    "addr:housenumber":"420",
    "addr:postcode":"26187",
    "addr:street":"Oakwood Ave",
    "iso:country":"US",
    "sg:address":"420 Oakwood Ave",
    "sg:city":"Williamstown",
    "sg:classifiers":[
        {
            "category":"Government",
            "subcategory":"Office",
            "type":"Public Place"
        }
    ],
    "sg:phone":"+1 304 375 2317",
    "sg:postcode":"26187",
    "sg:province":"WV",
    "wof:name":"Us Government",
    "wof:placetype":"venue"
},
  "geometry": {"coordinates":[-81.44715100000001,39.400632],"type":"Point"}
}