{
  "type": "Feature",
  "properties": {
    "addr:full":"311 Mountainview Rd Morgantown WV 26508",
    "addr:housenumber":"311",
    "addr:postcode":"26508",
    "addr:street":"Mountainview Rd",
    "iso:country":"US",
    "sg:address":"311 Mountainview Rd",
    "sg:city":"Morgantown",
    "sg:classifiers":[
        {
            "category":"Home & Garden",
            "subcategory":"Furniture",
            "type":"Retail Goods"
        },
        {
            "category":"Building & Trades",
            "subcategory":"Construction",
            "type":"Services"
        }
    ],
    "sg:phone":"+1 304 296 1002",
    "sg:postcode":"26508",
    "sg:province":"WV",
    "sg:tags":[
        "top",
        "counter",
        "contractor"
    ],
    "wof:name":"Mountain View Counter Tops & W",
    "wof:placetype":"venue"
},
  "geometry": {"coordinates":[-79.880444,39.54557],"type":"Point"}
}