{
  "type": "Feature",
  "properties": {
    "iso:country":"US",
    "sg:address":"1228 1st St",
    "sg:city":"Moundsville",
    "sg:classifiers":[
        {
            "category":"Organizations",
            "subcategory":"Non-profit Organization",
            "type":"Services"
        }
    ],
    "sg:phone":"+1 304 845 0110",
    "sg:postcode":"26041",
    "sg:province":"WV",
    "wof:name":"Moundsville Volunteer Fire",
    "wof:placetype":"venue"
},
  "geometry": {"coordinates":[-80.73876199999999,39.925323],"type":"Point"}
}