{
  "type": "Feature",
  "properties": {
    "iso:country":"US",
    "sg:address":"301 Airport Rd",
    "sg:city":"Beckley",
    "sg:classifiers":[
        {
            "category":"Government",
            "subcategory":"Office",
            "type":"Public Place"
        }
    ],
    "sg:phone":"+1 304 252 6426",
    "sg:postcode":"25813",
    "sg:province":"WV",
    "sg:tags":[
        "federal",
        "program"
    ],
    "wof:name":"US Agricultural Research Svc",
    "wof:placetype":"venue"
},
  "geometry": {"coordinates":[-81.115287,37.764214],"type":"Point"}
}