{
  "type": "Feature",
  "properties": {
    "iso:country":"US",
    "sg:address":"10 Fairway Dr",
    "sg:city":"Huntington",
    "sg:classifiers":[
        {
            "category":"Restaurant",
            "type":"Food & Drink"
        }
    ],
    "sg:phone":"+1 304 736 0504",
    "sg:postcode":"25705",
    "sg:province":"WV",
    "sg:tags":[
        "eating"
    ],
    "wof:name":"Tascalis",
    "wof:placetype":"venue"
},
  "geometry": {"coordinates":[-82.328446,38.421021],"type":"Point"}
}