{
  "type": "Feature",
  "properties": {
    "iso:country":"US",
    "sg:address":"661 7th St",
    "sg:city":"Parkersburg",
    "sg:classifiers":[
        {
            "category":"Autos & Motor Vehicles",
            "subcategory":"Automobile Sales",
            "type":"Retail Goods"
        }
    ],
    "sg:phone":"+1 304 422 6746",
    "sg:postcode":"26101",
    "sg:province":"WV",
    "sg:tags":[
        "car",
        "dealer"
    ],
    "wof:name":"Burdette Motors",
    "wof:placetype":"venue"
},
  "geometry": {"coordinates":[-81.550997,39.263724],"type":"Point"}
}