{
  "type": "Feature",
  "properties": {
    "addr:full":"1042 Virginia Ave Fairmont WV 26554",
    "addr:housenumber":"1042",
    "addr:postcode":"26554",
    "addr:street":"Virginia Ave",
    "iso:country":"US",
    "sg:address":"1042 Virginia Ave",
    "sg:city":"Fairmont",
    "sg:classifiers":[
        {
            "category":"Recreation",
            "type":"Entertainment"
        }
    ],
    "sg:phone":"+1 304 363 2308",
    "sg:postcode":"26554",
    "sg:province":"WV",
    "wof:name":"Wildlife Express Incorporated",
    "wof:placetype":"venue"
},
  "geometry": {"coordinates":[-80.151663,39.471354],"type":"Point"}
}