{
  "type": "Feature",
  "properties": {
    "iso:country":"US",
    "sg:address":"9 Grandview Pl",
    "sg:city":"Princeton",
    "sg:classifiers":[
        {
            "category":"Restaurant",
            "type":"Food & Drink"
        }
    ],
    "sg:phone":"+1 304 487 2568",
    "sg:postcode":"24740",
    "sg:province":"WV",
    "wof:name":"Roma Pizzeria Restaurant III",
    "wof:placetype":"venue"
},
  "geometry": {"coordinates":[-81.109246,37.381196],"type":"Point"}
}