{
  "type": "Feature",
  "properties": {
    "iso:country":"US",
    "sg:address":"5803 Maccorkle Ave",
    "sg:city":"Saint Albans",
    "sg:classifiers":[
        {
            "category":"Wholesale",
            "subcategory":"Auto Parts",
            "type":"Manufacturing & Wholesale Goods"
        }
    ],
    "sg:phone":"+1 304 768 0751",
    "sg:postcode":"25177",
    "sg:province":"WV",
    "sg:tags":[
        "body",
        "automotive",
        "repair",
        "supply"
    ],
    "wof:name":"D A R Collision Parts Inc",
    "wof:placetype":"venue"
},
  "geometry": {"coordinates":[-81.75339099999999,38.356671],"type":"Point"}
}