{
  "type": "Feature",
  "properties": {
    "addr:full":"3 Ada Dr New Martinsville WV 26155",
    "addr:housenumber":"3",
    "addr:postcode":"26155",
    "addr:street":"Ada Dr",
    "iso:country":"US",
    "sg:address":"3 Ada Dr",
    "sg:city":"New Martinsville",
    "sg:classifiers":[
        {
            "category":"Personal",
            "subcategory":"Beauty Salon",
            "type":"Services"
        }
    ],
    "sg:phone":"+1 304 455 3313",
    "sg:postcode":"26155",
    "sg:province":"WV",
    "sg:tags":[
        "shop"
    ],
    "wof:name":"R M S Hair Stylist",
    "wof:placetype":"venue"
},
  "geometry": {"coordinates":[-80.856534,39.686139],"type":"Point"}
}