{
  "type": "Feature",
  "properties": {
    "iso:country":"US",
    "sg:address":"1100 Market St",
    "sg:city":"Parkersburg",
    "sg:classifiers":[
        {
            "category":"Social Services",
            "type":"Services"
        }
    ],
    "sg:phone":"+1 304 428 8721",
    "sg:postcode":"26101",
    "sg:province":"WV",
    "wof:name":"Kids First Program",
    "wof:placetype":"venue"
},
  "geometry": {"coordinates":[-81.553477,39.271001],"type":"Point"}
}