{
  "type": "Feature",
  "properties": {
    "addr:full":"706 Ridgewood Rd Huntington WV 25701",
    "addr:housenumber":"706",
    "addr:postcode":"25701",
    "addr:street":"Ridgewood Rd",
    "iso:country":"US",
    "sg:address":"706 Ridgewood Rd",
    "sg:city":"Huntington",
    "sg:classifiers":[
        {
            "category":"Organizations",
            "subcategory":"Political Organization",
            "type":"Services"
        }
    ],
    "sg:phone":"+1 304 525 2244",
    "sg:postcode":"25701",
    "sg:province":"WV",
    "wof:name":"League of Women Voters of US",
    "wof:placetype":"venue"
},
  "geometry": {"coordinates":[-82.440752,38.403445],"type":"Point"}
}