{
  "type": "Feature",
  "properties": {
    "addr:full":"515 Market St Parkersburg WV 26101",
    "addr:housenumber":"515",
    "addr:postcode":"26101",
    "addr:street":"Market St",
    "iso:country":"US",
    "sg:address":"515 Market St",
    "sg:city":"Parkersburg",
    "sg:classifiers":[
        {
            "category":"Food & Beverages",
            "subcategory":"Groceries & Convenience Stores",
            "type":"Retail Goods"
        }
    ],
    "sg:phone":"+1 304 422 2585",
    "sg:postcode":"26101",
    "sg:province":"WV",
    "sg:tags":[
        "market"
    ],
    "wof:name":"Fifth At Market",
    "wof:placetype":"venue"
},
  "geometry": {"coordinates":[-81.5598,39.266138],"type":"Point"}
}