{
  "type": "Feature",
  "properties": {
    "addr:full":"616 Washington St St Albans WV 25177",
    "addr:housenumber":"616",
    "addr:postcode":"25177",
    "addr:street":"Washington St",
    "iso:country":"US",
    "sg:address":"616 Washington St",
    "sg:city":"St Albans",
    "sg:classifiers":[
        {
            "category":"Utilities",
            "subcategory":"Natural Gas",
            "type":"Services"
        }
    ],
    "sg:phone":"+1 304 727 3677",
    "sg:postcode":"25177",
    "sg:province":"WV",
    "sg:tags":[
        "company"
    ],
    "wof:name":"MCF Inc",
    "wof:placetype":"venue"
},
  "geometry": {"coordinates":[-81.82137400000001,38.382264],"type":"Point"}
}