{
  "type": "Feature",
  "properties": {
    "addr:full":"1145 Main St Milton WV 25541",
    "addr:housenumber":"1145",
    "addr:postcode":"25541",
    "addr:street":"Main St",
    "iso:country":"US",
    "sg:address":"1145 Main St",
    "sg:city":"Milton",
    "sg:classifiers":[
        {
            "category":"Restaurant",
            "type":"Food & Drink"
        }
    ],
    "sg:phone":"+1 304 743 5759",
    "sg:postcode":"25541",
    "sg:province":"WV",
    "sg:tags":[
        "eating"
    ],
    "wof:name":"Pizza Hut",
    "wof:placetype":"venue"
},
  "geometry": {"coordinates":[-82.146725,38.436705],"type":"Point"}
}