{
  "type": "Feature",
  "properties": {
    "addr:full":"635 Fayette St Oak Hill WV 25951",
    "addr:housenumber":"635",
    "addr:postcode":"25951",
    "addr:street":"Fayette St",
    "iso:country":"US",
    "sg:address":"635 Fayette St",
    "sg:city":"Oak Hill",
    "sg:classifiers":[
        {
            "category":"Shopping",
            "subcategory":"Pharmacy",
            "type":"Retail Goods"
        }
    ],
    "sg:phone":"+1 304 465 0511",
    "sg:postcode":"25951",
    "sg:province":"WV",
    "sg:tags":[
        "drug",
        "store"
    ],
    "wof:name":"CVS",
    "wof:placetype":"venue"
},
  "geometry": {"coordinates":[-80.878964,37.6772],"type":"Point"}
}