{
  "type": "Feature",
  "properties": {
    "iso:country":"US",
    "sg:address":"1710 Harper Rd",
    "sg:city":"Beckley",
    "sg:classifiers":[
        {
            "category":"Health Services",
            "subcategory":"Hospital",
            "type":"Services"
        }
    ],
    "sg:phone":"+1 304 256 4100",
    "sg:postcode":"25801",
    "sg:province":"WV",
    "sg:tags":[
        "general"
    ],
    "wof:name":"Columbia Raleigh General Hosp",
    "wof:placetype":"venue"
},
  "geometry": {"coordinates":[-81.203012,37.785968],"type":"Point"}
}