{
  "type": "Feature",
  "properties": {
    "addr:full":"5388 Big Tyler Rd Charleston WV 25313",
    "addr:housenumber":"5388",
    "addr:postcode":"25313",
    "addr:street":"Big Tyler Rd",
    "iso:country":"US",
    "sg:address":"5388 Big Tyler Rd",
    "sg:city":"Charleston",
    "sg:classifiers":[
        {
            "category":"Insurance",
            "subcategory":"Insurance Agent",
            "type":"Services"
        }
    ],
    "sg:phone":"+1 304 776 4176",
    "sg:postcode":"25313",
    "sg:province":"WV",
    "wof:name":"Principal Life Insurance Co",
    "wof:placetype":"venue"
},
  "geometry": {"coordinates":[-81.7804,38.430594],"type":"Point"}
}