{
  "type": "Feature",
  "properties": {
    "iso:country":"US",
    "sg:address":"290 Three Springs Dr",
    "sg:city":"Weirton",
    "sg:classifiers":[
        {
            "category":"Home & Garden",
            "subcategory":"Building Materials",
            "type":"Retail Goods"
        }
    ],
    "sg:phone":"+1 304 723 7222",
    "sg:postcode":"26062",
    "sg:province":"WV",
    "sg:tags":[
        "center"
    ],
    "wof:name":"Busy Beaver Building Ctr",
    "wof:placetype":"venue"
},
  "geometry": {"coordinates":[-80.549657,40.405275],"type":"Point"}
}