{
  "type": "Feature",
  "properties": {
    "iso:country":"US",
    "sg:address":"400 Hal Greer Blvd",
    "sg:city":"Huntington",
    "sg:classifiers":[
        {
            "category":"Education",
            "subcategory":"College",
            "type":"Public Place"
        }
    ],
    "sg:phone":"+1 304 696 2430",
    "sg:postcode":"25701",
    "sg:province":"WV",
    "wof:name":"Chemistry Department",
    "wof:placetype":"venue"
},
  "geometry": {"coordinates":[-82.431646,38.422148],"type":"Point"}
}