{
  "type": "Feature",
  "properties": {
    "addr:full":"2715 Murdoch Ave Parkersburg WV 26101",
    "addr:housenumber":"2715",
    "addr:postcode":"26101",
    "addr:street":"Murdoch Ave",
    "iso:country":"US",
    "sg:address":"2715 Murdoch Ave",
    "sg:city":"Parkersburg",
    "sg:classifiers":[
        {
            "category":"Shopping",
            "subcategory":"Used Merchandise",
            "type":"Retail Goods"
        },
        {
            "category":"Shopping",
            "subcategory":"Clothing, Apparel, & Fashions",
            "type":"Retail Goods"
        }
    ],
    "sg:phone":"+1 304 422 2005",
    "sg:postcode":"26101",
    "sg:province":"WV",
    "sg:tags":[
        "infant",
        "wear"
    ],
    "wof:name":"Once Upon A Child",
    "wof:placetype":"venue"
},
  "geometry": {"coordinates":[-81.547262,39.284622],"type":"Point"}
}