{
  "type": "Feature",
  "properties": {
    "iso:country":"US",
    "sg:address":"5218 Walnut Valley Dr",
    "sg:city":"Charleston",
    "sg:classifiers":[
        {
            "category":"Retail",
            "subcategory":"Repair Shop",
            "type":"Services"
        }
    ],
    "sg:phone":"+1 304 776 8440",
    "sg:postcode":"25313",
    "sg:province":"WV",
    "sg:tags":[
        "equipment",
        "consulting",
        "dental",
        "se",
        "x"
    ],
    "wof:name":"Intech Controls Inc",
    "wof:placetype":"venue"
},
  "geometry": {"coordinates":[-81.751806,38.438559],"type":"Point"}
}