{
  "type": "Feature",
  "properties": {
    "iso:country":"US",
    "sg:address":"2400 National Rd",
    "sg:city":"Wheeling",
    "sg:classifiers":[
        {
            "category":"Travel",
            "subcategory":"Hotels & Motels",
            "type":"Entertainment"
        }
    ],
    "sg:phone":"+1 304 243 9400",
    "sg:postcode":"26003",
    "sg:province":"WV",
    "sg:tags":[
        "lodging"
    ],
    "sg:website":"http://www.super8.com",
    "wof:name":"Super 8 Motel",
    "wof:placetype":"venue"
},
  "geometry": {"coordinates":[-80.654022,40.045731],"type":"Point"}
}