{
  "type": "Feature",
  "properties": {
    "addr:full":"448 3rd Ave Montgomery WV 25136",
    "addr:housenumber":"448",
    "addr:postcode":"25136",
    "addr:street":"3Rd Ave",
    "iso:country":"US",
    "sg:address":"448 3rd Ave",
    "sg:city":"Montgomery",
    "sg:classifiers":[
        {
            "category":"Restaurant",
            "type":"Food & Drink"
        }
    ],
    "sg:phone":"+1 304 442 2777",
    "sg:postcode":"25136",
    "sg:province":"WV",
    "wof:name":"Subway Sandwiches & Salads",
    "wof:placetype":"venue"
},
  "geometry": {"coordinates":[-81.324366,38.180896],"type":"Point"}
}