{
  "type": "Feature",
  "properties": {
    "addr:full":"815 Court St Charleston WV 25301",
    "addr:housenumber":"815",
    "addr:postcode":"25301",
    "addr:street":"Court St",
    "iso:country":"US",
    "sg:address":"815 Court St",
    "sg:city":"Charleston",
    "sg:classifiers":[
        {
            "category":"Organizations",
            "subcategory":"Professional Association",
            "type":"Services"
        }
    ],
    "sg:phone":"+1 304 746 0141",
    "sg:postcode":"25301",
    "sg:province":"WV",
    "wof:name":"Habitat For Humanity",
    "wof:placetype":"venue"
},
  "geometry": {"coordinates":[-81.62908899999999,38.35513],"type":"Point"}
}