{
  "type": "Feature",
  "properties": {
    "iso:country":"US",
    "sg:address":"3184 Booten Creek Rd",
    "sg:city":"Barboursville",
    "sg:classifiers":[
        {
            "category":"Building & Trades",
            "subcategory":"Construction",
            "type":"Services"
        }
    ],
    "sg:phone":"+1 304 733 1985",
    "sg:postcode":"25504",
    "sg:province":"WV",
    "sg:tags":[
        "house"
    ],
    "wof:name":"Gue Construction Company",
    "wof:placetype":"venue"
},
  "geometry": {"coordinates":[-82.295646,38.380469],"type":"Point"}
}