{
  "type": "Feature",
  "properties": {
    "iso:country":"US",
    "sg:address":"5 Courtney Dr",
    "sg:city":"Charleston",
    "sg:classifiers":[
        {
            "category":"Health Services",
            "subcategory":"Doctor",
            "type":"Services"
        }
    ],
    "sg:phone":"+1 304 926 0955",
    "sg:postcode":"25304",
    "sg:province":"WV",
    "sg:tags":[
        "medical"
    ],
    "wof:name":"Cataract Rfrctive Surgery Inst",
    "wof:placetype":"venue"
},
  "geometry": {"coordinates":[-81.59508,38.324427],"type":"Point"}
}