{
  "type": "Feature",
  "properties": {
    "iso:country":"US",
    "sg:address":"3106 Kanawha Ter",
    "sg:city":"Saint Albans",
    "sg:classifiers":[
        {
            "category":"Real Estate",
            "subcategory":"Real Estate Operator",
            "type":"Services"
        }
    ],
    "sg:phone":"+1 304 722 2493",
    "sg:postcode":"25177",
    "sg:province":"WV",
    "sg:tags":[
        "mobile",
        "home",
        "site"
    ],
    "wof:name":"Maples Trailer Court",
    "wof:placetype":"venue"
},
  "geometry": {"coordinates":[-81.787184,38.374925],"type":"Point"}
}