{
  "type": "Feature",
  "properties": {
    "addr:full":"17 Pembroke Ln Huntington WV 25705",
    "addr:housenumber":"17",
    "addr:postcode":"25705",
    "addr:street":"Pembroke Ln",
    "iso:country":"US",
    "sg:address":"17 Pembroke Ln",
    "sg:city":"Huntington",
    "sg:classifiers":[
        {
            "category":"Wholesale",
            "subcategory":"Non-durable Goods",
            "type":"Manufacturing & Wholesale Goods"
        }
    ],
    "sg:phone":"+1 304 736 8408",
    "sg:postcode":"25705",
    "sg:province":"WV",
    "wof:name":"Parkees Puzzles & Imports LLC",
    "wof:placetype":"venue"
},
  "geometry": {"coordinates":[-82.31207499999999,38.425357],"type":"Point"}
}