{
  "type": "Feature",
  "properties": {
    "iso:country":"US",
    "sg:address":"525 33rd St",
    "sg:city":"Parkersburg",
    "sg:classifiers":[
        {
            "category":"Professional",
            "subcategory":"Research",
            "type":"Services"
        }
    ],
    "sg:phone":"+1 304 428 8909",
    "sg:postcode":"26101",
    "sg:province":"WV",
    "sg:tags":[
        "environmental",
        "testing"
    ],
    "wof:name":"S A S",
    "wof:placetype":"venue"
},
  "geometry": {"coordinates":[-81.549994,39.292642],"type":"Point"}
}