{
  "type": "Feature",
  "properties": {
    "iso:country":"US",
    "sg:address":"110 Kennedy Ave",
    "sg:city":"Newell",
    "sg:classifiers":[
        {
            "category":"Recreation",
            "subcategory":"Marina",
            "type":"Entertainment"
        }
    ],
    "sg:phone":"+1 304 387 3063",
    "sg:postcode":"26037",
    "sg:province":"WV",
    "wof:name":"Kennedy Marina",
    "wof:placetype":"venue"
},
  "geometry": {"coordinates":[-80.58007000000001,40.317942],"type":"Point"}
}