{
  "type": "Feature",
  "properties": {
    "iso:country":"US",
    "sg:address":"508 Indiana Ave",
    "sg:city":"Chester",
    "sg:classifiers":[
        {
            "category":"Organizations",
            "subcategory":"Religious Organization",
            "type":"Services"
        }
    ],
    "sg:phone":"+1 304 387 2003",
    "sg:postcode":"26034",
    "sg:province":"WV",
    "sg:tags":[
        "church"
    ],
    "wof:name":"Westminster Presbyterian Chr",
    "wof:placetype":"venue"
},
  "geometry": {"coordinates":[-80.560886,40.612829],"type":"Point"}
}