{
  "type": "Feature",
  "properties": {
    "addr:full":"104 E McDonald Ave Man WV 25635",
    "addr:housenumber":"104",
    "addr:postcode":"25635",
    "addr:street":"E Mcdonald Ave",
    "iso:country":"US",
    "sg:address":"104 E McDonald Ave",
    "sg:city":"Man",
    "sg:classifiers":[
        {
            "category":"Organizations",
            "subcategory":"Religious Organization",
            "type":"Services"
        }
    ],
    "sg:phone":"+1 304 583 9743",
    "sg:postcode":"25635",
    "sg:province":"WV",
    "sg:tags":[
        "church"
    ],
    "wof:name":"Bruce Mcdonald Memorial United",
    "wof:placetype":"venue"
},
  "geometry": {"coordinates":[-81.87765899999999,37.73976],"type":"Point"}
}