{
  "type": "Feature",
  "properties": {
    "iso:country":"US",
    "sg:address":"167 16th St",
    "sg:city":"Wheeling",
    "sg:classifiers":[
        {
            "category":"Restaurant",
            "type":"Food & Drink"
        }
    ],
    "sg:phone":"+1 304 232 5654",
    "sg:postcode":"26003",
    "sg:province":"WV",
    "sg:tags":[
        "drinking",
        "eating"
    ],
    "wof:name":"Keg Und Kraut Inc",
    "wof:placetype":"venue"
},
  "geometry": {"coordinates":[-80.715987,40.064547],"type":"Point"}
}