{
  "type": "Feature",
  "properties": {
    "iso:country":"US",
    "sg:address":"6201 Webster Rd",
    "sg:city":"Summersville",
    "sg:classifiers":[
        {
            "category":"Education",
            "subcategory":"Library",
            "type":"Public Place"
        }
    ],
    "sg:phone":"+1 304 872 0844",
    "sg:postcode":"26651",
    "sg:province":"WV",
    "wof:name":"Summersville Public Library",
    "wof:placetype":"venue"
},
  "geometry": {"coordinates":[-80.831557,38.310908],"type":"Point"}
}