{
  "type": "Feature",
  "properties": {
    "iso:country":"US",
    "sg:address":"405 Main St",
    "sg:city":"Point Pleasant",
    "sg:classifiers":[
        {
            "category":"Restaurant",
            "type":"Food & Drink"
        }
    ],
    "sg:phone":"+1 304 675 8080",
    "sg:postcode":"25550",
    "sg:province":"WV",
    "wof:name":"Red Parrot Cafe",
    "wof:placetype":"venue"
},
  "geometry": {"coordinates":[-82.13884299999999,38.842626],"type":"Point"}
}