{
  "type": "Feature",
  "properties": {
    "iso:country":"US",
    "sg:address":"4501 Maccorkle Ave",
    "sg:city":"Charleston",
    "sg:classifiers":[
        {
            "category":"Shopping",
            "subcategory":"Pharmacy",
            "type":"Retail Goods"
        }
    ],
    "sg:phone":"+1 304 766 8484",
    "sg:postcode":"25309",
    "sg:province":"WV",
    "wof:name":"Bee Well Pharmacy",
    "wof:placetype":"venue"
},
  "geometry": {"coordinates":[-81.725025,38.356114],"type":"Point"}
}