{
  "type": "Feature",
  "properties": {
    "iso:country":"US",
    "sg:address":"2539 Grandview Rd",
    "sg:city":"Beaver",
    "sg:classifiers":[
        {
            "category":"Food & Beverages",
            "subcategory":"Fruits & Vegetables",
            "type":"Retail Goods"
        }
    ],
    "sg:phone":"+1 304 763 3756",
    "sg:postcode":"25813",
    "sg:province":"WV",
    "sg:tags":[
        "produce"
    ],
    "wof:name":"Grandview Country Store",
    "wof:placetype":"venue"
},
  "geometry": {"coordinates":[-81.064032,37.780178],"type":"Point"}
}