{
  "type": "Feature",
  "properties": {
    "iso:country":"US",
    "sg:address":"1756 Mileground Rd",
    "sg:city":"Fairmont",
    "sg:classifiers":[
        {
            "category":"Wholesale",
            "subcategory":"Office Equipment",
            "type":"Manufacturing & Wholesale Goods"
        },
        {
            "category":"Shopping",
            "type":"Retail Goods"
        }
    ],
    "sg:phone":"+1 304 291 5775",
    "sg:postcode":"26505",
    "sg:province":"WV",
    "sg:tags":[
        "machine",
        "duplicating",
        "merchandise",
        "copying"
    ],
    "wof:name":"Document Solutions",
    "wof:placetype":"venue"
},
  "geometry": {"coordinates":[-79.928012,39.644194],"type":"Point"}
}