{
  "type": "Feature",
  "properties": {
    "iso:country":"US",
    "sg:address":"31 Burdette St",
    "sg:city":"Point Pleasant",
    "sg:classifiers":[
        {
            "category":"Arts & Performance",
            "subcategory":"Theater",
            "type":"Entertainment"
        }
    ],
    "sg:phone":"+1 304 675 2440",
    "sg:postcode":"25550",
    "sg:province":"WV",
    "sg:tags":[
        "live",
        "music"
    ],
    "wof:name":"R & H DJ Svc",
    "wof:placetype":"venue"
},
  "geometry": {"coordinates":[-82.127833,38.881491],"type":"Point"}
}