{
  "type": "Feature",
  "properties": {
    "iso:country":"US",
    "sg:address":"455 Winfield Rd",
    "sg:city":"St Albans",
    "sg:classifiers":[
        {
            "category":"Professional",
            "type":"Services"
        }
    ],
    "sg:phone":"+1 304 722 0498",
    "sg:postcode":"25177",
    "sg:province":"WV",
    "sg:tags":[
        "establishment"
    ],
    "wof:name":"Dockery's",
    "wof:placetype":"venue"
},
  "geometry": {"coordinates":[-81.856145,38.400113],"type":"Point"}
}