{
  "type": "Feature",
  "properties": {
    "addr:full":"101 Holland Ave Morgantown WV 26501",
    "addr:housenumber":"101",
    "addr:postcode":"26501",
    "addr:street":"Holland Ave",
    "iso:country":"US",
    "sg:address":"101 Holland Ave",
    "sg:city":"Morgantown",
    "sg:classifiers":[
        {
            "category":"Insurance",
            "subcategory":"Insurance Agent",
            "type":"Services"
        }
    ],
    "sg:phone":"+1 304 292 7212",
    "sg:postcode":"26501",
    "sg:province":"WV",
    "wof:name":"State Farm Insurance",
    "wof:placetype":"venue"
},
  "geometry": {"coordinates":[-79.962497,39.633604],"type":"Point"}
}