{
  "type": "Feature",
  "properties": {
    "iso:country":"US",
    "sg:address":"102 Jones St",
    "sg:city":"Bluefield",
    "sg:classifiers":[
        {
            "category":"Organizations",
            "subcategory":"Religious Organization",
            "type":"Services"
        }
    ],
    "sg:phone":"+1 304 327 5076",
    "sg:postcode":"24701",
    "sg:province":"WV",
    "wof:name":"John Stwart Untd Mthdst Church",
    "wof:placetype":"venue"
},
  "geometry": {"coordinates":[-81.22004200000001,37.266606],"type":"Point"}
}