{
  "type": "Feature",
  "properties": {
    "addr:full":"300 Sevilla Dr Hurricane WV 25526",
    "addr:housenumber":"300",
    "addr:postcode":"25526",
    "addr:street":"Sevilla Dr",
    "iso:country":"US",
    "sg:address":"300 Sevilla Dr",
    "sg:city":"Hurricane",
    "sg:classifiers":[
        {
            "category":"Health Services",
            "subcategory":"Nursing And Care Facility",
            "type":"Services"
        }
    ],
    "sg:phone":"+1 304 757 6805",
    "sg:postcode":"25526",
    "sg:province":"WV",
    "sg:tags":[
        "skilled",
        "intermediate"
    ],
    "wof:name":"Sunbridge Care/Rehab Putnam",
    "wof:placetype":"venue"
},
  "geometry": {"coordinates":[-81.95144999999999,38.45247],"type":"Point"}
}