{
  "type": "Feature",
  "properties": {
    "iso:country":"US",
    "sg:address":"10 Kenton Dr",
    "sg:city":"Charleston",
    "sg:classifiers":[
        {
            "category":"Mining & Drilling",
            "type":"Manufacturing & Wholesale Goods"
        }
    ],
    "sg:phone":"+1 304 357 5700",
    "sg:postcode":"25311",
    "sg:province":"WV",
    "sg:tags":[
        "underground",
        "coal",
        "bituminous",
        "surface"
    ],
    "wof:name":"Ark Land Company",
    "wof:placetype":"venue"
},
  "geometry": {"coordinates":[-81.603005,38.353273],"type":"Point"}
}