{
  "type": "Feature",
  "properties": {
    "addr:full":"419 Fairmont Ave Fairmont WV 26554",
    "addr:housenumber":"419",
    "addr:postcode":"26554",
    "addr:street":"Fairmont Ave",
    "iso:country":"US",
    "sg:address":"419 Fairmont Ave",
    "sg:city":"Fairmont",
    "sg:classifiers":[
        {
            "category":"Banks & Credit Unions",
            "subcategory":"Investment Brokerage",
            "type":"Services"
        }
    ],
    "sg:phone":"+1 304 363 7300",
    "sg:postcode":"26554",
    "sg:province":"WV",
    "sg:tags":[
        "stock",
        "bond"
    ],
    "wof:name":"Edward Jones Co",
    "wof:placetype":"venue"
},
  "geometry": {"coordinates":[-80.148642,39.480077],"type":"Point"}
}