{
  "type": "Feature",
  "properties": {
    "iso:country":"US",
    "sg:address":"1212 Washington Blvd",
    "sg:city":"Belpre",
    "sg:classifiers":[
        {
            "category":"Wholesale",
            "subcategory":"Machinery & Supplies",
            "type":"Manufacturing & Wholesale Goods"
        }
    ],
    "sg:phone":"+1 440 234 8566",
    "sg:postcode":"45714",
    "sg:province":"OH",
    "sg:tags":[
        "pump"
    ],
    "wof:name":"Estabrook Corp",
    "wof:placetype":"venue"
},
  "geometry": {"coordinates":[-81.584469,39.274475],"type":"Point"}
}