{
  "type": "Feature",
  "properties": {
    "iso:country":"US",
    "sg:address":"200 Teays Meadows",
    "sg:city":"Scott Depot",
    "sg:classifiers":[
        {
            "category":"Organizations",
            "subcategory":"Religious Organization",
            "type":"Services"
        }
    ],
    "sg:phone":"+1 304 757 2622",
    "sg:postcode":"25560",
    "sg:province":"WV",
    "sg:tags":[
        "clergy"
    ],
    "wof:name":"Basil R Hudson",
    "wof:placetype":"venue"
},
  "geometry": {"coordinates":[-81.92899199999999,38.43154],"type":"Point"}
}