{
  "type": "Feature",
  "properties": {
    "iso:country":"US",
    "sg:address":"443 S Washington St",
    "sg:city":"Berkeley Springs",
    "sg:classifiers":[
        {
            "category":"Retail",
            "subcategory":"Auto Repair",
            "type":"Services"
        }
    ],
    "sg:phone":"+1 304 258 4900",
    "sg:postcode":"25411",
    "sg:province":"WV",
    "sg:tags":[
        "repairing",
        "automobile"
    ],
    "wof:name":"Kelly Service Ctr",
    "wof:placetype":"venue"
},
  "geometry": {"coordinates":[-78.22965499999999,39.624264],"type":"Point"}
}