{
  "type": "Feature",
  "properties": {
    "iso:country":"US",
    "sg:address":"669 Broadway Ave",
    "sg:city":"Morgantown",
    "sg:classifiers":[
        {
            "category":"Professional",
            "type":"Services"
        }
    ],
    "sg:phone":"+1 304 598 8759",
    "sg:postcode":"26505",
    "sg:province":"WV",
    "wof:name":"Performance Coaching Svcs LLC",
    "wof:placetype":"venue"
},
  "geometry": {"coordinates":[-79.982804,39.665921],"type":"Point"}
}