{
  "type": "Feature",
  "properties": {
    "addr:full":"601 6th Ave St Albans WV 25177",
    "addr:housenumber":"601",
    "addr:postcode":"25177",
    "addr:street":"6Th Ave",
    "iso:country":"US",
    "sg:address":"601 6th Ave",
    "sg:city":"St Albans",
    "sg:classifiers":[
        {
            "category":"Mining & Drilling",
            "type":"Manufacturing & Wholesale Goods"
        }
    ],
    "sg:phone":"+1 304 722 9323",
    "sg:postcode":"25177",
    "sg:province":"WV",
    "sg:tags":[
        "coal",
        "shipping"
    ],
    "wof:name":"Federal Coal Co",
    "wof:placetype":"venue"
},
  "geometry": {"coordinates":[-81.83041799999999,38.384992],"type":"Point"}
}