{
  "type": "Feature",
  "properties": {
    "addr:full":"517 Orchard Hill Rd Beaver WV 25813",
    "addr:housenumber":"517",
    "addr:postcode":"25813",
    "addr:street":"Orchard Hill Rd",
    "iso:country":"US",
    "sg:address":"517 Orchard Hill Rd",
    "sg:city":"Beaver",
    "sg:classifiers":[
        {
            "category":"Building & Trades",
            "subcategory":"Construction",
            "type":"Services"
        }
    ],
    "sg:phone":"+1 304 252 8571",
    "sg:postcode":"25813",
    "sg:province":"WV",
    "sg:tags":[
        "contractor"
    ],
    "wof:name":"4 Phase Drywall Inc",
    "wof:placetype":"venue"
},
  "geometry": {"coordinates":[-81.136009,37.757053],"type":"Point"}
}