{
  "type": "Feature",
  "properties": {
    "addr:full":"189 Laurelwood Ln Logan WV 25636",
    "addr:housenumber":"189",
    "addr:postcode":"25636",
    "addr:street":"Laurelwood Ln",
    "iso:country":"US",
    "sg:address":"189 Laurelwood Ln",
    "sg:city":"Logan",
    "sg:classifiers":[
        {
            "category":"Real Estate",
            "subcategory":"Real Estate Operator",
            "type":"Services"
        }
    ],
    "sg:phone":"+1 304 946 2411",
    "sg:postcode":"25636",
    "sg:province":"WV",
    "sg:tags":[
        "apartment"
    ],
    "wof:name":"Laurelwood Apartments",
    "wof:placetype":"venue"
},
  "geometry": {"coordinates":[-81.99602299999999,37.815028],"type":"Point"}
}