{
  "type": "Feature",
  "properties": {
    "iso:country":"US",
    "sg:address":"9 Gifford Ave",
    "sg:city":"Morgantown",
    "sg:classifiers":[
        {
            "category":"Personal",
            "subcategory":"Beauty Salon",
            "type":"Services"
        }
    ],
    "sg:phone":"+1 304 291 2597",
    "sg:postcode":"26501",
    "sg:province":"WV",
    "sg:tags":[
        "shop"
    ],
    "wof:name":"Max Jada Hair Studio",
    "wof:placetype":"venue"
},
  "geometry": {"coordinates":[-79.940879,39.623733],"type":"Point"}
}