{
  "type": "Feature",
  "properties": {
    "iso:country":"US",
    "sg:address":"11 Baltimore St",
    "sg:city":"Fairmont",
    "sg:classifiers":[
        {
            "category":"Retail",
            "subcategory":"Auto Repair",
            "type":"Services"
        }
    ],
    "sg:phone":"+1 304 366 1644",
    "sg:postcode":"26554",
    "sg:province":"WV",
    "sg:tags":[
        "body",
        "automobile",
        "painting"
    ],
    "wof:name":"Wilson's",
    "wof:placetype":"venue"
},
  "geometry": {"coordinates":[-80.133259,39.488252],"type":"Point"}
}