{
  "type": "Feature",
  "properties": {
    "iso:country":"US",
    "sg:address":"17 Elizabeth St",
    "sg:city":"Weston",
    "sg:classifiers":[
        {
            "category":"Shopping",
            "subcategory":"Department Store",
            "type":"Retail Goods"
        }
    ],
    "sg:phone":"+1 304 269 1751",
    "sg:postcode":"26426",
    "sg:province":"WV",
    "sg:tags":[
        "shop"
    ],
    "wof:name":"Dollar General",
    "wof:placetype":"venue"
},
  "geometry": {"coordinates":[-80.56862599999999,39.281311],"type":"Point"}
}