{
  "type": "Feature",
  "properties": {
    "iso:country":"US",
    "sg:address":"182 Harper Park Dr",
    "sg:city":"Beckley",
    "sg:classifiers":[
        {
            "category":"Restaurant",
            "type":"Food & Drink"
        }
    ],
    "sg:menulink":"http://www.allmenus.com/wv/mcalpin/114157-pasquale-mira-italian-restaurant/menu/",
    "sg:phone":"+1 304 255 5253",
    "sg:postcode":"25801",
    "sg:province":"WV",
    "sg:tags":[
        "italian"
    ],
    "wof:name":"Pasquale Mira Italian Restaurant",
    "wof:placetype":"venue"
},
  "geometry": {"coordinates":[-81.217534,37.793498],"type":"Point"}
}