{
  "type": "Feature",
  "properties": {
    "addr:full":"107 Pike St Weirton WV 26062",
    "addr:housenumber":"107",
    "addr:postcode":"26062",
    "addr:street":"Pike St",
    "iso:country":"US",
    "sg:address":"107 Pike St",
    "sg:city":"Weirton",
    "sg:classifiers":[
        {
            "category":"Building & Trades",
            "subcategory":"Landscaping Services",
            "type":"Services"
        }
    ],
    "sg:phone":"+1 304 723 1042",
    "sg:postcode":"26062",
    "sg:province":"WV",
    "sg:tags":[
        "landscape",
        "contractor"
    ],
    "wof:name":"Trugreen LP",
    "wof:placetype":"venue"
},
  "geometry": {"coordinates":[-80.539627,40.407966],"type":"Point"}
}