{
  "type": "Feature",
  "properties": {
    "addr:full":"1310 Stafford Dr Princeton WV 24740",
    "addr:housenumber":"1310",
    "addr:postcode":"24740",
    "addr:street":"Stafford Dr",
    "iso:country":"US",
    "sg:address":"1310 Stafford Dr",
    "sg:city":"Princeton",
    "sg:classifiers":[
        {
            "category":"Restaurant",
            "type":"Food & Drink"
        }
    ],
    "sg:menulink":"http://www.allmenus.com/wv/princeton/206492-mcdonalds/menu/",
    "sg:postcode":"24740",
    "sg:province":"WV",
    "sg:tags":[
        "burger",
        "american"
    ],
    "wof:name":"McDonald's",
    "wof:placetype":"venue"
},
  "geometry": {"coordinates":[-81.099255,37.360929],"type":"Point"}
}