{
  "type": "Feature",
  "properties": {
    "addr:full":"103 Mills Ave Beckley WV 25801",
    "addr:housenumber":"103",
    "addr:postcode":"25801",
    "addr:street":"Mills Ave",
    "iso:country":"US",
    "sg:address":"103 Mills Ave",
    "sg:city":"Beckley",
    "sg:classifiers":[
        {
            "category":"Organizations",
            "subcategory":"Religious Organization",
            "type":"Services"
        }
    ],
    "sg:phone":"+1 304 252 1002",
    "sg:postcode":"25801",
    "sg:province":"WV",
    "sg:tags":[
        "church"
    ],
    "wof:name":"Saint Matthew AME Church",
    "wof:placetype":"venue"
},
  "geometry": {"coordinates":[-81.176543,37.765133],"type":"Point"}
}