{
  "type": "Feature",
  "properties": {
    "iso:country":"US",
    "sg:address":"187 Turnpike Rd",
    "sg:city":"Summersville",
    "sg:classifiers":[
        {
            "category":"Organizations",
            "subcategory":"Religious Organization",
            "type":"Services"
        }
    ],
    "sg:phone":"+1 304 872 6539",
    "sg:postcode":"26651",
    "sg:province":"WV",
    "sg:tags":[
        "church"
    ],
    "wof:name":"Gilboa First Church Of God",
    "wof:placetype":"venue"
},
  "geometry": {"coordinates":[-80.90006700000001,38.309671],"type":"Point"}
}