{
  "type": "Feature",
  "properties": {
    "iso:country":"US",
    "sg:address":"269 Stanaford Rd",
    "sg:city":"Beckley",
    "sg:classifiers":[
        {
            "category":"Health Services",
            "subcategory":"Doctor",
            "type":"Services"
        }
    ],
    "sg:phone":"+1 304 255 2000",
    "sg:postcode":"25801",
    "sg:province":"WV",
    "sg:tags":[
        "clinic"
    ],
    "wof:name":"Doctor's Express Care Inc",
    "wof:placetype":"venue"
},
  "geometry": {"coordinates":[-81.172622,37.795574],"type":"Point"}
}