{
  "type": "Feature",
  "properties": {
    "iso:country":"US",
    "sg:address":"582 Terry Ave",
    "sg:city":"Oak Hill",
    "sg:classifiers":[
        {
            "category":"Personal",
            "subcategory":"Beauty Salon",
            "type":"Services"
        }
    ],
    "sg:phone":"+1 304 465 7377",
    "sg:postcode":"25901",
    "sg:province":"WV",
    "wof:name":"Bonita's Beauty Salon",
    "wof:placetype":"venue"
},
  "geometry": {"coordinates":[-81.131254,37.980849],"type":"Point"}
}