{
  "type": "Feature",
  "properties": {
    "addr:full":"314 Penco Rd Weirton WV 26062",
    "addr:housenumber":"314",
    "addr:postcode":"26062",
    "addr:street":"Penco Rd",
    "iso:country":"US",
    "sg:address":"314 Penco Rd",
    "sg:city":"Weirton",
    "sg:classifiers":[
        {
            "category":"Health Services",
            "subcategory":"Doctor",
            "type":"Services"
        }
    ],
    "sg:phone":"+1 304 723 5200",
    "sg:postcode":"26062",
    "sg:province":"WV",
    "sg:tags":[
        "medical"
    ],
    "wof:name":"Luthra Sucheta DMD DDS",
    "wof:placetype":"venue"
},
  "geometry": {"coordinates":[-80.547096,40.409181],"type":"Point"}
}