{
  "type": "Feature",
  "properties": {
    "iso:country":"US",
    "sg:address":"801 Madison Ave",
    "sg:city":"Huntington",
    "sg:classifiers":[
        {
            "category":"Building & Trades",
            "subcategory":"Construction",
            "type":"Services"
        }
    ],
    "sg:phone":"+1 304 528 5649",
    "sg:postcode":"25704",
    "sg:province":"WV",
    "wof:name":"WV Division of Highways",
    "wof:placetype":"venue"
},
  "geometry": {"coordinates":[-82.46907400000001,38.411825],"type":"Point"}
}