{
  "type": "Feature",
  "properties": {
    "iso:country":"US",
    "sg:address":"1069 W Pike St",
    "sg:city":"Clarksburg",
    "sg:classifiers":[
        {
            "category":"Building & Trades",
            "subcategory":"Construction",
            "type":"Services"
        }
    ],
    "sg:phone":"+1 304 622 4487",
    "sg:postcode":"26301",
    "sg:province":"WV",
    "sg:tags":[
        "general",
        "contractor"
    ],
    "wof:name":"E H Hughes Co",
    "wof:placetype":"venue"
},
  "geometry": {"coordinates":[-80.35408200000001,39.286633],"type":"Point"}
}