{
  "type": "Feature",
  "properties": {
    "iso:country":"US",
    "sg:address":"1903 Grandview Rd",
    "sg:city":"Glen Dale",
    "sg:classifiers":[
        {
            "category":"Building & Trades",
            "subcategory":"Construction",
            "type":"Services"
        }
    ],
    "sg:phone":"+1 304 232 0080",
    "sg:postcode":"26038",
    "sg:province":"WV",
    "sg:tags":[
        "insulation",
        "contractor"
    ],
    "wof:name":"Als Valley Insulation Service",
    "wof:placetype":"venue"
},
  "geometry": {"coordinates":[-80.711876,39.971202],"type":"Point"}
}