{
  "type": "Feature",
  "properties": {
    "iso:country":"US",
    "sg:address":"72 Simpson Dr",
    "sg:city":"Huntington",
    "sg:classifiers":[
        {
            "category":"Real Estate",
            "subcategory":"Real Estate Agent",
            "type":"Services"
        }
    ],
    "sg:phone":"+1 304 522 4232",
    "sg:postcode":"25705",
    "sg:province":"WV",
    "wof:name":"Fairfield Realty",
    "wof:placetype":"venue"
},
  "geometry": {"coordinates":[-82.382845,38.401678],"type":"Point"}
}