{
  "type": "Feature",
  "properties": {
    "iso:country":"US",
    "sg:address":"4710 Chimney Dr",
    "sg:city":"Charleston",
    "sg:classifiers":[
        {
            "category":"Government",
            "subcategory":"Office",
            "type":"Public Place"
        }
    ],
    "sg:phone":"+1 304 965 0376",
    "sg:postcode":"25302",
    "sg:province":"WV",
    "wof:name":"Structural Barriers Compliance",
    "wof:placetype":"venue"
},
  "geometry": {"coordinates":[-81.53314399999999,38.405096],"type":"Point"}
}