{
  "type": "Feature",
  "properties": {
    "addr:full":"364 1st St Morgantown WV 26505",
    "addr:housenumber":"364",
    "addr:postcode":"26505",
    "addr:street":"1St St",
    "iso:country":"US",
    "sg:address":"364 1st St",
    "sg:city":"Morgantown",
    "sg:classifiers":[
        {
            "category":"Retail",
            "subcategory":"Self-service Laundry",
            "type":"Services"
        }
    ],
    "sg:phone":"+1 304 599 1999",
    "sg:postcode":"26505",
    "sg:province":"WV",
    "sg:tags":[
        "coin"
    ],
    "wof:name":"Man & Assoc Co",
    "wof:placetype":"venue"
},
  "geometry": {"coordinates":[-79.955566,39.638083],"type":"Point"}
}