{
  "type": "Feature",
  "properties": {
    "iso:country":"US",
    "sg:address":"107 W Main St",
    "sg:city":"Ripley",
    "sg:classifiers":[
        {
            "category":"Manufacturing",
            "subcategory":"Printing",
            "type":"Manufacturing & Wholesale Goods"
        }
    ],
    "sg:phone":"+1 304 372 8000",
    "sg:postcode":"25271",
    "sg:province":"WV",
    "sg:tags":[
        "newspaper"
    ],
    "wof:name":"Traders Guide",
    "wof:placetype":"venue"
},
  "geometry": {"coordinates":[-81.71181300000001,38.818975],"type":"Point"}
}