{
  "type": "Feature",
  "properties": {
    "iso:country":"US",
    "sg:address":"202 3rd Ave",
    "sg:city":"Montgomery",
    "sg:classifiers":[
        {
            "category":"Health Services",
            "subcategory":"Doctor",
            "type":"Services"
        }
    ],
    "sg:phone":"+1 304 442 5136",
    "sg:postcode":"25136",
    "sg:province":"WV",
    "wof:name":"John M Falbo DDS Associates",
    "wof:placetype":"venue"
},
  "geometry": {"coordinates":[-81.322554,38.180905],"type":"Point"}
}