{
  "type": "Feature",
  "properties": {
    "addr:full":"1412 Buckhannon Pike Clarksburg WV 26301",
    "addr:housenumber":"1412",
    "addr:postcode":"26301",
    "addr:street":"Buckhannon Pike",
    "iso:country":"US",
    "sg:address":"1412 Buckhannon Pike",
    "sg:city":"Clarksburg",
    "sg:classifiers":[
        {
            "category":"Health Services",
            "subcategory":"Clinic",
            "type":"Services"
        }
    ],
    "sg:phone":"+1 304 624 0099",
    "sg:postcode":"26301",
    "sg:province":"WV",
    "sg:tags":[
        "home"
    ],
    "wof:name":"Senior Care Of North Central",
    "wof:placetype":"venue"
},
  "geometry": {"coordinates":[-80.323328,39.258947],"type":"Point"}
}