{
  "type": "Feature",
  "properties": {
    "iso:country":"US",
    "sg:address":"6007 US Hwy 60",
    "sg:city":"Barboursville",
    "sg:classifiers":[
        {
            "category":"Social Services",
            "type":"Services"
        }
    ],
    "sg:phone":"+1 304 736 8624",
    "sg:postcode":"25504",
    "sg:province":"WV",
    "sg:tags":[
        "organization",
        "welfare"
    ],
    "wof:name":"Goodwill Industries",
    "wof:placetype":"venue"
},
  "geometry": {"coordinates":[-82.29957899999999,38.414911],"type":"Point"}
}