{
  "type": "Feature",
  "properties": {
    "addr:full":"8609 State Rte 217 Scottown OH 45678",
    "addr:housenumber":"8609",
    "addr:postcode":"45678",
    "addr:street":"State Rte 217",
    "iso:country":"US",
    "sg:address":"8609 State Rte 217",
    "sg:city":"Scottown",
    "sg:classifiers":[
        {
            "category":"Building & Trades",
            "subcategory":"Pest Control",
            "type":"Services"
        }
    ],
    "sg:phone":"+1 740 886 6757",
    "sg:postcode":"45678",
    "sg:province":"OH",
    "sg:tags":[
        "house"
    ],
    "wof:name":"Jim's Termite & Pest Control",
    "wof:placetype":"venue"
},
  "geometry": {"coordinates":[-82.42786700000001,38.553762],"type":"Point"}
}