{
  "type": "Feature",
  "properties": {
    "addr:full":"937 Grafton Rd Morgantown WV 26508",
    "addr:housenumber":"937",
    "addr:postcode":"26508",
    "addr:street":"Grafton Rd",
    "iso:country":"US",
    "sg:address":"937 Grafton Rd",
    "sg:city":"Morgantown",
    "sg:classifiers":[
        {
            "category":"Arts & Performance",
            "subcategory":"Theater",
            "type":"Entertainment"
        }
    ],
    "sg:phone":"+1 304 296 1561",
    "sg:postcode":"26508",
    "sg:province":"WV",
    "sg:tags":[
        "group"
    ],
    "wof:name":"Superior Entertainment",
    "wof:placetype":"venue"
},
  "geometry": {"coordinates":[-79.95005,39.577309],"type":"Point"}
}