{
  "type": "Feature",
  "properties": {
    "iso:country":"US",
    "sg:address":"1123 Minor Ave",
    "sg:city":"Fairmont",
    "sg:classifiers":[
        {
            "category":"Professional",
            "type":"Services"
        }
    ],
    "sg:phone":"+1 304 366 9415",
    "sg:postcode":"26554",
    "sg:province":"WV",
    "sg:tags":[
        "establishment"
    ],
    "wof:name":"Express Envelopes",
    "wof:placetype":"venue"
},
  "geometry": {"coordinates":[-80.150739,39.469151],"type":"Point"}
}