{
  "type": "Feature",
  "properties": {
    "iso:country":"US",
    "sg:address":"101 Cherry Ln",
    "sg:city":"Glasgow",
    "sg:classifiers":[
        {
            "category":"Freight",
            "type":"Transportation"
        }
    ],
    "sg:phone":"+1 304 595 4528",
    "sg:postcode":"25086",
    "sg:province":"WV",
    "sg:tags":[
        "operator",
        "local",
        "trucking"
    ],
    "wof:name":"Johnny Clark Trucking",
    "wof:placetype":"venue"
},
  "geometry": {"coordinates":[-81.424134,38.215064],"type":"Point"}
}