{
  "type": "Feature",
  "properties": {
    "iso:country":"US",
    "sg:address":"3013 Webster Rd",
    "sg:city":"Summersville",
    "sg:classifiers":[
        {
            "category":"Personal",
            "subcategory":"Beauty Salon",
            "type":"Services"
        }
    ],
    "sg:phone":"+1 304 872 0749",
    "sg:postcode":"26651",
    "sg:province":"WV",
    "sg:tags":[
        "shop"
    ],
    "wof:name":"King Cut Rate Tobacco",
    "wof:placetype":"venue"
},
  "geometry": {"coordinates":[-80.837543,38.291768],"type":"Point"}
}