{
  "type": "Feature",
  "properties": {
    "iso:country":"US",
    "sg:address":"3158 West St",
    "sg:city":"Weirton",
    "sg:classifiers":[
        {
            "category":"Retail",
            "subcategory":"Repair Shop",
            "type":"Services"
        }
    ],
    "sg:phone":"+1 304 748 0911",
    "sg:postcode":"26062",
    "sg:province":"WV",
    "sg:tags":[
        "appliance"
    ],
    "wof:name":"Tri-State Electronics",
    "wof:placetype":"venue"
},
  "geometry": {"coordinates":[-80.589573,40.406567],"type":"Point"}
}