{
  "type": "Feature",
  "properties": {
    "iso:country":"US",
    "sg:address":"514 N Jefferson St",
    "sg:city":"Lewisburg",
    "sg:classifiers":[
        {
            "category":"Food & Beverages",
            "subcategory":"Groceries & Convenience Stores",
            "type":"Retail Goods"
        }
    ],
    "sg:phone":"+1 304 645 4700",
    "sg:postcode":"24901",
    "sg:province":"WV",
    "wof:name":"Optima Quickmart",
    "wof:placetype":"venue"
},
  "geometry": {"coordinates":[-80.428287,37.816226],"type":"Point"}
}