{
  "type": "Feature",
  "properties": {
    "iso:country":"US",
    "sg:address":"4 Riddle Ct",
    "sg:city":"Morgantown",
    "sg:classifiers":[
        {
            "category":"Building & Trades",
            "subcategory":"Construction",
            "type":"Services"
        }
    ],
    "sg:phone":"+1 304 599 0850",
    "sg:postcode":"26505",
    "sg:province":"WV",
    "sg:tags":[
        "hardware",
        "commercial",
        "contractor"
    ],
    "wof:name":"Pineview Apartments",
    "wof:placetype":"venue"
},
  "geometry": {"coordinates":[-79.951137,39.663574],"type":"Point"}
}