{
  "type": "Feature",
  "properties": {
    "iso:country":"US",
    "sg:address":"330 State St",
    "sg:city":"Madison",
    "sg:classifiers":[
        {
            "category":"Professional",
            "subcategory":"Lawyer & Legal Services",
            "type":"Services"
        }
    ],
    "sg:phone":"+1 304 369 0511",
    "sg:postcode":"25130",
    "sg:province":"WV",
    "sg:tags":[
        "attorney"
    ],
    "wof:name":"Shaffer & Shaffer",
    "wof:placetype":"venue"
},
  "geometry": {"coordinates":[-81.821155,38.064169],"type":"Point"}
}