{
  "type": "Feature",
  "properties": {
    "iso:country":"US",
    "sg:address":"1580 Earl L Core Rd",
    "sg:city":"Morgantown",
    "sg:classifiers":[
        {
            "category":"Home & Garden",
            "subcategory":"Building Materials",
            "type":"Retail Goods"
        }
    ],
    "sg:phone":"+1 304 292 1340",
    "sg:postcode":"26505",
    "sg:province":"WV",
    "sg:website":"www.wvcsc.com",
    "wof:name":"Construction Supply Co",
    "wof:placetype":"venue"
},
  "geometry": {"coordinates":[-79.921745,39.610579],"type":"Point"}
}