{
  "type": "Feature",
  "properties": {
    "addr:full":"623 4th Ave Huntington WV 25701",
    "addr:housenumber":"623",
    "addr:postcode":"25701",
    "addr:street":"4Th Ave",
    "iso:country":"US",
    "sg:address":"623 4th Ave",
    "sg:city":"Huntington",
    "sg:classifiers":[
        {
            "category":"Professional",
            "subcategory":"Lawyer & Legal Services",
            "type":"Services"
        }
    ],
    "sg:phone":"+1 304 697 2070",
    "sg:postcode":"25701",
    "sg:province":"WV",
    "sg:tags":[
        "attorney"
    ],
    "wof:name":"West Virginia Legal Svc Plan",
    "wof:placetype":"venue"
},
  "geometry": {"coordinates":[-82.447587,38.420042],"type":"Point"}
}