{
  "type": "Feature",
  "properties": {
    "addr:full":"208 N Queen St Martinsburg WV 25401",
    "addr:housenumber":"208",
    "addr:postcode":"25401",
    "addr:street":"N Queen St",
    "iso:country":"US",
    "sg:address":"208 N Queen St",
    "sg:city":"Martinsburg",
    "sg:classifiers":[
        {
            "category":"Retail",
            "subcategory":"Portrait Studio",
            "type":"Services"
        }
    ],
    "sg:phone":"+1 304 260 5730",
    "sg:postcode":"25401",
    "sg:province":"WV",
    "sg:tags":[
        "photographer"
    ],
    "wof:name":"Turner Photography Studio",
    "wof:placetype":"venue"
},
  "geometry": {"coordinates":[-77.963138,39.459115],"type":"Point"}
}