{
  "type": "Feature",
  "properties": {
    "iso:country":"US",
    "sg:address":"717 Fairmont Ave",
    "sg:city":"Fairmont",
    "sg:classifiers":[
        {
            "category":"Professional",
            "subcategory":"Lawyer & Legal Services",
            "type":"Services"
        }
    ],
    "sg:phone":"+1 304 363 8300",
    "sg:postcode":"26554",
    "sg:province":"WV",
    "wof:name":"Yoneda Legal Services",
    "wof:placetype":"venue"
},
  "geometry": {"coordinates":[-80.15100700000001,39.476526],"type":"Point"}
}