{
  "type": "Feature",
  "properties": {
    "addr:full":"1703 Jefferson St Bluefield WV 24701",
    "addr:housenumber":"1703",
    "addr:postcode":"24701",
    "addr:street":"Jefferson St",
    "iso:country":"US",
    "sg:address":"1703 Jefferson St",
    "sg:city":"Bluefield",
    "sg:classifiers":[
        {
            "category":"Retail",
            "subcategory":"Repair Shop",
            "type":"Services"
        }
    ],
    "sg:phone":"+1 304 327 6757",
    "sg:postcode":"24701",
    "sg:province":"WV",
    "sg:tags":[
        "radios-citizens",
        "band"
    ],
    "sg:website":"http://www.twowayradioinc.com",
    "wof:name":"Two-Way Radio, Inc.",
    "wof:placetype":"venue"
},
  "geometry": {"coordinates":[-81.22124599999999,37.25779],"type":"Point"}
}