{
  "type": "Feature",
  "properties": {
    "addr:full":"3203 Pennsylvania Ave Weirton WV 26062",
    "addr:housenumber":"3203",
    "addr:postcode":"26062",
    "addr:street":"Pennsylvania Ave",
    "iso:country":"US",
    "sg:address":"3203 Pennsylvania Ave",
    "sg:city":"Weirton",
    "sg:classifiers":[
        {
            "category":"Professional",
            "subcategory":"Lawyer & Legal Services",
            "type":"Services"
        }
    ],
    "sg:phone":"+1 304 723 7201",
    "sg:postcode":"26062",
    "sg:province":"WV",
    "sg:tags":[
        "attorney"
    ],
    "wof:name":"Hinerman & Assoc",
    "wof:placetype":"venue"
},
  "geometry": {"coordinates":[-80.541214,40.409407],"type":"Point"}
}