{
  "type": "Feature",
  "properties": {
    "iso:country":"US",
    "sg:address":"202 Viking Way",
    "sg:city":"Martinsburg",
    "sg:classifiers":[
        {
            "category":"Real Estate",
            "subcategory":"Real Estate Agent",
            "type":"Services"
        }
    ],
    "sg:phone":"+1 304 596 5500",
    "sg:postcode":"25401",
    "sg:province":"WV",
    "wof:name":"Remax Success Realty",
    "wof:placetype":"venue"
},
  "geometry": {"coordinates":[-77.988327,39.462745],"type":"Point"}
}