{
  "type": "Feature",
  "properties": {
    "addr:full":"332 North St Bluefield WV 24701",
    "addr:housenumber":"332",
    "addr:postcode":"24701",
    "addr:street":"North St",
    "iso:country":"US",
    "sg:address":"332 North St",
    "sg:city":"Bluefield",
    "sg:classifiers":[
        {
            "category":"Health Services",
            "subcategory":"Optometrist",
            "type":"Services"
        }
    ],
    "sg:phone":"+1 304 325 8685",
    "sg:postcode":"24701",
    "sg:province":"WV",
    "wof:name":"Hendrix John P OD",
    "wof:placetype":"venue"
},
  "geometry": {"coordinates":[-81.22248399999999,37.258062],"type":"Point"}
}