{
  "type": "Feature",
  "properties": {
    "iso:country":"US",
    "sg:address":"334 N Lawrence St",
    "sg:city":"Charles Town",
    "sg:classifiers":[
        {
            "category":"Social Services",
            "type":"Services"
        }
    ],
    "sg:phone":"+1 304 728 3143",
    "sg:postcode":"25414",
    "sg:province":"WV",
    "sg:tags":[
        "youth",
        "organization",
        "center"
    ],
    "wof:name":"Boys & Girls Club-Jefferson",
    "wof:placetype":"venue"
},
  "geometry": {"coordinates":[-77.86350400000001,39.290875],"type":"Point"}
}