{
  "type": "Feature",
  "properties": {
    "addr:full":"1116 7th St Parkersburg WV 26101",
    "addr:housenumber":"1116",
    "addr:postcode":"26101",
    "addr:street":"7Th St",
    "iso:country":"US",
    "sg:address":"1116 7th St",
    "sg:city":"Parkersburg",
    "sg:classifiers":[
        {
            "category":"Food & Beverages",
            "subcategory":"Bakery",
            "type":"Retail Goods"
        }
    ],
    "sg:phone":"+1 304 424 9221",
    "sg:postcode":"26101",
    "sg:province":"WV",
    "sg:tags":[
        "product",
        "mfg"
    ],
    "wof:name":"McHappys",
    "wof:placetype":"venue"
},
  "geometry": {"coordinates":[-81.54368700000001,39.263359],"type":"Point"}
}