{
  "type": "Feature",
  "properties": {
    "iso:country":"US",
    "sg:address":"1801 1st St",
    "sg:city":"Moundsville",
    "sg:classifiers":[
        {
            "category":"Organizations",
            "subcategory":"Religious Organization",
            "type":"Services"
        }
    ],
    "sg:phone":"+1 304 845 2818",
    "sg:postcode":"26041",
    "sg:province":"WV",
    "sg:tags":[
        "church"
    ],
    "wof:name":"Moundsville Church-Nazarene",
    "wof:placetype":"venue"
},
  "geometry": {"coordinates":[-80.732945,39.926711],"type":"Point"}
}