{
  "type": "Feature",
  "properties": {
    "iso:country":"US",
    "sg:address":"807 Quarrier St",
    "sg:city":"Charleston",
    "sg:classifiers":[
        {
            "category":"Restaurant",
            "type":"Food & Drink"
        }
    ],
    "sg:phone":"+1 304 345 6700",
    "sg:postcode":"25301",
    "sg:province":"WV",
    "sg:tags":[
        "eating"
    ],
    "wof:name":"Sub Shop",
    "wof:placetype":"venue"
},
  "geometry": {"coordinates":[-81.634784,38.349566],"type":"Point"}
}