{
  "type": "Feature",
  "properties": {
    "addr:full":"6416 US Hwy 60 Barboursville WV 25504",
    "addr:housenumber":"6416",
    "addr:postcode":"25504",
    "addr:street":"Us Hwy 60",
    "iso:country":"US",
    "sg:address":"6416 US Hwy 60",
    "sg:city":"Barboursville",
    "sg:classifiers":[
        {
            "category":"Autos & Motor Vehicles",
            "subcategory":"Auto Supplies",
            "type":"Retail Goods"
        }
    ],
    "sg:phone":"+1 304 736 7237",
    "sg:postcode":"25504",
    "sg:province":"WV",
    "sg:tags":[
        "tire"
    ],
    "wof:name":"Tire Stop",
    "wof:placetype":"venue"
},
  "geometry": {"coordinates":[-82.29772800000001,38.415346],"type":"Point"}
}