{
  "type": "Feature",
  "properties": {
    "iso:country":"US",
    "sg:address":"61705 Sandy Ridge Rd",
    "sg:city":"Barnesville",
    "sg:classifiers":[
        {
            "category":"Farming",
            "subcategory":"Orchard",
            "type":"Manufacturing & Wholesale Goods"
        }
    ],
    "sg:phone":"+1 740 425 2710",
    "sg:postcode":"43713",
    "sg:province":"OH",
    "sg:tags":[
        "deciduous",
        "fruit",
        "tree"
    ],
    "wof:name":"Rockwell Orchards",
    "wof:placetype":"venue"
},
  "geometry": {"coordinates":[-81.150334,39.988217],"type":"Point"}
}