{
  "type": "Feature",
  "properties": {
    "iso:country":"US",
    "sg:address":"743 N Main St",
    "sg:city":"Moorefield",
    "sg:classifiers":[
        {
            "category":"Shopping",
            "subcategory":"Pharmacy",
            "type":"Retail Goods"
        }
    ],
    "sg:phone":"+1 304 538 2356",
    "sg:postcode":"26836",
    "sg:province":"WV",
    "wof:name":"CVS Pharmacy",
    "wof:placetype":"venue"
},
  "geometry": {"coordinates":[-78.966758,39.072908],"type":"Point"}
}