{
  "type": "Feature",
  "properties": {
    "addr:full":"617 Ohio Ave Clarksburg WV 26301",
    "addr:housenumber":"617",
    "addr:postcode":"26301",
    "addr:street":"Ohio Ave",
    "iso:country":"US",
    "sg:address":"617 Ohio Ave",
    "sg:city":"Clarksburg",
    "sg:classifiers":[
        {
            "category":"Freight",
            "type":"Transportation"
        }
    ],
    "sg:phone":"+1 304 622 1546",
    "sg:postcode":"26301",
    "sg:province":"WV",
    "sg:tags":[
        "operator",
        "local",
        "trucking"
    ],
    "wof:name":"E A Shuttleworth & Son Inc",
    "wof:placetype":"venue"
},
  "geometry": {"coordinates":[-80.31752299999999,39.264014],"type":"Point"}
}