{
  "type": "Feature",
  "properties": {
    "addr:full":"57 Glendale Rd Parkersburg WV 26105",
    "addr:housenumber":"57",
    "addr:postcode":"26105",
    "addr:street":"Glendale Rd",
    "iso:country":"US",
    "sg:address":"57 Glendale Rd",
    "sg:city":"Parkersburg",
    "sg:classifiers":[
        {
            "category":"Home & Garden",
            "subcategory":"Building Materials",
            "type":"Retail Goods"
        }
    ],
    "sg:phone":"+1 304 295 7009",
    "sg:postcode":"26105",
    "sg:province":"WV",
    "sg:tags":[
        "door"
    ],
    "wof:name":"Miller Door Inc",
    "wof:placetype":"venue"
},
  "geometry": {"coordinates":[-81.516025,39.34934],"type":"Point"}
}