{
  "type": "Feature",
  "properties": {
    "iso:country":"US",
    "sg:address":"57 Mill St",
    "sg:city":"Salem",
    "sg:classifiers":[
        {
            "category":"Retail",
            "subcategory":"Auto Repair",
            "type":"Services"
        }
    ],
    "sg:phone":"+1 304 782 9600",
    "sg:postcode":"26426",
    "sg:province":"WV",
    "sg:tags":[
        "repairing",
        "automobile"
    ],
    "wof:name":"Davis Auto Repair",
    "wof:placetype":"venue"
},
  "geometry": {"coordinates":[-80.559234,39.283429],"type":"Point"}
}