{
  "type": "Feature",
  "properties": {
    "iso:country":"US",
    "sg:address":"219 2nd St",
    "sg:city":"Marietta",
    "sg:classifiers":[
        {
            "category":"Social Services",
            "type":"Services"
        }
    ],
    "sg:phone":"+1 740 374 5980",
    "sg:postcode":"45750",
    "sg:province":"OH",
    "sg:tags":[
        "worker"
    ],
    "wof:name":"Job's For Ohio's Graduates",
    "wof:placetype":"venue"
},
  "geometry": {"coordinates":[-81.452885,39.413388],"type":"Point"}
}