{
  "type": "Feature",
  "properties": {
    "iso:country":"US",
    "sg:address":"3722 Pennsylvania Ave",
    "sg:city":"Weirton",
    "sg:classifiers":[
        {
            "category":"Personal",
            "subcategory":"Beauty Salon",
            "type":"Services"
        }
    ],
    "sg:phone":"+1 304 723 5360",
    "sg:postcode":"26062",
    "sg:province":"WV",
    "sg:tags":[
        "shop"
    ],
    "wof:name":"New Creation Beauty Salon",
    "wof:placetype":"venue"
},
  "geometry": {"coordinates":[-80.521575,40.406277],"type":"Point"}
}