{
  "type": "Feature",
  "properties": {
    "addr:full":"126 E 2nd St Weston WV 26452",
    "addr:housenumber":"126",
    "addr:postcode":"26452",
    "addr:street":"E 2Nd St",
    "iso:country":"US",
    "sg:address":"126 E 2nd St",
    "sg:city":"Weston",
    "sg:classifiers":[
        {
            "category":"Manufacturing",
            "subcategory":"Printing",
            "type":"Manufacturing & Wholesale Goods"
        }
    ],
    "sg:phone":"+1 304 269 4233",
    "sg:postcode":"26452",
    "sg:province":"WV",
    "sg:tags":[
        "print",
        "printer",
        "lithographic",
        "typesetting"
    ],
    "wof:name":"Colonial Press Printing Co",
    "wof:placetype":"venue"
},
  "geometry": {"coordinates":[-80.467242,39.038165],"type":"Point"}
}