{
  "type": "Feature",
  "properties": {
    "addr:full":"100 Sycamore St Ravenswood WV 26164",
    "addr:housenumber":"100",
    "addr:postcode":"26164",
    "addr:street":"Sycamore St",
    "iso:country":"US",
    "sg:address":"100 Sycamore St",
    "sg:city":"Ravenswood",
    "sg:classifiers":[
        {
            "category":"Autos & Motor Vehicles",
            "subcategory":"Auto Supplies",
            "type":"Retail Goods"
        }
    ],
    "sg:phone":"+1 304 273 3466",
    "sg:postcode":"26164",
    "sg:province":"WV",
    "sg:tags":[
        "battery"
    ],
    "wof:name":"Interstate Battery System",
    "wof:placetype":"venue"
},
  "geometry": {"coordinates":[-81.76281,38.949256],"type":"Point"}
}