{
  "type": "Feature",
  "properties": {
    "addr:full":"1431 Honaker Ave Princeton WV 24740",
    "addr:housenumber":"1431",
    "addr:postcode":"24740",
    "addr:street":"Honaker Ave",
    "iso:country":"US",
    "sg:address":"1431 Honaker Ave",
    "sg:city":"Princeton",
    "sg:classifiers":[
        {
            "category":"Retail",
            "subcategory":"Laundry & Dry Cleaning",
            "type":"Services"
        }
    ],
    "sg:phone":"+1 304 487 1596",
    "sg:postcode":"24740",
    "sg:province":"WV",
    "wof:name":"Super Clean Coin Laundry II",
    "wof:placetype":"venue"
},
  "geometry": {"coordinates":[-81.101088,37.36659],"type":"Point"}
}