{
  "type": "Feature",
  "properties": {
    "iso:country":"US",
    "sg:address":"384 Penco Rd",
    "sg:city":"Weirton",
    "sg:classifiers":[
        {
            "category":"Professional",
            "type":"Services"
        }
    ],
    "sg:phone":"+1 304 723 2880",
    "sg:postcode":"26062",
    "sg:province":"WV",
    "sg:tags":[
        "establishment"
    ],
    "wof:name":"Nikolas A Kamarados Ohio Vly",
    "wof:placetype":"venue"
},
  "geometry": {"coordinates":[-80.547178,40.409023],"type":"Point"}
}