{
  "type": "Feature",
  "properties": {
    "iso:country":"US",
    "sg:address":"3845 Teays Valley Rd",
    "sg:city":"Hurricane",
    "sg:classifiers":[
        {
            "category":"Health Services",
            "subcategory":"Podiatrist",
            "type":"Services"
        }
    ],
    "sg:phone":"+1 304 757 1111",
    "sg:postcode":"25526",
    "sg:province":"WV",
    "wof:name":"Gregory D Borowski DPM",
    "wof:placetype":"venue"
},
  "geometry": {"coordinates":[-81.941639,38.448433],"type":"Point"}
}