{
  "type": "Feature",
  "properties": {
    "iso:country":"US",
    "sg:address":"301 Maple St",
    "sg:city":"Lewisburg",
    "sg:classifiers":[
        {
            "category":"Professional",
            "type":"Services"
        }
    ],
    "sg:phone":"+1 304 645 2847",
    "sg:postcode":"24901",
    "sg:province":"WV",
    "sg:tags":[
        "establishment"
    ],
    "wof:name":"Brown Extermntng",
    "wof:placetype":"venue"
},
  "geometry": {"coordinates":[-80.44738599999999,37.807117],"type":"Point"}
}