{
  "type": "Feature",
  "properties": {
    "iso:country":"US",
    "sg:address":"5885 Davis Creek Rd",
    "sg:city":"Barboursville",
    "sg:classifiers":[
        {
            "category":"Personal",
            "subcategory":"Barber",
            "type":"Services"
        }
    ],
    "sg:phone":"+1 304 736 8601",
    "sg:postcode":"25504",
    "sg:province":"WV",
    "wof:name":"Woomer's Barber Shop",
    "wof:placetype":"venue"
},
  "geometry": {"coordinates":[-82.32687900000001,38.395389],"type":"Point"}
}