{
  "type": "Feature",
  "properties": {
    "addr:full":"212 20th St Huntington WV 25703",
    "addr:housenumber":"212",
    "addr:postcode":"25703",
    "addr:street":"20Th St",
    "iso:country":"US",
    "sg:address":"212 20th St",
    "sg:city":"Huntington",
    "sg:classifiers":[
        {
            "category":"Retail",
            "subcategory":"Repair Shop",
            "type":"Services"
        }
    ],
    "sg:phone":"+1 304 522 0737",
    "sg:postcode":"25703",
    "sg:province":"WV",
    "sg:tags":[
        "appliance"
    ],
    "wof:name":"Mike's Appliance & Svc Co",
    "wof:placetype":"venue"
},
  "geometry": {"coordinates":[-82.423204,38.425582],"type":"Point"}
}