{
  "type": "Feature",
  "properties": {
    "iso:country":"US",
    "sg:address":"16 Camden Ave",
    "sg:city":"Buckhannon",
    "sg:classifiers":[
        {
            "category":"Restaurant",
            "type":"Food & Drink"
        }
    ],
    "sg:phone":"+1 304 473 8367",
    "sg:postcode":"26201",
    "sg:province":"WV",
    "sg:tags":[
        "building",
        "eating",
        "maintenance"
    ],
    "wof:name":"Maintenance Department",
    "wof:placetype":"venue"
},
  "geometry": {"coordinates":[-80.217556,38.987734],"type":"Point"}
}