{
  "type": "Feature",
  "properties": {
    "iso:country":"US",
    "sg:address":"382 G C and P Rd",
    "sg:city":"Wheeling",
    "sg:classifiers":[
        {
            "category":"Retail",
            "subcategory":"Veterinary Services",
            "type":"Services"
        }
    ],
    "sg:phone":"+1 304 232 2605",
    "sg:postcode":"26003",
    "sg:province":"WV",
    "wof:name":"Harrold Pamela Dvm",
    "wof:placetype":"venue"
},
  "geometry": {"coordinates":[-80.662346,40.115083],"type":"Point"}
}