{
  "type": "Feature",
  "properties": {
    "iso:country":"US",
    "sg:address":"532 US Hwy 33",
    "sg:city":"Weston",
    "sg:classifiers":[
        {
            "category":"Shopping",
            "subcategory":"Tobacco",
            "type":"Retail Goods"
        }
    ],
    "sg:phone":"+1 304 269 7844",
    "sg:postcode":"26452",
    "sg:province":"WV",
    "sg:tags":[
        "cigarette",
        "product",
        "cigar",
        "dealer"
    ],
    "wof:name":"Smokehouse Tobacco & Beer Outl",
    "wof:placetype":"venue"
},
  "geometry": {"coordinates":[-80.479703,39.048009],"type":"Point"}
}