{
  "type": "Feature",
  "properties": {
    "addr:full":"258 Ragland Rd Beckley WV 25801",
    "addr:housenumber":"258",
    "addr:postcode":"25801",
    "addr:street":"Ragland Rd",
    "iso:country":"US",
    "sg:address":"258 Ragland Rd",
    "sg:city":"Beckley",
    "sg:classifiers":[
        {
            "category":"Retail",
            "subcategory":"Repair Shop",
            "type":"Services"
        }
    ],
    "sg:phone":"+1 304 256 3914",
    "sg:postcode":"25801",
    "sg:province":"WV",
    "sg:tags":[
        "repairing",
        "equipment",
        "electrical",
        "electric"
    ],
    "wof:name":"Eaton Electrical Inc",
    "wof:placetype":"venue"
},
  "geometry": {"coordinates":[-81.17886300000001,37.808547],"type":"Point"}
}