{
  "type": "Feature",
  "properties": {
    "iso:country":"US",
    "sg:address":"2 W Main St",
    "sg:city":"Richwood",
    "sg:classifiers":[
        {
            "category":"Shopping",
            "subcategory":"Used Merchandise",
            "type":"Retail Goods"
        }
    ],
    "sg:phone":"+1 304 846 4578",
    "sg:postcode":"26261",
    "sg:province":"WV",
    "wof:name":"Main St USA Antq Collectibles",
    "wof:placetype":"venue"
},
  "geometry": {"coordinates":[-80.53332899999999,38.225089],"type":"Point"}
}