{
  "type": "Feature",
  "properties": {
    "addr:full":"601 Main St Mt Hope WV 25880",
    "addr:housenumber":"601",
    "addr:postcode":"25880",
    "addr:street":"Main St",
    "iso:country":"US",
    "sg:address":"601 Main St",
    "sg:city":"Mt Hope",
    "sg:classifiers":[
        {
            "category":"Shopping",
            "subcategory":"Florist",
            "type":"Retail Goods"
        }
    ],
    "sg:phone":"+1 304 877 2221",
    "sg:postcode":"25880",
    "sg:province":"WV",
    "wof:name":"Webbs Of Mt Hope Florist",
    "wof:placetype":"venue"
},
  "geometry": {"coordinates":[-81.167821,37.892811],"type":"Point"}
}