{
  "type": "Feature",
  "properties": {
    "addr:full":"34 Island Ave Buckhannon WV 26201",
    "addr:housenumber":"34",
    "addr:postcode":"26201",
    "addr:street":"Island Ave",
    "iso:country":"US",
    "sg:address":"34 Island Ave",
    "sg:city":"Buckhannon",
    "sg:classifiers":[
        {
            "category":"Health Services",
            "subcategory":"Chiropractor",
            "type":"Services"
        }
    ],
    "sg:phone":"+1 304 472 6070",
    "sg:postcode":"26201",
    "sg:province":"WV",
    "wof:name":"William H Downer DC",
    "wof:placetype":"venue"
},
  "geometry": {"coordinates":[-80.222397,38.99579],"type":"Point"}
}