{
  "type": "Feature",
  "properties": {
    "addr:full":"1972 Kelmont Ln Charleston WV 25320",
    "addr:housenumber":"1972",
    "addr:postcode":"25320",
    "addr:street":"Kelmont Ln",
    "iso:country":"US",
    "sg:address":"1972 Kelmont Ln",
    "sg:city":"Charleston",
    "sg:classifiers":[
        {
            "category":"Wholesale",
            "subcategory":"Construction Materials",
            "type":"Manufacturing & Wholesale Goods"
        }
    ],
    "sg:phone":"+1 304 984 0808",
    "sg:postcode":"25320",
    "sg:province":"WV",
    "sg:tags":[
        "fence"
    ],
    "wof:name":"Valley Fence Co",
    "wof:placetype":"venue"
},
  "geometry": {"coordinates":[-81.645933,38.488924],"type":"Point"}
}