{
  "type": "Feature",
  "properties": {
    "iso:country":"US",
    "sg:address":"306 Main St",
    "sg:city":"Man",
    "sg:classifiers":[
        {
            "category":"Health Services",
            "subcategory":"Doctor",
            "type":"Services"
        }
    ],
    "sg:phone":"+1 304 583 7146",
    "sg:postcode":"25635",
    "sg:province":"WV",
    "sg:tags":[
        "physician",
        "surgeon"
    ],
    "wof:name":"Ulysses D Agas Inc",
    "wof:placetype":"venue"
},
  "geometry": {"coordinates":[-81.873143,37.744356],"type":"Point"}
}