{
  "type": "Feature",
  "properties": {
    "addr:full":"113 1st Ave Beckley WV 25801",
    "addr:housenumber":"113",
    "addr:postcode":"25801",
    "addr:street":"1St Ave",
    "iso:country":"US",
    "sg:address":"113 1st Ave",
    "sg:city":"Beckley",
    "sg:classifiers":[
        {
            "category":"Organizations",
            "subcategory":"Religious Organization",
            "type":"Services"
        }
    ],
    "sg:phone":"+1 304 253 2858",
    "sg:postcode":"25801",
    "sg:province":"WV",
    "wof:name":"Fellowship-Christian Athletes",
    "wof:placetype":"venue"
},
  "geometry": {"coordinates":[-81.191641,37.775439],"type":"Point"}
}