{
  "type": "Feature",
  "properties": {
    "addr:full":"1402 4th Ave Huntington WV 25701",
    "addr:housenumber":"1402",
    "addr:postcode":"25701",
    "addr:street":"4Th Ave",
    "iso:country":"US",
    "sg:address":"1402 4th Ave",
    "sg:city":"Huntington",
    "sg:classifiers":[
        {
            "category":"Restaurant",
            "type":"Food & Drink"
        }
    ],
    "sg:phone":"+1 304 697 5000",
    "sg:postcode":"25701",
    "sg:province":"WV",
    "wof:name":"Romero's",
    "wof:placetype":"venue"
},
  "geometry": {"coordinates":[-82.433587,38.422595],"type":"Point"}
}