{
  "type": "Feature",
  "properties": {
    "iso:country":"US",
    "sg:address":"111 Caroline Cir",
    "sg:city":"Hurricane",
    "sg:classifiers":[
        {
            "category":"Retail",
            "subcategory":"Repair Shop",
            "type":"Services"
        }
    ],
    "sg:phone":"+1 304 562 2554",
    "sg:postcode":"25526",
    "sg:province":"WV",
    "wof:name":"Rons Television Service Inc",
    "wof:placetype":"venue"
},
  "geometry": {"coordinates":[-82.015686,38.43134],"type":"Point"}
}