{
  "type": "Feature",
  "properties": {
    "addr:full":"500 E Main St Ste B Romney WV 26757",
    "addr:housenumber":"500",
    "addr:postcode":"26757",
    "addr:street":"E Main St Ste B",
    "iso:country":"US",
    "sg:address":"500 E Main St Ste B",
    "sg:city":"Romney",
    "sg:classifiers":[
        {
            "category":"Health Services",
            "subcategory":"Chiropractor",
            "type":"Services"
        }
    ],
    "sg:phone":"+1 304 822 3425",
    "sg:postcode":"26757",
    "sg:province":"WV",
    "sg:tags":[
        "chiropractic"
    ],
    "wof:name":"Earthsong Organic Health Store",
    "wof:placetype":"venue"
},
  "geometry": {"coordinates":[-78.75197,39.339732],"type":"Point"}
}