{
  "type": "Feature",
  "properties": {
    "iso:country":"US",
    "sg:address":"331 18th St",
    "sg:city":"Dunbar",
    "sg:classifiers":[
        {
            "category":"Home & Garden",
            "subcategory":"Home Furnishings",
            "type":"Retail Goods"
        }
    ],
    "sg:phone":"+1 304 766 8466",
    "sg:postcode":"25064",
    "sg:province":"WV",
    "sg:tags":[
        "blind",
        "mini"
    ],
    "wof:name":"We Do Blinds",
    "wof:placetype":"venue"
},
  "geometry": {"coordinates":[-81.74786,38.360739],"type":"Point"}
}