{
  "type": "Feature",
  "properties": {
    "addr:full":"521 Elk St Gassaway WV 26624",
    "addr:housenumber":"521",
    "addr:postcode":"26624",
    "addr:street":"Elk St",
    "iso:country":"US",
    "sg:address":"521 Elk St",
    "sg:city":"Gassaway",
    "sg:classifiers":[
        {
            "category":"Home & Garden",
            "subcategory":"Carpets & Floor Coverings",
            "type":"Retail Goods"
        }
    ],
    "sg:phone":"+1 304 364 8880",
    "sg:postcode":"26624",
    "sg:province":"WV",
    "wof:name":"Quality Carpet",
    "wof:placetype":"venue"
},
  "geometry": {"coordinates":[-80.774857,38.672849],"type":"Point"}
}