{
  "type": "Feature",
  "properties": {
    "iso:country":"US",
    "sg:address":"241 Miami Ave",
    "sg:city":"Weirton",
    "sg:classifiers":[
        {
            "category":"Organizations",
            "subcategory":"Religious Organization",
            "type":"Services"
        }
    ],
    "sg:phone":"+1 304 748 2629",
    "sg:postcode":"26062",
    "sg:province":"WV",
    "sg:tags":[
        "clergy"
    ],
    "wof:name":"Craig Greathouse",
    "wof:placetype":"venue"
},
  "geometry": {"coordinates":[-80.576042,40.412766],"type":"Point"}
}