{
  "type": "Feature",
  "properties": {
    "iso:country":"US",
    "sg:address":"1124 E Main St",
    "sg:city":"Clarksburg",
    "sg:classifiers":[
        {
            "category":"Shopping",
            "subcategory":"Bicycles & Sporting Goods",
            "type":"Retail Goods"
        }
    ],
    "sg:phone":"+1 304 626 3292",
    "sg:postcode":"26301",
    "sg:province":"WV",
    "sg:tags":[
        "gun",
        "gunsmith"
    ],
    "wof:name":"Z Man Guns Etc",
    "wof:placetype":"venue"
},
  "geometry": {"coordinates":[-80.320786,39.271073],"type":"Point"}
}