{
  "type": "Feature",
  "properties": {
    "iso:country":"US",
    "sg:address":"120 1st St",
    "sg:city":"Elkins",
    "sg:classifiers":[
        {
            "category":"Retail",
            "subcategory":"Funeral Services",
            "type":"Services"
        }
    ],
    "sg:phone":"+1 304 636 4440",
    "sg:postcode":"26241",
    "sg:province":"WV",
    "sg:tags":[
        "director"
    ],
    "wof:name":"Lohr & Barb Funeral Home",
    "wof:placetype":"venue"
},
  "geometry": {"coordinates":[-79.849418,38.92299],"type":"Point"}
}