{
  "type": "Feature",
  "properties": {
    "iso:country":"US",
    "sg:address":"122 3rd St",
    "sg:city":"Elkins",
    "sg:classifiers":[
        {
            "category":"Shopping",
            "subcategory":"Gifts & Souvenirs",
            "type":"Retail Goods"
        }
    ],
    "sg:phone":"+1 304 636 6660",
    "sg:postcode":"26241",
    "sg:province":"WV",
    "sg:tags":[
        "shop"
    ],
    "wof:name":"Mc Manus Gifts Inc",
    "wof:placetype":"venue"
},
  "geometry": {"coordinates":[-79.84917299999999,38.925105],"type":"Point"}
}