{
  "type": "Feature",
  "properties": {
    "iso:country":"US",
    "sg:address":"829 Main St",
    "sg:city":"Charleston",
    "sg:classifiers":[
        {
            "category":"Organizations",
            "subcategory":"Religious Organization",
            "type":"Services"
        }
    ],
    "sg:phone":"+1 304 345 4650",
    "sg:postcode":"25302",
    "sg:province":"WV",
    "wof:name":"Song Evangelist",
    "wof:placetype":"venue"
},
  "geometry": {"coordinates":[-81.65469,38.363661],"type":"Point"}
}