{
  "type": "Feature",
  "properties": {
    "iso:country":"US",
    "sg:address":"70 New Jersey St",
    "sg:city":"Wheeling",
    "sg:classifiers":[
        {
            "category":"Bars & Pubs",
            "type":"Food & Drink"
        }
    ],
    "sg:phone":"+1 304 232 1728",
    "sg:postcode":"26003",
    "sg:province":"WV",
    "wof:name":"Just One More",
    "wof:placetype":"venue"
},
  "geometry": {"coordinates":[-80.732501,40.075938],"type":"Point"}
}