{
  "type": "Feature",
  "properties": {
    "iso:country":"US",
    "sg:address":"242 Green St",
    "sg:city":"Morgantown",
    "sg:classifiers":[
        {
            "category":"Wholesale",
            "subcategory":"Groceries",
            "type":"Manufacturing & Wholesale Goods"
        }
    ],
    "sg:phone":"+1 304 291 5418",
    "sg:postcode":"26501",
    "sg:province":"WV",
    "sg:tags":[
        "water",
        "bottled",
        "supply"
    ],
    "wof:name":"Morgantown Bottled Water",
    "wof:placetype":"venue"
},
  "geometry": {"coordinates":[-79.95099500000001,39.625712],"type":"Point"}
}