{
  "type": "Feature",
  "properties": {
    "iso:country":"US",
    "sg:address":"308 Locust St",
    "sg:city":"Princeton",
    "sg:classifiers":[
        {
            "category":"Real Estate",
            "subcategory":"Real Estate Agent",
            "type":"Services"
        }
    ],
    "sg:phone":"+1 304 425 2220",
    "sg:postcode":"24740",
    "sg:province":"WV",
    "wof:name":"Country Roads Real Estate",
    "wof:placetype":"venue"
},
  "geometry": {"coordinates":[-81.07858299999999,37.36214],"type":"Point"}
}