{
  "type": "Feature",
  "properties": {
    "addr:full":"520 Heather Dr Elkview WV 25071",
    "addr:housenumber":"520",
    "addr:postcode":"25071",
    "addr:street":"Heather Dr",
    "iso:country":"US",
    "sg:address":"520 Heather Dr",
    "sg:city":"Elkview",
    "sg:classifiers":[
        {
            "category":"Retail",
            "subcategory":"Repair Shop",
            "type":"Services"
        }
    ],
    "sg:phone":"+1 304 965 3065",
    "sg:postcode":"25071",
    "sg:province":"WV",
    "sg:tags":[
        "electrical"
    ],
    "wof:name":"Hoovers Sales & Service",
    "wof:placetype":"venue"
},
  "geometry": {"coordinates":[-81.52254600000001,38.407081],"type":"Point"}
}