{
  "type": "Feature",
  "properties": {
    "iso:country":"US",
    "sg:address":"1030 E Bethlehem Blvd",
    "sg:city":"Wheeling",
    "sg:classifiers":[
        {
            "category":"Retail",
            "subcategory":"Car Wash",
            "type":"Services"
        }
    ],
    "sg:phone":"+1 304 242 0010",
    "sg:postcode":"26003",
    "sg:province":"WV",
    "sg:tags":[
        "carwash"
    ],
    "wof:name":"Petri Detailing",
    "wof:placetype":"venue"
},
  "geometry": {"coordinates":[-80.679917,40.040022],"type":"Point"}
}