{
  "type": "Feature",
  "properties": {
    "iso:country":"US",
    "sg:address":"800 Mercer St",
    "sg:city":"Princeton",
    "sg:classifiers":[
        {
            "category":"Personal",
            "subcategory":"Tanning Parlor",
            "type":"Services"
        }
    ],
    "sg:phone":"+1 304 425 2066",
    "sg:postcode":"24740",
    "sg:province":"WV",
    "sg:tags":[
        "salon"
    ],
    "wof:name":"Hot Topics Tanning & Toning",
    "wof:placetype":"venue"
},
  "geometry": {"coordinates":[-81.093272,37.369658],"type":"Point"}
}