{
  "type": "Feature",
  "properties": {
    "iso:country":"US",
    "sg:address":"4001 Emerson Ave",
    "sg:city":"Parkersburg",
    "sg:classifiers":[
        {
            "category":"Shopping",
            "subcategory":"Florist",
            "type":"Retail Goods"
        }
    ],
    "sg:phone":"+1 304 485 4532",
    "sg:postcode":"26104",
    "sg:province":"WV",
    "wof:name":"Flower Garden Florist",
    "wof:placetype":"venue"
},
  "geometry": {"coordinates":[-81.530214,39.289537],"type":"Point"}
}