{
  "type": "Feature",
  "properties": {
    "iso:country":"US",
    "sg:address":"522 Buffington St",
    "sg:city":"Huntington",
    "sg:classifiers":[
        {
            "category":"Organizations",
            "subcategory":"Religious Organization",
            "type":"Services"
        }
    ],
    "sg:phone":"+1 304 522 2931",
    "sg:postcode":"25702",
    "sg:province":"WV",
    "wof:name":"Thomas Memorial Free Will Bapt",
    "wof:placetype":"venue"
},
  "geometry": {"coordinates":[-82.387171,38.423688],"type":"Point"}
}