{
  "type": "Feature",
  "properties": {
    "addr:full":"703 Rayon Dr Parkersburg WV 26101",
    "addr:housenumber":"703",
    "addr:postcode":"26101",
    "addr:street":"Rayon Dr",
    "iso:country":"US",
    "sg:address":"703 Rayon Dr",
    "sg:city":"Parkersburg",
    "sg:classifiers":[
        {
            "category":"Wholesale",
            "subcategory":"Auto Parts",
            "type":"Manufacturing & Wholesale Goods"
        }
    ],
    "sg:phone":"+1 304 485 2036",
    "sg:postcode":"26101",
    "sg:province":"WV",
    "sg:tags":[
        "equipment",
        "truck"
    ],
    "wof:name":"Fleet Pride Inc",
    "wof:placetype":"venue"
},
  "geometry": {"coordinates":[-81.527418,39.236336],"type":"Point"}
}