{
  "type": "Feature",
  "properties": {
    "addr:full":"701 Viand St Point Pleasant WV 25550",
    "addr:housenumber":"701",
    "addr:postcode":"25550",
    "addr:street":"Viand St",
    "iso:country":"US",
    "sg:address":"701 Viand St",
    "sg:city":"Point Pleasant",
    "sg:classifiers":[
        {
            "category":"Professional",
            "subcategory":"Lawyer & Legal Services",
            "type":"Services"
        }
    ],
    "sg:phone":"+1 304 675 6990",
    "sg:postcode":"25550",
    "sg:province":"WV",
    "wof:name":"W D Roll Attorney At Law",
    "wof:placetype":"venue"
},
  "geometry": {"coordinates":[-82.13686,38.845661],"type":"Point"}
}