{
  "type": "Feature",
  "properties": {
    "iso:country":"US",
    "sg:address":"1221 9th Ave",
    "sg:city":"Huntington",
    "sg:classifiers":[
        {
            "category":"Wholesale",
            "subcategory":"Electrical",
            "type":"Manufacturing & Wholesale Goods"
        }
    ],
    "sg:phone":"+1 304 523 0356",
    "sg:postcode":"25701",
    "sg:province":"WV",
    "sg:tags":[
        "alarm",
        "burglar",
        "system"
    ],
    "wof:name":"Alarm Systems",
    "wof:placetype":"venue"
},
  "geometry": {"coordinates":[-82.43528499999999,38.414735],"type":"Point"}
}