{
  "type": "Feature",
  "properties": {
    "addr:full":"322 Dry Hill Rd Beckley WV 25801",
    "addr:housenumber":"322",
    "addr:postcode":"25801",
    "addr:street":"Dry Hill Rd",
    "iso:country":"US",
    "sg:address":"322 Dry Hill Rd",
    "sg:city":"Beckley",
    "sg:classifiers":[
        {
            "category":"Autos & Motor Vehicles",
            "subcategory":"Automobile Sales",
            "type":"Retail Goods"
        }
    ],
    "sg:phone":"+1 304 254 7827",
    "sg:postcode":"25801",
    "sg:province":"WV",
    "sg:tags":[
        "truck"
    ],
    "wof:name":"Heritage Equipment Inc",
    "wof:placetype":"venue"
},
  "geometry": {"coordinates":[-81.226546,37.800238],"type":"Point"}
}