{
  "type": "Feature",
  "properties": {
    "iso:country":"US",
    "sg:address":"532 29th St",
    "sg:city":"Parkersburg",
    "sg:classifiers":[
        {
            "category":"Home & Garden",
            "subcategory":"Building Materials",
            "type":"Retail Goods"
        }
    ],
    "sg:phone":"+1 304 422 2635",
    "sg:postcode":"26101",
    "sg:province":"WV",
    "sg:tags":[
        "plasterboard",
        "wallboard"
    ],
    "wof:name":"Parkersburg Flood Wall Board",
    "wof:placetype":"venue"
},
  "geometry": {"coordinates":[-81.55182600000001,39.289335],"type":"Point"}
}