{
  "type": "Feature",
  "properties": {
    "addr:full":"313 Rock Cliff Dr Martinsburg WV 25401",
    "addr:housenumber":"313",
    "addr:postcode":"25401",
    "addr:street":"Rock Cliff Dr",
    "iso:country":"US",
    "sg:address":"313 Rock Cliff Dr",
    "sg:city":"Martinsburg",
    "sg:classifiers":[
        {
            "category":"Restaurant",
            "type":"Food & Drink"
        }
    ],
    "sg:phone":"+1 304 262 0155",
    "sg:postcode":"25401",
    "sg:province":"WV",
    "sg:tags":[
        "eating"
    ],
    "wof:name":"King NY Pizza",
    "wof:placetype":"venue"
},
  "geometry": {"coordinates":[-77.97024500000001,39.473329],"type":"Point"}
}