{
  "type": "Feature",
  "properties": {
    "iso:country":"US",
    "sg:address":"153 Stollings Ave",
    "sg:city":"Logan",
    "sg:classifiers":[
        {
            "category":"Government",
            "subcategory":"Office",
            "type":"Public Place"
        }
    ],
    "sg:phone":"+1 304 752 2412",
    "sg:postcode":"25601",
    "sg:province":"WV",
    "sg:tags":[
        "armed",
        "national",
        "force",
        "security",
        "recruiting"
    ],
    "wof:name":"US Army Recruiting",
    "wof:placetype":"venue"
},
  "geometry": {"coordinates":[-81.96591600000001,37.840426],"type":"Point"}
}