{
  "type": "Feature",
  "properties": {
    "iso:country":"US",
    "sg:address":"249 North St",
    "sg:city":"New Martinsville",
    "sg:classifiers":[
        {
            "category":"Utilities",
            "subcategory":"Refuse",
            "type":"Services"
        }
    ],
    "sg:phone":"+1 304 455 6000",
    "sg:postcode":"26155",
    "sg:province":"WV",
    "sg:tags":[
        "system"
    ],
    "wof:name":"Northern Mountain State Metals",
    "wof:placetype":"venue"
},
  "geometry": {"coordinates":[-80.860181,39.642539],"type":"Point"}
}