{
  "type": "Feature",
  "properties": {
    "iso:country":"US",
    "sg:address":"112 Raleigh Ave",
    "sg:city":"Beckley",
    "sg:classifiers":[
        {
            "category":"Education",
            "subcategory":"Dance Studio",
            "type":"Public Place"
        }
    ],
    "sg:phone":"+1 304 255 5684",
    "sg:postcode":"25801",
    "sg:province":"WV",
    "sg:tags":[
        "school",
        "hall"
    ],
    "wof:name":"Beckley Dance Theatre",
    "wof:placetype":"venue"
},
  "geometry": {"coordinates":[-81.197337,37.771046],"type":"Point"}
}