{
  "type": "Feature",
  "properties": {
    "iso:country":"US",
    "sg:address":"5007 Ohio St",
    "sg:city":"Charleston",
    "sg:classifiers":[
        {
            "category":"Organizations",
            "subcategory":"Religious Organization",
            "type":"Services"
        }
    ],
    "sg:phone":"+1 304 768 8162",
    "sg:postcode":"25309",
    "sg:province":"WV",
    "sg:tags":[
        "church"
    ],
    "wof:name":"Southwest Church of God",
    "wof:placetype":"venue"
},
  "geometry": {"coordinates":[-81.73488500000001,38.352311],"type":"Point"}
}