{
  "type": "Feature",
  "properties": {
    "iso:country":"US",
    "sg:address":"508 US Hwy 33",
    "sg:city":"Weston",
    "sg:classifiers":[
        {
            "category":"Autos & Motor Vehicles",
            "subcategory":"Fuel & Gas Station",
            "type":"Retail Goods"
        }
    ],
    "sg:phone":"+1 304 269 3702",
    "sg:postcode":"26452",
    "sg:province":"WV",
    "sg:tags":[
        "station",
        "gasoline",
        "oil"
    ],
    "wof:name":"Burton's Service Station",
    "wof:placetype":"venue"
},
  "geometry": {"coordinates":[-80.47583899999999,39.046038],"type":"Point"}
}