{
  "type": "Feature",
  "properties": {
    "iso:country":"US",
    "sg:address":"2982 Washington Blvd",
    "sg:city":"Belpre",
    "sg:classifiers":[
        {
            "category":"Banks & Credit Unions",
            "subcategory":"Bank",
            "type":"Services"
        }
    ],
    "sg:phone":"+1 740 423 2382",
    "sg:postcode":"45714",
    "sg:province":"OH",
    "sg:tags":[
        "federally",
        "chartered"
    ],
    "wof:name":"Kraton Credit Union",
    "wof:placetype":"venue"
},
  "geometry": {"coordinates":[-81.62306700000001,39.279738],"type":"Point"}
}