{
  "type": "Feature",
  "properties": {
    "iso:country":"US",
    "sg:address":"202 Back Fork St",
    "sg:city":"Webster Springs",
    "sg:classifiers":[
        {
            "category":"Communications",
            "subcategory":"Radio Station",
            "type":"Services"
        }
    ],
    "sg:phone":"+1 304 847 5141",
    "sg:postcode":"26288",
    "sg:province":"WV",
    "sg:tags":[
        "company",
        "broadcasting"
    ],
    "wof:name":"WAFD",
    "wof:placetype":"venue"
},
  "geometry": {"coordinates":[-80.41188699999999,38.479358],"type":"Point"}
}