{
  "type": "Feature",
  "properties": {
    "iso:country":"US",
    "sg:address":"1301 Hal Greer Blvd",
    "sg:city":"Huntington",
    "sg:classifiers":[
        {
            "category":"Health Services",
            "subcategory":"Doctor",
            "type":"Services"
        }
    ],
    "sg:phone":"+1 304 696 7141",
    "sg:postcode":"25701",
    "sg:province":"WV",
    "sg:tags":[
        "medical"
    ],
    "wof:name":"Abulafia Ovadia",
    "wof:placetype":"venue"
},
  "geometry": {"coordinates":[-82.42862100000001,38.410641],"type":"Point"}
}