{
  "type": "Feature",
  "properties": {
    "iso:country":"US",
    "sg:address":"4000 Murdoch Ave",
    "sg:city":"Parkersburg",
    "sg:classifiers":[
        {
            "category":"Shopping",
            "subcategory":"Department Store",
            "type":"Retail Goods"
        }
    ],
    "sg:phone":"+1 304 424 0670",
    "sg:postcode":"26105",
    "sg:province":"WV",
    "wof:name":"T J Maxx",
    "wof:placetype":"venue"
},
  "geometry": {"coordinates":[-81.54831799999999,39.300611],"type":"Point"}
}