{
  "type": "Feature",
  "properties": {
    "addr:full":"224 Center St Weston WV 26452",
    "addr:housenumber":"224",
    "addr:postcode":"26452",
    "addr:street":"Center St",
    "iso:country":"US",
    "sg:address":"224 Center St",
    "sg:city":"Weston",
    "sg:classifiers":[
        {
            "category":"Education",
            "subcategory":"School",
            "type":"Public Place"
        }
    ],
    "sg:phone":"+1 304 269 5547",
    "sg:postcode":"26452",
    "sg:province":"WV",
    "wof:name":"St Patrick School",
    "wof:placetype":"venue"
},
  "geometry": {"coordinates":[-80.465991,39.037588],"type":"Point"}
}