{
  "type": "Feature",
  "properties": {
    "addr:full":"138 Putnam St Marietta OH 45750",
    "addr:housenumber":"138",
    "addr:postcode":"45750",
    "addr:street":"Putnam St",
    "iso:country":"US",
    "sg:address":"138 Putnam St",
    "sg:city":"Marietta",
    "sg:classifiers":[
        {
            "category":"Banks & Credit Unions",
            "subcategory":"Investment Brokerage",
            "type":"Services"
        }
    ],
    "sg:phone":"+1 740 376 7576",
    "sg:postcode":"45750",
    "sg:province":"OH",
    "sg:tags":[
        "stock",
        "bond"
    ],
    "wof:name":"Raymond James Financial Svc",
    "wof:placetype":"venue"
},
  "geometry": {"coordinates":[-81.45504099999999,39.41498],"type":"Point"}
}