{
  "type": "Feature",
  "properties": {
    "iso:country":"US",
    "sg:address":"204 W Main St",
    "sg:city":"Kingwood",
    "sg:classifiers":[
        {
            "category":"Home & Garden",
            "subcategory":"Furniture",
            "type":"Retail Goods"
        }
    ],
    "sg:phone":"+1 304 329 0777",
    "sg:postcode":"26537",
    "sg:province":"WV",
    "sg:tags":[
        "household",
        "carpet"
    ],
    "wof:name":"Bowyers Furniture & Appliances",
    "wof:placetype":"venue"
},
  "geometry": {"coordinates":[-79.691231,39.472121],"type":"Point"}
}