{
  "type": "Feature",
  "properties": {
    "iso:country":"US",
    "sg:address":"212 Main St",
    "sg:city":"Mt Hope",
    "sg:classifiers":[
        {
            "category":"Home & Garden",
            "subcategory":"Hardware",
            "type":"Retail Goods"
        }
    ],
    "sg:phone":"+1 304 877 6441",
    "sg:postcode":"25880",
    "sg:province":"WV",
    "sg:tags":[
        "material"
    ],
    "wof:name":"American Truevale Hardware",
    "wof:placetype":"venue"
},
  "geometry": {"coordinates":[-81.16113799999999,37.897121],"type":"Point"}
}