{
  "type": "Feature",
  "properties": {
    "addr:full":"304 Rock Cliff Dr Martinsburg WV 25401",
    "addr:housenumber":"304",
    "addr:postcode":"25401",
    "addr:street":"Rock Cliff Dr",
    "iso:country":"US",
    "sg:address":"304 Rock Cliff Dr",
    "sg:city":"Martinsburg",
    "sg:classifiers":[
        {
            "category":"Home & Garden",
            "subcategory":"Furniture",
            "type":"Retail Goods"
        }
    ],
    "sg:phone":"+1 304 267 7769",
    "sg:postcode":"25401",
    "sg:province":"WV",
    "wof:name":"Rings Furniture",
    "wof:placetype":"venue"
},
  "geometry": {"coordinates":[-77.97008099999999,39.473384],"type":"Point"}
}