{
  "type": "Feature",
  "properties": {
    "addr:full":"2213 1st St Moundsville WV 26041",
    "addr:housenumber":"2213",
    "addr:postcode":"26041",
    "addr:street":"1St St",
    "iso:country":"US",
    "sg:address":"2213 1st St",
    "sg:city":"Moundsville",
    "sg:classifiers":[
        {
            "category":"Restaurant",
            "type":"Food & Drink"
        }
    ],
    "sg:phone":"+1 304 845 3379",
    "sg:postcode":"26041",
    "sg:province":"WV",
    "wof:name":"Home Restaurant",
    "wof:placetype":"venue"
},
  "geometry": {"coordinates":[-80.730127,39.927359],"type":"Point"}
}