{
  "type": "Feature",
  "properties": {
    "addr:full":"36 York Rd Martinsburg WV 25403",
    "addr:housenumber":"36",
    "addr:postcode":"25403",
    "addr:street":"York Rd",
    "iso:country":"US",
    "sg:address":"36 York Rd",
    "sg:city":"Martinsburg",
    "sg:classifiers":[
        {
            "category":"Transit Center",
            "subcategory":"Freight",
            "type":"Transportation"
        },
        {
            "category":"Freight",
            "type":"Transportation"
        }
    ],
    "sg:phone":"+1 304 267 4811",
    "sg:postcode":"25403",
    "sg:province":"WV",
    "sg:tags":[
        "trucking-motor",
        "trucking"
    ],
    "wof:name":"R&S Trucking Co Inc",
    "wof:placetype":"venue"
},
  "geometry": {"coordinates":[-77.974907,39.498949],"type":"Point"}
}