{
  "type": "Feature",
  "properties": {
    "iso:country":"US",
    "sg:address":"447 W Myles Ave",
    "sg:city":"Pennsboro",
    "sg:classifiers":[
        {
            "category":"Retail",
            "subcategory":"Funeral Services",
            "type":"Services"
        }
    ],
    "sg:phone":"+1 304 659 2251",
    "sg:postcode":"26415",
    "sg:province":"WV",
    "sg:tags":[
        "director"
    ],
    "wof:name":"Mc Cullough Rogers & Raiguel",
    "wof:placetype":"venue"
},
  "geometry": {"coordinates":[-80.978657,39.283879],"type":"Point"}
}