{
  "type": "Feature",
  "properties": {
    "addr:full":"168 High St Harpers Ferry WV 25425",
    "addr:housenumber":"168",
    "addr:postcode":"25425",
    "addr:street":"High St",
    "iso:country":"US",
    "sg:address":"168 High St",
    "sg:city":"Harpers Ferry",
    "sg:classifiers":[
        {
            "category":"Museum",
            "type":"Entertainment"
        }
    ],
    "sg:phone":"+1 304 535 6342",
    "sg:postcode":"25425",
    "sg:province":"WV",
    "wof:name":"John Brown Wax Museum",
    "wof:placetype":"venue"
},
  "geometry": {"coordinates":[-77.730735,39.32341],"type":"Point"}
}