{
  "type": "Feature",
  "properties": {
    "addr:city":"Harpers Ferry",
    "addr:full":"168 High St Harpers Ferry, Wv 25425",
    "addr:house_number":"168",
    "addr:housenumber":"168",
    "addr:phone":"+1 304-535-6342",
    "addr:postcode":"25425",
    "addr:road":"High St",
    "addr:state":"WV",
    "addr:street":"High St",
    "iso:country":"US",
    "sg:address":"168 High St",
    "sg:city":"Harpers Ferry",
    "sg:classifiers":[
        {
            "category":"Museum",
            "type":"Entertainment"
        }
    ],
    "sg:phone":"+1 304 535 6342",
    "sg:postcode":"25425",
    "sg:province":"WV",
    "wof:name":"John Brown Wax Museum",
    "wof:placetype":"venue"
},
  "geometry": {"coordinates":[-77.73146,39.32385],"type":"Point"}
}