{
  "type": "Feature",
  "properties": {
    "iso:country":"US",
    "sg:address":"730 Oak St",
    "sg:city":"Kenova",
    "sg:classifiers":[
        {
            "category":"Health Services",
            "subcategory":"Doctor",
            "type":"Services"
        }
    ],
    "sg:phone":"+1 304 453 6136",
    "sg:postcode":"25530",
    "sg:province":"WV",
    "sg:tags":[
        "physician",
        "surgeon"
    ],
    "wof:name":"CHH Family Medical Ctr",
    "wof:placetype":"venue"
},
  "geometry": {"coordinates":[-82.56758499999999,38.398028],"type":"Point"}
}