{
  "type": "Feature",
  "properties": {
    "addr:full":"105 Elmridge Ct Beckley WV 25801",
    "addr:housenumber":"105",
    "addr:postcode":"25801",
    "addr:street":"Elmridge Ct",
    "iso:country":"US",
    "sg:address":"105 Elmridge Ct",
    "sg:city":"Beckley",
    "sg:classifiers":[
        {
            "category":"Health Services",
            "subcategory":"Doctor",
            "type":"Services"
        }
    ],
    "sg:phone":"+1 304 253 2606",
    "sg:postcode":"25801",
    "sg:province":"WV",
    "sg:tags":[
        "medical"
    ],
    "wof:name":"E H Isaac Dr",
    "wof:placetype":"venue"
},
  "geometry": {"coordinates":[-81.204415,37.807738],"type":"Point"}
}