{
  "type": "Feature",
  "properties": {
    "iso:country":"US",
    "sg:address":"510 Cherry St",
    "sg:city":"Bluefield",
    "sg:classifiers":[
        {
            "category":"Health Services",
            "subcategory":"Doctor",
            "type":"Services"
        }
    ],
    "sg:phone":"+1 304 325 6177",
    "sg:postcode":"24701",
    "sg:province":"WV",
    "sg:tags":[
        "physician",
        "surgeon"
    ],
    "wof:name":"Adult & Pediatric Urology Inc",
    "wof:placetype":"venue"
},
  "geometry": {"coordinates":[-81.234149,37.255751],"type":"Point"}
}