{
  "type": "Feature",
  "properties": {
    "iso:country":"US",
    "sg:address":"215 Brookshire Ln",
    "sg:city":"Beckley",
    "sg:classifiers":[
        {
            "category":"Social Services",
            "subcategory":"Job Training",
            "type":"Services"
        }
    ],
    "sg:phone":"+1 304 255 5200",
    "sg:postcode":"25801",
    "sg:province":"WV",
    "sg:tags":[
        "rehabilitation"
    ],
    "wof:name":"Healthsouth Southern Hills Ctr",
    "wof:placetype":"venue"
},
  "geometry": {"coordinates":[-81.15937099999999,37.77021],"type":"Point"}
}