{
  "type": "Feature",
  "properties": {
    "addr:full":"1990 Fairmont Ave Fairmont WV 26554",
    "addr:housenumber":"1990",
    "addr:postcode":"26554",
    "addr:street":"Fairmont Ave",
    "iso:country":"US",
    "sg:address":"1990 Fairmont Ave",
    "sg:city":"Fairmont",
    "sg:classifiers":[
        {
            "category":"Wholesale",
            "subcategory":"Electrical",
            "type":"Manufacturing & Wholesale Goods"
        }
    ],
    "sg:phone":"+1 304 363 4463",
    "sg:postcode":"26554",
    "sg:province":"WV",
    "sg:tags":[
        "communication",
        "radio",
        "system"
    ],
    "wof:name":"Country Roads Mobile Comm Svc",
    "wof:placetype":"venue"
},
  "geometry": {"coordinates":[-80.17481100000001,39.450613],"type":"Point"}
}