{
  "type": "Feature",
  "properties": {
    "iso:country":"US",
    "sg:address":"319 E Main St",
    "sg:city":"Harrisville",
    "sg:classifiers":[
        {
            "category":"Government",
            "subcategory":"Office",
            "type":"Public Place"
        }
    ],
    "sg:phone":"+1 304 643 2658",
    "sg:postcode":"26362",
    "sg:province":"WV",
    "wof:name":"Honorable Teresa C Harper",
    "wof:placetype":"venue"
},
  "geometry": {"coordinates":[-81.050541,39.209638],"type":"Point"}
}