{
  "type": "Feature",
  "properties": {
    "iso:country":"US",
    "sg:address":"406 Beech Ave",
    "sg:city":"Charleston",
    "sg:classifiers":[
        {
            "category":"Professional",
            "subcategory":"Art Services",
            "type":"Services"
        }
    ],
    "sg:phone":"+1 304 344 3192",
    "sg:postcode":"25302",
    "sg:province":"WV",
    "sg:tags":[
        "graphic",
        "designer"
    ],
    "wof:name":"Anne Meyer Design",
    "wof:placetype":"venue"
},
  "geometry": {"coordinates":[-81.64297500000001,38.368202],"type":"Point"}
}