{
  "type": "Feature",
  "properties": {
    "iso:country":"US",
    "sg:address":"350 Old Piney Trl",
    "sg:city":"Beaver",
    "sg:classifiers":[
        {
            "category":"Professional",
            "subcategory":"Business Services",
            "type":"Services"
        }
    ],
    "sg:phone":"+1 304 252 9099",
    "sg:postcode":"25813",
    "sg:province":"WV",
    "wof:name":"Tim Thompson",
    "wof:placetype":"venue"
},
  "geometry": {"coordinates":[-81.131067,37.776219],"type":"Point"}
}