{
  "type": "Feature",
  "properties": {
    "addr:full":"910 Delaware St Mount Hope WV 25880",
    "addr:housenumber":"910",
    "addr:postcode":"25880",
    "addr:street":"Delaware St",
    "iso:country":"US",
    "sg:address":"910 Delaware St",
    "sg:city":"Mount Hope",
    "sg:classifiers":[
        {
            "category":"Bars & Pubs",
            "type":"Food & Drink"
        }
    ],
    "sg:phone":"+1 304 877 6948",
    "sg:postcode":"25880",
    "sg:province":"WV",
    "sg:tags":[
        "drinking"
    ],
    "wof:name":"Sams Place",
    "wof:placetype":"venue"
},
  "geometry": {"coordinates":[-81.17247399999999,37.890347],"type":"Point"}
}