{
  "type": "Feature",
  "properties": {
    "iso:country":"US",
    "sg:address":"1001 3rd Ave",
    "sg:city":"Huntington",
    "sg:classifiers":[
        {
            "category":"Travel",
            "subcategory":"Hotels & Motels",
            "type":"Entertainment"
        }
    ],
    "sg:phone":"+1 304 525 1001",
    "sg:postcode":"25701",
    "sg:province":"WV",
    "wof:name":"Radisson Hotel",
    "wof:placetype":"venue"
},
  "geometry": {"coordinates":[-82.440834,38.422506],"type":"Point"}
}