{
  "type": "Feature",
  "properties": {
    "iso:country":"US",
    "sg:address":"7796 Winchester Ave",
    "sg:city":"Inwood",
    "sg:classifiers":[
        {
            "category":"Government",
            "subcategory":"Post Office",
            "type":"Public Place"
        }
    ],
    "sg:phone":"+1 304 229 7244",
    "sg:postcode":"25428",
    "sg:province":"WV",
    "wof:name":"United States Postal Services",
    "wof:placetype":"venue"
},
  "geometry": {"coordinates":[-78.037372,39.361098],"type":"Point"}
}