{
  "type": "Feature",
  "properties": {
    "addr:full":"500 Carolina Ave Chester WV 26034",
    "addr:housenumber":"500",
    "addr:postcode":"26034",
    "addr:street":"Carolina Ave",
    "iso:country":"US",
    "sg:address":"500 Carolina Ave",
    "sg:city":"Chester",
    "sg:classifiers":[
        {
            "category":"Organizations",
            "subcategory":"Community Association",
            "type":"Services"
        }
    ],
    "sg:phone":"+1 304 387 1189",
    "sg:postcode":"26034",
    "sg:province":"WV",
    "sg:tags":[
        "club"
    ],
    "wof:name":"P-2 Club",
    "wof:placetype":"venue"
},
  "geometry": {"coordinates":[-80.562489,40.613203],"type":"Point"}
}