{
  "type": "Feature",
  "properties": {
    "iso:country":"US",
    "sg:address":"34 Poplar Ave",
    "sg:city":"Wheeling",
    "sg:classifiers":[
        {
            "category":"Organizations",
            "subcategory":"Religious Organization",
            "type":"Services"
        }
    ],
    "sg:phone":"+1 304 232 0861",
    "sg:postcode":"26003",
    "sg:province":"WV",
    "sg:tags":[
        "church"
    ],
    "wof:name":"Greggsville United Meth Church",
    "wof:placetype":"venue"
},
  "geometry": {"coordinates":[-80.68884300000001,40.080693],"type":"Point"}
}