{
  "type": "Feature",
  "properties": {
    "addr:full":"1105 Market St Wheeling WV 26003",
    "addr:housenumber":"1105",
    "addr:postcode":"26003",
    "addr:street":"Market St",
    "iso:country":"US",
    "sg:address":"1105 Market St",
    "sg:city":"Wheeling",
    "sg:classifiers":[
        {
            "category":"Professional",
            "subcategory":"Detective & Security Services",
            "type":"Services"
        },
        {
            "category":"Professional",
            "subcategory":"Business Services",
            "type":"Services"
        }
    ],
    "sg:phone":"+1 304 234 4470",
    "sg:postcode":"26003",
    "sg:province":"WV",
    "sg:tags":[
        "investigator"
    ],
    "wof:name":"Brian T Ferda",
    "wof:placetype":"venue"
},
  "geometry": {"coordinates":[-80.722599,40.067322],"type":"Point"}
}