{
  "type": "Feature",
  "properties": {
    "iso:country":"US",
    "sg:address":"89 E Main St",
    "sg:city":"White Sulphur Springs",
    "sg:classifiers":[
        {
            "category":"Autos & Motor Vehicles",
            "subcategory":"Automobile Sales",
            "type":"Retail Goods"
        }
    ],
    "sg:phone":"+1 304 536 4192",
    "sg:postcode":"24986",
    "sg:province":"WV",
    "sg:tags":[
        "used"
    ],
    "wof:name":"Old White Mtrs Pr-Wned Spclist",
    "wof:placetype":"venue"
},
  "geometry": {"coordinates":[-80.298551,37.795503],"type":"Point"}
}