{
  "type": "Feature",
  "properties": {
    "iso:country":"US",
    "sg:address":"104 Albright Ave",
    "sg:city":"Kingwood",
    "sg:classifiers":[
        {
            "category":"Real Estate",
            "subcategory":"Developer",
            "type":"Services"
        }
    ],
    "sg:phone":"+1 304 329 3462",
    "sg:postcode":"26537",
    "sg:province":"WV",
    "sg:tags":[
        "cemetery"
    ],
    "wof:name":"Gordon Cemetery Assoc",
    "wof:placetype":"venue"
},
  "geometry": {"coordinates":[-79.698331,39.473725],"type":"Point"}
}