{
  "type": "Feature",
  "properties": {
    "iso:country":"US",
    "sg:address":"113 Clarksburg St",
    "sg:city":"Mannington",
    "sg:classifiers":[
        {
            "category":"Social Services",
            "subcategory":"Child Care",
            "type":"Services"
        }
    ],
    "sg:phone":"+1 304 986 3219",
    "sg:postcode":"26582",
    "sg:province":"WV",
    "sg:tags":[
        "kindergarten",
        "academic",
        "school"
    ],
    "wof:name":"Mannington Head Start",
    "wof:placetype":"venue"
},
  "geometry": {"coordinates":[-80.34455,39.529531],"type":"Point"}
}