{
  "type": "Feature",
  "properties": {
    "iso:country":"US",
    "sg:address":"403 Howard St",
    "sg:city":"Shinnston",
    "sg:classifiers":[
        {
            "category":"Health Services",
            "subcategory":"Chiropractor",
            "type":"Services"
        }
    ],
    "sg:phone":"+1 304 592 3301",
    "sg:postcode":"26431",
    "sg:province":"WV",
    "wof:name":"Shinnston Chiropractic Center",
    "wof:placetype":"venue"
},
  "geometry": {"coordinates":[-80.307897,39.391002],"type":"Point"}
}