{
  "type": "Feature",
  "properties": {
    "iso:country":"US",
    "sg:address":"55 E Main St",
    "sg:city":"Richwood",
    "sg:classifiers":[
        {
            "category":"Travel",
            "subcategory":"Hotels & Motels",
            "type":"Entertainment"
        }
    ],
    "sg:phone":"+1 304 846 4605",
    "sg:postcode":"26261",
    "sg:province":"WV",
    "wof:name":"Four Seasons Lodge",
    "wof:placetype":"venue"
},
  "geometry": {"coordinates":[-80.53117399999999,38.225839],"type":"Point"}
}