{
  "type": "Feature",
  "properties": {
    "iso:country":"US",
    "sg:address":"2300 River Rd",
    "sg:city":"Vienna",
    "sg:classifiers":[
        {
            "category":"Education",
            "subcategory":"Library",
            "type":"Public Place"
        }
    ],
    "sg:phone":"+1 304 295 7771",
    "sg:postcode":"26105",
    "sg:province":"WV",
    "sg:tags":[
        "executive"
    ],
    "wof:name":"Vienna Public Library",
    "wof:placetype":"venue"
},
  "geometry": {"coordinates":[-81.553798,39.322556],"type":"Point"}
}