{
  "type": "Feature",
  "properties": {
    "iso:country":"US",
    "sg:address":"6 Cloverleaf Cir",
    "sg:city":"Charleston",
    "sg:classifiers":[
        {
            "category":"Manufacturing",
            "subcategory":"Retail Goods",
            "type":"Manufacturing & Wholesale Goods"
        }
    ],
    "sg:phone":"+1 304 925 1495",
    "sg:postcode":"25306",
    "sg:province":"WV",
    "sg:tags":[
        "marking",
        "devices",
        "mfg"
    ],
    "wof:name":"Cook Paul",
    "wof:placetype":"venue"
},
  "geometry": {"coordinates":[-81.55718899999999,38.302879],"type":"Point"}
}