{
  "type": "Feature",
  "properties": {
    "iso:country":"US",
    "sg:address":"110 McKinley Dr",
    "sg:city":"Follansbee",
    "sg:classifiers":[
        {
            "category":"Building & Trades",
            "subcategory":"Construction",
            "type":"Services"
        }
    ],
    "sg:phone":"+1 304 527 1990",
    "sg:postcode":"26037",
    "sg:province":"WV",
    "sg:tags":[
        "house"
    ],
    "wof:name":"B U Construction",
    "wof:placetype":"venue"
},
  "geometry": {"coordinates":[-80.581197,40.318989],"type":"Point"}
}