{
  "type": "Feature",
  "properties": {
    "addr:full":"503 21st St Vienna WV 26105",
    "addr:housenumber":"503",
    "addr:postcode":"26105",
    "addr:street":"21St St",
    "iso:country":"US",
    "sg:address":"503 21st St",
    "sg:city":"Vienna",
    "sg:classifiers":[
        {
            "category":"Freight",
            "type":"Transportation"
        }
    ],
    "sg:phone":"+1 304 295 0964",
    "sg:postcode":"26105",
    "sg:province":"WV",
    "sg:tags":[
        "commercial",
        "storage",
        "special"
    ],
    "wof:name":"Vienna Mini Storage",
    "wof:placetype":"venue"
},
  "geometry": {"coordinates":[-81.551305,39.320074],"type":"Point"}
}