{
  "type": "Feature",
  "properties": {
    "addr:full":"308 Locust St Princeton WV 24740",
    "addr:housenumber":"308",
    "addr:postcode":"24740",
    "addr:street":"Locust St",
    "iso:country":"US",
    "sg:address":"308 Locust St",
    "sg:city":"Princeton",
    "sg:classifiers":[
        {
            "category":"Shopping",
            "subcategory":"Gifts & Souvenirs",
            "type":"Retail Goods"
        }
    ],
    "sg:phone":"+1 304 487 8899",
    "sg:postcode":"24740",
    "sg:province":"WV",
    "sg:tags":[
        "shop"
    ],
    "wof:name":"Primitive Corner",
    "wof:placetype":"venue"
},
  "geometry": {"coordinates":[-81.07858299999999,37.36214],"type":"Point"}
}