{
  "type": "Feature",
  "properties": {
    "addr:full":"1000 Williams Dr Weirton WV 26062",
    "addr:housenumber":"1000",
    "addr:postcode":"26062",
    "addr:street":"Williams Dr",
    "iso:country":"US",
    "sg:address":"1000 Williams Dr",
    "sg:city":"Weirton",
    "sg:classifiers":[
        {
            "category":"Social Services",
            "type":"Services"
        },
        {
            "category":"Organizations",
            "subcategory":"Membership Organization",
            "type":"Services"
        },
        {
            "category":"Professional",
            "subcategory":"Employment Agencies",
            "type":"Services"
        },
        {
            "category":"Sports & Exercise",
            "subcategory":"Golf",
            "type":"Entertainment"
        }
    ],
    "sg:phone":"+1 304 748 8455",
    "sg:postcode":"26062",
    "sg:province":"WV",
    "sg:tags":[
        "placement",
        "club",
        "private",
        "course",
        "workers'",
        "volunteer"
    ],
    "wof:name":"The Williams Country Club",
    "wof:placetype":"venue"
},
  "geometry": {"coordinates":[-80.601311,40.409492],"type":"Point"}
}