{
  "type": "Feature",
  "properties": {
    "iso:country":"US",
    "sg:address":"15063 Maccorkle Ave",
    "sg:city":"Cabin Creek",
    "sg:classifiers":[
        {
            "category":"Shopping",
            "subcategory":"Discount & Variety Stores",
            "type":"Retail Goods"
        }
    ],
    "sg:phone":"+1 304 595 3100",
    "sg:postcode":"25035",
    "sg:province":"WV",
    "wof:name":"Dollar General",
    "wof:placetype":"venue"
},
  "geometry": {"coordinates":[-81.490578,38.195256],"type":"Point"}
}