{
  "type": "Feature",
  "properties": {
    "iso:country":"US",
    "sg:address":"4150 State Route 34",
    "sg:city":"Hurricane",
    "sg:classifiers":[
        {
            "category":"Restaurant",
            "type":"Food & Drink"
        }
    ],
    "sg:menulink":"http://www.allmenus.com/wv/teays/101057-captain-ds-seafood/menu/",
    "sg:phone":"+1 304 757 8144",
    "sg:postcode":"25526",
    "sg:province":"WV",
    "sg:tags":[
        "seafood",
        "american"
    ],
    "wof:name":"Captain D's Seafood",
    "wof:placetype":"venue"
},
  "geometry": {"coordinates":[-81.93788000000001,38.45261],"type":"Point"}
}