{
  "type": "Feature",
  "properties": {
    "addr:full":"664 Main St Barboursville WV 25504",
    "addr:housenumber":"664",
    "addr:postcode":"25504",
    "addr:street":"Main St",
    "iso:country":"US",
    "sg:address":"664 Main St",
    "sg:city":"Barboursville",
    "sg:classifiers":[
        {
            "category":"Shopping",
            "subcategory":"Jewelry",
            "type":"Retail Goods"
        }
    ],
    "sg:phone":"+1 304 733 6500",
    "sg:postcode":"25504",
    "sg:province":"WV",
    "wof:name":"Alexanders Sterling & ACC",
    "wof:placetype":"venue"
},
  "geometry": {"coordinates":[-82.295197,38.409759],"type":"Point"}
}