{
  "type": "Feature",
  "properties": {
    "iso:country":"US",
    "sg:address":"2580 Grant Gardens",
    "sg:city":"Ona",
    "sg:classifiers":[
        {
            "category":"Social Services",
            "subcategory":"Adult Care",
            "type":"Services"
        }
    ],
    "sg:phone":"+1 304 743 4439",
    "sg:postcode":"25545",
    "sg:province":"WV",
    "sg:tags":[
        "residential",
        "disturbed",
        "for",
        "child"
    ],
    "wof:name":"Pressley Ridge Schools",
    "wof:placetype":"venue"
},
  "geometry": {"coordinates":[-82.203608,38.432697],"type":"Point"}
}