{
  "type": "Feature",
  "properties": {
    "iso:country":"US",
    "sg:address":"375 Carolina Ave",
    "sg:city":"Chester",
    "sg:classifiers":[
        {
            "category":"Government",
            "subcategory":"Office",
            "type":"Public Place"
        }
    ],
    "sg:phone":"+1 304 387 0772",
    "sg:postcode":"26034",
    "sg:province":"WV",
    "sg:tags":[
        "management"
    ],
    "wof:name":"Pump House",
    "wof:placetype":"venue"
},
  "geometry": {"coordinates":[-80.564044,40.61236],"type":"Point"}
}