{
  "type": "Feature",
  "properties": {
    "addr:full":"102 Chips Ln Follansbee WV 26037",
    "addr:housenumber":"102",
    "addr:postcode":"26037",
    "addr:street":"Chips Ln",
    "iso:country":"US",
    "sg:address":"102 Chips Ln",
    "sg:city":"Follansbee",
    "sg:classifiers":[
        {
            "category":"Building & Trades",
            "subcategory":"Construction",
            "type":"Services"
        }
    ],
    "sg:phone":"+1 304 527 4198",
    "sg:postcode":"26037",
    "sg:province":"WV",
    "sg:tags":[
        "residential"
    ],
    "wof:name":"Bonaventura Construction",
    "wof:placetype":"venue"
},
  "geometry": {"coordinates":[-80.57862,40.316135],"type":"Point"}
}