{
  "type": "Feature",
  "properties": {
    "iso:country":"US",
    "sg:address":"126 Oakwood Rd",
    "sg:city":"Charleston",
    "sg:classifiers":[
        {
            "category":"Real Estate",
            "subcategory":"Real Estate Agent",
            "type":"Services"
        }
    ],
    "sg:phone":"+1 304 346 9082",
    "sg:postcode":"25314",
    "sg:province":"WV",
    "wof:name":"Antique Appraisals",
    "wof:placetype":"venue"
},
  "geometry": {"coordinates":[-81.651494,38.33434],"type":"Point"}
}