{
  "type": "Feature",
  "properties": {
    "iso:country":"US",
    "sg:address":"1921 19th St",
    "sg:city":"Nitro",
    "sg:classifiers":[
        {
            "category":"Education",
            "subcategory":"School",
            "type":"Public Place"
        }
    ],
    "sg:phone":"+1 304 755 2451",
    "sg:postcode":"25143",
    "sg:province":"WV",
    "sg:tags":[
        "elementary"
    ],
    "wof:name":"Nitro Elementary School",
    "wof:placetype":"venue"
},
  "geometry": {"coordinates":[-81.841213,38.420398],"type":"Point"}
}