{
  "type": "Feature",
  "properties": {
    "iso:country":"US",
    "sg:address":"202 Adams St",
    "sg:city":"Fairmont",
    "sg:classifiers":[
        {
            "category":"Real Estate",
            "subcategory":"Real Estate Agent",
            "type":"Services"
        }
    ],
    "sg:phone":"+1 304 363 1170",
    "sg:postcode":"26554",
    "sg:province":"WV",
    "sg:tags":[
        "agency"
    ],
    "wof:name":"R S Pizatella & Associates",
    "wof:placetype":"venue"
},
  "geometry": {"coordinates":[-80.142664,39.484761],"type":"Point"}
}