{
  "type": "Feature",
  "properties": {
    "addr:full":"36 Fox Sparrow Rd Beckley WV 25801",
    "addr:housenumber":"36",
    "addr:postcode":"25801",
    "addr:street":"Fox Sparrow Rd",
    "iso:country":"US",
    "sg:address":"36 Fox Sparrow Rd",
    "sg:city":"Beckley",
    "sg:classifiers":[
        {
            "category":"Professional",
            "type":"Services"
        }
    ],
    "sg:phone":"+1 304 255 0821",
    "sg:postcode":"25801",
    "sg:province":"WV",
    "sg:tags":[
        "establishment"
    ],
    "wof:name":"Professional Medical Trnscrptn",
    "wof:placetype":"venue"
},
  "geometry": {"coordinates":[-81.159668,37.803592],"type":"Point"}
}