{
  "type": "Feature",
  "properties": {
    "iso:country":"US",
    "sg:address":"581 Fairchance Rd",
    "sg:city":"Morgantown",
    "sg:classifiers":[
        {
            "category":"Government",
            "subcategory":"Office",
            "type":"Public Place"
        }
    ],
    "sg:phone":"+1 304 594 2632",
    "sg:postcode":"26508",
    "sg:province":"WV",
    "sg:tags":[
        "management"
    ],
    "wof:name":"Air Quality Analysis",
    "wof:placetype":"venue"
},
  "geometry": {"coordinates":[-79.82761000000001,39.690842],"type":"Point"}
}