{
  "type": "Feature",
  "properties": {
    "iso:country":"US",
    "sg:address":"1222 Mount Vernon Pl",
    "sg:city":"Charleston",
    "sg:classifiers":[
        {
            "category":"Health Services",
            "subcategory":"Health Practitioner",
            "type":"Services"
        }
    ],
    "sg:phone":"+1 304 343 8691",
    "sg:postcode":"25314",
    "sg:province":"WV",
    "wof:name":"Tonia L Chismar",
    "wof:placetype":"venue"
},
  "geometry": {"coordinates":[-81.654976,38.316716],"type":"Point"}
}