{
  "type": "Feature",
  "properties": {
    "addr:full":"779 Ganotown E Rd Gerrardstown WV 25420",
    "addr:housenumber":"779",
    "addr:postcode":"25420",
    "addr:street":"Ganotown E Rd",
    "iso:country":"US",
    "sg:address":"779 Ganotown E Rd",
    "sg:city":"Gerrardstown",
    "sg:classifiers":[
        {
            "category":"Retail",
            "subcategory":"Auto Repair",
            "type":"Services"
        }
    ],
    "sg:phone":"+1 304 229 3522",
    "sg:postcode":"25420",
    "sg:province":"WV",
    "wof:name":"Richard's Auto Shop",
    "wof:placetype":"venue"
},
  "geometry": {"coordinates":[-78.095703,39.3783],"type":"Point"}
}