{
  "type": "Feature",
  "properties": {
    "addr:full":"301 10th Ave Huntington WV 25701",
    "addr:housenumber":"301",
    "addr:postcode":"25701",
    "addr:street":"10Th Ave",
    "iso:country":"US",
    "sg:address":"301 10th Ave",
    "sg:city":"Huntington",
    "sg:classifiers":[
        {
            "category":"Building & Trades",
            "subcategory":"Landscaping Services",
            "type":"Services"
        }
    ],
    "sg:phone":"+1 304 522 4421",
    "sg:postcode":"25701",
    "sg:province":"WV",
    "wof:name":"Lucille Shivel",
    "wof:placetype":"venue"
},
  "geometry": {"coordinates":[-82.450048,38.410865],"type":"Point"}
}