{
  "type": "Feature",
  "properties": {
    "addr:full":"711 Bluefield Ave Bluefield WV 24701",
    "addr:housenumber":"711",
    "addr:postcode":"24701",
    "addr:street":"Bluefield Ave",
    "iso:country":"US",
    "sg:address":"711 Bluefield Ave",
    "sg:city":"Bluefield",
    "sg:classifiers":[
        {
            "category":"Autos & Motor Vehicles",
            "subcategory":"Auto Supplies",
            "type":"Retail Goods"
        }
    ],
    "sg:phone":"+1 304 324 8281",
    "sg:postcode":"24701",
    "sg:province":"WV",
    "sg:tags":[
        "automobile",
        "parts"
    ],
    "sg:website":"www.autozone.com",
    "wof:name":"Autozone",
    "wof:placetype":"venue"
},
  "geometry": {"coordinates":[-81.232919,37.266023],"type":"Point"}
}