{
  "type": "Feature",
  "properties": {
    "addr:full":"2595 Williamsport Pike Martinsburg WV 25404",
    "addr:housenumber":"2595",
    "addr:postcode":"25404",
    "addr:street":"Williamsport Pike",
    "iso:country":"US",
    "sg:address":"2595 Williamsport Pike",
    "sg:city":"Martinsburg",
    "sg:classifiers":[
        {
            "category":"Autos & Motor Vehicles",
            "subcategory":"Automobile Sales",
            "type":"Retail Goods"
        }
    ],
    "sg:phone":"+1 304 263 0505",
    "sg:postcode":"25404",
    "sg:province":"WV",
    "sg:tags":[
        "dealers-used",
        "car",
        "used",
        "cars-wholesale"
    ],
    "wof:name":"Charity Car Barn",
    "wof:placetype":"venue"
},
  "geometry": {"coordinates":[-77.93493100000001,39.507701],"type":"Point"}
}