{
  "type": "Feature",
  "properties": {
    "iso:country":"US",
    "sg:address":"1539 Washington St W",
    "sg:city":"Charleston",
    "sg:classifiers":[
        {
            "category":"Retail",
            "subcategory":"Repair Shop",
            "type":"Services"
        }
    ],
    "sg:phone":"+1 304 344 3451",
    "sg:postcode":"25312",
    "sg:province":"WV",
    "sg:tags":[
        "equipment"
    ],
    "wof:name":"Central Service Co",
    "wof:placetype":"venue"
},
  "geometry": {"coordinates":[-81.661058,38.371795],"type":"Point"}
}