{
  "type": "Feature",
  "properties": {
    "iso:country":"US",
    "sg:address":"681 Riverside Dr",
    "sg:city":"Welch",
    "sg:classifiers":[
        {
            "category":"Banks & Credit Unions",
            "subcategory":"Bank",
            "type":"Services"
        }
    ],
    "sg:phone":"+1 304 436 2171",
    "sg:postcode":"24801",
    "sg:province":"WV",
    "wof:name":"Ameribank",
    "wof:placetype":"venue"
},
  "geometry": {"coordinates":[-81.57161499999999,37.399135],"type":"Point"}
}