{
  "type": "Feature",
  "properties": {
    "iso:country":"US",
    "sg:address":"201 4th Ave",
    "sg:city":"Huntington",
    "sg:classifiers":[
        {
            "category":"Organizations",
            "subcategory":"Community Association",
            "type":"Services"
        }
    ],
    "sg:phone":"+1 304 696 9179",
    "sg:postcode":"25701",
    "sg:province":"WV",
    "sg:tags":[
        "civic",
        "social"
    ],
    "wof:name":"Caper",
    "wof:placetype":"venue"
},
  "geometry": {"coordinates":[-82.454218,38.418973],"type":"Point"}
}