{
  "type": "Feature",
  "properties": {
    "addr:full":"11220 Veterans Memorial Hwy Masontown WV 26542",
    "addr:housenumber":"11220",
    "addr:postcode":"26542",
    "addr:street":"Veterans Memorial Hwy",
    "iso:country":"US",
    "sg:address":"11220 Veterans Memorial Hwy",
    "sg:city":"Masontown",
    "sg:classifiers":[
        {
            "category":"Health Services",
            "subcategory":"Chiropractor",
            "type":"Services"
        }
    ],
    "sg:phone":"+1 304 864 5870",
    "sg:postcode":"26542",
    "sg:province":"WV",
    "sg:tags":[
        "chiropractic"
    ],
    "wof:name":"Mary Rehe",
    "wof:placetype":"venue"
},
  "geometry": {"coordinates":[-79.797642,39.531858],"type":"Point"}
}