{
  "type": "Feature",
  "properties": {
    "iso:country":"US",
    "sg:address":"1014 Winchester Ave",
    "sg:city":"Martinsburg",
    "sg:classifiers":[
        {
            "category":"Retail",
            "subcategory":"Auto Rental",
            "type":"Services"
        }
    ],
    "sg:phone":"+1 304 267 7675",
    "sg:postcode":"25401",
    "sg:province":"WV",
    "sg:tags":[
        "passenger",
        "car"
    ],
    "wof:name":"Thrifty Car Rental",
    "wof:placetype":"venue"
},
  "geometry": {"coordinates":[-77.98019499999999,39.44703],"type":"Point"}
}