{
  "type": "Feature",
  "properties": {
    "iso:country":"US",
    "sg:address":"2187 National Rd",
    "sg:city":"Wheeling",
    "sg:classifiers":[
        {
            "category":"Shopping",
            "subcategory":"Bicycles & Sporting Goods",
            "type":"Retail Goods"
        }
    ],
    "sg:phone":"+1 304 242 2100",
    "sg:postcode":"26003",
    "sg:province":"WV",
    "wof:name":"Wheelcraft Limited",
    "wof:placetype":"venue"
},
  "geometry": {"coordinates":[-80.659772,40.044768],"type":"Point"}
}