{
  "type": "Feature",
  "properties": {
    "iso:country":"US",
    "sg:address":"88 High St",
    "sg:city":"Morgantown",
    "sg:classifiers":[
        {
            "category":"Shopping",
            "subcategory":"Stationery & Office Supplies",
            "type":"Retail Goods"
        }
    ],
    "sg:phone":"+1 304 292 5751",
    "sg:postcode":"26505",
    "sg:province":"WV",
    "wof:name":"City Office Equipment",
    "wof:placetype":"venue"
},
  "geometry": {"coordinates":[-79.957632,39.627614],"type":"Point"}
}