{
  "type": "Feature",
  "properties": {
    "iso:country":"US",
    "sg:address":"610 Rogers St",
    "sg:city":"Princeton",
    "sg:classifiers":[
        {
            "category":"Personal",
            "subcategory":"Beauty Salon",
            "type":"Services"
        }
    ],
    "sg:phone":"+1 304 431 2557",
    "sg:postcode":"24740",
    "sg:province":"WV",
    "sg:tags":[
        "shop"
    ],
    "wof:name":"Cuttin Loose Hair & Tan Salon",
    "wof:placetype":"venue"
},
  "geometry": {"coordinates":[-81.078484,37.365222],"type":"Point"}
}