{
  "type": "Feature",
  "properties": {
    "iso:country":"US",
    "sg:address":"253 Fowler Hill Rd",
    "sg:city":"Wellsburg",
    "sg:classifiers":[
        {
            "category":"Building & Trades",
            "subcategory":"Cleaning & Sanitation",
            "type":"Services"
        }
    ],
    "sg:phone":"+1 304 737 4707",
    "sg:postcode":"26070",
    "sg:province":"WV",
    "sg:tags":[
        "maintenance"
    ],
    "wof:name":"Natl Vacuuming Corp",
    "wof:placetype":"venue"
},
  "geometry": {"coordinates":[-80.54723799999999,40.278371],"type":"Point"}
}