{
  "type": "Feature",
  "properties": {
    "iso:country":"US",
    "sg:address":"191 Armstrong St",
    "sg:city":"Keyser",
    "sg:classifiers":[
        {
            "category":"Personal",
            "subcategory":"Beauty Salon",
            "type":"Services"
        },
        {
            "category":"Personal",
            "subcategory":"Nail Salon",
            "type":"Services"
        }
    ],
    "sg:phone":"+1 304 788 7818",
    "sg:postcode":"26726",
    "sg:province":"WV",
    "sg:tags":[
        "hair",
        "stylist"
    ],
    "wof:name":"Full Volumn Hair & Nail Salon",
    "wof:placetype":"venue"
},
  "geometry": {"coordinates":[-78.972961,39.440152],"type":"Point"}
}