{
  "type": "Feature",
  "properties": {
    "iso:country":"US",
    "sg:address":"68 W Piedmont St",
    "sg:city":"Keyser",
    "sg:classifiers":[
        {
            "category":"Personal",
            "subcategory":"Beauty Salon",
            "type":"Services"
        }
    ],
    "sg:phone":"+1 304 788 0582",
    "sg:postcode":"26726",
    "sg:province":"WV",
    "sg:tags":[
        "shop"
    ],
    "wof:name":"Forrest's Hair Styling",
    "wof:placetype":"venue"
},
  "geometry": {"coordinates":[-78.978886,39.44114],"type":"Point"}
}