{
  "type": "Feature",
  "properties": {
    "iso:country":"US",
    "sg:address":"201 2nd St",
    "sg:city":"St Marys",
    "sg:classifiers":[
        {
            "category":"Professional",
            "subcategory":"Employment Agencies",
            "type":"Services"
        }
    ],
    "sg:phone":"+1 304 684 3113",
    "sg:postcode":"26170",
    "sg:province":"WV",
    "sg:tags":[
        "opportunity"
    ],
    "wof:name":"Workforce West Virginia",
    "wof:placetype":"venue"
},
  "geometry": {"coordinates":[-81.206682,39.390113],"type":"Point"}
}