{
  "type": "Feature",
  "properties": {
    "addr:full":"621 Washington St W Charleston WV 25302",
    "addr:housenumber":"621",
    "addr:postcode":"25302",
    "addr:street":"Washington St W",
    "iso:country":"US",
    "sg:address":"621 Washington St W",
    "sg:city":"Charleston",
    "sg:classifiers":[
        {
            "category":"Restaurant",
            "type":"Food & Drink"
        }
    ],
    "sg:menulink":"http://www.allmenus.com/wv/blue-creek/195877-wendys/menu/",
    "sg:phone":"+1 304 343 9175",
    "sg:postcode":"25302",
    "sg:province":"WV",
    "sg:tags":[
        "burger",
        "american",
        "soup"
    ],
    "wof:name":"Wendy's",
    "wof:placetype":"venue"
},
  "geometry": {"coordinates":[-81.645805,38.365191],"type":"Point"}
}