{
  "type": "Feature",
  "properties": {
    "iso:country":"US",
    "sg:address":"706 Crim Ave",
    "sg:city":"Belington",
    "sg:classifiers":[
        {
            "category":"Building & Trades",
            "subcategory":"Pest Control",
            "type":"Services"
        }
    ],
    "sg:phone":"+1 304 823 3258",
    "sg:postcode":"26250",
    "sg:province":"WV",
    "wof:name":"Ace Exterminators",
    "wof:placetype":"venue"
},
  "geometry": {"coordinates":[-79.938824,39.013215],"type":"Point"}
}