{
  "type": "Feature",
  "properties": {
    "addr:full":"410 Virginia St Oak Hill WV 25901",
    "addr:housenumber":"410",
    "addr:postcode":"25901",
    "addr:street":"Virginia St",
    "iso:country":"US",
    "sg:address":"410 Virginia St",
    "sg:city":"Oak Hill",
    "sg:classifiers":[
        {
            "category":"Personal",
            "subcategory":"Beauty Salon",
            "type":"Services"
        }
    ],
    "sg:phone":"+1 304 469 2368",
    "sg:postcode":"25901",
    "sg:province":"WV",
    "wof:name":"Dorothy's Hair Hut",
    "wof:placetype":"venue"
},
  "geometry": {"coordinates":[-81.156188,37.976072],"type":"Point"}
}