{
  "type": "Feature",
  "properties": {
    "iso:country":"US",
    "sg:address":"113 Tanglewood Dr",
    "sg:city":"Mount Hope",
    "sg:classifiers":[
        {
            "category":"Real Estate",
            "subcategory":"Real Estate Operator",
            "type":"Services"
        }
    ],
    "sg:phone":"+1 304 877 6589",
    "sg:postcode":"25880",
    "sg:province":"WV",
    "sg:tags":[
        "building",
        "apartment"
    ],
    "wof:name":"Crosswood Apartments",
    "wof:placetype":"venue"
},
  "geometry": {"coordinates":[-81.203419,37.85055],"type":"Point"}
}