{
  "type": "Feature",
  "properties": {
    "iso:country":"US",
    "sg:address":"299 Aikens Center",
    "sg:city":"Martinsburg",
    "sg:classifiers":[
        {
            "category":"Health Services",
            "subcategory":"Optometrist",
            "type":"Services"
        }
    ],
    "sg:phone":"+1 304 263 6716",
    "sg:postcode":"25401",
    "sg:province":"WV",
    "wof:name":"Berkeley Optical",
    "wof:placetype":"venue"
},
  "geometry": {"coordinates":[-77.960556,39.486059],"type":"Point"}
}