{
  "type": "Feature",
  "properties": {
    "addr:full":"709 Warwood Ave Warwood WV 26003",
    "addr:housenumber":"709",
    "addr:postcode":"26003",
    "addr:street":"Warwood Ave",
    "iso:country":"US",
    "sg:address":"709 Warwood Ave",
    "sg:city":"Warwood",
    "sg:classifiers":[
        {
            "category":"Personal",
            "subcategory":"Barber",
            "type":"Services"
        }
    ],
    "sg:phone":"+1 304 277 3393",
    "sg:postcode":"26003",
    "sg:province":"WV",
    "wof:name":"Ron's Barber Shop",
    "wof:placetype":"venue"
},
  "geometry": {"coordinates":[-80.698402,40.11015],"type":"Point"}
}