{
  "type": "Feature",
  "properties": {
    "iso:country":"US",
    "sg:address":"434 Pike St",
    "sg:city":"Shinnston",
    "sg:classifiers":[
        {
            "category":"Autos & Motor Vehicles",
            "subcategory":"Auto Supplies",
            "type":"Retail Goods"
        }
    ],
    "sg:phone":"+1 304 592 1203",
    "sg:postcode":"26431",
    "sg:province":"WV",
    "wof:name":"NAPA Auto Parts",
    "wof:placetype":"venue"
},
  "geometry": {"coordinates":[-80.29980999999999,39.396241],"type":"Point"}
}