{
  "type": "Feature",
  "properties": {
    "iso:country":"US",
    "sg:address":"1000 Mississippi St",
    "sg:city":"Morgantown",
    "sg:classifiers":[
        {
            "category":"Education",
            "subcategory":"School",
            "type":"Public Place"
        }
    ],
    "sg:phone":"+1 304 291 9243",
    "sg:postcode":"26501",
    "sg:province":"WV",
    "wof:name":"Monogolia County Adult Educatn",
    "wof:placetype":"venue"
},
  "geometry": {"coordinates":[-79.954989,39.608667],"type":"Point"}
}