{
  "type": "Feature",
  "properties": {
    "iso:country":"US",
    "sg:address":"216 Main St",
    "sg:city":"Parsons",
    "sg:classifiers":[
        {
            "category":"Government",
            "subcategory":"Fire Station",
            "type":"Public Place"
        }
    ],
    "sg:phone":"+1 304 478 3017",
    "sg:postcode":"26287",
    "sg:province":"WV",
    "sg:tags":[
        "protection"
    ],
    "wof:name":"Parsons Volunteer Fire Dept",
    "wof:placetype":"venue"
},
  "geometry": {"coordinates":[-79.682166,39.097952],"type":"Point"}
}