{
  "type": "Feature",
  "properties": {
    "iso:country":"US",
    "sg:address":"3842 Teays Valley Rd",
    "sg:city":"Hurricane",
    "sg:classifiers":[
        {
            "category":"Retail",
            "subcategory":"Veterinary Services",
            "type":"Services"
        }
    ],
    "sg:phone":"+1 304 757 8781",
    "sg:postcode":"25526",
    "sg:province":"WV",
    "sg:tags":[
        "veterinarian"
    ],
    "wof:name":"Godfrey's Animal Clinic",
    "wof:placetype":"venue"
},
  "geometry": {"coordinates":[-81.941639,38.448433],"type":"Point"}
}