{
  "type": "Feature",
  "properties": {
    "iso:country":"US",
    "sg:address":"1303 Washington St W",
    "sg:city":"Charleston",
    "sg:classifiers":[
        {
            "category":"Manufacturing",
            "subcategory":"Printing",
            "type":"Manufacturing & Wholesale Goods"
        }
    ],
    "sg:phone":"+1 304 346 1869",
    "sg:postcode":"25302",
    "sg:province":"WV",
    "sg:tags":[
        "printer"
    ],
    "wof:name":"Riffe Printing Co",
    "wof:placetype":"venue"
},
  "geometry": {"coordinates":[-81.657741,38.370227],"type":"Point"}
}