{
  "type": "Feature",
  "properties": {
    "addr:full":"243 Three Springs Dr Weirton WV 26062",
    "addr:housenumber":"243",
    "addr:postcode":"26062",
    "addr:street":"Three Springs Dr",
    "iso:country":"US",
    "sg:address":"243 Three Springs Dr",
    "sg:city":"Weirton",
    "sg:classifiers":[
        {
            "category":"Professional",
            "subcategory":"Accounting & Tax Preparation",
            "type":"Services"
        }
    ],
    "sg:phone":"+1 304 723 6076",
    "sg:postcode":"26062",
    "sg:province":"WV",
    "sg:tags":[
        "return",
        "filing"
    ],
    "wof:name":"H & R Block Tax Svc",
    "wof:placetype":"venue"
},
  "geometry": {"coordinates":[-80.549989,40.405801],"type":"Point"}
}