{
  "type": "Feature",
  "properties": {
    "iso:country":"US",
    "sg:address":"2640 Pleasant Ave",
    "sg:city":"Wellsburg",
    "sg:classifiers":[
        {
            "category":"Organizations",
            "subcategory":"Religious Organization",
            "type":"Services"
        }
    ],
    "sg:phone":"+1 304 737 0424",
    "sg:postcode":"26070",
    "sg:province":"WV",
    "wof:name":"Christian Faith Assembly God",
    "wof:placetype":"venue"
},
  "geometry": {"coordinates":[-80.606925,40.288672],"type":"Point"}
}