{
  "type": "Feature",
  "properties": {
    "iso:country":"US",
    "sg:address":"2790 Centralia Rd",
    "sg:city":"Sutton",
    "sg:classifiers":[
        {
            "category":"Mining & Drilling",
            "type":"Manufacturing & Wholesale Goods"
        }
    ],
    "sg:phone":"+1 304 765 5288",
    "sg:postcode":"26601",
    "sg:province":"WV",
    "sg:tags":[
        "reclamation",
        "mine"
    ],
    "wof:name":"Mc Court & Son Construction",
    "wof:placetype":"venue"
},
  "geometry": {"coordinates":[-80.62418099999999,38.6103],"type":"Point"}
}