{
  "type": "Feature",
  "properties": {
    "addr:full":"1306 Crim Ave Belington WV 26250",
    "addr:housenumber":"1306",
    "addr:postcode":"26250",
    "addr:street":"Crim Ave",
    "iso:country":"US",
    "sg:address":"1306 Crim Ave",
    "sg:city":"Belington",
    "sg:classifiers":[
        {
            "category":"Shopping",
            "subcategory":"Computers & Home Electronics",
            "type":"Retail Goods"
        }
    ],
    "sg:phone":"+1 304 823 1685",
    "sg:postcode":"26250",
    "sg:province":"WV",
    "sg:tags":[
        "equipment",
        "electronic",
        "supply"
    ],
    "wof:name":"Signals Electronics",
    "wof:placetype":"venue"
},
  "geometry": {"coordinates":[-79.93879099999999,39.01309],"type":"Point"}
}