{
  "type": "Feature",
  "properties": {
    "iso:country":"US",
    "sg:address":"1117 University Ave",
    "sg:city":"Morgantown",
    "sg:classifiers":[
        {
            "category":"Travel",
            "subcategory":"Travel Agent",
            "type":"Entertainment"
        }
    ],
    "sg:phone":"+1 304 292 8471",
    "sg:postcode":"26505",
    "sg:province":"WV",
    "sg:tags":[
        "agency",
        "bureau"
    ],
    "wof:name":"Morgantown Travel Svc",
    "wof:placetype":"venue"
},
  "geometry": {"coordinates":[-79.95882,39.629339],"type":"Point"}
}