{
  "type": "Feature",
  "properties": {
    "iso:country":"US",
    "sg:address":"105 Murry Rd",
    "sg:city":"Morgantown",
    "sg:classifiers":[
        {
            "category":"Building & Trades",
            "subcategory":"Construction",
            "type":"Services"
        }
    ],
    "sg:phone":"+1 304 292 5254",
    "sg:postcode":"26508",
    "sg:province":"WV",
    "sg:tags":[
        "concrete",
        "contractor"
    ],
    "wof:name":"David W Dalton",
    "wof:placetype":"venue"
},
  "geometry": {"coordinates":[-79.885093,39.566546],"type":"Point"}
}