{
  "type": "Feature",
  "properties": {
    "iso:country":"US",
    "sg:address":"496 W Main St",
    "sg:city":"Romney",
    "sg:classifiers":[
        {
            "category":"Home & Garden",
            "subcategory":"Building Materials",
            "type":"Retail Goods"
        }
    ],
    "sg:phone":"+1 304 822 3576",
    "sg:postcode":"26757",
    "sg:province":"WV",
    "sg:tags":[
        "lumber"
    ],
    "wof:name":"Eastern Building Supply Inc",
    "wof:placetype":"venue"
},
  "geometry": {"coordinates":[-78.76293699999999,39.342527],"type":"Point"}
}