{
  "type": "Feature",
  "properties": {
    "iso:country":"US",
    "sg:address":"226 E B Saunders Way",
    "sg:city":"Clarksburg",
    "sg:classifiers":[
        {
            "category":"Wholesale",
            "subcategory":"Hardware",
            "type":"Manufacturing & Wholesale Goods"
        }
    ],
    "sg:phone":"+1 304 624 5546",
    "sg:postcode":"26301",
    "sg:province":"WV",
    "sg:tags":[
        "plumbing",
        "fixture",
        "supply"
    ],
    "wof:name":"Hajoca Corp",
    "wof:placetype":"venue"
},
  "geometry": {"coordinates":[-80.335646,39.27177],"type":"Point"}
}