{
  "type": "Feature",
  "properties": {
    "iso:country":"US",
    "sg:address":"540 10th St",
    "sg:city":"Huntington",
    "sg:classifiers":[
        {
            "category":"Professional",
            "subcategory":"Accounting & Tax Preparation",
            "type":"Services"
        }
    ],
    "sg:phone":"+1 304 523 9337",
    "sg:postcode":"25701",
    "sg:province":"WV",
    "sg:tags":[
        "billing"
    ],
    "wof:name":"Med Corp Inc",
    "wof:placetype":"venue"
},
  "geometry": {"coordinates":[-82.441703,38.419578],"type":"Point"}
}