{
  "type": "Feature",
  "properties": {
    "addr:full":"3007 Webster Rd Summersville WV 26651",
    "addr:housenumber":"3007",
    "addr:postcode":"26651",
    "addr:street":"Webster Rd",
    "iso:country":"US",
    "sg:address":"3007 Webster Rd",
    "sg:city":"Summersville",
    "sg:classifiers":[
        {
            "category":"Home & Garden",
            "subcategory":"Furniture",
            "type":"Retail Goods"
        }
    ],
    "sg:phone":"+1 304 872 4550",
    "sg:postcode":"26651",
    "sg:province":"WV",
    "sg:tags":[
        "mattress"
    ],
    "wof:name":"Mattress Mart Furn Gallery LLC",
    "wof:placetype":"venue"
},
  "geometry": {"coordinates":[-80.837543,38.291769],"type":"Point"}
}