{
  "type": "Feature",
  "properties": {
    "iso:country":"US",
    "sg:address":"122 Windsor Ct",
    "sg:city":"Fayetteville",
    "sg:classifiers":[
        {
            "category":"Shopping",
            "type":"Retail Goods"
        }
    ],
    "sg:phone":"+1 304 574 0430",
    "sg:postcode":"25832",
    "sg:province":"WV",
    "sg:tags":[
        "cosmetic",
        "perfume"
    ],
    "wof:name":"Beauti Control Cosmetics Inc",
    "wof:placetype":"venue"
},
  "geometry": {"coordinates":[-81.132822,37.736964],"type":"Point"}
}