{
  "type": "Feature",
  "properties": {
    "iso:country":"US",
    "sg:address":"614 D St",
    "sg:city":"South Charleston",
    "sg:classifiers":[
        {
            "category":"Professional",
            "subcategory":"Computer Services",
            "type":"Services"
        }
    ],
    "sg:phone":"+1 304 746 4401",
    "sg:postcode":"25303",
    "sg:province":"WV",
    "sg:tags":[
        "consultant",
        "designer"
    ],
    "sg:website":"www.attgwv.com",
    "wof:name":"Applied Technology & Training",
    "wof:placetype":"venue"
},
  "geometry": {"coordinates":[-81.69638500000001,38.368521],"type":"Point"}
}