{
  "type": "Feature",
  "properties": {
    "iso:country":"US",
    "sg:address":"1250 State Rte 2",
    "sg:city":"New Martinsville",
    "sg:classifiers":[
        {
            "category":"Real Estate",
            "subcategory":"Real Estate Operator",
            "type":"Services"
        }
    ],
    "sg:phone":"+1 304 455 5967",
    "sg:postcode":"26155",
    "sg:province":"WV",
    "sg:tags":[
        "apartment"
    ],
    "wof:name":"Club Apartments",
    "wof:placetype":"venue"
},
  "geometry": {"coordinates":[-80.855035,39.690265],"type":"Point"}
}