{
  "type": "Feature",
  "properties": {
    "iso:country":"US",
    "sg:address":"2012 Pleasant Valley Rd",
    "sg:city":"Fairmont",
    "sg:classifiers":[
        {
            "category":"Health Services",
            "subcategory":"Doctor",
            "type":"Services"
        }
    ],
    "sg:phone":"+1 304 368 0342",
    "sg:postcode":"26554",
    "sg:province":"WV",
    "sg:tags":[
        "dentist"
    ],
    "wof:name":"Linda Ray DDS",
    "wof:placetype":"venue"
},
  "geometry": {"coordinates":[-80.167593,39.442318],"type":"Point"}
}