{
  "type": "Feature",
  "properties": {
    "iso:country":"US",
    "sg:address":"1706 Main St E",
    "sg:city":"Oak Hill",
    "sg:classifiers":[
        {
            "category":"Utilities",
            "subcategory":"Refuse",
            "type":"Services"
        }
    ],
    "sg:phone":"+1 304 465 8500",
    "sg:postcode":"25901",
    "sg:province":"WV",
    "sg:tags":[
        "system"
    ],
    "wof:name":"Basham Metal Company",
    "wof:placetype":"venue"
},
  "geometry": {"coordinates":[-81.13207199999999,37.99483],"type":"Point"}
}