{
  "type": "Feature",
  "properties": {
    "iso:country":"US",
    "sg:address":"1615 19th St",
    "sg:city":"Parkersburg",
    "sg:classifiers":[
        {
            "category":"Building & Trades",
            "subcategory":"Electrical",
            "type":"Services"
        }
    ],
    "sg:phone":"+1 304 422 5200",
    "sg:postcode":"26101",
    "sg:province":"WV",
    "sg:tags":[
        "electric",
        "contractor"
    ],
    "wof:name":"Valley Electric Svc",
    "wof:placetype":"venue"
},
  "geometry": {"coordinates":[-81.538113,39.273165],"type":"Point"}
}