{
  "type": "Feature",
  "properties": {
    "iso:country":"US",
    "sg:address":"106 N George St",
    "sg:city":"Charles Town",
    "sg:classifiers":[
        {
            "category":"Building & Trades",
            "subcategory":"Construction",
            "type":"Services"
        }
    ],
    "sg:phone":"+1 304 724 7018",
    "sg:postcode":"25414",
    "sg:province":"WV",
    "sg:tags":[
        "general",
        "contractor"
    ],
    "wof:name":"James R Weddle/Trim Carpentry",
    "wof:placetype":"venue"
},
  "geometry": {"coordinates":[-77.860429,39.289803],"type":"Point"}
}