{
  "type": "Feature",
  "properties": {
    "iso:country":"US",
    "sg:address":"4707 Ohio St",
    "sg:city":"Charleston",
    "sg:classifiers":[
        {
            "category":"Organizations",
            "subcategory":"Religious Organization",
            "type":"Services"
        }
    ],
    "sg:phone":"+1 304 768 6932",
    "sg:postcode":"25309",
    "sg:province":"WV",
    "sg:tags":[
        "church"
    ],
    "wof:name":"Spring Hill Baptist Church",
    "wof:placetype":"venue"
},
  "geometry": {"coordinates":[-81.728199,38.353749],"type":"Point"}
}