{
  "type": "Feature",
  "properties": {
    "iso:country":"US",
    "sg:address":"1210 Kanawha Blvd E",
    "sg:city":"Charleston",
    "sg:classifiers":[
        {
            "category":"Real Estate",
            "subcategory":"Real Estate Agent",
            "type":"Services"
        }
    ],
    "sg:phone":"+1 304 344 2581",
    "sg:postcode":"25301",
    "sg:province":"WV",
    "wof:name":"Old Colony Co Realtors",
    "wof:placetype":"venue"
},
  "geometry": {"coordinates":[-81.63224,38.344246],"type":"Point"}
}