{
  "type": "Feature",
  "properties": {
    "iso:country":"US",
    "sg:address":"514 Market St",
    "sg:city":"Parkersburg",
    "sg:classifiers":[
        {
            "category":"Government",
            "subcategory":"Office",
            "type":"Public Place"
        }
    ],
    "sg:phone":"+1 304 428 8056",
    "sg:postcode":"26101",
    "sg:province":"WV",
    "sg:tags":[
        "federal",
        "program",
        "adm"
    ],
    "wof:name":"US Census Bureau",
    "wof:placetype":"venue"
},
  "geometry": {"coordinates":[-81.55939600000001,39.266232],"type":"Point"}
}