{
  "type": "Feature",
  "properties": {
    "iso:country":"US",
    "sg:address":"286 Railroad St",
    "sg:city":"Gauley Bridge",
    "sg:classifiers":[
        {
            "category":"Education",
            "subcategory":"Library",
            "type":"Public Place"
        }
    ],
    "sg:phone":"+1 304 632 2172",
    "sg:postcode":"25085",
    "sg:province":"WV",
    "wof:name":"Gauley Bridge Public Library",
    "wof:placetype":"venue"
},
  "geometry": {"coordinates":[-81.196657,38.164674],"type":"Point"}
}