{
  "type": "Feature",
  "properties": {
    "addr:full":"135 Maple Ave Fairmont WV 26554",
    "addr:housenumber":"135",
    "addr:postcode":"26554",
    "addr:street":"Maple Ave",
    "iso:country":"US",
    "sg:address":"135 Maple Ave",
    "sg:city":"Fairmont",
    "sg:classifiers":[
        {
            "category":"Organizations",
            "subcategory":"Religious Organization",
            "type":"Services"
        }
    ],
    "sg:phone":"+1 304 363 0669",
    "sg:postcode":"26554",
    "sg:province":"WV",
    "sg:tags":[
        "church"
    ],
    "wof:name":"Mt Zion Baptist Church",
    "wof:placetype":"venue"
},
  "geometry": {"coordinates":[-80.140463,39.488348],"type":"Point"}
}