{
  "type": "Feature",
  "properties": {
    "addr:full":"230 Market Dr Charleston WV 25302",
    "addr:housenumber":"230",
    "addr:postcode":"25302",
    "addr:street":"Market Dr",
    "iso:country":"US",
    "sg:address":"230 Market Dr",
    "sg:city":"Charleston",
    "sg:classifiers":[
        {
            "category":"Shopping",
            "subcategory":"Discount & Variety Stores",
            "type":"Retail Goods"
        }
    ],
    "sg:phone":"+1 304 776 1141",
    "sg:postcode":"25302",
    "sg:province":"WV",
    "sg:tags":[
        "merchandise",
        "general"
    ],
    "wof:name":"Dollar Tree",
    "wof:placetype":"venue"
},
  "geometry": {"coordinates":[-81.63114299999999,38.360826],"type":"Point"}
}