{
  "type": "Feature",
  "properties": {
    "iso:country":"US",
    "sg:address":"509 28th St",
    "sg:city":"Vienna",
    "sg:classifiers":[
        {
            "category":"Manufacturing",
            "subcategory":"Printing",
            "type":"Manufacturing & Wholesale Goods"
        }
    ],
    "sg:phone":"+1 304 295 9400",
    "sg:postcode":"26105",
    "sg:province":"WV",
    "sg:tags":[
        "screen"
    ],
    "wof:name":"Absolute Art & Design Inc",
    "wof:placetype":"venue"
},
  "geometry": {"coordinates":[-81.549475,39.324205],"type":"Point"}
}