{
  "type": "Feature",
  "properties": {
    "addr:full":"18 White Tail Dr Berkeley Springs WV 25421",
    "addr:housenumber":"18",
    "addr:postcode":"25421",
    "addr:street":"White Tail Dr",
    "iso:country":"US",
    "sg:address":"18 White Tail Dr",
    "sg:city":"Berkeley Springs",
    "sg:classifiers":[
        {
            "category":"Professional",
            "subcategory":"Engineering",
            "type":"Services"
        }
    ],
    "sg:phone":"+1 304 258 4545",
    "sg:postcode":"25421",
    "sg:province":"WV",
    "sg:tags":[
        "engineer"
    ],
    "wof:name":"Colab Scientific",
    "wof:placetype":"venue"
},
  "geometry": {"coordinates":[-78.154689,39.354334],"type":"Point"}
}