{
  "type": "Feature",
  "properties": {
    "iso:country":"US",
    "sg:address":"223 George St",
    "sg:city":"Beckley",
    "sg:classifiers":[
        {
            "category":"Professional",
            "subcategory":"Engineering",
            "type":"Services"
        }
    ],
    "sg:phone":"+1 304 252 5872",
    "sg:postcode":"25801",
    "sg:province":"WV",
    "sg:tags":[
        "engineer"
    ],
    "wof:name":"Jones & Jordan Engineering Inc",
    "wof:placetype":"venue"
},
  "geometry": {"coordinates":[-81.223583,37.79125],"type":"Point"}
}