{
  "type": "Feature",
  "properties": {
    "iso:country":"US",
    "sg:address":"680 Beverly Pike",
    "sg:city":"Elkins",
    "sg:classifiers":[
        {
            "category":"Retail",
            "subcategory":"Auto Repair",
            "type":"Services"
        }
    ],
    "sg:phone":"+1 304 636 7557",
    "sg:postcode":"26250",
    "sg:province":"WV",
    "sg:tags":[
        "automotive"
    ],
    "wof:name":"5 Lane Quick Lube",
    "wof:placetype":"venue"
},
  "geometry": {"coordinates":[-79.933249,39.021314],"type":"Point"}
}