{
  "type": "Feature",
  "properties": {
    "addr:full":"13 Diana Dr Fairmont WV 26554",
    "addr:housenumber":"13",
    "addr:postcode":"26554",
    "addr:street":"Diana Dr",
    "iso:country":"US",
    "sg:address":"13 Diana Dr",
    "sg:city":"Fairmont",
    "sg:classifiers":[
        {
            "category":"Insurance",
            "subcategory":"Insurance Agent",
            "type":"Services"
        }
    ],
    "sg:phone":"+1 304 366 4486",
    "sg:postcode":"26554",
    "sg:province":"WV",
    "wof:name":"Horace Mann Insurance Co",
    "wof:placetype":"venue"
},
  "geometry": {"coordinates":[-80.189165,39.474678],"type":"Point"}
}