{
  "type": "Feature",
  "properties": {
    "addr:full":"1200 Harper Rd Beckley WV 25801",
    "addr:housenumber":"1200",
    "addr:postcode":"25801",
    "addr:street":"Harper Rd",
    "iso:country":"US",
    "sg:address":"1200 Harper Rd",
    "sg:city":"Beckley",
    "sg:classifiers":[
        {
            "category":"Retail",
            "subcategory":"Funeral Services",
            "type":"Services"
        }
    ],
    "sg:phone":"+1 304 253 8100",
    "sg:postcode":"25801",
    "sg:province":"WV",
    "sg:tags":[
        "home"
    ],
    "wof:name":"Melton Mortuary Inc",
    "wof:placetype":"venue"
},
  "geometry": {"coordinates":[-81.202231,37.778836],"type":"Point"}
}