{
  "type": "Feature",
  "properties": {
    "addr:full":"209 Cedar Lakes Dr Ripley WV 25271",
    "addr:housenumber":"209",
    "addr:postcode":"25271",
    "addr:street":"Cedar Lakes Dr",
    "iso:country":"US",
    "sg:address":"209 Cedar Lakes Dr",
    "sg:city":"Ripley",
    "sg:classifiers":[
        {
            "category":"Organizations",
            "subcategory":"Religious Organization",
            "type":"Services"
        }
    ],
    "sg:phone":"+1 304 372 5348",
    "sg:postcode":"25271",
    "sg:province":"WV",
    "wof:name":"Church Of The Nazarene",
    "wof:placetype":"venue"
},
  "geometry": {"coordinates":[-81.698616,38.807898],"type":"Point"}
}