{
  "type": "Feature",
  "properties": {
    "addr:full":"500 4th St St Albans WV 25177",
    "addr:housenumber":"500",
    "addr:postcode":"25177",
    "addr:street":"4Th St",
    "iso:country":"US",
    "sg:address":"500 4th St",
    "sg:city":"St Albans",
    "sg:classifiers":[
        {
            "category":"Organizations",
            "subcategory":"Non-profit Organization",
            "type":"Services"
        },
        {
            "category":"Social Services",
            "type":"Services"
        }
    ],
    "sg:phone":"+1 304 722 2019",
    "sg:postcode":"25177",
    "sg:province":"WV",
    "sg:tags":[
        "alternative",
        "abortion"
    ],
    "wof:name":"Birthright of St Albans",
    "wof:placetype":"venue"
},
  "geometry": {"coordinates":[-81.83362,38.386348],"type":"Point"}
}