{
  "type": "Feature",
  "properties": {
    "iso:country":"US",
    "sg:address":"1010 Irwin St",
    "sg:city":"Morgantown",
    "sg:classifiers":[
        {
            "category":"Real Estate",
            "subcategory":"Developer",
            "type":"Services"
        },
        {
            "category":"Real Estate",
            "subcategory":"Real Estate Operator",
            "type":"Services"
        }
    ],
    "sg:phone":"+1 304 599 4959",
    "sg:postcode":"26505",
    "sg:province":"WV",
    "sg:tags":[
        "apartment",
        "subdivider"
    ],
    "wof:name":"Copperfield Court Apartments",
    "wof:placetype":"venue"
},
  "geometry": {"coordinates":[-79.952859,39.652334],"type":"Point"}
}