{
  "type": "Feature",
  "properties": {
    "iso:country":"US",
    "sg:address":"1306 Terrace St",
    "sg:city":"Hinton",
    "sg:classifiers":[
        {
            "category":"Health Services",
            "subcategory":"Doctor",
            "type":"Services"
        }
    ],
    "sg:phone":"+1 304 466 9202",
    "sg:postcode":"25951",
    "sg:province":"WV",
    "sg:tags":[
        "clinic"
    ],
    "wof:name":"Avis Community Clinic",
    "wof:placetype":"venue"
},
  "geometry": {"coordinates":[-80.859078,37.650739],"type":"Point"}
}