{
  "type": "Feature",
  "properties": {
    "iso:country":"US",
    "sg:address":"715 Charles St",
    "sg:city":"Wellsburg",
    "sg:classifiers":[
        {
            "category":"Restaurant",
            "type":"Food & Drink"
        }
    ],
    "sg:phone":"+1 304 737 1900",
    "sg:postcode":"26070",
    "sg:province":"WV",
    "wof:name":"Our Hero's Hometown Restaurant",
    "wof:placetype":"venue"
},
  "geometry": {"coordinates":[-80.61265,40.270154],"type":"Point"}
}