{
  "type": "Feature",
  "properties": {
    "addr:full":"1698 Quarrier St E Charleston WV 25311",
    "addr:housenumber":"1698",
    "addr:postcode":"25311",
    "addr:street":"Quarrier St E",
    "iso:country":"US",
    "sg:address":"1698 Quarrier St E",
    "sg:city":"Charleston",
    "sg:classifiers":[
        {
            "category":"Organizations",
            "subcategory":"Religious Organization",
            "type":"Services"
        }
    ],
    "sg:phone":"+1 304 342 0845",
    "sg:postcode":"25311",
    "sg:province":"WV",
    "sg:tags":[
        "church"
    ],
    "wof:name":"Ruffner Memorial Presbt Church",
    "wof:placetype":"venue"
},
  "geometry": {"coordinates":[-81.61696999999999,38.339104],"type":"Point"}
}