{
  "type": "Feature",
  "properties": {
    "addr:full":"3909 Emerson Ave Parkersburg WV 26104",
    "addr:housenumber":"3909",
    "addr:postcode":"26104",
    "addr:street":"Emerson Ave",
    "iso:country":"US",
    "sg:address":"3909 Emerson Ave",
    "sg:city":"Parkersburg",
    "sg:classifiers":[
        {
            "category":"Shopping",
            "type":"Retail Goods"
        }
    ],
    "sg:phone":"+1 304 422 2251",
    "sg:postcode":"26104",
    "sg:province":"WV",
    "sg:tags":[
        "cosmetic",
        "perfume"
    ],
    "wof:name":"Avon Products",
    "wof:placetype":"venue"
},
  "geometry": {"coordinates":[-81.52998599999999,39.289721],"type":"Point"}
}