{
  "type": "Feature",
  "properties": {
    "iso:country":"US",
    "sg:address":"1500 7th St",
    "sg:city":"Parkersburg",
    "sg:classifiers":[
        {
            "category":"Autos & Motor Vehicles",
            "subcategory":"Automobile Sales",
            "type":"Retail Goods"
        }
    ],
    "sg:phone":"+1 304 485 6401",
    "sg:postcode":"26101",
    "sg:province":"WV",
    "sg:tags":[
        "car",
        "dealer"
    ],
    "wof:name":"Dils Motorcars",
    "wof:placetype":"venue"
},
  "geometry": {"coordinates":[-81.53474300000001,39.266307],"type":"Point"}
}