{
  "type": "Feature",
  "properties": {
    "iso:country":"US",
    "sg:address":"167 Meadow St",
    "sg:city":"Mt Hope",
    "sg:classifiers":[
        {
            "category":"Retail",
            "subcategory":"Auto Repair",
            "type":"Services"
        }
    ],
    "sg:phone":"+1 304 877 3773",
    "sg:postcode":"25880",
    "sg:province":"WV",
    "sg:tags":[
        "truck"
    ],
    "wof:name":"Reliable Truck & Equip Repair",
    "wof:placetype":"venue"
},
  "geometry": {"coordinates":[-81.231588,37.875315],"type":"Point"}
}