{
  "type": "Feature",
  "properties": {
    "iso:country":"US",
    "sg:address":"3728 Teays Valley Rd",
    "sg:city":"Hurricane",
    "sg:classifiers":[
        {
            "category":"Personal",
            "subcategory":"Beauty Salon",
            "type":"Services"
        }
    ],
    "sg:phone":"+1 304 757 7550",
    "sg:postcode":"25526",
    "sg:province":"WV",
    "sg:tags":[
        "shop"
    ],
    "wof:name":"Karey's Hair Salon",
    "wof:placetype":"venue"
},
  "geometry": {"coordinates":[-81.965918,38.446108],"type":"Point"}
}