{
  "type": "Feature",
  "properties": {
    "addr:full":"2060 National Rd Wheeling WV 26003",
    "addr:housenumber":"2060",
    "addr:postcode":"26003",
    "addr:street":"National Rd",
    "iso:country":"US",
    "sg:address":"2060 National Rd",
    "sg:city":"Wheeling",
    "sg:classifiers":[
        {
            "category":"Autos & Motor Vehicles",
            "subcategory":"Fuel & Gas Station",
            "type":"Retail Goods"
        }
    ],
    "sg:phone":"+1 304 242 8500",
    "sg:postcode":"26003",
    "sg:province":"WV",
    "sg:tags":[
        "oil"
    ],
    "wof:name":"Elm Grove Exxon",
    "wof:placetype":"venue"
},
  "geometry": {"coordinates":[-80.663685,40.048697],"type":"Point"}
}