{
  "type": "Feature",
  "properties": {
    "addr:full":"204 Howard Ave Mullens WV 25882",
    "addr:housenumber":"204",
    "addr:postcode":"25882",
    "addr:street":"Howard Ave",
    "iso:country":"US",
    "sg:address":"204 Howard Ave",
    "sg:city":"Mullens",
    "sg:classifiers":[
        {
            "category":"Health Services",
            "subcategory":"Health Practitioner",
            "type":"Services"
        }
    ],
    "sg:phone":"+1 304 294 5150",
    "sg:postcode":"25882",
    "sg:province":"WV",
    "sg:tags":[
        "psychologist"
    ],
    "wof:name":"Assessments Inc",
    "wof:placetype":"venue"
},
  "geometry": {"coordinates":[-81.381345,37.583534],"type":"Point"}
}