{
  "type": "Feature",
  "properties": {
    "iso:country":"US",
    "sg:address":"515 Market St",
    "sg:city":"Parkersburg",
    "sg:classifiers":[
        {
            "category":"Professional",
            "subcategory":"Lawyer & Legal Services",
            "type":"Services"
        }
    ],
    "sg:phone":"+1 304 485 0990",
    "sg:postcode":"26101",
    "sg:province":"WV",
    "sg:tags":[
        "attorney"
    ],
    "wof:name":"Cosenza Merriman & Wolf",
    "wof:placetype":"venue"
},
  "geometry": {"coordinates":[-81.5598,39.266138],"type":"Point"}
}