{
  "type": "Feature",
  "properties": {
    "iso:country":"US",
    "sg:address":"231 Straight St",
    "sg:city":"Ripley",
    "sg:classifiers":[
        {
            "category":"Home & Garden",
            "subcategory":"Building Materials",
            "type":"Retail Goods"
        }
    ],
    "sg:phone":"+1 304 372 6621",
    "sg:postcode":"25271",
    "sg:province":"WV",
    "sg:tags":[
        "lumber"
    ],
    "wof:name":"J Co Lumber Inc",
    "wof:placetype":"venue"
},
  "geometry": {"coordinates":[-81.716446,38.8222],"type":"Point"}
}