{
  "type": "Feature",
  "properties": {
    "addr:full":"116 E 3rd Ave Ranson WV 25438",
    "addr:housenumber":"116",
    "addr:postcode":"25438",
    "addr:street":"E 3Rd Ave",
    "iso:country":"US",
    "sg:address":"116 E 3rd Ave",
    "sg:city":"Ranson",
    "sg:classifiers":[
        {
            "category":"Health Services",
            "subcategory":"Doctor",
            "type":"Services"
        }
    ],
    "sg:phone":"+1 304 725 0431",
    "sg:postcode":"25438",
    "sg:province":"WV",
    "sg:tags":[
        "physician",
        "surgeon"
    ],
    "wof:name":"Shenandoah Eye Ctr",
    "wof:placetype":"venue"
},
  "geometry": {"coordinates":[-77.85958100000001,39.294436],"type":"Point"}
}