{
  "type": "Feature",
  "properties": {
    "iso:country":"US",
    "sg:address":"101 National Rd",
    "sg:city":"Wheeling",
    "sg:classifiers":[
        {
            "category":"Shopping",
            "subcategory":"Jewelry",
            "type":"Retail Goods"
        }
    ],
    "sg:phone":"+1 304 232 3488",
    "sg:postcode":"26003",
    "sg:province":"WV",
    "sg:tags":[
        "jeweler"
    ],
    "sg:website":"www.antiquitus.com",
    "wof:name":"Antiquities",
    "wof:placetype":"venue"
},
  "geometry": {"coordinates":[-80.720817,40.081075],"type":"Point"}
}