{
  "type": "Feature",
  "properties": {
    "iso:country":"US",
    "sg:address":"262 Mount Tabor Rd",
    "sg:city":"Beckley",
    "sg:classifiers":[
        {
            "category":"Organizations",
            "subcategory":"Religious Organization",
            "type":"Services"
        },
        {
            "category":"Education",
            "subcategory":"School",
            "type":"Public Place"
        }
    ],
    "sg:phone":"+1 304 252 9739",
    "sg:postcode":"25801",
    "sg:province":"WV",
    "sg:tags":[
        "academic",
        "special"
    ],
    "wof:name":"Mount Tabor Christian School",
    "wof:placetype":"venue"
},
  "geometry": {"coordinates":[-81.23139999999999,37.794008],"type":"Point"}
}