{
  "type": "Feature",
  "properties": {
    "addr:full":"407 Main St Point Pleasant WV 25550",
    "addr:housenumber":"407",
    "addr:postcode":"25550",
    "addr:street":"Main St",
    "iso:country":"US",
    "sg:address":"407 Main St",
    "sg:city":"Point Pleasant",
    "sg:classifiers":[
        {
            "category":"Real Estate",
            "subcategory":"Real Estate Operator",
            "type":"Services"
        }
    ],
    "sg:phone":"+1 304 675 5928",
    "sg:postcode":"25550",
    "sg:province":"WV",
    "sg:tags":[
        "mall",
        "shopping",
        "center"
    ],
    "wof:name":"Woodyards Mini Mall 3",
    "wof:placetype":"venue"
},
  "geometry": {"coordinates":[-82.13878099999999,38.842583],"type":"Point"}
}