{
  "type": "Feature",
  "properties": {
    "addr:full":"115 Spring St Charleston WV 25302",
    "addr:housenumber":"115",
    "addr:postcode":"25302",
    "addr:street":"Spring St",
    "iso:country":"US",
    "sg:address":"115 Spring St",
    "sg:city":"Charleston",
    "sg:classifiers":[
        {
            "category":"Social Services",
            "subcategory":"Job Training",
            "type":"Services"
        }
    ],
    "sg:phone":"+1 304 343 8259",
    "sg:postcode":"25302",
    "sg:province":"WV",
    "sg:tags":[
        "apprenticeship",
        "program"
    ],
    "wof:name":"Joint Painting & Decorating",
    "wof:placetype":"venue"
},
  "geometry": {"coordinates":[-81.62747899999999,38.360428],"type":"Point"}
}