{
  "type": "Feature",
  "properties": {
    "addr:full":"3209 6th Ave Parkersburg WV 26101",
    "addr:housenumber":"3209",
    "addr:postcode":"26101",
    "addr:street":"6Th Ave",
    "iso:country":"US",
    "sg:address":"3209 6th Ave",
    "sg:city":"Parkersburg",
    "sg:classifiers":[
        {
            "category":"Social Services",
            "subcategory":"Child Care",
            "type":"Services"
        }
    ],
    "sg:phone":"+1 304 422 3085",
    "sg:postcode":"26101",
    "sg:province":"WV",
    "sg:tags":[
        "day"
    ],
    "wof:name":"Lovingkindness Child Care Ctr",
    "wof:placetype":"venue"
},
  "geometry": {"coordinates":[-81.539542,39.25094],"type":"Point"}
}