{
  "type": "Feature",
  "properties": {
    "iso:country":"US",
    "sg:address":"496 National Rd",
    "sg:city":"Wheeling",
    "sg:classifiers":[
        {
            "category":"Insurance",
            "subcategory":"Insurance Agent",
            "type":"Services"
        }
    ],
    "sg:phone":"+1 304 232 5800",
    "sg:postcode":"26003",
    "sg:province":"WV",
    "sg:tags":[
        "adjuster"
    ],
    "wof:name":"Irvine & Associates Inc",
    "wof:placetype":"venue"
},
  "geometry": {"coordinates":[-80.711207,40.078147],"type":"Point"}
}