{
  "type": "Feature",
  "properties": {
    "iso:country":"US",
    "sg:address":"500 W Main St",
    "sg:city":"Clarksburg",
    "sg:classifiers":[
        {
            "category":"Social Services",
            "type":"Services"
        }
    ],
    "sg:phone":"+1 304 623 6795",
    "sg:postcode":"26301",
    "sg:province":"WV",
    "sg:tags":[
        "for",
        "elderly"
    ],
    "wof:name":"Harrison Cnty Snior Ctzens Ctr",
    "wof:placetype":"venue"
},
  "geometry": {"coordinates":[-80.34270100000001,39.28018],"type":"Point"}
}