{
  "type": "Feature",
  "properties": {
    "iso:country":"US",
    "sg:address":"558 Burroughs St",
    "sg:city":"Morgantown",
    "sg:classifiers":[
        {
            "category":"Professional",
            "subcategory":"Business Services",
            "type":"Services"
        }
    ],
    "sg:phone":"+1 304 599 2768",
    "sg:postcode":"26505",
    "sg:province":"WV",
    "wof:name":"Work Wise",
    "wof:placetype":"venue"
},
  "geometry": {"coordinates":[-79.966866,39.657616],"type":"Point"}
}