{
  "type": "Feature",
  "properties": {
    "iso:country":"US",
    "sg:address":"360 Seneca Trl",
    "sg:city":"Ronceverte",
    "sg:classifiers":[
        {
            "category":"Utilities",
            "subcategory":"Fuel Oil & Lpg",
            "type":"Services"
        }
    ],
    "sg:phone":"+1 304 647 5160",
    "sg:postcode":"24970",
    "sg:province":"WV",
    "sg:tags":[
        "product",
        "petroleum",
        "dealer"
    ],
    "wof:name":"Whiting Jamison Oil",
    "wof:placetype":"venue"
},
  "geometry": {"coordinates":[-80.458619,37.777466],"type":"Point"}
}