{
  "type": "Feature",
  "properties": {
    "addr:full":"205 Silo Ln Lewisburg WV 24901",
    "addr:housenumber":"205",
    "addr:postcode":"24901",
    "addr:street":"Silo Ln",
    "iso:country":"US",
    "sg:address":"205 Silo Ln",
    "sg:city":"Lewisburg",
    "sg:classifiers":[
        {
            "category":"Recreation",
            "subcategory":"Arcade",
            "type":"Entertainment"
        }
    ],
    "sg:phone":"+1 304 645 3321",
    "sg:postcode":"24901",
    "sg:province":"WV",
    "sg:tags":[
        "device",
        "operator",
        "amusement"
    ],
    "wof:name":"Cruse Amusements",
    "wof:placetype":"venue"
},
  "geometry": {"coordinates":[-80.436747,37.805555],"type":"Point"}
}