{
  "type": "Feature",
  "properties": {
    "iso:country":"US",
    "sg:address":"4424 Emerson Ave",
    "sg:city":"Parkersburg",
    "sg:classifiers":[
        {
            "category":"Professional",
            "subcategory":"Management & Consulting",
            "type":"Services"
        }
    ],
    "sg:phone":"+1 304 485 6485",
    "sg:postcode":"26104",
    "sg:province":"WV",
    "sg:tags":[
        "consultant",
        "business"
    ],
    "sg:website":"www.gopmca.com",
    "wof:name":"Parkersburg-Marietta Contrs",
    "wof:placetype":"venue"
},
  "geometry": {"coordinates":[-81.524659,39.292697],"type":"Point"}
}