{
  "type": "Feature",
  "properties": {
    "iso:country":"US",
    "sg:address":"203 S Kanawha St",
    "sg:city":"Beckley",
    "sg:classifiers":[
        {
            "category":"Social Services",
            "subcategory":"Child Care",
            "type":"Services"
        }
    ],
    "sg:phone":"+1 304 250 0262",
    "sg:postcode":"25801",
    "sg:province":"WV",
    "sg:tags":[
        "kindergarten",
        "academic",
        "school"
    ],
    "wof:name":"Montessori Childrens House",
    "wof:placetype":"venue"
},
  "geometry": {"coordinates":[-81.187136,37.776824],"type":"Point"}
}