{
  "type": "Feature",
  "properties": {
    "addr:full":"220 W Burke St Martinsburg WV 25401",
    "addr:housenumber":"220",
    "addr:postcode":"25401",
    "addr:street":"W Burke St",
    "iso:country":"US",
    "sg:address":"220 W Burke St",
    "sg:city":"Martinsburg",
    "sg:classifiers":[
        {
            "category":"Social Services",
            "type":"Services"
        }
    ],
    "sg:phone":"+1 304 263 6205",
    "sg:postcode":"25401",
    "sg:province":"WV",
    "sg:tags":[
        "counselor",
        "marriage",
        "family"
    ],
    "wof:name":"Tri County Pastoral Counseling",
    "wof:placetype":"venue"
},
  "geometry": {"coordinates":[-77.965773,39.457982],"type":"Point"}
}