{
  "type": "Feature",
  "properties": {
    "iso:country":"US",
    "sg:address":"104 Highland Ave",
    "sg:city":"Williamstown",
    "sg:classifiers":[
        {
            "category":"Retail",
            "subcategory":"Repair Shop",
            "type":"Services"
        }
    ],
    "sg:phone":"+1 304 375 7509",
    "sg:postcode":"26187",
    "sg:province":"WV",
    "sg:tags":[
        "electrical"
    ],
    "wof:name":"Great American Floor Care Ctr",
    "wof:placetype":"venue"
},
  "geometry": {"coordinates":[-81.448193,39.405477],"type":"Point"}
}