{
  "type": "Feature",
  "properties": {
    "iso:country":"US",
    "sg:address":"1646 Washington Blvd",
    "sg:city":"Huntington",
    "sg:classifiers":[
        {
            "category":"Real Estate",
            "subcategory":"Real Estate Operator",
            "type":"Services"
        }
    ],
    "sg:phone":"+1 304 523 5827",
    "sg:postcode":"25701",
    "sg:province":"WV",
    "sg:tags":[
        "building",
        "apartment"
    ],
    "wof:name":"Vernon R & Phyllis J Bell",
    "wof:placetype":"venue"
},
  "geometry": {"coordinates":[-82.426317,38.404366],"type":"Point"}
}