{
  "type": "Feature",
  "properties": {
    "iso:country":"US",
    "sg:address":"600 6th St",
    "sg:city":"Moundsville",
    "sg:classifiers":[
        {
            "category":"Health Services",
            "subcategory":"Doctor",
            "type":"Services"
        }
    ],
    "sg:phone":"+1 304 845 0908",
    "sg:postcode":"26041",
    "sg:province":"WV",
    "sg:tags":[
        "physician",
        "surgeon"
    ],
    "wof:name":"Anwar Eye Ctr",
    "wof:placetype":"venue"
},
  "geometry": {"coordinates":[-80.746162,39.919364],"type":"Point"}
}