{
  "type": "Feature",
  "properties": {
    "iso:country":"US",
    "sg:address":"3962 Teays Valley Rd",
    "sg:city":"Hurricane",
    "sg:classifiers":[
        {
            "category":"Professional",
            "subcategory":"Lawyer & Legal Services",
            "type":"Services"
        }
    ],
    "sg:phone":"+1 304 757 7932",
    "sg:postcode":"25526",
    "sg:province":"WV",
    "sg:tags":[
        "attorney"
    ],
    "wof:name":"Fields & Boggs Pllc",
    "wof:placetype":"venue"
},
  "geometry": {"coordinates":[-81.940326,38.448583],"type":"Point"}
}