{
  "type": "Feature",
  "properties": {
    "iso:country":"US",
    "sg:address":"181 Main St",
    "sg:city":"Sutton",
    "sg:classifiers":[
        {
            "category":"Professional",
            "subcategory":"Lawyer & Legal Services",
            "type":"Services"
        }
    ],
    "sg:phone":"+1 304 765 2821",
    "sg:postcode":"26601",
    "sg:province":"WV",
    "sg:tags":[
        "attorney"
    ],
    "wof:name":"James W Douglas",
    "wof:placetype":"venue"
},
  "geometry": {"coordinates":[-80.711152,38.665037],"type":"Point"}
}