{
  "type": "Feature",
  "properties": {
    "addr:full":"1512 Grand Central Ave Vienna WV 26105",
    "addr:housenumber":"1512",
    "addr:postcode":"26105",
    "addr:street":"Grand Central Ave",
    "iso:country":"US",
    "sg:address":"1512 Grand Central Ave",
    "sg:city":"Vienna",
    "sg:classifiers":[
        {
            "category":"Shopping",
            "subcategory":"Clothing, Apparel, & Fashions",
            "type":"Retail Goods"
        }
    ],
    "sg:phone":"+1 304 295 5650",
    "sg:postcode":"26105",
    "sg:province":"WV",
    "wof:name":"Applause",
    "wof:placetype":"venue"
},
  "geometry": {"coordinates":[-81.55348499999999,39.314077],"type":"Point"}
}