{
  "type": "Feature",
  "properties": {
    "iso:country":"US",
    "sg:address":"105 Harriet Dr",
    "sg:city":"Dunbar",
    "sg:classifiers":[
        {
            "category":"Professional",
            "subcategory":"Management & Consulting",
            "type":"Services"
        }
    ],
    "sg:phone":"+1 304 768 3448",
    "sg:postcode":"25064",
    "sg:province":"WV",
    "sg:tags":[
        "business"
    ],
    "wof:name":"Patricia Petty",
    "wof:placetype":"venue"
},
  "geometry": {"coordinates":[-81.75270399999999,38.378451],"type":"Point"}
}