{
  "type": "Feature",
  "properties": {
    "addr:full":"156 2nd Ave SW Charleston WV 25303",
    "addr:housenumber":"156",
    "addr:postcode":"25303",
    "addr:street":"2Nd Ave Sw",
    "iso:country":"US",
    "sg:address":"156 2nd Ave SW",
    "sg:city":"Charleston",
    "sg:classifiers":[
        {
            "category":"Freight",
            "type":"Transportation"
        }
    ],
    "sg:phone":"+1 304 744 0430",
    "sg:postcode":"25303",
    "sg:province":"WV",
    "sg:tags":[
        "distance",
        "hauling",
        "long"
    ],
    "wof:name":"Petes Trucking",
    "wof:placetype":"venue"
},
  "geometry": {"coordinates":[-81.696335,38.363108],"type":"Point"}
}