{
  "type": "Feature",
  "properties": {
    "iso:country":"US",
    "sg:address":"724 Indiana Ave",
    "sg:city":"Charleston",
    "sg:classifiers":[
        {
            "category":"Professional",
            "subcategory":"Engineering",
            "type":"Services"
        }
    ],
    "sg:phone":"+1 304 347 0826",
    "sg:postcode":"25302",
    "sg:province":"WV",
    "sg:tags":[
        "engineer"
    ],
    "wof:name":"Morth Engineering Consulting",
    "wof:placetype":"venue"
},
  "geometry": {"coordinates":[-81.639391,38.361313],"type":"Point"}
}