{
  "type": "Feature",
  "properties": {
    "iso:country":"US",
    "sg:address":"142 Main St",
    "sg:city":"Spencer",
    "sg:classifiers":[
        {
            "category":"Shopping",
            "subcategory":"Musical Instruments",
            "type":"Retail Goods"
        }
    ],
    "sg:phone":"+1 304 927 1677",
    "sg:postcode":"25276",
    "sg:province":"WV",
    "wof:name":"H & C Music",
    "wof:placetype":"venue"
},
  "geometry": {"coordinates":[-81.35012399999999,38.80164],"type":"Point"}
}