{
  "type": "Feature",
  "properties": {
    "addr:full":"5 Marjorie Ann Dr Buckhannon WV 26201",
    "addr:housenumber":"5",
    "addr:postcode":"26201",
    "addr:street":"Marjorie Ann Dr",
    "iso:country":"US",
    "sg:address":"5 Marjorie Ann Dr",
    "sg:city":"Buckhannon",
    "sg:classifiers":[
        {
            "category":"Building & Trades",
            "subcategory":"Landscaping Services",
            "type":"Services"
        }
    ],
    "sg:phone":"+1 304 472 5898",
    "sg:postcode":"26201",
    "sg:province":"WV",
    "wof:name":"Quality Tree Service",
    "wof:placetype":"venue"
},
  "geometry": {"coordinates":[-80.294335,38.953078],"type":"Point"}
}