{
  "type": "Feature",
  "properties": {
    "iso:country":"US",
    "sg:address":"4097 Indian Creek Rd",
    "sg:city":"Elkview",
    "sg:classifiers":[
        {
            "category":"Food & Beverages",
            "subcategory":"Groceries & Convenience Stores",
            "type":"Retail Goods"
        }
    ],
    "sg:phone":"+1 304 965 2200",
    "sg:postcode":"25071",
    "sg:province":"WV",
    "sg:tags":[
        "grocer"
    ],
    "wof:name":"B & B Market",
    "wof:placetype":"venue"
},
  "geometry": {"coordinates":[-81.48369700000001,38.40094],"type":"Point"}
}