{
  "type": "Feature",
  "properties": {
    "iso:country":"US",
    "sg:address":"3211 Emerson Ave",
    "sg:city":"Parkersburg",
    "sg:classifiers":[
        {
            "category":"Health Services",
            "subcategory":"Chiropractor",
            "type":"Services"
        }
    ],
    "sg:phone":"+1 304 485 9124",
    "sg:postcode":"26104",
    "sg:province":"WV",
    "wof:name":"Folwell Byron R",
    "wof:placetype":"venue"
},
  "geometry": {"coordinates":[-81.53665100000001,39.286656],"type":"Point"}
}