{
  "type": "Feature",
  "properties": {
    "iso:country":"US",
    "sg:address":"1401 Smith St",
    "sg:city":"Charleston",
    "sg:classifiers":[
        {
            "category":"Wholesale",
            "subcategory":"Construction Materials",
            "type":"Manufacturing & Wholesale Goods"
        }
    ],
    "sg:phone":"+1 304 345 9192",
    "sg:postcode":"25301",
    "sg:province":"WV",
    "sg:tags":[
        "tile"
    ],
    "wof:name":"Casto Tile & Marble",
    "wof:placetype":"venue"
},
  "geometry": {"coordinates":[-81.62083800000001,38.346865],"type":"Point"}
}