{
  "type": "Feature",
  "properties": {
    "iso:country":"US",
    "sg:address":"175 Philpott Ln",
    "sg:city":"Beaver",
    "sg:classifiers":[
        {
            "category":"Professional",
            "type":"Services"
        }
    ],
    "sg:phone":"+1 304 254 9262",
    "sg:postcode":"25813",
    "sg:province":"WV",
    "wof:name":"Beckley Treatment Center Inc",
    "wof:placetype":"venue"
},
  "geometry": {"coordinates":[-81.115296,37.796672],"type":"Point"}
}