{
  "type": "Feature",
  "properties": {
    "iso:country":"US",
    "sg:address":"4778 Big Tyler Rd",
    "sg:city":"Charleston",
    "sg:classifiers":[
        {
            "category":"Personal",
            "subcategory":"Beauty Salon",
            "type":"Services"
        }
    ],
    "sg:phone":"+1 304 776 2019",
    "sg:postcode":"25313",
    "sg:province":"WV",
    "sg:tags":[
        "shop"
    ],
    "wof:name":"DAlvins Beauty Shop",
    "wof:placetype":"venue"
},
  "geometry": {"coordinates":[-81.729671,38.408545],"type":"Point"}
}