{
  "type": "Feature",
  "properties": {
    "iso:country":"US",
    "sg:address":"555 Bluefield Ave",
    "sg:city":"Bluefield",
    "sg:classifiers":[
        {
            "category":"Restaurant",
            "type":"Food & Drink"
        }
    ],
    "sg:menulink":"http://www.allmenus.com/wv/bramwell/188090-mcdonalds/menu/",
    "sg:phone":"+1 304 327 5828",
    "sg:postcode":"24701",
    "sg:province":"WV",
    "sg:tags":[
        "burger",
        "american"
    ],
    "wof:name":"McDonald's",
    "wof:placetype":"venue"
},
  "geometry": {"coordinates":[-81.231622,37.266503],"type":"Point"}
}