{
  "type": "Feature",
  "properties": {
    "iso:country":"US",
    "sg:address":"117 Dye Dr",
    "sg:city":"Beckley",
    "sg:classifiers":[
        {
            "category":"Real Estate",
            "subcategory":"Architect",
            "type":"Services"
        }
    ],
    "sg:phone":"+1 304 252 0400",
    "sg:postcode":"25801",
    "sg:province":"WV",
    "sg:tags":[
        "specification",
        "architectural"
    ],
    "wof:name":"Worley Management Inc",
    "wof:placetype":"venue"
},
  "geometry": {"coordinates":[-81.221119,37.790253],"type":"Point"}
}