{
  "type": "Feature",
  "properties": {
    "addr:full":"301 Morris St Charleston WV 25301",
    "addr:housenumber":"301",
    "addr:postcode":"25301",
    "addr:street":"Morris St",
    "iso:country":"US",
    "sg:address":"301 Morris St",
    "sg:city":"Charleston",
    "sg:classifiers":[
        {
            "category":"Health Services",
            "subcategory":"Health Practitioner",
            "type":"Services"
        }
    ],
    "sg:phone":"+1 304 345 5210",
    "sg:postcode":"25301",
    "sg:province":"WV",
    "sg:tags":[
        "therapist",
        "physical"
    ],
    "wof:name":"Physical Therapy Assoc",
    "wof:placetype":"venue"
},
  "geometry": {"coordinates":[-81.627618,38.345983],"type":"Point"}
}