{
  "type": "Feature",
  "properties": {
    "addr:full":"106 N Jefferson St Lewisburg WV 24901",
    "addr:housenumber":"106",
    "addr:postcode":"24901",
    "addr:street":"N Jefferson St",
    "iso:country":"US",
    "sg:address":"106 N Jefferson St",
    "sg:city":"Lewisburg",
    "sg:classifiers":[
        {
            "category":"Professional",
            "subcategory":"Lawyer & Legal Services",
            "type":"Services"
        }
    ],
    "sg:phone":"+1 304 645 5700",
    "sg:postcode":"24901",
    "sg:province":"WV",
    "sg:tags":[
        "attorney"
    ],
    "wof:name":"Stroebel & Johnson",
    "wof:placetype":"venue"
},
  "geometry": {"coordinates":[-80.444692,37.80237],"type":"Point"}
}