{
  "type": "Feature",
  "properties": {
    "iso:country":"US",
    "sg:address":"25 Mustang Acres",
    "sg:city":"Parkersburg",
    "sg:classifiers":[
        {
            "category":"Real Estate",
            "subcategory":"Real Estate Agent",
            "type":"Services"
        }
    ],
    "sg:phone":"+1 304 422 2225",
    "sg:postcode":"26104",
    "sg:province":"WV",
    "wof:name":"Kenneth Hoelscher",
    "wof:placetype":"venue"
},
  "geometry": {"coordinates":[-81.482855,39.281438],"type":"Point"}
}