{
  "type": "Feature",
  "properties": {
    "addr:full":"3423 US Hwy 60 Barboursville WV 25504",
    "addr:housenumber":"3423",
    "addr:postcode":"25504",
    "addr:street":"Us Hwy 60",
    "iso:country":"US",
    "sg:address":"3423 US Hwy 60",
    "sg:city":"Barboursville",
    "sg:classifiers":[
        {
            "category":"Education",
            "subcategory":"Vocational School",
            "type":"Public Place"
        }
    ],
    "sg:phone":"+1 304 733 0972",
    "sg:postcode":"25504",
    "sg:province":"WV",
    "wof:name":"CSX",
    "wof:placetype":"venue"
},
  "geometry": {"coordinates":[-82.26326,38.41177],"type":"Point"}
}