{
  "type": "Feature",
  "properties": {
    "addr:full":"1309 Stafford Dr Princeton WV 24740",
    "addr:housenumber":"1309",
    "addr:postcode":"24740",
    "addr:street":"Stafford Dr",
    "iso:country":"US",
    "sg:address":"1309 Stafford Dr",
    "sg:city":"Princeton",
    "sg:classifiers":[
        {
            "category":"Banks & Credit Unions",
            "subcategory":"Bank",
            "type":"Services"
        }
    ],
    "sg:phone":"+1 304 487 5915",
    "sg:postcode":"24740",
    "sg:province":"WV",
    "sg:tags":[
        "national",
        "commercial",
        "mortgage"
    ],
    "wof:name":"One Valley Bank",
    "wof:placetype":"venue"
},
  "geometry": {"coordinates":[-81.098877,37.360952],"type":"Point"}
}