{
  "type": "Feature",
  "properties": {
    "iso:country":"US",
    "sg:address":"1317 Ohio St",
    "sg:city":"Point Pleasant",
    "sg:classifiers":[
        {
            "category":"Shopping",
            "subcategory":"Hobbies, Toys, & Games",
            "type":"Retail Goods"
        }
    ],
    "sg:phone":"+1 304 675 7720",
    "sg:postcode":"25550",
    "sg:province":"WV",
    "sg:tags":[
        "equipment",
        "ceramic",
        "supply"
    ],
    "wof:name":"Dab-It Shop",
    "wof:placetype":"venue"
},
  "geometry": {"coordinates":[-82.136246,38.852516],"type":"Point"}
}