{
  "type": "Feature",
  "properties": {
    "iso:country":"US",
    "sg:address":"1908 Willow St",
    "sg:city":"Huntington",
    "sg:classifiers":[
        {
            "category":"Insurance",
            "subcategory":"Health Insurance",
            "type":"Services"
        }
    ],
    "sg:phone":"+1 304 525 6678",
    "sg:postcode":"25701",
    "sg:province":"WV",
    "sg:tags":[
        "carrier"
    ],
    "wof:name":"Diana Bishop",
    "wof:placetype":"venue"
},
  "geometry": {"coordinates":[-82.41956500000001,38.410798],"type":"Point"}
}