{
  "type": "Feature",
  "properties": {
    "addr:full":"1227 Warwood Ave Wheeling WV 26003",
    "addr:housenumber":"1227",
    "addr:postcode":"26003",
    "addr:street":"Warwood Ave",
    "iso:country":"US",
    "sg:address":"1227 Warwood Ave",
    "sg:city":"Wheeling",
    "sg:classifiers":[
        {
            "category":"Shopping",
            "subcategory":"Tobacco",
            "type":"Retail Goods"
        }
    ],
    "sg:phone":"+1 304 277 3206",
    "sg:postcode":"26003",
    "sg:province":"WV",
    "sg:tags":[
        "cigarette",
        "cigar",
        "dealer"
    ],
    "wof:name":"Smoker Friendly",
    "wof:placetype":"venue"
},
  "geometry": {"coordinates":[-80.698311,40.114588],"type":"Point"}
}