{
  "type": "Feature",
  "properties": {
    "iso:country":"US",
    "sg:address":"1301 Airport Rd",
    "sg:city":"Beaver",
    "sg:classifiers":[
        {
            "category":"Government",
            "subcategory":"Office",
            "type":"Public Place"
        }
    ],
    "sg:phone":"+1 304 256 3220",
    "sg:postcode":"25813",
    "sg:province":"WV",
    "sg:tags":[
        "safety",
        "health",
        "mine"
    ],
    "wof:name":"Beckley Northeastern District",
    "wof:placetype":"venue"
},
  "geometry": {"coordinates":[-81.084487,37.772042],"type":"Point"}
}