{
  "type": "Feature",
  "properties": {
    "iso:country":"US",
    "sg:address":"1599 Virginia St E",
    "sg:city":"Charleston",
    "sg:classifiers":[
        {
            "category":"Organizations",
            "subcategory":"Religious Organization",
            "type":"Services"
        }
    ],
    "sg:phone":"+1 304 346 4722",
    "sg:postcode":"25311",
    "sg:province":"WV",
    "sg:tags":[
        "synagogue"
    ],
    "wof:name":"B'Nai Jacob Synagogue",
    "wof:placetype":"venue"
},
  "geometry": {"coordinates":[-81.61873799999999,38.338696],"type":"Point"}
}