{
  "type": "Feature",
  "properties": {
    "iso:country":"US",
    "sg:address":"3100 Maccorkle Ave SE",
    "sg:city":"Charleston",
    "sg:classifiers":[
        {
            "category":"Health Services",
            "subcategory":"Doctor",
            "type":"Services"
        }
    ],
    "sg:phone":"+1 304 344 3785",
    "sg:postcode":"25304",
    "sg:province":"WV",
    "sg:tags":[
        "medical"
    ],
    "wof:name":"Oliver R Samuel Jr",
    "wof:placetype":"venue"
},
  "geometry": {"coordinates":[-81.60206100000001,38.328497],"type":"Point"}
}