{
  "type": "Feature",
  "properties": {
    "iso:country":"US",
    "sg:address":"12 E 4th Ave",
    "sg:city":"Williamson",
    "sg:classifiers":[
        {
            "category":"Health Services",
            "subcategory":"Dentist",
            "type":"Services"
        }
    ],
    "sg:phone":"+1 304 235 0018",
    "sg:postcode":"25661",
    "sg:province":"WV",
    "wof:name":"Stephen D Shoultz Dds Ltd",
    "wof:placetype":"venue"
},
  "geometry": {"coordinates":[-82.27433600000001,37.670022],"type":"Point"}
}