{
  "type": "Feature",
  "properties": {
    "iso:country":"US",
    "sg:address":"1 Government Sq",
    "sg:city":"Parkersburg",
    "sg:classifiers":[
        {
            "category":"Government",
            "subcategory":"Office",
            "type":"Public Place"
        }
    ],
    "sg:phone":"+1 304 424 8541",
    "sg:postcode":"26101",
    "sg:province":"WV",
    "sg:tags":[
        "village"
    ],
    "wof:name":"Parkersburg Personnel Dept",
    "wof:placetype":"venue"
},
  "geometry": {"coordinates":[-81.562736,39.264568],"type":"Point"}
}