{
  "type": "Feature",
  "properties": {
    "iso:country":"US",
    "sg:address":"126 Fairfax St",
    "sg:city":"Berkeley Springs",
    "sg:classifiers":[
        {
            "category":"Health Services",
            "subcategory":"Health Practitioner",
            "type":"Services"
        }
    ],
    "sg:phone":"+1 304 258 4959",
    "sg:postcode":"25411",
    "sg:province":"WV",
    "sg:tags":[
        "acupuncture"
    ],
    "wof:name":"Tamora R Marggraf",
    "wof:placetype":"venue"
},
  "geometry": {"coordinates":[-78.22824799999999,39.627201],"type":"Point"}
}