{
  "type": "Feature",
  "properties": {
    "iso:country":"US",
    "sg:address":"1317 Norfolk St",
    "sg:city":"Bluefield",
    "sg:classifiers":[
        {
            "category":"Building & Trades",
            "subcategory":"Construction",
            "type":"Services"
        }
    ],
    "sg:phone":"+1 304 325 8891",
    "sg:postcode":"24701",
    "sg:province":"WV",
    "sg:tags":[
        "concrete",
        "contractor"
    ],
    "wof:name":"Stone Bathtub Reglazing",
    "wof:placetype":"venue"
},
  "geometry": {"coordinates":[-81.213643,37.276635],"type":"Point"}
}