{
  "type": "Feature",
  "properties": {
    "addr:full":"2208 11th Ave Parkersburg WV 26101",
    "addr:housenumber":"2208",
    "addr:postcode":"26101",
    "addr:street":"11Th Ave",
    "iso:country":"US",
    "sg:address":"2208 11th Ave",
    "sg:city":"Parkersburg",
    "sg:classifiers":[
        {
            "category":"Arena",
            "subcategory":"Sports Club",
            "type":"Entertainment"
        }
    ],
    "sg:phone":"+1 304 485 8345",
    "sg:postcode":"26101",
    "sg:province":"WV",
    "sg:tags":[
        "manager",
        "recruiter",
        "promoter"
    ],
    "wof:name":"Badgley Promotions & Mgmt",
    "wof:placetype":"venue"
},
  "geometry": {"coordinates":[-81.550273,39.247285],"type":"Point"}
}