{
  "type": "Feature",
  "properties": {
    "addr:full":"511 3rd Ave SW South Charleston WV 25303",
    "addr:housenumber":"511",
    "addr:postcode":"25303",
    "addr:street":"3Rd Ave Sw",
    "iso:country":"US",
    "sg:address":"511 3rd Ave SW",
    "sg:city":"South Charleston",
    "sg:classifiers":[
        {
            "category":"Retail",
            "subcategory":"Auto Repair",
            "type":"Services"
        }
    ],
    "sg:phone":"+1 304 744 3900",
    "sg:postcode":"25303",
    "sg:province":"WV",
    "sg:tags":[
        "body",
        "automobile",
        "painting"
    ],
    "wof:name":"Body Shop",
    "wof:placetype":"venue"
},
  "geometry": {"coordinates":[-81.688829,38.367321],"type":"Point"}
}