{
  "type": "Feature",
  "properties": {
    "addr:full":"108 Royal Ave Ravenswood WV 26164",
    "addr:housenumber":"108",
    "addr:postcode":"26164",
    "addr:street":"Royal Ave",
    "iso:country":"US",
    "sg:address":"108 Royal Ave",
    "sg:city":"Ravenswood",
    "sg:classifiers":[
        {
            "category":"Social Services",
            "subcategory":"Child Care",
            "type":"Services"
        }
    ],
    "sg:phone":"+1 304 273 3155",
    "sg:postcode":"26164",
    "sg:province":"WV",
    "wof:name":"Kiddy Korner Nursery",
    "wof:placetype":"venue"
},
  "geometry": {"coordinates":[-81.764931,38.953186],"type":"Point"}
}