{
  "type": "Feature",
  "properties": {
    "iso:country":"US",
    "sg:address":"1301 University Ave",
    "sg:city":"Morgantown",
    "sg:classifiers":[
        {
            "category":"Retail",
            "subcategory":"Auto Repair",
            "type":"Services"
        }
    ],
    "sg:phone":"+1 304 292 4257",
    "sg:postcode":"26505",
    "sg:province":"WV",
    "sg:tags":[
        "automobile",
        "towing"
    ],
    "wof:name":"Vics Garage & Towing",
    "wof:placetype":"venue"
},
  "geometry": {"coordinates":[-79.957126,39.631152],"type":"Point"}
}