{
  "type": "Feature",
  "properties": {
    "iso:country":"US",
    "sg:address":"200 Lafayette Ave",
    "sg:city":"Moundsville",
    "sg:classifiers":[
        {
            "category":"Food & Beverages",
            "subcategory":"Groceries & Convenience Stores",
            "type":"Retail Goods"
        }
    ],
    "sg:phone":"+1 304 843 0040",
    "sg:postcode":"26041",
    "sg:province":"WV",
    "wof:name":"Giant Eagle Pharmacy",
    "wof:placetype":"venue"
},
  "geometry": {"coordinates":[-80.751695,39.930404],"type":"Point"}
}