{
  "type": "Feature",
  "properties": {
    "iso:country":"US",
    "sg:address":"2292 Roxalana Rd",
    "sg:city":"Dunbar",
    "sg:classifiers":[
        {
            "category":"Freight",
            "type":"Transportation"
        }
    ],
    "sg:phone":"+1 304 744 1521",
    "sg:postcode":"25064",
    "sg:province":"WV",
    "sg:tags":[
        "operator",
        "local",
        "trucking"
    ],
    "sg:website":"www.yellowcorp.com",
    "wof:name":"Yellow Transportation Inc",
    "wof:placetype":"venue"
},
  "geometry": {"coordinates":[-81.714444,38.375249],"type":"Point"}
}