{
  "type": "Feature",
  "properties": {
    "iso:country":"US",
    "sg:address":"160 Parkway Dr",
    "sg:city":"Wellsburg",
    "sg:classifiers":[
        {
            "category":"Building & Trades",
            "subcategory":"Construction",
            "type":"Services"
        }
    ],
    "sg:phone":"+1 304 737 4245",
    "sg:postcode":"26070",
    "sg:province":"WV",
    "sg:tags":[
        "house"
    ],
    "wof:name":"Palmer Home Improvement",
    "wof:placetype":"venue"
},
  "geometry": {"coordinates":[-80.56036,40.27988],"type":"Point"}
}