{
  "type": "Feature",
  "properties": {
    "iso:country":"US",
    "sg:address":"305 Congress St",
    "sg:city":"Berkeley Springs",
    "sg:classifiers":[
        {
            "category":"Shopping",
            "subcategory":"Computers & Home Electronics",
            "type":"Retail Goods"
        }
    ],
    "sg:phone":"+1 304 258 1277",
    "sg:postcode":"25411",
    "sg:province":"WV",
    "sg:tags":[
        "equipment",
        "satellite",
        "system"
    ],
    "wof:name":"Joe's Radio Shop",
    "wof:placetype":"venue"
},
  "geometry": {"coordinates":[-78.22672300000001,39.627422],"type":"Point"}
}