{
  "type": "Feature",
  "properties": {
    "addr:full":"132 Rural Acres Dr Beckley WV 25801",
    "addr:housenumber":"132",
    "addr:postcode":"25801",
    "addr:street":"Rural Acres Dr",
    "iso:country":"US",
    "sg:address":"132 Rural Acres Dr",
    "sg:city":"Beckley",
    "sg:classifiers":[
        {
            "category":"Organizations",
            "subcategory":"Religious Organization",
            "type":"Services"
        }
    ],
    "sg:phone":"+1 304 253 4415",
    "sg:postcode":"25801",
    "sg:province":"WV",
    "wof:name":"Calloway Hgts Bapt C",
    "wof:placetype":"venue"
},
  "geometry": {"coordinates":[-81.181755,37.792558],"type":"Point"}
}