{
  "type": "Feature",
  "properties": {
    "addr:full":"25 Hillcrest Dr Charleston WV 25302",
    "addr:housenumber":"25",
    "addr:postcode":"25302",
    "addr:street":"Hillcrest Dr",
    "iso:country":"US",
    "sg:address":"25 Hillcrest Dr",
    "sg:city":"Charleston",
    "sg:classifiers":[
        {
            "category":"Building & Trades",
            "subcategory":"Construction",
            "type":"Services"
        }
    ],
    "sg:phone":"+1 304 343 0857",
    "sg:postcode":"25302",
    "sg:province":"WV",
    "sg:tags":[
        "house"
    ],
    "wof:name":"Hugh L Breedlove Jr Builder",
    "wof:placetype":"venue"
},
  "geometry": {"coordinates":[-81.63525199999999,38.364609],"type":"Point"}
}