{
  "type": "Feature",
  "properties": {
    "addr:full":"677 Central Ave Barboursville WV 25504",
    "addr:housenumber":"677",
    "addr:postcode":"25504",
    "addr:street":"Central Ave",
    "iso:country":"US",
    "sg:address":"677 Central Ave",
    "sg:city":"Barboursville",
    "sg:classifiers":[
        {
            "category":"Health Services",
            "subcategory":"Doctor",
            "type":"Services"
        }
    ],
    "sg:phone":"+1 304 733 2300",
    "sg:postcode":"25504",
    "sg:province":"WV",
    "wof:name":"Allen Van Atter DDS",
    "wof:placetype":"venue"
},
  "geometry": {"coordinates":[-82.29538599999999,38.407937],"type":"Point"}
}