{
  "type": "Feature",
  "properties": {
    "addr:full":"717 N Jefferson St Lewisburg WV 24901",
    "addr:housenumber":"717",
    "addr:postcode":"24901",
    "addr:street":"N Jefferson St",
    "iso:country":"US",
    "sg:address":"717 N Jefferson St",
    "sg:city":"Lewisburg",
    "sg:classifiers":[
        {
            "category":"Government",
            "subcategory":"Office",
            "type":"Public Place"
        }
    ],
    "sg:phone":"+1 304 645 6173",
    "sg:postcode":"24901",
    "sg:province":"WV",
    "wof:name":"Greenbrier County Soil Cnsrvtn",
    "wof:placetype":"venue"
},
  "geometry": {"coordinates":[-80.42333499999999,37.821448],"type":"Point"}
}