{
  "type": "Feature",
  "properties": {
    "iso:country":"US",
    "sg:address":"741 N Main St",
    "sg:city":"Moorefield",
    "sg:classifiers":[
        {
            "category":"Health Services",
            "subcategory":"Optometrist",
            "type":"Services"
        }
    ],
    "sg:phone":"+1 304 538 6542",
    "sg:postcode":"26836",
    "sg:province":"WV",
    "wof:name":"Terry S Mangold Dr",
    "wof:placetype":"venue"
},
  "geometry": {"coordinates":[-78.966746,39.072951],"type":"Point"}
}