{
  "type": "Feature",
  "properties": {
    "iso:country":"US",
    "sg:address":"4349 US Hwy 60",
    "sg:city":"Huntington",
    "sg:classifiers":[
        {
            "category":"Autos & Motor Vehicles",
            "subcategory":"Auto Supplies",
            "type":"Retail Goods"
        }
    ],
    "sg:phone":"+1 304 736 3741",
    "sg:postcode":"25705",
    "sg:province":"WV",
    "sg:tags":[
        "automobile",
        "stereo",
        "radio"
    ],
    "wof:name":"Elite Sound & Image",
    "wof:placetype":"venue"
},
  "geometry": {"coordinates":[-82.364259,38.412085],"type":"Point"}
}