{
  "type": "Feature",
  "properties": {
    "iso:country":"US",
    "sg:address":"4626 Maccorkle Ave",
    "sg:city":"South Charleston",
    "sg:classifiers":[
        {
            "category":"Wholesale",
            "subcategory":"Office Equipment",
            "type":"Manufacturing & Wholesale Goods"
        }
    ],
    "sg:phone":"+1 304 768 6363",
    "sg:postcode":"25309",
    "sg:province":"WV",
    "sg:tags":[
        "machine",
        "duplicating",
        "copying"
    ],
    "wof:name":"Ropho Sales Inc",
    "wof:placetype":"venue"
},
  "geometry": {"coordinates":[-81.727093,38.355452],"type":"Point"}
}