{
  "type": "Feature",
  "properties": {
    "addr:full":"500 Williamsport Pike B Martinsburg WV 25404",
    "addr:housenumber":"500",
    "addr:postcode":"25404",
    "addr:street":"Williamsport Pike",
    "iso:country":"US",
    "sg:address":"500 Williamsport Pike B",
    "sg:city":"Martinsburg",
    "sg:classifiers":[
        {
            "category":"Insurance",
            "subcategory":"Insurance Agent",
            "type":"Services"
        },
        {
            "category":"Insurance",
            "subcategory":"Hazard Insurance",
            "type":"Services"
        },
        {
            "category":"Banks & Credit Unions",
            "subcategory":"Financial Services",
            "type":"Services"
        }
    ],
    "sg:phone":"+1 304 267 4915",
    "sg:postcode":"25404",
    "sg:province":"WV",
    "sg:tags":[
        "auto",
        "commercial",
        "business",
        "mortgage"
    ],
    "wof:name":"Fargo Insurance",
    "wof:placetype":"venue"
},
  "geometry": {"coordinates":[-77.955635,39.476594],"type":"Point"}
}