{
  "type": "Feature",
  "properties": {
    "addr:full":"107 Charleston Rd Spencer WV 25276",
    "addr:housenumber":"107",
    "addr:postcode":"25276",
    "addr:street":"Charleston Rd",
    "iso:country":"US",
    "sg:address":"107 Charleston Rd",
    "sg:city":"Spencer",
    "sg:classifiers":[
        {
            "category":"Education",
            "subcategory":"School",
            "type":"Public Place"
        }
    ],
    "sg:phone":"+1 304 927 6420",
    "sg:postcode":"25276",
    "sg:province":"WV",
    "wof:name":"Roane Co Child Development",
    "wof:placetype":"venue"
},
  "geometry": {"coordinates":[-81.35566900000001,38.790742],"type":"Point"}
}