{
  "type": "Feature",
  "properties": {
    "iso:country":"US",
    "sg:address":"900 Washington St E",
    "sg:city":"Charleston",
    "sg:classifiers":[
        {
            "category":"Organizations",
            "subcategory":"Religious Organization",
            "type":"Services"
        }
    ],
    "sg:phone":"+1 304 344 8330",
    "sg:postcode":"25301",
    "sg:province":"WV",
    "wof:name":"Ives S Clifton Bishop",
    "wof:placetype":"venue"
},
  "geometry": {"coordinates":[-81.630771,38.349937],"type":"Point"}
}