{
  "type": "Feature",
  "properties": {
    "iso:country":"US",
    "sg:address":"377 Conner Bowers Rd",
    "sg:city":"Hedgesville",
    "sg:classifiers":[
        {
            "category":"Shopping",
            "subcategory":"Gifts & Souvenirs",
            "type":"Retail Goods"
        }
    ],
    "sg:phone":"+1 304 754 5909",
    "sg:postcode":"25427",
    "sg:province":"WV",
    "sg:tags":[
        "shop"
    ],
    "wof:name":"Whisperwood",
    "wof:placetype":"venue"
},
  "geometry": {"coordinates":[-78.03549,39.580991],"type":"Point"}
}