{
  "type": "Feature",
  "properties": {
    "addr:full":"1947 Fairmont Ave Fairmont WV 26554",
    "addr:housenumber":"1947",
    "addr:postcode":"26554",
    "addr:street":"Fairmont Ave",
    "iso:country":"US",
    "sg:address":"1947 Fairmont Ave",
    "sg:city":"Fairmont",
    "sg:classifiers":[
        {
            "category":"Real Estate",
            "subcategory":"Real Estate Agent",
            "type":"Services"
        }
    ],
    "sg:phone":"+1 304 366 6550",
    "sg:postcode":"26554",
    "sg:province":"WV",
    "wof:name":"Real Estate Plus",
    "wof:placetype":"venue"
},
  "geometry": {"coordinates":[-80.174868,39.450755],"type":"Point"}
}