{
  "type": "Feature",
  "properties": {
    "iso:country":"US",
    "sg:address":"30 6th Ave W",
    "sg:city":"Huntington",
    "sg:classifiers":[
        {
            "category":"Insurance",
            "subcategory":"Insurance Agent",
            "type":"Services"
        }
    ],
    "sg:phone":"+1 304 429 8200",
    "sg:postcode":"25701",
    "sg:province":"WV",
    "wof:name":"Tpa Services",
    "wof:placetype":"venue"
},
  "geometry": {"coordinates":[-82.457679,38.415596],"type":"Point"}
}