{
  "type": "Feature",
  "properties": {
    "addr:full":"35 Turkey Run Rd Buckhannon WV 26201",
    "addr:housenumber":"35",
    "addr:postcode":"26201",
    "addr:street":"Turkey Run Rd",
    "iso:country":"US",
    "sg:address":"35 Turkey Run Rd",
    "sg:city":"Buckhannon",
    "sg:classifiers":[
        {
            "category":"Manufacturing",
            "subcategory":"Wood Products",
            "type":"Manufacturing & Wholesale Goods"
        }
    ],
    "sg:phone":"+1 304 472 8485",
    "sg:postcode":"26201",
    "sg:province":"WV",
    "sg:tags":[
        "mill",
        "preserving",
        "mfg"
    ],
    "wof:name":"Savin Lumber Company",
    "wof:placetype":"venue"
},
  "geometry": {"coordinates":[-80.2418,39.038559],"type":"Point"}
}