{
  "type": "Feature",
  "properties": {
    "iso:country":"US",
    "sg:address":"501 Main St",
    "sg:city":"Point Pleasant",
    "sg:classifiers":[
        {
            "category":"Professional",
            "subcategory":"Lawyer & Legal Services",
            "type":"Services"
        }
    ],
    "sg:phone":"+1 304 675 3637",
    "sg:postcode":"25550",
    "sg:province":"WV",
    "sg:tags":[
        "attorney"
    ],
    "wof:name":"Constance J Fisher",
    "wof:placetype":"venue"
},
  "geometry": {"coordinates":[-82.13834199999999,38.844204],"type":"Point"}
}