{
  "type": "Feature",
  "properties": {
    "iso:country":"US",
    "sg:address":"1907 Marshall St S",
    "sg:city":"Benwood",
    "sg:classifiers":[
        {
            "category":"Retail",
            "subcategory":"Repair Shop",
            "type":"Services"
        }
    ],
    "sg:phone":"+1 304 232 7446",
    "sg:postcode":"26031",
    "sg:province":"WV",
    "sg:tags":[
        "welding"
    ],
    "wof:name":"Carrie Lough Welding",
    "wof:placetype":"venue"
},
  "geometry": {"coordinates":[-80.73131600000001,39.998422],"type":"Point"}
}