{
  "type": "Feature",
  "properties": {
    "iso:country":"US",
    "sg:address":"269 North St",
    "sg:city":"New Martinsville",
    "sg:classifiers":[
        {
            "category":"Professional",
            "subcategory":"Employment Agencies",
            "type":"Services"
        }
    ],
    "sg:phone":"+1 304 455 6969",
    "sg:postcode":"26155",
    "sg:province":"WV",
    "sg:tags":[
        "opportunity"
    ],
    "wof:name":"Career Search One Inc",
    "wof:placetype":"venue"
},
  "geometry": {"coordinates":[-80.859819,39.642517],"type":"Point"}
}