{
  "type": "Feature",
  "properties": {
    "iso:country":"US",
    "sg:address":"400 Hal Greer Blvd",
    "sg:city":"Huntington",
    "sg:classifiers":[
        {
            "category":"Restaurant",
            "type":"Food & Drink"
        }
    ],
    "sg:phone":"+1 304 696 2534",
    "sg:postcode":"25701",
    "sg:province":"WV",
    "wof:name":"Sodexho Inc",
    "wof:placetype":"venue"
},
  "geometry": {"coordinates":[-82.431646,38.422148],"type":"Point"}
}