{
  "type": "Feature",
  "properties": {
    "addr:full":"5304 Church Dr Charleston WV 25306",
    "addr:housenumber":"5304",
    "addr:postcode":"25306",
    "addr:street":"Church Dr",
    "iso:country":"US",
    "sg:address":"5304 Church Dr",
    "sg:city":"Charleston",
    "sg:classifiers":[
        {
            "category":"Retail",
            "subcategory":"Laundry & Dry Cleaning",
            "type":"Services"
        }
    ],
    "sg:phone":"+1 304 755 9510",
    "sg:postcode":"25306",
    "sg:province":"WV",
    "sg:tags":[
        "cleaners",
        "rug",
        "carpet"
    ],
    "wof:name":"Servpro",
    "wof:placetype":"venue"
},
  "geometry": {"coordinates":[-81.564437,38.283266],"type":"Point"}
}