{
  "type": "Feature",
  "properties": {
    "iso:country":"US",
    "sg:address":"7715 Sissonville Dr",
    "sg:city":"Charleston",
    "sg:classifiers":[
        {
            "category":"Professional",
            "subcategory":"Business Services",
            "type":"Services"
        }
    ],
    "sg:phone":"+1 304 965 9511",
    "sg:postcode":"25320",
    "sg:province":"WV",
    "sg:tags":[
        "auctioneer"
    ],
    "wof:name":"Pink Ribbon E Auctions",
    "wof:placetype":"venue"
},
  "geometry": {"coordinates":[-81.637394,38.510995],"type":"Point"}
}