{
  "type": "Feature",
  "properties": {
    "addr:full":"5511 Charles Town Rd Kearneysville WV 25430",
    "addr:housenumber":"5511",
    "addr:postcode":"25430",
    "addr:street":"Charles Town Rd",
    "iso:country":"US",
    "sg:address":"5511 Charles Town Rd",
    "sg:city":"Kearneysville",
    "sg:classifiers":[
        {
            "category":"Shopping",
            "subcategory":"Bicycles & Sporting Goods",
            "type":"Retail Goods"
        }
    ],
    "sg:phone":"+1 304 876 8499",
    "sg:postcode":"25430",
    "sg:province":"WV",
    "wof:name":"Dead Box Paintball Pro Shop",
    "wof:placetype":"venue"
},
  "geometry": {"coordinates":[-77.885346,39.387242],"type":"Point"}
}