{
  "type": "Feature",
  "properties": {
    "iso:country":"US",
    "sg:address":"198 Old Cheat Rd",
    "sg:city":"Morgantown",
    "sg:classifiers":[
        {
            "category":"Retail",
            "subcategory":"Repair Shop",
            "type":"Services"
        }
    ],
    "sg:phone":"+1 304 296 4414",
    "sg:postcode":"26508",
    "sg:province":"WV",
    "sg:tags":[
        "scooter",
        "motorcycle",
        "motor"
    ],
    "wof:name":"T J Smith Cycle Works",
    "wof:placetype":"venue"
},
  "geometry": {"coordinates":[-79.90122700000001,39.652946],"type":"Point"}
}