{
  "type": "Feature",
  "properties": {
    "iso:country":"US",
    "sg:address":"3972 Teays Valley Rd",
    "sg:city":"Hurricane",
    "sg:classifiers":[
        {
            "category":"Professional",
            "subcategory":"Lawyer & Legal Services",
            "type":"Services"
        }
    ],
    "sg:phone":"+1 304 757 2691",
    "sg:postcode":"25526",
    "sg:province":"WV",
    "sg:tags":[
        "attorney"
    ],
    "wof:name":"Armada Rogers & Thompson",
    "wof:placetype":"venue"
},
  "geometry": {"coordinates":[-81.94056399999999,38.448521],"type":"Point"}
}