{
  "type": "Feature",
  "properties": {
    "iso:country":"US",
    "sg:address":"1010 Young St",
    "sg:city":"Charleston",
    "sg:classifiers":[
        {
            "category":"Building & Trades",
            "subcategory":"Electrical",
            "type":"Services"
        }
    ],
    "sg:phone":"+1 304 525 3890",
    "sg:postcode":"25301",
    "sg:province":"WV",
    "sg:tags":[
        "electric",
        "contractor"
    ],
    "wof:name":"Graybar Electric Huntington",
    "wof:placetype":"venue"
},
  "geometry": {"coordinates":[-81.628057,38.355907],"type":"Point"}
}