{
  "type": "Feature",
  "properties": {
    "iso:country":"US",
    "sg:address":"1 Orion Ln",
    "sg:city":"Fairmont",
    "sg:classifiers":[
        {
            "category":"Education",
            "subcategory":"School",
            "type":"Public Place"
        }
    ],
    "sg:phone":"+1 304 367 2123",
    "sg:postcode":"26554",
    "sg:province":"WV",
    "sg:tags":[
        "high",
        "senior"
    ],
    "wof:name":"East Fairmont High School",
    "wof:placetype":"venue"
},
  "geometry": {"coordinates":[-80.132285,39.48086],"type":"Point"}
}