{
  "type": "Feature",
  "properties": {
    "iso:country":"US",
    "sg:address":"100 W State Ave",
    "sg:city":"Terra Alta",
    "sg:classifiers":[
        {
            "category":"Building & Trades",
            "subcategory":"Construction",
            "type":"Services"
        }
    ],
    "sg:phone":"+1 304 789 2747",
    "sg:postcode":"26764",
    "sg:province":"WV",
    "sg:tags":[
        "house",
        "general",
        "nonresidential",
        "contractor"
    ],
    "wof:name":"High Country Contractors Inc",
    "wof:placetype":"venue"
},
  "geometry": {"coordinates":[-79.54650599999999,39.445798],"type":"Point"}
}