{
  "type": "Feature",
  "properties": {
    "iso:country":"US",
    "sg:address":"150 Main St",
    "sg:city":"Cameron",
    "sg:classifiers":[
        {
            "category":"Building & Trades",
            "subcategory":"Construction",
            "type":"Services"
        }
    ],
    "sg:phone":"+1 304 686 2148",
    "sg:postcode":"26033",
    "sg:province":"WV",
    "sg:tags":[
        "contractor"
    ],
    "wof:name":"Harold Strahl",
    "wof:placetype":"venue"
},
  "geometry": {"coordinates":[-80.574648,39.82749],"type":"Point"}
}