{
  "type": "Feature",
  "properties": {
    "iso:country":"US",
    "sg:address":"945 4th Ave",
    "sg:city":"Huntington",
    "sg:classifiers":[
        {
            "category":"Professional",
            "subcategory":"Advertising",
            "type":"Services"
        }
    ],
    "sg:phone":"+1 304 399 1997",
    "sg:postcode":"25701",
    "sg:province":"WV",
    "sg:tags":[
        "counselor"
    ],
    "wof:name":"Pamela Wise & Assoc",
    "wof:placetype":"venue"
},
  "geometry": {"coordinates":[-82.442797,38.420853],"type":"Point"}
}