{
  "type": "Feature",
  "properties": {
    "iso:country":"US",
    "sg:address":"806 Old Mill Rd",
    "sg:city":"Hedgesville",
    "sg:classifiers":[
        {
            "category":"Farming",
            "subcategory":"Orchard",
            "type":"Manufacturing & Wholesale Goods"
        }
    ],
    "sg:phone":"+1 304 754 3373",
    "sg:postcode":"25413",
    "sg:province":"WV",
    "sg:tags":[
        "fruit",
        "tree"
    ],
    "wof:name":"Marvin Ellis",
    "wof:placetype":"venue"
},
  "geometry": {"coordinates":[-77.985697,39.469539],"type":"Point"}
}