{
  "type": "Feature",
  "properties": {
    "iso:country":"US",
    "sg:address":"787 Twin Oaks Dr",
    "sg:city":"Bridgeport",
    "sg:classifiers":[
        {
            "category":"Retail",
            "subcategory":"Repair Shop",
            "type":"Services"
        }
    ],
    "sg:phone":"+1 304 623 3405",
    "sg:postcode":"26330",
    "sg:province":"WV",
    "wof:name":"Clean Tech",
    "wof:placetype":"venue"
},
  "geometry": {"coordinates":[-80.26453600000001,39.28304],"type":"Point"}
}