{
  "type": "Feature",
  "properties": {
    "addr:full":"98 16th St Wheeling WV 26003",
    "addr:housenumber":"98",
    "addr:postcode":"26003",
    "addr:street":"16Th St",
    "iso:country":"US",
    "sg:address":"98 16th St",
    "sg:city":"Wheeling",
    "sg:classifiers":[
        {
            "category":"Professional",
            "subcategory":"Advertising",
            "type":"Services"
        }
    ],
    "sg:phone":"+1 304 233 1122",
    "sg:postcode":"26003",
    "sg:province":"WV",
    "sg:tags":[
        "counselor",
        "agency"
    ],
    "wof:name":"Emcor Media Network Inc",
    "wof:placetype":"venue"
},
  "geometry": {"coordinates":[-80.7184,40.064318],"type":"Point"}
}