{
  "type": "Feature",
  "properties": {
    "addr:full":"27 E Main St Richwood WV 26261",
    "addr:housenumber":"27",
    "addr:postcode":"26261",
    "addr:street":"E Main St",
    "iso:country":"US",
    "sg:address":"27 E Main St",
    "sg:city":"Richwood",
    "sg:classifiers":[
        {
            "category":"Shopping",
            "subcategory":"Florist",
            "type":"Retail Goods"
        }
    ],
    "sg:phone":"+1 304 846 9000",
    "sg:postcode":"26261",
    "sg:province":"WV",
    "wof:name":"Country Lane Florist",
    "wof:placetype":"venue"
},
  "geometry": {"coordinates":[-80.532298,38.225496],"type":"Point"}
}