{
  "type": "Feature",
  "properties": {
    "addr:full":"907 E Moler Ave Martinsburg WV 25401",
    "addr:housenumber":"907",
    "addr:postcode":"25401",
    "addr:street":"E Moler Ave",
    "iso:country":"US",
    "sg:address":"907 E Moler Ave",
    "sg:city":"Martinsburg",
    "sg:classifiers":[
        {
            "category":"Retail",
            "subcategory":"Auto Repair",
            "type":"Services"
        }
    ],
    "sg:phone":"+1 304 271 8718",
    "sg:postcode":"25401",
    "sg:province":"WV",
    "sg:tags":[
        "repairing",
        "automobile",
        "general"
    ],
    "wof:name":"Guy's Little Detroit",
    "wof:placetype":"venue"
},
  "geometry": {"coordinates":[-77.94374500000001,39.464874],"type":"Point"}
}