{
  "type": "Feature",
  "properties": {
    "iso:country":"US",
    "sg:address":"700 Elk St",
    "sg:city":"Gassaway",
    "sg:classifiers":[
        {
            "category":"Banks & Credit Unions",
            "subcategory":"Financial Services",
            "type":"Services"
        }
    ],
    "sg:phone":"+1 304 364 5138",
    "sg:postcode":"26624",
    "sg:province":"WV",
    "sg:tags":[
        "company",
        "holding"
    ],
    "wof:name":"Gassaway Bancshares Inc",
    "wof:placetype":"venue"
},
  "geometry": {"coordinates":[-80.772471,38.675272],"type":"Point"}
}