{
  "type": "Feature",
  "properties": {
    "iso:country":"US",
    "sg:address":"33 Woodland Ave",
    "sg:city":"Parkersburg",
    "sg:classifiers":[
        {
            "category":"Health Services",
            "subcategory":"Clinic",
            "type":"Services"
        }
    ],
    "sg:phone":"+1 304 428 0551",
    "sg:postcode":"26101",
    "sg:province":"WV",
    "wof:name":"Albright John Ptrick Fundation",
    "wof:placetype":"venue"
},
  "geometry": {"coordinates":[-81.506934,39.266645],"type":"Point"}
}