{
  "type": "Feature",
  "properties": {
    "addr:full":"1702 Core Rd Parkersburg WV 26104",
    "addr:housenumber":"1702",
    "addr:postcode":"26104",
    "addr:street":"Core Rd",
    "iso:country":"US",
    "sg:address":"1702 Core Rd",
    "sg:city":"Parkersburg",
    "sg:classifiers":[
        {
            "category":"Building & Trades",
            "subcategory":"Construction",
            "type":"Services"
        }
    ],
    "sg:phone":"+1 304 428 5626",
    "sg:postcode":"26104",
    "sg:province":"WV",
    "sg:tags":[
        "boring",
        "drilling",
        "contractor"
    ],
    "wof:name":"Whited Water Well Drilling",
    "wof:placetype":"venue"
},
  "geometry": {"coordinates":[-81.50166400000001,39.278961],"type":"Point"}
}