{
  "type": "Feature",
  "properties": {
    "iso:country":"US",
    "sg:address":"500 Donnally St",
    "sg:city":"Charleston",
    "sg:classifiers":[
        {
            "category":"Health Services",
            "subcategory":"Doctor",
            "type":"Services"
        }
    ],
    "sg:phone":"+1 304 343 3888",
    "sg:postcode":"25301",
    "sg:province":"WV",
    "sg:tags":[
        "physician",
        "surgeon",
        "medical"
    ],
    "wof:name":"Rheumatology Associates",
    "wof:placetype":"venue"
},
  "geometry": {"coordinates":[-81.63208299999999,38.353727],"type":"Point"}
}