{
  "type": "Feature",
  "properties": {
    "iso:country":"US",
    "sg:address":"2013 Camden Ave",
    "sg:city":"Parkersburg",
    "sg:classifiers":[
        {
            "category":"Retail",
            "subcategory":"Repair Shop",
            "type":"Services"
        }
    ],
    "sg:phone":"+1 304 422 0072",
    "sg:postcode":"26101",
    "sg:province":"WV",
    "sg:tags":[
        "scooter",
        "motorcycle",
        "motor"
    ],
    "wof:name":"Action Motorsports",
    "wof:placetype":"venue"
},
  "geometry": {"coordinates":[-81.553378,39.255076],"type":"Point"}
}