{
  "type": "Feature",
  "properties": {
    "addr:full":"317 Don Knotts Blvd Morgantown WV 26501",
    "addr:housenumber":"317",
    "addr:postcode":"26501",
    "addr:street":"Don Knotts Blvd",
    "iso:country":"US",
    "sg:address":"317 Don Knotts Blvd",
    "sg:city":"Morgantown",
    "sg:classifiers":[
        {
            "category":"Bars & Pubs",
            "type":"Food & Drink"
        }
    ],
    "sg:menulink":"http://www.allmenus.com/wv/central/241929-tailgators-bar-and-grill/menu/",
    "sg:phone":"+1 304 599 1564",
    "sg:postcode":"26501",
    "sg:province":"WV",
    "sg:tags":[
        "american"
    ],
    "wof:name":"Tailgators Bar And Grill",
    "wof:placetype":"venue"
},
  "geometry": {"coordinates":[-79.96960799999999,39.610895],"type":"Point"}
}