{
  "type": "Feature",
  "properties": {
    "iso:country":"US",
    "sg:address":"4000 Emerson Ave",
    "sg:city":"Parkersburg",
    "sg:classifiers":[
        {
            "category":"Restaurant",
            "type":"Food & Drink"
        }
    ],
    "sg:phone":"+1 304 422 7655",
    "sg:postcode":"26104",
    "sg:province":"WV",
    "sg:tags":[
        "eating"
    ],
    "wof:name":"Front Row Sports Bar & Grill",
    "wof:placetype":"venue"
},
  "geometry": {"coordinates":[-81.53012,39.28942],"type":"Point"}
}