{
  "type": "Feature",
  "properties": {
    "iso:country":"US",
    "sg:address":"769 Washington St",
    "sg:city":"Harpers Ferry",
    "sg:classifiers":[
        {
            "category":"Real Estate",
            "subcategory":"Architect",
            "type":"Services"
        }
    ],
    "sg:phone":"+1 304 535 6693",
    "sg:postcode":"25425",
    "sg:province":"WV",
    "wof:name":"Stowell Galleries B & B",
    "wof:placetype":"venue"
},
  "geometry": {"coordinates":[-77.73990999999999,39.325554],"type":"Point"}
}