{
  "type": "Feature",
  "properties": {
    "addr:full":"1085 Van Voorhis Rd Morgantown WV 26505",
    "addr:housenumber":"1085",
    "addr:postcode":"26505",
    "addr:street":"Van Voorhis Rd",
    "iso:country":"US",
    "sg:address":"1085 Van Voorhis Rd",
    "sg:city":"Morgantown",
    "sg:classifiers":[
        {
            "category":"Professional",
            "subcategory":"Lawyer & Legal Services",
            "type":"Services"
        }
    ],
    "sg:phone":"+1 304 598 8151",
    "sg:postcode":"26505",
    "sg:province":"WV",
    "sg:tags":[
        "attorney"
    ],
    "wof:name":"Steptoe & Johnson",
    "wof:placetype":"venue"
},
  "geometry": {"coordinates":[-79.963649,39.652616],"type":"Point"}
}