{
  "type": "Feature",
  "properties": {
    "addr:full":"909 Morgantown Ave Fairmont WV 26554",
    "addr:housenumber":"909",
    "addr:postcode":"26554",
    "addr:street":"Morgantown Ave",
    "iso:country":"US",
    "sg:address":"909 Morgantown Ave",
    "sg:city":"Fairmont",
    "sg:classifiers":[
        {
            "category":"Cinema",
            "subcategory":"Movie Rental",
            "type":"Entertainment"
        }
    ],
    "sg:phone":"+1 304 368 1500",
    "sg:postcode":"26554",
    "sg:province":"WV",
    "sg:tags":[
        "leasing",
        "video",
        "disc",
        "tape"
    ],
    "wof:name":"Video Warehouse",
    "wof:placetype":"venue"
},
  "geometry": {"coordinates":[-80.123627,39.479097],"type":"Point"}
}