{
  "type": "Feature",
  "properties": {
    "addr:full":"348 Middleway Rd Inwood WV 25413",
    "addr:housenumber":"348",
    "addr:postcode":"25413",
    "addr:street":"Middleway Rd",
    "iso:country":"US",
    "sg:address":"348 Middleway Rd",
    "sg:city":"Inwood",
    "sg:classifiers":[
        {
            "category":"Health Services",
            "subcategory":"Doctor",
            "type":"Services"
        }
    ],
    "sg:phone":"+1 304 229 5851",
    "sg:postcode":"25413",
    "sg:province":"WV",
    "wof:name":"Bonner & Griffith",
    "wof:placetype":"venue"
},
  "geometry": {"coordinates":[-78.042237,39.308105],"type":"Point"}
}