{
  "type": "Feature",
  "properties": {
    "addr:full":"1205 S Hills Rd Morgantown WV 26508",
    "addr:housenumber":"1205",
    "addr:postcode":"26508",
    "addr:street":"S Hills Rd",
    "iso:country":"US",
    "sg:address":"1205 S Hills Rd",
    "sg:city":"Morgantown",
    "sg:classifiers":[
        {
            "category":"Building & Trades",
            "subcategory":"Equipment Rental",
            "type":"Services"
        }
    ],
    "sg:phone":"+1 304 594 1371",
    "sg:postcode":"26508",
    "sg:province":"WV",
    "wof:name":"R&L Rentals",
    "wof:placetype":"venue"
},
  "geometry": {"coordinates":[-79.99296099999999,39.568356],"type":"Point"}
}