{
  "type": "Feature",
  "properties": {
    "iso:country":"US",
    "sg:address":"1435 Crescent Rd",
    "sg:city":"Charleston",
    "sg:classifiers":[
        {
            "category":"Freight",
            "type":"Transportation"
        }
    ],
    "sg:phone":"+1 304 345 2100",
    "sg:postcode":"25302",
    "sg:province":"WV",
    "sg:tags":[
        "warehouse",
        "tobacco"
    ],
    "wof:name":"Tobacco Plus",
    "wof:placetype":"venue"
},
  "geometry": {"coordinates":[-81.623786,38.362703],"type":"Point"}
}