{
  "type": "Feature",
  "properties": {
    "addr:full":"1562 Kanawha Blvd E Charleston WV 25311",
    "addr:housenumber":"1562",
    "addr:postcode":"25311",
    "addr:street":"Kanawha Blvd E",
    "iso:country":"US",
    "sg:address":"1562 Kanawha Blvd E",
    "sg:city":"Charleston",
    "sg:classifiers":[
        {
            "category":"Professional",
            "subcategory":"Lawyer & Legal Services",
            "type":"Services"
        }
    ],
    "sg:phone":"+1 304 345 1990",
    "sg:postcode":"25311",
    "sg:province":"WV",
    "sg:tags":[
        "attorney"
    ],
    "sg:website":"www.kcybl.com",
    "wof:name":"Ranson Law Offices",
    "wof:placetype":"venue"
},
  "geometry": {"coordinates":[-81.623695,38.339452],"type":"Point"}
}