{
  "type": "Feature",
  "properties": {
    "iso:country":"US",
    "sg:address":"305 S West St",
    "sg:city":"Charles Town",
    "sg:classifiers":[
        {
            "category":"Sports & Exercise",
            "subcategory":"Gym",
            "type":"Entertainment"
        }
    ],
    "sg:phone":"+1 304 725 3482",
    "sg:postcode":"25414",
    "sg:province":"WV",
    "sg:tags":[
        "club",
        "health",
        "studio",
        "gymnasium"
    ],
    "wof:name":"Charles Town Curves",
    "wof:placetype":"venue"
},
  "geometry": {"coordinates":[-77.862539,39.286022],"type":"Point"}
}