{
  "type": "Feature",
  "properties": {
    "iso:country":"US",
    "sg:address":"69 Main St",
    "sg:city":"Poca",
    "sg:classifiers":[
        {
            "category":"Shopping",
            "subcategory":"Tobacco",
            "type":"Retail Goods"
        }
    ],
    "sg:phone":"+1 304 755 5799",
    "sg:postcode":"25159",
    "sg:province":"WV",
    "sg:tags":[
        "cigarette",
        "cigar",
        "dealer"
    ],
    "wof:name":"Freedom Tobacco",
    "wof:placetype":"venue"
},
  "geometry": {"coordinates":[-81.81453500000001,38.470371],"type":"Point"}
}