{
  "type": "Feature",
  "properties": {
    "addr:full":"539 9th St Huntington WV 25701",
    "addr:housenumber":"539",
    "addr:postcode":"25701",
    "addr:street":"9Th St",
    "iso:country":"US",
    "sg:address":"539 9th St",
    "sg:city":"Huntington",
    "sg:classifiers":[
        {
            "category":"Wholesale",
            "subcategory":"Groceries",
            "type":"Manufacturing & Wholesale Goods"
        }
    ],
    "sg:phone":"+1 304 522 9054",
    "sg:postcode":"25701",
    "sg:province":"WV",
    "sg:tags":[
        "food",
        "broker"
    ],
    "wof:name":"Mike's",
    "wof:placetype":"venue"
},
  "geometry": {"coordinates":[-82.443555,38.419225],"type":"Point"}
}