{
  "type": "Feature",
  "properties": {
    "addr:full":"234 4th Ave Huntington WV 25701",
    "addr:housenumber":"234",
    "addr:postcode":"25701",
    "addr:street":"4Th Ave",
    "iso:country":"US",
    "sg:address":"234 4th Ave",
    "sg:city":"Huntington",
    "sg:classifiers":[
        {
            "category":"Organizations",
            "subcategory":"Labor Organization",
            "type":"Services"
        }
    ],
    "sg:phone":"+1 304 342 2836",
    "sg:postcode":"25701",
    "sg:province":"WV",
    "wof:name":"AFSCME",
    "wof:placetype":"venue"
},
  "geometry": {"coordinates":[-82.454688,38.418947],"type":"Point"}
}