{
  "type": "Feature",
  "properties": {
    "iso:country":"US",
    "sg:address":"45 Cory Rd",
    "sg:city":"Fairmont",
    "sg:classifiers":[
        {
            "category":"Retail",
            "subcategory":"Auto Repair",
            "type":"Services"
        }
    ],
    "sg:phone":"+1 304 366 4497",
    "sg:postcode":"26554",
    "sg:province":"WV",
    "sg:tags":[
        "body",
        "automobile",
        "painting"
    ],
    "wof:name":"Astro Body Ctr",
    "wof:placetype":"venue"
},
  "geometry": {"coordinates":[-80.197354,39.422165],"type":"Point"}
}