{
  "type": "Feature",
  "properties": {
    "addr:full":"4718 Kanawha Ave SW Charleston WV 25309",
    "addr:housenumber":"4718",
    "addr:postcode":"25309",
    "addr:street":"Kanawha Ave Sw",
    "iso:country":"US",
    "sg:address":"4718 Kanawha Ave SW",
    "sg:city":"Charleston",
    "sg:classifiers":[
        {
            "category":"Social Services",
            "subcategory":"Adult Care",
            "type":"Services"
        }
    ],
    "sg:phone":"+1 304 766 2464",
    "sg:postcode":"25309",
    "sg:province":"WV",
    "sg:tags":[
        "residential"
    ],
    "wof:name":"Unity Apartments",
    "wof:placetype":"venue"
},
  "geometry": {"coordinates":[-81.73061,38.355756],"type":"Point"}
}