{
  "type": "Feature",
  "properties": {
    "iso:country":"US",
    "sg:address":"400 Eagle Mountain Rd",
    "sg:city":"Charleston",
    "sg:classifiers":[
        {
            "category":"Building & Trades",
            "subcategory":"Construction",
            "type":"Services"
        }
    ],
    "sg:phone":"+1 304 345 3964",
    "sg:postcode":"25311",
    "sg:province":"WV",
    "sg:tags":[
        "hanging",
        "contractor"
    ],
    "wof:name":"Wr Mollohan Inc",
    "wof:placetype":"venue"
},
  "geometry": {"coordinates":[-81.59166,38.365456],"type":"Point"}
}