{
  "type": "Feature",
  "properties": {
    "addr:full":"827 Fairmont Rd Morgantown WV 26501",
    "addr:housenumber":"827",
    "addr:postcode":"26501",
    "addr:street":"Fairmont Rd",
    "iso:country":"US",
    "sg:address":"827 Fairmont Rd",
    "sg:city":"Morgantown",
    "sg:classifiers":[
        {
            "category":"Wholesale",
            "subcategory":"Computers",
            "type":"Manufacturing & Wholesale Goods"
        },
        {
            "category":"Professional",
            "subcategory":"Computer Services",
            "type":"Services"
        }
    ],
    "sg:phone":"+1 304 296 8270",
    "sg:postcode":"26501",
    "sg:province":"WV",
    "sg:tags":[
        "repair",
        "reseller"
    ],
    "wof:name":"S B C Computer Systems",
    "wof:placetype":"venue"
},
  "geometry": {"coordinates":[-79.982018,39.632572],"type":"Point"}
}