{
  "type": "Feature",
  "properties": {
    "iso:country":"US",
    "sg:address":"505 Western Ave",
    "sg:city":"Martinsburg",
    "sg:classifiers":[
        {
            "category":"Building & Trades",
            "subcategory":"Construction",
            "type":"Services"
        }
    ],
    "sg:phone":"+1 304 263 8547",
    "sg:postcode":"25401",
    "sg:province":"WV",
    "sg:tags":[
        "roofing",
        "contractor"
    ],
    "wof:name":"Thomas Roofing",
    "wof:placetype":"venue"
},
  "geometry": {"coordinates":[-77.946844,39.469728],"type":"Point"}
}