{
  "type": "Feature",
  "properties": {
    "iso:country":"US",
    "sg:address":"1701 19th Ave",
    "sg:city":"Parkersburg",
    "sg:classifiers":[
        {
            "category":"Organizations",
            "subcategory":"Religious Organization",
            "type":"Services"
        }
    ],
    "sg:phone":"+1 304 428 6174",
    "sg:postcode":"26101",
    "sg:province":"WV",
    "wof:name":"First Lutheran Church",
    "wof:placetype":"venue"
},
  "geometry": {"coordinates":[-81.559579,39.240892],"type":"Point"}
}