{
  "type": "Feature",
  "properties": {
    "addr:full":"121 N Main St Moorefield WV 26836",
    "addr:housenumber":"121",
    "addr:postcode":"26836",
    "addr:street":"N Main St",
    "iso:country":"US",
    "sg:address":"121 N Main St",
    "sg:city":"Moorefield",
    "sg:classifiers":[
        {
            "category":"Museum",
            "type":"Entertainment"
        }
    ],
    "sg:phone":"+1 304 538 7115",
    "sg:postcode":"26836",
    "sg:province":"WV",
    "wof:name":"Mc Coy-Mc Mechen Museum Inc",
    "wof:placetype":"venue"
},
  "geometry": {"coordinates":[-78.969746,39.06291],"type":"Point"}
}