{
  "type": "Feature",
  "properties": {
    "iso:country":"US",
    "sg:address":"717 Orchard Dr",
    "sg:city":"Ravenswood",
    "sg:classifiers":[
        {
            "category":"Utilities",
            "subcategory":"Telephone",
            "type":"Services"
        }
    ],
    "sg:phone":"+1 304 273 5158",
    "sg:postcode":"26164",
    "sg:province":"WV",
    "sg:tags":[
        "communications"
    ],
    "wof:name":"Accurate Telecommunication",
    "wof:placetype":"venue"
},
  "geometry": {"coordinates":[-81.764734,38.955444],"type":"Point"}
}