{
  "type": "Feature",
  "properties": {
    "addr:full":"709 Water St Summersville WV 26651",
    "addr:housenumber":"709",
    "addr:postcode":"26651",
    "addr:street":"Water St",
    "iso:country":"US",
    "sg:address":"709 Water St",
    "sg:city":"Summersville",
    "sg:classifiers":[
        {
            "category":"Wholesale",
            "subcategory":"Machinery & Supplies",
            "type":"Manufacturing & Wholesale Goods"
        }
    ],
    "sg:phone":"+1 304 872 6534",
    "sg:postcode":"26651",
    "sg:province":"WV",
    "sg:tags":[
        "vacuum",
        "system",
        "cleaning"
    ],
    "wof:name":"Universal Systems",
    "wof:placetype":"venue"
},
  "geometry": {"coordinates":[-80.850416,38.281837],"type":"Point"}
}