{
  "type": "Feature",
  "properties": {
    "addr:full":"110 Beech St Branchland WV 25506",
    "addr:housenumber":"110",
    "addr:postcode":"25506",
    "addr:street":"Beech St",
    "iso:country":"US",
    "sg:address":"110 Beech St",
    "sg:city":"Branchland",
    "sg:classifiers":[
        {
            "category":"Social Services",
            "subcategory":"Child Care",
            "type":"Services"
        }
    ],
    "sg:phone":"+1 304 824 7002",
    "sg:postcode":"25506",
    "sg:province":"WV",
    "sg:tags":[
        "day"
    ],
    "wof:name":"Lincoln Cnty Fmly Rsrce Netwrk",
    "wof:placetype":"venue"
},
  "geometry": {"coordinates":[-82.190877,38.248618],"type":"Point"}
}