{
  "type": "Feature",
  "properties": {
    "iso:country":"US",
    "sg:address":"334 Randolph Ave",
    "sg:city":"Elkins",
    "sg:classifiers":[
        {
            "category":"Shopping",
            "subcategory":"Bicycles & Sporting Goods",
            "type":"Retail Goods"
        }
    ],
    "sg:phone":"+1 304 636 3157",
    "sg:postcode":"26241",
    "sg:province":"WV",
    "wof:name":"Broughton's Sports",
    "wof:placetype":"venue"
},
  "geometry": {"coordinates":[-79.846254,38.925796],"type":"Point"}
}