{
  "type": "Feature",
  "properties": {
    "addr:full":"400 Winters Rd Chesapeake OH 45619",
    "addr:housenumber":"400",
    "addr:postcode":"45619",
    "addr:street":"Winters Rd",
    "iso:country":"US",
    "sg:address":"400 Winters Rd",
    "sg:city":"Chesapeake",
    "sg:classifiers":[
        {
            "category":"Government",
            "subcategory":"Fire Station",
            "type":"Public Place"
        }
    ],
    "sg:phone":"+1 740 867 5988",
    "sg:postcode":"45619",
    "sg:province":"OH",
    "sg:tags":[
        "department"
    ],
    "wof:name":"Chesapeake Fire Dept",
    "wof:placetype":"venue"
},
  "geometry": {"coordinates":[-82.45727599999999,38.429542],"type":"Point"}
}