{
  "type": "Feature",
  "properties": {
    "iso:country":"US",
    "sg:address":"1401 Bland St",
    "sg:city":"Bluefield",
    "sg:classifiers":[
        {
            "category":"Organizations",
            "subcategory":"Community Association",
            "type":"Services"
        }
    ],
    "sg:phone":"+1 304 324 8911",
    "sg:postcode":"24701",
    "sg:province":"WV",
    "sg:tags":[
        "club"
    ],
    "wof:name":"Bluefield Shrine Club",
    "wof:placetype":"venue"
},
  "geometry": {"coordinates":[-81.22004099999999,37.259826],"type":"Point"}
}