{
  "type": "Feature",
  "properties": {
    "addr:full":"3300 Northfield Dr Charleston WV 25312",
    "addr:housenumber":"3300",
    "addr:postcode":"25312",
    "addr:street":"Northfield Dr",
    "iso:country":"US",
    "sg:address":"3300 Northfield Dr",
    "sg:city":"Charleston",
    "sg:classifiers":[
        {
            "category":"Building & Trades",
            "subcategory":"Construction",
            "type":"Services"
        }
    ],
    "sg:phone":"+1 304 342 8200",
    "sg:postcode":"25312",
    "sg:province":"WV",
    "sg:tags":[
        "excavating",
        "contractor"
    ],
    "wof:name":"Rodney Loftis & Son Contrctng",
    "wof:placetype":"venue"
},
  "geometry": {"coordinates":[-81.65042,38.41243],"type":"Point"}
}