{
  "type": "Feature",
  "properties": {
    "iso:country":"US",
    "sg:address":"301 Eagle Mountain Rd",
    "sg:city":"Charleston",
    "sg:classifiers":[
        {
            "category":"Airport",
            "type":"Transportation"
        }
    ],
    "sg:phone":"+1 304 347 5353",
    "sg:postcode":"25311",
    "sg:province":"WV",
    "sg:tags":[
        "support",
        "airline"
    ],
    "wof:name":"United States Fed Aviation",
    "wof:placetype":"venue"
},
  "geometry": {"coordinates":[-81.59108999999999,38.3628],"type":"Point"}
}