{
  "type": "Feature",
  "properties": {
    "iso:country":"US",
    "sg:address":"137 Main St",
    "sg:city":"Oak Hill",
    "sg:classifiers":[
        {
            "category":"Shopping",
            "subcategory":"Used Merchandise",
            "type":"Retail Goods"
        }
    ],
    "sg:phone":"+1 304 465 4800",
    "sg:postcode":"25901",
    "sg:province":"WV",
    "sg:tags":[
        "shop",
        "consignment"
    ],
    "wof:name":"Consignment Blessings",
    "wof:placetype":"venue"
},
  "geometry": {"coordinates":[-81.14749999999999,37.973374],"type":"Point"}
}