{
  "type": "Feature",
  "properties": {
    "addr:full":"4619 Rte 152 Lavalette WV 25535",
    "addr:housenumber":"4619",
    "addr:postcode":"25535",
    "addr:street":"Rte 152",
    "iso:country":"US",
    "sg:address":"4619 Rte 152",
    "sg:city":"Lavalette",
    "sg:classifiers":[
        {
            "category":"Retail",
            "subcategory":"Auto Repair",
            "type":"Services"
        }
    ],
    "sg:phone":"+1 304 522 1166",
    "sg:postcode":"25535",
    "sg:province":"WV",
    "sg:tags":[
        "automobile",
        "lubrication"
    ],
    "wof:name":"Fast Change Lube & Oil Nc",
    "wof:placetype":"venue"
},
  "geometry": {"coordinates":[-82.454673,38.334939],"type":"Point"}
}