{
  "type": "Feature",
  "properties": {
    "iso:country":"US",
    "sg:address":"9 Craddock Way",
    "sg:city":"Poca",
    "sg:classifiers":[
        {
            "category":"Building & Trades",
            "subcategory":"Construction",
            "type":"Services"
        }
    ],
    "sg:phone":"+1 304 755 7004",
    "sg:postcode":"25159",
    "sg:province":"WV",
    "sg:tags":[
        "home",
        "improvement"
    ],
    "wof:name":"Sears Home Improvement",
    "wof:placetype":"venue"
},
  "geometry": {"coordinates":[-81.820905,38.453859],"type":"Point"}
}