{
  "type": "Feature",
  "properties": {
    "addr:full":"400 Hamilton St Summersville WV 26651",
    "addr:housenumber":"400",
    "addr:postcode":"26651",
    "addr:street":"Hamilton St",
    "iso:country":"US",
    "sg:address":"400 Hamilton St",
    "sg:city":"Summersville",
    "sg:classifiers":[
        {
            "category":"Real Estate",
            "subcategory":"Real Estate Agent",
            "type":"Services"
        }
    ],
    "sg:phone":"+1 304 872 1460",
    "sg:postcode":"26651",
    "sg:province":"WV",
    "wof:name":"Community Square",
    "wof:placetype":"venue"
},
  "geometry": {"coordinates":[-80.85171099999999,38.277575],"type":"Point"}
}