{
  "type": "Feature",
  "properties": {
    "iso:country":"US",
    "sg:address":"3520 Teays Valley Rd",
    "sg:city":"Hurricane",
    "sg:classifiers":[
        {
            "category":"Retail",
            "subcategory":"Animal Services",
            "type":"Services"
        }
    ],
    "sg:phone":"+1 304 562 3000",
    "sg:postcode":"25526",
    "sg:province":"WV",
    "sg:tags":[
        "pet",
        "grooming",
        "washing"
    ],
    "wof:name":"Brookeview Pet Spa",
    "wof:placetype":"venue"
},
  "geometry": {"coordinates":[-81.98616199999999,38.441784],"type":"Point"}
}