{
  "type": "Feature",
  "properties": {
    "addr:full":"2900 Chapline St Wheeling WV 26003",
    "addr:housenumber":"2900",
    "addr:postcode":"26003",
    "addr:street":"Chapline St",
    "iso:country":"US",
    "sg:address":"2900 Chapline St",
    "sg:city":"Wheeling",
    "sg:classifiers":[
        {
            "category":"Retail",
            "subcategory":"Auto Rental",
            "type":"Services"
        }
    ],
    "sg:phone":"+1 304 232 6161",
    "sg:postcode":"26003",
    "sg:province":"WV",
    "sg:tags":[
        "trailer",
        "utility"
    ],
    "wof:name":"First Fleet Leasing & Rentals",
    "wof:placetype":"venue"
},
  "geometry": {"coordinates":[-80.72590700000001,40.050714],"type":"Point"}
}