{
  "type": "Feature",
  "properties": {
    "iso:country":"US",
    "sg:address":"4043 Pennsylvania Ave",
    "sg:city":"Charleston",
    "sg:classifiers":[
        {
            "category":"Professional",
            "type":"Services"
        }
    ],
    "sg:phone":"+1 304 984 3740",
    "sg:postcode":"25302",
    "sg:province":"WV",
    "wof:name":"Bar Inc",
    "wof:placetype":"venue"
},
  "geometry": {"coordinates":[-81.54963600000001,38.402935],"type":"Point"}
}