{
  "type": "Feature",
  "properties": {
    "iso:country":"US",
    "sg:address":"100 River Rd",
    "sg:city":"Barboursville",
    "sg:classifiers":[
        {
            "category":"Local Transit",
            "type":"Transportation"
        }
    ],
    "sg:phone":"+1 304 733 0861",
    "sg:postcode":"25504",
    "sg:province":"WV",
    "wof:name":"Transload America LLC",
    "wof:placetype":"venue"
},
  "geometry": {"coordinates":[-82.30738599999999,38.413204],"type":"Point"}
}