{
  "type": "Feature",
  "properties": {
    "iso:country":"US",
    "sg:address":"301 Main St",
    "sg:city":"Point Pleasant",
    "sg:classifiers":[
        {
            "category":"Food & Beverages",
            "subcategory":"Liquor & Beverages",
            "type":"Retail Goods"
        }
    ],
    "sg:phone":"+1 304 675 2330",
    "sg:postcode":"25550",
    "sg:province":"WV",
    "sg:tags":[
        "alcoholic"
    ],
    "wof:name":"Main Street Liquor Market",
    "wof:placetype":"venue"
},
  "geometry": {"coordinates":[-82.13892199999999,38.842255],"type":"Point"}
}