{
  "type": "Feature",
  "properties": {
    "addr:full":"229 Walnut St Parsons WV 26287",
    "addr:housenumber":"229",
    "addr:postcode":"26287",
    "addr:street":"Walnut St",
    "iso:country":"US",
    "sg:address":"229 Walnut St",
    "sg:city":"Parsons",
    "sg:classifiers":[
        {
            "category":"Health Services",
            "subcategory":"Doctor",
            "type":"Services"
        }
    ],
    "sg:phone":"+1 304 478 4029",
    "sg:postcode":"26287",
    "sg:province":"WV",
    "sg:tags":[
        "medical"
    ],
    "wof:name":"N B Chandran MD",
    "wof:placetype":"venue"
},
  "geometry": {"coordinates":[-79.680233,39.09729],"type":"Point"}
}