{
  "type": "Feature",
  "properties": {
    "iso:country":"US",
    "sg:address":"126 Vale St",
    "sg:city":"Beckley",
    "sg:classifiers":[
        {
            "category":"Shopping",
            "subcategory":"Department Store",
            "type":"Retail Goods"
        }
    ],
    "sg:phone":"+1 304 253 8400",
    "sg:postcode":"25801",
    "sg:province":"WV",
    "sg:tags":[
        "shop"
    ],
    "wof:name":"Value City Department Store",
    "wof:placetype":"venue"
},
  "geometry": {"coordinates":[-81.185973,37.776986],"type":"Point"}
}