{
  "type": "Feature",
  "properties": {
    "addr:full":"4010 Teays Valley Rd Scott Depot WV 25560",
    "addr:housenumber":"4010",
    "addr:postcode":"25560",
    "addr:street":"Teays Valley Rd",
    "iso:country":"US",
    "sg:address":"4010 Teays Valley Rd",
    "sg:city":"Scott Depot",
    "sg:classifiers":[
        {
            "category":"Real Estate",
            "subcategory":"Surveying",
            "type":"Services"
        }
    ],
    "sg:phone":"+1 304 757 8424",
    "sg:postcode":"25560",
    "sg:province":"WV",
    "sg:tags":[
        "surveyor"
    ],
    "wof:name":"Converse Surveying",
    "wof:placetype":"venue"
},
  "geometry": {"coordinates":[-81.939403,38.448915],"type":"Point"}
}