{
  "type": "Feature",
  "properties": {
    "iso:country":"US",
    "sg:address":"426 Main St",
    "sg:city":"Point Pleasant",
    "sg:classifiers":[
        {
            "category":"Recreation",
            "type":"Entertainment"
        }
    ],
    "sg:phone":"+1 304 675 2009",
    "sg:postcode":"25550",
    "sg:province":"WV",
    "sg:tags":[
        "karate",
        "judo",
        "instr"
    ],
    "wof:name":"Kang's Tae KWON Do Academy",
    "wof:placetype":"venue"
},
  "geometry": {"coordinates":[-82.13845499999999,38.843429],"type":"Point"}
}