{
  "type": "Feature",
  "properties": {
    "addr:full":"415 Wilson St Martinsburg WV 25401",
    "addr:housenumber":"415",
    "addr:postcode":"25401",
    "addr:street":"Wilson St",
    "iso:country":"US",
    "sg:address":"415 Wilson St",
    "sg:city":"Martinsburg",
    "sg:classifiers":[
        {
            "category":"Communications",
            "subcategory":"Newspaper",
            "type":"Services"
        }
    ],
    "sg:phone":"+1 304 267 9983",
    "sg:postcode":"25401",
    "sg:province":"WV",
    "wof:name":"Buyers Guide",
    "wof:placetype":"venue"
},
  "geometry": {"coordinates":[-77.971419,39.445844],"type":"Point"}
}