{
  "type": "Feature",
  "properties": {
    "iso:country":"US",
    "sg:address":"211 Swans Ln",
    "sg:city":"St Albans",
    "sg:classifiers":[
        {
            "category":"Retail",
            "subcategory":"Car Wash",
            "type":"Services"
        }
    ],
    "sg:phone":"+1 304 727 7758",
    "sg:postcode":"25177",
    "sg:province":"WV",
    "sg:tags":[
        "polishing",
        "washing"
    ],
    "wof:name":"Superior II Automotive Detail",
    "wof:placetype":"venue"
},
  "geometry": {"coordinates":[-81.85040100000001,38.398873],"type":"Point"}
}