{
  "type": "Feature",
  "properties": {
    "iso:country":"US",
    "sg:address":"4805 Orchard St",
    "sg:city":"Charleston",
    "sg:classifiers":[
        {
            "category":"Retail",
            "subcategory":"Repair Shop",
            "type":"Services"
        }
    ],
    "sg:phone":"+1 304 768 2131",
    "sg:postcode":"25309",
    "sg:province":"WV",
    "sg:tags":[
        "upholsterer"
    ],
    "wof:name":"Dodd's Upholstery",
    "wof:placetype":"venue"
},
  "geometry": {"coordinates":[-81.72510699999999,38.344283],"type":"Point"}
}