{
  "type": "Feature",
  "properties": {
    "iso:country":"US",
    "sg:address":"2628 5th Ave",
    "sg:city":"Huntington",
    "sg:classifiers":[
        {
            "category":"Social Services",
            "subcategory":"Adult Care",
            "type":"Services"
        }
    ],
    "sg:phone":"+1 304 529 2790",
    "sg:postcode":"25702",
    "sg:province":"WV",
    "sg:tags":[
        "residential"
    ],
    "wof:name":"Elite of WV Voca",
    "wof:placetype":"venue"
},
  "geometry": {"coordinates":[-82.406336,38.425916],"type":"Point"}
}