{
  "type": "Feature",
  "properties": {
    "iso:country":"US",
    "sg:address":"224 W King St",
    "sg:city":"Martinsburg",
    "sg:classifiers":[
        {
            "category":"Professional",
            "subcategory":"Computer Services",
            "type":"Services"
        }
    ],
    "sg:phone":"+1 304 260 9520",
    "sg:postcode":"25401",
    "sg:province":"WV",
    "sg:tags":[
        "software",
        "developer"
    ],
    "wof:name":"Butterflynet Inc",
    "wof:placetype":"venue"
},
  "geometry": {"coordinates":[-77.966143,39.456727],"type":"Point"}
}