{
  "type": "Feature",
  "properties": {
    "addr:full":"149 Armstrong St Keyser WV 26726",
    "addr:housenumber":"149",
    "addr:postcode":"26726",
    "addr:street":"Armstrong St",
    "iso:country":"US",
    "sg:address":"149 Armstrong St",
    "sg:city":"Keyser",
    "sg:classifiers":[
        {
            "category":"Professional",
            "subcategory":"Lawyer & Legal Services",
            "type":"Services"
        }
    ],
    "sg:phone":"+1 304 788 1721",
    "sg:postcode":"26726",
    "sg:province":"WV",
    "sg:tags":[
        "plan"
    ],
    "wof:name":"Gary H Athey",
    "wof:placetype":"venue"
},
  "geometry": {"coordinates":[-78.973416,39.440516],"type":"Point"}
}