{
  "type": "Feature",
  "properties": {
    "iso:country":"US",
    "sg:address":"1446 Edwin Miller Blvd",
    "sg:city":"Martinsburg",
    "sg:classifiers":[
        {
            "category":"Personal",
            "subcategory":"Beauty Salon",
            "type":"Services"
        }
    ],
    "sg:phone":"+1 304 263 1137",
    "sg:postcode":"25401",
    "sg:province":"WV",
    "sg:tags":[
        "treatment",
        "skin"
    ],
    "wof:name":"Edge Salon",
    "wof:placetype":"venue"
},
  "geometry": {"coordinates":[-77.957947,39.484921],"type":"Point"}
}