{
  "type": "Feature",
  "properties": {
    "addr:full":"71 Riverside Dr Charleston WV 25303",
    "addr:housenumber":"71",
    "addr:postcode":"25303",
    "addr:street":"Riverside Dr",
    "iso:country":"US",
    "sg:address":"71 Riverside Dr",
    "sg:city":"Charleston",
    "sg:classifiers":[
        {
            "category":"Retail",
            "subcategory":"Laundry & Dry Cleaning",
            "type":"Services"
        }
    ],
    "sg:phone":"+1 304 744 2478",
    "sg:postcode":"25303",
    "sg:province":"WV",
    "sg:tags":[
        "cleaners",
        "rug",
        "carpet"
    ],
    "wof:name":"Carpet Cleaners",
    "wof:placetype":"venue"
},
  "geometry": {"coordinates":[-81.712467,38.36468],"type":"Point"}
}