{
  "type": "Feature",
  "properties": {
    "addr:full":"1611 Kanawha Blvd W Charleston WV 25312",
    "addr:housenumber":"1611",
    "addr:postcode":"25312",
    "addr:street":"Kanawha Blvd W",
    "iso:country":"US",
    "sg:address":"1611 Kanawha Blvd W",
    "sg:city":"Charleston",
    "sg:classifiers":[
        {
            "category":"Restaurant",
            "type":"Food & Drink"
        }
    ],
    "sg:menulink":"http://www.allmenus.com/wv/blue-creek/71713-pizza-hut/menu/",
    "sg:phone":"+1 304 342 2300",
    "sg:postcode":"25312",
    "sg:province":"WV",
    "sg:tags":[
        "american",
        "pizza"
    ],
    "wof:name":"Pizza Hut",
    "wof:placetype":"venue"
},
  "geometry": {"coordinates":[-81.66652999999999,38.366328],"type":"Point"}
}