{
  "type": "Feature",
  "properties": {
    "iso:country":"US",
    "sg:address":"1583 Ridge Rd",
    "sg:city":"Shenandoah Junction",
    "sg:classifiers":[
        {
            "category":"Farming",
            "subcategory":"Orchard",
            "type":"Manufacturing & Wholesale Goods"
        }
    ],
    "sg:phone":"+1 304 876 2920",
    "sg:postcode":"25414",
    "sg:province":"WV",
    "sg:tags":[
        "fruit",
        "tree"
    ],
    "wof:name":"Twin Ridge Orchard Co Inc",
    "wof:placetype":"venue"
},
  "geometry": {"coordinates":[-77.83545700000001,39.214838],"type":"Point"}
}