{
  "type": "Feature",
  "properties": {
    "iso:country":"US",
    "sg:address":"1 Alice Ct",
    "sg:city":"Huntington",
    "sg:classifiers":[
        {
            "category":"Autos & Motor Vehicles",
            "subcategory":"Automobile Sales",
            "type":"Retail Goods"
        }
    ],
    "sg:phone":"+1 304 736 1705",
    "sg:postcode":"25705",
    "sg:province":"WV",
    "sg:tags":[
        "used"
    ],
    "wof:name":"Alice Perry",
    "wof:placetype":"venue"
},
  "geometry": {"coordinates":[-82.345147,38.407903],"type":"Point"}
}