{
  "type": "Feature",
  "properties": {
    "iso:country":"US",
    "sg:address":"1300 Park Ave",
    "sg:city":"Nitro",
    "sg:classifiers":[
        {
            "category":"Education",
            "subcategory":"School",
            "type":"Public Place"
        }
    ],
    "sg:phone":"+1 304 755 4511",
    "sg:postcode":"25143",
    "sg:province":"WV",
    "wof:name":"Nitro High Field House",
    "wof:placetype":"venue"
},
  "geometry": {"coordinates":[-81.845901,38.418628],"type":"Point"}
}