{
  "type": "Feature",
  "properties": {
    "iso:country":"US",
    "sg:address":"1512 Buckhannon Pike",
    "sg:city":"Clarksburg",
    "sg:classifiers":[
        {
            "category":"Shopping",
            "subcategory":"Tobacco",
            "type":"Retail Goods"
        }
    ],
    "sg:phone":"+1 304 326 2295",
    "sg:postcode":"26301",
    "sg:province":"WV",
    "sg:tags":[
        "cigarette",
        "cigar",
        "dealer"
    ],
    "wof:name":"Tobacco Outlet",
    "wof:placetype":"venue"
},
  "geometry": {"coordinates":[-80.322153,39.257386],"type":"Point"}
}