{
  "type": "Feature",
  "properties": {
    "addr:full":"101 Buffalo Creek Rd Huntington WV 25704",
    "addr:housenumber":"101",
    "addr:postcode":"25704",
    "addr:street":"Buffalo Creek Rd",
    "iso:country":"US",
    "sg:address":"101 Buffalo Creek Rd",
    "sg:city":"Huntington",
    "sg:classifiers":[
        {
            "category":"Restaurant",
            "type":"Food & Drink"
        }
    ],
    "sg:phone":"+1 304 429 4133",
    "sg:postcode":"25704",
    "sg:province":"WV",
    "wof:name":"Rocky Tops Pizza",
    "wof:placetype":"venue"
},
  "geometry": {"coordinates":[-82.509349,38.355513],"type":"Point"}
}