{
  "type": "Feature",
  "properties": {
    "iso:country":"US",
    "sg:address":"775 National Rd",
    "sg:city":"Wheeling",
    "sg:classifiers":[
        {
            "category":"Restaurant",
            "type":"Food & Drink"
        }
    ],
    "sg:menulink":"http://www.allmenus.com/wv/wheeling/44193-bob-evans/menu/",
    "sg:phone":"+1 304 232 4139",
    "sg:postcode":"26003",
    "sg:province":"WV",
    "sg:tags":[
        "american"
    ],
    "wof:name":"Bob Evans",
    "wof:placetype":"venue"
},
  "geometry": {"coordinates":[-80.698981,40.075893],"type":"Point"}
}