{
  "type": "Feature",
  "properties": {
    "addr:full":"301 W Burke St Martinsburg WV 25401",
    "addr:housenumber":"301",
    "addr:postcode":"25401",
    "addr:street":"W Burke St",
    "iso:country":"US",
    "sg:address":"301 W Burke St",
    "sg:city":"Martinsburg",
    "sg:classifiers":[
        {
            "category":"Banks & Credit Unions",
            "subcategory":"Bank",
            "type":"Services"
        }
    ],
    "sg:phone":"+1 304 264 5000",
    "sg:postcode":"25401",
    "sg:province":"WV",
    "sg:website":"www.fmbt.com",
    "wof:name":"F & M Bank",
    "wof:placetype":"venue"
},
  "geometry": {"coordinates":[-77.96604000000001,39.457955],"type":"Point"}
}