{
  "type": "Feature",
  "properties": {
    "iso:country":"US",
    "sg:address":"113 E Liberty St",
    "sg:city":"Charles Town",
    "sg:classifiers":[
        {
            "category":"Organizations",
            "subcategory":"Labor Organization",
            "type":"Services"
        }
    ],
    "sg:phone":"+1 304 725 8692",
    "sg:postcode":"25414",
    "sg:province":"WV",
    "wof:name":"Memorial Post 3522 Quartermstr",
    "wof:placetype":"venue"
},
  "geometry": {"coordinates":[-77.859213,39.290196],"type":"Point"}
}