{
  "type": "Feature",
  "properties": {
    "iso:country":"US",
    "sg:address":"1538 2nd Ave",
    "sg:city":"Charleston",
    "sg:classifiers":[
        {
            "category":"Social Services",
            "subcategory":"Child Care",
            "type":"Services"
        }
    ],
    "sg:phone":"+1 304 342 1999",
    "sg:postcode":"25312",
    "sg:province":"WV",
    "sg:tags":[
        "day"
    ],
    "wof:name":"L H Claytor Child Care",
    "wof:placetype":"venue"
},
  "geometry": {"coordinates":[-81.66315299999999,38.366335],"type":"Point"}
}