{
  "type": "Feature",
  "properties": {
    "iso:country":"US",
    "sg:address":"801 Loudon Heights Rd",
    "sg:city":"Charleston",
    "sg:classifiers":[
        {
            "category":"Wholesale",
            "subcategory":"Metals & Minerals",
            "type":"Manufacturing & Wholesale Goods"
        }
    ],
    "sg:phone":"+1 304 343 0555",
    "sg:postcode":"25314",
    "sg:province":"WV",
    "sg:tags":[
        "coal",
        "broker"
    ],
    "wof:name":"Brocoal Inc",
    "wof:placetype":"venue"
},
  "geometry": {"coordinates":[-81.637478,38.340218],"type":"Point"}
}