{
  "type": "Feature",
  "properties": {
    "addr:full":"341 Spruce St Morgantown WV 26505",
    "addr:housenumber":"341",
    "addr:postcode":"26505",
    "addr:street":"Spruce St",
    "iso:country":"US",
    "sg:address":"341 Spruce St",
    "sg:city":"Morgantown",
    "sg:classifiers":[
        {
            "category":"Health Services",
            "subcategory":"Doctor",
            "type":"Services"
        }
    ],
    "sg:phone":"+1 304 292 8234",
    "sg:postcode":"26505",
    "sg:province":"WV",
    "sg:tags":[
        "clinic"
    ],
    "wof:name":"Morgantown Health Right Clinic",
    "wof:placetype":"venue"
},
  "geometry": {"coordinates":[-79.954222,39.630279],"type":"Point"}
}