{
  "type": "Feature",
  "properties": {
    "iso:country":"US",
    "sg:address":"8 River Walk Mall",
    "sg:city":"Charleston",
    "sg:classifiers":[
        {
            "category":"Health Services",
            "subcategory":"Optometrist",
            "type":"Services"
        }
    ],
    "sg:phone":"+1 304 744 9533",
    "sg:postcode":"25303",
    "sg:province":"WV",
    "wof:name":"Eye Care One",
    "wof:placetype":"venue"
},
  "geometry": {"coordinates":[-81.71387799999999,38.363449],"type":"Point"}
}