{
  "type": "Feature",
  "properties": {
    "iso:country":"US",
    "sg:address":"520 Robert C Byrd Dr",
    "sg:city":"Sophia",
    "sg:classifiers":[
        {
            "category":"Shopping",
            "subcategory":"Bicycles & Sporting Goods",
            "type":"Retail Goods"
        }
    ],
    "sg:phone":"+1 304 683 3773",
    "sg:postcode":"25921",
    "sg:province":"WV",
    "sg:tags":[
        "gun",
        "gunsmith"
    ],
    "sg:website":"www.precisionweaponscorp.com",
    "wof:name":"Precision Weapons Corp",
    "wof:placetype":"venue"
},
  "geometry": {"coordinates":[-81.25165699999999,37.720101],"type":"Point"}
}