{
  "type": "Feature",
  "properties": {
    "iso:country":"US",
    "sg:address":"5 Water St",
    "sg:city":"Petersburg",
    "sg:classifiers":[
        {
            "category":"Shopping",
            "type":"Retail Goods"
        }
    ],
    "sg:phone":"+1 304 257 4513",
    "sg:postcode":"26847",
    "sg:province":"WV",
    "sg:tags":[
        "art",
        "gallery",
        "dealer"
    ],
    "wof:name":"Water Street Gallery",
    "wof:placetype":"venue"
},
  "geometry": {"coordinates":[-79.124413,38.992527],"type":"Point"}
}