{
  "type": "Feature",
  "properties": {
    "iso:country":"US",
    "sg:address":"183 E Main St",
    "sg:city":"Salem",
    "sg:classifiers":[
        {
            "category":"Organizations",
            "subcategory":"Religious Organization",
            "type":"Services"
        }
    ],
    "sg:phone":"+1 304 782 3246",
    "sg:postcode":"26426",
    "sg:province":"WV",
    "wof:name":"Salem United Methodist Church",
    "wof:placetype":"venue"
},
  "geometry": {"coordinates":[-80.552688,39.282204],"type":"Point"}
}