{
  "type": "Feature",
  "properties": {
    "iso:country":"US",
    "sg:address":"422 North St",
    "sg:city":"Bluefield",
    "sg:classifiers":[
        {
            "category":"Professional",
            "subcategory":"Management & Consulting",
            "type":"Services"
        }
    ],
    "sg:phone":"+1 304 325 2644",
    "sg:postcode":"24701",
    "sg:province":"WV",
    "wof:name":"Investors Financial Advisors",
    "wof:placetype":"venue"
},
  "geometry": {"coordinates":[-81.22326700000001,37.257317],"type":"Point"}
}