{
  "type": "Feature",
  "properties": {
    "iso:country":"US",
    "sg:address":"501 Harrison St",
    "sg:city":"Princeton",
    "sg:classifiers":[
        {
            "category":"Social Services",
            "type":"Services"
        }
    ],
    "sg:phone":"+1 304 425 3766",
    "sg:postcode":"24740",
    "sg:province":"WV",
    "sg:tags":[
        "organization",
        "welfare"
    ],
    "wof:name":"Wyoming County Senior Citizens",
    "wof:placetype":"venue"
},
  "geometry": {"coordinates":[-81.090102,37.369124],"type":"Point"}
}