{
  "type": "Feature",
  "properties": {
    "iso:country":"US",
    "sg:address":"1389 Saratoga Ave",
    "sg:city":"Star City",
    "sg:classifiers":[
        {
            "category":"Wholesale",
            "subcategory":"Medical Equipment & Supplies",
            "type":"Manufacturing & Wholesale Goods"
        }
    ],
    "sg:phone":"+1 304 598 0860",
    "sg:postcode":"26505",
    "sg:province":"WV",
    "sg:tags":[
        "hospital"
    ],
    "wof:name":"Health Care Solutions",
    "wof:placetype":"venue"
},
  "geometry": {"coordinates":[-79.984948,39.653523],"type":"Point"}
}