{
  "type": "Feature",
  "properties": {
    "iso:country":"US",
    "sg:address":"209 Ragland Rd",
    "sg:city":"Beckley",
    "sg:classifiers":[
        {
            "category":"Wholesale",
            "subcategory":"Electrical",
            "type":"Manufacturing & Wholesale Goods"
        }
    ],
    "sg:phone":"+1 304 253 0669",
    "sg:postcode":"25801",
    "sg:province":"WV",
    "sg:tags":[
        "fire",
        "equipment",
        "protection"
    ],
    "wof:name":"FIRE Safety Products Inc",
    "wof:placetype":"venue"
},
  "geometry": {"coordinates":[-81.180296,37.807562],"type":"Point"}
}