{
  "type": "Feature",
  "properties": {
    "addr:full":"731 5th St W Huntington WV 25701",
    "addr:housenumber":"731",
    "addr:postcode":"25701",
    "addr:street":"5Th St W",
    "iso:country":"US",
    "sg:address":"731 5th St W",
    "sg:city":"Huntington",
    "sg:classifiers":[
        {
            "category":"Education",
            "subcategory":"Dance Studio",
            "type":"Public Place"
        }
    ],
    "sg:phone":"+1 304 697 2840",
    "sg:postcode":"25701",
    "sg:province":"WV",
    "sg:tags":[
        "instruction",
        "dancing"
    ],
    "wof:name":"Nancy's School Of Dance",
    "wof:placetype":"venue"
},
  "geometry": {"coordinates":[-82.462622,38.412845],"type":"Point"}
}