{
  "type": "Feature",
  "properties": {
    "iso:country":"US",
    "sg:address":"4260 Pisgah Rd",
    "sg:city":"Princeton",
    "sg:classifiers":[
        {
            "category":"Building & Trades",
            "subcategory":"Construction",
            "type":"Services"
        }
    ],
    "sg:phone":"+1 800 363 3809",
    "sg:postcode":"24740",
    "sg:province":"WV",
    "sg:tags":[
        "driveway",
        "contractor"
    ],
    "wof:name":"K&W Paving",
    "wof:placetype":"venue"
},
  "geometry": {"coordinates":[-81.074093,37.368734],"type":"Point"}
}