{
  "type": "Feature",
  "properties": {
    "iso:country":"US",
    "sg:address":"601 Pyles Ave",
    "sg:city":"Mannington",
    "sg:classifiers":[
        {
            "category":"Retail",
            "subcategory":"Animal Services",
            "type":"Services"
        }
    ],
    "sg:phone":"+1 304 986 2985",
    "sg:postcode":"26582",
    "sg:province":"WV",
    "sg:tags":[
        "pet",
        "grooming",
        "washing"
    ],
    "wof:name":"Pets Inn",
    "wof:placetype":"venue"
},
  "geometry": {"coordinates":[-80.345676,39.539437],"type":"Point"}
}