{
  "type": "Feature",
  "properties": {
    "iso:country":"US",
    "sg:address":"607 Ashley Ln",
    "sg:city":"Summersville",
    "sg:classifiers":[
        {
            "category":"Organizations",
            "subcategory":"Professional Association",
            "type":"Services"
        }
    ],
    "sg:phone":"+1 304 872 6794",
    "sg:postcode":"26651",
    "sg:province":"WV",
    "wof:name":"West Virginia Assn Ldscp N",
    "wof:placetype":"venue"
},
  "geometry": {"coordinates":[-80.836377,38.302061],"type":"Point"}
}