{
  "type": "Feature",
  "properties": {
    "iso:country":"US",
    "sg:address":"100 Princeton Ave",
    "sg:city":"Bluefield",
    "sg:classifiers":[
        {
            "category":"Retail",
            "subcategory":"Repair Shop",
            "type":"Services"
        }
    ],
    "sg:phone":"+1 304 325 9262",
    "sg:postcode":"24701",
    "sg:province":"WV",
    "sg:tags":[
        "equipment",
        "hydraulic"
    ],
    "wof:name":"Larry's Pneumatic Svc",
    "wof:placetype":"venue"
},
  "geometry": {"coordinates":[-81.225579,37.269014],"type":"Point"}
}