{
  "type": "Feature",
  "properties": {
    "iso:country":"US",
    "sg:address":"101 Lauren Ave",
    "sg:city":"Beckley",
    "sg:classifiers":[
        {
            "category":"Professional",
            "type":"Services"
        }
    ],
    "sg:phone":"+1 304 255 4333",
    "sg:postcode":"25801",
    "sg:province":"WV",
    "wof:name":"S&S Scale Co LLC",
    "wof:placetype":"venue"
},
  "geometry": {"coordinates":[-81.16739099999999,37.777896],"type":"Point"}
}