{
  "type": "Feature",
  "properties": {
    "iso:country":"US",
    "sg:address":"301 Courtney Dr",
    "sg:city":"Lewisburg",
    "sg:classifiers":[
        {
            "category":"Education",
            "subcategory":"Library",
            "type":"Public Place"
        }
    ],
    "sg:phone":"+1 304 645 2350",
    "sg:postcode":"24901",
    "sg:province":"WV",
    "wof:name":"Greenbrier County Library",
    "wof:placetype":"venue"
},
  "geometry": {"coordinates":[-80.44774700000001,37.803235],"type":"Point"}
}