{
  "type": "Feature",
  "properties": {
    "iso:country":"US",
    "sg:address":"1600 Jefferson St",
    "sg:city":"Bluefield",
    "sg:classifiers":[
        {
            "category":"Bars & Pubs",
            "type":"Food & Drink"
        }
    ],
    "sg:phone":"+1 304 324 8770",
    "sg:postcode":"24701",
    "sg:province":"WV",
    "wof:name":"Neons Bar",
    "wof:placetype":"venue"
},
  "geometry": {"coordinates":[-81.22162299999999,37.258055],"type":"Point"}
}