{
  "type": "Feature",
  "properties": {
    "addr:full":"147 W Main St Salem WV 26426",
    "addr:housenumber":"147",
    "addr:postcode":"26426",
    "addr:street":"W Main St",
    "iso:country":"US",
    "sg:address":"147 W Main St",
    "sg:city":"Salem",
    "sg:classifiers":[
        {
            "category":"Government",
            "subcategory":"Post Office",
            "type":"Public Place"
        }
    ],
    "sg:phone":"+1 304 782 1400",
    "sg:postcode":"26426",
    "sg:province":"WV",
    "sg:tags":[
        "postal",
        "us"
    ],
    "wof:name":"US Post Office",
    "wof:placetype":"venue"
},
  "geometry": {"coordinates":[-80.560637,39.282917],"type":"Point"}
}