{
  "type": "Feature",
  "properties": {
    "iso:country":"US",
    "sg:address":"609 Grandview Pt",
    "sg:city":"Dunbar",
    "sg:classifiers":[
        {
            "category":"Travel",
            "subcategory":"Travel Agent",
            "type":"Entertainment"
        }
    ],
    "sg:phone":"+1 304 768 6398",
    "sg:postcode":"25064",
    "sg:province":"WV",
    "sg:tags":[
        "agency"
    ],
    "wof:name":"Yatra Travels LLC",
    "wof:placetype":"venue"
},
  "geometry": {"coordinates":[-81.743619,38.370295],"type":"Point"}
}