{
  "type": "Feature",
  "properties": {
    "iso:country":"US",
    "sg:address":"207 S Elm St",
    "sg:city":"Moorefield",
    "sg:classifiers":[
        {
            "category":"Personal",
            "subcategory":"Beauty Salon",
            "type":"Services"
        }
    ],
    "sg:phone":"+1 304 538 6900",
    "sg:postcode":"26836",
    "sg:province":"WV",
    "wof:name":"Anna's Beauty Salon",
    "wof:placetype":"venue"
},
  "geometry": {"coordinates":[-78.967375,39.058719],"type":"Point"}
}