{
  "type": "Feature",
  "properties": {
    "iso:country":"US",
    "sg:address":"223 Putnam St",
    "sg:city":"Marietta",
    "sg:classifiers":[
        {
            "category":"Government",
            "subcategory":"Office",
            "type":"Public Place"
        }
    ],
    "sg:phone":"+1 740 373 6623",
    "sg:postcode":"45750",
    "sg:province":"OH",
    "wof:name":"Washington County Commissioner",
    "wof:placetype":"venue"
},
  "geometry": {"coordinates":[-81.453597,39.416061],"type":"Point"}
}