{
  "type": "Feature",
  "properties": {
    "addr:full":"401 6th Ave Montgomery WV 25136",
    "addr:housenumber":"401",
    "addr:postcode":"25136",
    "addr:street":"6Th Ave",
    "iso:country":"US",
    "sg:address":"401 6th Ave",
    "sg:city":"Montgomery",
    "sg:classifiers":[
        {
            "category":"Health Services",
            "subcategory":"Doctor",
            "type":"Services"
        }
    ],
    "sg:phone":"+1 304 442 2585",
    "sg:postcode":"25136",
    "sg:province":"WV",
    "sg:tags":[
        "medical"
    ],
    "wof:name":"Tony Haber MD",
    "wof:placetype":"venue"
},
  "geometry": {"coordinates":[-81.32391200000001,38.182884],"type":"Point"}
}