{
  "type": "Feature",
  "properties": {
    "iso:country":"US",
    "sg:address":"5088 Washington St W",
    "sg:city":"Charleston",
    "sg:classifiers":[
        {
            "category":"Professional",
            "subcategory":"Engineering",
            "type":"Services"
        }
    ],
    "sg:phone":"+1 304 769 0821",
    "sg:postcode":"25313",
    "sg:province":"WV",
    "wof:name":"Michael Baker Jr Inc",
    "wof:placetype":"venue"
},
  "geometry": {"coordinates":[-81.782461,38.420832],"type":"Point"}
}