{
  "type": "Feature",
  "properties": {
    "addr:full":"406 Parkersburg Rd Spencer WV 25276",
    "addr:housenumber":"406",
    "addr:postcode":"25276",
    "addr:street":"Parkersburg Rd",
    "iso:country":"US",
    "sg:address":"406 Parkersburg Rd",
    "sg:city":"Spencer",
    "sg:classifiers":[
        {
            "category":"Organizations",
            "subcategory":"Religious Organization",
            "type":"Services"
        }
    ],
    "sg:phone":"+1 304 927 2393",
    "sg:postcode":"25276",
    "sg:province":"WV",
    "wof:name":"Presbyterian Church",
    "wof:placetype":"venue"
},
  "geometry": {"coordinates":[-81.36240100000001,38.814316],"type":"Point"}
}