{
  "type": "Feature",
  "properties": {
    "iso:country":"US",
    "sg:address":"1341 Old Courthouse Sq",
    "sg:city":"Martinsburg",
    "sg:classifiers":[
        {
            "category":"Real Estate",
            "subcategory":"Real Estate Agent",
            "type":"Services"
        }
    ],
    "sg:phone":"+1 304 267 0984",
    "sg:postcode":"25401",
    "sg:province":"WV",
    "sg:tags":[
        "agency",
        "rental"
    ],
    "wof:name":"Rentals Purchase Prime Time",
    "wof:placetype":"venue"
},
  "geometry": {"coordinates":[-77.95693799999999,39.47391],"type":"Point"}
}