{
  "type": "Feature",
  "properties": {
    "addr:full":"230 Capitol St Charleston WV 25301",
    "addr:housenumber":"230",
    "addr:postcode":"25301",
    "addr:street":"Capitol St",
    "iso:country":"US",
    "sg:address":"230 Capitol St",
    "sg:city":"Charleston",
    "sg:classifiers":[
        {
            "category":"Professional",
            "subcategory":"Lawyer & Legal Services",
            "type":"Services"
        }
    ],
    "sg:phone":"+1 304 343 9959",
    "sg:postcode":"25301",
    "sg:province":"WV",
    "wof:name":"Shawn Anthony Taylor",
    "wof:placetype":"venue"
},
  "geometry": {"coordinates":[-81.633504,38.350631],"type":"Point"}
}