{
  "type": "Feature",
  "properties": {
    "iso:country":"US",
    "sg:address":"306 9th St E",
    "sg:city":"Belle",
    "sg:classifiers":[
        {
            "category":"Organizations",
            "subcategory":"Religious Organization",
            "type":"Services"
        }
    ],
    "sg:phone":"+1 304 949 2568",
    "sg:postcode":"25015",
    "sg:province":"WV",
    "wof:name":"Belle Churh of Nazarene",
    "wof:placetype":"venue"
},
  "geometry": {"coordinates":[-81.537243,38.230936],"type":"Point"}
}