{
  "type": "Feature",
  "properties": {
    "iso:country":"US",
    "sg:address":"211 Ferndale Dr",
    "sg:city":"Charleston",
    "sg:classifiers":[
        {
            "category":"Retail",
            "subcategory":"Repair Shop",
            "type":"Services"
        },
        {
            "category":"Building & Trades",
            "subcategory":"Construction",
            "type":"Services"
        }
    ],
    "sg:phone":"+1 304 345 5116",
    "sg:postcode":"25302",
    "sg:province":"WV",
    "sg:tags":[
        "refinishing",
        "bathtub",
        "sink",
        "contractor"
    ],
    "wof:name":"Tri State Tub & Tile Refinishi",
    "wof:placetype":"venue"
},
  "geometry": {"coordinates":[-81.599755,38.388636],"type":"Point"}
}