{
  "type": "Feature",
  "properties": {
    "iso:country":"US",
    "sg:address":"238 Maple Acres Rd",
    "sg:city":"Princeton",
    "sg:classifiers":[
        {
            "category":"Building & Trades",
            "subcategory":"Construction",
            "type":"Services"
        }
    ],
    "sg:phone":"+1 304 425 5494",
    "sg:postcode":"24740",
    "sg:province":"WV",
    "sg:tags":[
        "heavy"
    ],
    "wof:name":"Associated Cnstr & Trckg",
    "wof:placetype":"venue"
},
  "geometry": {"coordinates":[-81.154647,37.34315],"type":"Point"}
}