{
  "type": "Feature",
  "properties": {
    "addr:full":"179 Plaza Ct Kingwood WV 26537",
    "addr:housenumber":"179",
    "addr:postcode":"26537",
    "addr:street":"Plaza Ct",
    "iso:country":"US",
    "sg:address":"179 Plaza Ct",
    "sg:city":"Kingwood",
    "sg:classifiers":[
        {
            "category":"Wholesale",
            "subcategory":"Farm Supplies",
            "type":"Manufacturing & Wholesale Goods"
        },
        {
            "category":"Wholesale",
            "subcategory":"Machinery & Supplies",
            "type":"Manufacturing & Wholesale Goods"
        }
    ],
    "sg:phone":"+1 304 329 3793",
    "sg:postcode":"26537",
    "sg:province":"WV",
    "sg:tags":[
        "baling",
        "equipment"
    ],
    "sg:website":"http://www.mytscstore.com",
    "wof:name":"Tractor Supply 206",
    "wof:placetype":"venue"
},
  "geometry": {"coordinates":[-79.668324,39.468586],"type":"Point"}
}