{
  "type": "Feature",
  "properties": {
    "addr:full":"602 Temple St Hinton WV 25951",
    "addr:housenumber":"602",
    "addr:postcode":"25951",
    "addr:street":"Temple St",
    "iso:country":"US",
    "sg:address":"602 Temple St",
    "sg:city":"Hinton",
    "sg:classifiers":[
        {
            "category":"Government",
            "subcategory":"Office",
            "type":"Public Place"
        }
    ],
    "sg:phone":"+1 304 466 6026",
    "sg:postcode":"25951",
    "sg:province":"WV",
    "wof:name":"Summers County Floodplain Ofcr",
    "wof:placetype":"venue"
},
  "geometry": {"coordinates":[-80.885487,37.675798],"type":"Point"}
}