{
  "type": "Feature",
  "properties": {
    "addr:full":"602 Clearview Hts Charleston WV 25312",
    "addr:housenumber":"602",
    "addr:postcode":"25312",
    "addr:street":"Clearview Hts",
    "iso:country":"US",
    "sg:address":"602 Clearview Hts",
    "sg:city":"Charleston",
    "sg:classifiers":[
        {
            "category":"Freight",
            "type":"Transportation"
        }
    ],
    "sg:phone":"+1 304 984 0000",
    "sg:postcode":"25312",
    "sg:province":"WV",
    "sg:tags":[
        "general"
    ],
    "wof:name":"Sissonville Mini Storage",
    "wof:placetype":"venue"
},
  "geometry": {"coordinates":[-81.670633,38.478829],"type":"Point"}
}