{
  "type": "Feature",
  "properties": {
    "iso:country":"US",
    "sg:address":"1010 Market St",
    "sg:city":"Parkersburg",
    "sg:classifiers":[
        {
            "category":"Organizations",
            "subcategory":"Community Association",
            "type":"Services"
        }
    ],
    "sg:phone":"+1 304 428 0331",
    "sg:postcode":"26101",
    "sg:province":"WV",
    "wof:name":"Knights Columbus Council 594",
    "wof:placetype":"venue"
},
  "geometry": {"coordinates":[-81.554996,39.268713],"type":"Point"}
}