{
  "type": "Feature",
  "properties": {
    "addr:full":"3548 US Hwy 60 Barboursville WV 25504",
    "addr:housenumber":"3548",
    "addr:postcode":"25504",
    "addr:street":"Us Hwy 60",
    "iso:country":"US",
    "sg:address":"3548 US Hwy 60",
    "sg:city":"Barboursville",
    "sg:classifiers":[
        {
            "category":"Shopping",
            "type":"Retail Goods"
        }
    ],
    "sg:phone":"+1 304 733 6348",
    "sg:postcode":"25504",
    "sg:province":"WV",
    "sg:tags":[
        "cards",
        "sport",
        "baseball",
        "memorabilia"
    ],
    "wof:name":"Parkers Players",
    "wof:placetype":"venue"
},
  "geometry": {"coordinates":[-82.311425,38.412825],"type":"Point"}
}