{
  "type": "Feature",
  "properties": {
    "iso:country":"US",
    "sg:address":"414 Kearneysville Pke.",
    "sg:city":"Kearneysville",
    "sg:classifiers":[
        {
            "category":"Building & Trades",
            "subcategory":"Landscaping Services",
            "type":"Services"
        },
        {
            "category":"Professional",
            "subcategory":"Advertising",
            "type":"Services"
        },
        {
            "category":"Building & Trades",
            "subcategory":"Construction",
            "type":"Services"
        }
    ],
    "sg:phone":"+1 304 268 4149",
    "sg:postcode":"25430",
    "sg:province":"WV",
    "sg:tags":[
        "lawn",
        "outdoor",
        "handyman",
        "contractor",
        "painting",
        "landscape"
    ],
    "wof:name":"Jimbo's Landscaping & Design",
    "wof:placetype":"venue"
},
  "geometry": {"coordinates":[-77.88136799999999,39.391215],"type":"Point"}
}