{
  "type": "Feature",
  "properties": {
    "addr:full":"5074 Elk River Rd Elkview WV 25071",
    "addr:housenumber":"5074",
    "addr:postcode":"25071",
    "addr:street":"Elk River Rd",
    "iso:country":"US",
    "sg:address":"5074 Elk River Rd",
    "sg:city":"Elkview",
    "sg:classifiers":[
        {
            "category":"Organizations",
            "subcategory":"Community Association",
            "type":"Services"
        }
    ],
    "sg:phone":"+1 304 965 3246",
    "sg:postcode":"25071",
    "sg:province":"WV",
    "sg:tags":[
        "military"
    ],
    "wof:name":"Disabled American Veterans",
    "wof:placetype":"venue"
},
  "geometry": {"coordinates":[-81.48885,38.437951],"type":"Point"}
}