{
  "type": "Feature",
  "properties": {
    "iso:country":"US",
    "sg:address":"401 Buffalo St",
    "sg:city":"Mannington",
    "sg:classifiers":[
        {
            "category":"Autos & Motor Vehicles",
            "subcategory":"Automobile Sales",
            "type":"Retail Goods"
        }
    ],
    "sg:phone":"+1 304 986 3462",
    "sg:postcode":"26582",
    "sg:province":"WV",
    "sg:tags":[
        "used"
    ],
    "wof:name":"Carnes Auto Brokers",
    "wof:placetype":"venue"
},
  "geometry": {"coordinates":[-80.349768,39.52966],"type":"Point"}
}