{
  "type": "Feature",
  "properties": {
    "iso:country":"US",
    "sg:address":"1617 Washington St W",
    "sg:city":"Charleston",
    "sg:classifiers":[
        {
            "category":"Restaurant",
            "type":"Food & Drink"
        }
    ],
    "sg:phone":"+1 304 342 1123",
    "sg:postcode":"25312",
    "sg:province":"WV",
    "sg:tags":[
        "eating"
    ],
    "wof:name":"West Side Cafe",
    "wof:placetype":"venue"
},
  "geometry": {"coordinates":[-81.661962,38.372386],"type":"Point"}
}