{
  "type": "Feature",
  "properties": {
    "addr:full":"3306 Avery St Parkersburg WV 26104",
    "addr:housenumber":"3306",
    "addr:postcode":"26104",
    "addr:street":"Avery St",
    "iso:country":"US",
    "sg:address":"3306 Avery St",
    "sg:city":"Parkersburg",
    "sg:classifiers":[
        {
            "category":"Real Estate",
            "subcategory":"Real Estate Agent",
            "type":"Services"
        }
    ],
    "sg:phone":"+1 304 420 9064",
    "sg:postcode":"26104",
    "sg:province":"WV",
    "wof:name":"McDaniel & Rice",
    "wof:placetype":"venue"
},
  "geometry": {"coordinates":[-81.540925,39.288846],"type":"Point"}
}