{
  "type": "Feature",
  "properties": {
    "iso:country":"US",
    "sg:address":"202 High St",
    "sg:city":"Saint Marys",
    "sg:classifiers":[
        {
            "category":"Food & Beverages",
            "subcategory":"Liquor & Beverages",
            "type":"Retail Goods"
        }
    ],
    "sg:phone":"+1 304 684 7111",
    "sg:postcode":"26170",
    "sg:province":"WV",
    "sg:tags":[
        "convenient",
        "market"
    ],
    "wof:name":"Economy Food Market",
    "wof:placetype":"venue"
},
  "geometry": {"coordinates":[-81.201347,39.396183],"type":"Point"}
}