{
  "type": "Feature",
  "properties": {
    "iso:country":"US",
    "sg:address":"500 W Pike St",
    "sg:city":"Clarksburg",
    "sg:classifiers":[
        {
            "category":"Government",
            "subcategory":"Court House",
            "type":"Public Place"
        }
    ],
    "sg:phone":"+1 304 622 8513",
    "sg:postcode":"26301",
    "sg:province":"WV",
    "sg:tags":[
        "federal"
    ],
    "wof:name":"US District Court Clerk",
    "wof:placetype":"venue"
},
  "geometry": {"coordinates":[-80.343046,39.281406],"type":"Point"}
}