{
  "type": "Feature",
  "properties": {
    "iso:country":"US",
    "sg:address":"364 Riverview Ave",
    "sg:city":"Logan",
    "sg:classifiers":[
        {
            "category":"Health Services",
            "subcategory":"Health Practitioner",
            "type":"Services"
        }
    ],
    "sg:phone":"+1 304 752 4443",
    "sg:postcode":"25601",
    "sg:province":"WV",
    "sg:tags":[
        "therapist",
        "physical"
    ],
    "wof:name":"Logan Physical Therapy",
    "wof:placetype":"venue"
},
  "geometry": {"coordinates":[-82.00823699999999,37.847132],"type":"Point"}
}