{
  "type": "Feature",
  "properties": {
    "iso:country":"US",
    "sg:address":"207 S Price St",
    "sg:city":"Kingwood",
    "sg:classifiers":[
        {
            "category":"Education",
            "subcategory":"School",
            "type":"Public Place"
        }
    ],
    "sg:phone":"+1 304 329 1034",
    "sg:postcode":"26537",
    "sg:province":"WV",
    "sg:tags":[
        "elementary"
    ],
    "wof:name":"Kingwood Elementary School",
    "wof:placetype":"venue"
},
  "geometry": {"coordinates":[-79.687044,39.467782],"type":"Point"}
}