{
  "type": "Feature",
  "properties": {
    "addr:full":"309 Beckley Crossing Shpg Center Beckley WV 25801",
    "addr:housenumber":"309",
    "addr:postcode":"25801",
    "addr:street":"Beckley Crossing Shpg Center",
    "iso:country":"US",
    "sg:address":"309 Beckley Crossing Shpg Center",
    "sg:city":"Beckley",
    "sg:classifiers":[
        {
            "category":"Banks & Credit Unions",
            "subcategory":"Bank",
            "type":"Services"
        }
    ],
    "sg:phone":"+1 304 256 0100",
    "sg:postcode":"25801",
    "sg:province":"WV",
    "sg:tags":[
        "loan",
        "real estate"
    ],
    "wof:name":"American General Finance Inc",
    "wof:placetype":"venue"
},
  "geometry": {"coordinates":[-81.18252200000001,37.802297],"type":"Point"}
}