{
  "type": "Feature",
  "properties": {
    "addr:full":"3334 Main St Weirton WV 26062",
    "addr:housenumber":"3334",
    "addr:postcode":"26062",
    "addr:street":"Main St",
    "iso:country":"US",
    "sg:address":"3334 Main St",
    "sg:city":"Weirton",
    "sg:classifiers":[
        {
            "category":"Professional",
            "subcategory":"Lawyer & Legal Services",
            "type":"Services"
        }
    ],
    "sg:phone":"+1 304 748 0868",
    "sg:postcode":"26062",
    "sg:province":"WV",
    "sg:tags":[
        "attorney"
    ],
    "wof:name":"William J Moore",
    "wof:placetype":"venue"
},
  "geometry": {"coordinates":[-80.58869,40.403921],"type":"Point"}
}