{
  "type": "Feature",
  "properties": {
    "iso:country":"US",
    "sg:address":"3412 Greenview Dr",
    "sg:city":"Parkersburg",
    "sg:classifiers":[
        {
            "category":"Freight",
            "type":"Transportation"
        }
    ],
    "sg:phone":"+1 304 424 5299",
    "sg:postcode":"26104",
    "sg:province":"WV",
    "sg:tags":[
        "trucking"
    ],
    "wof:name":"CJM Transportation",
    "wof:placetype":"venue"
},
  "geometry": {"coordinates":[-81.510244,39.282449],"type":"Point"}
}