{
  "type": "Feature",
  "properties": {
    "iso:country":"US",
    "sg:address":"200 State Rte 98",
    "sg:city":"Clarksburg",
    "sg:classifiers":[
        {
            "category":"Health Services",
            "subcategory":"Doctor",
            "type":"Services"
        }
    ],
    "sg:phone":"+1 304 622 0704",
    "sg:postcode":"26301",
    "sg:province":"WV",
    "sg:tags":[
        "physician",
        "medical",
        "surgeon"
    ],
    "wof:name":"Stoneybrooke Health Care",
    "wof:placetype":"venue"
},
  "geometry": {"coordinates":[-80.33049099999999,39.264682],"type":"Point"}
}