{
  "type": "Feature",
  "properties": {
    "iso:country":"US",
    "sg:address":"112 Stone Dr",
    "sg:city":"Elkview",
    "sg:classifiers":[
        {
            "category":"Retail",
            "subcategory":"Repair Shop",
            "type":"Services"
        }
    ],
    "sg:phone":"+1 304 965 1609",
    "sg:postcode":"25071",
    "sg:province":"WV",
    "wof:name":"Frame & Leany Resources",
    "wof:placetype":"venue"
},
  "geometry": {"coordinates":[-81.485013,38.39919],"type":"Point"}
}