{
  "type": "Feature",
  "properties": {
    "iso:country":"US",
    "sg:address":"211 W Washington St",
    "sg:city":"Charles Town",
    "sg:classifiers":[
        {
            "category":"Professional",
            "subcategory":"Lawyer & Legal Services",
            "type":"Services"
        }
    ],
    "sg:phone":"+1 304 728 7718",
    "sg:postcode":"25414",
    "sg:province":"WV",
    "sg:tags":[
        "attorney"
    ],
    "wof:name":"Bankruptcy Clinic",
    "wof:placetype":"venue"
},
  "geometry": {"coordinates":[-77.8091,39.430039],"type":"Point"}
}