{
  "type": "Feature",
  "properties": {
    "iso:country":"US",
    "sg:address":"878 E Main St",
    "sg:city":"Milton",
    "sg:classifiers":[
        {
            "category":"Real Estate",
            "subcategory":"Real Estate Operator",
            "type":"Services"
        }
    ],
    "sg:phone":"+1 304 743 6301",
    "sg:postcode":"25541",
    "sg:province":"WV",
    "sg:tags":[
        "mobile",
        "home",
        "site"
    ],
    "wof:name":"Tommy Harbour",
    "wof:placetype":"venue"
},
  "geometry": {"coordinates":[-82.13064799999999,38.434583],"type":"Point"}
}