{
  "type": "Feature",
  "properties": {
    "iso:country":"US",
    "sg:address":"724 Indiana Ave",
    "sg:city":"Charleston",
    "sg:classifiers":[
        {
            "category":"Professional",
            "subcategory":"Business Services",
            "type":"Services"
        }
    ],
    "sg:phone":"+1 304 343 5636",
    "sg:postcode":"25302",
    "sg:province":"WV",
    "sg:tags":[
        "paging",
        "answering"
    ],
    "wof:name":"Telephone Answering-Sincerely",
    "wof:placetype":"venue"
},
  "geometry": {"coordinates":[-81.639391,38.361313],"type":"Point"}
}