{
  "type": "Feature",
  "properties": {
    "addr:full":"804 Crim Ave Belington WV 26250",
    "addr:housenumber":"804",
    "addr:postcode":"26250",
    "addr:street":"Crim Ave",
    "iso:country":"US",
    "sg:address":"804 Crim Ave",
    "sg:city":"Belington",
    "sg:classifiers":[
        {
            "category":"Autos & Motor Vehicles",
            "subcategory":"Auto Supplies",
            "type":"Retail Goods"
        }
    ],
    "sg:phone":"+1 304 823 2766",
    "sg:postcode":"26250",
    "sg:province":"WV",
    "sg:tags":[
        "automobile",
        "parts"
    ],
    "wof:name":"Morgan's Auto Parts",
    "wof:placetype":"venue"
},
  "geometry": {"coordinates":[-79.938824,39.013215],"type":"Point"}
}