{
  "type": "Feature",
  "properties": {
    "iso:country":"US",
    "sg:address":"123 W Main St",
    "sg:city":"Ansted",
    "sg:classifiers":[
        {
            "category":"Manufacturing",
            "subcategory":"Printing",
            "type":"Manufacturing & Wholesale Goods"
        }
    ],
    "sg:phone":"+1 304 658 4454",
    "sg:postcode":"25812",
    "sg:province":"WV",
    "sg:tags":[
        "screen"
    ],
    "wof:name":"L & S Designs",
    "wof:placetype":"venue"
},
  "geometry": {"coordinates":[-81.104195,38.132795],"type":"Point"}
}