{
  "type": "Feature",
  "properties": {
    "iso:country":"US",
    "sg:address":"611 Tennessee Ave",
    "sg:city":"Charleston",
    "sg:classifiers":[
        {
            "category":"Home & Garden",
            "subcategory":"Building Materials",
            "type":"Retail Goods"
        }
    ],
    "sg:phone":"+1 304 766 6800",
    "sg:postcode":"25302",
    "sg:province":"WV",
    "sg:tags":[
        "door"
    ],
    "wof:name":"Pella Window & Door Co",
    "wof:placetype":"venue"
},
  "geometry": {"coordinates":[-81.641276,38.36101],"type":"Point"}
}