{
  "type": "Feature",
  "properties": {
    "iso:country":"US",
    "sg:address":"1901 19th St",
    "sg:city":"Nitro",
    "sg:classifiers":[
        {
            "category":"Home & Garden",
            "subcategory":"Building Materials",
            "type":"Retail Goods"
        }
    ],
    "sg:phone":"+1 304 727 8942",
    "sg:postcode":"25143",
    "sg:province":"WV",
    "wof:name":"Building Center",
    "wof:placetype":"venue"
},
  "geometry": {"coordinates":[-81.842896,38.420907],"type":"Point"}
}