{
  "type": "Feature",
  "properties": {
    "addr:full":"3510 Murdoch Ave Parkersburg WV 26101",
    "addr:housenumber":"3510",
    "addr:postcode":"26101",
    "addr:street":"Murdoch Ave",
    "iso:country":"US",
    "sg:address":"3510 Murdoch Ave",
    "sg:city":"Parkersburg",
    "sg:classifiers":[
        {
            "category":"Restaurant",
            "type":"Food & Drink"
        }
    ],
    "sg:phone":"+1 304 865 4320",
    "sg:postcode":"26101",
    "sg:province":"WV",
    "wof:name":"Backporch Grill",
    "wof:placetype":"venue"
},
  "geometry": {"coordinates":[-81.546147,39.293177],"type":"Point"}
}