{
  "type": "Feature",
  "properties": {
    "iso:country":"US",
    "sg:address":"50 Carmel Rd",
    "sg:city":"Wheeling",
    "sg:classifiers":[
        {
            "category":"Restaurant",
            "type":"Food & Drink"
        }
    ],
    "sg:menulink":"http://www.allmenus.com/wv/wheeling/274050-ye-olde-alpha/menu/",
    "sg:phone":"+1 304 242 1090",
    "sg:postcode":"26003",
    "sg:province":"WV",
    "sg:tags":[
        "american"
    ],
    "wof:name":"Ye Olde Alpha",
    "wof:placetype":"venue"
},
  "geometry": {"coordinates":[-80.682605,40.077514],"type":"Point"}
}