{
  "type": "Feature",
  "properties": {
    "iso:country":"US",
    "sg:address":"214 W Main St",
    "sg:city":"Salem",
    "sg:classifiers":[
        {
            "category":"Food & Beverages",
            "subcategory":"Groceries & Convenience Stores",
            "type":"Retail Goods"
        }
    ],
    "sg:phone":"+1 304 782 3039",
    "sg:postcode":"26426",
    "sg:province":"WV",
    "wof:name":"Pantry Food Store",
    "wof:placetype":"venue"
},
  "geometry": {"coordinates":[-80.564493,39.28302],"type":"Point"}
}