{
  "type": "Feature",
  "properties": {
    "addr:full":"200 Fairmont Ave Fairmont WV 26554",
    "addr:housenumber":"200",
    "addr:postcode":"26554",
    "addr:street":"Fairmont Ave",
    "iso:country":"US",
    "sg:address":"200 Fairmont Ave",
    "sg:city":"Fairmont",
    "sg:classifiers":[
        {
            "category":"Education",
            "subcategory":"Special Training",
            "type":"Public Place"
        }
    ],
    "sg:phone":"+1 304 366 8764",
    "sg:postcode":"26554",
    "sg:province":"WV",
    "sg:tags":[
        "class",
        "provides",
        "ambulance"
    ],
    "wof:name":"West Virginia Ems Technical",
    "wof:placetype":"venue"
},
  "geometry": {"coordinates":[-80.14679599999999,39.481989],"type":"Point"}
}