{
  "type": "Feature",
  "properties": {
    "iso:country":"US",
    "sg:address":"225 Stone Church Rd",
    "sg:city":"Wheeling",
    "sg:classifiers":[
        {
            "category":"Building & Trades",
            "subcategory":"Equipment Rental",
            "type":"Services"
        }
    ],
    "sg:phone":"+1 304 242 6827",
    "sg:postcode":"26003",
    "sg:province":"WV",
    "wof:name":"Wallace Rentals LLC",
    "wof:placetype":"venue"
},
  "geometry": {"coordinates":[-80.65137300000001,40.040904],"type":"Point"}
}