{
  "type": "Feature",
  "properties": {
    "iso:country":"US",
    "sg:address":"421 N 20th St",
    "sg:city":"Weirton",
    "sg:classifiers":[
        {
            "category":"Building & Trades",
            "subcategory":"Construction",
            "type":"Services"
        }
    ],
    "sg:phone":"+1 304 723 1187",
    "sg:postcode":"26062",
    "sg:province":"WV",
    "sg:tags":[
        "house",
        "nonresidential"
    ],
    "wof:name":"Pryor Billy General Contg",
    "wof:placetype":"venue"
},
  "geometry": {"coordinates":[-80.56230499999999,40.432343],"type":"Point"}
}