{
  "type": "Feature",
  "properties": {
    "addr:full":"1226 Chapline St Wheeling WV 26003",
    "addr:housenumber":"1226",
    "addr:postcode":"26003",
    "addr:street":"Chapline St",
    "iso:country":"US",
    "sg:address":"1226 Chapline St",
    "sg:city":"Wheeling",
    "sg:classifiers":[
        {
            "category":"Professional",
            "subcategory":"Lawyer & Legal Services",
            "type":"Services"
        }
    ],
    "sg:phone":"+1 304 233 3511",
    "sg:postcode":"26003",
    "sg:province":"WV",
    "sg:tags":[
        "attorney"
    ],
    "sg:website":"www.hometownjustice.com",
    "wof:name":"Bachmann Hess Bachmann Garden",
    "wof:placetype":"venue"
},
  "geometry": {"coordinates":[-80.72102099999999,40.065943],"type":"Point"}
}