{
  "type": "Feature",
  "properties": {
    "iso:country":"US",
    "sg:address":"285 Middletown Rd",
    "sg:city":"Fairmont",
    "sg:classifiers":[
        {
            "category":"Wholesale",
            "subcategory":"Electrical",
            "type":"Manufacturing & Wholesale Goods"
        }
    ],
    "sg:phone":"+1 304 363 3600",
    "sg:postcode":"26554",
    "sg:province":"WV",
    "sg:tags":[
        "equipment"
    ],
    "wof:name":"Mosebach Electric",
    "wof:placetype":"venue"
},
  "geometry": {"coordinates":[-80.188952,39.428662],"type":"Point"}
}