{
  "type": "Feature",
  "properties": {
    "iso:country":"US",
    "sg:address":"5111 Ridgecross Dr",
    "sg:city":"Charleston",
    "sg:classifiers":[
        {
            "category":"Insurance",
            "subcategory":"Insurance Agent",
            "type":"Services"
        }
    ],
    "sg:phone":"+1 304 776 4973",
    "sg:postcode":"25313",
    "sg:province":"WV",
    "wof:name":"Thrivent Fincl For Lutherans",
    "wof:placetype":"venue"
},
  "geometry": {"coordinates":[-81.761122,38.428886],"type":"Point"}
}