{
  "type": "Feature",
  "properties": {
    "iso:country":"US",
    "sg:address":"3711 Pennsylvania Ave",
    "sg:city":"Weirton",
    "sg:classifiers":[
        {
            "category":"Restaurant",
            "type":"Food & Drink"
        }
    ],
    "sg:phone":"+1 304 723 7218",
    "sg:postcode":"26062",
    "sg:province":"WV",
    "wof:name":"Wes",
    "wof:placetype":"venue"
},
  "geometry": {"coordinates":[-80.522136,40.406714],"type":"Point"}
}