{
  "type": "Feature",
  "properties": {
    "addr:full":"664 Jefferson Ave Charles Town WV 25414",
    "addr:housenumber":"664",
    "addr:postcode":"25414",
    "addr:street":"Jefferson Ave",
    "iso:country":"US",
    "sg:address":"664 Jefferson Ave",
    "sg:city":"Charles Town",
    "sg:classifiers":[
        {
            "category":"Professional",
            "subcategory":"Management & Consulting",
            "type":"Services"
        }
    ],
    "sg:phone":"+1 304 725 1491",
    "sg:postcode":"25414",
    "sg:province":"WV",
    "sg:tags":[
        "real estate"
    ],
    "wof:name":"Cricky Inc",
    "wof:placetype":"venue"
},
  "geometry": {"coordinates":[-77.848772,39.285475],"type":"Point"}
}