{
  "type": "Feature",
  "properties": {
    "addr:full":"107 Stratton St Logan WV 25601",
    "addr:housenumber":"107",
    "addr:postcode":"25601",
    "addr:street":"Stratton St",
    "iso:country":"US",
    "sg:address":"107 Stratton St",
    "sg:city":"Logan",
    "sg:classifiers":[
        {
            "category":"Banks & Credit Unions",
            "subcategory":"Bank",
            "type":"Services"
        }
    ],
    "sg:phone":"+1 304 752 6390",
    "sg:postcode":"25601",
    "sg:province":"WV",
    "sg:tags":[
        "financing"
    ],
    "wof:name":"American General Finance Inc",
    "wof:placetype":"venue"
},
  "geometry": {"coordinates":[-81.993894,37.848053],"type":"Point"}
}