{
  "type": "Feature",
  "properties": {
    "iso:country":"US",
    "sg:address":"412 Sun Valley Dr",
    "sg:city":"St Albans",
    "sg:classifiers":[
        {
            "category":"Organizations",
            "subcategory":"Religious Organization",
            "type":"Services"
        }
    ],
    "sg:phone":"+1 304 722 5321",
    "sg:postcode":"25177",
    "sg:province":"WV",
    "sg:tags":[
        "clergy"
    ],
    "wof:name":"David R Bess",
    "wof:placetype":"venue"
},
  "geometry": {"coordinates":[-81.828909,38.366399],"type":"Point"}
}