{
  "type": "Feature",
  "properties": {
    "iso:country":"US",
    "sg:address":"150 E Reynolds Ave",
    "sg:city":"Princeton",
    "sg:classifiers":[
        {
            "category":"Arts & Performance",
            "subcategory":"Theater",
            "type":"Entertainment"
        }
    ],
    "sg:phone":"+1 304 425 6733",
    "sg:postcode":"24740",
    "sg:province":"WV",
    "sg:tags":[
        "live",
        "music"
    ],
    "wof:name":"Steve Gregory's Jukebox Prdctn",
    "wof:placetype":"venue"
},
  "geometry": {"coordinates":[-81.05530400000001,37.363971],"type":"Point"}
}