{
  "type": "Feature",
  "properties": {
    "addr:full":"50 Tram St Morgantown WV 26501",
    "addr:housenumber":"50",
    "addr:postcode":"26501",
    "addr:street":"Tram St",
    "iso:country":"US",
    "sg:address":"50 Tram St",
    "sg:city":"Morgantown",
    "sg:classifiers":[
        {
            "category":"Shopping",
            "subcategory":"Bicycles & Sporting Goods",
            "type":"Retail Goods"
        }
    ],
    "sg:phone":"+1 304 983 8575",
    "sg:postcode":"26501",
    "sg:province":"WV",
    "wof:name":"Conrads Sport Shop",
    "wof:placetype":"venue"
},
  "geometry": {"coordinates":[-80.011528,39.607218],"type":"Point"}
}