{
  "type": "Feature",
  "properties": {
    "addr:full":"301 Patteson Dr Morgantown WV 26505",
    "addr:housenumber":"301",
    "addr:postcode":"26505",
    "addr:street":"Patteson Dr",
    "iso:country":"US",
    "sg:address":"301 Patteson Dr",
    "sg:city":"Morgantown",
    "sg:classifiers":[
        {
            "category":"Autos & Motor Vehicles",
            "subcategory":"Fuel & Gas Station",
            "type":"Retail Goods"
        }
    ],
    "sg:phone":"+1 304 292 2620",
    "sg:postcode":"26505",
    "sg:province":"WV",
    "sg:tags":[
        "repair",
        "station",
        "gasoline",
        "general"
    ],
    "wof:name":"Exxon",
    "wof:placetype":"venue"
},
  "geometry": {"coordinates":[-79.97835000000001,39.6489],"type":"Point"}
}