{
  "type": "Feature",
  "properties": {
    "iso:country":"US",
    "sg:address":"106 Moreau Cir",
    "sg:city":"Oak Hill",
    "sg:classifiers":[
        {
            "category":"Wholesale",
            "subcategory":"Machinery & Supplies",
            "type":"Manufacturing & Wholesale Goods"
        }
    ],
    "sg:phone":"+1 304 252 3500",
    "sg:postcode":"25901",
    "sg:province":"WV",
    "sg:tags":[
        "supplier",
        "mining",
        "parts"
    ],
    "wof:name":"Jt Parts and Services LLC",
    "wof:placetype":"venue"
},
  "geometry": {"coordinates":[-81.134258,37.943581],"type":"Point"}
}