{
  "type": "Feature",
  "properties": {
    "iso:country":"US",
    "sg:address":"402 Penco Rd",
    "sg:city":"Weirton",
    "sg:classifiers":[
        {
            "category":"Shopping",
            "type":"Retail Goods"
        }
    ],
    "sg:phone":"+1 304 723 0542",
    "sg:postcode":"26062",
    "sg:province":"WV",
    "sg:tags":[
        "merchandise"
    ],
    "wof:name":"Celebration Art & Frame",
    "wof:placetype":"venue"
},
  "geometry": {"coordinates":[-80.54719900000001,40.408983],"type":"Point"}
}