{
  "type": "Feature",
  "properties": {
    "iso:country":"US",
    "sg:address":"110 S Mill Ave",
    "sg:city":"Mount Hope",
    "sg:classifiers":[
        {
            "category":"Shopping",
            "subcategory":"Department Store",
            "type":"Retail Goods"
        }
    ],
    "sg:phone":"+1 304 255 5600",
    "sg:postcode":"25880",
    "sg:province":"WV",
    "wof:name":"Belk",
    "wof:placetype":"venue"
},
  "geometry": {"coordinates":[-81.16836000000001,37.891218],"type":"Point"}
}