{
  "type": "Feature",
  "properties": {
    "iso:country":"US",
    "sg:address":"319 Main St",
    "sg:city":"Madison",
    "sg:classifiers":[
        {
            "category":"Health Services",
            "subcategory":"Doctor",
            "type":"Services"
        }
    ],
    "sg:phone":"+1 304 369 1117",
    "sg:postcode":"25130",
    "sg:province":"WV",
    "sg:tags":[
        "dentist"
    ],
    "wof:name":"Sean C Senator DDS",
    "wof:placetype":"venue"
},
  "geometry": {"coordinates":[-81.821539,38.064916],"type":"Point"}
}