{
  "type": "Feature",
  "properties": {
    "addr:full":"313 Chestnut St Morgantown WV 26505",
    "addr:housenumber":"313",
    "addr:postcode":"26505",
    "addr:street":"Chestnut St",
    "iso:country":"US",
    "sg:address":"313 Chestnut St",
    "sg:city":"Morgantown",
    "sg:classifiers":[
        {
            "category":"Shopping",
            "subcategory":"Gifts & Souvenirs",
            "type":"Retail Goods"
        }
    ],
    "sg:phone":"+1 304 296 7825",
    "sg:postcode":"26505",
    "sg:province":"WV",
    "sg:tags":[
        "shop"
    ],
    "wof:name":"Old Stone House",
    "wof:placetype":"venue"
},
  "geometry": {"coordinates":[-79.956649,39.630361],"type":"Point"}
}