{
  "type": "Feature",
  "properties": {
    "iso:country":"US",
    "sg:address":"133 Mool Ave",
    "sg:city":"Beckley",
    "sg:classifiers":[
        {
            "category":"Organizations",
            "subcategory":"Religious Organization",
            "type":"Services"
        }
    ],
    "sg:phone":"+1 304 252 8334",
    "sg:postcode":"25801",
    "sg:province":"WV",
    "sg:tags":[
        "clergy"
    ],
    "wof:name":"N B Staples",
    "wof:placetype":"venue"
},
  "geometry": {"coordinates":[-81.174527,37.764829],"type":"Point"}
}