{
  "type": "Feature",
  "properties": {
    "iso:country":"US",
    "sg:address":"2300 Maccorkle Ave SE",
    "sg:city":"Charleston",
    "sg:classifiers":[
        {
            "category":"Education",
            "subcategory":"Library",
            "type":"Public Place"
        }
    ],
    "sg:phone":"+1 304 357 4780",
    "sg:postcode":"25304",
    "sg:province":"WV",
    "wof:name":"Schoenbaum Library",
    "wof:placetype":"venue"
},
  "geometry": {"coordinates":[-81.618926,38.332543],"type":"Point"}
}