{
  "type": "Feature",
  "properties": {
    "iso:country":"US",
    "sg:address":"310 Hurricane Creek Rd",
    "sg:city":"Hurricane",
    "sg:classifiers":[
        {
            "category":"Restaurant",
            "type":"Food & Drink"
        }
    ],
    "sg:phone":"+1 304 562 2059",
    "sg:postcode":"25526",
    "sg:province":"WV",
    "wof:name":"Biscuit World",
    "wof:placetype":"venue"
},
  "geometry": {"coordinates":[-82.016817,38.436741],"type":"Point"}
}