{
  "type": "Feature",
  "properties": {
    "addr:full":"745 W Pike St Clarksburg WV 26301",
    "addr:housenumber":"745",
    "addr:postcode":"26301",
    "addr:street":"W Pike St",
    "iso:country":"US",
    "sg:address":"745 W Pike St",
    "sg:city":"Clarksburg",
    "sg:classifiers":[
        {
            "category":"Restaurant",
            "type":"Food & Drink"
        }
    ],
    "sg:menulink":"http://www.allmenus.com/wv/south-urban/206325-mcdonalds/menu/",
    "sg:postcode":"26301",
    "sg:province":"WV",
    "sg:tags":[
        "burger",
        "american"
    ],
    "wof:name":"McDonald's",
    "wof:placetype":"venue"
},
  "geometry": {"coordinates":[-80.34836199999999,39.282161],"type":"Point"}
}