{
  "type": "Feature",
  "properties": {
    "iso:country":"US",
    "sg:address":"105 Sandy Dr",
    "sg:city":"Bridgeport",
    "sg:classifiers":[
        {
            "category":"Government",
            "subcategory":"Office",
            "type":"Public Place"
        }
    ],
    "sg:phone":"+1 304 842 0610",
    "sg:postcode":"26330",
    "sg:province":"WV",
    "sg:tags":[
        "sector",
        "regulation",
        "commercial"
    ],
    "wof:name":"Bridgeport District 3",
    "wof:placetype":"venue"
},
  "geometry": {"coordinates":[-80.202941,39.305249],"type":"Point"}
}