{
  "type": "Feature",
  "properties": {
    "addr:full":"314 Twp Rd 275 Proctorville OH 45669",
    "addr:housenumber":"314",
    "addr:postcode":"45669",
    "addr:street":"Twp Rd 275",
    "iso:country":"US",
    "sg:address":"314 Twp Rd 275",
    "sg:city":"Proctorville",
    "sg:classifiers":[
        {
            "category":"Freight",
            "type":"Transportation"
        }
    ],
    "sg:phone":"+1 740 886 8249",
    "sg:postcode":"45669",
    "sg:province":"OH",
    "sg:tags":[
        "operator",
        "local",
        "trucking"
    ],
    "wof:name":"Buddy Moore Excavating",
    "wof:placetype":"venue"
},
  "geometry": {"coordinates":[-82.369485,38.463458],"type":"Point"}
}