{
  "type": "Feature",
  "properties": {
    "iso:country":"US",
    "sg:address":"108 Mellon St",
    "sg:city":"Beckley",
    "sg:classifiers":[
        {
            "category":"Wholesale",
            "subcategory":"Medical Equipment & Supplies",
            "type":"Manufacturing & Wholesale Goods"
        }
    ],
    "sg:phone":"+1 304 252 9600",
    "sg:postcode":"25801",
    "sg:province":"WV",
    "wof:name":"Pioneer Medical",
    "wof:placetype":"venue"
},
  "geometry": {"coordinates":[-81.17928000000001,37.796123],"type":"Point"}
}