{
  "type": "Feature",
  "properties": {
    "addr:full":"1800 Speedway St Fairmont WV 26554",
    "addr:housenumber":"1800",
    "addr:postcode":"26554",
    "addr:street":"Speedway St",
    "iso:country":"US",
    "sg:address":"1800 Speedway St",
    "sg:city":"Fairmont",
    "sg:classifiers":[
        {
            "category":"Manufacturing",
            "subcategory":"Metals",
            "type":"Manufacturing & Wholesale Goods"
        }
    ],
    "sg:phone":"+1 304 367 5000",
    "sg:postcode":"26554",
    "sg:province":"WV",
    "sg:tags":[
        "extruded",
        "product",
        "aluminum"
    ],
    "wof:name":"Alcan Aluminum Corp",
    "wof:placetype":"venue"
},
  "geometry": {"coordinates":[-80.106951,39.490393],"type":"Point"}
}