{
  "type": "Feature",
  "properties": {
    "iso:country":"US",
    "sg:address":"4420 Emerson Ave",
    "sg:city":"Parkersburg",
    "sg:classifiers":[
        {
            "category":"Manufacturing",
            "subcategory":"Wood Products",
            "type":"Manufacturing & Wholesale Goods"
        },
        {
            "category":"Building & Trades",
            "subcategory":"Construction",
            "type":"Services"
        }
    ],
    "sg:phone":"+1 304 485 4050",
    "sg:postcode":"26104",
    "sg:province":"WV",
    "sg:tags":[
        "woodworker",
        "repair",
        "industrial",
        "mfg"
    ],
    "sg:website":"www.woodcraft.com",
    "wof:name":"Woodworker's Club",
    "wof:placetype":"venue"
},
  "geometry": {"coordinates":[-81.52453,39.292774],"type":"Point"}
}