{
  "type": "Feature",
  "properties": {
    "iso:country":"US",
    "sg:address":"100 Capitol St",
    "sg:city":"Charleston",
    "sg:classifiers":[
        {
            "category":"Professional",
            "subcategory":"Lawyer & Legal Services",
            "type":"Services"
        }
    ],
    "sg:phone":"+1 304 346 1201",
    "sg:postcode":"25301",
    "sg:province":"WV",
    "wof:name":"Jacqueline A Hallinan Law Off",
    "wof:placetype":"venue"
},
  "geometry": {"coordinates":[-81.635485,38.349647],"type":"Point"}
}