{
  "type": "Feature",
  "properties": {
    "iso:country":"US",
    "sg:address":"2210 Fairview Ave",
    "sg:city":"Parkersburg",
    "sg:classifiers":[
        {
            "category":"Organizations",
            "subcategory":"Religious Organization",
            "type":"Services"
        }
    ],
    "sg:phone":"+1 304 485 6164",
    "sg:postcode":"26101",
    "sg:province":"WV",
    "sg:tags":[
        "church"
    ],
    "wof:name":"Parkview United Methodist Chr",
    "wof:placetype":"venue"
},
  "geometry": {"coordinates":[-81.521939,39.270769],"type":"Point"}
}