{
  "type": "Feature",
  "properties": {
    "addr:full":"3836 Franklin St Bellaire OH 43906",
    "addr:housenumber":"3836",
    "addr:postcode":"43906",
    "addr:street":"Franklin St",
    "iso:country":"US",
    "sg:address":"3836 Franklin St",
    "sg:city":"Bellaire",
    "sg:classifiers":[
        {
            "category":"Building & Trades",
            "subcategory":"Construction",
            "type":"Services"
        }
    ],
    "sg:phone":"+1 740 676 0726",
    "sg:postcode":"43906",
    "sg:province":"OH",
    "sg:tags":[
        "house"
    ],
    "wof:name":"Crozier Construction",
    "wof:placetype":"venue"
},
  "geometry": {"coordinates":[-80.744575,40.021348],"type":"Point"}
}