{
  "type": "Feature",
  "properties": {
    "iso:country":"US",
    "sg:address":"100 Main St",
    "sg:city":"West Alexander",
    "sg:classifiers":[
        {
            "category":"Government",
            "subcategory":"Fire Station",
            "type":"Public Place"
        }
    ],
    "sg:phone":"+1   ",
    "sg:postcode":"15376",
    "sg:province":"WV",
    "sg:tags":[
        "protection"
    ],
    "wof:name":"Alexander West Fire Co",
    "wof:placetype":"venue"
},
  "geometry": {"coordinates":[-80.51113100000001,40.104683],"type":"Point"}
}