{
  "type": "Feature",
  "properties": {
    "iso:country":"US",
    "sg:address":"146 Washington Run",
    "sg:city":"Ravenswood",
    "sg:classifiers":[
        {
            "category":"Farming",
            "subcategory":"Livestock Farm",
            "type":"Manufacturing & Wholesale Goods"
        }
    ],
    "sg:phone":"+1 304 273 8069",
    "sg:postcode":"26164",
    "sg:province":"WV",
    "sg:tags":[
        "beef",
        "feedlot",
        "tobacco",
        "cattle"
    ],
    "wof:name":"David Delong",
    "wof:placetype":"venue"
},
  "geometry": {"coordinates":[-81.77843300000001,39.048246],"type":"Point"}
}