{
  "type": "Feature",
  "properties": {
    "iso:country":"US",
    "sg:address":"1105 9th St",
    "sg:city":"Vienna",
    "sg:classifiers":[
        {
            "category":"Health Services",
            "subcategory":"Doctor",
            "type":"Services"
        }
    ],
    "sg:phone":"+1 304 295 4525",
    "sg:postcode":"26105",
    "sg:province":"WV",
    "sg:tags":[
        "medical"
    ],
    "wof:name":"Ernest E Miller",
    "wof:placetype":"venue"
},
  "geometry": {"coordinates":[-81.551104,39.307493],"type":"Point"}
}