{
  "type": "Feature",
  "properties": {
    "iso:country":"US",
    "sg:address":"204 Bond St",
    "sg:city":"Clarksburg",
    "sg:classifiers":[
        {
            "category":"Bars & Pubs",
            "type":"Food & Drink"
        }
    ],
    "sg:phone":"+1 304 622 8591",
    "sg:postcode":"26301",
    "sg:province":"WV",
    "sg:tags":[
        "drinking"
    ],
    "wof:name":"Wild Wild West Saloon Inc",
    "wof:placetype":"venue"
},
  "geometry": {"coordinates":[-80.359516,39.282857],"type":"Point"}
}