{
  "type": "Feature",
  "properties": {
    "iso:country":"US",
    "sg:address":"3128 Pennsylvania Ave",
    "sg:city":"Weirton",
    "sg:classifiers":[
        {
            "category":"Autos & Motor Vehicles",
            "subcategory":"Fuel & Gas Station",
            "type":"Retail Goods"
        }
    ],
    "sg:phone":"+1 304 723 0660",
    "sg:postcode":"26062",
    "sg:province":"WV",
    "sg:tags":[
        "station",
        "gasoline"
    ],
    "wof:name":"Old Oak Service",
    "wof:placetype":"venue"
},
  "geometry": {"coordinates":[-80.544144,40.410668],"type":"Point"}
}