{
  "type": "Feature",
  "properties": {
    "addr:full":"811 W Main St Harrisville WV 26362",
    "addr:housenumber":"811",
    "addr:postcode":"26362",
    "addr:street":"W Main St",
    "iso:country":"US",
    "sg:address":"811 W Main St",
    "sg:city":"Harrisville",
    "sg:classifiers":[
        {
            "category":"Building & Trades",
            "subcategory":"Landscaping Services",
            "type":"Services"
        }
    ],
    "sg:phone":"+1 304 643 4225",
    "sg:postcode":"26362",
    "sg:province":"WV",
    "sg:tags":[
        "landscape",
        "contractor"
    ],
    "wof:name":"Total Lawn Care",
    "wof:placetype":"venue"
},
  "geometry": {"coordinates":[-81.061735,39.210632],"type":"Point"}
}