{
  "type": "Feature",
  "properties": {
    "iso:country":"US",
    "sg:address":"3 Tygart Valley Mall",
    "sg:city":"Fairmont",
    "sg:classifiers":[
        {
            "category":"Health Services",
            "subcategory":"Health Practitioner",
            "type":"Services"
        }
    ],
    "sg:phone":"+1 304 363 3167",
    "sg:postcode":"26554",
    "sg:province":"WV",
    "wof:name":"Fairmont Rhblttion Ctr Otptent",
    "wof:placetype":"venue"
},
  "geometry": {"coordinates":[-80.19501099999999,39.425457],"type":"Point"}
}