{
  "type": "Feature",
  "properties": {
    "addr:full":"109 Commercial St New Martinsville WV 26155",
    "addr:housenumber":"109",
    "addr:postcode":"26155",
    "addr:street":"Commercial St",
    "iso:country":"US",
    "sg:address":"109 Commercial St",
    "sg:city":"New Martinsville",
    "sg:classifiers":[
        {
            "category":"Bars & Pubs",
            "type":"Food & Drink"
        }
    ],
    "sg:phone":"+1 304 455 1723",
    "sg:postcode":"26155",
    "sg:province":"WV",
    "sg:tags":[
        "drinking",
        "eating"
    ],
    "wof:name":"Pink Panther Club",
    "wof:placetype":"venue"
},
  "geometry": {"coordinates":[-80.86599699999999,39.636037],"type":"Point"}
}