{
  "type": "Feature",
  "properties": {
    "iso:country":"US",
    "sg:address":"51 16th St",
    "sg:city":"Wheeling",
    "sg:classifiers":[
        {
            "category":"Social Services",
            "subcategory":"Child Care",
            "type":"Services"
        }
    ],
    "sg:phone":"+1 304 233 3290",
    "sg:postcode":"26003",
    "sg:province":"WV",
    "sg:website":"www.npheadstart.org",
    "wof:name":"Northern Panhandle Head Start",
    "wof:placetype":"venue"
},
  "geometry": {"coordinates":[-80.720174,40.064175],"type":"Point"}
}