{
  "type": "Feature",
  "properties": {
    "addr:full":"1126 Hancock Dr Beckley WV 25801",
    "addr:housenumber":"1126",
    "addr:postcode":"25801",
    "addr:street":"Hancock Dr",
    "iso:country":"US",
    "sg:address":"1126 Hancock Dr",
    "sg:city":"Beckley",
    "sg:classifiers":[
        {
            "category":"Personal",
            "subcategory":"Beauty Salon",
            "type":"Services"
        }
    ],
    "sg:phone":"+1 304 250 0271",
    "sg:postcode":"25801",
    "sg:province":"WV",
    "sg:tags":[
        "shop"
    ],
    "wof:name":"Image Makers Salon",
    "wof:placetype":"venue"
},
  "geometry": {"coordinates":[-81.171665,37.791648],"type":"Point"}
}