{
  "type": "Feature",
  "properties": {
    "iso:country":"US",
    "sg:address":"909 4th St",
    "sg:city":"Weirton",
    "sg:classifiers":[
        {
            "category":"Wholesale",
            "subcategory":"Chemicals & Plastics",
            "type":"Manufacturing & Wholesale Goods"
        }
    ],
    "sg:phone":"+1 304 748 6501",
    "sg:postcode":"26062",
    "sg:province":"WV",
    "wof:name":"Boc Groupe",
    "wof:placetype":"venue"
},
  "geometry": {"coordinates":[-80.600413,40.426002],"type":"Point"}
}