{
  "type": "Feature",
  "properties": {
    "addr:full":"1600 S Jefferson Dr Huntington WV 25701",
    "addr:housenumber":"1600",
    "addr:postcode":"25701",
    "addr:street":"S Jefferson Dr",
    "iso:country":"US",
    "sg:address":"1600 S Jefferson Dr",
    "sg:city":"Huntington",
    "sg:classifiers":[
        {
            "category":"Travel",
            "subcategory":"Hotels & Motels",
            "type":"Entertainment"
        }
    ],
    "sg:phone":"+1 304 429 1872",
    "sg:postcode":"25701",
    "sg:province":"WV",
    "wof:name":"S I Beaver",
    "wof:placetype":"venue"
},
  "geometry": {"coordinates":[-82.51477800000001,38.392998],"type":"Point"}
}