{
  "type": "Feature",
  "properties": {
    "iso:country":"US",
    "sg:address":"605 Nicholas St",
    "sg:city":"Rupert",
    "sg:classifiers":[
        {
            "category":"Government",
            "subcategory":"Office",
            "type":"Public Place"
        }
    ],
    "sg:phone":"+1 304 392 5682",
    "sg:postcode":"25984",
    "sg:province":"WV",
    "sg:tags":[
        "city"
    ],
    "wof:name":"Rupert City Hall",
    "wof:placetype":"venue"
},
  "geometry": {"coordinates":[-80.690167,37.963229],"type":"Point"}
}