{
  "type": "Feature",
  "properties": {
    "addr:full":"368 Boyd Crawford Dr Cool Ridge WV 25825",
    "addr:housenumber":"368",
    "addr:postcode":"25825",
    "addr:street":"Boyd Crawford Dr Cool Ridge",
    "iso:country":"US",
    "sg:address":"368 Boyd Crawford Dr",
    "sg:city":"Cool Ridge",
    "sg:classifiers":[
        {
            "category":"Building & Trades",
            "subcategory":"Landscaping Services",
            "type":"Services"
        }
    ],
    "sg:phone":"+1 304 763 4006",
    "sg:postcode":"25825",
    "sg:province":"WV",
    "sg:tags":[
        "landscape"
    ],
    "wof:name":"Calliope James",
    "wof:placetype":"venue"
},
  "geometry": {"coordinates":[-81.12153499999999,37.672288],"type":"Point"}
}