{
  "type": "Feature",
  "properties": {
    "iso:country":"US",
    "sg:address":"212 S Main St",
    "sg:city":"Philippi",
    "sg:classifiers":[
        {
            "category":"Professional",
            "subcategory":"Accounting & Tax Preparation",
            "type":"Services"
        }
    ],
    "sg:phone":"+1 304 457 2286",
    "sg:postcode":"26416",
    "sg:province":"WV",
    "sg:tags":[
        "accountant"
    ],
    "wof:name":"Andrea Poling CPA",
    "wof:placetype":"venue"
},
  "geometry": {"coordinates":[-80.03608199999999,39.147797],"type":"Point"}
}