{
  "type": "Feature",
  "properties": {
    "addr:full":"800 5th Ave Huntington WV 25701",
    "addr:housenumber":"800",
    "addr:postcode":"25701",
    "addr:street":"5Th Ave",
    "iso:country":"US",
    "sg:address":"800 5th Ave",
    "sg:city":"Huntington",
    "sg:classifiers":[
        {
            "category":"Government",
            "subcategory":"Office",
            "type":"Public Place"
        }
    ],
    "sg:phone":"+1 304 696 4486",
    "sg:postcode":"25701",
    "sg:province":"WV",
    "sg:tags":[
        "village"
    ],
    "wof:name":"Development & Planning Dept",
    "wof:placetype":"venue"
},
  "geometry": {"coordinates":[-82.44352000000001,38.419378],"type":"Point"}
}