{
  "type": "Feature",
  "properties": {
    "iso:country":"US",
    "sg:address":"415 Potomac Ave",
    "sg:city":"Fairmont",
    "sg:classifiers":[
        {
            "category":"Organizations",
            "subcategory":"Religious Organization",
            "type":"Services"
        }
    ],
    "sg:phone":"+1 304 363 0169",
    "sg:postcode":"26554",
    "sg:province":"WV",
    "wof:name":"Apostolic Chrn Temple & Acad",
    "wof:placetype":"venue"
},
  "geometry": {"coordinates":[-80.130505,39.478405],"type":"Point"}
}