{
  "type": "Feature",
  "properties": {
    "iso:country":"US",
    "sg:address":"1201 Dunbar Ave",
    "sg:city":"Dunbar",
    "sg:classifiers":[
        {
            "category":"Social Services",
            "type":"Services"
        }
    ],
    "sg:phone":"+1 304 766 0015",
    "sg:postcode":"25064",
    "sg:province":"WV",
    "sg:tags":[
        "organization",
        "welfare"
    ],
    "wof:name":"Community Enrchment Opprtnties",
    "wof:placetype":"venue"
},
  "geometry": {"coordinates":[-81.73990499999999,38.36043],"type":"Point"}
}