{
  "type": "Feature",
  "properties": {
    "iso:country":"US",
    "sg:address":"12 N Kanawha St",
    "sg:city":"Buckhannon",
    "sg:classifiers":[
        {
            "category":"Professional",
            "subcategory":"Lawyer & Legal Services",
            "type":"Services"
        }
    ],
    "sg:phone":"+1 304 472 0988",
    "sg:postcode":"26201",
    "sg:province":"WV",
    "wof:name":"Hartman & Hartman Pllc Attnys",
    "wof:placetype":"venue"
},
  "geometry": {"coordinates":[-80.230683,38.994014],"type":"Point"}
}