{
  "type": "Feature",
  "properties": {
    "iso:country":"US",
    "sg:address":"53 14th St",
    "sg:city":"Wheeling",
    "sg:classifiers":[
        {
            "category":"Real Estate",
            "subcategory":"Real Estate Operator",
            "type":"Services"
        }
    ],
    "sg:phone":"+1 304 232 6690",
    "sg:postcode":"26003",
    "sg:province":"WV",
    "sg:tags":[
        "building",
        "parks"
    ],
    "wof:name":"Riley Building",
    "wof:placetype":"venue"
},
  "geometry": {"coordinates":[-80.722247,40.065608],"type":"Point"}
}