{
  "type": "Feature",
  "properties": {
    "iso:country":"US",
    "sg:address":"6012 Maccorkle Ave",
    "sg:city":"St Albans",
    "sg:classifiers":[
        {
            "category":"Arts & Performance",
            "subcategory":"Theater",
            "type":"Entertainment"
        }
    ],
    "sg:phone":"+1 304 766 0936",
    "sg:postcode":"25177",
    "sg:province":"WV",
    "sg:tags":[
        "entertainer"
    ],
    "wof:name":"J B Gentleman's Club",
    "wof:placetype":"venue"
},
  "geometry": {"coordinates":[-81.75361100000001,38.356924],"type":"Point"}
}