{
  "type": "Feature",
  "properties": {
    "addr:full":"150 Court St Charleston WV 25301",
    "addr:housenumber":"150",
    "addr:postcode":"25301",
    "addr:street":"Court St",
    "iso:country":"US",
    "sg:address":"150 Court St",
    "sg:city":"Charleston",
    "sg:classifiers":[
        {
            "category":"Restaurant",
            "type":"Food & Drink"
        }
    ],
    "sg:phone":"+1 304 344 0500",
    "sg:postcode":"25301",
    "sg:province":"WV",
    "wof:name":"Fujita Express",
    "wof:placetype":"venue"
},
  "geometry": {"coordinates":[-81.63708,38.35187],"type":"Point"}
}