{
  "type": "Feature",
  "properties": {
    "iso:country":"US",
    "sg:address":"123 Smith St",
    "sg:city":"Weirton",
    "sg:classifiers":[
        {
            "category":"Health Services",
            "subcategory":"Nursing And Care Facility",
            "type":"Services"
        }
    ],
    "sg:phone":"+1 304 723 4125",
    "sg:postcode":"26062",
    "sg:province":"WV",
    "sg:tags":[
        "skilled"
    ],
    "wof:name":"Hatchs Brbara Rsdntial Barding",
    "wof:placetype":"venue"
},
  "geometry": {"coordinates":[-80.529129,40.402599],"type":"Point"}
}