{
  "type": "Feature",
  "properties": {
    "iso:country":"US",
    "sg:address":"4537 Teays Valley Rd",
    "sg:city":"Scott Depot",
    "sg:classifiers":[
        {
            "category":"Retail",
            "subcategory":"Auto Repair",
            "type":"Services"
        }
    ],
    "sg:phone":"+1 304 757 8515",
    "sg:postcode":"25560",
    "sg:province":"WV",
    "sg:tags":[
        "repairing",
        "automobile"
    ],
    "wof:name":"Smitty's Auto Repair",
    "wof:placetype":"venue"
},
  "geometry": {"coordinates":[-81.891796,38.451663],"type":"Point"}
}