{
  "type": "Feature",
  "properties": {
    "iso:country":"US",
    "sg:address":"509 Washington St",
    "sg:city":"Ravenswood",
    "sg:classifiers":[
        {
            "category":"Restaurant",
            "type":"Food & Drink"
        }
    ],
    "sg:menulink":"http://www.allmenus.com/wv/northern/206266-mcdonalds/menu/",
    "sg:postcode":"26164",
    "sg:province":"WV",
    "sg:tags":[
        "burger",
        "american"
    ],
    "wof:name":"McDonald's",
    "wof:placetype":"venue"
},
  "geometry": {"coordinates":[-81.764019,38.952702],"type":"Point"}
}