{
  "type": "Feature",
  "properties": {
    "addr:full":"330 Merrymount Rd Wheeling WV 26003",
    "addr:housenumber":"330",
    "addr:postcode":"26003",
    "addr:street":"Merrymount Rd",
    "iso:country":"US",
    "sg:address":"330 Merrymount Rd",
    "sg:city":"Wheeling",
    "sg:classifiers":[
        {
            "category":"Professional",
            "subcategory":"Detective & Security Services",
            "type":"Services"
        }
    ],
    "sg:phone":"+1 304 233 3674",
    "sg:postcode":"26003",
    "sg:province":"WV",
    "sg:tags":[
        "investigator"
    ],
    "wof:name":"Hearne & Co",
    "wof:placetype":"venue"
},
  "geometry": {"coordinates":[-80.674582,40.112639],"type":"Point"}
}