{
  "type": "Feature",
  "properties": {
    "iso:country":"US",
    "sg:address":"535 Winchester Ave",
    "sg:city":"Martinsburg",
    "sg:classifiers":[
        {
            "category":"Restaurant",
            "type":"Food & Drink"
        }
    ],
    "sg:phone":"+1 304 267 0822",
    "sg:postcode":"25401",
    "sg:province":"WV",
    "sg:tags":[
        "eating"
    ],
    "sg:website":"http://www.empireofchina2.com",
    "wof:name":"Empire China Rest",
    "wof:placetype":"venue"
},
  "geometry": {"coordinates":[-77.97411,39.453771],"type":"Point"}
}