{
  "type": "Feature",
  "properties": {
    "iso:country":"US",
    "sg:address":"227 Main St",
    "sg:city":"Huntington",
    "sg:classifiers":[
        {
            "category":"Organizations",
            "subcategory":"Non-profit Organization",
            "type":"Services"
        }
    ],
    "sg:phone":"+1 304 523 9738",
    "sg:postcode":"25702",
    "sg:province":"WV",
    "wof:name":"Veterans Of Foreign Wars",
    "wof:placetype":"venue"
},
  "geometry": {"coordinates":[-82.388783,38.429624],"type":"Point"}
}