{
  "type": "Feature",
  "properties": {
    "iso:country":"US",
    "sg:address":"110 Baker St",
    "sg:city":"Webster Springs",
    "sg:classifiers":[
        {
            "category":"Health Services",
            "subcategory":"Hospital",
            "type":"Services"
        }
    ],
    "sg:phone":"+1 304 847 5059",
    "sg:postcode":"26288",
    "sg:province":"WV",
    "sg:tags":[
        "mental"
    ],
    "sg:website":"www.shsinc.org",
    "wof:name":"Seneca Health Svc Inc",
    "wof:placetype":"venue"
},
  "geometry": {"coordinates":[-80.413535,38.479424],"type":"Point"}
}