{
  "type": "Feature",
  "properties": {
    "iso:country":"US",
    "sg:address":"203 S Kanawha St",
    "sg:city":"Beckley",
    "sg:classifiers":[
        {
            "category":"Social Services",
            "subcategory":"Child Care",
            "type":"Services"
        }
    ],
    "sg:phone":"+1 304 255 1745",
    "sg:postcode":"25801",
    "sg:province":"WV",
    "sg:tags":[
        "day"
    ],
    "wof:name":"YMCA Happy Kids Preschool",
    "wof:placetype":"venue"
},
  "geometry": {"coordinates":[-81.187136,37.776824],"type":"Point"}
}