{
  "type": "Feature",
  "properties": {
    "addr:full":"635 W Main St Bridgeport WV 26330",
    "addr:housenumber":"635",
    "addr:postcode":"26330",
    "addr:street":"W Main St",
    "iso:country":"US",
    "sg:address":"635 W Main St",
    "sg:city":"Bridgeport",
    "sg:classifiers":[
        {
            "category":"Autos & Motor Vehicles",
            "subcategory":"Fuel & Gas Station",
            "type":"Retail Goods"
        }
    ],
    "sg:phone":"+1 304 842 4551",
    "sg:postcode":"26330",
    "sg:province":"WV",
    "sg:tags":[
        "oil"
    ],
    "wof:name":"Super America",
    "wof:placetype":"venue"
},
  "geometry": {"coordinates":[-80.262699,39.281326],"type":"Point"}
}