{
  "type": "Feature",
  "properties": {
    "iso:country":"US",
    "sg:address":"216 N Walnut St",
    "sg:city":"Philippi",
    "sg:classifiers":[
        {
            "category":"Retail",
            "subcategory":"Funeral Services",
            "type":"Services"
        }
    ],
    "sg:phone":"+1 304 457 2121",
    "sg:postcode":"26416",
    "sg:province":"WV",
    "sg:tags":[
        "director"
    ],
    "wof:name":"Wright Funeral Home",
    "wof:placetype":"venue"
},
  "geometry": {"coordinates":[-80.041315,39.154511],"type":"Point"}
}