{
  "type": "Feature",
  "properties": {
    "addr:full":"330 Washington St Ravenswood WV 26164",
    "addr:housenumber":"330",
    "addr:postcode":"26164",
    "addr:street":"Washington St",
    "iso:country":"US",
    "sg:address":"330 Washington St",
    "sg:city":"Ravenswood",
    "sg:classifiers":[
        {
            "category":"Autos & Motor Vehicles",
            "subcategory":"Auto Supplies",
            "type":"Retail Goods"
        }
    ],
    "sg:phone":"+1 304 273 0415",
    "sg:postcode":"26164",
    "sg:province":"WV",
    "wof:name":"Advance Auto Parts",
    "wof:placetype":"venue"
},
  "geometry": {"coordinates":[-81.762927,38.951025],"type":"Point"}
}