{
  "type": "Feature",
  "properties": {
    "addr:full":"301 N 2nd St Princeton WV 24740",
    "addr:housenumber":"301",
    "addr:postcode":"24740",
    "addr:street":"N 2Nd St",
    "iso:country":"US",
    "sg:address":"301 N 2nd St",
    "sg:city":"Princeton",
    "sg:classifiers":[
        {
            "category":"Wholesale",
            "subcategory":"Groceries",
            "type":"Manufacturing & Wholesale Goods"
        }
    ],
    "sg:phone":"+1 304 425 2679",
    "sg:postcode":"24740",
    "sg:province":"WV",
    "sg:tags":[
        "grocer"
    ],
    "wof:name":"Sterling Grocery Co",
    "wof:placetype":"venue"
},
  "geometry": {"coordinates":[-81.08699799999999,37.372645],"type":"Point"}
}