{
  "type": "Feature",
  "properties": {
    "iso:country":"US",
    "sg:address":"2911 7th Ave",
    "sg:city":"Charleston",
    "sg:classifiers":[
        {
            "category":"Restaurant",
            "type":"Food & Drink"
        }
    ],
    "sg:phone":"+1 304 744 0478",
    "sg:postcode":"25312",
    "sg:province":"WV",
    "sg:tags":[
        "eating"
    ],
    "wof:name":"Tuesday Management",
    "wof:placetype":"venue"
},
  "geometry": {"coordinates":[-81.682604,38.376998],"type":"Point"}
}