{
  "type": "Feature",
  "properties": {
    "addr:full":"211 N Court St Lewisburg WV 24901",
    "addr:housenumber":"211",
    "addr:postcode":"24901",
    "addr:street":"N Court St",
    "iso:country":"US",
    "sg:address":"211 N Court St",
    "sg:city":"Lewisburg",
    "sg:classifiers":[
        {
            "category":"Professional",
            "subcategory":"Lawyer & Legal Services",
            "type":"Services"
        }
    ],
    "sg:phone":"+1 304 645 5500",
    "sg:postcode":"24901",
    "sg:province":"WV",
    "sg:tags":[
        "attorney"
    ],
    "wof:name":"David M Moore",
    "wof:placetype":"venue"
},
  "geometry": {"coordinates":[-80.44462,37.804222],"type":"Point"}
}