{
  "type": "Feature",
  "properties": {
    "iso:country":"US",
    "sg:address":"578 Robert C Byrd Dr",
    "sg:city":"Sophia",
    "sg:classifiers":[
        {
            "category":"Manufacturing",
            "subcategory":"Tools & Machinery",
            "type":"Manufacturing & Wholesale Goods"
        }
    ],
    "sg:phone":"+1 304 683 4595",
    "sg:postcode":"25921",
    "sg:province":"WV",
    "sg:tags":[
        "compressor",
        "gas",
        "air"
    ],
    "sg:website":"www.threadsaver.com",
    "wof:name":"AMERICANAIRWORKS.COM",
    "wof:placetype":"venue"
},
  "geometry": {"coordinates":[-81.25165699999999,37.720101],"type":"Point"}
}