{
  "type": "Feature",
  "properties": {
    "iso:country":"US",
    "sg:address":"2208 Eoff St",
    "sg:city":"Wheeling",
    "sg:classifiers":[
        {
            "category":"Real Estate",
            "subcategory":"Real Estate Services",
            "type":"Services"
        }
    ],
    "sg:phone":"+1 304 233 4900",
    "sg:postcode":"26003",
    "sg:province":"WV",
    "sg:tags":[
        "company",
        "abstract",
        "title"
    ],
    "wof:name":"Experienced Title Inc",
    "wof:placetype":"venue"
},
  "geometry": {"coordinates":[-80.721943,40.058864],"type":"Point"}
}