{
  "type": "Feature",
  "properties": {
    "iso:country":"US",
    "sg:address":"4105 Staunton Ave SE",
    "sg:city":"Charleston",
    "sg:classifiers":[
        {
            "category":"Wholesale",
            "subcategory":"Farm Supplies",
            "type":"Manufacturing & Wholesale Goods"
        }
    ],
    "sg:phone":"+1 304 925 2499",
    "sg:postcode":"25304",
    "sg:province":"WV",
    "wof:name":"Turf Management Services Inc",
    "wof:placetype":"venue"
},
  "geometry": {"coordinates":[-81.586859,38.326672],"type":"Point"}
}