{
  "type": "Feature",
  "properties": {
    "addr:full":"3560 Us Route 60 E Barboursville WV 25504",
    "addr:housenumber":"3560",
    "addr:postcode":"25504",
    "addr:street":"Us Route 60 E",
    "iso:country":"US",
    "sg:address":"3560 Us Route 60 E",
    "sg:city":"Barboursville",
    "sg:classifiers":[
        {
            "category":"Restaurant",
            "type":"Food & Drink"
        }
    ],
    "sg:menulink":"http://www.allmenus.com/wv/barboursville/214052-taco-bell/menu/",
    "sg:phone":"+1 304 733 5657",
    "sg:postcode":"25504",
    "sg:province":"WV",
    "sg:tags":[
        "mexican"
    ],
    "wof:name":"Taco Bell",
    "wof:placetype":"venue"
},
  "geometry": {"coordinates":[-82.26196400000001,38.413321],"type":"Point"}
}