{
  "type": "Feature",
  "properties": {
    "iso:country":"US",
    "sg:address":"2619 Pennsylvania Ave",
    "sg:city":"Weirton",
    "sg:classifiers":[
        {
            "category":"Health Services",
            "subcategory":"Doctor",
            "type":"Services"
        }
    ],
    "sg:phone":"+1 304 797 7678",
    "sg:postcode":"26062",
    "sg:province":"WV",
    "sg:tags":[
        "physician",
        "surgeon"
    ],
    "wof:name":"Steel Valley Sports Medicine",
    "wof:placetype":"venue"
},
  "geometry": {"coordinates":[-80.556155,40.417683],"type":"Point"}
}