{
  "type": "Feature",
  "properties": {
    "iso:country":"US",
    "sg:address":"1809 Jefferson St",
    "sg:city":"Bluefield",
    "sg:classifiers":[
        {
            "category":"Social Services",
            "type":"Services"
        }
    ],
    "sg:phone":"+1 304 323 3388",
    "sg:postcode":"24701",
    "sg:province":"WV",
    "sg:tags":[
        "counseling"
    ],
    "wof:name":"Weisiger Counseling Services",
    "wof:placetype":"venue"
},
  "geometry": {"coordinates":[-81.22000800000001,37.256894],"type":"Point"}
}