{
  "type": "Feature",
  "properties": {
    "addr:full":"6121 Robert C Byrd Dr Bradley WV 25818",
    "addr:housenumber":"6121",
    "addr:postcode":"25818",
    "addr:street":"Robert C Byrd Dr",
    "iso:country":"US",
    "sg:address":"6121 Robert C Byrd Dr",
    "sg:city":"Bradley",
    "sg:classifiers":[
        {
            "category":"Building & Trades",
            "subcategory":"Construction",
            "type":"Services"
        }
    ],
    "sg:phone":"+1 304 877 6460",
    "sg:postcode":"25818",
    "sg:province":"WV",
    "sg:tags":[
        "general",
        "contractor"
    ],
    "wof:name":"Massie Reclamation Inc",
    "wof:placetype":"venue"
},
  "geometry": {"coordinates":[-81.193456,37.866762],"type":"Point"}
}