{
  "type": "Feature",
  "properties": {
    "addr:full":"208 E Main St Bridgeport WV 26330",
    "addr:housenumber":"208",
    "addr:postcode":"26330",
    "addr:street":"E Main St",
    "iso:country":"US",
    "sg:address":"208 E Main St",
    "sg:city":"Bridgeport",
    "sg:classifiers":[
        {
            "category":"Real Estate",
            "subcategory":"Real Estate Agent",
            "type":"Services"
        }
    ],
    "sg:phone":"+1 304 842 7112",
    "sg:postcode":"26330",
    "sg:province":"WV",
    "sg:tags":[
        "appraiser"
    ],
    "wof:name":"Fusco Real Estate Appraisal",
    "wof:placetype":"venue"
},
  "geometry": {"coordinates":[-80.248953,39.286021],"type":"Point"}
}