{
  "type": "Feature",
  "properties": {
    "iso:country":"US",
    "sg:address":"310 Main Ave",
    "sg:city":"Nitro",
    "sg:classifiers":[
        {
            "category":"Retail",
            "subcategory":"Auto Repair",
            "type":"Services"
        }
    ],
    "sg:phone":"+1 304 755 7158",
    "sg:postcode":"25143",
    "sg:province":"WV",
    "sg:tags":[
        "repairing",
        "automobile"
    ],
    "wof:name":"Stork's Body Shop",
    "wof:placetype":"venue"
},
  "geometry": {"coordinates":[-81.843694,38.407306],"type":"Point"}
}