{
  "type": "Feature",
  "properties": {
    "addr:full":"11 Meadow Dr Mineral Wells WV 26150",
    "addr:housenumber":"11",
    "addr:postcode":"26150",
    "addr:street":"Meadow Dr",
    "iso:country":"US",
    "sg:address":"11 Meadow Dr",
    "sg:city":"Mineral Wells",
    "sg:classifiers":[
        {
            "category":"Manufacturing",
            "subcategory":"Metals",
            "type":"Manufacturing & Wholesale Goods"
        }
    ],
    "sg:phone":"+1 304 489 2672",
    "sg:postcode":"26150",
    "sg:province":"WV",
    "sg:tags":[
        "steel"
    ],
    "wof:name":"Somerville Custom Fabricators",
    "wof:placetype":"venue"
},
  "geometry": {"coordinates":[-81.51691599999999,39.18102],"type":"Point"}
}