{
  "type": "Feature",
  "properties": {
    "addr:full":"633 Fayette St Oak Hill WV 25951",
    "addr:housenumber":"633",
    "addr:postcode":"25951",
    "addr:street":"Fayette St",
    "iso:country":"US",
    "sg:address":"633 Fayette St",
    "sg:city":"Oak Hill",
    "sg:classifiers":[
        {
            "category":"Autos & Motor Vehicles",
            "subcategory":"Auto Supplies",
            "type":"Retail Goods"
        }
    ],
    "sg:phone":"+1 304 469 4404",
    "sg:postcode":"25951",
    "sg:province":"WV",
    "sg:tags":[
        "automobile",
        "parts"
    ],
    "wof:name":"Autozone",
    "wof:placetype":"venue"
},
  "geometry": {"coordinates":[-80.878964,37.677203],"type":"Point"}
}