{
  "type": "Feature",
  "properties": {
    "addr:full":"1821 Speedway St Fairmont WV 26554",
    "addr:housenumber":"1821",
    "addr:postcode":"26554",
    "addr:street":"Speedway St",
    "iso:country":"US",
    "sg:address":"1821 Speedway St",
    "sg:city":"Fairmont",
    "sg:classifiers":[
        {
            "category":"Shopping",
            "subcategory":"Florist",
            "type":"Retail Goods"
        }
    ],
    "sg:phone":"+1 304 363 7264",
    "sg:postcode":"26554",
    "sg:province":"WV",
    "sg:tags":[
        "gourmet",
        "food",
        "gift"
    ],
    "wof:name":"World Of Plants & Flowers Inc",
    "wof:placetype":"venue"
},
  "geometry": {"coordinates":[-80.106842,39.489445],"type":"Point"}
}