{
  "type": "Feature",
  "properties": {
    "iso:country":"US",
    "sg:address":"600 Shrewsbury St",
    "sg:city":"Charleston",
    "sg:classifiers":[
        {
            "category":"Organizations",
            "subcategory":"Religious Organization",
            "type":"Services"
        }
    ],
    "sg:phone":"+1 304 343 3360",
    "sg:postcode":"25301",
    "sg:province":"WV",
    "sg:tags":[
        "church"
    ],
    "wof:name":"Justice & Life",
    "wof:placetype":"venue"
},
  "geometry": {"coordinates":[-81.628484,38.351483],"type":"Point"}
}