{
  "type": "Feature",
  "properties": {
    "addr:full":"203 Main St Mannington WV 26582",
    "addr:housenumber":"203",
    "addr:postcode":"26582",
    "addr:street":"Main St",
    "iso:country":"US",
    "sg:address":"203 Main St",
    "sg:city":"Mannington",
    "sg:classifiers":[
        {
            "category":"Shopping",
            "subcategory":"Tobacco",
            "type":"Retail Goods"
        }
    ],
    "sg:phone":"+1 304 986 1725",
    "sg:postcode":"26582",
    "sg:province":"WV",
    "sg:tags":[
        "cigarette",
        "cigar",
        "dealer"
    ],
    "wof:name":"Mannington Smokehouse Outlet",
    "wof:placetype":"venue"
},
  "geometry": {"coordinates":[-80.341835,39.531209],"type":"Point"}
}