{
  "type": "Feature",
  "properties": {
    "addr:full":"7 Craddock Way Poca WV 25159",
    "addr:housenumber":"7",
    "addr:postcode":"25159",
    "addr:street":"Craddock Way",
    "iso:country":"US",
    "sg:address":"7 Craddock Way",
    "sg:city":"Poca",
    "sg:classifiers":[
        {
            "category":"Retail",
            "subcategory":"Repair Shop",
            "type":"Services"
        }
    ],
    "sg:phone":"+1 304 755 3703",
    "sg:postcode":"25159",
    "sg:province":"WV",
    "sg:tags":[
        "refrigeration"
    ],
    "wof:name":"Nitro",
    "wof:placetype":"venue"
},
  "geometry": {"coordinates":[-81.820899,38.453889],"type":"Point"}
}