{
  "type": "Feature",
  "properties": {
    "addr:full":"1513 Richards Ave Clarksburg WV 26301",
    "addr:housenumber":"1513",
    "addr:postcode":"26301",
    "addr:street":"Richards Ave",
    "iso:country":"US",
    "sg:address":"1513 Richards Ave",
    "sg:city":"Clarksburg",
    "sg:classifiers":[
        {
            "category":"Personal",
            "subcategory":"Beauty Salon",
            "type":"Services"
        }
    ],
    "sg:phone":"+1 304 622 1603",
    "sg:postcode":"26301",
    "sg:province":"WV",
    "wof:name":"New Image",
    "wof:placetype":"venue"
},
  "geometry": {"coordinates":[-80.34308799999999,39.294402],"type":"Point"}
}