{
  "type": "Feature",
  "properties": {
    "iso:country":"US",
    "sg:address":"1233 University Ave",
    "sg:city":"Morgantown",
    "sg:classifiers":[
        {
            "category":"Shopping",
            "subcategory":"Hobbies, Toys, & Games",
            "type":"Retail Goods"
        }
    ],
    "sg:phone":"+1 304 296 6400",
    "sg:postcode":"26505",
    "sg:province":"WV",
    "wof:name":"Lane Merrywood",
    "wof:placetype":"venue"
},
  "geometry": {"coordinates":[-79.958399,39.629725],"type":"Point"}
}