{
  "type": "Feature",
  "properties": {
    "iso:country":"US",
    "sg:address":"5202 Cross Dr",
    "sg:city":"Cross Lanes",
    "sg:classifiers":[
        {
            "category":"Social Services",
            "subcategory":"Adult Care",
            "type":"Services"
        }
    ],
    "sg:phone":"+1 304 776 5010",
    "sg:postcode":"25313",
    "sg:province":"WV",
    "sg:tags":[
        "home",
        "group"
    ],
    "sg:website":"www.rescare.com",
    "wof:name":"Cross Lanes Group Home",
    "wof:placetype":"venue"
},
  "geometry": {"coordinates":[-81.761411,38.428777],"type":"Point"}
}