{
  "type": "Feature",
  "properties": {
    "iso:country":"US",
    "sg:address":"306 S Fairfax Blvd",
    "sg:city":"Ranson",
    "sg:classifiers":[
        {
            "category":"Shopping",
            "subcategory":"Used Merchandise",
            "type":"Retail Goods"
        }
    ],
    "sg:phone":"+1 304 724 6881",
    "sg:postcode":"25438",
    "sg:province":"WV",
    "sg:tags":[
        "appliance"
    ],
    "wof:name":"J R's Appliance",
    "wof:placetype":"venue"
},
  "geometry": {"coordinates":[-77.860663,39.295027],"type":"Point"}
}